Workbook

Sheet Performances by Week
E1: Status: | F1: Updated 9/29 | H1: Denotes Piazza | I1: Update all fields in Blue each week | J1: We expect 50% of Single Sales 1 Week Prior | K1: 85%+ occupancy | V1: 100%+ of Target
K2: 70-85% occupancy | V2: 90-99% of Target
G3: Week # | K3: <70% occupancy | V3: <90% of Target
D4: TICKET SALES REPORT as of 9/29/2025 | G4: 5 | I4: TOTAL SALES (Singles + Subs) | S4: Single Tickets | AB4: Subscription Tickets | AF4: Hall Data | AI4: Audience Data | AL4: Revenue last week | AM4: Increase over week
A5: Wk # | B5: # Weeks Until Perf | C5: Perf. Week (Mon) | D5: Performance | G5: Performance Date(s) | H5: Performance Type | I5: % OCC Target | J5: Actual OCC SOLD | K5: Actual Total Tickets Sold | L5: Total Actual Revenue | M5: TOTAL BUDGET | N5: Actual - Budget | O5: Projected Total OCC at Performance | P5: Projected Total Tickets Sold | Q5: Projected Total Revenue | R5: Projected- Budget | S5: Actual Single Tickets Sold | T5: Maximum Single Ticket Capacity | U5: Target Single Tickets for % OCC Target | V5: Projected Single Tickets | W5: Projected Single Tickets vs % OCC Target | X5: Actual Revenue | Y5: BUDGET | Z5: Actual/ Budget % | AA5: Projected/ Budget % | AB5: Actual Sub Tickets Sold | AC5: Actual Revenue | AD5: BUDGET | AE5: Actual vs Budget % | AF5: Max CAP | AG5: Single Ticket ATP | AH5: # New HH | AI5: # Ret HH | AJ5: # Total HH
A6: 1 | B6: =A6-$G$4 -> -4 | C6: 45901 | D6: 26 Morgan Freeman's Symphonic Blues | G6: 45902.833 | H6: Specials | I6: 0.85 | J6: =K6/AF6 -> 0.89093702 | K6: =S6+AB6 -> 1160 | L6: =X6+AC6 -> 137698 | M6: =Y6+AD6 -> 153473 | N6: =L6-M6 -> -15775 | O6: =IF(P6="Too early",P6,P6/AF6) -> #N/A | P6: =IF(V6="Too early",V6,V6+AB6) -> #N/A | Q6: =AC6+V6*AG6 -> #N/A | R6: =IF(V6="Too early",V6,Q6-M6) -> #N/A | S6: 1160 | T6: =AF6-AB6 -> 1302 | U6: =(AF6-AB6)*I6 -> 1106.7 | V6: =IF(B6<11,MIN((S6/VLOOKUP(B6,'Sales Pacing'!$A$23:$E$36,2)),T6),"Too early") -> #N/A | W6: =IF(V6="Too early","Too early",V6/U6) -> #N/A | X6: 137698 | Y6: 153473 | Z6: =IF(X6>0,X6/Y6,"") -> 0.89721319 | AA6: =IF($V6="Too early",V6,V6*AG6/Y6) -> #N/A | AD6: 0 | AE6: =IF(AC6>0,AC6/AD6,"") | AF6: 1302 | AG6: =X6/S6 -> 118.70517 | AH6: 228 | AI6: 295 | AJ6: 523 | AK6: 137698 | AL6: =L6-AK6 -> 0
A7: 1 | B7: =A7-$G$4 -> -4 | C7: 45901 | D7: 26 Morgan Freeman's Symphonic Blues | G7: 45903.833 | H7: Specials | I7: 0.85 | J7: =K7/AF7 -> 0.87480799 | K7: =S7+AB7 -> 1139 | L7: =X7+AC7 -> 134386 | M7: =Y7+AD7 -> 153473 | N7: =L7-M7 -> -19087 | O7: =IF(P7="Too early",P7,P7/AF7) -> #N/A | P7: =IF(V7="Too early",V7,V7+AB7) -> #N/A | Q7: =AC7+V7*AG7 -> #N/A | R7: =IF(V7="Too early",V7,Q7-M7) -> #N/A | S7: 1139 | T7: =AF7-AB7 -> 1302 | U7: =(AF7-AB7)*I7 -> 1106.7 | V7: =IF(B7<11,MIN((S7/VLOOKUP(B7,'Sales Pacing'!$A$23:$E$36,2)),T7),"Too early") -> #N/A | W7: =IF(V7="Too early","Too early",V7/U7) -> #N/A | X7: 134386 | Y7: 153473 | Z7: =IF(X7>0,X7/Y7,"") -> 0.87563285 | AA7: =IF($V7="Too early",V7,V7*AG7/Y7) -> #N/A | AD7: 0 | AE7: =IF(AC7>0,AC7/AD7,"") | AF7: 1302 | AG7: =X7/S7 -> 117.98595 | AH7: 227 | AI7: 289 | AJ7: 516 | AK7: 134386 | AL7: =L7-AK7 -> 0
A8: 1 | B8: =A8-$G$4 -> -4 | C8: 45901 | D8: 26 La nuit sombre | G8: 45905.833 | H8: Specials | I8: 0.85 | J8: =K8/AF8 -> 1.165 | K8: =S8+AB8 -> 699 | L8: =X8+AC8 -> 20005 | M8: =Y8+AD8 -> 15000 | N8: =L8-M8 -> 5005 | O8: =IF(P8="Too early",P8,P8/AF8) -> #N/A | P8: =IF(V8="Too early",V8,V8+AB8) -> #N/A | Q8: =AC8+V8*AG8 -> #N/A | R8: =IF(V8="Too early",V8,Q8-M8) -> #N/A | S8: 699 | T8: =AF8-AB8 -> 600 | U8: =(AF8-AB8)*I8 -> 510 | V8: =IF(B8<11,MIN((S8/VLOOKUP(B8,'Sales Pacing'!$A$23:$E$36,2)),T8),"Too early") -> #N/A | W8: =IF(V8="Too early","Too early",V8/U8) -> #N/A | X8: 20005 | Y8: 15000 | Z8: =IF(X8>0,X8/Y8,"") -> 1.3336667 | AA8: =IF($V8="Too early",V8,V8*AG8/Y8) -> #N/A | AD8: 0 | AE8: =IF(AC8>0,AC8/AD8,"") | AF8: 600 | AG8: =X8/S8 -> 28.619456 | AH8: 86 | AI8: 209 | AJ8: 295 | AK8: 20005 | AL8: =L8-AK8 -> 0
A9: 2 | B9: =A9-$G$4 -> -3 | C9: 45908 | D9: OPEN - Recording Week | J9: =K9/AF9 -> #DIV/0! | K9: =S9+AB9 -> 0 | P9: =IF(V9="Too early",V9,V9+AB9) -> #N/A | Q9: =AC9+V9*AG9 -> #N/A | R9: =IF(V9="Too early",V9,Q9-M9) -> #N/A | T9: =AF9-AB9 -> 0 | U9: =(AF9-AB9)*I9 -> 0 | V9: =IF(B9<11,MIN((S9/VLOOKUP(B9,'Sales Pacing'!$A$23:$E$36,2)),T9),"Too early") -> #N/A | Z9: =IF(X9>0,X9/Y9,"") | AE9: N/A
A10: 3 | B10: =A10-$G$4 -> -2 | C10: 45915 | D10: 26 PS1 Music of Journey | G10: 45919.833 | H10: Pops | I10: 0.85 | J10: =K10/AF10 -> 0.71069182 | K10: =S10+AB10 -> 1130 | L10: =X10+AC10 -> 75221.6 | M10: =Y10+AD10 -> 100666 | N10: =L10-M10 -> -25444.4 | O10: =IF(P10="Too early",P10,P10/AF10) -> #N/A | P10: =IF(V10="Too early",V10,V10+AB10) -> #N/A | Q10: =AC10+V10*AG10 -> #N/A | R10: =IF(V10="Too early",V10,Q10-M10) -> #N/A | S10: 515 | T10: =AF10-AB10 -> 975 | U10: =(AF10-AB10)*I10 -> 828.75 | V10: =IF(B10<11,MIN((S10/VLOOKUP(B10,'Sales Pacing'!$A$23:$E$36,2)),T10),"Too early") -> #N/A | W10: =IF(V10="Too early","Too early",V10/U10) -> #N/A | X10: 29853 | Y10: 59333 | Z10: =IF(X10>0,X10/Y10,"") -> 0.50314328 | AA10: =IF($V10="Too early",V10,V10*AG10/Y10) -> #N/A | AB10: 615 | AC10: 45368.6 | AD10: 41333 | AE10: =IF(AC10>0,AC10/AD10,"") -> 1.0976363 | AF10: 1590 | AG10: =X10/S10 -> 57.96699 | AH10: 67 | AI10: 416 | AJ10: 483 | AK10: 71854.6 | AL10: =L10-AK10 -> 3367
A11: 3 | B11: =A11-$G$4 -> -2 | C11: 45915 | D11: 26 PS1 Music of Journey | G11: 45920.833 | H11: Pops | I11: 0.85 | J11: =K11/AF11 -> 0.66918239 | K11: =S11+AB11 -> 1064 | L11: =X11+AC11 -> 73932.3 | M11: =Y11+AD11 -> 100667 | N11: =L11-M11 -> -26734.7 | O11: =IF(P11="Too early",P11,P11/AF11) -> #N/A | P11: =IF(V11="Too early",V11,V11+AB11) -> #N/A | Q11: =AC11+V11*AG11 -> #N/A | R11: =IF(V11="Too early",V11,Q11-M11) -> #N/A | S11: 550 | T11: =AF11-AB11 -> 1076 | U11: =(AF11-AB11)*I11 -> 914.6 | V11: =IF(B11<11,MIN((S11/VLOOKUP(B11,'Sales Pacing'!$A$23:$E$36,2)),T11),"Too early") -> #N/A | W11: =IF(V11="Too early","Too early",V11/U11) -> #N/A | X11: 35384 | Y11: 59333 | Z11: =IF(X11>0,X11/Y11,"") -> 0.5963629 | AA11: =IF($V11="Too early",V11,V11*AG11/Y11) -> #N/A | AB11: 514 | AC11: 38548.3 | AD11: 41334 | AE11: =IF(AC11>0,AC11/AD11,"") -> 0.93260512 | AF11: 1590 | AG11: =X11/S11 -> 64.334545 | AH11: 78 | AI11: 376 | AJ11: 454 | AK11: 70013.3 | AL11: =L11-AK11 -> 3919
A12: 3 | B12: =A12-$G$4 -> -2 | C12: 45915 | D12: 26 PS1 Music of Journey | G12: 45921.583 | H12: Pops | I12: 0.85 | J12: =K12/AF12 -> 0.6327044 | K12: =S12+AB12 -> 1006 | L12: =X12+AC12 -> 64333.8 | M12: =Y12+AD12 -> 100666 | N12: =L12-M12 -> -36332.2 | O12: =IF(P12="Too early",P12,P12/AF12) -> #N/A | P12: =IF(V12="Too early",V12,V12+AB12) -> #N/A | Q12: =AC12+V12*AG12 -> #N/A | R12: =IF(V12="Too early",V12,Q12-M12) -> #N/A | S12: 662 | T12: =AF12-AB12 -> 1246 | U12: =(AF12-AB12)*I12 -> 1059.1 | V12: =IF(B12<11,MIN((S12/VLOOKUP(B12,'Sales Pacing'!$A$23:$E$36,2)),T12),"Too early") -> #N/A | W12: =IF(V12="Too early","Too early",V12/U12) -> #N/A | X12: 40186 | Y12: 59333 | Z12: =IF(X12>0,X12/Y12,"") -> 0.67729594 | AA12: =IF($V12="Too early",V12,V12*AG12/Y12) -> #N/A | AB12: 344 | AC12: 24147.8 | AD12: 41333 | AE12: =IF(AC12>0,AC12/AD12,"") -> 0.58422568 | AF12: 1590 | AG12: =X12/S12 -> 60.703927 | AH12: 74 | AI12: 286 | AJ12: 360 | AK12: 56072.3 | AL12: =L12-AK12 -> 8261.5
A13: 4 | B13: =A13-$G$4 -> -1 | C13: 45922 | D13: 26 FS1 The Orchestra Games | G13: 45928.583 | H13: Family | I13: 0.5 | J13: =K13/AF13 -> 0.53993856 | K13: =S13+AB13 -> 703 | L13: =X13+AC13 -> 22183 | M13: =Y13+AD13 -> 19500 | N13: =L13-M13 -> 2683 | O13: =IF(P13="Too early",P13,P13/AF13) -> #N/A | P13: =IF(V13="Too early",V13,V13+AB13) -> #N/A | Q13: =IF(V13="Too early",V13,AC13+V13*AG13) -> #N/A | R13: =IF(V13="Too early",V13,Q13-M13) -> #N/A | S13: 507 | T13: =AF13-AB13 -> 1106 | U13: =(AF13-AB13)*I13 -> 553 | V13: =IF(B13<11,MIN((S13/VLOOKUP(B13,'Sales Pacing'!$A$23:$E$36,2)),T13),"Too early") -> #N/A | W13: =IF(V13="Too early","Too early",V13/U13) -> #N/A | X13: 16966 | Y13: 10000 | Z13: =IF(X13>0,X13/Y13,"") -> 1.6966 | AA13: =IF($V13="Too early",V13,V13*AG13/Y13) -> #N/A | AB13: 196 | AC13: 5217 | AD13: 9500 | AE13: =IF(AC13>0,AC13/AD13,"") -> 0.54915789 | AF13: 1302 | AG13: =X13/S13 -> 33.463511 | AH13: 21 | AI13: 104 | AJ13: 125 | AK13: 12684 | AL13: =L13-AK13 -> 9499
A14: 5 | B14: =A14-$G$4 -> 0 | C14: 45929 | D14: OPEN - was Chicken Fried | J14: =K14/AF14 -> #DIV/0! | Q14: =IF(V14="Too early",V14,AC14+V14*AG14) -> 0 | R14: =IF(V14="Too early",V14,Q14-M14) -> 0 | T14: =AF14-AB14 -> 0 | U14: =(AF14-AB14)*I14 -> 0 | V14: =IF(B14<11,MIN((S14/VLOOKUP(B14,'Sales Pacing'!$A$23:$E$36,2)),T14),"Too early") -> 0
A15: 6 | B15: =A15-$G$4 -> 1 | C15: 45936 | D15: 26 CS01 Appalachian Spring | G15: 45940.833 | H15: Classical | I15: 0.85 | J15: =K15/AF15 -> 0.58269365 | K15: =S15+AB15 -> 835 | L15: =X15+AC15 -> 50877 | M15: =Y15+AD15 -> 49999 | N15: =L15-M15 -> 878 | O15: =IF(P15="Too early",P15,P15/AF15) -> 0.74078323 | P15: =IF(V15="Too early",V15,V15+AB15) -> 1061.5424 | Q15: =IF(V15="Too early",V15,AC15+V15*AG15) -> 62630.797 | R15: =IF(V15="Too early",V15,Q15-M15) -> 12631.797 | S15: 326 | T15: =AF15-AB15 -> 924 | U15: =(AF15-AB15)*I15 -> 785.4 | V15: =IF(B15<11,MIN((S15/VLOOKUP(B15,'Sales Pacing'!$A$23:$E$36,2)),T15),"Too early") -> 552.54237 | W15: =IF(V15="Too early","Too early",V15/U15) -> 0.70351715 | X15: 16914 | Y15: 16666 | Z15: =IF(X15>0,X15/Y15,"") -> 1.0148806 | AA15: =IF($V15="Too early",V15,V15*AG15/Y15) -> 1.7201366 | AB15: 509 | AC15: 33963 | AD15: 33333 | AE15: =IF(AC15>0,AC15/AD15,"") -> 1.0189002 | AF15: 1433 | AG15: =X15/S15 -> 51.883436 | AH15: 13 | AI15: 370 | AJ15: 383 | AK15: 47640 | AL15: =L15-AK15 -> 3237
A16: 6 | B16: =A16-$G$4 -> 1 | C16: 45936 | D16: 26 CS01 Appalachian Spring | G16: 45941.833 | H16: Classical | I16: 0.85 | J16: =K16/AF16 -> 0.64549895 | K16: =S16+AB16 -> 925 | L16: =X16+AC16 -> 58900.1 | M16: =Y16+AD16 -> 49999 | N16: =L16-M16 -> 8901.1 | O16: =IF(P16="Too early",P16,P16/AF16) -> 0.81765172 | P16: =IF(V16="Too early",V16,V16+AB16) -> 1171.6949 | Q16: =IF(V16="Too early",V16,AC16+V16*AG16) -> 73004.1 | R16: =IF(V16="Too early",V16,Q16-M16) -> 23005.1 | S16: 355 | T16: =AF16-AB16 -> 863 | U16: =(AF16-AB16)*I16 -> 733.55 | V16: =IF(B16<11,MIN((S16/VLOOKUP(B16,'Sales Pacing'!$A$23:$E$36,2)),T16),"Too early") -> 601.69492 | W16: =IF(V16="Too early","Too early",V16/U16) -> 0.82025072 | X16: 20296 | Y16: 16666 | Z16: =IF(X16>0,X16/Y16,"") -> 1.2178087 | AA16: =IF($V16="Too early",V16,V16*AG16/Y16) -> 2.0640826 | AB16: 570 | AC16: 38604.1 | AD16: 33333 | AE16: =IF(AC16>0,AC16/AD16,"") -> 1.1581346 | AF16: 1433 | AG16: =X16/S16 -> 57.171831 | AH16: 21 | AI16: 386 | AJ16: 407 | AK16: 55614.1 | AL16: =L16-AK16 -> 3286
A17: 6 | B17: =A17-$G$4 -> 1 | C17: 45936 | D17: 26 CS01 Appalachian Spring | G17: 45942.583 | H17: Classical | I17: 0.85 | J17: =K17/AF17 -> 0.71807397 | K17: =S17+AB17 -> 1029 | L17: =X17+AC17 -> 63564.6 | M17: =Y17+AD17 -> 50000 | N17: =L17-M17 -> 13564.6 | O17: =IF(P17="Too early",P17,P17/AF17) -> 0.92659704 | P17: =IF(V17="Too early",V17,V17+AB17) -> 1327.8136 | Q17: =IF(V17="Too early",V17,AC17+V17*AG17) -> 80868.685 | R17: =IF(V17="Too early",V17,Q17-M17) -> 30868.685 | S17: 430 | T17: =AF17-AB17 -> 834 | U17: =(AF17-AB17)*I17 -> 708.9 | V17: =IF(B17<11,MIN((S17/VLOOKUP(B17,'Sales Pacing'!$A$23:$E$36,2)),T17),"Too early") -> 728.81356 | W17: =IF(V17="Too early","Too early",V17/U17) -> 1.0280908 | X17: 24901 | Y17: 16666 | Z17: =IF(X17>0,X17/Y17,"") -> 1.4941198 | AA17: =IF($V17="Too early",V17,V17*AG17/Y17) -> 2.5324064 | AB17: 599 | AC17: 38663.6 | AD17: 33334 | AE17: =IF(AC17>0,AC17/AD17,"") -> 1.1598848 | AF17: 1433 | AG17: =X17/S17 -> 57.909302 | AH17: 17 | AI17: 455 | AJ17: 472 | AK17: 57932.6 | AL17: =L17-AK17 -> 5632
A18: 7 | B18: =A18-$G$4 -> 2 | C18: 45943 | D18: 26 Top Gun: Maverick in Concert | G18: 45947.792 | H18: Specials/Film | I18: 0.85 | J18: =K18/AF18 -> 0.65284178 | K18: =S18+AB18 -> 850 | L18: =X18+AC18 -> 63699 | M18: =Y18+AD18 -> 103497 | N18: =L18-M18 -> -39798 | O18: =IF(P18="Too early",P18,P18/AF18) -> 1 | P18: =IF(V18="Too early",V18,V18+AB18) -> 1302 | Q18: =IF(V18="Too early",V18,AC18+V18*AG18) -> 97571.88 | R18: =IF(V18="Too early",V18,Q18-M18) -> -5925.12 | S18: 850 | T18: =AF18-AB18 -> 1302 | U18: =(AF18-AB18)*I18 -> 1106.7 | V18: =IF(B18<11,MIN((S18/VLOOKUP(B18,'Sales Pacing'!$A$23:$E$36,2)),T18),"Too early") -> 1302 | W18: =IF(V18="Too early","Too early",V18/U18) -> 1.1764706 | X18: 63699 | Y18: 103497 | Z18: =IF(X18>0,X18/Y18,"") -> 0.61546711 | AA18: =IF($V18="Too early",V18,V18*AG18/Y18) -> 0.9427508 | AE18: =IF(AC18>0,AC18/AD18,"") | AF18: 1302 | AG18: =X18/S18 -> 74.94 | AH18: 51 | AI18: 179 | AJ18: 230 | AK18: 48750 | AL18: =L18-AK18 -> 14949
A19: 7 | B19: =A19-$G$4 -> 2 | C19: 45943 | D19: 26 Top Gun: Maverick in Concert | G19: 45948.792 | H19: Specials/Film | I19: 0.85 | J19: =K19/AF19 -> 0.75729647 | K19: =S19+AB19 -> 986 | L19: =X19+AC19 -> 73005 | M19: =Y19+AD19 -> 103497 | N19: =L19-M19 -> -30492 | O19: =IF(P19="Too early",P19,P19/AF19) -> 1 | P19: =IF(V19="Too early",V19,V19+AB19) -> 1302 | Q19: =IF(V19="Too early",V19,AC19+V19*AG19) -> 96402.14 | R19: =IF(V19="Too early",V19,Q19-M19) -> -7094.86 | S19: 986 | T19: =AF19-AB19 -> 1302 | U19: =(AF19-AB19)*I19 -> 1106.7 | V19: =IF(B19<11,MIN((S19/VLOOKUP(B19,'Sales Pacing'!$A$23:$E$36,2)),T19),"Too early") -> 1302 | W19: =IF(V19="Too early","Too early",V19/U19) -> 1.1764706 | X19: 73005 | Y19: 103497 | Z19: =IF(X19>0,X19/Y19,"") -> 0.70538276 | AA19: =IF($V19="Too early",V19,V19*AG19/Y19) -> 0.93144864 | AE19: =IF(AC19>0,AC19/AD19,"") | AF19: 1302 | AG19: =X19/S19 -> 74.041582 | AH19: 74 | AI19: 184 | AJ19: 258 | AK19: 60628 | AL19: =L19-AK19 -> 12377
A20: 7 | B20: =A20-$G$4 -> 2 | C20: 45943 | D20: 26 Top Gun: Maverick in Concert | G20: 45949.583 | H20: Specials/Film | I20: 0.85 | J20: =K20/AF20 -> 0.55913978 | K20: =S20+AB20 -> 728 | L20: =X20+AC20 -> 55135 | M20: =Y20+AD20 -> 103496 | N20: =L20-M20 -> -48361 | O20: =IF(P20="Too early",P20,P20/AF20) -> 1 | P20: =IF(V20="Too early",V20,V20+AB20) -> 1302 | Q20: =IF(V20="Too early",V20,AC20+V20*AG20) -> 98606.827 | R20: =IF(V20="Too early",V20,Q20-M20) -> -4889.1731 | S20: 728 | T20: =AF20-AB20 -> 1302 | U20: =(AF20-AB20)*I20 -> 1106.7 | V20: =IF(B20<11,MIN((S20/VLOOKUP(B20,'Sales Pacing'!$A$23:$E$36,2)),T20),"Too early") -> 1302 | W20: =IF(V20="Too early","Too early",V20/U20) -> 1.1764706 | X20: 55135 | Y20: 103496 | Z20: =IF(X20>0,X20/Y20,"") -> 0.5327259 | AA20: =IF($V20="Too early",V20,V20*AG20/Y20) -> 0.95275979 | AE20: =IF(AC20>0,AC20/AD20,"") | AF20: 1302 | AG20: =X20/S20 -> 75.73489 | AH20: 38 | AI20: 149 | AJ20: 187 | AK20: 44494 | AL20: =L20-AK20 -> 10641
A21: 8 | B21: =A21-$G$4 -> 3 | C21: 45950 | D21: 26 The Lodger | G21: 45952.792 | H21: Specials/Film | I21: 0.5 | J21: =K21/AF21 -> 0.19662058 | K21: =S21+AB21 -> 256 | L21: =X21+AC21 -> 13747 | M21: =Y21+AD21 -> 50000 | N21: =L21-M21 -> -36253 | O21: =IF(P21="Too early",P21,P21/AF21) -> 0.50415534 | P21: =IF(V21="Too early",V21,V21+AB21) -> 656.41026 | Q21: =IF(V21="Too early",V21,AC21+V21*AG21) -> 35248.718 | R21: =IF(V21="Too early",V21,Q21-M21) -> -14751.282 | S21: 256 | T21: =AF21-AB21 -> 1302 | U21: =(AF21-AB21)*I21 -> 651 | V21: =IF(B21<11,MIN((S21/VLOOKUP(B21,'Sales Pacing'!$A$23:$E$36,2)),T21),"Too early") -> 656.41026 | W21: =IF(V21="Too early","Too early",V21/U21) -> 1.0083107 | X21: 13747 | Y21: 50000 | Z21: =IF(X21>0,X21/Y21,"") -> 0.27494 | AA21: =IF($V21="Too early",V21,V21*AG21/Y21) -> 0.70497436 | AE21: =IF(AC21>0,AC21/AD21,"") | AF21: 1302 | AG21: =X21/S21 -> 53.699219 | AH21: 5 | AI21: 78 | AJ21: 83 | AK21: 10588 | AL21: =L21-AK21 -> 3159
A22: 8 | B22: =A22-$G$4 -> 3 | C22: 45950 | D22: 26 PS2 90s Mixtape | G22: 45954.833 | H22: Pops | I22: 0.85 | J22: =K22/AF22 -> 0.53647799 | K22: =S22+AB22 -> 853 | L22: =X22+AC22 -> 60234.9 | M22: =Y22+AD22 -> 92333 | N22: =L22-M22 -> -32098.1 | O22: =IF(P22="Too early",P22,P22/AF22) -> 0.67911627 | P22: =IF(V22="Too early",V22,V22+AB22) -> 1079.7949 | Q22: =IF(V22="Too early",V22,AC22+V22*AG22) -> 74241.438 | R22: =IF(V22="Too early",V22,Q22-M22) -> -18091.562 | S22: 145 | T22: =AF22-AB22 -> 882 | U22: =(AF22-AB22)*I22 -> 749.7 | V22: =IF(B22<11,MIN((S22/VLOOKUP(B22,'Sales Pacing'!$A$23:$E$36,2)),T22),"Too early") -> 371.79487 | W22: =IF(V22="Too early","Too early",V22/U22) -> 0.49592487 | X22: 8955 | Y22: 53333 | Z22: =IF(X22>0,X22/Y22,"") -> 0.1679073 | AA22: =IF($V22="Too early",V22,V22*AG22/Y22) -> 0.43053154 | AB22: 708 | AC22: 51279.9 | AD22: 39000 | AE22: =IF(AC22>0,AC22/AD22,"") -> 1.3148692 | AF22: 1590 | AG22: =X22/S22 -> 61.758621 | AH22: 7 | AI22: 350 | AJ22: 357 | AK22: 57609.1 | AL22: =L22-AK22 -> 2625.8
A23: 8 | B23: =A23-$G$4 -> 3 | C23: 45950 | D23: 26 PS2 90s Mixtape | G23: 45955.833 | H23: Pops | I23: 0.85 | J23: =K23/AF23 -> 0.51509434 | K23: =S23+AB23 -> 819 | L23: =X23+AC23 -> 56647.8 | M23: =Y23+AD23 -> 92333 | N23: =L23-M23 -> -35685.2 | O23: =IF(P23="Too early",P23,P23/AF23) -> 0.70199968 | P23: =IF(V23="Too early",V23,V23+AB23) -> 1116.1795 | Q23: =IF(V23="Too early",V23,AC23+V23*AG23) -> 74614.646 | R23: =IF(V23="Too early",V23,Q23-M23) -> -17718.354 | S23: 190 | T23: =AF23-AB23 -> 961 | U23: =(AF23-AB23)*I23 -> 816.85 | V23: =IF(B23<11,MIN((S23/VLOOKUP(B23,'Sales Pacing'!$A$23:$E$36,2)),T23),"Too early") -> 487.17949 | W23: =IF(V23="Too early","Too early",V23/U23) -> 0.59641242 | X23: 11487 | Y23: 53333 | Z23: =IF(X23>0,X23/Y23,"") -> 0.2153826 | AA23: =IF($V23="Too early",V23,V23*AG23/Y23) -> 0.55226307 | AB23: 629 | AC23: 45160.8 | AD23: 39000 | AE23: =IF(AC23>0,AC23/AD23,"") -> 1.1579692 | AF23: 1590 | AG23: =X23/S23 -> 60.457895 | AH23: 11 | AI23: 320 | AJ23: 311 | AK23: 52382.8 | AL23: =L23-AK23 -> 4265
A24: 8 | B24: =A24-$G$4 -> 3 | C24: 45950 | D24: 26 PS2 90s Mixtape | G24: 45956.583 | H24: Pops | I24: 0.85 | J24: =K24/AF24 -> 0.3427673 | K24: =S24+AB24 -> 545 | L24: =X24+AC24 -> 36579.5 | M24: =Y24+AD24 -> 92333 | N24: =L24-M24 -> -55753.5 | O24: =IF(P24="Too early",P24,P24/AF24) -> 0.5031124 | P24: =IF(V24="Too early",V24,V24+AB24) -> 799.94872 | Q24: =IF(V24="Too early",V24,AC24+V24*AG24) -> 53285.679 | R24: =IF(V24="Too early",V24,Q24-M24) -> -39047.321 | S24: 163 | T24: =AF24-AB24 -> 1208 | U24: =(AF24-AB24)*I24 -> 1026.8 | V24: =IF(B24<11,MIN((S24/VLOOKUP(B24,'Sales Pacing'!$A$23:$E$36,2)),T24),"Too early") -> 417.94872 | W24: =IF(V24="Too early","Too early",V24/U24) -> 0.40704004 | X24: 10681 | Y24: 53333 | Z24: =IF(X24>0,X24/Y24,"") -> 0.20027 | AA24: =IF($V24="Too early",V24,V24*AG24/Y24) -> 0.51351282 | AB24: 382 | AC24: 25898.5 | AD24: 39000 | AE24: =IF(AC24>0,AC24/AD24,"") -> 0.6640641 | AF24: 1590 | AG24: =X24/S24 -> 65.527607 | AH24: 6 | AI24: 209 | AJ24: 203 | AK24: 31818.5 | AL24: =L24-AK24 -> 4761
A25: 9 | B25: =A25-$G$4 -> 4 | C25: 45957 | D25: 26 On-Stage 1 George Li | G25: 45959.833 | H25: On Stage | I25: 0.85 | J25: =K25/AF25 -> 0.29 | K25: =S25+AB25 -> 29 | L25: =X25+AC25 -> 3360 | M25: 11200 | N25: =L25-M25 -> -7840 | O25: =IF(P25="Too early",P25,P25/AF25) -> 0.87878788 | P25: =IF(V25="Too early",V25,V25+AB25) -> 87.878788 | Q25: =IF(V25="Too early",V25,AC25+V25*AG25) -> 10181.818 | R25: =IF(V25="Too early",V25,Q25-M25) -> -1018.1818 | S25: 29 | T25: =AF25-AB25 -> 100 | U25: =(AF25-AB25)*I25 -> 85 | V25: =IF(B25<11,MIN((S25/VLOOKUP(B25,'Sales Pacing'!$A$23:$E$36,2)),T25),"Too early") -> 87.878788 | W25: =IF(V25="Too early","Too early",V25/U25) -> 1.0338681 | X25: 3360 | Y25: 11200 | Z25: =IF(X25>0,X25/Y25,"") -> 0.3 | AA25: =IF($V25="Too early",V25,V25*AG25/Y25) -> 0.90909091 | AE25: =IF(AC25>0,AC25/AD25,"") | AF25: 100 | AG25: =X25/S25 -> 115.86207 | AH25: 0 | AI25: 11 | AJ25: 11 | AK25: 2800 | AL25: =L25-AK25 -> 560
A26: 9 | B26: =A26-$G$4 -> 4 | C26: 45957 | D26: 26 CS02 Rachmaninoff Cele Pt 1 | G26: 45961.833 | H26: Classical | I26: 0.5 | J26: =K26/AF26 -> 0.33914864 | K26: =S26+AB26 -> 486 | L26: =X26+AC26 -> 31409 | M26: =Y26+AD26 -> 52000 | N26: =L26-M26 -> -20591 | O26: =IF(P26="Too early",P26,P26/AF26) -> 0.54317072 | P26: =IF(V26="Too early",V26,V26+AB26) -> 778.36364 | Q26: =IF(V26="Too early",V26,AC26+V26*AG26) -> 46855.545 | R26: =IF(V26="Too early",V26,Q26-M26) -> -5144.4545 | S26: 144 | T26: =AF26-AB26 -> 1091 | U26: =(AF26-AB26)*I26 -> 545.5 | V26: =IF(B26<11,MIN((S26/VLOOKUP(B26,'Sales Pacing'!$A$23:$E$36,2)),T26),"Too early") -> 436.36364 | W26: =IF(V26="Too early","Too early",V26/U26) -> 0.79993334 | X26: 7608 | Y26: 22000 | Z26: =IF(X26>0,X26/Y26,"") -> 0.34581818 | AA26: =IF($V26="Too early",V26,V26*AG26/Y26) -> 1.0479339 | AB26: 342 | AC26: 23801 | AD26: 30000 | AE26: =IF(AC26>0,AC26/AD26,"") -> 0.79336667 | AF26: 1433 | AG26: =X26/S26 -> 52.833333 | AH26: 10 | AI26: 222 | AJ26: 232 | AK26: 30757 | AL26: =L26-AK26 -> 652
A27: 9 | B27: =A27-$G$4 -> 4 | C27: 45957 | D27: 26 CS02 Rachmaninoff Cele Pt 1 | G27: 45962.833 | H27: Classical | I27: 0.85 | J27: =K27/AF27 -> 0.70062805 | K27: =S27+AB27 -> 1004 | L27: =X27+AC27 -> 61737 | M27: =Y27+AD27 -> 86500 | N27: =L27-M27 -> -24763 | O27: =IF(P27="Too early",P27,P27/AF27) -> 1 | P27: =IF(V27="Too early",V27,V27+AB27) -> 1433 | Q27: =IF(V27="Too early",V27,AC27+V27*AG27) -> 86030.327 | R27: =IF(V27="Too early",V27,Q27-M27) -> -469.67265 | S27: 446 | T27: =AF27-AB27 -> 875 | U27: =(AF27-AB27)*I27 -> 743.75 | V27: =IF(B27<11,MIN((S27/VLOOKUP(B27,'Sales Pacing'!$A$23:$E$36,2)),T27),"Too early") -> 875 | W27: =IF(V27="Too early","Too early",V27/U27) -> 1.1764706 | X27: 25256 | Y27: 31500 | Z27: =IF(X27>0,X27/Y27,"") -> 0.80177778 | AA27: =IF($V27="Too early",V27,V27*AG27/Y27) -> 1.5729945 | AB27: 558 | AC27: 36481 | AD27: 55000 | AE27: =IF(AC27>0,AC27/AD27,"") -> 0.66329091 | AF27: 1433 | AG27: =X27/S27 -> 56.627803 | AH27: 26 | AI27: 397 | AJ27: 423 | AK27: 57693 | AL27: =L27-AK27 -> 4044
A28: 9 | B28: =A28-$G$4 -> 4 | C28: 45957 | D28: 26 CS02 Rachmaninoff Cele Pt 1 | G28: 45963.583 | H28: Classical | I28: 0.85 | J28: =K28/AF28 -> 0.60711793 | K28: =S28+AB28 -> 870 | L28: =X28+AC28 -> 54318.1 | M28: =Y28+AD28 -> 86500 | N28: =L28-M28 -> -32181.9 | O28: =IF(P28="Too early",P28,P28/AF28) -> 1 | P28: =IF(V28="Too early",V28,V28+AB28) -> 1433 | Q28: =IF(V28="Too early",V28,AC28+V28*AG28) -> 87343.789 | R28: =IF(V28="Too early",V28,Q28-M28) -> 843.78932 | S28: 309 | T28: =AF28-AB28 -> 872 | U28: =(AF28-AB28)*I28 -> 741.2 | V28: =IF(B28<11,MIN((S28/VLOOKUP(B28,'Sales Pacing'!$A$23:$E$36,2)),T28),"Too early") -> 872 | W28: =IF(V28="Too early","Too early",V28/U28) -> 1.1764706 | X28: 18126 | Y28: 31500 | Z28: =IF(X28>0,X28/Y28,"") -> 0.57542857 | AA28: =IF($V28="Too early",V28,V28*AG28/Y28) -> 1.6238632 | AB28: 561 | AC28: 36192.1 | AD28: 55000 | AE28: =IF(AC28>0,AC28/AD28,"") -> 0.65803818 | AF28: 1433 | AG28: =X28/S28 -> 58.660194 | AH28: 17 | AI28: 407 | AJ28: 424 | AK28: 51432.1 | AL28: =L28-AK28 -> 2886
A29: 10 | B29: =A29-$G$4 -> 5 | C29: 45964 | D29: 26 FS2 Carnival of the Animals | G29: 45970.583 | H29: Family | I29: 0.5 | J29: =K29/AF29 -> 0.36615385 | K29: =S29+AB29 -> 476 | L29: =X29+AC29 -> 11664 | M29: =Y29+AD29 -> 19500 | N29: =L29-M29 -> -7836 | O29: =IF(P29="Too early",P29,P29/AF29) -> 0.66948718 | P29: =IF(V29="Too early",V29,V29+AB29) -> 870.33333 | Q29: =IF(V29="Too early",V29,AC29+V29*AG29) -> 22929.333 | R29: =IF(V29="Too early",V29,Q29-M29) -> 3429.3333 | S29: 169 | T29: =AF29-AB29 -> 993 | U29: =(AF29-AB29)*I29 -> 496.5 | V29: =IF(B29<11,MIN((S29/VLOOKUP(B29,'Sales Pacing'!$A$23:$E$36,2)),T29),"Too early") -> 563.33333 | W29: =IF(V29="Too early","Too early",V29/U29) -> 1.1346089 | X29: 4828 | Y29: 10000 | Z29: =IF(X29>0,X29/Y29,"") -> 0.4828 | AA29: =IF($V29="Too early",V29,V29*AG29/Y29) -> 1.6093333 | AB29: 307 | AC29: 6836 | AD29: 9500 | AE29: =IF(AC29>0,AC29/AD29,"") -> 0.71957895 | AF29: 1300 | AG29: =X29/S29 -> 28.568047 | AH29: 9 | AI29: 103 | AJ29: 112 | AK29: 10703 | AL29: =L29-AK29 -> 961
A30: 11 | B30: =A30-$G$4 -> 6 | C30: 45971 | D30: OPEN | J30: =K30/AF30 -> #DIV/0! | K30: =S30+AB30 -> 0 | L30: =X30+AC30 -> 0 | M30: =Y30+AD30 -> 0 | P30: =IF(V30="Too early",V30,V30+AB30) -> 0 | Q30: =IF(V30="Too early",V30,AC30+V30*AG30) -> #DIV/0! | R30: =IF(V30="Too early",V30,Q30-M30) -> #DIV/0! | T30: =AF30-AB30 -> 0 | U30: =(AF30-AB30)*I30 -> 0 | V30: =IF(B30<7,(S30/VLOOKUP(B30,'Sales Pacing'!$A$23:$E$36,2)),"Too early") -> 0 | Z30: =IF(X30>0,X30/Y30,"") | AE30: N/A | AG30: =X30/S30 -> #DIV/0! | AK30: 0
A31: 12 | B31: =A31-$G$4 -> 7 | C31: 45978 | D31: 26 CS03 Matthias and Mahler 7 | G31: 45982.833 | H31: Classical | I31: 0.5 | J31: =K31/AF31 -> 0.27798742 | K31: =S31+AB31 -> 442 | L31: =X31+AC31 -> 29152 | M31: =Y31+AD31 -> 40000 | N31: =L31-M31 -> -10848 | O31: =IF(P31="Too early",P31,P31/AF31) -> 0.42735849 | P31: =IF(V31="Too early",V31,V31+AB31) -> 679.5 | Q31: =IF(V31="Too early",V31,AC31+V31*AG31) -> 41198 | R31: =IF(V31="Too early",V31,Q31-M31) -> 1198 | S31: 75 | T31: =AF31-AB31 -> 1223 | U31: =(AF31-AB31)*I31 -> 611.5 | V31: =IF(B31<11,MIN((S31/VLOOKUP(B31,'Sales Pacing'!$A$23:$E$36,2)),T31),"Too early") -> 312.5 | W31: =IF(V31="Too early","Too early",V31/U31) -> 0.51103843 | X31: 3804 | Y31: 15000 | Z31: =IF(X31>0,X31/Y31,"") -> 0.2536 | AA31: =IF($V31="Too early",V31,V31*AG31/Y31) -> 1.0566667 | AB31: 367 | AC31: 25348 | AD31: 25000 | AE31: =IF(AC31>0,AC31/AD31,"") -> 1.01392 | AF31: 1590 | AG31: =X31/S31 -> 50.72 | AH31: 1 | AI31: 221 | AJ31: 222 | AK31: 29114 | AL31: =L31-AK31 -> 38
A32: 12 | B32: =A32-$G$4 -> 7 | C32: 45978 | D32: 26 CS03 Matthias and Mahler 7 | G32: 45983.833 | H32: Classical | I32: 0.85 | J32: =K32/AF32 -> 0.45660377 | K32: =S32+AB32 -> 726 | L32: =X32+AC32 -> 48098.9 | M32: =Y32+AD32 -> 66500 | N32: =L32-M32 -> -18401.1 | O32: =IF(P32="Too early",P32,P32/AF32) -> 0.74140461 | P32: =IF(V32="Too early",V32,V32+AB32) -> 1178.8333 | Q32: =IF(V32="Too early",V32,AC32+V32*AG32) -> 74673.567 | R32: =IF(V32="Too early",V32,Q32-M32) -> 8173.5667 | S32: 143 | T32: =AF32-AB32 -> 1007 | U32: =(AF32-AB32)*I32 -> 855.95 | V32: =IF(B32<11,MIN((S32/VLOOKUP(B32,'Sales Pacing'!$A$23:$E$36,2)),T32),"Too early") -> 595.83333 | W32: =IF(V32="Too early","Too early",V32/U32) -> 0.69610764 | X32: 8392 | Y32: 11500 | Z32: =IF(X32>0,X32/Y32,"") -> 0.72973913 | AA32: =IF($V32="Too early",V32,V32*AG32/Y32) -> 3.0405797 | AB32: 583 | AC32: 39706.9 | AD32: 55000 | AE32: =IF(AC32>0,AC32/AD32,"") -> 0.72194364 | AF32: 1590 | AG32: =X32/S32 -> 58.685315 | AH32: 4 | AI32: 347 | AJ32: 351 | AK32: 47477.9 | AL32: =L32-AK32 -> 621
A33: 12 | B33: =A33-$G$4 -> 7 | C33: 45978 | D33: 26 CS03 Matthias and Mahler 7 | G33: 45984.583 | H33: Classical | I33: 0.85 | J33: =K33/AF33 -> 0.44968553 | K33: =S33+AB33 -> 715 | L33: =X33+AC33 -> 46572.2 | M33: =Y33+AD33 -> 66500 | N33: =L33-M33 -> -19927.8 | O33: =IF(P33="Too early",P33,P33/AF33) -> 0.63490566 | P33: =IF(V33="Too early",V33,V33+AB33) -> 1009.5 | Q33: =IF(V33="Too early",V33,AC33+V33*AG33) -> 66892.7 | R33: =IF(V33="Too early",V33,Q33-M33) -> 392.7 | S33: 93 | T33: =AF33-AB33 -> 968 | U33: =(AF33-AB33)*I33 -> 822.8 | V33: =IF(B33<11,MIN((S33/VLOOKUP(B33,'Sales Pacing'!$A$23:$E$36,2)),T33),"Too early") -> 387.5 | W33: =IF(V33="Too early","Too early",V33/U33) -> 0.47095284 | X33: 6417 | Y33: 11500 | Z33: =IF(X33>0,X33/Y33,"") -> 0.558 | AA33: =IF($V33="Too early",V33,V33*AG33/Y33) -> 2.325 | AB33: 622 | AC33: 40155.2 | AD33: 55000 | AE33: =IF(AC33>0,AC33/AD33,"") -> 0.73009455 | AF33: 1590 | AG33: =X33/S33 -> 69 | AH33: 3 | AI33: 391 | AJ33: 394 | AK33: 46613.2 | AL33: =L33-AK33 -> -41
A34: 13 | B34: =A34-$G$4 -> 8 | C34: 45985 | D34: 26 Elf™ in Concert | G34: 45989.792 | H34: Specials/Film | I34: 0.85 | J34: =K34/AF34 -> 0.26036866 | K34: =S34+AB34 -> 339 | L34: =X34+AC34 -> 23191 | M34: =Y34+AD34 -> 107500 | N34: =L34-M34 -> -84309 | O34: =IF(P34="Too early",P34,P34/AF34) -> 1 | P34: =IF(V34="Too early",V34,V34+AB34) -> 1302 | Q34: =IF(V34="Too early",V34,AC34+V34*AG34) -> 89069.858 | R34: =IF(V34="Too early",V34,Q34-M34) -> -18430.142 | S34: 339 | T34: =AF34-AB34 -> 1302 | U34: =(AF34-AB34)*I34 -> 1106.7 | V34: =IF(B34<11,MIN((S34/VLOOKUP(B34,'Sales Pacing'!$A$23:$E$36,2)),T34),"Too early") -> 1302 | W34: =IF(V34="Too early","Too early",V34/U34) -> 1.1764706 | X34: 23191 | Y34: 107500 | Z34: =IF(X34>0,X34/Y34,"") -> 0.21573023 | AA34: =IF($V34="Too early",V34,V34*AG34/Y34) -> 0.82855682 | AE34: =IF(AC34>0,AC34/AD34,"") | AF34: 1302 | AG34: =X34/S34 -> 68.410029 | AH34: 17 | AI34: 45 | AJ34: 62 | AK34: 20977.6 | AL34: =L34-AK34 -> 2213.4
A35: 13 | B35: =A35-$G$4 -> 8 | C35: 45985 | D35: 26 Elf™ in Concert | G35: 45990.542 | H35: Specials/Film | I35: 0.85 | J35: =K35/AF35 -> 0.31797235 | K35: =S35+AB35 -> 414 | L35: =X35+AC35 -> 27757 | M35: =Y35+AD35 -> 107500 | N35: =L35-M35 -> -79743 | O35: =IF(P35="Too early",P35,P35/AF35) -> 1 | P35: =IF(V35="Too early",V35,V35+AB35) -> 1302 | Q35: =IF(V35="Too early",V35,AC35+V35*AG35) -> 87293.754 | R35: =IF(V35="Too early",V35,Q35-M35) -> -20206.246 | S35: 414 | T35: =AF35-AB35 -> 1302 | U35: =(AF35-AB35)*I35 -> 1106.7 | V35: =IF(B35<11,MIN((S35/VLOOKUP(B35,'Sales Pacing'!$A$23:$E$36,2)),T35),"Too early") -> 1302 | W35: =IF(V35="Too early","Too early",V35/U35) -> 1.1764706 | X35: 27757 | Y35: 107500 | Z35: =IF(X35>0,X35/Y35,"") -> 0.25820465 | AA35: =IF($V35="Too early",V35,V35*AG35/Y35) -> 0.81203492 | AE35: =IF(AC35>0,AC35/AD35,"") | AF35: 1302 | AG35: =X35/S35 -> 67.045894 | AH35: 22 | AI35: 53 | AJ35: 75 | AK35: 24414.6 | AL35: =L35-AK35 -> 3342.4
A36: 13 | B36: =A36-$G$4 -> 8 | C36: 45985 | D36: 26 Elf™ in Concert | G36: 45990.792 | H36: Specials/Film | I36: 0.85 | J36: =K36/AF36 -> 0.25268817 | K36: =S36+AB36 -> 329 | L36: =X36+AC36 -> 22388 | M36: =Y36+AD36 -> 107500 | N36: =L36-M36 -> -85112 | O36: =IF(P36="Too early",P36,P36/AF36) -> 1 | P36: =IF(V36="Too early",V36,V36+AB36) -> 1302 | Q36: =IF(V36="Too early",V36,AC36+V36*AG36) -> 88599.319 | R36: =IF(V36="Too early",V36,Q36-M36) -> -18900.681 | S36: 329 | T36: =AF36-AB36 -> 1302 | U36: =(AF36-AB36)*I36 -> 1106.7 | V36: =IF(B36<11,MIN((S36/VLOOKUP(B36,'Sales Pacing'!$A$23:$E$36,2)),T36),"Too early") -> 1302 | W36: =IF(V36="Too early","Too early",V36/U36) -> 1.1764706 | X36: 22388 | Y36: 107500 | Z36: =IF(X36>0,X36/Y36,"") -> 0.20826047 | AA36: =IF($V36="Too early",V36,V36*AG36/Y36) -> 0.82417971 | AE36: =IF(AC36>0,AC36/AD36,"") | AF36: 1302 | AG36: =X36/S36 -> 68.048632 | AH36: 12 | AI36: 56 | AJ36: 68 | AK36: 19000 | AL36: =L36-AK36 -> 3388
A37: 13 | B37: =A37-$G$4 -> 8 | C37: 45985 | D37: 26 Elf™ in Concert | G37: 45991.583 | H37: Specials/Film | I37: 0.85 | J37: =K37/AF37 -> 0.41628264 | K37: =S37+AB37 -> 542 | L37: =X37+AC37 -> 37521 | M37: =Y37+AD37 -> 107500 | N37: =L37-M37 -> -69979 | O37: =IF(P37="Too early",P37,P37/AF37) -> 1 | P37: =IF(V37="Too early",V37,V37+AB37) -> 1302 | Q37: =IF(V37="Too early",V37,AC37+V37*AG37) -> 90133.472 | R37: =IF(V37="Too early",V37,Q37-M37) -> -17366.528 | S37: 542 | T37: =AF37-AB37 -> 1302 | U37: =(AF37-AB37)*I37 -> 1106.7 | V37: =IF(B37<11,MIN((S37/VLOOKUP(B37,'Sales Pacing'!$A$23:$E$36,2)),T37),"Too early") -> 1302 | W37: =IF(V37="Too early","Too early",V37/U37) -> 1.1764706 | X37: 37521 | Y37: 107500 | Z37: =IF(X37>0,X37/Y37,"") -> 0.34903256 | AA37: =IF($V37="Too early",V37,V37*AG37/Y37) -> 0.83845091 | AE37: =IF(AC37>0,AC37/AD37,"") | AF37: 1302 | AG37: =X37/S37 -> 69.226937 | AH37: 21 | AI37: 88 | AJ37: 109 | AK37: 34569.6 | AL37: =L37-AK37 -> 2951.4
A38: 14 | B38: =A38-$G$4 -> 9 | C38: 45992 | D38: 26 Handel's Messiah | G38: 45996.792 | H38: Holiday | I38: 0.85 | J38: =K38/AF38 -> 0.26029309 | K38: =S38+AB38 -> 373 | L38: =X38+AC38 -> 19843.5 | M38: =Y38+AD38 -> 78333 | N38: =L38-M38 -> -58489.5 | O38: =IF(P38="Too early",P38,P38/AF38) -> 1 | P38: =IF(V38="Too early",V38,V38+AB38) -> 1433 | Q38: =IF(V38="Too early",V38,AC38+V38*AG38) -> 76235.216 | R38: =IF(V38="Too early",V38,Q38-M38) -> -2097.7842 | S38: 373 | T38: =AF38-AB38 -> 1433 | U38: =(AF38-AB38)*I38 -> 1218.05 | V38: =IF(B38<11,MIN((S38/VLOOKUP(B38,'Sales Pacing'!$A$23:$E$36,2)),T38),"Too early") -> 1433 | W38: =IF(V38="Too early","Too early",V38/U38) -> 1.1764706 | X38: 19843.5 | Y38: 78333 | Z38: =IF(X38>0,X38/Y38,"") -> 0.25332235 | AA38: =IF($V38="Too early",V38,V38*AG38/Y38) -> 0.97321966 | AE38: =IF(AC38>0,AC38/AD38,"") | AF38: 1433 | AG38: =X38/S38 -> 53.199732 | AH38: 19 | AI38: 86 | AJ38: 105 | AK38: 18853.5 | AL38: =L38-AK38 -> 990
A39: 14 | B39: =A39-$G$4 -> 9 | C39: 45992 | D39: 26 Handel's Messiah | G39: 45997.792 | H39: Holiday | I39: 0.85 | J39: =K39/AF39 -> 0.26378227 | K39: =S39+AB39 -> 378 | L39: =X39+AC39 -> 22606.5 | M39: =Y39+AD39 -> 78334 | N39: =L39-M39 -> -55727.5 | O39: =IF(P39="Too early",P39,P39/AF39) -> 1 | P39: =IF(V39="Too early",V39,V39+AB39) -> 1433 | Q39: =IF(V39="Too early",V39,AC39+V39*AG39) -> 85701.361 | R39: =IF(V39="Too early",V39,Q39-M39) -> 7367.3611 | S39: 378 | T39: =AF39-AB39 -> 1433 | U39: =(AF39-AB39)*I39 -> 1218.05 | V39: =IF(B39<11,MIN((S39/VLOOKUP(B39,'Sales Pacing'!$A$23:$E$36,2)),T39),"Too early") -> 1433 | W39: =IF(V39="Too early","Too early",V39/U39) -> 1.1764706 | X39: 22606.5 | Y39: 78334 | Z39: =IF(X39>0,X39/Y39,"") -> 0.28859116 | AA39: =IF($V39="Too early",V39,V39*AG39/Y39) -> 1.0940506 | AE39: =IF(AC39>0,AC39/AD39,"") | AF39: 1433 | AG39: =X39/S39 -> 59.805556 | AH39: 20 | AI39: 95 | AJ39: 115 | AK39: 22001.5 | AL39: =L39-AK39 -> 605
A40: 14 | B40: =A40-$G$4 -> 9 | C40: 45992 | D40: 26 Handel's Messiah | G40: 45998.583 | H40: Holiday | I40: 0.85 | J40: =K40/AF40 -> 0.2965806 | K40: =S40+AB40 -> 425 | L40: =X40+AC40 -> 22602.5 | M40: =Y40+AD40 -> 78333 | N40: =L40-M40 -> -55730.5 | O40: =IF(P40="Too early",P40,P40/AF40) -> 1 | P40: =IF(V40="Too early",V40,V40+AB40) -> 1433 | Q40: =IF(V40="Too early",V40,AC40+V40*AG40) -> 76210.312 | R40: =IF(V40="Too early",V40,Q40-M40) -> -2122.6882 | S40: 425 | T40: =AF40-AB40 -> 1433 | U40: =(AF40-AB40)*I40 -> 1218.05 | V40: =IF(B40<11,MIN((S40/VLOOKUP(B40,'Sales Pacing'!$A$23:$E$36,2)),T40),"Too early") -> 1433 | W40: =IF(V40="Too early","Too early",V40/U40) -> 1.1764706 | X40: 22602.5 | Y40: 78333 | Z40: =IF(X40>0,X40/Y40,"") -> 0.28854378 | AA40: =IF($V40="Too early",V40,V40*AG40/Y40) -> 0.97290174 | AE40: =IF(AC40>0,AC40/AD40,"") | AF40: 1433 | AG40: =X40/S40 -> 53.182353 | AH40: 26 | AI40: 105 | AJ40: 131 | AK40: 21652.5 | AL40: =L40-AK40 -> 950
A41: 15 | B41: =A41-$G$4 -> 10 | C41: 45999 | D41: 26 Leslie Odom Jr.: Christmas | G41: 46003.792 | H41: Specials | I41: 0.85 | J41: =K41/AF41 -> 0.69245283 | K41: =S41+AB41 -> 1101 | L41: =X41+AC41 -> 112007 | M41: =Y41+AD41 -> 150000 | N41: =L41-M41 -> -37993 | O41: =IF(P41="Too early",P41,P41/AF41) -> 1 | P41: =IF(V41="Too early",V41,V41+AB41) -> 1590 | Q41: =IF(V41="Too early",V41,AC41+V41*AG41) -> 161753.98 | R41: =IF(V41="Too early",V41,Q41-M41) -> 11753.978 | S41: 1101 | T41: =AF41-AB41 -> 1590 | U41: =(AF41-AB41)*I41 -> 1351.5 | V41: =IF(B41<11,MIN((S41/VLOOKUP(B41,'Sales Pacing'!$A$23:$E$36,2)),T41),"Too early") -> 1590 | W41: =IF(V41="Too early","Too early",V41/U41) -> 1.1764706 | X41: 112007 | Y41: 150000 | Z41: =IF(X41>0,X41/Y41,"") -> 0.74671333 | AA41: =IF($V41="Too early",V41,V41*AG41/Y41) -> 1.0783599 | AE41: =IF(AC41>0,AC41/AD41,"") | AF41: 1590 | AG41: =X41/S41 -> 101.73206 | AH41: 87 | AI41: 264 | AJ41: 351 | AK41: 103427 | AL41: =L41-AK41 -> 8580
A42: 15 | B42: =A42-$G$4 -> 10 | C42: 45999 | D42: 26 Leslie Odom Jr.: Christmas | G42: 46004.792 | H42: Specials | I42: 0.85 | J42: =K42/AF42 -> 0.82893082 | K42: =S42+AB42 -> 1318 | L42: =X42+AC42 -> 130041 | M42: =Y42+AD42 -> 150000 | N42: =L42-M42 -> -19959 | O42: =IF(P42="Too early",P42,P42/AF42) -> 1 | P42: =IF(V42="Too early",V42,V42+AB42) -> 1590 | Q42: =IF(V42="Too early",V42,AC42+V42*AG42) -> 156877.99 | R42: =IF(V42="Too early",V42,Q42-M42) -> 6877.9894 | S42: 1318 | T42: =AF42-AB42 -> 1590 | U42: =(AF42-AB42)*I42 -> 1351.5 | V42: =IF(B42<11,MIN((S42/VLOOKUP(B42,'Sales Pacing'!$A$23:$E$36,2)),T42),"Too early") -> 1590 | W42: =IF(V42="Too early","Too early",V42/U42) -> 1.1764706 | X42: 130041 | Y42: 150000 | Z42: =IF(X42>0,X42/Y42,"") -> 0.86694 | AA42: =IF($V42="Too early",V42,V42*AG42/Y42) -> 1.0458533 | AE42: =IF(AC42>0,AC42/AD42,"") | AF42: 1590 | AG42: =X42/S42 -> 98.665402 | AH42: 128 | AI42: 291 | AJ42: 419 | AK42: 123198 | AL42: =L42-AK42 -> 6843
A43: 16 | B43: =A43-$G$4 -> 11 | C43: 46006 | D43: 26 Christmas Festival | G43: 46009.792 | H43: Holiday | I43: 0.85 | J43: =K43/AF43 -> 0.15352408 | K43: =S43+AB43 -> 220 | L43: =X43+AC43 -> 13448 | M43: =Y43+AD43 -> 75833 | N43: =L43-M43 -> -62385 | O43: =IF(P43="Too early",P43,P43/AF43) -> Too early | P43: =IF(V43="Too early",V43,V43+AB43) -> Too early | Q43: =IF(V43="Too early",V43,AC43+V43*AG43) -> Too early | R43: =IF(V43="Too early",V43,Q43-M43) -> Too early | S43: 220 | T43: =AF43-AB43 -> 1433 | U43: =(AF43-AB43)*I43 -> 1218.05 | V43: =IF(B43<11,MIN((S43/VLOOKUP(B43,'Sales Pacing'!$A$23:$E$36,2)),T43),"Too early") -> Too early | W43: =IF(V43="Too early","Too early",V43/U43) -> Too early | X43: 13448 | Y43: 75833 | Z43: =IF(X43>0,X43/Y43,"") -> 0.17733704 | AA43: =IF($V43="Too early",V43,V43*AG43/Y43) -> Too early | AE43: =IF(AC43>0,AC43/AD43,"") | AF43: 1433 | AG43: =X43/S43 -> 61.127273 | AK43: 13189 | AL43: =L43-AK43 -> 259
A44: 16 | B44: =A44-$G$4 -> 11 | C44: 46006 | D44: 26 Christmas Festival | G44: 46010.792 | H44: Holiday | I44: 0.85 | J44: =K44/AF44 -> 0.14724355 | K44: =S44+AB44 -> 211 | L44: =X44+AC44 -> 12725 | M44: =Y44+AD44 -> 75833 | N44: =L44-M44 -> -63108 | O44: =IF(P44="Too early",P44,P44/AF44) -> Too early | P44: =IF(V44="Too early",V44,V44+AB44) -> Too early | Q44: =IF(V44="Too early",V44,AC44+V44*AG44) -> Too early | R44: =IF(V44="Too early",V44,Q44-M44) -> Too early | S44: 211 | T44: =AF44-AB44 -> 1433 | U44: =(AF44-AB44)*I44 -> 1218.05 | V44: =IF(B44<11,MIN((S44/VLOOKUP(B44,'Sales Pacing'!$A$23:$E$36,2)),T44),"Too early") -> Too early | W44: =IF(V44="Too early","Too early",V44/U44) -> Too early | X44: 12725 | Y44: 75833 | Z44: =IF(X44>0,X44/Y44,"") -> 0.16780294 | AA44: =IF($V44="Too early",V44,V44*AG44/Y44) -> Too early | AE44: =IF(AC44>0,AC44/AD44,"") | AF44: 1433 | AG44: =X44/S44 -> 60.308057 | AK44: 11666.5 | AL44: =L44-AK44 -> 1058.5
A45: 16 | B45: =A45-$G$4 -> 11 | C45: 46006 | D45: 26 Christmas Festival | G45: 46011.542 | H45: Holiday | I45: 0.85 | J45: =K45/AF45 -> 0.27076064 | K45: =S45+AB45 -> 388 | L45: =X45+AC45 -> 23671 | M45: =Y45+AD45 -> 75833 | N45: =L45-M45 -> -52162 | O45: =IF(P45="Too early",P45,P45/AF45) -> Too early | P45: =IF(V45="Too early",V45,V45+AB45) -> Too early | Q45: =IF(V45="Too early",V45,AC45+V45*AG45) -> Too early | R45: =IF(V45="Too early",V45,Q45-M45) -> Too early | S45: 388 | T45: =AF45-AB45 -> 1433 | U45: =(AF45-AB45)*I45 -> 1218.05 | V45: =IF(B45<11,MIN((S45/VLOOKUP(B45,'Sales Pacing'!$A$23:$E$36,2)),T45),"Too early") -> Too early | W45: =IF(V45="Too early","Too early",V45/U45) -> Too early | X45: 23671 | Y45: 75833 | Z45: =IF(X45>0,X45/Y45,"") -> 0.31214643 | AA45: =IF($V45="Too early",V45,V45*AG45/Y45) -> Too early | AE45: =IF(AC45>0,AC45/AD45,"") | AF45: 1433 | AG45: =X45/S45 -> 61.007732 | AK45: 21404.5 | AL45: =L45-AK45 -> 2266.5
A46: 16 | B46: =A46-$G$4 -> 11 | C46: 46006 | D46: 26 Christmas Festival | G46: 46011.792 | H46: Holiday | I46: 0.85 | J46: =K46/AF46 -> 0.20376832 | K46: =S46+AB46 -> 292 | L46: =X46+AC46 -> 18196 | M46: =Y46+AD46 -> 75833 | N46: =L46-M46 -> -57637 | O46: =IF(P46="Too early",P46,P46/AF46) -> Too early | P46: =IF(V46="Too early",V46,V46+AB46) -> Too early | Q46: =IF(V46="Too early",V46,AC46+V46*AG46) -> Too early | R46: =IF(V46="Too early",V46,Q46-M46) -> Too early | S46: 292 | T46: =AF46-AB46 -> 1433 | U46: =(AF46-AB46)*I46 -> 1218.05 | V46: =IF(B46<11,MIN((S46/VLOOKUP(B46,'Sales Pacing'!$A$23:$E$36,2)),T46),"Too early") -> Too early | W46: =IF(V46="Too early","Too early",V46/U46) -> Too early | X46: 18196 | Y46: 75833 | Z46: =IF(X46>0,X46/Y46,"") -> 0.23994831 | AA46: =IF($V46="Too early",V46,V46*AG46/Y46) -> Too early | AE46: =IF(AC46>0,AC46/AD46,"") | AF46: 1433 | AG46: =X46/S46 -> 62.315068 | AK46: 13817 | AL46: =L46-AK46 -> 4379
A47: 16 | B47: =A47-$G$4 -> 11 | C47: 46006 | D47: 26 Christmas Festival | G47: 46012.583 | H47: Holiday | I47: 0.85 | J47: =K47/AF47 -> 0.43893929 | K47: =S47+AB47 -> 629 | L47: =X47+AC47 -> 26133 | M47: =Y47+AD47 -> 88284 | N47: =L47-M47 -> -62151 | O47: =IF(P47="Too early",P47,P47/AF47) -> Too early | P47: =IF(V47="Too early",V47,V47+AB47) -> Too early | Q47: =IF(V47="Too early",V47,AC47+V47*AG47) -> Too early | R47: =IF(V47="Too early",V47,Q47-M47) -> Too early | S47: 328 | T47: =AF47-AB47 -> 1132 | U47: =(AF47-AB47)*I47 -> 962.2 | V47: =IF(B47<11,MIN((S47/VLOOKUP(B47,'Sales Pacing'!$A$23:$E$36,2)),T47),"Too early") -> Too early | W47: =IF(V47="Too early","Too early",V47/U47) -> Too early | X47: 19456 | Y47: 75834 | Z47: =IF(X47>0,X47/Y47,"") -> 0.25656038 | AA47: =IF($V47="Too early",V47,V47*AG47/Y47) -> Too early | AB47: 301 | AC47: 6677 | AD47: 12450 | AE47: =IF(AC47>0,AC47/AD47,"") -> 0.53630522 | AF47: 1433 | AG47: =X47/S47 -> 59.317073 | AK47: 23553 | AL47: =L47-AK47 -> 2580
A48: 16 | B48: =A48-$G$4 -> 11 | C48: 46006 | D48: 26 Christmas Festival | G48: 46012.792 | H48: Holiday | I48: 0.85 | J48: =K48/AF48 -> 0.10607118 | K48: =S48+AB48 -> 152 | L48: =X48+AC48 -> 8879 | M48: =Y48+AD48 -> 75834 | N48: =L48-M48 -> -66955 | O48: =IF(P48="Too early",P48,P48/AF48) -> Too early | P48: =IF(V48="Too early",V48,V48+AB48) -> Too early | Q48: =IF(V48="Too early",V48,AC48+V48*AG48) -> Too early | R48: =IF(V48="Too early",V48,Q48-M48) -> Too early | S48: 152 | T48: =AF48-AB48 -> 1433 | U48: =(AF48-AB48)*I48 -> 1218.05 | V48: =IF(B48<11,MIN((S48/VLOOKUP(B48,'Sales Pacing'!$A$23:$E$36,2)),T48),"Too early") -> Too early | W48: =IF(V48="Too early","Too early",V48/U48) -> Too early | X48: 8879 | Y48: 75834 | Z48: =IF(X48>0,X48/Y48,"") -> 0.11708468 | AA48: =IF($V48="Too early",V48,V48*AG48/Y48) -> Too early | AE48: =IF(AC48>0,AC48/AD48,"") | AF48: 1433 | AG48: =X48/S48 -> 58.414474 | AK48: 7896 | AL48: =L48-AK48 -> 983
A49: 17 | B49: =A49-$G$4 -> 12 | C49: 46013 | D49: 26 It's a Wonderful Life | G49: 46014.792 | H49: Specials/Film | I49: 0.85 | J49: =K49/AF49 -> 0.70046083 | K49: =S49+AB49 -> 912 | L49: =X49+AC49 -> 71586 | M49: =Y49+AD49 -> 100000 | N49: =L49-M49 -> -28414 | O49: =IF(P49="Too early",P49,P49/AF49) -> Too early | P49: =IF(V49="Too early",V49,V49+AB49) -> Too early | Q49: =IF(V49="Too early",V49,AC49+V49*AG49) -> Too early | R49: =IF(V49="Too early",V49,Q49-M49) -> Too early | S49: 912 | T49: =AF49-AB49 -> 1302 | U49: =(AF49-AB49)*I49 -> 1106.7 | V49: =IF(B49<11,MIN((S49/VLOOKUP(B49,'Sales Pacing'!$A$23:$E$36,2)),T49),"Too early") -> Too early | W49: =IF(V49="Too early","Too early",V49/U49) -> Too early | X49: 71586 | Y49: 100000 | Z49: =IF(X49>0,X49/Y49,"") -> 0.71586 | AA49: =IF($V49="Too early",V49,V49*AG49/Y49) -> Too early | AE49: =IF(AC49>0,AC49/AD49,"") | AF49: 1302 | AG49: =X49/S49 -> 78.493421 | AK49: 66653.6 | AL49: =L49-AK49 -> 4932.4
A50: 17 | B50: =A50-$G$4 -> 12 | C50: 46013 | D50: 26 It's a Wonderful Life | G50: 46015.458 | H50: Specials/Film | I50: 0.85 | J50: =K50/AF50 -> 0.16973886 | K50: =S50+AB50 -> 221 | L50: =X50+AC50 -> 15226 | M50: =Y50+AD50 -> 100000 | N50: =L50-M50 -> -84774 | O50: =IF(P50="Too early",P50,P50/AF50) -> Too early | P50: =IF(V50="Too early",V50,V50+AB50) -> Too early | Q50: =IF(V50="Too early",V50,AC50+V50*AG50) -> Too early | R50: =IF(V50="Too early",V50,Q50-M50) -> Too early | S50: 221 | T50: =AF50-AB50 -> 1302 | U50: =(AF50-AB50)*I50 -> 1106.7 | V50: =IF(B50<11,MIN((S50/VLOOKUP(B50,'Sales Pacing'!$A$23:$E$36,2)),T50),"Too early") -> Too early | W50: =IF(V50="Too early","Too early",V50/U50) -> Too early | X50: 15226 | Y50: 100000 | Z50: =IF(X50>0,X50/Y50,"") -> 0.15226 | AA50: =IF($V50="Too early",V50,V50*AG50/Y50) -> Too early | AE50: =IF(AC50>0,AC50/AD50,"") | AF50: 1302 | AG50: =X50/S50 -> 68.895928 | AK50: 14364.4 | AL50: =L50-AK50 -> 861.6
A51: 18 | B51: =A51-$G$4 -> 13 | C51: 46020 | D51: OPEN | J51: =K51/AF51 -> #DIV/0! | K51: =S51+AB51 -> 0 | L51: =X51+AC51 -> 0 | M51: =Y51+AD51 -> 0 | P51: =IF(V51="Too early",V51,V51+AB51) -> Too early | Q51: =IF(V51="Too early",V51,AC51+V51*AG51) -> Too early | R51: =IF(V51="Too early",V51,Q51-M51) -> Too early | T51: =AF51-AB51 -> 0 | U51: =(AF51-AB51)*I51 -> 0 | V51: =IF(B51<11,MIN((S51/VLOOKUP(B51,'Sales Pacing'!$A$23:$E$36,2)),T51),"Too early") -> Too early | Z51: =IF(X51>0,X51/Y51,"") | AE51: N/A | AG51: =X51/S51 -> #DIV/0! | AK51: 0
A52: 19 | B52: =A52-$G$4 -> 14 | C52: 46027 | D52: 26 CS04 Brahms' Fourth Symphony | G52: 46031.833 | H52: Classical | I52: 0.85 | J52: =K52/AF52 -> 0.37987421 | K52: =S52+AB52 -> 604 | L52: =X52+AC52 -> 39771 | M52: =Y52+AD52 -> 54999 | N52: =L52-M52 -> -15228 | O52: =IF(P52="Too early",P52,P52/AF52) -> Too early | P52: =IF(V52="Too early",V52,V52+AB52) -> Too early | Q52: =IF(V52="Too early",V52,AC52+V52*AG52) -> Too early | R52: =IF(V52="Too early",V52,Q52-M52) -> Too early | S52: 31 | T52: =AF52-AB52 -> 1017 | U52: =(AF52-AB52)*I52 -> 864.45 | V52: =IF(B52<11,MIN((S52/VLOOKUP(B52,'Sales Pacing'!$A$23:$E$36,2)),T52),"Too early") -> Too early | W52: =IF(V52="Too early","Too early",V52/U52) -> Too early | X52: 1334 | Y52: 21666 | Z52: =IF(X52>0,X52/Y52,"") -> 0.061571125 | AA52: =IF($V52="Too early",V52,V52*AG52/Y52) -> Too early | AB52: 573 | AC52: 38437 | AD52: 33333 | AE52: =IF(AC52>0,AC52/AD52,"") -> 1.1531215 | AF52: 1590 | AG52: =X52/S52 -> 43.032258 | AK52: 39591 | AL52: =L52-AK52 -> 180
A53: 19 | B53: =A53-$G$4 -> 14 | C53: 46027 | D53: 27 CS04 Brahms' Fourth Symphony | G53: 46032.833 | H53: Classical | I53: 0.85 | J53: =K53/AF53 -> 0.39622642 | K53: =S53+AB53 -> 630 | L53: =X53+AC53 -> 40664 | M53: =Y53+AD53 -> 54999 | N53: =L53-M53 -> -14335 | O53: =IF(P53="Too early",P53,P53/AF53) -> Too early | P53: =IF(V53="Too early",V53,V53+AB53) -> Too early | Q53: =IF(V53="Too early",V53,AC53+V53*AG53) -> Too early | R53: =IF(V53="Too early",V53,Q53-M53) -> Too early | S53: 73 | T53: =AF53-AB53 -> 1033 | U53: =(AF53-AB53)*I53 -> 878.05 | V53: =IF(B53<11,MIN((S53/VLOOKUP(B53,'Sales Pacing'!$A$23:$E$36,2)),T53),"Too early") -> Too early | W53: =IF(V53="Too early","Too early",V53/U53) -> Too early | X53: 4273 | Y53: 21666 | Z53: =IF(X53>0,X53/Y53,"") -> 0.19722145 | AA53: =IF($V53="Too early",V53,V53*AG53/Y53) -> Too early | AB53: 557 | AC53: 36391 | AD53: 33333 | AE53: =IF(AC53>0,AC53/AD53,"") -> 1.0917409 | AF53: 1590 | AG53: =X53/S53 -> 58.534247 | AK53: 40128 | AL53: =L53-AK53 -> 536
A54: 19 | B54: =A54-$G$4 -> 14 | C54: 46027 | D54: 28 CS04 Brahms' Fourth Symphony | G54: 46033.583 | H54: Classical | I54: 0.85 | J54: =K54/AF54 -> 0.39371069 | K54: =S54+AB54 -> 626 | L54: =X54+AC54 -> 39937.5 | M54: =Y54+AD54 -> 55000 | N54: =L54-M54 -> -15062.5 | O54: =IF(P54="Too early",P54,P54/AF54) -> Too early | P54: =IF(V54="Too early",V54,V54+AB54) -> Too early | Q54: =IF(V54="Too early",V54,AC54+V54*AG54) -> Too early | R54: =IF(V54="Too early",V54,Q54-M54) -> Too early | S54: 55 | T54: =AF54-AB54 -> 1019 | U54: =(AF54-AB54)*I54 -> 866.15 | V54: =IF(B54<11,MIN((S54/VLOOKUP(B54,'Sales Pacing'!$A$23:$E$36,2)),T54),"Too early") -> Too early | W54: =IF(V54="Too early","Too early",V54/U54) -> Too early | X54: 3188 | Y54: 21666 | Z54: =IF(X54>0,X54/Y54,"") -> 0.14714299 | AA54: =IF($V54="Too early",V54,V54*AG54/Y54) -> Too early | AB54: 571 | AC54: 36749.5 | AD54: 33334 | AE54: =IF(AC54>0,AC54/AD54,"") -> 1.102463 | AF54: 1590 | AG54: =X54/S54 -> 57.963636 | AK54: 39791.5 | AL54: =L54-AK54 -> 146
A55: 20 | B55: =A55-$G$4 -> 15 | C55: 46034 | D55: 26 CS05 Pines of Rome & Bruch | G55: 46038.833 | H55: Classical | I55: 0.85 | J55: =K55/AF55 -> 0.26352201 | K55: =S55+AB55 -> 419 | L55: =X55+AC55 -> 28302 | M55: =Y55+AD55 -> 60000 | N55: =L55-M55 -> -31698 | O55: =IF(P55="Too early",P55,P55/AF55) -> Too early | P55: =IF(V55="Too early",V55,V55+AB55) -> Too early | Q55: =IF(V55="Too early",V55,AC55+V55*AG55) -> Too early | R55: =IF(V55="Too early",V55,Q55-M55) -> Too early | S55: 51 | T55: =AF55-AB55 -> 1222 | U55: =(AF55-AB55)*I55 -> 1038.7 | V55: =IF(B55<11,MIN((S55/VLOOKUP(B55,'Sales Pacing'!$A$23:$E$36,2)),T55),"Too early") -> Too early | W55: =IF(V55="Too early","Too early",V55/U55) -> Too early | X55: 2960 | Y55: 30000 | Z55: =IF(X55>0,X55/Y55,"") -> 0.098666667 | AA55: =IF($V55="Too early",V55,V55*AG55/Y55) -> Too early | AB55: 368 | AC55: 25342 | AD55: 30000 | AE55: =IF(AC55>0,AC55/AD55,"") -> 0.84473333 | AF55: 1590 | AG55: =X55/S55 -> 58.039216 | AK55: 28243 | AL55: =L55-AK55 -> 59
A56: 20 | B56: =A56-$G$4 -> 15 | C56: 46034 | D56: 26 CS05 Pines of Rome & Bruch | G56: 46039.833 | H56: Classical | I56: 0.85 | J56: =K56/AF56 -> 0.45660377 | K56: =S56+AB56 -> 726 | L56: =X56+AC56 -> 47864.9 | M56: =Y56+AD56 -> 75000 | N56: =L56-M56 -> -27135.1 | O56: =IF(P56="Too early",P56,P56/AF56) -> Too early | P56: =IF(V56="Too early",V56,V56+AB56) -> Too early | Q56: =IF(V56="Too early",V56,AC56+V56*AG56) -> Too early | R56: =IF(V56="Too early",V56,Q56-M56) -> Too early | S56: 126 | T56: =AF56-AB56 -> 990 | U56: =(AF56-AB56)*I56 -> 841.5 | V56: =IF(B56<11,MIN((S56/VLOOKUP(B56,'Sales Pacing'!$A$23:$E$36,2)),T56),"Too early") -> Too early | W56: =IF(V56="Too early","Too early",V56/U56) -> Too early | X56: 7358 | Y56: 20000 | Z56: =IF(X56>0,X56/Y56,"") -> 0.3679 | AA56: =IF($V56="Too early",V56,V56*AG56/Y56) -> Too early | AB56: 600 | AC56: 40506.9 | AD56: 55000 | AE56: =IF(AC56>0,AC56/AD56,"") -> 0.73648909 | AF56: 1590 | AG56: =X56/S56 -> 58.396825 | AK56: 47394.9 | AL56: =L56-AK56 -> 470
A57: 20 | B57: =A57-$G$4 -> 15 | C57: 46034 | D57: 26 CS05 Pines of Rome & Bruch | G57: 46040.583 | H57: Classical | I57: 0.85 | J57: =K57/AF57 -> 0.4408805 | K57: =S57+AB57 -> 701 | L57: =X57+AC57 -> 44947.2 | M57: =Y57+AD57 -> 75000 | N57: =L57-M57 -> -30052.8 | O57: =IF(P57="Too early",P57,P57/AF57) -> Too early | P57: =IF(V57="Too early",V57,V57+AB57) -> Too early | Q57: =IF(V57="Too early",V57,AC57+V57*AG57) -> Too early | R57: =IF(V57="Too early",V57,Q57-M57) -> Too early | S57: 93 | T57: =AF57-AB57 -> 982 | U57: =(AF57-AB57)*I57 -> 834.7 | V57: =IF(B57<11,MIN((S57/VLOOKUP(B57,'Sales Pacing'!$A$23:$E$36,2)),T57),"Too early") -> Too early | W57: =IF(V57="Too early","Too early",V57/U57) -> Too early | X57: 5931 | Y57: 20000 | Z57: =IF(X57>0,X57/Y57,"") -> 0.29655 | AA57: =IF($V57="Too early",V57,V57*AG57/Y57) -> Too early | AB57: 608 | AC57: 39016.2 | AD57: 55000 | AE57: =IF(AC57>0,AC57/AD57,"") -> 0.70938545 | AF57: 1590 | AG57: =X57/S57 -> 63.774194 | AK57: 44600.2 | AL57: =L57-AK57 -> 347
A58: 21 | B58: =A58-$G$4 -> 16 | C58: 46041 | D58: 26 Indiana Jones: Raiders Lost | G58: 46044.792 | H58: Specials/Film | I58: 0.85 | J58: =K58/AF58 -> 0.10061444 | K58: =S58+AB58 -> 131 | L58: =X58+AC58 -> 7965 | M58: =Y58+AD58 -> 90000 | N58: =L58-M58 -> -82035 | O58: =IF(P58="Too early",P58,P58/AF58) -> Too early | P58: =IF(V58="Too early",V58,V58+AB58) -> Too early | Q58: =IF(V58="Too early",V58,AC58+V58*AG58) -> Too early | R58: =IF(V58="Too early",V58,Q58-M58) -> Too early | S58: 131 | T58: =AF58-AB58 -> 1302 | U58: =(AF58-AB58)*I58 -> 1106.7 | V58: =IF(B58<11,MIN((S58/VLOOKUP(B58,'Sales Pacing'!$A$23:$E$36,2)),T58),"Too early") -> Too early | W58: =IF(V58="Too early","Too early",V58/U58) -> Too early | X58: 7965 | Y58: 90000 | Z58: =IF(X58>0,X58/Y58,"") -> 0.0885 | AA58: =IF($V58="Too early",V58,V58*AG58/Y58) -> Too early | AE58: =IF(AC58>0,AC58/AD58,"") | AF58: 1302 | AG58: =X58/S58 -> 60.801527 | AK58: 7410 | AL58: =L58-AK58 -> 555
A59: 21 | B59: =A59-$G$4 -> 16 | C59: 46041 | D59: 26 Indiana Jones: Raiders Lost | G59: 46045.792 | H59: Specials/Film | I59: 0.85 | J59: =K59/AF59 -> 0.23502304 | K59: =S59+AB59 -> 306 | L59: =X59+AC59 -> 22141.9 | M59: =Y59+AD59 -> 90000 | N59: =L59-M59 -> -67858.1 | O59: =IF(P59="Too early",P59,P59/AF59) -> Too early | P59: =IF(V59="Too early",V59,V59+AB59) -> Too early | Q59: =IF(V59="Too early",V59,AC59+V59*AG59) -> Too early | R59: =IF(V59="Too early",V59,Q59-M59) -> Too early | S59: 306 | T59: =AF59-AB59 -> 1302 | U59: =(AF59-AB59)*I59 -> 1106.7 | V59: =IF(B59<11,MIN((S59/VLOOKUP(B59,'Sales Pacing'!$A$23:$E$36,2)),T59),"Too early") -> Too early | W59: =IF(V59="Too early","Too early",V59/U59) -> Too early | X59: 22141.9 | Y59: 90000 | Z59: =IF(X59>0,X59/Y59,"") -> 0.24602111 | AA59: =IF($V59="Too early",V59,V59*AG59/Y59) -> Too early | AE59: =IF(AC59>0,AC59/AD59,"") | AF59: 1302 | AG59: =X59/S59 -> 72.35915 | AK59: 21481.9 | AL59: =L59-AK59 -> 660
A60: 21 | B60: =A60-$G$4 -> 16 | C60: 46041 | D60: 26 Indiana Jones: Raiders Lost | G60: 46046.792 | H60: Specials/Film | I60: 0.85 | J60: =K60/AF60 -> 0.38479263 | K60: =S60+AB60 -> 501 | L60: =X60+AC60 -> 36718.1 | M60: =Y60+AD60 -> 90000 | N60: =L60-M60 -> -53281.9 | O60: =IF(P60="Too early",P60,P60/AF60) -> Too early | P60: =IF(V60="Too early",V60,V60+AB60) -> Too early | Q60: =IF(V60="Too early",V60,AC60+V60*AG60) -> Too early | R60: =IF(V60="Too early",V60,Q60-M60) -> Too early | S60: 501 | T60: =AF60-AB60 -> 1302 | U60: =(AF60-AB60)*I60 -> 1106.7 | V60: =IF(B60<11,MIN((S60/VLOOKUP(B60,'Sales Pacing'!$A$23:$E$36,2)),T60),"Too early") -> Too early | W60: =IF(V60="Too early","Too early",V60/U60) -> Too early | X60: 36718.1 | Y60: 90000 | Z60: =IF(X60>0,X60/Y60,"") -> 0.40797889 | AA60: =IF($V60="Too early",V60,V60*AG60/Y60) -> Too early | AE60: =IF(AC60>0,AC60/AD60,"") | AF60: 1302 | AG60: =X60/S60 -> 73.289621 | AK60: 34988.1 | AL60: =L60-AK60 -> 1730
A61: 21 | B61: =A61-$G$4 -> 16 | C61: 46041 | D61: 26 Indiana Jones: Raiders Lost | G61: 46047.583 | H61: Specials/Film | I61: 0.85 | J61: =K61/AF61 -> 0.29493088 | K61: =S61+AB61 -> 384 | L61: =X61+AC61 -> 26947.1 | M61: =Y61+AD61 -> 90000 | N61: =L61-M61 -> -63052.9 | O61: =IF(P61="Too early",P61,P61/AF61) -> Too early | P61: =IF(V61="Too early",V61,V61+AB61) -> Too early | Q61: =IF(V61="Too early",V61,AC61+V61*AG61) -> Too early | R61: =IF(V61="Too early",V61,Q61-M61) -> Too early | S61: 384 | T61: =AF61-AB61 -> 1302 | U61: =(AF61-AB61)*I61 -> 1106.7 | V61: =IF(B61<11,MIN((S61/VLOOKUP(B61,'Sales Pacing'!$A$23:$E$36,2)),T61),"Too early") -> Too early | W61: =IF(V61="Too early","Too early",V61/U61) -> Too early | X61: 26947.1 | Y61: 90000 | Z61: =IF(X61>0,X61/Y61,"") -> 0.29941222 | AA61: =IF($V61="Too early",V61,V61*AG61/Y61) -> Too early | AE61: =IF(AC61>0,AC61/AD61,"") | AF61: 1302 | AG61: =X61/S61 -> 70.17474 | AK61: 26457.1 | AL61: =L61-AK61 -> 490
A62: 22 | B62: =A62-$G$4 -> 17 | C62: 46048 | D62: 26 CS06 Beethoven+ | G62: 46052.833 | H62: Classical | I62: 0.85 | J62: =K62/AF62 -> 0.27358491 | K62: =S62+AB62 -> 435 | L62: =X62+AC62 -> 28716 | M62: =Y62+AD62 -> 54000 | N62: =L62-M62 -> -25284 | O62: =IF(P62="Too early",P62,P62/AF62) -> Too early | P62: =IF(V62="Too early",V62,V62+AB62) -> Too early | Q62: =IF(V62="Too early",V62,AC62+V62*AG62) -> Too early | R62: =IF(V62="Too early",V62,Q62-M62) -> Too early | S62: 71 | T62: =AF62-AB62 -> 1226 | U62: =(AF62-AB62)*I62 -> 1042.1 | V62: =IF(B62<11,MIN((S62/VLOOKUP(B62,'Sales Pacing'!$A$23:$E$36,2)),T62),"Too early") -> Too early | W62: =IF(V62="Too early","Too early",V62/U62) -> Too early | X62: 3847 | Y62: 24000 | Z62: =IF(X62>0,X62/Y62,"") -> 0.16029167 | AA62: =IF($V62="Too early",V62,V62*AG62/Y62) -> Too early | AB62: 364 | AC62: 24869 | AD62: 30000 | AE62: =IF(AC62>0,AC62/AD62,"") -> 0.82896667 | AF62: 1590 | AG62: =X62/S62 -> 54.183099 | AK62: 28368 | AL62: =L62-AK62 -> 348
A63: 22 | B63: =A63-$G$4 -> 17 | C63: 46048 | D63: 26 CS06 Beethoven+ | G63: 46053.833 | H63: Classical | I63: 0.85 | J63: =K63/AF63 -> 0.43522013 | K63: =S63+AB63 -> 692 | L63: =X63+AC63 -> 45477.9 | M63: =Y63+AD63 -> 75000 | N63: =L63-M63 -> -29522.1 | O63: =IF(P63="Too early",P63,P63/AF63) -> Too early | P63: =IF(V63="Too early",V63,V63+AB63) -> Too early | Q63: =IF(V63="Too early",V63,AC63+V63*AG63) -> Too early | R63: =IF(V63="Too early",V63,Q63-M63) -> Too early | S63: 94 | T63: =AF63-AB63 -> 992 | U63: =(AF63-AB63)*I63 -> 843.2 | V63: =IF(B63<11,MIN((S63/VLOOKUP(B63,'Sales Pacing'!$A$23:$E$36,2)),T63),"Too early") -> Too early | W63: =IF(V63="Too early","Too early",V63/U63) -> Too early | X63: 5569 | Y63: 20000 | Z63: =IF(X63>0,X63/Y63,"") -> 0.27845 | AA63: =IF($V63="Too early",V63,V63*AG63/Y63) -> Too early | AB63: 598 | AC63: 39908.9 | AD63: 55000 | AE63: =IF(AC63>0,AC63/AD63,"") -> 0.72561636 | AF63: 1590 | AG63: =X63/S63 -> 59.244681 | AK63: 45500.9 | AL63: =L63-AK63 -> -23
A64: 22 | B64: =A64-$G$4 -> 17 | C64: 46048 | D64: 26 CS06 Beethoven+ | G64: 46054.583 | H64: Classical | I64: 0.85 | J64: =K64/AF64 -> 0.42830189 | K64: =S64+AB64 -> 681 | L64: =X64+AC64 -> 43667.2 | M64: =Y64+AD64 -> 75000 | N64: =L64-M64 -> -31332.8 | O64: =IF(P64="Too early",P64,P64/AF64) -> Too early | P64: =IF(V64="Too early",V64,V64+AB64) -> Too early | Q64: =IF(V64="Too early",V64,AC64+V64*AG64) -> Too early | R64: =IF(V64="Too early",V64,Q64-M64) -> Too early | S64: 72 | T64: =AF64-AB64 -> 981 | U64: =(AF64-AB64)*I64 -> 833.85 | V64: =IF(B64<11,MIN((S64/VLOOKUP(B64,'Sales Pacing'!$A$23:$E$36,2)),T64),"Too early") -> Too early | W64: =IF(V64="Too early","Too early",V64/U64) -> Too early | X64: 4644 | Y64: 20000 | Z64: =IF(X64>0,X64/Y64,"") -> 0.2322 | AA64: =IF($V64="Too early",V64,V64*AG64/Y64) -> Too early | AB64: 609 | AC64: 39023.2 | AD64: 55000 | AE64: =IF(AC64>0,AC64/AD64,"") -> 0.70951273 | AF64: 1590 | AG64: =X64/S64 -> 64.5 | AK64: 43394.2 | AL64: =L64-AK64 -> 273
A65: 23 | B65: =A65-$G$4 -> 18 | C65: 46055 | D65: 26 On-Stage 2 Leila Josefowicz | G65: 46058.833 | H65: On Stage | I65: 0.85 | J65: =K65/AF65 -> 0.19 | K65: =S65+AB65 -> 19 | L65: =X65+AC65 -> 1960 | M65: 9000 | N65: =L65-M65 -> -7040 | O65: =IF(P65="Too early",P65,P65/AF65) -> Too early | P65: =IF(V65="Too early",V65,V65+AB65) -> Too early | Q65: =IF(V65="Too early",V65,AC65+V65*AG65) -> Too early | R65: =IF(V65="Too early",V65,Q65-M65) -> Too early | S65: 19 | T65: =AF65-AB65 -> 100 | U65: =(AF65-AB65)*I65 -> 85 | V65: =IF(B65<11,MIN((S65/VLOOKUP(B65,'Sales Pacing'!$A$23:$E$36,2)),T65),"Too early") -> Too early | W65: =IF(V65="Too early","Too early",V65/U65) -> Too early | X65: 1960 | Y65: 9000 | Z65: =IF(X65>0,X65/Y65,"") -> 0.21777778 | AA65: =IF($V65="Too early",V65,V65*AG65/Y65) -> Too early | AE65: =IF(AC65>0,AC65/AD65,"") | AF65: 100 | AG65: =X65/S65 -> 103.15789 | AK65: 1960 | AL65: =L65-AK65 -> 0
A66: 23 | B66: =A66-$G$4 -> 18 | C66: 46055 | D66: 26 CS07 Prokofiev's Fifth Symphony | G66: 46059.833 | H66: Classical | I66: 0.85 | J66: =K66/AF66 -> 0.39245283 | K66: =S66+AB66 -> 624 | L66: =X66+AC66 -> 40003 | M66: =Y66+AD66 -> 46666 | N66: =L66-M66 -> -6663 | O66: =IF(P66="Too early",P66,P66/AF66) -> Too early | P66: =IF(V66="Too early",V66,V66+AB66) -> Too early | Q66: =IF(V66="Too early",V66,AC66+V66*AG66) -> Too early | R66: =IF(V66="Too early",V66,Q66-M66) -> Too early | S66: 62 | T66: =AF66-AB66 -> 1028 | U66: =(AF66-AB66)*I66 -> 873.8 | V66: =IF(B66<11,MIN((S66/VLOOKUP(B66,'Sales Pacing'!$A$23:$E$36,2)),T66),"Too early") -> Too early | W66: =IF(V66="Too early","Too early",V66/U66) -> Too early | X66: 2540 | Y66: 13333 | Z66: =IF(X66>0,X66/Y66,"") -> 0.19050476 | AA66: =IF($V66="Too early",V66,V66*AG66/Y66) -> Too early | AB66: 562 | AC66: 37463 | AD66: 33333 | AE66: =IF(AC66>0,AC66/AD66,"") -> 1.1239012 | AF66: 1590 | AG66: =X66/S66 -> 40.967742 | AK66: 39823 | AL66: =L66-AK66 -> 180
A67: 23 | B67: =A67-$G$4 -> 18 | C67: 46055 | D67: 27 CS07 Prokofiev's Fifth Symphony | G67: 46060.833 | H67: Classical | I67: 0.85 | J67: =K67/AF67 -> 0.38238994 | K67: =S67+AB67 -> 608 | L67: =X67+AC67 -> 38795.2 | M67: =Y67+AD67 -> 46666 | N67: =L67-M67 -> -7870.8 | O67: =IF(P67="Too early",P67,P67/AF67) -> Too early | P67: =IF(V67="Too early",V67,V67+AB67) -> Too early | Q67: =IF(V67="Too early",V67,AC67+V67*AG67) -> Too early | R67: =IF(V67="Too early",V67,Q67-M67) -> Too early | S67: 49 | T67: =AF67-AB67 -> 1031 | U67: =(AF67-AB67)*I67 -> 876.35 | V67: =IF(B67<11,MIN((S67/VLOOKUP(B67,'Sales Pacing'!$A$23:$E$36,2)),T67),"Too early") -> Too early | W67: =IF(V67="Too early","Too early",V67/U67) -> Too early | X67: 2478 | Y67: 13333 | Z67: =IF(X67>0,X67/Y67,"") -> 0.18585465 | AA67: =IF($V67="Too early",V67,V67*AG67/Y67) -> Too early | AB67: 559 | AC67: 36317.2 | AD67: 33333 | AE67: =IF(AC67>0,AC67/AD67,"") -> 1.0895269 | AF67: 1590 | AG67: =X67/S67 -> 50.571429 | AK67: 38606.2 | AL67: =L67-AK67 -> 189
A68: 23 | B68: =A68-$G$4 -> 18 | C68: 46055 | D68: 28 CS07 Prokofiev's Fifth Symphony | G68: 46061.583 | H68: Classical | I68: 0.85 | J68: =K68/AF68 -> 0.38113208 | K68: =S68+AB68 -> 606 | L68: =X68+AC68 -> 38109.1 | M68: =Y68+AD68 -> 46667 | N68: =L68-M68 -> -8557.9 | O68: =IF(P68="Too early",P68,P68/AF68) -> Too early | P68: =IF(V68="Too early",V68,V68+AB68) -> Too early | Q68: =IF(V68="Too early",V68,AC68+V68*AG68) -> Too early | R68: =IF(V68="Too early",V68,Q68-M68) -> Too early | S68: 44 | T68: =AF68-AB68 -> 1028 | U68: =(AF68-AB68)*I68 -> 873.8 | V68: =IF(B68<11,MIN((S68/VLOOKUP(B68,'Sales Pacing'!$A$23:$E$36,2)),T68),"Too early") -> Too early | W68: =IF(V68="Too early","Too early",V68/U68) -> Too early | X68: 1922 | Y68: 13333 | Z68: =IF(X68>0,X68/Y68,"") -> 0.1441536 | AA68: =IF($V68="Too early",V68,V68*AG68/Y68) -> Too early | AB68: 562 | AC68: 36187.1 | AD68: 33334 | AE68: =IF(AC68>0,AC68/AD68,"") -> 1.0855913 | AF68: 1590 | AG68: =X68/S68 -> 43.681818 | AK68: 38063.1 | AL68: =L68-AK68 -> 46
A69: 24 | B69: =A69-$G$4 -> 19 | C69: 46062 | D69: 26 Chris Thile | G69: 46065.792 | H69: Specials | I69: 0.85 | J69: =K69/AF69 -> 0.21383648 | K69: =S69+AB69 -> 340 | L69: =X69+AC69 -> 30162 | M69: =Y69+AD69 -> 128900 | N69: =L69-M69 -> -98738 | O69: =IF(P69="Too early",P69,P69/AF69) -> Too early | P69: =IF(V69="Too early",V69,V69+AB69) -> Too early | Q69: =IF(V69="Too early",V69,AC69+V69*AG69) -> Too early | R69: =IF(V69="Too early",V69,Q69-M69) -> Too early | S69: 340 | T69: =AF69-AB69 -> 1590 | U69: =(AF69-AB69)*I69 -> 1351.5 | V69: =IF(B69<11,MIN((S69/VLOOKUP(B69,'Sales Pacing'!$A$23:$E$36,2)),T69),"Too early") -> Too early | W69: =IF(V69="Too early","Too early",V69/U69) -> Too early | X69: 30162 | Y69: 128900 | Z69: =IF(X69>0,X69/Y69,"") -> 0.23399535 | AA69: =IF($V69="Too early",V69,V69*AG69/Y69) -> Too early | AE69: =IF(AC69>0,AC69/AD69,"") | AF69: 1590 | AG69: =X69/S69 -> 88.711765 | AK69: 27005 | AL69: =L69-AK69 -> 3157
A70: 24 | B70: =A70-$G$4 -> 19 | C70: 46062 | D70: 26 PS3 She's Got Soul | G70: 46066.833 | H70: Pops | I70: 0.85 | J70: =K70/AF70 -> 0.49622642 | K70: =S70+AB70 -> 789 | L70: =X70+AC70 -> 56081.1 | M70: =Y70+AD70 -> 94666 | N70: =L70-M70 -> -38584.9 | O70: =IF(P70="Too early",P70,P70/AF70) -> Too early | P70: =IF(V70="Too early",V70,V70+AB70) -> Too early | Q70: =IF(V70="Too early",V70,AC70+V70*AG70) -> Too early | R70: =IF(V70="Too early",V70,Q70-M70) -> Too early | S70: 66 | T70: =AF70-AB70 -> 867 | U70: =(AF70-AB70)*I70 -> 736.95 | V70: =IF(B70<11,MIN((S70/VLOOKUP(B70,'Sales Pacing'!$A$23:$E$36,2)),T70),"Too early") -> Too early | W70: =IF(V70="Too early","Too early",V70/U70) -> Too early | X70: 4067 | Y70: 53333 | Z70: =IF(X70>0,X70/Y70,"") -> 0.076256727 | AA70: =IF($V70="Too early",V70,V70*AG70/Y70) -> Too early | AB70: 723 | AC70: 52014.1 | AD70: 41333 | AE70: =IF(AC70>0,AC70/AD70,"") -> 1.2584158 | AF70: 1590 | AG70: =X70/S70 -> 61.621212 | AK70: 55909.1 | AL70: =L70-AK70 -> 172
A71: 24 | B71: =A71-$G$4 -> 19 | C71: 46062 | D71: 26 PS3 She's Got Soul | G71: 46067.833 | H71: Pops | I71: 0.85 | J71: =K71/AF71 -> 0.44591195 | K71: =S71+AB71 -> 709 | L71: =X71+AC71 -> 50062.8 | M71: =Y71+AD71 -> 94667 | N71: =L71-M71 -> -44604.2 | O71: =IF(P71="Too early",P71,P71/AF71) -> Too early | P71: =IF(V71="Too early",V71,V71+AB71) -> Too early | Q71: =IF(V71="Too early",V71,AC71+V71*AG71) -> Too early | R71: =IF(V71="Too early",V71,Q71-M71) -> Too early | S71: 46 | T71: =AF71-AB71 -> 927 | U71: =(AF71-AB71)*I71 -> 787.95 | V71: =IF(B71<11,MIN((S71/VLOOKUP(B71,'Sales Pacing'!$A$23:$E$36,2)),T71),"Too early") -> Too early | W71: =IF(V71="Too early","Too early",V71/U71) -> Too early | X71: 2151 | Y71: 53333 | Z71: =IF(X71>0,X71/Y71,"") -> 0.040331502 | AA71: =IF($V71="Too early",V71,V71*AG71/Y71) -> Too early | AB71: 663 | AC71: 47911.8 | AD71: 41334 | AE71: =IF(AC71>0,AC71/AD71,"") -> 1.1591378 | AF71: 1590 | AG71: =X71/S71 -> 46.76087 | AK71: 50570.8 | AL71: =L71-AK71 -> -508
A72: 24 | B72: =A72-$G$4 -> 19 | C72: 46062 | D72: 26 PS3 She's Got Soul | G72: 46068.583 | H72: Pops | I72: 0.85 | J72: =K72/AF72 -> 0.28176101 | K72: =S72+AB72 -> 448 | L72: =X72+AC72 -> 30213.3 | M72: =Y72+AD72 -> 94666 | N72: =L72-M72 -> -64452.7 | O72: =IF(P72="Too early",P72,P72/AF72) -> Too early | P72: =IF(V72="Too early",V72,V72+AB72) -> Too early | Q72: =IF(V72="Too early",V72,AC72+V72*AG72) -> Too early | R72: =IF(V72="Too early",V72,Q72-M72) -> Too early | S72: 63 | T72: =AF72-AB72 -> 1205 | U72: =(AF72-AB72)*I72 -> 1024.25 | V72: =IF(B72<11,MIN((S72/VLOOKUP(B72,'Sales Pacing'!$A$23:$E$36,2)),T72),"Too early") -> Too early | W72: =IF(V72="Too early","Too early",V72/U72) -> Too early | X72: 3982 | Y72: 53333 | Z72: =IF(X72>0,X72/Y72,"") -> 0.074662967 | AA72: =IF($V72="Too early",V72,V72*AG72/Y72) -> Too early | AB72: 385 | AC72: 26231.3 | AD72: 41333 | AE72: =IF(AC72>0,AC72/AD72,"") -> 0.63463334 | AF72: 1590 | AG72: =X72/S72 -> 63.206349 | AK72: 29655.3 | AL72: =L72-AK72 -> 558
A73: 25 | B73: =A73-$G$4 -> 20 | C73: 46069 | D73: 26 Harry Potter 2: Chamber | G73: 46072.792 | H73: Specials/Film | I73: 0.85 | J73: =K73/AF73 -> 0.10291859 | K73: =S73+AB73 -> 134 | L73: =X73+AC73 -> 9551.5 | M73: =Y73+AD73 -> 111250 | N73: =L73-M73 -> -101698.5 | O73: =IF(P73="Too early",P73,P73/AF73) -> Too early | P73: =IF(V73="Too early",V73,V73+AB73) -> Too early | Q73: =IF(V73="Too early",V73,AC73+V73*AG73) -> Too early | R73: =IF(V73="Too early",V73,Q73-M73) -> Too early | S73: 134 | T73: =AF73-AB73 -> 1302 | U73: =(AF73-AB73)*I73 -> 1106.7 | V73: =IF(B73<11,MIN((S73/VLOOKUP(B73,'Sales Pacing'!$A$23:$E$36,2)),T73),"Too early") -> Too early | W73: =IF(V73="Too early","Too early",V73/U73) -> Too early | X73: 9551.5 | Y73: 111250 | Z73: =IF(X73>0,X73/Y73,"") -> 0.08585618 | AA73: =IF($V73="Too early",V73,V73*AG73/Y73) -> Too early | AE73: =IF(AC73>0,AC73/AD73,"") | AF73: 1302 | AG73: =X73/S73 -> 71.279851 | AK73: 9361.5 | AL73: =L73-AK73 -> 190
A74: 25 | B74: =A74-$G$4 -> 20 | C74: 46069 | D74: 26 Harry Potter 2: Chamber | G74: 46073.792 | H74: Specials/Film | I74: 0.85 | J74: =K74/AF74 -> 0.18817204 | K74: =S74+AB74 -> 245 | L74: =X74+AC74 -> 17743 | M74: =Y74+AD74 -> 111250 | N74: =L74-M74 -> -93507 | O74: =IF(P74="Too early",P74,P74/AF74) -> Too early | P74: =IF(V74="Too early",V74,V74+AB74) -> Too early | Q74: =IF(V74="Too early",V74,AC74+V74*AG74) -> Too early | R74: =IF(V74="Too early",V74,Q74-M74) -> Too early | S74: 245 | T74: =AF74-AB74 -> 1302 | U74: =(AF74-AB74)*I74 -> 1106.7 | V74: =IF(B74<11,MIN((S74/VLOOKUP(B74,'Sales Pacing'!$A$23:$E$36,2)),T74),"Too early") -> Too early | W74: =IF(V74="Too early","Too early",V74/U74) -> Too early | X74: 17743 | Y74: 111250 | Z74: =IF(X74>0,X74/Y74,"") -> 0.15948764 | AA74: =IF($V74="Too early",V74,V74*AG74/Y74) -> Too early | AE74: =IF(AC74>0,AC74/AD74,"") | AF74: 1302 | AG74: =X74/S74 -> 72.420408 | AK74: 17663 | AL74: =L74-AK74 -> 80
A75: 25 | B75: =A75-$G$4 -> 20 | C75: 46069 | D75: 26 Harry Potter 2: Chamber | G75: 46074.792 | H75: Specials/Film | I75: 0.85 | J75: =K75/AF75 -> 0.34101382 | K75: =S75+AB75 -> 444 | L75: =X75+AC75 -> 33393 | M75: =Y75+AD75 -> 111250 | N75: =L75-M75 -> -77857 | O75: =IF(P75="Too early",P75,P75/AF75) -> Too early | P75: =IF(V75="Too early",V75,V75+AB75) -> Too early | Q75: =IF(V75="Too early",V75,AC75+V75*AG75) -> Too early | R75: =IF(V75="Too early",V75,Q75-M75) -> Too early | S75: 444 | T75: =AF75-AB75 -> 1302 | U75: =(AF75-AB75)*I75 -> 1106.7 | V75: =IF(B75<11,MIN((S75/VLOOKUP(B75,'Sales Pacing'!$A$23:$E$36,2)),T75),"Too early") -> Too early | W75: =IF(V75="Too early","Too early",V75/U75) -> Too early | X75: 33393 | Y75: 111250 | Z75: =IF(X75>0,X75/Y75,"") -> 0.3001618 | AA75: =IF($V75="Too early",V75,V75*AG75/Y75) -> Too early | AE75: =IF(AC75>0,AC75/AD75,"") | AF75: 1302 | AG75: =X75/S75 -> 75.209459 | AK75: 31515 | AL75: =L75-AK75 -> 1878
A76: 25 | B76: =A76-$G$4 -> 20 | C76: 46069 | D76: 26 Harry Potter 2: Chamber | G76: 46075.583 | H76: Specials/Film | I76: 0.85 | J76: =K76/AF76 -> 0.38786482 | K76: =S76+AB76 -> 505 | L76: =X76+AC76 -> 34032.5 | M76: =Y76+AD76 -> 111250 | N76: =L76-M76 -> -77217.5 | O76: =IF(P76="Too early",P76,P76/AF76) -> Too early | P76: =IF(V76="Too early",V76,V76+AB76) -> Too early | Q76: =IF(V76="Too early",V76,AC76+V76*AG76) -> Too early | R76: =IF(V76="Too early",V76,Q76-M76) -> Too early | S76: 505 | T76: =AF76-AB76 -> 1302 | U76: =(AF76-AB76)*I76 -> 1106.7 | V76: =IF(B76<11,MIN((S76/VLOOKUP(B76,'Sales Pacing'!$A$23:$E$36,2)),T76),"Too early") -> Too early | W76: =IF(V76="Too early","Too early",V76/U76) -> Too early | X76: 34032.5 | Y76: 111250 | Z76: =IF(X76>0,X76/Y76,"") -> 0.30591011 | AA76: =IF($V76="Too early",V76,V76*AG76/Y76) -> Too early | AE76: =IF(AC76>0,AC76/AD76,"") | AF76: 1302 | AG76: =X76/S76 -> 67.391089 | AK76: 33792.5 | AL76: =L76-AK76 -> 240
A77: 26 | B77: =A77-$G$4 -> 21 | C77: 46076 | D77: 26 FS3 Philharmonia Fantastique | G77: 46082.583 | H77: Family | I77: 0.5 | J77: =K77/AF77 -> 0.27419355 | K77: =S77+AB77 -> 357 | L77: =X77+AC77 -> 8297 | M77: =Y77+AD77 -> 19500 | N77: =L77-M77 -> -11203 | O77: =IF(P77="Too early",P77,P77/AF77) -> Too early | P77: =IF(V77="Too early",V77,V77+AB77) -> Too early | Q77: =IF(V77="Too early",V77,AC77+V77*AG77) -> Too early | R77: =IF(V77="Too early",V77,Q77-M77) -> Too early | S77: 50 | T77: =AF77-AB77 -> 995 | U77: =(AF77-AB77)*I77 -> 497.5 | V77: =IF(B77<11,MIN((S77/VLOOKUP(B77,'Sales Pacing'!$A$23:$E$36,2)),T77),"Too early") -> Too early | W77: =IF(V77="Too early","Too early",V77/U77) -> Too early | X77: 1461 | Y77: 10000 | Z77: =IF(X77>0,X77/Y77,"") -> 0.1461 | AA77: =IF($V77="Too early",V77,V77*AG77/Y77) -> Too early | AB77: 307 | AC77: 6836 | AD77: 9500 | AE77: =IF(AC77>0,AC77/AD77,"") -> 0.71957895 | AF77: 1302 | AG77: =X77/S77 -> 29.22 | AK77: 8100 | AL77: =L77-AK77 -> 197
A78: 27 | B78: =A78-$G$4 -> 22 | C78: 46083 | D78: OPEN | J78: =K78/AF78 -> #DIV/0! | K78: =S78+AB78 -> 0 | L78: =X78+AC78 -> 0 | M78: =Y78+AD78 -> 0 | P78: =IF(V78="Too early",V78,V78+AB78) -> Too early | Q78: =IF(V78="Too early",V78,AC78+V78*AG78) -> Too early | R78: =IF(V78="Too early",V78,Q78-M78) -> Too early | T78: =AF78-AB78 -> 0 | U78: =(AF78-AB78)*I78 -> 0 | V78: =IF(B78<11,MIN((S78/VLOOKUP(B78,'Sales Pacing'!$A$23:$E$36,2)),T78),"Too early") -> Too early | Z78: =IF(X78>0,X78/Y78,"") | AE78: N/A | AG78: =X78/S78 -> #DIV/0! | AK78: 0
A79: 28 | B79: =A79-$G$4 -> 23 | C79: 46090 | D79: 26 CS08 Saint-Saëns & Strauss | G79: 46094.833 | H79: Classical | I79: 0.85 | J79: =K79/AF79 -> 0.39371069 | K79: =S79+AB79 -> 626 | L79: =X79+AC79 -> 41199 | M79: =Y79+AD79 -> 54999 | N79: =L79-M79 -> -13800 | O79: =IF(P79="Too early",P79,P79/AF79) -> Too early | P79: =IF(V79="Too early",V79,V79+AB79) -> Too early | Q79: =IF(V79="Too early",V79,AC79+V79*AG79) -> Too early | R79: =IF(V79="Too early",V79,Q79-M79) -> Too early | S79: 53 | T79: =AF79-AB79 -> 1017 | U79: =(AF79-AB79)*I79 -> 864.45 | V79: =IF(B79<11,MIN((S79/VLOOKUP(B79,'Sales Pacing'!$A$23:$E$36,2)),T79),"Too early") -> Too early | W79: =IF(V79="Too early","Too early",V79/U79) -> Too early | X79: 2862 | Y79: 18333 | Z79: =IF(X79>0,X79/Y79,"") -> 0.15611193 | AA79: =IF($V79="Too early",V79,V79*AG79/Y79) -> Too early | AB79: 573 | AC79: 38337 | AD79: 36666 | AE79: =IF(AC79>0,AC79/AD79,"") -> 1.0455736 | AF79: 1590 | AG79: =X79/S79 -> 54 | AK79: 40846 | AL79: =L79-AK79 -> 353
A80: 28 | B80: =A80-$G$4 -> 23 | C80: 46090 | D80: 26 CS08 Saint-Saëns & Strauss | G80: 46095.833 | H80: Classical | I80: 0.85 | J80: =K80/AF80 -> 0.3918239 | K80: =S80+AB80 -> 623 | L80: =X80+AC80 -> 39776.2 | M80: =Y80+AD80 -> 55000 | N80: =L80-M80 -> -15223.8 | O80: =IF(P80="Too early",P80,P80/AF80) -> Too early | P80: =IF(V80="Too early",V80,V80+AB80) -> Too early | Q80: =IF(V80="Too early",V80,AC80+V80*AG80) -> Too early | R80: =IF(V80="Too early",V80,Q80-M80) -> Too early | S80: 61 | T80: =AF80-AB80 -> 1028 | U80: =(AF80-AB80)*I80 -> 873.8 | V80: =IF(B80<11,MIN((S80/VLOOKUP(B80,'Sales Pacing'!$A$23:$E$36,2)),T80),"Too early") -> Too early | W80: =IF(V80="Too early","Too early",V80/U80) -> Too early | X80: 3360 | Y80: 18333 | Z80: =IF(X80>0,X80/Y80,"") -> 0.18327606 | AA80: =IF($V80="Too early",V80,V80*AG80/Y80) -> Too early | AB80: 562 | AC80: 36416.2 | AD80: 36667 | AE80: =IF(AC80>0,AC80/AD80,"") -> 0.99316006 | AF80: 1590 | AG80: =X80/S80 -> 55.081967 | AK80: 39753.2 | AL80: =L80-AK80 -> 23
A81: 28 | B81: =A81-$G$4 -> 23 | C81: 46090 | D81: 26 CS08 Saint-Saëns & Strauss | G81: 46096.583 | H81: Classical | I81: 0.85 | J81: =K81/AF81 -> 0.4081761 | K81: =S81+AB81 -> 649 | L81: =X81+AC81 -> 41376.1 | M81: =Y81+AD81 -> 55000 | N81: =L81-M81 -> -13623.9 | O81: =IF(P81="Too early",P81,P81/AF81) -> Too early | P81: =IF(V81="Too early",V81,V81+AB81) -> Too early | Q81: =IF(V81="Too early",V81,AC81+V81*AG81) -> Too early | R81: =IF(V81="Too early",V81,Q81-M81) -> Too early | S81: 76 | T81: =AF81-AB81 -> 1017 | U81: =(AF81-AB81)*I81 -> 864.45 | V81: =IF(B81<11,MIN((S81/VLOOKUP(B81,'Sales Pacing'!$A$23:$E$36,2)),T81),"Too early") -> Too early | W81: =IF(V81="Too early","Too early",V81/U81) -> Too early | X81: 4624 | Y81: 18333 | Z81: =IF(X81>0,X81/Y81,"") -> 0.25222277 | AA81: =IF($V81="Too early",V81,V81*AG81/Y81) -> Too early | AB81: 573 | AC81: 36752.1 | AD81: 36667 | AE81: =IF(AC81>0,AC81/AD81,"") -> 1.0023209 | AF81: 1590 | AG81: =X81/S81 -> 60.842105 | AK81: 41030.1 | AL81: =L81-AK81 -> 346
A82: 29 | B82: =A82-$G$4 -> 24 | C82: 46097 | D82: OPEN | J82: =K82/AF82 -> #DIV/0! | K82: =S82+AB82 -> 0 | L82: =X82+AC82 -> 0 | M82: =Y82+AD82 -> 0 | P82: =IF(V82="Too early",V82,V82+AB82) -> Too early | Q82: =IF(V82="Too early",V82,AC82+V82*AG82) -> Too early | R82: =IF(V82="Too early",V82,Q82-M82) -> Too early | T82: =AF82-AB82 -> 0 | U82: =(AF82-AB82)*I82 -> 0 | V82: =IF(B82<11,MIN((S82/VLOOKUP(B82,'Sales Pacing'!$A$23:$E$36,2)),T82),"Too early") -> Too early | Z82: =IF(X82>0,X82/Y82,"") | AE82: N/A | AG82: =X82/S82 -> #DIV/0! | AK82: 0
A83: 30 | B83: =A83-$G$4 -> 25 | C83: 46104 | D83: Final Symphony | G83: 46106 | H83: Specials | I83: 0.85 | J83: =K83/AF83 -> 0.05408805 | K83: =S83+AB83 -> 86 | L83: =X83+AC83 -> 5437 | M83: =Y83+AD83 -> 84109 | N83: =L83-M83 -> -78672 | O83: =IF(P83="Too early",P83,P83/AF83) -> Too early | P83: =IF(V83="Too early",V83,V83+AB83) -> Too early | Q83: =IF(V83="Too early",V83,AC83+V83*AG83) -> Too early | R83: =IF(V83="Too early",V83,Q83-M83) -> Too early | S83: 86 | T83: =AF83-AB83 -> 1590 | U83: =(AF83-AB83)*I83 -> 1351.5 | V83: =IF(B83<11,MIN((S83/VLOOKUP(B83,'Sales Pacing'!$A$23:$E$36,2)),T83),"Too early") -> Too early | W83: =IF(V83="Too early","Too early",V83/U83) -> Too early | X83: 5437 | Y83: 84109 | Z83: =IF(X83>0,X83/Y83,"") -> 0.064642309 | AA83: =IF($V83="Too early",V83,V83*AG83/Y83) -> Too early | AF83: 1590 | AG83: =X83/S83 -> 63.22093 | AK83: 5437 | AL83: =L83-AK83 -> 0
A84: 30 | B84: =A84-$G$4 -> 25 | C84: 46104 | D84: Final Symphony | G84: 46107 | H84: Specials | I84: 0.85 | J84: =K84/AF84 -> 0.054716981 | K84: =S84+AB84 -> 87 | L84: =X84+AC84 -> 5027.5 | M84: =Y84+AD84 -> 84109 | N84: =L84-M84 -> -79081.5 | O84: =IF(P84="Too early",P84,P84/AF84) -> Too early | P84: =IF(V84="Too early",V84,V84+AB84) -> Too early | Q84: =IF(V84="Too early",V84,AC84+V84*AG84) -> Too early | R84: =IF(V84="Too early",V84,Q84-M84) -> Too early | S84: 87 | T84: =AF84-AB84 -> 1590 | U84: =(AF84-AB84)*I84 -> 1351.5 | V84: =IF(B84<11,MIN((S84/VLOOKUP(B84,'Sales Pacing'!$A$23:$E$36,2)),T84),"Too early") -> Too early | W84: =IF(V84="Too early","Too early",V84/U84) -> Too early | X84: 5027.5 | Y84: 84109 | Z84: =IF(X84>0,X84/Y84,"") -> 0.059773627 | AA84: =IF($V84="Too early",V84,V84*AG84/Y84) -> Too early | AF84: 1590 | AG84: =X84/S84 -> 57.787356 | AK84: 5027.5 | AL84: =L84-AK84 -> 0
A85: 30 | B85: =A85-$G$4 -> 25 | C85: 46104 | D85: 26 PS4 Billy Joel & Elton John | G85: 46108.833 | H85: Pops | I85: 0.85 | J85: =K85/AF85 -> 0.56792453 | K85: =S85+AB85 -> 903 | L85: =X85+AC85 -> 64363.1 | M85: =Y85+AD85 -> 94666 | N85: =L85-M85 -> -30302.9 | O85: =IF(P85="Too early",P85,P85/AF85) -> Too early | P85: =IF(V85="Too early",V85,V85+AB85) -> Too early | Q85: =IF(V85="Too early",V85,AC85+V85*AG85) -> Too early | R85: =IF(V85="Too early",V85,Q85-M85) -> Too early | S85: 164 | T85: =AF85-AB85 -> 851 | U85: =(AF85-AB85)*I85 -> 723.35 | V85: =IF(B85<11,MIN((S85/VLOOKUP(B85,'Sales Pacing'!$A$23:$E$36,2)),T85),"Too early") -> Too early | W85: =IF(V85="Too early","Too early",V85/U85) -> Too early | X85: 11069 | Y85: 53333 | Z85: =IF(X85>0,X85/Y85,"") -> 0.20754505 | AA85: =IF($V85="Too early",V85,V85*AG85/Y85) -> Too early | AB85: 739 | AC85: 53294.1 | AD85: 41333 | AE85: =IF(AC85>0,AC85/AD85,"") -> 1.2893838 | AF85: 1590 | AG85: =X85/S85 -> 67.493902 | AK85: 64129.1 | AL85: =L85-AK85 -> 234
A86: 30 | B86: =A86-$G$4 -> 25 | C86: 46104 | D86: 26 PS4 Billy Joel & Elton John | G86: 46109.833 | H86: Pops | I86: 0.85 | J86: =K86/AF86 -> 0.53773585 | K86: =S86+AB86 -> 855 | L86: =X86+AC86 -> 61452.8 | M86: =Y86+AD86 -> 94667 | N86: =L86-M86 -> -33214.2 | O86: =IF(P86="Too early",P86,P86/AF86) -> Too early | P86: =IF(V86="Too early",V86,V86+AB86) -> Too early | Q86: =IF(V86="Too early",V86,AC86+V86*AG86) -> Too early | R86: =IF(V86="Too early",V86,Q86-M86) -> Too early | S86: 185 | T86: =AF86-AB86 -> 920 | U86: =(AF86-AB86)*I86 -> 782 | V86: =IF(B86<11,MIN((S86/VLOOKUP(B86,'Sales Pacing'!$A$23:$E$36,2)),T86),"Too early") -> Too early | W86: =IF(V86="Too early","Too early",V86/U86) -> Too early | X86: 13007 | Y86: 53333 | Z86: =IF(X86>0,X86/Y86,"") -> 0.24388277 | AA86: =IF($V86="Too early",V86,V86*AG86/Y86) -> Too early | AB86: 670 | AC86: 48445.8 | AD86: 41334 | AE86: =IF(AC86>0,AC86/AD86,"") -> 1.1720569 | AF86: 1590 | AG86: =X86/S86 -> 70.308108 | AK86: 60900.8 | AL86: =L86-AK86 -> 552
A87: 30 | B87: =A87-$G$4 -> 25 | C87: 46104 | D87: 26 PS4 Billy Joel & Elton John | G87: 46110.583 | H87: Pops | I87: 0.85 | J87: =K87/AF87 -> 0.38930818 | K87: =S87+AB87 -> 619 | L87: =X87+AC87 -> 43141.6 | M87: =Y87+AD87 -> 94666 | N87: =L87-M87 -> -51524.4 | O87: =IF(P87="Too early",P87,P87/AF87) -> Too early | P87: =IF(V87="Too early",V87,V87+AB87) -> Too early | Q87: =IF(V87="Too early",V87,AC87+V87*AG87) -> Too early | R87: =IF(V87="Too early",V87,Q87-M87) -> Too early | S87: 230 | T87: =AF87-AB87 -> 1201 | U87: =(AF87-AB87)*I87 -> 1020.85 | V87: =IF(B87<11,MIN((S87/VLOOKUP(B87,'Sales Pacing'!$A$23:$E$36,2)),T87),"Too early") -> Too early | W87: =IF(V87="Too early","Too early",V87/U87) -> Too early | X87: 16690 | Y87: 53333 | Z87: =IF(X87>0,X87/Y87,"") -> 0.31293946 | AA87: =IF($V87="Too early",V87,V87*AG87/Y87) -> Too early | AB87: 389 | AC87: 26451.6 | AD87: 41333 | AE87: =IF(AC87>0,AC87/AD87,"") -> 0.63996323 | AF87: 1590 | AG87: =X87/S87 -> 72.565217 | AK87: 41992.6 | AL87: =L87-AK87 -> 1149
A88: 31 | B88: =A88-$G$4 -> 26 | C88: 46111 | D88: OPEN | J88: =K88/AF88 -> #DIV/0! | K88: =S88+AB88 -> 0 | L88: =X88+AC88 -> 0 | M88: =Y88+AD88 -> 0 | P88: =IF(V88="Too early",V88,V88+AB88) -> Too early | Q88: =IF(V88="Too early",V88,AC88+V88*AG88) -> Too early | R88: =IF(V88="Too early",V88,Q88-M88) -> Too early | T88: =AF88-AB88 -> 0 | U88: =(AF88-AB88)*I88 -> 0 | V88: =IF(B88<11,MIN((S88/VLOOKUP(B88,'Sales Pacing'!$A$23:$E$36,2)),T88),"Too early") -> Too early | Z88: =IF(X88>0,X88/Y88,"") | AE88: N/A | AG88: =X88/S88 -> #DIV/0! | AK88: 0
A89: 32 | B89: =A89-$G$4 -> 27 | C89: 46118 | D89: 26 CS09 Midsummer Night's Dream | G89: 46122.833 | H89: Classical | I89: 0.5 | J89: =K89/AF89 -> 0.29309142 | K89: =S89+AB89 -> 420 | L89: =X89+AC89 -> 28125 | M89: =Y89+AD89 -> 52000 | N89: =L89-M89 -> -23875 | O89: =IF(P89="Too early",P89,P89/AF89) -> Too early | P89: =IF(V89="Too early",V89,V89+AB89) -> Too early | Q89: =IF(V89="Too early",V89,AC89+V89*AG89) -> Too early | R89: =IF(V89="Too early",V89,Q89-M89) -> Too early | S89: 52 | T89: =AF89-AB89 -> 1065 | U89: =(AF89-AB89)*I89 -> 532.5 | V89: =IF(B89<11,MIN((S89/VLOOKUP(B89,'Sales Pacing'!$A$23:$E$36,2)),T89),"Too early") -> Too early | W89: =IF(V89="Too early","Too early",V89/U89) -> Too early | X89: 2411 | Y89: 22000 | Z89: =IF(X89>0,X89/Y89,"") -> 0.10959091 | AA89: =IF($V89="Too early",V89,V89*AG89/Y89) -> Too early | AB89: 368 | AC89: 25714 | AD89: 30000 | AE89: =IF(AC89>0,AC89/AD89,"") -> 0.85713333 | AF89: 1433 | AG89: =X89/S89 -> 46.365385 | AK89: 27729 | AL89: =L89-AK89 -> 396
A90: 32 | B90: =A90-$G$4 -> 27 | C90: 46118 | D90: 26 CS09 Midsummer Night's Dream | G90: 46123.833 | H90: Classical | I90: 0.85 | J90: =K90/AF90 -> 0.4619679 | K90: =S90+AB90 -> 662 | L90: =X90+AC90 -> 41374 | M90: =Y90+AD90 -> 74000 | N90: =L90-M90 -> -32626 | O90: =IF(P90="Too early",P90,P90/AF90) -> Too early | P90: =IF(V90="Too early",V90,V90+AB90) -> Too early | Q90: =IF(V90="Too early",V90,AC90+V90*AG90) -> Too early | R90: =IF(V90="Too early",V90,Q90-M90) -> Too early | S90: 97 | T90: =AF90-AB90 -> 868 | U90: =(AF90-AB90)*I90 -> 737.8 | V90: =IF(B90<11,MIN((S90/VLOOKUP(B90,'Sales Pacing'!$A$23:$E$36,2)),T90),"Too early") -> Too early | W90: =IF(V90="Too early","Too early",V90/U90) -> Too early | X90: 5001 | Y90: 24000 | Z90: =IF(X90>0,X90/Y90,"") -> 0.208375 | AA90: =IF($V90="Too early",V90,V90*AG90/Y90) -> Too early | AB90: 565 | AC90: 36373 | AD90: 50000 | AE90: =IF(AC90>0,AC90/AD90,"") -> 0.72746 | AF90: 1433 | AG90: =X90/S90 -> 51.556701 | AK90: 41302 | AL90: =L90-AK90 -> 72
A91: 32 | B91: =A91-$G$4 -> 27 | C91: 46118 | D91: 26 CS09 Midsummer Night's Dream | G91: 46124.583 | H91: Classical | I91: 0.85 | J91: =K91/AF91 -> 0.44801117 | K91: =S91+AB91 -> 642 | L91: =X91+AC91 -> 39965.1 | M91: =Y91+AD91 -> 74000 | N91: =L91-M91 -> -34034.9 | O91: =IF(P91="Too early",P91,P91/AF91) -> Too early | P91: =IF(V91="Too early",V91,V91+AB91) -> Too early | Q91: =IF(V91="Too early",V91,AC91+V91*AG91) -> Too early | R91: =IF(V91="Too early",V91,Q91-M91) -> Too early | S91: 70 | T91: =AF91-AB91 -> 861 | U91: =(AF91-AB91)*I91 -> 731.85 | V91: =IF(B91<11,MIN((S91/VLOOKUP(B91,'Sales Pacing'!$A$23:$E$36,2)),T91),"Too early") -> Too early | W91: =IF(V91="Too early","Too early",V91/U91) -> Too early | X91: 3060 | Y91: 24000 | Z91: =IF(X91>0,X91/Y91,"") -> 0.1275 | AA91: =IF($V91="Too early",V91,V91*AG91/Y91) -> Too early | AB91: 572 | AC91: 36905.1 | AD91: 50000 | AE91: =IF(AC91>0,AC91/AD91,"") -> 0.738102 | AF91: 1433 | AG91: =X91/S91 -> 43.714286 | AK91: 39738.1 | AL91: =L91-AK91 -> 227
A92: 33 | B92: =A92-$G$4 -> 28 | C92: 46125 | D92: 26 CS10 Farrenc/Dvorák/Schuman | G92: 46129.833 | H92: Classical | I92: 0.85 | J92: =K92/AF92 -> 0.38301887 | K92: =S92+AB92 -> 609 | L92: =X92+AC92 -> 39973 | M92: =Y92+AD92 -> 46666 | N92: =L92-M92 -> -6693 | O92: =IF(P92="Too early",P92,P92/AF92) -> Too early | P92: =IF(V92="Too early",V92,V92+AB92) -> Too early | Q92: =IF(V92="Too early",V92,AC92+V92*AG92) -> Too early | R92: =IF(V92="Too early",V92,Q92-M92) -> Too early | S92: 31 | T92: =AF92-AB92 -> 1012 | U92: =(AF92-AB92)*I92 -> 860.2 | V92: =IF(B92<11,MIN((S92/VLOOKUP(B92,'Sales Pacing'!$A$23:$E$36,2)),T92),"Too early") -> Too early | W92: =IF(V92="Too early","Too early",V92/U92) -> Too early | X92: 1099 | Y92: 13333 | Z92: =IF(X92>0,X92/Y92,"") -> 0.082427061 | AA92: =IF($V92="Too early",V92,V92*AG92/Y92) -> Too early | AB92: 578 | AC92: 38874 | AD92: 33333 | AE92: =IF(AC92>0,AC92/AD92,"") -> 1.1662317 | AF92: 1590 | AG92: =X92/S92 -> 35.451613 | AK92: 39793 | AL92: =L92-AK92 -> 180
A93: 33 | B93: =A93-$G$4 -> 28 | C93: 46125 | D93: 26 CS10 Farrenc/Dvorák/Schuman | G93: 46130.833 | H93: Classical | I93: 0.85 | J93: =K93/AF93 -> 0.39245283 | K93: =S93+AB93 -> 624 | L93: =X93+AC93 -> 41660.9 | M93: =Y93+AD93 -> 46666 | N93: =L93-M93 -> -5005.1 | O93: =IF(P93="Too early",P93,P93/AF93) -> Too early | P93: =IF(V93="Too early",V93,V93+AB93) -> Too early | Q93: =IF(V93="Too early",V93,AC93+V93*AG93) -> Too early | R93: =IF(V93="Too early",V93,Q93-M93) -> Too early | S93: 32 | T93: =AF93-AB93 -> 998 | U93: =(AF93-AB93)*I93 -> 848.3 | V93: =IF(B93<11,MIN((S93/VLOOKUP(B93,'Sales Pacing'!$A$23:$E$36,2)),T93),"Too early") -> Too early | W93: =IF(V93="Too early","Too early",V93/U93) -> Too early | X93: 1399 | Y93: 13333 | Z93: =IF(X93>0,X93/Y93,"") -> 0.10492762 | AA93: =IF($V93="Too early",V93,V93*AG93/Y93) -> Too early | AB93: 592 | AC93: 40261.9 | AD93: 33333 | AE93: =IF(AC93>0,AC93/AD93,"") -> 1.2078691 | AF93: 1590 | AG93: =X93/S93 -> 43.71875 | AK93: 41723.9 | AL93: =L93-AK93 -> -63
A94: 33 | B94: =A94-$G$4 -> 28 | C94: 46125 | D94: 26 CS10 Farrenc/Dvorák/Schuman | G94: 46131.583 | H94: Classical | I94: 0.85 | J94: =K94/AF94 -> 0.41446541 | K94: =S94+AB94 -> 659 | L94: =X94+AC94 -> 41694.2 | M94: =Y94+AD94 -> 46667 | N94: =L94-M94 -> -4972.8 | O94: =IF(P94="Too early",P94,P94/AF94) -> Too early | P94: =IF(V94="Too early",V94,V94+AB94) -> Too early | Q94: =IF(V94="Too early",V94,AC94+V94*AG94) -> Too early | R94: =IF(V94="Too early",V94,Q94-M94) -> Too early | S94: 40 | T94: =AF94-AB94 -> 971 | U94: =(AF94-AB94)*I94 -> 825.35 | V94: =IF(B94<11,MIN((S94/VLOOKUP(B94,'Sales Pacing'!$A$23:$E$36,2)),T94),"Too early") -> Too early | W94: =IF(V94="Too early","Too early",V94/U94) -> Too early | X94: 1731 | Y94: 13333 | Z94: =IF(X94>0,X94/Y94,"") -> 0.12982825 | AA94: =IF($V94="Too early",V94,V94*AG94/Y94) -> Too early | AB94: 619 | AC94: 39963.2 | AD94: 33334 | AE94: =IF(AC94>0,AC94/AD94,"") -> 1.198872 | AF94: 1590 | AG94: =X94/S94 -> 43.275 | AK94: 41460.2 | AL94: =L94-AK94 -> 234
A95: 34 | B95: =A95-$G$4 -> 29 | C95: 46132 | D95: OPEN | J95: =K95/AF95 -> #DIV/0! | K95: =S95+AB95 -> 0 | L95: =X95+AC95 -> 0 | M95: =Y95+AD95 -> 0 | P95: =IF(V95="Too early",V95,V95+AB95) -> Too early | Q95: =IF(V95="Too early",V95,AC95+V95*AG95) -> Too early | R95: =IF(V95="Too early",V95,Q95-M95) -> Too early | T95: =AF95-AB95 -> 0 | U95: =(AF95-AB95)*I95 -> 0 | V95: =IF(B95<11,MIN((S95/VLOOKUP(B95,'Sales Pacing'!$A$23:$E$36,2)),T95),"Too early") -> Too early | Z95: =IF(X95>0,X95/Y95,"") | AE95: N/A | AG95: =X95/S95 -> #DIV/0! | AK95: 0
A96: 35 | B96: =A96-$G$4 -> 30 | C96: 46139 | D96: OPEN | J96: =K96/AF96 -> #DIV/0! | K96: =S96+AB96 -> 0 | L96: =X96+AC96 -> 0 | M96: =Y96+AD96 -> 0 | P96: =IF(V96="Too early",V96,V96+AB96) -> Too early | Q96: =IF(V96="Too early",V96,AC96+V96*AG96) -> Too early | R96: =IF(V96="Too early",V96,Q96-M96) -> Too early | T96: =AF96-AB96 -> 0 | U96: =(AF96-AB96)*I96 -> 0 | V96: =IF(B96<11,MIN((S96/VLOOKUP(B96,'Sales Pacing'!$A$23:$E$36,2)),T96),"Too early") -> Too early | Z96: =IF(X96>0,X96/Y96,"") | AE96: N/A | AG96: =X96/S96 -> #DIV/0! | AK96: 0
A97: 36 | B97: =A97-$G$4 -> 31 | C97: 46146 | D97: 26 CS11 Grieg's Piano Concerto | G97: 46150.833 | H97: Classical | I97: 0.5 | J97: =K97/AF97 -> 0.26666667 | K97: =S97+AB97 -> 424 | L97: =X97+AC97 -> 28112 | M97: =Y97+AD97 -> 45000 | N97: =L97-M97 -> -16888 | O97: =IF(P97="Too early",P97,P97/AF97) -> Too early | P97: =IF(V97="Too early",V97,V97+AB97) -> Too early | Q97: =IF(V97="Too early",V97,AC97+V97*AG97) -> Too early | R97: =IF(V97="Too early",V97,Q97-M97) -> Too early | S97: 50 | T97: =AF97-AB97 -> 1216 | U97: =(AF97-AB97)*I97 -> 608 | V97: =IF(B97<11,MIN((S97/VLOOKUP(B97,'Sales Pacing'!$A$23:$E$36,2)),T97),"Too early") -> Too early | W97: =IF(V97="Too early","Too early",V97/U97) -> Too early | X97: 2349 | Y97: 20000 | Z97: =IF(X97>0,X97/Y97,"") -> 0.11745 | AA97: =IF($V97="Too early",V97,V97*AG97/Y97) -> Too early | AB97: 374 | AC97: 25763 | AD97: 25000 | AE97: =IF(AC97>0,AC97/AD97,"") -> 1.03052 | AF97: 1590 | AG97: =X97/S97 -> 46.98 | AK97: 27937 | AL97: =L97-AK97 -> 175
A98: 36 | B98: =A98-$G$4 -> 31 | C98: 46146 | D98: 26 CS11 Grieg's Piano Concerto | G98: 46151.833 | H98: Classical | I98: 0.85 | J98: =K98/AF98 -> 0.43333333 | K98: =S98+AB98 -> 689 | L98: =X98+AC98 -> 45719.9 | M98: =Y98+AD98 -> 65000 | N98: =L98-M98 -> -19280.1 | O98: =IF(P98="Too early",P98,P98/AF98) -> Too early | P98: =IF(V98="Too early",V98,V98+AB98) -> Too early | Q98: =IF(V98="Too early",V98,AC98+V98*AG98) -> Too early | R98: =IF(V98="Too early",V98,Q98-M98) -> Too early | S98: 89 | T98: =AF98-AB98 -> 990 | U98: =(AF98-AB98)*I98 -> 841.5 | V98: =IF(B98<11,MIN((S98/VLOOKUP(B98,'Sales Pacing'!$A$23:$E$36,2)),T98),"Too early") -> Too early | W98: =IF(V98="Too early","Too early",V98/U98) -> Too early | X98: 5356 | Y98: 17500 | Z98: =IF(X98>0,X98/Y98,"") -> 0.30605714 | AA98: =IF($V98="Too early",V98,V98*AG98/Y98) -> Too early | AB98: 600 | AC98: 40363.9 | AD98: 47500 | AE98: =IF(AC98>0,AC98/AD98,"") -> 0.84976632 | AF98: 1590 | AG98: =X98/S98 -> 60.179775 | AK98: 45768.9 | AL98: =L98-AK98 -> -49
A99: 36 | B99: =A99-$G$4 -> 31 | C99: 46146 | D99: 26 CS11 Grieg's Piano Concerto | G99: 46152.583 | H99: Classical | I99: 0.85 | J99: =K99/AF99 -> 0.42767296 | K99: =S99+AB99 -> 680 | L99: =X99+AC99 -> 43281.2 | M99: =Y99+AD99 -> 65000 | N99: =L99-M99 -> -21718.8 | O99: =IF(P99="Too early",P99,P99/AF99) -> Too early | P99: =IF(V99="Too early",V99,V99+AB99) -> Too early | Q99: =IF(V99="Too early",V99,AC99+V99*AG99) -> Too early | R99: =IF(V99="Too early",V99,Q99-M99) -> Too early | S99: 69 | T99: =AF99-AB99 -> 979 | U99: =(AF99-AB99)*I99 -> 832.15 | V99: =IF(B99<11,MIN((S99/VLOOKUP(B99,'Sales Pacing'!$A$23:$E$36,2)),T99),"Too early") -> Too early | W99: =IF(V99="Too early","Too early",V99/U99) -> Too early | X99: 3734 | Y99: 17500 | Z99: =IF(X99>0,X99/Y99,"") -> 0.21337143 | AA99: =IF($V99="Too early",V99,V99*AG99/Y99) -> Too early | AB99: 611 | AC99: 39547.2 | AD99: 47500 | AE99: =IF(AC99>0,AC99/AD99,"") -> 0.83257263 | AF99: 1590 | AG99: =X99/S99 -> 54.115942 | AK99: 42812.2 | AL99: =L99-AK99 -> 469
A100: 37 | B100: =A100-$G$4 -> 32 | C100: 46153 | D100: 26 PS5 Dolly Parton's Threads | G100: 46157.833 | H100: Pops | I100: 0.85 | J100: =K100/AF100 -> 0.62135177 | K100: =S100+AB100 -> 809 | L100: =X100+AC100 -> 67940 | M100: =Y100+AD100 -> 103333 | N100: =L100-M100 -> -35393 | O100: =IF(P100="Too early",P100,P100/AF100) -> Too early | P100: =IF(V100="Too early",V100,V100+AB100) -> Too early | Q100: =IF(V100="Too early",V100,AC100+V100*AG100) -> Too early | R100: =IF(V100="Too early",V100,Q100-M100) -> Too early | S100: 71 | T100: =AF100-AB100 -> 564 | U100: =(AF100-AB100)*I100 -> 479.4 | V100: =IF(B100<11,MIN((S100/VLOOKUP(B100,'Sales Pacing'!$A$23:$E$36,2)),T100),"Too early") -> Too early | W100: =IF(V100="Too early","Too early",V100/U100) -> Too early | X100: 5507 | Y100: 60000 | Z100: =IF(X100>0,X100/Y100,"") -> 0.091783333 | AA100: =IF($V100="Too early",V100,V100*AG100/Y100) -> Too early | AB100: 738 | AC100: 62433 | AD100: 43333 | AE100: =IF(AC100>0,AC100/AD100,"") -> 1.4407726 | AF100: 1302 | AG100: =X100/S100 -> 77.56338 | AK100: 67716 | AL100: =L100-AK100 -> 224
...

Sheet PS1 Journey
B1: # weeks out
A2: Single Tickets | B2: 5 | C2: 4 | D2: 3 | E2: 2 | F2: 1 | G2: 0 | L2: Estimates Only | P2: Historical Data
A3: PS1 Journey | B3: 45880 | C3: 45887 | D3: 45894 | E3: 45901 | F3: 45908 | G3: 45915 | H3: # Single Tickets to sell out 100% | I3: Projected OCC% | K3: # Weeks Until Performance | L3: 10 | M3: 9 | N3: 8 | O3: 7 | P3: 6 | Q3: 5 | R3: 4 | S3: 3 | T3: 2 | U3: 1 | V3: 0
A4: 9/19/2025 Sales (Fri) | B4: 60 | C4: 160 | D4: 205 | E4: 262 | F4: 311 | G4: 390 | H4: ='Performances by Week'!AF10-'Performances by Week'!AB10 -> 975 | I4: ='Performances by Week'!O10 -> #N/A | K4: Classical | L4: 0.15 | M4: 0.18 | N4: 0.21 | O4: 0.24 | P4: 0.27 | Q4: 0.3 | R4: 0.33 | S4: 0.39 | T4: 0.46 | U4: 0.59 | V4: 1
A5: 9/20/2025 Sales (Sat) | B5: 63 | C5: 206 | D5: 250 | E5: 294 | F5: 360 | G5: 422 | H5: ='Performances by Week'!AF11-'Performances by Week'!AB11 -> 1076 | I5: ='Performances by Week'!O11 -> #N/A | K5: Pops | L5: 0.15 | M5: 0.18 | N5: 0.21 | O5: 0.24 | P5: 0.27 | Q5: 0.3 | R5: 0.33 | S5: 0.39 | T5: 0.46 | U5: 0.59 | V5: 1
A6: 9/21/2025 Sales (Sun) | B6: 57 | C6: 219 | D6: 296 | E6: 322 | F6: 444 | G6: 516 | H6: ='Performances by Week'!AF12-'Performances by Week'!AB12 -> 1246 | I6: ='Performances by Week'!O12 -> #N/A | K6: Specials | L6: 0.15 | M6: 0.18 | N6: 0.21 | O6: 0.24 | P6: 0.27 | Q6: 0.3 | R6: 0.33 | S6: 0.39 | T6: 0.46 | U6: 0.59 | V6: 1
A7: Pace for 85% OCC | B7: =$H$7*$H$10*Q5 -> 280.245 | C7: =$H$7*$H$10*R5 -> 308.2695 | D7: =$H$7*$H$10*S5 -> 364.3185 | E7: =$H$7*$H$10*T5 -> 429.709 | F7: =$H$7*$H$10*U5 -> 551.1485 | G7: =$H$7*$H$10*V5 -> 934.15 | H7: =AVERAGE(H4:H6) -> 1099 | K7: Other | L7: 0.15 | M7: 0.18 | N7: 0.21 | O7: 0.24 | P7: 0.27 | Q7: 0.3 | R7: 0.33 | S7: 0.39 | T7: 0.46 | U7: 0.59 | V7: 1
A8: Avg/Show vs Target Pace: | B8: =IF(B4>0,AVERAGE(B4:B6)-B7,"TBD") -> -220.245 | C8: =IF(C4>0,AVERAGE(C4:C6)-C7,"TBD") -> -113.2695 | D8: =IF(D4>0,AVERAGE(D4:D6)-D7,"TBD") -> -113.98517 | E8: =IF(E4>0,AVERAGE(E4:E6)-E7,"TBD") -> -137.04233 | F8: =IF(F4>0,AVERAGE(F4:F6)-F7,"TBD") -> -179.48183 | G8: =IF(G4>0,AVERAGE(G4:G6)-G7,"TBD") -> -491.48333
H9: OCC Target
H10: 0.85
I12: Final Sales: | J12: Sep 15-21 Sales | K12: % of Total
I13: 511 | J13: =I13-G4 -> 121 | K13: =J13/I13 -> 0.23679061
I14: 550 | J14: =I14-G5 -> 128 | K14: =J14/I14 -> 0.23272727
I15: 662 | J15: =I15-G6 -> 146 | K15: =J15/I15 -> 0.22054381

Sheet CS1 Appalachian
B1: # weeks out
A2: Single Tickets | B2: 8 | C2: 7 | D2: 6 | E2: 5 | F2: 4 | G2: 3 | H2: 2 | I2: 1 | J2: 0 | O2: Estimates Only | S2: Historical Data
A3: CS1 Appalachian | B3: 45880 | C3: 45887 | D3: 45894 | E3: 45901 | F3: 45908 | G3: 45915 | H3: 45922 | I3: 45929 | J3: 45936 | K3: # Single Tickets to sell out 100% | L3: Projected OCC% | N3: # Weeks Until Performance | O3: 10 | P3: 9 | Q3: 8 | R3: 7 | S3: 6 | T3: 5 | U3: 4 | V3: 3 | W3: 2 | X3: 1 | Y3: 0
A4: 10/10/2025 Sales (Fri) | B4: 60 | C4: 100 | D4: 106 | E4: 135 | F4: 193 | G4: 212 | H4: 238 | I4: 326 | K4: =1433-543 -> 890 | L4: ='Performances by Week'!O15 -> 0.74078323 | N4: Classical | O4: 0.15 | P4: 0.18 | Q4: 0.21 | R4: 0.24 | S4: 0.27 | T4: 0.3 | U4: 0.33 | V4: 0.39 | W4: 0.46 | X4: 0.59 | Y4: 1
A5: 10/11/2025 Sales (Sat) | B5: 63 | C5: 98 | D5: 115 | E5: 130 | F5: 179 | G5: 225 | H5: 258 | I5: 355 | K5: =1433-581 -> 852 | L5: ='Performances by Week'!O16 -> 0.81765172 | N5: Pops | O5: 0.15 | P5: 0.18 | Q5: 0.21 | R5: 0.24 | S5: 0.27 | T5: 0.3 | U5: 0.33 | V5: 0.39 | W5: 0.46 | X5: 0.59 | Y5: 1
A6: 10/12/2025 Sales (Sun) | B6: 57 | C6: 137 | D6: 154 | E6: 174 | F6: 239 | G6: 295 | H6: 328 | I6: 430 | K6: =1433-613 -> 820 | L6: ='Performances by Week'!O17 -> 0.92659704 | N6: Specials | O6: 0.15 | P6: 0.18 | Q6: 0.21 | R6: 0.24 | S6: 0.27 | T6: 0.3 | U6: 0.33 | V6: 0.39 | W6: 0.46 | X6: 0.59 | Y6: 1
A7: Pace for 85% OCC | B7: =$K$7*$K$10*Q4 -> 151.725 | C7: =$K$7*$K$10*R4 -> 173.4 | D7: =$K$7*$K$10*S4 -> 195.075 | E7: =$K$7*$K$10*T4 -> 216.75 | F7: =$K$7*$K$10*U4 -> 238.425 | G7: =$K$7*$K$10*V4 -> 281.775 | H7: =$K$7*$K$10*W4 -> 332.35 | I7: =$K$7*$K$10*X4 -> 426.275 | J7: =$K$7*$K$10*Y4 -> 722.5 | K7: 850 | N7: Other | O7: 0.15 | P7: 0.18 | Q7: 0.21 | R7: 0.24 | S7: 0.27 | T7: 0.3 | U7: 0.33 | V7: 0.39 | W7: 0.46 | X7: 0.59 | Y7: 1
A8: Avg/Show vs Target Pace: | B8: =IF(B4>0,AVERAGE(B4:B6)-B7,"TBD") -> -91.725 | C8: =IF(C4>0,AVERAGE(C4:C6)-C7,"TBD") -> -61.733333 | D8: =IF(D4>0,AVERAGE(D4:D6)-D7,"TBD") -> -70.075 | E8: =IF(E4>0,AVERAGE(E4:E6)-E7,"TBD") -> -70.416667 | F8: =IF(F4>0,AVERAGE(F4:F6)-F7,"TBD") -> -34.758333 | G8: =IF(G4>0,AVERAGE(G4:G6)-G7,"TBD") -> -37.775 | H8: =IF(H4>0,AVERAGE(H4:H6)-H7,"TBD") -> -57.683333 | I8: =IF(I4>0,AVERAGE(I4:I6)-I7,"TBD") -> -55.941667 | J8: =IF(J4>0,AVERAGE(J4:J6)-J7,"TBD") -> TBD
E9: =E7-D7 -> 21.675 | F9: =F7-E7 -> 21.675 | G9: =G7-F7 -> 43.35 | H9: =H7-G7 -> 50.575 | K9: OCC Target
K10: 0.85

Sheet PS2 90s Mixtape
B1: # Weeks Out | Q1: Estimates Only | U1: Historical Data
A2: Single Tickets | B2: 10 | C2: 9 | D2: 8 | E2: 7 | F2: 6 | G2: 5 | H2: 4 | I2: 3 | J2: 2 | K2: 1 | L2: 0 | P2: # Weeks Until Performance | Q2: 10 | R2: 9 | S2: 8 | T2: 7 | U2: 6 | V2: 5 | W2: 4 | X2: 3 | Y2: 2 | Z2: 1 | AA2: 0
A3: PS2 90s Mixtape (Name?) | B3: 45880 | C3: 45887 | D3: 45894 | E3: 45901 | F3: 45908 | G3: 45915 | H3: 45922 | I3: 45929 | J3: 45936 | K3: 45943 | L3: 45950 | M3: # Single Tickets to sell out 100% | N3: Projected OCC% | P3: Classical | Q3: 0.15 | R3: 0.18 | S3: 0.21 | T3: 0.24 | U3: 0.27 | V3: 0.3 | W3: 0.33 | X3: 0.39 | Y3: 0.46 | Z3: 0.59 | AA3: 1
A4: 10/24/2025 Sales (Fri) | B4: 60 | C4: 64 | D4: 68 | E4: 74 | F4: 80 | G4: 92 | H4: 145 | M4: ='Performances by Week'!AF22-'Performances by Week'!AB22 -> 882 | N4: ='Performances by Week'!O22 -> 0.67911627 | P4: Pops | Q4: 0.15 | R4: 0.18 | S4: 0.21 | T4: 0.24 | U4: 0.27 | V4: 0.3 | W4: 0.33 | X4: 0.39 | Y4: 0.46 | Z4: 0.59 | AA4: 1
A5: 10/25/2025 Sales (Sat) | B5: 63 | C5: 63 | D5: 73 | E5: 93 | F5: 106 | G5: 114 | H5: 190 | M5: ='Performances by Week'!AF23-'Performances by Week'!AB23 -> 961 | N5: ='Performances by Week'!O23 -> 0.70199968 | P5: Specials | Q5: 0.15 | R5: 0.18 | S5: 0.21 | T5: 0.24 | U5: 0.27 | V5: 0.3 | W5: 0.33 | X5: 0.39 | Y5: 0.46 | Z5: 0.59 | AA5: 1
A6: 10/26/2025 Sales (Sun) | B6: 57 | C6: 59 | D6: 66 | E6: 74 | F6: 76 | G6: 87 | H6: 163 | M6: ='Performances by Week'!AF24-'Performances by Week'!AB24 -> 1208 | N6: ='Performances by Week'!O24 -> 0.5031124 | P6: Other | Q6: 0.15 | R6: 0.18 | S6: 0.21 | T6: 0.24 | U6: 0.27 | V6: 0.3 | W6: 0.33 | X6: 0.39 | Y6: 0.46 | Z6: 0.59 | AA6: 1
A7: Pace for 85% OCC | B7: =$M$7*$M$10*Q4 -> 129.6675 | C7: =$M$7*$M$10*R4 -> 155.601 | D7: =$M$7*$M$10*S4 -> 181.5345 | E7: =$M$7*$M$10*T4 -> 207.468 | F7: =$M$7*$M$10*U4 -> 233.4015 | G7: =$M$7*$M$10*V4 -> 259.335 | H7: =$M$7*$M$10*W4 -> 285.2685 | I7: =$M$7*$M$10*X4 -> 337.1355 | ... L7: =$M$7*$M$10*AA4 -> 864.45 | M7: =AVERAGE(M4:M6) -> 1017
A8: Avg/Show vs Target Pace: | B8: =IF(B4>0,AVERAGE(B4:B6)-B7,"TBD") -> -69.6675 | C8: =IF(C4>0,AVERAGE(C4:C6)-C7,"TBD") -> -93.601 | D8: =IF(D4>0,AVERAGE(D4:D6)-D7,"TBD") -> -112.5345 | E8: =IF(E4>0,AVERAGE(E4:E6)-E7,"TBD") -> -127.13467 | F8: =IF(F4>0,AVERAGE(F4:F6)-F7,"TBD") -> -146.06817 | G8: =IF(G4>0,AVERAGE(G4:G6)-G7,"TBD") -> -161.66833 | H8: =IF(H4>0,AVERAGE(H4:H6)-H7,"TBD") -> -119.2685 | I8: =IF(I4>0,AVERAGE(I4:I6)-I7,"TBD") -> TBD | ... L8: =IF(L4>0,AVERAGE(L4:L6)-L7,"TBD") -> TBD
M9: OCC Target
M10: 0.85

Sheet MFSB
A1: Single Tickets | B1: 3 | C1: 2 | D1: 1 | E1: 0 | L1: Single Tickets
A2: MFSB | B2: 45880 | C2: 45887 | D2: 45894 | E2: 45901 | F2: # Single Tickets to sell out 100% | K2: # Weeks Until Performance | L2: Classical | M2: Pops | N2: Specials | O2: Other
A3: 9/2/2025 Sales (Tue) | B3: 754 | C3: 915 | D3: 1013 | E3: 1096 | G3: =E3/F5 -> 0.84178187
A4: 9/3/2025 Sales (Wed) | B4: 651 | C4: 826 | D4: 926 | E4: 1027 | G4: =E4/F5 -> 0.78878648 | K4: 0 | L4: 1 | M4: 1 | N4: 1 | O4: 1
A5: Pace for 85% OCC | B5: =$F$5*$G$5*N7 -> 431.613 | C5: =$F$5*$G$5*N6 -> 509.082 | D5: =$F$5*$G$5*N5 -> 652.953 | E5: =$F$5*$G$5*N4 -> 1106.7 | F5: 1302 | G5: 0.85 | K5: 1 | L5: 0.59 | M5: 0.59 | N5: 0.59 | O5: 0.59
K6: 2 | L6: 0.46 | M6: 0.46 | N6: 0.46 | O6: 0.46
K7: 3 | L7: 0.39 | M7: 0.39 | N7: 0.39 | O7: 0.39
K8: 4 | L8: 0.33 | M8: 0.33 | N8: 0.33 | O8: 0.33
K9: 5 | L9: 0.3 | M9: 0.3 | N9: 0.3 | O9: 0.3
K10: 6 | L10: 0.27 | M10: 0.27 | N10: 0.27 | O10: 0.27

Sheet CS2 Rachmaninoff
D1: # weeks out
A2: Single Tickets | B2: 10 | C2: 9 | D2: 8 | E2: 7 | F2: 6 | G2: 5 | H2: 4 | I2: 3 | J2: 2 | K2: 1 | L2: 0 | Q2: Estimates Only | U2: Historical Data
A3: CS2 Rachmaninoff | B3: 45887 | C3: 45894 | D3: 45901 | E3: 45908 | F3: 45915 | G3: 45922 | H3: 45929 | I3: 45936 | J3: 45943 | K3: 45950 | L3: 45957 | M3: # Single Tickets to sell out 100% | N3: Projected OCC% | P3: # Weeks Until Performance | Q3: 10 | R3: 9 | S3: 8 | T3: 7 | U3: 6 | V3: 5 | W3: 4 | X3: 3 | Y3: 2 | Z3: 1 | AA3: 0
A4: 10/31/2025 Sales (Fri, Piazza) | B4: 87 | C4: 93 | D4: 102 | E4: 106 | F4: 111 | G4: 124 | H4: 144 | M4: ='Performances by Week'!AF26-'Performances by Week'!AB26 -> 1091 | N4: ='Performances by Week'!O26 -> 0.54317072 | P4: Classical | Q4: 0.15 | R4: 0.18 | S4: 0.21 | T4: 0.24 | U4: 0.27 | V4: 0.3 | W4: 0.33 | X4: 0.39 | Y4: 0.46 | Z4: 0.59 | AA4: 1
A5: 11/01/2025 Sales (Sat) | B5: 192 | C5: 209 | D5: 256 | E5: 310 | F5: 340 | G5: 382 | H5: 446 | M5: ='Performances by Week'!AF27-'Performances by Week'!AB27 -> 875 | N5: ='Performances by Week'!O27 -> 1 | P5: Pops | Q5: 0.15 | R5: 0.18 | S5: 0.21 | T5: 0.24 | U5: 0.27 | V5: 0.3 | W5: 0.33 | X5: 0.39 | Y5: 0.46 | Z5: 0.59 | AA5: 1
A6: 11/02/2025 Sales (Sun) | B6: 138 | C6: 165 | D6: 187 | E6: 219 | F6: 232 | G6: 267 | H6: 309 | M6: ='Performances by Week'!AF28-'Performances by Week'!AB28 -> 872 | N6: ='Performances by Week'!O28 -> 1 | P6: Specials | Q6: 0.15 | R6: 0.18 | S6: 0.21 | T6: 0.24 | U6: 0.27 | V6: 0.3 | W6: 0.33 | X6: 0.39 | Y6: 0.46 | Z6: 0.59 | AA6: 1
A7: Pace for 85% OCC | B7: =$M$7*$M$10*Q4 -> 120.615 | C7: =$M$7*$M$10*R4 -> 144.738 | D7: =$M$7*$M$10*S4 -> 168.861 | E7: =$M$7*$M$10*T4 -> 192.984 | F7: =$M$7*$M$10*U4 -> 217.107 | G7: =$M$7*$M$10*V4 -> 241.23 | H7: =$M$7*$M$10*W4 -> 265.353 | I7: =$M$7*$M$10*X4 -> 313.599 | ... L7: =$M$7*$M$10*AA4 -> 804.1 | M7: =AVERAGE(M4:M6) -> 946 | P7: Other | Q7: 0.15 | R7: 0.18 | S7: 0.21 | T7: 0.24 | U7: 0.27 | V7: 0.3 | W7: 0.33 | X7: 0.39 | Y7: 0.46 | Z7: 0.59 | AA7: 1
A8: Avg/Show vs Target Pace: | B8: =IF(B4>0,AVERAGE(B4:B6)-B7,"TBD") -> 18.385 | C8: =IF(C4>0,AVERAGE(C4:C6)-C7,"TBD") -> 10.928667 | D8: =IF(D4>0,AVERAGE(D4:D6)-D7,"TBD") -> 12.805667 | E8: =IF(E4>0,AVERAGE(E4:E6)-E7,"TBD") -> 18.682667 | F8: =IF(F4>0,AVERAGE(F4:F6)-F7,"TBD") -> 10.559667 | G8: =IF(G4>0,AVERAGE(G4:G6)-G7,"TBD") -> 16.436667 | H8: =IF(H4>0,AVERAGE(H4:H6)-H7,"TBD") -> 34.313667 | I8: =IF(I4>0,AVERAGE(I4:I6)-I7,"TBD") -> TBD | ... L8: =IF(L4>0,AVERAGE(L4:L6)-L7,"TBD") -> TBD
M9: OCC Target
M10: 0.85

Sheet CS3 Mahler
D1: # weeks out
A2: Single Tickets | B2: 10 | C2: 9 | D2: 8 | E2: 7 | F2: 6 | G2: 5 | H2: 4 | I2: 3 | J2: 2 | K2: 1 | L2: 0 | Q2: Estimates Only | U2: Historical Data
A3: CS3 Mahler | B3: 45908 | C3: 45915 | D3: 45922 | E3: 45929 | F3: 45936 | G3: 45943 | H3: 45950 | I3: 45957 | J3: 45964 | K3: 45971 | L3: 45978 | M3: # Single Tickets to sell out 100% | N3: Projected OCC% | P3: # Weeks Until Performance | Q3: 10 | R3: 9 | S3: 8 | T3: 7 | U3: 6 | V3: 5 | W3: 4 | X3: 3 | Y3: 2 | Z3: 1 | AA3: 0
A4: 11/21/2025 Sales (Fri, Piazza) | B4: 55 | C4: 60 | D4: 66 | E4: 75 | M4: ='Performances by Week'!AF31-'Performances by Week'!AB31 -> 1223 | N4: ='Performances by Week'!O31 -> 0.42735849 | P4: Classical | Q4: 0.15 | R4: 0.18 | S4: 0.21 | T4: 0.24 | U4: 0.27 | V4: 0.3 | W4: 0.33 | X4: 0.39 | Y4: 0.46 | Z4: 0.59 | AA4: 1
A5: 11/22/2025 Sales (Sat) | B5: 95 | C5: 110 | D5: 114 | E5: 143 | M5: ='Performances by Week'!AF32-'Performances by Week'!AB32 -> 1007 | N5: ='Performances by Week'!O32 -> 0.74140461 | P5: Pops | Q5: 0.15 | R5: 0.18 | S5: 0.21 | T5: 0.24 | U5: 0.27 | V5: 0.3 | W5: 0.33 | X5: 0.39 | Y5: 0.46 | Z5: 0.59 | AA5: 1
A6: 11/23/2025 Sales (Sun) | B6: 75 | C6: 81 | D6: 83 | E6: 93 | M6: ='Performances by Week'!AF33-'Performances by Week'!AB33 -> 968 | N6: ='Performances by Week'!O33 -> 0.63490566 | P6: Specials | Q6: 0.15 | R6: 0.18 | S6: 0.21 | T6: 0.24 | U6: 0.27 | V6: 0.3 | W6: 0.33 | X6: 0.39 | Y6: 0.46 | Z6: 0.59 | AA6: 1
A7: Pace for 85% OCC | B7: =$M$7*$M$10*Q4 -> 135.915 | C7: =$M$7*$M$10*R4 -> 163.098 | D7: =$M$7*$M$10*S4 -> 190.281 | E7: =$M$7*$M$10*T4 -> 217.464 | F7: =$M$7*$M$10*U4 -> 244.647 | G7: =$M$7*$M$10*V4 -> 271.83 | H7: =$M$7*$M$10*W4 -> 299.013 | I7: =$M$7*$M$10*X4 -> 353.379 | ... L7: =$M$7*$M$10*AA4 -> 906.1 | M7: =AVERAGE(M4:M6) -> 1066 | P7: Other | Q7: 0.15 | R7: 0.18 | S7: 0.21 | T7: 0.24 | U7: 0.27 | V7: 0.3 | W7: 0.33 | X7: 0.39 | Y7: 0.46 | Z7: 0.59 | AA7: 1
A8: Avg/Show vs Target Pace: | B8: =IF(B4>0,AVERAGE(B4:B6)-B7,"TBD") -> -60.915 | C8: =IF(C4>0,AVERAGE(C4:C6)-C7,"TBD") -> -79.431333 | D8: =IF(D4>0,AVERAGE(D4:D6)-D7,"TBD") -> -102.61433 | E8: =IF(E4>0,AVERAGE(E4:E6)-E7,"TBD") -> -113.79733 | F8: =IF(F4>0,AVERAGE(F4:F6)-F7,"TBD") -> TBD | G8: =IF(G4>0,AVERAGE(G4:G6)-G7,"TBD") -> TBD | H8: =IF(H4>0,AVERAGE(H4:H6)-H7,"TBD") -> TBD | I8: =IF(I4>0,AVERAGE(I4:I6)-I7,"TBD") -> TBD | ... L8: =IF(L4>0,AVERAGE(L4:L6)-L7,"TBD") -> TBD
M9: OCC Target
M10: 0.85

Sheet Elf
D1: # weeks out
A2: Single Tickets | B2: 10 | C2: 9 | D2: 8 | E2: 7 | F2: 6 | G2: 5 | H2: 4 | I2: 3 | J2: 2 | K2: 1 | L2: 0 | Q2: Estimates Only | U2: Historical Data
A3: Elf in Concert | B3: 45915 | C3: 45922 | D3: 45929 | E3: 45936 | F3: 45943 | G3: 45950 | H3: 45957 | I3: 45964 | J3: 45971 | K3: 45978 | L3: 45985 | M3: # Single Tickets to sell out 100% | N3: Projected OCC% | P3: # Weeks Until Performance | Q3: 10 | R3: 9 | S3: 8 | T3: 7 | U3: 6 | V3: 5 | W3: 4 | X3: 3 | Y3: 2 | Z3: 1 | AA3: 0
A4: 11/28/2025 (Fri) | B4: 306 | C4: 323 | D4: 339 | M4: ='Performances by Week'!AF34-'Performances by Week'!AB34 -> 1302 | N4: ='Performances by Week'!O34 -> 1 | P4: Classical | Q4: 0.15 | R4: 0.18 | S4: 0.21 | T4: 0.24 | U4: 0.27 | V4: 0.3 | W4: 0.33 | X4: 0.39 | Y4: 0.46 | Z4: 0.59 | AA4: 1
A5: 11/29/2025 (Sat 1) | B5: 370 | C5: 374 | D5: 414 | M5: ='Performances by Week'!AF35-'Performances by Week'!AB35 -> 1302 | N5: ='Performances by Week'!O35 -> 1 | P5: Pops | Q5: 0.15 | R5: 0.18 | S5: 0.21 | T5: 0.24 | U5: 0.27 | V5: 0.3 | W5: 0.33 | X5: 0.39 | Y5: 0.46 | Z5: 0.59 | AA5: 1
A6: 11/29/2025 (Sat 2) | B6: 283 | C6: 303 | D6: 329 | M6: ='Performances by Week'!AF36-'Performances by Week'!AB36 -> 1302 | N6: ='Performances by Week'!O36 -> 1 | P6: Specials | Q6: 0.15 | R6: 0.18 | S6: 0.21 | T6: 0.24 | U6: 0.27 | V6: 0.3 | W6: 0.33 | X6: 0.39 | Y6: 0.46 | Z6: 0.59 | AA6: 1
A7: 11/30/2025 (Sun) | B7: 483 | C7: 514 | D7: 542 | M7: ='Performances by Week'!AF37-'Performances by Week'!AB37 -> 1302 | N7: ='Performances by Week'!O37 -> 1 | P7: Other | Q7: 0.15 | R7: 0.18 | S7: 0.21 | T7: 0.24 | U7: 0.27 | V7: 0.3 | W7: 0.33 | X7: 0.39 | Y7: 0.46 | Z7: 0.59 | AA7: 1
A8: Pace for 85% OCC | B8: =$M$8*$M$13*Q6 -> 166.005 | C8: =$M$8*$M$13*R6 -> 199.206 | D8: =$M$8*$M$13*S6 -> 232.407 | E8: =$M$8*$M$13*T6 -> 265.608 | F8: =$M$8*$M$13*U6 -> 298.809 | G8: =$M$8*$M$13*V6 -> 332.01 | H8: =$M$8*$M$13*W6 -> 365.211 | I8: =$M$8*$M$13*X6 -> 431.613 | ... L8: =$M$8*$M$13*AA6 -> 1106.7 | M8: =AVERAGE(M4:M7) -> 1302
A9: Home Alone 2024 | B9: =AVERAGE(B32:B35) -> 480.5 | C9: =AVERAGE(C32:C35) -> 532.5 | D9: =AVERAGE(D32:D35) -> 570.5 | E9: =AVERAGE(E32:E35) -> 607.5 | F9: =AVERAGE(F32:F35) -> 645.75 | G9: =AVERAGE(G32:G35) -> 720 | H9: =AVERAGE(H32:H35) -> 836.5 | I9: =AVERAGE(I32:I35) -> 956.75 | ... L9: =AVERAGE(L32:L35) -> 1293.25
A10: Muppet XMas 2023 | B10: =AVERAGE(B43:B44) -> 943.5 | C10: =AVERAGE(C43:C44) -> 992.5 | D10: =AVERAGE(D43:D44) -> 1056 | E10: =AVERAGE(E43:E44) -> 1088 | F10: =AVERAGE(F43:F44) -> 1158 | G10: =AVERAGE(G43:G44) -> 1220 | H10: =AVERAGE(H43:H44) -> 1242.5 | I10: =AVERAGE(I43:I44) -> 1259.5 | ... L10: =AVERAGE(L43:L44) -> 1288.5
A11: Avg/Show vs 2024 Pace: | B11: =IF(B4>0,AVERAGE(B4:B7)-B9,"TBD") -> -120 | C11: =IF(C4>0,AVERAGE(C4:C7)-C9,"TBD") -> -154 | D11: =IF(D4>0,AVERAGE(D4:D7)-D9,"TBD") -> -164.5 | E11: =IF(E4>0,AVERAGE(E4:E7)-E9,"TBD") -> TBD | F11: =IF(F4>0,AVERAGE(F4:F7)-F9,"TBD") -> TBD | G11: =IF(G4>0,AVERAGE(G4:G7)-G9,"TBD") -> TBD | H11: =IF(H4>0,AVERAGE(H4:H7)-H9,"TBD") -> TBD | I11: =IF(I4>0,AVERAGE(I4:I7)-I9,"TBD") -> TBD | ... L11: =IF(L4>0,AVERAGE(L4:L7)-L9,"TBD") -> TBD
M12: OCC Target
M13: 0.85
A30: Single Tickets | B30: 10 | C30: 9 | D30: 8 | E30: 7 | F30: 6 | G30: 5 | H30: 4 | I30: 3 | J30: 2 | K30: 1 | L30: 0
A31: Home Alone | B31: 45551 | C31: 45558 | D31: 45565 | E31: 45572 | F31: 45579 | G31: 45586 | H31: 45593 | I31: 45600 | J31: 45607 | K31: 45614 | L31: 45621 | M31: # Single Tickets to sell out 100% | N31: Final Occupancy Sold %
A32: 11/29/2024 Sales (Friday) | B32: 395 | C32: 422 | D32: 451 | E32: 488 | F32: 518 | G32: 591 | H32: 667 | I32: 754 | J32: 913 | K32: 1165 | L32: 1276 | M32: 1342 | N32: 0.9664
A33: 11/30/2024, 2pm (Saturday) | B33: 604 | C33: 669 | D33: 701 | E33: 735 | F33: 763 | G33: 832 | H33: 955 | I33: 1040 | J33: 1229 | K33: 1269 | L33: 1301 | M33: 1342 | N33: 0.9873
A34: 11/30/2024, 8pm (Saturday) | B34: 302 | C34: 353 | D34: 391 | E34: 422 | F34: 454 | G34: 500 | H34: 657 | I34: 813 | J34: 988 | K34: 1200 | L34: 1301 | M34: 1342 | N34: 0.9836
A35: 12/01/2024 Sales (Sunday) | B35: 621 | C35: 686 | D35: 739 | E35: 785 | F35: 848 | G35: 957 | H35: 1067 | I35: 1220 | J35: 1269 | K35: 1275 | L35: 1295 | M35: 1342 | N35: 0.9813
A36: Pace for 85% OCC
A37: Avg/Show vs Target Pace:
M38: OCC Target
M39: 0.85
A41: Single Tickets | B41: 10 | C41: 9 | D41: 8 | E41: 7 | F41: 6 | G41: 5 | H41: 4 | I41: 3 | J41: 2 | K41: 1 | L41: 0
A42: A Muppet Christmas Carol | B42: 45194 | C42: 45201 | D42: 45208 | E42: 45215 | F42: 45222 | G42: 45229 | H42: 45236 | I42: 45243 | J42: 45250 | K42: 45988 | L42: 45995 | M42: # Single Tickets to sell out 100% | N42: Final Occupancy Sold %
A43: 12/08/2023 Sales (Friday) | B43: 844 | C43: 894 | D43: 980 | E43: 1010 | F43: 1104 | G43: 1218 | H43: 1244 | I43: 1264 | J43: 1268 | K43: 1279 | L43: 1289 | M43: 1334 | N43: 0.9962
A44: 12/09/2023, 1pm Sales (Saturday) | B44: 1043 | C44: 1091 | D44: 1132 | E44: 1166 | F44: 1212 | G44: 1222 | H44: 1241 | I44: 1255 | J44: 1265 | K44: 1270 | L44: 1288 | M44: 1334 | N44: 0.979
A45: Pace for 85% OCC
A46: Avg/Show vs Target Pace:
M47: OCC Target
M48: 0.85

Sheet Messiah
D1: # weeks out
A2: Single Tickets | B2: 10 | C2: 9 | D2: 8 | E2: 7 | F2: 6 | G2: 5 | H2: 4 | I2: 3 | J2: 2 | K2: 1 | L2: 0 | Q2: Estimates Only | U2: Historical Data
A3: Handel's Messiah | B3: 45922 | C3: 45929 | D3: 45936 | E3: 45943 | F3: 45950 | G3: 45957 | H3: 45964 | I3: 45971 | J3: 45978 | K3: 45985 | L3: 45992 | M3: # Single Tickets to sell out 100% | N3: Projected OCC% | P3: # Weeks Until Performance | Q3: 10 | R3: 9 | S3: 8 | T3: 7 | U3: 6 | V3: 5 | W3: 4 | X3: 3 | Y3: 2 | Z3: 1 | AA3: 0
A4: 12/5/2025 (Fri) | B4: 369 | C4: 395 | M4: ='Performances by Week'!AF38-'Performances by Week'!AB38 -> 1433 | N4: ='Performances by Week'!O38 -> 1 | P4: Classical | Q4: 0.15 | R4: 0.18 | S4: 0.21 | T4: 0.24 | U4: 0.27 | V4: 0.3 | W4: 0.33 | X4: 0.39 | Y4: 0.46 | Z4: 0.59 | AA4: 1
A5: 12/6/2025 (Sat) | B5: 369 | C5: 386 | M5: ='Performances by Week'!AF39-'Performances by Week'!AB39 -> 1433 | N5: ='Performances by Week'!O39 -> 1 | P5: Pops | Q5: 0.15 | R5: 0.18 | S5: 0.21 | T5: 0.24 | U5: 0.27 | V5: 0.3 | W5: 0.33 | X5: 0.39 | Y5: 0.46 | Z5: 0.59 | AA5: 1
A6: 12/7/2025 (Sun) | B6: 410 | C6: 443 | M6: ='Performances by Week'!AF40-'Performances by Week'!AB40 -> 1433 | N6: ='Performances by Week'!O40 -> 1 | P6: Specials | Q6: 0.15 | R6: 0.18 | S6: 0.21 | T6: 0.24 | U6: 0.27 | V6: 0.3 | W6: 0.33 | X6: 0.39 | Y6: 0.46 | Z6: 0.59 | AA6: 1
A7: Pace for 85% OCC | B7: =$M$7*$M$14*Q6 -> 182.7075 | C7: =$M$7*$M$14*R6 -> 219.249 | D7: =$M$7*$M$14*S6 -> 255.7905 | E7: =$M$7*$M$14*T6 -> 292.332 | F7: =$M$7*$M$14*U6 -> 328.8735 | G7: =$M$7*$M$14*V6 -> 365.415 | H7: =$M$7*$M$14*W6 -> 401.9565 | I7: =$M$7*$M$14*X6 -> 475.0395 | ... L7: =$M$7*$M$14*AA6 -> 1218.05 | M7: =AVERAGE(M4:M6) -> 1433 | P7: Other | Q7: 0.15 | R7: 0.18 | S7: 0.21 | T7: 0.24 | U7: 0.27 | V7: 0.3 | W7: 0.33 | X7: 0.39 | Y7: 0.46 | Z7: 0.59 | AA7: 1
A8: Weekly new sales needed for Target Pace | C8: =C7-B7 -> 36.5415 | D8: =D7-C7 -> 36.5415 | E8: =E7-D7 -> 36.5415 | F8: =F7-E7 -> 36.5415 | G8: =G7-F7 -> 36.5415 | H8: =H7-G7 -> 36.5415 | I8: =I7-H7 -> 73.083 | J8: =J7-I7 -> 85.2635 | ... L8: =L7-K7 -> 499.4005
A9: Actual Weekly Sales | C9: =C6-B6 -> 33
A10: Messiah 2024 | B10: =AVERAGE(B33:B35) -> 300.33333 | C10: =AVERAGE(C33:C35) -> 322.33333 | D10: =AVERAGE(D33:D35) -> 360 | E10: =AVERAGE(E33:E35) -> 395.66667 | F10: =AVERAGE(F33:F35) -> 431 | G10: =AVERAGE(G33:G35) -> 486.33333 | H10: =AVERAGE(H33:H35) -> 568.33333 | I10: =AVERAGE(I33:I35) -> 667 | ... L10: =AVERAGE(L33:L35) -> 1146
A11: Messiah 2023 | B11: =AVERAGE(B43:B45) -> 338 | C11: =AVERAGE(C43:C45) -> 372 | D11: =AVERAGE(D43:D45) -> 411 | E11: =AVERAGE(E43:E45) -> 447.33333 | F11: =AVERAGE(F43:F45) -> 494.66667 | G11: =AVERAGE(G43:G45) -> 557 | H11: =AVERAGE(H43:H45) -> 657.66667 | I11: =AVERAGE(I43:I45) -> 738.33333 | ... L11: =AVERAGE(L43:L45) -> 1180.3333
A12: Avg/Show vs Target Pace: | B12: =IF(B4>0,AVERAGE(B4:B6)-B10,"TBD") -> 82.333333 | C12: =IF(C4>0,AVERAGE(C4:C6)-C10,"TBD") -> 85.666667 | D12: =IF(D4>0,AVERAGE(D4:D6)-D10,"TBD") -> TBD | E12: =IF(E4>0,AVERAGE(E4:E6)-E10,"TBD") -> TBD | F12: =IF(F4>0,AVERAGE(F4:F6)-F10,"TBD") -> TBD | G12: =IF(G4>0,AVERAGE(G4:G6)-G10,"TBD") -> TBD | H12: =IF(H4>0,AVERAGE(H4:H6)-H10,"TBD") -> TBD | I12: =IF(I4>0,AVERAGE(I4:I6)-I10,"TBD") -> TBD | ... L12: =IF(L4>0,AVERAGE(L4:L6)-L10,"TBD") -> TBD
M13: OCC Target
M14: 0.85
A31: Single Tickets | B31: 10 | C31: 9 | D31: 8 | E31: 7 | F31: 6 | G31: 5 | H31: 4 | I31: 3 | J31: 2 | K31: 1 | L31: 0
A32: Handel's Messiah | B32: 45558 | C32: 45565 | D32: 45572 | E32: 45579 | F32: 45586 | G32: 45593 | H32: 45600 | I32: 45607 | J32: 45614 | K32: 45621 | L32: 45628 | M32: # Single Tickets to sell out 100% | N32: Final Occupancy Sold %
A33: 12/06/2024 Sales (Friday) | B33: 269 | C33: 295 | D33: 314 | E33: 335 | F33: 385 | G33: 425 | H33: 522 | I33: 615 | J33: 771 | K33: 912 | L33: 1078 | M33: 1450 | N33: 0.8834
A34: 12/07/2024 Sales (Saturday) | B34: 318 | C34: 333 | D34: 368 | E34: 392 | F34: 424 | G34: 483 | H34: 549 | I34: 660 | J34: 751 | K34: 918 | L34: 1127 | M34: 1450 | N34: 0.9662
A35: 12/08/2024 Sales (Sunday) | B35: 314 | C35: 339 | D35: 398 | E35: 460 | F35: 484 | G35: 551 | H35: 634 | I35: 726 | J35: 849 | K35: 1033 | L35: 1233 | M35: 1450 | N35: 0.9751
A36: Pace for 85% OCC
A37: Avg/Show vs Target Pace:
M38: OCC Target
M39: 0.85
A41: Single Tickets | B41: 10 | C41: 9 | D41: 8 | E41: 7 | F41: 6 | G41: 5 | H41: 4 | I41: 3 | J41: 2 | K41: 1 | L41: 0
A42: Handel's Messiah | B42: 45187 | C42: 45194 | D42: 45201 | E42: 45208 | F42: 45215 | G42: 45222 | H42: 45229 | I42: 45236 | J42: 45243 | K42: 45250 | L42: 45988 | M42: # Single Tickets to sell out 100% | N42: Final Occupancy Sold %
A43: 12/01/2023 Sales (Friday) | B43: 292 | C43: 312 | D43: 345 | E43: 367 | F43: 421 | G43: 468 | H43: 562 | I43: 635 | J43: 855 | K43: 992 | L43: 1129 | M43: 1450 | N43: 0.9434
A44: 12/02/2023 Sales (Saturday) | B44: 345 | C44: 396 | D44: 439 | E44: 495 | F44: 538 | G44: 590 | H44: 693 | I44: 784 | J44: 929 | K44: 1043 | L44: 1153 | M44: 1450 | N44: 0.991
A45: 12/03/2023 Sales (Sunday) | B45: 377 | C45: 408 | D45: 449 | E45: 480 | F45: 525 | G45: 613 | H45: 718 | I45: 796 | J45: 945 | K45: 1105 | L45: 1259 | M45: 1450 | N45: 1
A46: Avg/Show vs Target Pace:
M47: OCC Target
M48: 0.85

Sheet XMas Festival
D1: # weeks out
A2: Single Tickets | B2: 10 | C2: 9 | D2: 8 | E2: 7 | F2: 6 | G2: 5 | H2: 4 | I2: 3 | J2: 2 | K2: 1 | L2: 0 | Q2: Estimates Only | U2: Historical Data
A3: Christmas Festival | B3: 45936 | C3: 45943 | D3: 45950 | E3: 45957 | F3: 45964 | G3: 45971 | H3: 45978 | I3: 45985 | J3: 45992 | K3: 45999 | L3: 46006 | M3: # Single Tickets to sell out 100% | N3: Projected OCC% | P3: # Weeks Until Performance | Q3: 10 | R3: 9 | S3: 8 | T3: 7 | U3: 6 | V3: 5 | W3: 4 | X3: 3 | Y3: 2 | Z3: 1 | AA3: 0
A4: 12/18/2025 (Thu) | B4: 220 | M4: ='Performances by Week'!AF43-'Performances by Week'!AB43 -> 1433 | N4: ='Performances by Week'!O43 -> Too early | P4: Classical | Q4: 0.15 | R4: 0.18 | S4: 0.21 | T4: 0.24 | U4: 0.27 | V4: 0.3 | W4: 0.33 | X4: 0.39 | Y4: 0.46 | Z4: 0.59 | AA4: 1
A5: 12/19/2025 (Fri) | B5: 211 | M5: ='Performances by Week'!AF44-'Performances by Week'!AB44 -> 1433 | N5: ='Performances by Week'!O44 -> Too early | P5: Pops | Q5: 0.15 | R5: 0.18 | S5: 0.21 | T5: 0.24 | U5: 0.27 | V5: 0.3 | W5: 0.33 | X5: 0.39 | Y5: 0.46 | Z5: 0.59 | AA5: 1
A6: 12/20/2025 (Sat 1) | B6: 388 | M6: ='Performances by Week'!AF45-'Performances by Week'!AB45 -> 1433 | N6: ='Performances by Week'!O45 -> Too early | P6: Specials | Q6: 0.15 | R6: 0.18 | S6: 0.21 | T6: 0.24 | U6: 0.27 | V6: 0.3 | W6: 0.33 | X6: 0.39 | Y6: 0.46 | Z6: 0.59 | AA6: 1
A7: 12/20/2025 (Sat 2) | B7: 292 | M7: ='Performances by Week'!AF46-'Performances by Week'!AB46 -> 1433 | N7: ='Performances by Week'!O46 -> Too early | P7: Other | Q7: 0.15 | R7: 0.18 | S7: 0.21 | T7: 0.24 | U7: 0.27 | V7: 0.3 | W7: 0.33 | X7: 0.39 | Y7: 0.46 | Z7: 0.59 | AA7: 1
A8: 12/21/2025 (Sun 1) | B8: 328 | M8: ='Performances by Week'!AF47-'Performances by Week'!AB47 -> 1132 | N8: ='Performances by Week'!O47 -> Too early
A9: 12/21/2025 (Sun 2) | B9: 152 | M9: ='Performances by Week'!AF48-'Performances by Week'!AB48 -> 1433 | N9: ='Performances by Week'!O48 -> Too early
A10: Pace for 85% OCC | B10: =$M$10*$M$15*Q6 -> 176.31125 | C10: =$M$10*$M$15*R6 -> 211.5735 | D10: =$M$10*$M$15*S6 -> 246.83575 | E10: =$M$10*$M$15*T6 -> 282.098 | F10: =$M$10*$M$15*U6 -> 317.36025 | G10: =$M$10*$M$15*V6 -> 352.6225 | H10: =$M$10*$M$15*W6 -> 387.88475 | I10: =$M$10*$M$15*X6 -> 458.40925 | ... L10: =$M$10*$M$15*AA6 -> 1175.4083 | M10: =AVERAGE(M4:M9) -> 1382.8333
A11: XMas 2024 | B11: =AVERAGE(B34:B39) -> 261.33333 | C11: =AVERAGE(C34:C39) -> 282.66667 | D11: =AVERAGE(D34:D39) -> 315.5 | E11: =AVERAGE(E34:E39) -> 360.16667 | F11: =AVERAGE(F34:F39) -> 412.16667 | G11: =AVERAGE(G34:G39) -> 494.33333 | H11: =AVERAGE(H34:H39) -> 597.83333 | I11: =AVERAGE(I34:I39) -> 699.5 | ... L11: =AVERAGE(L34:L39) -> 1111.3333
A12: XMas 2023 | B12: =AVERAGE(B45:B50) -> 349.16667 | C12: =AVERAGE(C45:C50) -> 378.16667 | D12: =AVERAGE(D45:D50) -> 414.66667 | E12: =AVERAGE(E45:E50) -> 459.16667 | F12: =AVERAGE(F45:F50) -> 530.83333 | G12: =AVERAGE(G45:G50) -> 599.66667 | H12: =AVERAGE(H45:H50) -> 709 | I12: =AVERAGE(I45:I50) -> 795.5 | ... L12: =AVERAGE(L45:L50) -> 1105.8333
A13: Avg/Show vs Target Pace: | B13: =IF(B4>0,AVERAGE(B4:B9)-B10,"TBD") -> 88.855417 | C13: =IF(C4>0,AVERAGE(C4:C9)-C10,"TBD") -> TBD | D13: =IF(D4>0,AVERAGE(D4:D9)-D10,"TBD") -> TBD | E13: =IF(E4>0,AVERAGE(E4:E9)-E10,"TBD") -> TBD | F13: =IF(F4>0,AVERAGE(F4:F9)-F10,"TBD") -> TBD | G13: =IF(G4>0,AVERAGE(G4:G9)-G10,"TBD") -> TBD | H13: =IF(H4>0,AVERAGE(H4:H9)-H10,"TBD") -> TBD | I13: =IF(I4>0,AVERAGE(I4:I9)-I10,"TBD") -> TBD | ... L13: =IF(L4>0,AVERAGE(L4:L9)-L10,"TBD") -> TBD
M14: OCC Target
M15: 0.85
A32: Single Tickets | B32: 10 | C32: 9 | D32: 8 | E32: 7 | F32: 6 | G32: 5 | H32: 4 | I32: 3 | J32: 2 | K32: 1 | L32: 0
A33: Christmas Festival | B33: 45572 | C33: 45579 | D33: 45586 | E33: 45593 | F33: 45600 | G33: 45607 | H33: 45614 | I33: 45621 | J33: 45628 | K33: 45635 | L33: 45642 | M33: # Single Tickets to sell out 100% | N33: Final Occupancy Sold %
A34: 12/19/2024 Sales (Thursday) | B34: 261 | C34: 267 | D34: 297 | E34: 341 | F34: 395 | G34: 447 | H34: 602 | I34: 693 | J34: 750 | K34: 932 | L34: 1069 | M34: 1446 | N34: 0.7897
A35: 12/20/2024 Sales (Friday) | B35: 206 | C35: 216 | D35: 256 | E35: 310 | F35: 370 | G35: 432 | H35: 509 | I35: 605 | J35: 732 | K35: 848 | L35: 1052 | M35: 1476 | N35: 0.8741
A36: 12/21/2024, 1pm Sales (Saturday) | B36: 349 | C36: 398 | D36: 427 | E36: 464 | F36: 526 | G36: 606 | H36: 670 | I36: 745 | J36: 848 | K36: 1034 | L36: 1180 | M36: 1476 | N36: 0.8934
A37: 12/21/2024, 7pm Sales (Saturday) | B37: 276 | C37: 294 | D37: 340 | E37: 375 | F37: 400 | G37: 480 | H37: 584 | I37: 715 | J37: 844 | K37: 995 | L37: 1184 | M37: 1476 | N37: 0.9591
A38: 12/22/2024, 2pm Sales (Sunday) | B38: 302 | C38: 336 | D38: 363 | E38: 411 | F38: 486 | G38: 624 | H38: 730 | I38: 857 | J38: 986 | K38: 1089 | L38: 1104 | M38: 1168 | N38: 0.9412
A39: 12/22/2024, 7pm Sales (Sunday) | B39: 174 | C39: 185 | D39: 210 | E39: 260 | F39: 296 | G39: 377 | H39: 492 | I39: 582 | J39: 677 | K39: 833 | L39: 1079 | M39: 1476 | N39: 0.9751
M40: OCC Target
M41: 0.85
A43: Single Tickets | B43: 10 | C43: 9 | D43: 8 | E43: 7 | F43: 6 | G43: 5 | H43: 4 | I43: 3 | J43: 2 | K43: 1 | L43: 0
A44: Christmas Festival | B44: 45201 | C44: 45208 | D44: 45215 | E44: 45222 | F44: 45229 | G44: 45236 | H44: 45243 | I44: 45250 | J44: 45988 | K44: 45995 | L44: 46002 | M44: # Single Tickets to sell out 100% | N44: Final Occupancy Sold %
A45: 12/14/2023 Sales (Thursday) | B45: 279 | C45: 293 | D45: 309 | E45: 348 | F45: 410 | G45: 485 | H45: 540 | I45: 608 | J45: 674 | K45: 793 | L45: 912 | M45: 1446 | N45: 0.7627
A46: 12/15/2023 Sales (Friday) | B46: 288 | C46: 332 | D46: 391 | E46: 435 | F46: 536 | G46: 605 | H46: 744 | I46: 845 | J46: 942 | K46: 1068 | L46: 1230 | M46: 1446 | N46: 0.9273
A47: 12/16/2023, 1pm Sales (Saturday) | B47: 506 | C47: 529 | D47: 575 | E47: 625 | F47: 741 | G47: 835 | H47: 972 | I47: 1097 | J47: 1175 | K47: 1315 | L47: 1382 | M47: 1446 | N47: 0.9723
A48: 12/16/2023, 7pm Sales (Saturday) | B48: 396 | C48: 417 | D48: 462 | E48: 520 | F48: 554 | G48: 619 | H48: 806 | I48: 887 | J48: 965 | K48: 1139 | L48: 1312 | M48: 1446 | N48: 0.9764
A49: 12/17/2023, 2pm Sales (Sunday) | B49: 442 | C49: 467 | D49: 499 | E49: 559 | F49: 648 | G49: 712 | H49: 800 | I49: 857 | J49: 866 | K49: 903 | L49: 925 | M49: 969 | N49: 0.9917
A50: 12/17/2023, 7pm Sales (Sunday) | B50: 184 | C50: 231 | D50: 252 | E50: 268 | F50: 296 | G50: 342 | H50: 392 | I50: 479 | J50: 584 | K50: 729 | L50: 874 | M50: 1446 | N50: 0.9702

Sheet Subscriptions
B1: KANSAS CITY SYMPHONY | E1: Update all fields in Blue each week | J1: 100%+ of FY26 Goal
B2: 2025-26 Subscriptions | E2: We expect 50% of Total by Week 5 | J2: 90-99% of FY26 Goal | N2: Classical | S2: FY26 Budget - Classical
E3: We expect 90% of Total by Week 10/11 | J3: <90% of FY26 Goal | N3: 0.72 | O3: % of total subscriptions | S3: Units | T3: Revenue
O4: =O8/S8*S4 -> 190.76952 | P4: =P8/O8*O4 -> 67934.779 | Q4: =Q8/S8*S4 -> 2954.7347 | R4: =R8/Q8*Q4 -> 1567065.2 | S4: =T4/(T8/S8) -> 3145.5043 | T4: 1635000 | U4: Total
B5: FY26 Sales - Classical | O5: =O9/S9*S5 -> 8.6708651 | P5: =P9/O9*O5 -> 2639.1544 | Q5: =Q9/S9*S5 -> 267.83339 | R5: =R9/Q9*Q5 -> 147753.15 | S5: =T5/(T8/S8) -> 276.50425 | T5: =T4-T8 -> 143724 | U5: Difference vs FY25
C6: New | F6: Renewals | I6: Total | N6: FY25 Actuals - Classical
A7: Weeks On Sale | C7: Actual Units | D7: Proj | E7: Actual Rev | F7: Actual Units | G7: Proj | H7: Actual Rev | I7: Actual Units | J7: Proj | K7: Actual Rev | L7: W/W Change | O7: New Units | P7: New Revenue | Q7: Renewal Units | R7: Renewal Revenue | S7: Total Units | T7: Total Revenue | U7: Change
A8: Projected Total | I8: =I16 -> 2456 | K8: =K16 -> 1408430 | N8: Final | O8: =O21 -> 174 | P8: =P21 -> 61963 | Q8: =Q21 -> 2695 | R8: =R21 -> 1429313 | S8: =S21 -> 2869 | T8: =T21 -> 1491276
A9: 1 | B9: 45747 | C9: 30 | D9: =C9/'Sales Pacing'!B3 -> 713.33333 | E9: 16220 | F9: 898 | G9: =F9/'Sales Pacing'!E3 -> 3554.0218 | H9: 527973 | I9: =C9+F9 -> 928 | J9: =D9+G9 -> 4267.3552 | K9: =E9+H9 -> 544193 | N9: 45383 | O9: 27 | P9: 8218 | Q9: 834 | R9: 460085 | S9: =O9+Q9 -> 861 | T9: =P9+R9 -> 468303
A10: 2 | B10: 45754 | C10: 39 | D10: =C10/'Sales Pacing'!B4 -> 642 | E10: 21024 | F10: 1136 | G10: =F10/'Sales Pacing'!E4 -> 3593.8233 | H10: 652031 | I10: =C10+F10 -> 1175 | J10: =D10+G10 -> 4235.8233 | K10: =E10+H10 -> 673055 | L10: =IF(K10>0,K10-K9,0) -> 128862 | N10: =N9+7 -> 45390 | O10: 32 | P10: 12068 | Q10: 1194 | R10: 655718 | S10: =O10+Q10 -> 1226 | T10: =P10+R10 -> 667786 | U10: =IF(T10>0,T10-T9,0) -> 199483
A11: 3 | B11: 45761 | C11: 50 | D11: =C11/'Sales Pacing'!B5 -> 455.31915 | E11: 27424 | F11: 1387 | G11: =F11/'Sales Pacing'!E5 -> 3529.55 | H11: 817109 | I11: =C11+F11 -> 1437 | J11: =D11+G11 -> 3984.8691 | K11: =E11+H11 -> 844533 | L11: =IF(K11>0,K11-K10,0) -> 171478 | N11: =N10+7 -> 45397 | O11: 36 | P11: 13657 | Q11: 1434 | R11: 789833 | S11: =O11+Q11 -> 1470 | T11: =P11+R11 -> 803490 | U11: =IF(T11>0,T11-T10,0) -> 135704
A12: 4 | B12: 45768 | C12: 76 | D12: =C12/'Sales Pacing'!B6 -> 591.41818 | E12: 40984 | F12: 1739 | G12: =F12/'Sales Pacing'!E6 -> 3653.0333 | H12: 1005395 | I12: =C12+F12 -> 1815 | J12: =D12+G12 -> 4244.4515 | K12: =E12+H12 -> 1046379 | L12: =IF(K12>0,K12-K11,0) -> 201846 | N12: =N11+7 -> 45404 | O12: 45 | P12: 17584 | Q12: 1789 | R12: 976040 | S12: =O12+Q12 -> 1834 | T12: =P12+R12 -> 993624 | U12: =IF(T12>0,T12-T11,0) -> 190134
A13: 5 | B13: =B12+7 -> 45775 | C13: 112 | D13: =C13/'Sales Pacing'!B7 -> 684.8 | E13: 54163 | F13: 2160 | G13: =F13/'Sales Pacing'!E7 -> 3788.4885 | H13: 1232817 | I13: =C13+F13 -> 2272 | J13: =D13+G13 -> 4473.2885 | K13: =E13+H13 -> 1286980 | L13: =IF(K13>0,K13-K12,0) -> 240601 | N13: =N12+7 -> 45411 | O13: 47 | P13: 17987 | Q13: 2005 | R13: 1080463 | S13: =O13+Q13 -> 2052 | T13: =P13+R13 -> 1098450 | U13: =IF(T13>0,T13-T12,0) -> 104826
A14: 6 | B14: =B13+7 -> 45782 | C14: 121 | D14: =C14/'Sales Pacing'!B8 -> 533.89691 | E14: 58153 | F14: 2252 | G14: =F14/'Sales Pacing'!E8 -> 3121.3817 | H14: 1294295 | I14: =C14+F14 -> 2373 | J14: =D14+G14 -> 3655.2787 | K14: =E14+H14 -> 1352448 | L14: =IF(K14>0,K14-K13,0) -> 65468 | N14: =N13+7 -> 45418 | O14: 70 | P14: 26832 | Q14: 2362 | R14: 1271615 | S14: =O14+Q14 -> 2432 | T14: =P14+R14 -> 1298447 | U14: =IF(T14>0,T14-T13,0) -> 199997
A15: 7 | B15: =B14+7 -> 45789 | C15: 122 | D15: =C15/'Sales Pacing'!B9 -> 404.77519 | E15: 59763 | F15: 2293 | G15: =F15/'Sales Pacing'!E9 -> 2534.0926 | H15: 1322554 | I15: =C15+F15 -> 2415 | J15: =D15+G15 -> 2938.8678 | K15: =E15+H15 -> 1382317 | L15: =IF(K15>0,K15-K14,0) -> 29869 | N15: =N14+7 -> 45425 | O15: 76 | P15: 28802 | Q15: 2443 | R15: 1319275 | S15: =O15+Q15 -> 2519 | T15: =P15+R15 -> 1348077 | U15: =IF(T15>0,T15-T14,0) -> 49630
A16: 8 | B16: =B15+7 -> 45796 | C16: 134 | D16: =C16/'Sales Pacing'!B10 -> 382.34667 | E16: 63528 | F16: 2322 | G16: =F16/'Sales Pacing'!E10 -> 2473.787 | H16: 1344902 | I16: =C16+F16 -> 2456 | J16: =D16+G16 -> 2856.1337 | K16: =E16+H16 -> 1408430 | L16: =IF(K16>0,K16-K15,0) -> 26113 | N16: =N15+7 -> 45432 | O16: 85 | P16: 30752 | Q16: 2473 | R16: 1329297 | S16: =O16+Q16 -> 2558 | T16: =P16+R16 -> 1360049 | U16: =IF(T16>0,T16-T15,0) -> 11972
A17: 9 | B17: =B16+7 -> 45803 | C17: 146 | D17: =C17/'Sales Pacing'!B11 -> 369.75148 | E17: 67946 | F17: 2345 | G17: =F17/'Sales Pacing'!E11 -> 2468.3763 | H17: 1357272 | I17: =C17+F17 -> 2491 | J17: =D17+G17 -> 2838.1277 | K17: =E17+H17 -> 1425218 | L17: =IF(K17>0,K17-K16,0) -> 16788 | N17: =N16+7 -> 45439 | O17: 91 | P17: 32154 | Q17: 2513 | R17: 1344658 | S17: =O17+Q17 -> 2604 | T17: =P17+R17 -> 1376812 | U17: =IF(T17>0,T17-T16,0) -> 16763
A18: 10 | B18: =B17+7 -> 45810 | C18: 165 | D18: =C18/'Sales Pacing'!B12 -> 377.64706 | E18: 75744 | F18: 2369 | G18: =F18/'Sales Pacing'!E12 -> 2461.486 | H18: 1380368 | I18: =C18+F18 -> 2534 | J18: =D18+G18 -> 2839.1331 | K18: =E18+H18 -> 1456112 | L18: =IF(K18>0,K18-K17,0) -> 30894 | N18: =N17+7 -> 45446 | O18: 94 | P18: 32854 | Q18: 2608 | R18: 1391277 | S18: =O18+Q18 -> 2702 | T18: =P18+R18 -> 1424131 | U18: =IF(T18>0,T18-T17,0) -> 47319
A19: 11 | B19: =B18+7 -> 45817 | C19: 186 | D19: =C19/'Sales Pacing'!B13 -> 396.0597 | E19: 89633 | F19: 2384 | G19: =F19/'Sales Pacing'!E13 -> 2469.1125 | H19: 1390065 | I19: =C19+F19 -> 2570 | J19: =D19+G19 -> 2865.1722 | K19: =E19+H19 -> 1479698 | L19: =IF(K19>0,K19-K18,0) -> 23586 | N19: =N18+7 -> 45453 | O19: 95 | P19: 33169 | Q19: 2628 | R19: 1398365 | S19: =O19+Q19 -> 2723 | T19: =P19+R19 -> 1431534 | U19: =IF(T19>0,T19-T18,0) -> 7403
A20: 12 | B20: =B19+7 -> 45824 | C20: 205 | D20: =C20/'Sales Pacing'!B14 -> 404.3318 | E20: 94753 | F20: 2413 | G20: =F20/'Sales Pacing'!E14 -> 2491.1434 | H20: 1408181 | I20: =C20+F20 -> 2618 | J20: =D20+G20 -> 2895.4752 | K20: =E20+H20 -> 1502934 | L20: =IF(K20>0,K20-K19,0) -> 23236 | N20: =N19+7 -> 45460 | O20: 103 | P20: 35745 | Q20: 2655 | R20: 1411925 | S20: =O20+Q20 -> 2758 | T20: =P20+R20 -> 1447670 | U20: =IF(T20>0,T20-T19,0) -> 16136
A21: 13+ | B21: 45922 | C21: 320 | D21: =C21/'Sales Pacing'!B15 -> 320 | E21: 141042 | F21: 2427 | G21: =F21/'Sales Pacing'!E15 -> 2427 | H21: 1411610 | I21: =C21+F21 -> 2747 | J21: =D21+G21 -> 2747 | K21: =E21+H21 -> 1552652 | L21: =IF(K21>0,K21-K20,0) -> 49718 | N21: Rest of Season | O21: 174 | P21: 61963 | Q21: 2695 | R21: 1429313 | S21: =O21+Q21 -> 2869 | T21: =P21+R21 -> 1491276 | U21: =IF(T21>0,T21-T20,0) -> 43606
I22: vs. FY26 Goal | J22: =J21/$S$4 -> 0.8733099 | K22: =K21/$T$4 -> 0.94963425
B23: 25-26 Churn | C23: #
B24: =(1-F21/S8) -> 0.15406065 | C24: =S8-F21 -> 442 | E24: 3rd Classical mailer drops 22nd/23rd of August | N24: Pops | S24: FY26 Budget - Pops
N25: 0.26 | O25: % of total subscriptions | S25: Units | T25: Revenue
O26: =O30/S30*S26 -> 240.07343 | P26: =P30/O30*O26 -> 69318.269 | Q26: =Q30/S30*S26 -> 1547.1399 | R26: =R30/Q30*Q26 -> 549681.73 | S26: =T26/(T30/S30) -> 1787.2133 | T26: 619000 | U26: Total
B27: FY26 Sales - Pops | O27: =O31/S31*S27 -> 3.2060949 | P27: =P31/O31*O27 -> 1038.7747 | Q27: =Q31/S31*S27 -> 109.00723 | R27: =R31/Q31*Q27 -> 44362.735 | S27: =T27/(T30/S30) -> 112.21332 | T27: =T26-T30 -> 38865 | U27: Difference vs FY25
C28: New | F28: Renewals | I28: Total | N28: FY25 Actuals - Pops
C29: Actual Units | D29: Proj | E29: Actual Rev | F29: Actual Units | G29: Proj | H29: Actual Rev | I29: Actual Units | J29: Proj | K29: Actual Rev | L29: W/W Change | O29: New Units | P29: New Revenue | Q29: Renewal Units | R29: Renewal Revenue | S29: Total Units | T29: Total Revenue | U29: Change
A30: Projected Total | I30: =I38 -> 1561 | K30: =K38 -> 591188 | N30: Final | O30: =O43 -> 225 | P30: =P43 -> 64966 | Q30: =Q43 -> 1450 | R30: =R43 -> 515169 | S30: =S43 -> 1675 | T30: =T43 -> 580135
A31: 1 | B31: 45747 | C31: 38 | D31: =C31/'Sales Pacing'!C3 -> 1048.1667 | E31: 13163 | F31: 636 | G31: =F31/'Sales Pacing'!F3 -> 5546.3927 | H31: 258782 | I31: =C31+F31 -> 674 | J31: =D31+G31 -> 6594.5593 | K31: =E31+H31 -> 271945 | N31: 45383 | O31: 2 | P31: 648 | Q31: 68 | R31: 27674 | S31: =O31+Q31 -> 70 | T31: =P31+R31 -> 28322
A32: 2 | B32: 45754 | C32: 44 | D32: =C32/'Sales Pacing'!C4 -> 606.83333 | E32: 14651 | F32: 785 | G32: =F32/'Sales Pacing'!F4 -> 3783.5789 | H32: 312531 | I32: =C32+F32 -> 829 | J32: =D32+G32 -> 4390.4122 | K32: =E32+H32 -> 327182 | L32: =IF(K32>0,K32-K31,0) -> 55237 | N32: =N31+7 -> 45390 | O32: 54 | P32: 17576 | Q32: 181 | R32: 68648 | S32: =O32+Q32 -> 235 | T32: =P32+R32 -> 86224 | U32: =IF(T32>0,T32-T31,0) -> 57902
A33: 3 | B33: 45761 | C33: 54 | D33: =C33/'Sales Pacing'!C5 -> 616.34483 | E33: 19061 | F33: 893 | G33: =F33/'Sales Pacing'!F5 -> 3135.2144 | H33: 353304 | I33: =C33+F33 -> 947 | J33: =D33+G33 -> 3751.5592 | K33: =E33+H33 -> 372365 | L33: =IF(K33>0,K33-K32,0) -> 45183 | N33: =N32+7 -> 45397 | O33: 66 | P33: 20302 | Q33: 283 | R33: 105425 | S33: =O33+Q33 -> 349 | T33: =P33+R33 -> 125727 | U33: =IF(T33>0,T33-T32,0) -> 39503
A34: 4 | B34: 45768 | C34: 60 | D34: =C34/'Sales Pacing'!C6 -> 484.39024 | E34: 20782 | F34: 1067 | G34: =F34/'Sales Pacing'!F6 -> 2921.075 | H34: 417996 | I34: =C34+F34 -> 1127 | J34: =D34+G34 -> 3405.4653 | K34: =E34+H34 -> 438778 | L34: =IF(K34>0,K34-K33,0) -> 66413 | N34: =N33+7 -> 45404 | O34: 86 | P34: 26557 | Q34: 389 | R34: 146108 | S34: =O34+Q34 -> 475 | T34: =P34+R34 -> 172665 | U34: =IF(T34>0,T34-T33,0) -> 46938
A35: 5 | B35: =B34+7 -> 45775 | C35: 118 | D35: =C35/'Sales Pacing'!C7 -> 566.05797 | E35: 38918 | F35: 1300 | G35: =F35/'Sales Pacing'!F7 -> 2887.9509 | H35: 502867 | I35: =C35+F35 -> 1418 | J35: =D35+G35 -> 3454.0088 | K35: =E35+H35 -> 541785 | L35: =IF(K35>0,K35-K34,0) -> 103007 | N35: =N34+7 -> 45411 | O35: 86 | P35: 26557 | Q35: 476 | R35: 178054 | S35: =O35+Q35 -> 562 | T35: =P35+R35 -> 204611 | U35: =IF(T35>0,T35-T34,0) -> 31946
A36: 6 | B36: =B35+7 -> 45782 | C36: 157 | D36: =C36/'Sales Pacing'!C8 -> 683.77632 | E36: 51765 | F36: 1358 | G36: =F36/'Sales Pacing'!F8 -> 2121.6398 | H36: 522161 | I36: =C36+F36 -> 1515 | J36: =D36+G36 -> 2805.4161 | K36: =E36+H36 -> 573926 | L36: =IF(K36>0,K36-K35,0) -> 32141 | N36: =N35+7 -> 45418 | O36: 98 | P36: 31472 | Q36: 806 | R36: 294720 | S36: =O36+Q36 -> 904 | T36: =P36+R36 -> 326192 | U36: =IF(T36>0,T36-T35,0) -> 121581
A37: 7 | B37: =B36+7 -> 45789 | C37: 165 | D37: =C37/'Sales Pacing'!C9 -> 593.6413 | E37: 54301 | F37: 1365 | G37: =F37/'Sales Pacing'!F9 -> 1717.375 | H37: 525805 | I37: =C37+F37 -> 1530 | J37: =D37+G37 -> 2311.0163 | K37: =E37+H37 -> 580106 | L37: =IF(K37>0,K37-K36,0) -> 6180 | N37: =N36+7 -> 45425 | O37: 113 | P37: 36672 | Q37: 1031 | R37: 372369 | S37: =O37+Q37 -> 1144 | T37: =P37+R37 -> 409041 | U37: =IF(T37>0,T37-T36,0) -> 82849
A38: 8 | B38: =B37+7 -> 45796 | C38: 199 | D38: =C38/'Sales Pacing'!C10 -> 639.50485 | E38: 65018 | F38: 1362 | G38: =F38/'Sales Pacing'!F10 -> 1532.8471 | H38: 526170 | I38: =C38+F38 -> 1561 | J38: =D38+G38 -> 2172.3519 | K38: =E38+H38 -> 591188 | L38: =IF(K38>0,K38-K37,0) -> 11082 | N38: =N37+7 -> 45432 | O38: 127 | P38: 40518 | Q38: 1267 | R38: 452816 | S38: =O38+Q38 -> 1394 | T38: =P38+R38 -> 493334 | U38: =IF(T38>0,T38-T37,0) -> 84293
A39: 9 | B39: =B38+7 -> 45803 | C39: 220 | D39: =C39/'Sales Pacing'!C11 -> 568.90625 | E39: 73218 | F39: 1368 | G39: =F39/'Sales Pacing'!F11 -> 1451.7935 | H39: 531352 | I39: =C39+F39 -> 1588 | J39: =D39+G39 -> 2020.6998 | K39: =E39+H39 -> 604570 | L39: =IF(K39>0,K39-K38,0) -> 13382 | N39: =N38+7 -> 45439 | O39: 160 | P39: 48485 | Q39: 1395 | R39: 497335 | S39: =O39+Q39 -> 1555 | T39: =P39+R39 -> 545820 | U39: =IF(T39>0,T39-T38,0) -> 52486
A40: 10 | B40: =B39+7 -> 45810 | C40: 239 | D40: =C40/'Sales Pacing'!C12 -> 557.10563 | E40: 80035 | F40: 1374 | G40: =F40/'Sales Pacing'!F12 -> 1439.2578 | H40: 536728 | I40: =C40+F40 -> 1613 | J40: =D40+G40 -> 1996.3634 | K40: =E40+H40 -> 616763 | L40: =IF(K40>0,K40-K39,0) -> 12193 | N40: =N39+7 -> 45446 | O40: 172 | P40: 51234 | Q40: 1411 | R40: 502695 | S40: =O40+Q40 -> 1583 | T40: =P40+R40 -> 553929 | U40: =IF(T40>0,T40-T39,0) -> 8109
A41: 11 | B41: =B40+7 -> 45817 | C41: 255 | D41: =C41/'Sales Pacing'!C13 -> 530.84906 | E41: 89633 | F41: 1407 | G41: =F41/'Sales Pacing'!F13 -> 1457.5735 | H41: 540393 | I41: =C41+F41 -> 1662 | J41: =D41+G41 -> 1988.4225 | K41: =E41+H41 -> 630026 | L41: =IF(K41>0,K41-K40,0) -> 13263 | N41: =N40+7 -> 45453 | O41: 187 | P41: 55826 | Q41: 1418 | R41: 505550 | S41: =O41+Q41 -> 1605 | T41: =P41+R41 -> 561376 | U41: =IF(T41>0,T41-T40,0) -> 7447
A42: 12 | B42: =B41+7 -> 45824 | C42: 270 | D42: =C42/'Sales Pacing'!C14 -> 470.36842 | E42: 90711 | F42: 1383 | G42: =F42/'Sales Pacing'!F14 -> 1420.054 | H42: 543160 | I42: =C42+F42 -> 1653 | J42: =D42+G42 -> 1890.4224 | K42: =E42+H42 -> 633871 | L42: =IF(K42>0,K42-K41,0) -> 3845 | N42: =N41+7 -> 45460 | O42: 193 | P42: 57355 | Q42: 1434 | R42: 510568 | S42: =O42+Q42 -> 1627 | T42: =P42+R42 -> 567923 | U42: =IF(T42>0,T42-T41,0) -> 6547
A43: 13+ | B43: 45922 | C43: 377 | D43: =C43/'Sales Pacing'!C15 -> 377 | E43: 117930 | F43: 1409 | G43: =F43/'Sales Pacing'!F15 -> 1409 | H43: 544870 | I43: =C43+F43 -> 1786 | J43: =D43+G43 -> 1786 | K43: =E43+H43 -> 662800 | L43: =IF(K43>0,K43-K42,0) -> 28929 | N43: Rest of Season | O43: 225 | P43: 64966 | Q43: 1450 | R43: 515169 | S43: =O43+Q43 -> 1675 | T43: =P43+R43 -> 580135 | U43: =IF(T43>0,T43-T42,0) -> 12212
I44: vs. FY26 Goal | J44: =J43/$S$26 -> 0.99932111 | K44: =K43/$T$26 -> 1.0707593
B45: 25-26 Churn | C45: #
B46: =(1-F43/S30) -> 0.15880597 | C46: =S30-F43 -> 266
A48: Future Improvements:
A49: Give true renewal rates
A50: Show renewals by customer cohort
A51: Add Family subscriptions (2%)

Sheet Summary (Draft)
B2: Overall Season | G2: # Tickets Sold | H2: Projected Tickets Sold | I2: Projected Occupancy (% +GYR) | J2: Total Revenue | K2: BUDGET | L2: Projected Revenue vs Budget (% +GYR)
B3: ALL CONCERTS | G3: ='Performances by Week'!I126 -> 0 | H3: ='Performances by Week'!J126 -> 0 | I3: ='Performances by Week'!K126 -> 0 | J3: ='Performances by Week'!M126 -> 0 | K3: ='Performances by Week'!O126 -> 6268640 | L3: ='Performances by Week'!Q126
B5: Season Attendance By Ticket Type | G5: # Tickets Sold | H5: Projected Tickets Sold | J5: Total Revenue | K5: BUDGET | L5: Projected Revenue vs Budget (% +GYR)
B6: All Subscriptions | G6: ='Performances by Week'!AA126 -> 0 | J6: ='Performances by Week'!AB126 -> 0 | K6: ='Performances by Week'!AC126 -> 2169893 | L6: ='Performances by Week'!AD126
B7: All Single Tickets | G7: ='Performances by Week'!#REF! -> #REF! | H7: ='Performances by Week'!U126 -> #REF! | J7: ='Performances by Week'!W126 -> 0 | K7: ='Performances by Week'!X126 -> 3973690 | L7: ='Performances by Week'!Z126
B9: Concert Attendance By Performance Type | G9: # Tickets Sold | H9: Projected Tickets Sold | I9: Projected Occupancy (% +GYR) | J9: Total Revenue | K9: BUDGET | L9: Projected Revenue vs Budget (% +GYR)
B10: CLASSICAL TRADITIONAL TOTAL | G10: ='Performances by Week'!I119 -> 0 | H10: ='Performances by Week'!J119 -> 0 | I10: ='Performances by Week'!K119 -> 0 | J10: ='Performances by Week'!M119 -> 0 | K10: ='Performances by Week'!O119 -> 2139000 | L10: ='Performances by Week'!Q119
B11: SYMPHONIC PIAZZA TOTAL | G11: ='Performances by Week'!I120 -> 0 | H11: ='Performances by Week'!J120 -> 0 | I11: ='Performances by Week'!K120 -> 0 | J11: ='Performances by Week'!M120 -> 0 | K11: ='Performances by Week'!O120 -> 363000 | L11: ='Performances by Week'!Q120
B12: POPS TOTAL | G12: ='Performances by Week'!I121 -> 0 | H12: ='Performances by Week'!J121 -> 0 | I12: ='Performances by Week'!K121 -> 0 | J12: ='Performances by Week'!M121 -> 0 | K12: ='Performances by Week'!O121 -> 1457000 | L12: ='Performances by Week'!Q121
B13: FAMILY SERIES TOTAL | G13: ='Performances by Week'!I122 -> 0 | H13: ='Performances by Week'!J122 -> 0 | I13: ='Performances by Week'!K122 -> 0 | J13: ='Performances by Week'!M122 -> 0 | K13: ='Performances by Week'!O122 -> 525950 | L13: ='Performances by Week'!Q122
B14: FILM TOTAL | G14: ='Performances by Week'!I123 -> 0 | H14: ='Performances by Week'!J123 -> 0 | I14: ='Performances by Week'!K123 -> 0 | J14: ='Performances by Week'!M123 -> 0 | K14: ='Performances by Week'!O123 -> 1745490 | L14: ='Performances by Week'!Q123
B15: ON STAGE CONCERTS TOTAL | G15: ='Performances by Week'!I124 -> 0 | H15: ='Performances by Week'!J124 -> 0 | I15: ='Performances by Week'!K124 -> 0 | J15: ='Performances by Week'!M124 -> 0 | K15: ='Performances by Week'!O124 -> 38200 | L15: ='Performances by Week'!Q124
B16: OTHER CONCERT TOTAL | G16: ='Performances by Week'!I125 -> 0 | H16: ='Performances by Week'!J125 -> 0 | I16: ='Performances by Week'!K125 -> 0 | J16: ='Performances by Week'!M125 -> 0 | K16: ='Performances by Week'!O125 -> 0 | L16: ='Performances by Week'!Q125

Sheet Sub Graphs
A16: Notes: | B16: FY19 was pre-COVID
B17: FY24 was -35% vs FY19, but also Michael Stern's final season so perhaps a one-time boost
B18: FY25 was -47% vs FY19 and -19% vs FY24
B19: FY26 is -4% vs FY25
B20: For FY27, it is important to start sales no later than Week 5 (coordinate with season anouncement) and understand how to boost renewal rate
J27: Notes: | K27: FY19 was pre-COVID
K28: FY24 was -19% vs FY19, but also Michael Stern's final season so perhaps a one-time boost
K29: FY25 was -29% vs FY19 and -12% vs FY24
K30: FY26 is +7% vs FY25, driven by growth in new subs
K31: For FY27, it is important to start sales no later than Week 5 and understand how to continue new sub growth

Sheet Channels (Draft)
A1: MARKETING CHANNEL PERFORMANCE
B2: Owned Marketing Channels | H2: Paid Channels
A3: To start, let’s pull last 12 months of data. | B3: Phone | C3: Direct Mail | D3: Email | E3: Social | F3: In-hall | G3: SEO | H3: SEM | I3: Media | J3: Phone | K3: Total
B4: (Box Office) | E4: (FB, IG, X, other) | F4: (book, posters) | I4: (TV, radio, OOH) | J4: (Bennett)
A5: # Impressions: | D5: 13.7M
A6: calls made, e/mails delivered, etc.
A7: # Engagement: | D7: 4.7M
A8: calls answered, opens, etc.
A9: Engagement rate | D9: 34%
A10: # Actions (Success): | D10: 89k
A11: conversations, clicks, etc.
A12: Action rate | D12: 0.6%
A13: % of total Actions
A15: Channel cost ($, time)
A16: ROI: $/Action
A17: Attributed revenue ($) | J17: ~$220k
A18: ROI: $/channel cost
A20: SALES CHANNEL PERFORMANCE
A21: To start, let’s pull last 12 months of data. | B21: Phone | C21: Website | D21: KCPA | E21: Total
B22: (Box Office)
A23: # Traffic: | C23: 471,563
A24: calls received, visits
A25: % Traffic by Marketing Channel
A26: #, $ Conversions (Success): | C26: 4,547
A27: Conversion rate | C27: 0.94%
A28: % of total Conversions | D28: 15%?
A29: Total Sales Revenue | B29: ~$6,500k? | C29: $877k
A31: Channel cost ($, time)
A32: ROI: $/Conversion
A33: Attributed revenue ($)
A34: ROI: $/channel cost
A36: EXPERIENCE CHANNEL PERFORMANCE
B37: Total
A38: # total attendance
A39: % Repeat:
A40: % returning from prior season
A41: # Frequency:
A42: avg. attendance/customer
A44: Total Revenue, ROI?
A45: Avg. CSAT, NPS
A46: Avg. CLV/attendee
A47: # high CLV VIPs

Sheet Sales Pacing
B1: New Subs | E1: Renewal Subs
A2: # Weeks On Sale | B2: Classical | C2: Pops | E2: Classical | F2: Pops
A3: 1 | B3: 0.042056075 | C3: 0.036253776 | E3: 0.25267149 | F3: 0.11466913
A4: 2 | B4: 0.060747664 | C4: 0.072507553 | E4: 0.3160979 | F4: 0.20747552
A5: 3 | B5: 0.10981308 | C5: 0.087613293 | E5: 0.39296794 | F5: 0.28482901
A6: 4 | B6: 0.12850467 | C6: 0.12386707 | E6: 0.47604274 | F6: 0.36527648
A7: 5 | B7: 0.1635514 | C7: 0.20845921 | E7: 0.57014822 | F7: 0.45014616
A8: 6 | B8: 0.22663551 | C8: 0.22960725 | E8: 0.72147535 | F8: 0.64007095
A9: 7 | B9: 0.30140187 | C9: 0.27794562 | E9: 0.90486039 | F9: 0.79481765
A10: 8 | B10: 0.35046729 | C10: 0.31117825 | E10: 0.93864185 | F10: 0.88854264
A11: 9 | B11: 0.39485981 | C11: 0.38670695 | E11: 0.95001724 | F11: 0.94228277
A12: 10 | B12: 0.43691589 | C12: 0.42900302 | E12: 0.96242675 | F12: 0.95465872
A13: 11 | B13: 0.46962617 | C13: 0.48036254 | E13: 0.96552913 | F13: 0.96530297
A14: 12 | B14: 0.50700935 | C14: 0.57401813 | E14: 0.96863151 | F14: 0.97390663
A15: 13+ | B15: 1 | C15: 1 | E15: 1 | F15: 1
B21: Single Tickets
A22: # Weeks Until Performance | B22: Classical | C22: Pops | D22: Specials | E22: Other
A23: 0 | B23: 1 | C23: 1 | D23: 1 | E23: 1
A24: 1 | B24: 0.59 | C24: 0.59 | D24: 0.59 | E24: 0.59
A25: 2 | B25: 0.46 | C25: 0.46 | D25: 0.46 | E25: 0.46
A26: 3 | B26: 0.39 | C26: 0.39 | D26: 0.39 | E26: 0.39
A27: 4 | B27: 0.33 | C27: 0.33 | D27: 0.33 | E27: 0.33
A28: 5 | B28: 0.3 | C28: 0.3 | D28: 0.3 | E28: 0.3
A29: 6 | B29: 0.27 | C29: 0.27 | D29: 0.27 | E29: 0.27
A30: 7 | B30: 0.24 | C30: 0.24 | D30: 0.24 | E30: 0.24
A31: 8 | B31: 0.21 | C31: 0.21 | D31: 0.21 | E31: 0.21
A32: 9 | B32: 0.18 | C32: 0.18 | D32: 0.18 | E32: 0.18
A33: 10 | B33: 0.15 | C33: 0.15 | D33: 0.15 | E33: 0.15
A34: 11
A35: 12
A36: 13+
A38: Future Improvements:
A39: Extend data for single ticket sales beyond 6 weeks
A40: Differentiate single ticket sales by performance type
A41: Improve pacing data (always)

Sheet Email Reporting
A1: EMAILS SENT | B1: DELIVERIES | C1: OPENS | D1: CLICK RATE
A2: 9/21 Journey KBYG SUN | B2: 348 | C2: 258 (74.1%) | D2: 103 (29.6%) | J2: AVERAGE OPEN RATE: | K2: 0.37
A3: 9/20 Journey KBYG SAT | B3: 398 | C3: 287 (72.1%) | D3: 104 (26.1%) | J3: AVERAGE CLICK RATE: | K3: 0.02
A4: 9/19 Journey KBYG FRI | B4: 417 | C4: 289 (69.3%) | D4: 101 (24.2%)
A5: 9/18 90s Standalone Email | B5: 95170 | C5: 33,599 (35.3%) | D5: 341 (0.4%)
A6: 9/16 Weekly Concert Promo | B6: 93715 | C6: 34,837 (37.2%) | D6: 729 (0.8%)
A7: 9/15 CS2 Standalone Email | B7: 93796 | C7: 34,769 (37.1%) | D7: 342 (0.4%)
A8: 9/10 Journey Giveaway | B8: 95517 | C8: 34,249 (35.9%) | D8: 751 (1%)
A9: 9/9 Weekly Concert Promo | B9: 93965 | C9: 35,513 (37.8%) | D9: 780 (1%)
A10: 9/5 CS1 BOGO Pops Buyers | B10: 4488 | C10: 2,377 (53%) | D10: 100 (2.2%) - 33 respond (98 tickets)
A11: 9/5 CS1 Morgan Freeman Buyers | B11: 1008 | C11: 588 (58.3%) | D11: 33 (3.3%) - 33 respond (98 tickets)
A12: 9/4 CS1 Matthias Video | B12: 95604 | C12: 35,461 (37.1%) | D12: 1,460 (1.5%)
A13: 9/4 Journey BOGO Promo | B13: 2721 | C13: 1,164 (42.8%) | D13: 54 (2%) - 15 respond (41 tickets)
A14: 9/3 Morgan Freeman KBYG | B14: 376 | C14: 306 (81.4%) | D14: 129 (34.3%)
A15: 9/2 Morgan Freeman KBYG | B15: 426 | C15: 354 (83.1%) | D15: 152 (35.7%)
... A18: 8/20 Bi-weekly Merchandise Email | B18: 95473 | C18: 35,125 (37%) | D18: 754 (1%)
A19: 8/12 Music of Journey Promo | B19: 94241 | C19: 35,743 (37.9%) | D19: 577 0.6% | E19: https://conta.cc/4mdHLVC
A20: 8/6 Bi-weekly Merchandise Email | B20: 94322 | C20: 36,401 (38.6%) | D20: 937 (1%) | E20: https://conta.cc/3Hoy3k2
A21: 7/21 La Nuit Sombre Matthias Video | B21: 95893 | C21: 35,531 (37.1%) | D21: 491 (0.5%)
A22: 7/23 Morgan Freeman Promo | B22: 96012 | C22: 35,064 (36.5%) | D22: 769 (0.8%)
A23: 7/15 Single Ticket On Sale Announcement | B23: 95831 | C23: 35,285 (37.2%) | D23: 1,708 (2%)
A24: 7/8 Leslie Odom Jr. Promo | B24: 94927 | C24: 35, 660 (37.6%) | D24: 550 (0.6%)
A25: Tuesday 7/1 Holiday Presentations On Sale | B25: 95059 | C25: 35039 (36.9%) | D25: 822 (0.9%) | E25: Header: 64, Elf in Concert: 473, Handel's Messiah: 390, LOJ: 110, Christmas Festival: 144, Wonderful Life: 129
A26: Tuesday 6/25 Special Presentations On Sale | B26: 95219 | C26: 35,617 (37%) | D26: 1,469 (2%) | E26: Full lineup: 248, Morgan Freeman: 438, Chicken Fried: 456, Top Gun: 559, Lodger: 100, Indiana Jones: 204, Chris Thile: 134, Harry Potter: 139, Final Symphony: 74, Ben Rector: 108, On Stage George: 45, On Stage Leila: 53, On Stage Gil: 37, On Stage 38
A27: Tuesday 6/17 Mark Your Calendar | B27: 104371 | C27: 37,343 (39%) | D27: 1,999 (2%)
A28: Monday 6/9 Mobile Music Box June Concert | B28: 95,460 | C28: 36,052 (38%) | D28: 594 (1%)
A29: Wednesday 6/4 CS14 Student Rush Promo | B29: 174 | C29: 77 (44%) | D29: 0
A30: Wednesday 6/4 CS14 Student Rush Promo | B30: 174 | C30: 77 (44%) | D30: 0
A31: Wednesday 6/4 CS14 Student Pass Promo | B31: 80 | C31: 38 (47%) | D31: 1
A32: Wednesday 6/4 CS14 BOGO Promo | B32: 4954 | C32: 2,165 (44%) | D32: 65 (1%)
A33: Wednesday 6/4 Four Larks Subscriber Early Access | B33: 2185 | C33: 1,452 (66.5%) | D33: 135 (6.2%)
A34: Friday 6/6 Four Lark Public On-Sale | B34: 96846 | C34: 35,136 (36%) | D34: 616 (0.6%)

Sheet Social Reporting
A1: DATE | B1: Social Post | C1: Views | D1: Engagement
A2: 45919 | B2: CS2 Graphic FB | C2: 1.6K reach | D2: 13 interactions
A3: 45919 | B3: CS2 Graphic IG | C3: 682 reach | D3: 13 interactions
A4: 45918 | B4: Orchestra Games Reel FB | C4: 1.2K reach | D4: 16 interactions
A5: 45918 | B5: Orchestra Games Reel IG | C5: 707 reach | D5: 31 interactions
A6: 45917 | B6: CS1 Graphic FB | C6: 1.7K reach | D6: 16 interactions
A7: 45917 | B7: CS1 Graphic IG | C7: 611 reach | D7: 22 interactions
A8: 45916 | B8: Journey musician feature IG | C8: 779 reach | D8: 17 interactions
A9: 45916 | B9: Journey musician feature FB | C9: 763 reach | D9: 12 interactions
A10: 45915 | B10: 90s Graphic FB | C10: 1.5K reach | D10: 7 interactions
A11: 45915 | B11: 90s Graphic IG | C11: 1.1K reach | D11: 18 interactions
A12: 45913 | B12: CS1 Mike G reel FB | C12: 2.7K reach | D12: 60 interactions
A13: 45913 | B13: CS1 Mike G reel IG | C13: 1.2K reach | D13: 51 interactions
... A25: 45902 | B25: KC Star Matthias article reshare FB | C25: 1.7K reach | D25: 42 interactions
A27: DATE | B27: Meta Ads | C27: Views | D27: Engagement
A28: 9/12-9/25 | B28: Top Gun Ad | C28: 83,913 reach, 154,220 impressions | D28: 3,352 link clicks
A29: 9/18-10/2 | B29: 90s Mixtape Ad | C29: 31,593 reach, 53,149 impressions | D29: 718 link clicks
A30: 9/4 - 9/18 | B30: CS1 Video Ad | C30: 33,438 reach, 63,806 impressions | D30: 2,410 link clicks
A40: 45898 | B40: Chicken Fried Rock FB Reel | C40: 1.4K reach | D40: 13 interactions, 2 shares
A41: 45898 | B41: Chicken Fried Rock IG Reel | C41: 1.1K reach | D41: 42 interactions, 3 shares
A42: 45897 | B42: ProAm post FB | C42: 3.7K reach | D42: 24 interactions, 13 shares
A43: 45897 | B43: ProAm post IG | C43: 1.3K reach | D43: 35 interactions, 6 shares
A44: 45896 | B44: MMB FB Reel | C44: 1.3K reach | D44: 16 interactions
A45: 45896 | B45: MMB IG Reel | C45: 1.1K reach | D45: 32 interactions
A46: 45895 | B46: New musician welcome FB | C46: 14.9K reach | D46: 223 interactions, 26 comments, 10 shares
A47: 45895 | B47: New musician welcome IG | C47: 9.1K reach | D47: 515 interactions, 7 comments, 64 shares
A48: 45891 | B48: Chicken Fried IG | C48: 1625 | D48: 11 interactions
A49: 45891 | B49: Chicken Fried FB | C49: 2570 | D49: 15 interactions, 6 link clicks
A50: 45890 | B50: Journey Reel IG | C50: 1005 | D50: 16 interactions
A51: 45890 | B51: Journey Reel FB | C51: 813 | D51: 12 interactions
A52: 45883 | B52: KC Blues Society Video IG | C52: 966 | D52: 32 interactions
A53: 45883 | B53: KC Blues Society Video FB | C53: 1895 | D53: 19 interactions, 61 link clicks
A54: 45881 | B54: CS1 Nora Video IG | C54: 3290 | D54: 42 interactions
A55: 45881 | B55: CS1 Nora Video FB | C55: 1785 | D55: 42 interactions
A56: 45876 | B56: Orchestra Games IG | C56: 2394 | D56: 54 interactions
A57: 45876 | B57: Orchestra Games FB | C57: 1879 | D57: 15 interactions, 2 link clicks
A58: 45876 | B58: Morgan Freeman interview reshare FB | C58: 2731 | D58: 52 interactions, 53 link clicks
A59: 45875 | B59: Nora Intro IG | C59: 3331 | D59: 65 interactions
... A84: 45856 | B84: Music is for Everyone YT | C84: 32 | D84: 1 interaction
B86: Meta Ads
A87: 45832 | B87: Specials/Films ad | C87: 1k impressions | D87: 18 clicks
A88: 45838 | B88: Morgan Freeman video | C88: 22k impressions | D88: 1234 link clicks
A89: 45841 | B89: Holiday concerts ad | C89: 68k impressions | D89: 1011 link clicks

Sheet Website Reporting
A1: Timeframe: August 11-18
A2: ECOMMERCE PURCHASES: 877 | B2: WEBSITE REVENUE: $74,429 | C2: # OF ITEMS
A3: Morgan Freeman | B3: 18052 | C3: 164
A4: Music of Journey | B4: 8322 | C4: 66
A5: Top Gun | B5: 7065 | C5: 86
A6: Leslie Odom Jr. | B6: 4084.5 | C6: 54
A7: Indiana Jones | B7: 3441 | C7: 38
A8: Elf in Concert | B8: 2892 | C8: 44
A9: Harry Potter | B9: 2521 | C9: 29
A10: It's a wonderful life | B10: 2454 | C10: 52
A12: Timeframe: July 20-July 28
A13: ECOMMERCE PURCHASES: 973 | B13: WEBSITE REVENUE: $67,220 | C13: # OF ITEMS
A14: Leslie Odom Jr. | B14: 17681 | C14: 161
A15: Morgan Freeman | B15: 7995 | C15: 64
A16: Top Gun | B16: 5293 | C16: 64
A17: 2025/26 COY Package | B17: 4084 | C17: 54
A18: It's a wonderful life | B18: 2684 | C18: 31
A19: Elf in Concert | B19: 2343 | C19: 26
A20: Christmas Festival | B20: 2341 | C20: 38
A21: La nuit sombre | B21: 2308 | C21: 49
A22: Harry Potter 2 | B22: 2030 | C22: 26
A23: Indiana Jones | B23: 2004 | C23: 26
A27: Timeframe: July 20-July 28
A28: ECOMMERCE PURCHASES: 1,718 | B28: WEBSITE REVENUE: $115,644 | C28: # OF ITEMS
A29: Morgan Freeman | B29: 27675 | C29: 215
A30: Top Gun | B30: 9650 | C30: 116
A31: It's a wonderful life | B31: 8677 | C31: 104
A32: Leslie Odom Jr. | B32: 9110 | C32: 84
A33: Elf in Concert | B33: 5110 | C33: 80
A34: 2025/26 COY Package | B34: 5435 | C34: 73
A35: Harry Potter 2 | B35: 5145 | C35: 61
A36: 2025/26 Sunday Masterworks | B36: 4200 | C36: 56
A37: Handel's Messiah | B37: 2970 | C37: 55
A43: Timeframe: July 14-July 20
A44: ECOMMERCE PURCHASES: 3,027 | B44: WEBSITE REVENUE: $188,688 | C44: # OF ITEMS
A45: Top Gun | B45: 19205 | C45: 234
A46: Morgan Freeman | B46: 16175 | C46: 130
A47: Leslie Odom Jr. | B47: 14107 | C47: 139
A48: Indiana Jones | B48: 12729 | C48: 186
A49: Billy Joel + Elton John | B49: 11391 | C49: 149
A50: Elf | B50: 11075 | C50: 168
A51: Harry Potter | B51: 10715 | C51: 155
A52: It's a wonderful life | B52: 9126 | C52: 129
A53: Music of Journey | B53: 6150 | C53: 91
A54: Ben Rector | B54: 6140 | C54: 60
A56: Traffic Acquistion
A57: SOURCE | B57: SESSIONS
A58: Organic Search
A59: Direct
A60: Paid Social
A61: Referral
A62: Organic Social

Sheet Grassroots Flyer Locations
A1: MF Location | B1: MF Staff Member | C1: Date Posted | E1: CF Location | F1: CF Staff Member | G1: Date Posted | I1: Fam Location | J1: Fam Staff Member | K1: Date Posted
A2: Mildreds (NO CORKBOARD)
A3: Pizza Shuttle | B3: Stephen, Sarah and Adeca | C3: 45870
A4: The Bauer Gallery | B4: Stephen, Sarah and Adeca | C4: 45870
A5: Bizz and Weezy's | B5: Stephen, Sarah and Adeca | C5: 45870
A6: The Sewing Labs | B6: Sarah | C6: 45875
A7: Filling Station - Midtown | B7: Hannah | C7: 45875
A8: Good Karma Coffee Shop | B8: Hannah | C8: 45875

Sheet Board
M1: Revised 9.17.25
A3: TICKET SALES REPORT as of 9/17/2025 | E3: SINGLE TICKETS | I3: SUBSCRIPTION TICKETS | L3: TOTAL SALES (Singles + Subs) | O3: Hall Data
A4: SERIES | D4: DATE(S) | E4: BUDGET | F4: ACTUAL | G4: VS. BUDGET | H4: # SOLD | I4: BUDGET | J4: ACTUAL | K4: # SOLD | L4: BUDGET | M4: ACTUAL | N4: # SOLD | O4: CAP | P4: CAP SOLD | Q4: ATP
A5: CLASSICAL TRADITIONAL
A6: CS1 | B6: Appalachian Spring | D6: Oct 10-12 | E6: =SUM('Performances by Week'!Y15:Y17) -> 49998 | F6: =SUM('Performances by Week'!X15:X17) -> 62111 | G6: =F6-E6 -> 12113 | H6: =SUM('Performances by Week'!S15:S17) -> 1111 | I6: =SUM('Performances by Week'!AD15:AD17) -> 100000 | J6: =SUM('Performances by Week'!AC15:AC17) -> 111230.7 | K6: =SUM('Performances by Week'!AB15:AB17) -> 1678 | L6: =SUM(E6,I6) -> 149998 | M6: =SUM(F6,J6) -> 173341.7 | N6: =SUM(H6,K6) -> 2789 | O6: =SUM('Performances by Week'!AF15:AF17) -> 4299 | P6: =N6/O6 -> 0.64875552 | Q6: =M6/N6 -> 62.151918
A7: CS2 | B7: Rachmaninoff Cele Pt 1 (SP) | D7: Oct 31-Nov 2 | E7: =SUM('Performances by Week'!Y26:Y28) -> 85000 | F7: =SUM('Performances by Week'!X26:X28) -> 50990 | G7: =F7-E7 -> -34010 | H7: =SUM('Performances by Week'!S26:S28) -> 899 | I7: =SUM('Performances by Week'!AD26:AD28) -> 140000 | J7: =SUM('Performances by Week'!AC26:AC28) -> 96474.1 | K7: =SUM('Performances by Week'!AB26:AB28) -> 1461 | L7: =SUM(E7,I7) -> 225000 | M7: =SUM(F7,J7) -> 147464.1 | N7: =SUM(H7,K7) -> 2360 | O7: =SUM('Performances by Week'!AF26:AF28) -> 4299 | P7: =N7/O7 -> 0.54896488 | Q7: =M7/N7 -> 62.484788
A8: CS3 | B8: Matthias and Mahler (SP) | D8: Nov 21-23 | E8: =SUM('Performances by Week'!Y31:Y33) -> 38000 | F8: =SUM('Performances by Week'!X31:X33) -> 18613 | G8: =F8-E8 -> -19387 | H8: =SUM('Performances by Week'!S31:S33) -> 311 | I8: =SUM('Performances by Week'!AD31:AD33) -> 135000 | J8: =SUM('Performances by Week'!AC31:AC33) -> 105210.1 | K8: =SUM('Performances by Week'!AB31:AB33) -> 1572 | L8: =SUM(E8,I8) -> 173000 | M8: =SUM(F8,J8) -> 123823.1 | N8: =SUM(H8,K8) -> 1883 | O8: =SUM('Performances by Week'!AF31:AF33) -> 4770 | P8: =N8/O8 -> 0.39475891 | Q8: =M8/N8 -> 65.758417
A9: CS4 | B9: Brahms' Fourth Symphony | D9: Jan 9-11 | E9: =SUM('Performances by Week'!Y52:Y54) -> 64998 | F9: =SUM('Performances by Week'!X52:X54) -> 8795 | G9: =F9-E9 -> -56203 | H9: =SUM('Performances by Week'!S52:S54) -> 159 | I9: =SUM('Performances by Week'!AD52:AD54) -> 100000 | J9: =SUM('Performances by Week'!AC52:AC54) -> 111577.5 | K9: =SUM('Performances by Week'!AB52:AB54) -> 1701 | L9: =SUM(E9,I9) -> 164998 | M9: =SUM(F9,J9) -> 120372.5 | N9: =SUM(H9,K9) -> 1860 | O9: =SUM('Performances by Week'!AF52:AF54) -> 4770 | P9: =N9/O9 -> 0.38993711 | Q9: =M9/N9 -> 64.716398
A10: CS5 | B10: Pines of Rome & Bruch (SP) | D10: Jan 16-18 | E10: =SUM('Performances by Week'!Y55:Y57) -> 70000 | F10: =SUM('Performances by Week'!X55:X57) -> 16249 | G10: =F10-E10 -> -53751 | H10: =SUM('Performances by Week'!S55:S57) -> 270 | I10: =SUM('Performances by Week'!AD55:AD57) -> 140000 | J10: =SUM('Performances by Week'!AC55:AC57) -> 104865.1 | K10: =SUM('Performances by Week'!AB55:AB57) -> 1576 | L10: =SUM(E10,I10) -> 210000 | M10: =SUM(F10,J10) -> 121114.1 | N10: =SUM(H10,K10) -> 1846 | O10: =SUM('Performances by Week'!AF55:AF57) -> 4770 | P10: =N10/O10 -> 0.3870021 | Q10: =M10/N10 -> 65.608938
A11: CS6 | B11: Beethoven+ (SP) | D11: Jan 30-Feb 1 | E11: =SUM('Performances by Week'!Y62:Y64) -> 64000 | F11: =SUM('Performances by Week'!X62:X64) -> 14060 | G11: =F11-E11 -> -49940 | H11: =SUM('Performances by Week'!S62:S64) -> 237 | I11: =SUM('Performances by Week'!AD62:AD64) -> 140000 | J11: =SUM('Performances by Week'!AC62:AC64) -> 103801.1 | K11: =SUM('Performances by Week'!AB62:AB64) -> 1571 | L11: =SUM(E11,I11) -> 204000 | M11: =SUM(F11,J11) -> 117861.1 | N11: =SUM(H11,K11) -> 1808 | O11: =SUM('Performances by Week'!AF62:AF64) -> 4770 | P11: =N11/O11 -> 0.37903564 | Q11: =M11/N11 -> 65.188662
A12: CS7 | B12: Prokofiev's Fifth Symphony | D12: Feb 6-8 | E12: =SUM('Performances by Week'!Y66:Y68) -> 39999 | F12: =SUM('Performances by Week'!X66:X68) -> 6940 | G12: =F12-E12 -> -33059 | H12: =SUM('Performances by Week'!S66:S68) -> 155 | I12: =SUM('Performances by Week'!AD66:AD68) -> 100000 | J12: =SUM('Performances by Week'!AC66:AC68) -> 109967.3 | K12: =SUM('Performances by Week'!AB66:AB68) -> 1683 | L12: =SUM(E12,I12) -> 139999 | M12: =SUM(F12,J12) -> 116907.3 | N12: =SUM(H12,K12) -> 1838 | O12: =SUM('Performances by Week'!AF66:AF68) -> 4770 | P12: =N12/O12 -> 0.38532495 | Q12: =M12/N12 -> 63.605713
A13: CS8 | B13: Saint-Saëns & Strauss | D13: Mar 13-15 | E13: =SUM('Performances by Week'!Y79:Y81) -> 54999 | F13: =SUM('Performances by Week'!X79:X81) -> 10846 | G13: =F13-E13 -> -44153 | H13: =SUM('Performances by Week'!S79:S81) -> 190 | I13: =SUM('Performances by Week'!AD79:AD81) -> 110000 | J13: =SUM('Performances by Week'!AC79:AC81) -> 111505.3 | K13: =SUM('Performances by Week'!AB79:AB81) -> 1708 | L13: =SUM(E13,I13) -> 164999 | M13: =SUM(F13,J13) -> 122351.3 | N13: =SUM(H13,K13) -> 1898 | O13: =SUM('Performances by Week'!AF79:AF81) -> 4770 | P13: =N13/O13 -> 0.39790356 | Q13: =M13/N13 -> 64.463277
A14: CS9 | B14: Midsummer Night's Dream (SP) | D14: Apr 10-12 | E14: =SUM('Performances by Week'!Y89:Y91) -> 70000 | F14: =SUM('Performances by Week'!X89:X91) -> 10472 | G14: =F14-E14 -> -59528 | H14: =SUM('Performances by Week'!S89:S91) -> 219 | I14: =SUM('Performances by Week'!AD89:AD91) -> 130000 | J14: =SUM('Performances by Week'!AC89:AC91) -> 98992.1 | K14: =SUM('Performances by Week'!AB89:AB91) -> 1505 | L14: =SUM(E14,I14) -> 200000 | M14: =SUM(F14,J14) -> 109464.1 | N14: =SUM(H14,K14) -> 1724 | O14: =SUM('Performances by Week'!AF89:AF91) -> 4299 | P14: =N14/O14 -> 0.40102349 | Q14: =M14/N14 -> 63.494258
A15: CS10 | B15: Farrenc/Dvorak/Schuman | D15: Apr 17-19 | E15: =SUM('Performances by Week'!Y92:Y94) -> 39999 | F15: =SUM('Performances by Week'!X92:X94) -> 4229 | G15: =F15-E15 -> -35770 | H15: =SUM('Performances by Week'!S92:S94) -> 103 | I15: =SUM('Performances by Week'!AD92:AD94) -> 100000 | J15: =SUM('Performances by Week'!AC92:AC94) -> 119099.1 | K15: =SUM('Performances by Week'!AB92:AB94) -> 1789 | L15: =SUM(E15,I15) -> 139999 | M15: =SUM(F15,J15) -> 123328.1 | N15: =SUM(H15,K15) -> 1892 | O15: =SUM('Performances by Week'!AF92:AF94) -> 4770 | P15: =N15/O15 -> 0.3966457 | Q15: =M15/N15 -> 65.183985
A16: CS11 | B16: Grieg's Piano Concerto (SP) | D16: May 8-10 | E16: =SUM('Performances by Week'!Y97:Y99) -> 55000 | F16: =SUM('Performances by Week'!X97:X99) -> 11439 | G16: =F16-E16 -> -43561 | H16: =SUM('Performances by Week'!S97:S99) -> 208 | I16: =SUM('Performances by Week'!AD97:AD99) -> 120000 | J16: =SUM('Performances by Week'!AC97:AC99) -> 105674.1 | K16: =SUM('Performances by Week'!AB97:AB99) -> 1585 | L16: =SUM(E16,I16) -> 175000 | M16: =SUM(F16,J16) -> 117113.1 | N16: =SUM(H16,K16) -> 1793 | O16: =SUM('Performances by Week'!AF97:AF99) -> 4770 | P16: =N16/O16 -> 0.37589099 | Q16: =M16/N16 -> 65.316843
A17: CS12 | B17: Gil Shaham Plays Brahm's 4th | D17: May 29-31 | E17: =SUM('Performances by Week'!Y107:Y109) -> 60000 | F17: =SUM('Performances by Week'!X107:X109) -> 6544 | G17: =F17-E17 -> -53456 | H17: =SUM('Performances by Week'!S107:S109) -> 162 | I17: =SUM('Performances by Week'!AD107:AD109) -> 95000 | J17: =SUM('Performances by Week'!AC107:AC109) -> 112084.5 | K17: =SUM('Performances by Week'!AB107:AB109) -> 1713 | L17: =SUM(E17,I17) -> 155000 | M17: =SUM(F17,J17) -> 118628.5 | N17: =SUM(H17,K17) -> 1875 | O17: =SUM('Performances by Week'!AF107:AF109) -> 4770 | P17: =N17/O17 -> 0.39308176 | Q17: =M17/N17 -> 63.268533
A18: CS13 | B18: Rachmaninoff Cele Pt 2 | D18: Jun 5-7 | E18: =SUM('Performances by Week'!Y111:Y113) -> 90000 | F18: =SUM('Performances by Week'!X111:X113) -> 13110 | G18: =F18-E18 -> -76890 | H18: =SUM('Performances by Week'!S111:S113) -> 225 | I18: =SUM('Performances by Week'!AD111:AD113) -> 110000 | J18: =SUM('Performances by Week'!AC111:AC113) -> 119909.5 | K18: =SUM('Performances by Week'!AB111:AB113) -> 1809 | L18: =SUM(E18,I18) -> 200000 | M18: =SUM(F18,J18) -> 133019.5 | N18: =SUM(H18,K18) -> 2034 | O18: =SUM('Performances by Week'!AF111:AF113) -> 4770 | P18: =N18/O18 -> 0.42641509 | Q18: =M18/N18 -> 65.397984
A19: CS14 | B19: Rhapsody in Blue (SP) | D19: Jun 19-21 | E19: =SUM('Performances by Week'!Y115:Y117) -> 85000 | F19: =SUM('Performances by Week'!X115:X117) -> 30540 | G19: =F19-E19 -> -54460 | H19: =SUM('Performances by Week'!S115:S117) -> 518 | I19: =SUM('Performances by Week'!AD115:AD117) -> 115000 | J19: =SUM('Performances by Week'!AC115:AC117) -> 101226 | K19: =SUM('Performances by Week'!AB115:AB117) -> 1538 | L19: =SUM(E19,I19) -> 200000 | M19: =SUM(F19,J19) -> 131766 | N19: =SUM(H19,K19) -> 2056 | O19: =SUM('Performances by Week'!AF115:AF117) -> 4770 | P19: =N19/O19 -> 0.43102725 | Q19: =M19/N19 -> 64.088521
A20: CLASSICAL TRADITIONAL TOTAL | E20: =SUM(E6:E19) -> 866993 | F20: =SUM(F6:F19) -> 264938 | G20: =F20-E20 -> -602055 | H20: =SUM(H6:H19) -> 4767 | I20: =SUM(I6:I19) -> 1635000 | J20: =SUM(J6:J19) -> 1511616.5 | K20: =SUM(K6:K19) -> 22889 | L20: =SUM(L6:L19) -> 2501993 | M20: =SUM(F20,J20) -> 1776554.5 | N20: =SUM(N6:N19) -> 27656 | O20: =SUM(O6:O19) -> 65367 | P20: =N20/O20 -> 0.4230881 | Q20: =M20/N20 -> 64.23758
A22: SYMPHONIC PIAZZA
A23: Piazza CS2 | B23: =B7 -> Rachmaninoff Cele Pt 1 (SP) | D23: Oct 31 | E23: ='Performances by Week'!$Y$26 -> 22000 | F23: ='Performances by Week'!$X$26 -> 7608 | G23: =F23-E23 -> -14392 | H23: ='Performances by Week'!$S$26 -> 144 | I23: ='Performances by Week'!$AD$26 -> 30000 | J23: ='Performances by Week'!$AC$26 -> 23801 | K23: ='Performances by Week'!$AB$26 -> 342 | L23: =SUM(E23,I23) -> 52000 | M23: =SUM(F23,J23) -> 31409 | N23: =SUM(H23,K23) -> 486 | O23: ='Performances by Week'!$AF$115 -> 1590 | P23: =N23/O23 -> 0.30566038 | Q23: =M23/N23 -> 64.627572
A24: Piazza CS3 | B24: =B8 -> Matthias and Mahler (SP) | D24: Nov 21 | E24: ='Performances by Week'!$Y$31 -> 15000 | F24: ='Performances by Week'!$X$31 -> 3804 | G24: =F24-E24 -> -11196 | H24: ='Performances by Week'!$S$31 -> 75 | I24: ='Performances by Week'!$AD$31 -> 25000 | J24: ='Performances by Week'!$AC$31 -> 25348 | K24: ='Performances by Week'!$AB$31 -> 367 | L24: =SUM(E24,I24) -> 40000 | M24: =SUM(F24,J24) -> 29152 | N24: =SUM(H24,K24) -> 442 | O24: ='Performances by Week'!$AF$31 -> 1590 | P24: =N24/O24 -> 0.27798742 | Q24: =M24/N24 -> 65.954751
A25: Piazza CS5 | B25: =B10 -> Pines of Rome & Bruch (SP) | D25: Jan 16 | E25: ='Performances by Week'!$Y$55 -> 30000 | F25: ='Performances by Week'!$X$55 -> 2960 | G25: =F25-E25 -> -27040 | H25: ='Performances by Week'!$S$55 -> 51 | I25: ='Performances by Week'!$AD$55 -> 30000 | J25: ='Performances by Week'!$AC$55 -> 25342 | K25: ='Performances by Week'!$AB$55 -> 368 | L25: =SUM(E25,I25) -> 60000 | M25: =SUM(F25,J25) -> 28302 | N25: =SUM(H25,K25) -> 419 | O25: ='Performances by Week'!$AF$55 -> 1590 | P25: =N25/O25 -> 0.26352201 | Q25: =M25/N25 -> 67.546539
A26: Piazza CS6 | B26: =B11 -> Beethoven+ (SP) | D26: Jan 30 | E26: ='Performances by Week'!$Y$62 -> 24000 | F26: ='Performances by Week'!$X$62 -> 3847 | G26: =F26-E26 -> -20153 | H26: ='Performances by Week'!$S$62 -> 71 | I26: ='Performances by Week'!$AD$62 -> 30000 | J26: ='Performances by Week'!$AC$62 -> 24869 | K26: ='Performances by Week'!$AB$62 -> 364 | L26: =SUM(E26,I26) -> 54000 | M26: =SUM(F26,J26) -> 28716 | N26: =SUM(H26,K26) -> 435 | O26: ='Performances by Week'!$AF$62 -> 1590 | P26: =N26/O26 -> 0.27358491 | Q26: =M26/N26 -> 66.013793
A27: Piazza CS9 | B27: =B14 -> Midsummer Night's Dream (SP) | D27: Apr 10 | E27: ='Performances by Week'!$Y$89 -> 22000 | F27: ='Performances by Week'!$X$89 -> 2411 | G27: =F27-E27 -> -19589 | H27: ='Performances by Week'!$S$89 -> 52 | I27: ='Performances by Week'!$AD$89 -> 30000 | J27: ='Performances by Week'!$AC$89 -> 25714 | K27: ='Performances by Week'!$AB$89 -> 368 | L27: =SUM(E27,I27) -> 52000 | M27: =SUM(F27,J27) -> 28125 | N27: =SUM(H27,K27) -> 420 | O27: ='Performances by Week'!$AF$89 -> 1433 | P27: =N27/O27 -> 0.29309142 | Q27: =M27/N27 -> 66.964286
A28: Piazza CS11 | B28: =B16 -> Grieg's Piano Concerto (SP) | D28: May 8 | E28: ='Performances by Week'!$Y$97 -> 20000 | F28: ='Performances by Week'!$X$97 -> 2349 | G28: =F28-E28 -> -17651 | H28: ='Performances by Week'!$S$97 -> 50 | I28: ='Performances by Week'!$AD$97 -> 25000 | J28: ='Performances by Week'!$AC$97 -> 25763 | K28: ='Performances by Week'!$AB$97 -> 374 | L28: =SUM(E28,I28) -> 45000 | M28: =SUM(F28,J28) -> 28112 | N28: =SUM(H28,K28) -> 424 | O28: ='Performances by Week'!$AF$97 -> 1590 | P28: =N28/O28 -> 0.26666667 | Q28: =M28/N28 -> 66.301887
A29: Piazza CS14 | B29: =B19 -> Rhapsody in Blue (SP) | D29: Jun 19 | E29: ='Performances by Week'!$Y$115 -> 30000 | F29: ='Performances by Week'!$X$115 -> 6390 | G29: =F29-E29 -> -23610 | H29: ='Performances by Week'!$S$115 -> 111 | I29: ='Performances by Week'!$AD$115 -> 30000 | J29: ='Performances by Week'!$AC$115 -> 26279 | K29: ='Performances by Week'!$AB$115 -> 380 | L29: =SUM(E29,I29) -> 60000 | M29: =SUM(F29,J29) -> 32669 | N29: =SUM(H29,K29) -> 491 | O29: ='Performances by Week'!$AF$115 -> 1590 | P29: =N29/O29 -> 0.30880503 | Q29: =M29/N29 -> 66.535642
A30: SYMPHONIC PIAZZA TOTAL | E30: =SUM(E23:E29) -> 163000 | F30: =SUM(F23:F29) -> 29369 | G30: =SUM(G23:G29) -> -133631 | H30: =SUM(H23:H29) -> 554 | I30: =SUM(I23:I29) -> 200000 | J30: =SUM(J23:J29) -> 177116 | K30: =SUM(K23:K29) -> 2563 | L30: =SUM(L23:L29) -> 363000 | ... O30: =SUM(O23:O29) -> 10973 | P30: =N30/O30 -> 0.28406088 | Q30: =M30/N30 -> 66.244787
A32: POPS
A33: PS1 | B33: Music of Journey | D33: Sep 19-21 | E33: =SUM('Performances by Week'!$Y$10:$Y$12) -> 177999 | F33: =SUM('Performances by Week'!$X$10:$X$12) -> 105423 | G33: =F33-E33 -> -72576 | H33: =SUM('Performances by Week'!$S$10:$S$12) -> 1727 | I33: =SUM('Performances by Week'!$AD$10:$AD$12) -> 124000 | J33: =SUM('Performances by Week'!$AC$10:$AC$12) -> 108064.7 | K33: =SUM('Performances by Week'!$AB$10:$AB$12) -> 1473 | L33: =SUM(E33,I33) -> 301999 | M33: =SUM(F33,J33) -> 213487.7 | N33: =SUM(H33,K33) -> 3200 | O33: =SUM('Performances by Week'!$AF$10:$AF$12) -> 4770 | P33: =N33/O33 -> 0.67085954 | Q33: =M33/N33 -> 66.714906
A34: PS2 | B34: 90s Mixtape | D34: Oct 24-26 | E34: =SUM('Performances by Week'!$Y$22:$Y$24) -> 159999 | F34: =SUM('Performances by Week'!$X$22:$X$24) -> 31123 | G34: =F34-E34 -> -128876 | H34: =SUM('Performances by Week'!$S$22:$S$24) -> 498 | I34: =SUM('Performances by Week'!$AD$22:$AD$24) -> 117000 | J34: =SUM('Performances by Week'!$AC$22:$AC$24) -> 122339.2 | K34: =SUM('Performances by Week'!$AB$22:$AB$24) -> 1719 | L34: =SUM(E34,I34) -> 276999 | M34: =SUM(F34,J34) -> 153462.2 | N34: =SUM(H34,K34) -> 2217 | O34: =SUM('Performances by Week'!$AF$22:$AF$24) -> 4770 | P34: =N34/O34 -> 0.46477987 | Q34: =M34/N34 -> 69.220659
A35: PS3 | B35: She's Got Soul | D35: Feb 13-15 | E35: =SUM('Performances by Week'!$Y$70:$Y$72) -> 159999 | F35: =SUM('Performances by Week'!$X$70:$X$72) -> 10200 | G35: =F35-E35 -> -149799 | H35: =SUM('Performances by Week'!$S$70:$S$72) -> 175 | I35: =SUM('Performances by Week'!$AD$70:$AD$72) -> 124000 | J35: =SUM('Performances by Week'!$AC$70:$AC$72) -> 126157.2 | K35: =SUM('Performances by Week'!$AB$70:$AB$72) -> 1771 | L35: =SUM(E35,I35) -> 283999 | M35: =SUM(F35,J35) -> 136357.2 | N35: =SUM(H35,K35) -> 1946 | O35: =SUM('Performances by Week'!$AF$70:$AF$72) -> 4770 | P35: =N35/O35 -> 0.40796646 | Q35: =M35/N35 -> 70.070504
A36: PS4 | B36: Billy Joel & Elton John | D36: Mar 27-29 | E36: =SUM('Performances by Week'!$Y$85:$Y$87) -> 159999 | F36: =SUM('Performances by Week'!$X$85:$X$87) -> 40766 | G36: =F36-E36 -> -119233 | H36: =SUM('Performances by Week'!$S$85:$S$87) -> 579 | I36: =SUM('Performances by Week'!$AD$85:$AD$87) -> 124000 | J36: =SUM('Performances by Week'!$AC$85:$AC$87) -> 128191.5 | K36: =SUM('Performances by Week'!$AB$85:$AB$87) -> 1798 | L36: =SUM(E36,I36) -> 283999 | M36: =SUM(F36,J36) -> 168957.5 | N36: =SUM(H36,K36) -> 2377 | O36: =SUM('Performances by Week'!$AF$85:$AF$87) -> 4770 | P36: =N36/O36 -> 0.49832285 | Q36: =M36/N36 -> 71.080143
A37: PS5 | B37: Dolly Parton's Threads | D37: May 15-17 | E37: =SUM('Performances by Week'!$Y$100:$Y$102) -> 180000 | F37: =SUM('Performances by Week'!$X$100:$X$102) -> 19555 | G37: =F37-E37 -> -160445 | H37: =SUM('Performances by Week'!$S$100:$S$102) -> 256 | I37: =SUM('Performances by Week'!$AD$100:$AD$102) -> 130000 | J37: =SUM('Performances by Week'!$AC$100:$AC$102) -> 150672 | K37: =SUM('Performances by Week'!$AB$100:$AB$102) -> 1801 | L37: =SUM(E37,I37) -> 310000 | M37: =SUM(F37,J37) -> 170227 | N37: =SUM(H37,K37) -> 2057 | O37: =SUM('Performances by Week'!$AF$100:$AF$102) -> 3906 | P37: =N37/O37 -> 0.5266257 | Q37: =M37/N37 -> 82.754983
A38: POPS TOTAL | E38: =SUM(E33:E37) -> 837996 | F38: =SUM(F33:F37) -> 207067 | G38: =SUM(G33:G37) -> -630929 | H38: =SUM(H33:H37) -> 3235 | I38: =SUM(I33:I37) -> 619000 | J38: =SUM(J33:J37) -> 635424.6 | K38: =SUM(K33:K37) -> 8562 | L38: =SUM(L33:L37) -> 1456996 | ... O38: =SUM(O33:O37) -> 22986 | P38: =N38/O38 -> 0.51322544 | Q38: =M38/N38 -> 71.41575
A40: FAMILY
A41: FS1 | B41: The Orchestra Games | D41: Sep 28 | E41: ='Performances by Week'!$Y$13 -> 10000 | F41: ='Performances by Week'!$X$13 -> 16966 | G41: =F41-E41 -> 6966 | H41: ='Performances by Week'!$S$13 -> 507 | I41: ='Performances by Week'!$AD$13 -> 9500 | J41: ='Performances by Week'!$AC$13 -> 5217 | K41: ='Performances by Week'!$AB$13 -> 196 | L41: =SUM(E41,I41) -> 19500 | M41: =SUM(F41,J41) -> 22183 | N41: =SUM(H41,K41) -> 703 | O41: ='Performances by Week'!$AF$13 -> 1302 | P41: =N41/O41 -> 0.53993856 | Q41: =M41/N41 -> 31.554765
A42: FS2 | B42: Carnival of the Animals | D42: Nov 9 | E42: ='Performances by Week'!$Y$29 -> 10000 | F42: ='Performances by Week'!$X$29 -> 4828 | G42: =F42-E42 -> -5172 | H42: ='Performances by Week'!$S$29 -> 169 | I42: ='Performances by Week'!$AD$29 -> 9500 | J42: ='Performances by Week'!$AC$29 -> 6836 | K42: ='Performances by Week'!$AB$29 -> 307 | L42: =SUM(E42,I42) -> 19500 | M42: =SUM(F42,J42) -> 11664 | N42: =SUM(H42,K42) -> 476 | O42: ='Performances by Week'!$AF$29 -> 1300 | P42: =N42/O42 -> 0.36615385 | Q42: =M42/N42 -> 24.504202
A43: Holiday | B43: Christmas Festival | D43: Dec 18-21 | E43: =SUM('Performances by Week'!$Y$43:$Y$48) -> 455000 | F43: =SUM('Performances by Week'!$X$43:$X$48) -> 96375 | G43: =F43-E43 -> -358625 | H43: =SUM('Performances by Week'!$S$43:$S$48) -> 1591 | I43: =SUM('Performances by Week'!$AD$43:$AD$48) -> 12450 | J43: =SUM('Performances by Week'!$AC$43:$AC$48) -> 6677 | K43: =SUM('Performances by Week'!$AB$43:$AB$48) -> 301 | L43: =SUM(E43,I43) -> 467450 | M43: =SUM(F43,J43) -> 103052 | N43: =SUM(H43,K43) -> 1892 | O43: =SUM('Performances by Week'!$AF$43:$AF$48) -> 8598 | P43: =N43/O43 -> 0.22005117 | Q43: =M43/N43 -> 54.46723
A44: FS3 | B44: Philharmonia Fantastique | D44: Mar 1 | E44: ='Performances by Week'!$Y$77 -> 10000 | F44: ='Performances by Week'!$X$77 -> 1461 | G44: =F44-E44 -> -8539 | H44: ='Performances by Week'!$S$77 -> 50 | I44: ='Performances by Week'!$AD$77 -> 9500 | J44: ='Performances by Week'!$AC$77 -> 6836 | K44: ='Performances by Week'!$AB$77 -> 307 | L44: =SUM(E44,I44) -> 19500 | M44: =SUM(F44,J44) -> 8297 | N44: =SUM(H44,K44) -> 357 | O44: ='Performances by Week'!$AF$77 -> 1302 | P44: =N44/O44 -> 0.27419355 | Q44: =M44/N44 -> 23.240896
A45: FAMILY SERIES TOTAL | E45: =SUM(E41:E44) -> 485000 | F45: =SUM(F41:F44) -> 119630 | G45: =F45-E45 -> -365370 | H45: =SUM(H41:H44) -> 2317 | I45: =SUM(I41:I44) -> 40950 | J45: =SUM(J41:J44) -> 25566 | K45: =SUM(K41:K44) -> 1111 | L45: =SUM(L41:L44) -> 525950 | M45: =SUM(M41:M44) -> 145196 | N45: =SUM(N41:N44) -> 3428 | O45: =SUM(O41:O44) -> 12502 | P45: =N45/O45 -> 0.27419613 | Q45: =M45/N45 -> 42.355893
A47: FILM
A48: Top Gun: Maverick in Concert | D48: Oct 17-19 | E48: =SUM('Performances by Week'!$Y$18:$Y$20) -> 310490 | F48: =SUM('Performances by Week'!$X$18:$X$20) -> 191839 | G48: =F48-E48 -> -118651 | H48: =SUM('Performances by Week'!$S$18:$S$20) -> 2564 | I48: $ - | J48: $ - | K48: - | L48: =SUM(E48,I48) -> 310490 | M48: =SUM(F48,J48) -> 191839 | N48: =SUM(H48,K48) -> 2564 | O48: =SUM('Performances by Week'!$AF$18:$AF$20) -> 3906 | P48: =N48/O48 -> 0.65642601 | Q48: =M48/N48 -> 74.820203
A49: The Lodger | D49: Oct 22 | E49: ='Performances by Week'!$Y$21 -> 50000 | F49: ='Performances by Week'!$X$21 -> 13747 | G49: =F49-E49 -> -36253 | H49: ='Performances by Week'!$S$21 -> 256 | I49: $ - | J49: $ - | K49: - | L49: =SUM(E49,I49) -> 50000 | M49: =SUM(F49,J49) -> 13747 | N49: =SUM(H49,K49) -> 256 | O49: ='Performances by Week'!$AF$21 -> 1302 | P49: =N49/O49 -> 0.19662058 | Q49: =M49/N49 -> 53.699219
A50: Elf™ in Concert | D50: Nov 28-30 | E50: =SUM('Performances by Week'!$Y$34:$Y$37) -> 430000 | F50: =SUM('Performances by Week'!$X$34:$X$37) -> 110857 | G50: =F50-E50 -> -319143 | H50: =SUM('Performances by Week'!$S$34:$S$37) -> 1624 | I50: $ - | J50: $ - | K50: - | L50: =SUM(E50,I50) -> 430000 | M50: =SUM(F50,J50) -> 110857 | N50: =SUM(H50,K50) -> 1624 | O50: =SUM('Performances by Week'!$AF$34:$AF$37) -> 5208 | P50: =N50/O50 -> 0.31182796 | Q50: =M50/N50 -> 68.2617
A51: It's a Wonderful Life | D51: Dec 23-24 | E51: =SUM('Performances by Week'!$Y$49:$Y$50) -> 200000 | F51: =SUM('Performances by Week'!$X$49:$X$50) -> 86812 | G51: =F51-E51 -> -113188 | H51: =SUM('Performances by Week'!$S$49:$S$50) -> 1133 | I51: $ - | J51: $ - | K51: - | L51: =SUM(E51,I51) -> 200000 | M51: =SUM(F51,J51) -> 86812 | N51: =SUM(H51,K51) -> 1133 | O51: =SUM('Performances by Week'!$AF$49:$AF$50) -> 2604 | P51: =N51/O51 -> 0.43509985 | Q51: =M51/N51 -> 76.621359
A52: Indiana Jones: Raiders Lost | D52: Jan 22-25 | E52: =SUM('Performances by Week'!$Y$58:$Y$61) -> 360000 | F52: =SUM('Performances by Week'!$X$58:$X$61) -> 93772.1 | G52: =F52-E52 -> -266227.9 | H52: =SUM('Performances by Week'!$S$58:$S$61) -> 1322 | I52: $ - | J52: $ - | K52: - | L52: =SUM(E52,I52) -> 360000 | M52: =SUM(F52,J52) -> 93772.1 | N52: =SUM(H52,K52) -> 1322 | O52: =SUM('Performances by Week'!$AF$58:$AF$61) -> 5208 | P52: =N52/O52 -> 0.25384025 | Q52: =M52/N52 -> 70.931997
A53: Harry Potter 2: Chamber | D53: Feb 19-22 | E53: =SUM('Performances by Week'!$Y$73:$Y$76) -> 445000 | F53: =SUM('Performances by Week'!$X$73:$X$76) -> 94720 | G53: =F53-E53 -> -350280 | H53: =SUM('Performances by Week'!$S$73:$S$76) -> 1328 | I53: $ - | J53: $ - | K53: - | L53: =SUM(E53,I53) -> 445000 | M53: =SUM(F53,J53) -> 94720 | N53: =SUM(H53,K53) -> 1328 | O53: =SUM('Performances by Week'!$AF$73:$AF$76) -> 5208 | P53: =N53/O53 -> 0.25499232 | Q53: =M53/N53 -> 71.325301
A54: FILM TOTAL | E54: =SUM(E48:E53) -> 1795490 | F54: =SUM(F48:F53) -> 591747.1 | G54: =SUM(G48:G53) -> -1203742.9 | H54: =SUM(H48:H53) -> 8227 | I54: $ - | J54: $ - | K54: - | L54: =SUM(L48:L53) -> 1795490 | M54: =SUM(M48:M53) -> 591747.1 | N54: =SUM(N48:N53) -> 8227 | O54: =SUM(O48:O53) -> 23436 | P54: =N54/O54 -> 0.35104113 | Q54: =M54/N54 -> 71.927446
A56: ON STAGE
A57: George Li | D57: Oct 29 | E57: ='Performances by Week'!$Y$25 -> 11200 | F57: ='Performances by Week'!$X$25 -> 3360 | G57: =F57-E57 -> -7840 | H57: ='Performances by Week'!$S$25 -> 29 | I57: $ - | J57: $ - | K57: - | L57: =SUM(E57,I57) -> 11200 | M57: =SUM(F57,J57) -> 3360 | N57: =SUM(H57,K57) -> 29 | O57: ='Performances by Week'!$AF$25 -> 100 | P57: =N57/O57 -> 0.29 | Q57: =M57/N57 -> 115.86207
A58: Leila Josefowicz | D58: Feb 5 | E58: ='Performances by Week'!$Y$65 -> 9000 | F58: ='Performances by Week'!$X$65 -> 1960 | G58: =F58-E58 -> -7040 | H58: ='Performances by Week'!$S$65 -> 19 | I58: $ - | J58: $ - | K58: - | L58: =SUM(E58,I58) -> 9000 | M58: =SUM(F58,J58) -> 1960 | N58: =SUM(H58,K58) -> 19 | O58: ='Performances by Week'!$AF$65 -> 100 | P58: =N58/O58 -> 0.19 | Q58: =M58/N58 -> 103.15789
A59: Gil Shaham | D59: May 28 | E59: ='Performances by Week'!$Y$106 -> 9000 | F59: ='Performances by Week'!$X$106 -> 1680 | G59: =F59-E59 -> -7320 | H59: ='Performances by Week'!$S$106 -> 17 | I59: $ - | J59: $ - | K59: - | L59: =SUM(E59,I59) -> 9000 | M59: =SUM(F59,J59) -> 1680 | N59: =SUM(H59,K59) -> 17 | O59: ='Performances by Week'!$AF$106 -> 100 | P59: =N59/O59 -> 0.17 | Q59: =M59/N59 -> 98.823529
A60: Yefim Bronfman | D60: Jun 4 | E60: ='Performances by Week'!$Y$110 -> 9000 | F60: ='Performances by Week'!$X$110 -> 2100 | G60: =F60-E60 -> -6900 | H60: ='Performances by Week'!$S$110 -> 20 | I60: $ - | J60: $ - | K60: - | L60: =SUM(E60,I60) -> 9000 | M60: =SUM(F60,J60) -> 2100 | N60: =SUM(H60,K60) -> 20 | O60: ='Performances by Week'!$AF$110 -> 100 | P60: =N60/O60 -> 0.2 | Q60: =M60/N60 -> 105
A61: ON STAGE CONCERTS TOTAL | E61: =SUM(E57:E60) -> 38200 | F61: =SUM(F57:F60) -> 9100 | G61: =SUM(G57:G60) -> -29100 | H61: =SUM(H57:H60) -> 85 | I61: $ - | J61: $ - | K61: - | L61: =SUM(L57:L60) -> 38200 | M61: =SUM(M57:M60) -> 9100 | N61: =SUM(N57:N60) -> 85 | O61: =SUM(O57:O60) -> 400 | P61: =N61/O61 -> 0.2125 | Q61: =M61/N61 -> 107.05882
A63: OTHER CONCERTS
A64: Morgan Freeman Symphonic Blues | D64: Sep 2-3 | E64: =SUM('Performances by Week'!$Y$6:$Y$7) -> 306946 | F64: =SUM('Performances by Week'!$X$6:$X$7) -> 272084 | G64: =F64-E64 -> -34862 | H64: =SUM('Performances by Week'!$S$6:$S$7) -> 2299 | I64: $ - | J64: $ - | L64: =SUM(E64,I64) -> 306946 | M64: =SUM(F64,J64) -> 272084 | N64: =SUM(H64,K64) -> 2299 | O64: =SUM('Performances by Week'!$AF$6:$AF$7) -> 2604 | P64: =N64/O64 -> 0.8828725 | Q64: =M64/N64 -> 118.34885
A65: La Nuit Sombre (Four Larks) | D65: Sep 5 | E65: ='Performances by Week'!$Y$8 -> 15000 | F65: ='Performances by Week'!$X$8 -> 20005 | G65: =F65-E65 -> 5005 | H65: ='Performances by Week'!$S$8 -> 699 | I65: $ - | J65: $ - | L65: =SUM(E65,I65) -> 15000 | M65: =SUM(F65,J65) -> 20005 | N65: =SUM(H65,K65) -> 699 | O65: ='Performances by Week'!$AF$8 -> 600 | P65: =N65/O65 -> 1.165 | Q65: =M65/N65 -> 28.619456
A66: Handel's Messiah | D66: Dec 5-7 | E66: =SUM('Performances by Week'!$Y$38:$Y$40) -> 235000 | F66: =SUM('Performances by Week'!$X$38:$X$40) -> 65052.5 | G66: =F66-E66 -> -169947.5 | H66: =SUM('Performances by Week'!$S$38:$S$40) -> 1176 | I66: $ - | J66: $ - | K66: - | L66: =SUM(E66,I66) -> 235000 | M66: =SUM(F66,J66) -> 65052.5 | N66: =SUM(H66,K66) -> 1176 | O66: =SUM('Performances by Week'!$AF$38:$AF$40) -> 4299 | P66: =N66/O66 -> 0.27355199 | Q66: =M66/N66 -> 55.316752
A67: Leslie Odom Jr.: Christmas | D67: Dec 12-13 | E67: =SUM('Performances by Week'!$Y$41:$Y$42) -> 300000 | F67: =SUM('Performances by Week'!$X$41:$X$42) -> 242048 | G67: =F67-E67 -> -57952 | H67: =SUM('Performances by Week'!$S$41:$S$42) -> 2419 | I67: $ - | J67: $ - | K67: - | L67: =SUM(E67,I67) -> 300000 | M67: =SUM(F67,J67) -> 242048 | N67: =SUM(H67,K67) -> 2419 | O67: =SUM('Performances by Week'!$AF$41:$AF$42) -> 3180 | P67: =N67/O67 -> 0.76069182 | Q67: =M67/N67 -> 100.06118
A68: Chris Thile | D68: Feb 12 | E68: ='Performances by Week'!$Y$69 -> 128900 | F68: ='Performances by Week'!$X$69 -> 30162 | G68: =F68-E68 -> -98738 | H68: ='Performances by Week'!$S$69 -> 340 | I68: $ - | J68: $ - | K68: - | L68: =SUM(E68,I68) -> 128900 | M68: =SUM(F68,J68) -> 30162 | N68: =SUM(H68,K68) -> 340 | O68: ='Performances by Week'!$AF$69 -> 1590 | P68: =N68/O68 -> 0.21383648 | Q68: =M68/N68 -> 88.711765
A69: Final Symphony | D69: Mar 25-26 | E69: =SUM('Performances by Week'!$Y$83:$Y$84) -> 168218 | F69: =SUM('Performances by Week'!$X$83:$X$84) -> 10464.5 | G69: =F69-E69 -> -157753.5 | H69: =SUM('Performances by Week'!$S$83:$S$84) -> 173 | I69: $ - | J69: $ - | K69: - | L69: =SUM(E69,I69) -> 168218 | M69: =SUM(F69,J69) -> 10464.5 | N69: =SUM(H69,K69) -> 173 | O69: =SUM('Performances by Week'!$AF$83:$AF$84) -> 3180 | P69: =N69/O69 -> 0.054402516 | Q69: =M69/N69 -> 60.488439
A70: Ben Rector | D70: May 21-22 | E70: =SUM('Performances by Week'!$Y$104:$Y$105) -> 224936 | F70: =SUM('Performances by Week'!$X$104:$X$105) -> 28268 | G70: =F70-E70 -> -196668 | H70: =SUM('Performances by Week'!$S$104:$S$105) -> 317 | L70: =SUM(E70,I70) -> 224936 | M70: =SUM(F70,J70) -> 28268 | N70: =SUM(H70,K70) -> 317 | O70: =SUM('Performances by Week'!$AF$104:$AF$105) -> 3180 | P70: =N70/O70 -> 0.099685535 | Q70: =M70/N70 -> 89.173502
A71: OTHER CONCERT TOTAL | E71: =SUM(E64:E70) -> 1379000 | F71: =SUM(F64:F70) -> 668084 | G71: =SUM(G64:G70) -> -710916 | H71: =SUM(H64:H70) -> 7423 | I71: $ - | J71: $ - | K71: - | L71: =SUM(L64:L70) -> 1379000 | M71: =SUM(M64:M70) -> 668084 | N71: =SUM(N64:N70) -> 7423 | O71: =SUM(O64:O70) -> 18633 | P71: =N71/O71 -> 0.39837922 | Q71: =M71/N71 -> 90.001886
A72: ALL CONCERTS | E72: =SUM(E71,E61,E54,E45,E38,E20) -> 5402679 | F72: =SUM(F71,F61,F54,F45,F38,F20) -> 1860566.1 | G72: =SUM(G71,G61,G54,G45,G38,G20) -> -3542112.9 | H72: =SUM(H71,H61,H54,H45,H38,H20) -> 26054 | I72: =SUM(I71,I61,I54,I45,I38,I20) -> 2294950 | J72: =SUM(J71,J61,J54,J45,J38,J20) -> 2172607.1 | K72: =SUM(K71,K61,K54,K45,K38,K20) -> 32562 | L72: =SUM(L71,L61,L54,L45,L38,L20) -> 7697629 | ... O72: =SUM(O71,O61,O54,O45,O38,O20) -> 143324 | P72: =N72/O72 -> 0.40897547 | Q72: =M72/N72 -> 68.806694
