Workbook

Sheet Performances by Week
E1: Status: | F1: Updated 9/22 | H1: Denotes Piazza | I1: Update all fields in Blue each week | J1: We expect 50% of Single Sales 1 Week Prior | K1: 85%+ occupancy | O1: 95%+ of Budget | S1: 100%+ of Target
K2: 70-85% occupancy | O2: 85-95% of Budget | S2: 90-99% of Target
G3: Week # | K3: <70% occupancy | O3: <85% of Budget | S3: <90% of Target
D4: TICKET SALES REPORT as of 9/22/2025 | G4: 4 | I4: TOTAL SALES (Singles + Subs) | P4: Single Tickets | X4: Subscription Tickets | AB4: Hall Data | AE4: Audience Data | AH4: Revenue last week | AI4: Increase over week
A5: Wk # | B5: # Weeks Until Perf | C5: Perf. Week (Mon) | D5: Performance | G5: Performance Date(s) | H5: Performance Type | I5: Actual Total Tickets Sold | J5: Projected Single Tickets + Actual Subs | K5: Projected Total OCC at Performance | L5: Total Actual Revenue | M5: TOTAL BUDGET | N5: Actual/ Budget % | O5: Projected/ Budget % | P5: Actual Single Tickets Sold | Q5: Target Single Tickets for 85% OCC | R5: Projected Single Tickets | S5: Projected Single Tickets vs 85% OCC Target | T5: Actual Revenue | U5: BUDGET | V5: Actual/ Budget % | W5: Projected/ Budget % | X5: Actual Sub Tickets Sold | Y5: Actual Revenue | Z5: BUDGET | AA5: Actual vs Budget % | AB5: Max CAP | AC5: Actual OCC SOLD | AD5: Single Ticket ATP | AE5: # New HH | AF5: # Ret HH | AG5: # Total HH
A6: 1 | B6: =A6-$G$4 -> -3 | C6: 45901 | D6: 26 Morgan Freeman's Symphonic Blues | G6: 45902.833 | H6: Specials | I6: =P6+X6 -> 1169 | J6: =IF(R6="Too early",R6,R6+X6) -> #N/A | K6: =IF(J6="Too early",J6,J6/AB6) -> #N/A | L6: =T6+Y6 -> 137698 | M6: =U6+Z6 -> 153473 | N6: =L6/M6 -> 0.89721319 | O6: =IF($J6="Too early",J6,J6*AD6/M6) -> #N/A | P6: 1169 | Q6: =(AB6-X6)*0.85 -> 1106.7 | R6: =IF(B6<7,(P6/VLOOKUP(B6,'Sales Pacing'!$A$23:$E$36,2)),"Too early") -> #N/A | S6: =IF(R6="Too early","Too early",R6/Q6) -> #N/A | T6: 137698 | U6: 153473 | V6: =IF(T6>0,T6/U6,"") -> 0.89721319 | W6: =IF($R6="Too early",R6,R6*AD6/U6) -> #N/A | Z6: 0 | AA6: =IF(Y6>0,Y6/Z6,"") | AB6: 1302 | AC6: =I6/AB6 -> 0.89784946 | AD6: =L6/I6 -> 117.79127 | AE6: 228 | AF6: 295 | AG6: 523 | AH6: 137698 | AI6: =L6-AH6 -> 0
A7: 1 | B7: =A7-$G$4 -> -3 | C7: 45901 | D7: 26 Morgan Freeman's Symphonic Blues | G7: 45903.833 | H7: Specials | I7: =P7+X7 -> 1148 | J7: =IF(R7="Too early",R7,R7+X7) -> #N/A | K7: =IF(J7="Too early",J7,J7/AB7) -> #N/A | L7: =T7+Y7 -> 134386 | M7: =U7+Z7 -> 153473 | N7: =L7/M7 -> 0.87563285 | O7: =IF($J7="Too early",J7,J7*AD7/M7) -> #N/A | P7: 1148 | Q7: =(AB7-X7)*0.85 -> 1106.7 | R7: =IF(B7<7,(P7/VLOOKUP(B7,'Sales Pacing'!$A$23:$E$36,2)),"Too early") -> #N/A | S7: =IF(R7="Too early","Too early",R7/Q7) -> #N/A | T7: 134386 | U7: 153473 | V7: =IF(T7>0,T7/U7,"") -> 0.87563285 | W7: =IF($R7="Too early",R7,R7*AD7/U7) -> #N/A | Z7: 0 | AA7: =IF(Y7>0,Y7/Z7,"") | AB7: 1302 | AC7: =I7/AB7 -> 0.88172043 | AD7: =L7/I7 -> 117.06098 | AE7: 227 | AF7: 289 | AG7: 516 | AH7: 134386 | AI7: =L7-AH7 -> 0
A8: 1 | B8: =A8-$G$4 -> -3 | C8: 45901 | D8: 26 La nuit sombre | G8: 45905.833 | H8: Specials | I8: =P8+X8 -> 699 | J8: =IF(R8="Too early",R8,R8+X8) -> #N/A | K8: =IF(J8="Too early",J8,J8/AB8) -> #N/A | L8: =T8+Y8 -> 20005 | M8: =U8+Z8 -> 15000 | N8: =L8/M8 -> 1.3336667 | O8: =IF($J8="Too early",J8,J8*AD8/M8) -> #N/A | P8: 699 | Q8: =(AB8-X8)*0.85 -> 510 | R8: =IF(B8<7,(P8/VLOOKUP(B8,'Sales Pacing'!$A$23:$E$36,2)),"Too early") -> #N/A | S8: =IF(R8="Too early","Too early",R8/Q8) -> #N/A | T8: 20005 | U8: 15000 | V8: =IF(T8>0,T8/U8,"") -> 1.3336667 | W8: =IF($R8="Too early",R8,R8*AD8/U8) -> #N/A | Z8: 0 | AA8: =IF(Y8>0,Y8/Z8,"") | AB8: 600 | AC8: =I8/AB8 -> 1.165 | AD8: =L8/I8 -> 28.619456 | AE8: 86 | AF8: 209 | AG8: 295 | AH8: 20005 | AI8: =L8-AH8 -> 0
A9: 2 | B9: =A9-$G$4 -> -2 | C9: 45908 | D9: OPEN - Recording Week | I9: =P9+X9 -> 0 | J9: =IF(R9="Too early",R9,R9+X9) -> #N/A | N9: =L9/M9 -> #DIV/0! | R9: =IF(B9<7,(P9/VLOOKUP(B9,'Sales Pacing'!$A$23:$E$36,2)),"Too early") -> #N/A | V9: =IF(T9>0,T9/U9,"") | AA9: N/A | AC9: =I9/AB9 -> #DIV/0!
A10: 3 | B10: =A10-$G$4 -> -1 | C10: 45915 | D10: 26 PS1 Music of Journey | G10: 45919.833 | H10: Pops | I10: =P10+X10 -> 1130 | J10: =IF(R10="Too early",R10,R10+X10) -> #N/A | K10: =IF(J10="Too early",J10,J10/AB10) -> #N/A | L10: =T10+Y10 -> 75516.6 | M10: =U10+Z10 -> 100666 | N10: =L10/M10 -> 0.75016987 | O10: =IF($J10="Too early",J10,J10*AD10/M10) -> #N/A | P10: 515 | Q10: =(AB10-X10)*0.85 -> 828.75 | R10: =IF(B10<7,(P10/VLOOKUP(B10,'Sales Pacing'!$A$23:$E$36,2)),"Too early") -> #N/A | S10: =IF(R10="Too early","Too early",R10/Q10) -> #N/A | T10: 30148 | U10: 59333 | V10: =IF(T10>0,T10/U10,"") -> 0.50811521 | W10: =IF($R10="Too early",R10,R10*AD10/U10) -> #N/A | X10: 615 | Y10: 45368.6 | Z10: 41333 | AA10: =IF(Y10>0,Y10/Z10,"") -> 1.0976363 | AB10: 1590 | AC10: =I10/AB10 -> 0.71069182 | AD10: =L10/I10 -> 66.82885 | AE10: 67 | AF10: 416 | AG10: 483 | AH10: 71854.6 | AI10: =L10-AH10 -> 3662
A11: 3 | B11: =A11-$G$4 -> -1 | C11: 45915 | D11: 26 PS1 Music of Journey | G11: 45920.833 | H11: Pops | I11: =P11+X11 -> 1068 | J11: =IF(R11="Too early",R11,R11+X11) -> #N/A | K11: =IF(J11="Too early",J11,J11/AB11) -> #N/A | L11: =T11+Y11 -> 74220.3 | M11: =U11+Z11 -> 100667 | N11: =L11/M11 -> 0.73728531 | O11: =IF($J11="Too early",J11,J11*AD11/M11) -> #N/A | P11: 554 | Q11: =(AB11-X11)*0.85 -> 914.6 | R11: =IF(B11<7,(P11/VLOOKUP(B11,'Sales Pacing'!$A$23:$E$36,2)),"Too early") -> #N/A | S11: =IF(R11="Too early","Too early",R11/Q11) -> #N/A | T11: 35672 | U11: 59333 | V11: =IF(T11>0,T11/U11,"") -> 0.60121686 | W11: =IF($R11="Too early",R11,R11*AD11/U11) -> #N/A | X11: 514 | Y11: 38548.3 | Z11: 41334 | AA11: =IF(Y11>0,Y11/Z11,"") -> 0.93260512 | AB11: 1590 | AC11: =I11/AB11 -> 0.67169811 | AD11: =L11/I11 -> 69.494663 | AE11: 78 | AF11: 376 | AG11: 454 | AH11: 70013.3 | AI11: =L11-AH11 -> 4207
A12: 3 | B12: =A12-$G$4 -> -1 | C12: 45915 | D12: 26 PS1 Music of Journey | G12: 45921.583 | H12: Pops | I12: =P12+X12 -> 1008 | J12: =IF(R12="Too early",R12,R12+X12) -> #N/A | K12: =IF(J12="Too early",J12,J12/AB12) -> #N/A | L12: =T12+Y12 -> 64499.8 | M12: =U12+Z12 -> 100666 | N12: =L12/M12 -> 0.64073073 | O12: =IF($J12="Too early",J12,J12*AD12/M12) -> #N/A | P12: 664 | Q12: =(AB12-X12)*0.85 -> 1059.1 | R12: =IF(B12<7,(P12/VLOOKUP(B12,'Sales Pacing'!$A$23:$E$36,2)),"Too early") -> #N/A | S12: =IF(R12="Too early","Too early",R12/Q12) -> #N/A | T12: 40352 | U12: 59333 | V12: =IF(T12>0,T12/U12,"") -> 0.68009371 | W12: =IF($R12="Too early",R12,R12*AD12/U12) -> #N/A | X12: 344 | Y12: 24147.8 | Z12: 41333 | AA12: =IF(Y12>0,Y12/Z12,"") -> 0.58422568 | AB12: 1590 | AC12: =I12/AB12 -> 0.63396226 | AD12: =L12/I12 -> 63.987897 | AE12: 74 | AF12: 286 | AG12: 360 | AH12: 56072.3 | AI12: =L12-AH12 -> 8427.5
A13: 4 | B13: =A13-$G$4 -> 0 | C13: 45922 | D13: 26 FS1 The Orchestra Games | G13: 45928.583 | H13: Family | I13: =P13+X13 -> 539 | J13: =IF(R13="Too early",R13,R13+X13) -> 539 | K13: =IF(J13="Too early",J13,J13/AB13) -> 0.41397849 | L13: =T13+Y13 -> 14134 | M13: =U13+Z13 -> 19500 | N13: =L13/M13 -> 0.72482051 | O13: =IF($J13="Too early",J13,J13*AD13/M13) -> 0.72482051 | P13: 343 | Q13: =(AB13-X13)*0.85 -> 940.1 | R13: =IF(B13<7,(P13/VLOOKUP(B13,'Sales Pacing'!$A$23:$E$36,2)),"Too early") -> 343 | S13: =IF(R13="Too early","Too early",R13/Q13) -> 0.3648548 | T13: 8917 | U13: 10000 | V13: =IF(T13>0,T13/U13,"") -> 0.8917 | W13: =IF($R13="Too early",R13,R13*AD13/U13) -> 0.89943636 | X13: 196 | Y13: 5217 | Z13: 9500 | AA13: =IF(Y13>0,Y13/Z13,"") -> 0.54915789 | AB13: 1302 | AC13: =I13/AB13 -> 0.41397849 | AD13: =L13/I13 -> 26.222635 | AE13: 21 | AF13: 104 | AG13: 125 | AH13: 12684 | AI13: =L13-AH13 -> 1450
A14: 5 | B14: =A14-$G$4 -> 1 | C14: 45929 | D14: Chicken Fried | G14: 45934 | H14: Specials | I14: =P14+X14 -> 52 | J14: =IF(R14="Too early",R14,R14+X14) -> 88.135593 | K14: =IF(J14="Too early",J14,J14/AB14) -> 0.055431191 | L14: =T14+Y14 -> 4410 | M14: =U14+Z14 -> 58000 | N14: =L14/M14 -> 0.076034483 | O14: =IF($J14="Too early",J14,J14*AD14/M14) -> 0.128872 | P14: 52 | Q14: =(AB14-X14)*0.85 -> 1351.5 | R14: =IF(B14<7,(P14/VLOOKUP(B14,'Sales Pacing'!$A$23:$E$36,2)),"Too early") -> 88.135593 | S14: =IF(R14="Too early","Too early",R14/Q14) -> 0.065213166 | T14: 4410 | U14: 58000 | V14: =IF(T14>0,T14/U14,"") -> 0.076034483 | W14: =IF($R14="Too early",R14,R14*AD14/U14) -> 0.128872 | AA14: =IF(Y14>0,Y14/Z14,"") | AB14: 1590 | AC14: =I14/AB14 -> 0.032704403 | AD14: =L14/I14 -> 84.807692 | AE14: 7 | AF14: 70 | AG14: 77 | AH14: 15091 | AI14: =L14-AH14 -> -10681
A15: 6 | B15: =A15-$G$4 -> 2 | C15: 45936 | D15: 26 CS01 Appalachian Spring | G15: 45940.833 | H15: Classical | I15: =P15+X15 -> 764 | J15: =IF(R15="Too early",R15,R15+X15) -> 1063.3478 | K15: =IF(J15="Too early",J15,J15/AB15) -> 0.74204314 | L15: =T15+Y15 -> 48632 | M15: =U15+Z15 -> 49999 | N15: =L15/M15 -> 0.97265945 | O15: =IF($J15="Too early",J15,J15*AD15/M15) -> 1.3537635 | P15: 255 | Q15: =(AB15-X15)*0.85 -> 785.4 | R15: =IF(B15<7,(P15/VLOOKUP(B15,'Sales Pacing'!$A$23:$E$36,2)),"Too early") -> 554.34783 | S15: =IF(R15="Too early","Too early",R15/Q15) -> 0.70581592 | T15: 14669 | U15: 16666 | V15: =IF(T15>0,T15/U15,"") -> 0.88017521 | W15: =IF($R15="Too early",R15,R15*AD15/U15) -> 2.1172871 | X15: 509 | Y15: 33963 | Z15: 33333 | AA15: =IF(Y15>0,Y15/Z15,"") -> 1.0189002 | AB15: 1433 | AC15: =I15/AB15 -> 0.53314724 | AD15: =L15/I15 -> 63.65445 | AE15: 13 | AF15: 370 | AG15: 383 | AH15: 47640 | AI15: =L15-AH15 -> 992
A16: 6 | B16: =A16-$G$4 -> 2 | C16: 45936 | D16: 26 CS01 Appalachian Spring | G16: 45941.833 | H16: Classical | I16: =P16+X16 -> 859 | J16: =IF(R16="Too early",R16,R16+X16) -> 1198.2609 | K16: =IF(J16="Too early",J16,J16/AB16) -> 0.83619042 | L16: =T16+Y16 -> 56697.1 | M16: =U16+Z16 -> 49999 | N16: =L16/M16 -> 1.1339647 | O16: =IF($J16="Too early",J16,J16*AD16/M16) -> 1.5818225 | P16: 289 | Q16: =(AB16-X16)*0.85 -> 733.55 | R16: =IF(B16<7,(P16/VLOOKUP(B16,'Sales Pacing'!$A$23:$E$36,2)),"Too early") -> 628.26087 | S16: =IF(R16="Too early","Too early",R16/Q16) -> 0.85646632 | T16: 18093 | U16: 16666 | V16: =IF(T16>0,T16/U16,"") -> 1.0856234 | W16: =IF($R16="Too early",R16,R16*AD16/U16) -> 2.4881486 | X16: 570 | Y16: 38604.1 | Z16: 33333 | AA16: =IF(Y16>0,Y16/Z16,"") -> 1.1581346 | AB16: 1433 | AC16: =I16/AB16 -> 0.59944173 | AD16: =L16/I16 -> 66.003609 | AE16: 21 | AF16: 386 | AG16: 407 | AH16: 55614.1 | AI16: =L16-AH16 -> 1083
A17: 6 | B17: =A17-$G$4 -> 2 | C17: 45936 | D17: 26 CS01 Appalachian Spring | G17: 45942.583 | H17: Classical | I17: =P17+X17 -> 950 | J17: =IF(R17="Too early",R17,R17+X17) -> 1362.0435 | K17: =IF(J17="Too early",J17,J17/AB17) -> 0.95048393 | L17: =T17+Y17 -> 59240.6 | M17: =U17+Z17 -> 50000 | N17: =L17/M17 -> 1.184812 | O17: =IF($J17="Too early",J17,J17*AD17/M17) -> 1.6987005 | P17: 351 | Q17: =(AB17-X17)*0.85 -> 708.9 | R17: =IF(B17<7,(P17/VLOOKUP(B17,'Sales Pacing'!$A$23:$E$36,2)),"Too early") -> 763.04348 | S17: =IF(R17="Too early","Too early",R17/Q17) -> 1.0763768 | T17: 20577 | U17: 16666 | V17: =IF(T17>0,T17/U17,"") -> 1.2346694 | W17: =IF($R17="Too early",R17,R17*AD17/U17) -> 2.8550502 | X17: 599 | Y17: 38663.6 | Z17: 33334 | AA17: =IF(Y17>0,Y17/Z17,"") -> 1.1598848 | AB17: 1433 | AC17: =I17/AB17 -> 0.66294487 | AD17: =L17/I17 -> 62.358526 | AE17: 17 | AF17: 455 | AG17: 472 | AH17: 57932.6 | AI17: =L17-AH17 -> 1308
A18: 7 | B18: =A18-$G$4 -> 3 | C18: 45943 | D18: 26 Top Gun: Maverick in Concert | G18: 45947.792 | H18: Specials/Film | I18: =P18+X18 -> 716 | J18: =IF(R18="Too early",R18,R18+X18) -> 1835.8974 | K18: =IF(J18="Too early",J18,J18/AB18) -> 1.4100595 | L18: =T18+Y18 -> 53565.5 | M18: =U18+Z18 -> 103497 | N18: =L18/M18 -> 0.51755606 | O18: =IF($J18="Too early",J18,J18*AD18/M18) -> 1.3270668 | P18: 716 | Q18: =(AB18-X18)*0.85 -> 1106.7 | R18: =IF(B18<7,(P18/VLOOKUP(B18,'Sales Pacing'!$A$23:$E$36,2)),"Too early") -> 1835.8974 | S18: =IF(R18="Too early","Too early",R18/Q18) -> 1.6588935 | T18: 53565.5 | U18: 103497 | V18: =IF(T18>0,T18/U18,"") -> 0.51755606 | W18: =IF($R18="Too early",R18,R18*AD18/U18) -> 1.3270668 | AA18: =IF(Y18>0,Y18/Z18,"") | AB18: 1302 | AC18: =I18/AB18 -> 0.5499232 | AD18: =L18/I18 -> 74.812151 | AE18: 51 | AF18: 179 | AG18: 230 | AH18: 48750 | AI18: =L18-AH18 -> 4815.5
A19: 7 | B19: =A19-$G$4 -> 3 | C19: 45943 | D19: 26 Top Gun: Maverick in Concert | G19: 45948.792 | H19: Specials/Film | I19: =P19+X19 -> 861 | J19: =IF(R19="Too early",R19,R19+X19) -> 2207.6923 | K19: =IF(J19="Too early",J19,J19/AB19) -> 1.6956162 | L19: =T19+Y19 -> 64353 | M19: =U19+Z19 -> 103497 | N19: =L19/M19 -> 0.62178614 | O19: =IF($J19="Too early",J19,J19*AD19/M19) -> 1.5943234 | P19: 861 | Q19: =(AB19-X19)*0.85 -> 1106.7 | R19: =IF(B19<7,(P19/VLOOKUP(B19,'Sales Pacing'!$A$23:$E$36,2)),"Too early") -> 2207.6923 | S19: =IF(R19="Too early","Too early",R19/Q19) -> 1.9948426 | T19: 64353 | U19: 103497 | V19: =IF(T19>0,T19/U19,"") -> 0.62178614 | W19: =IF($R19="Too early",R19,R19*AD19/U19) -> 1.5943234 | AA19: =IF(Y19>0,Y19/Z19,"") | AB19: 1302 | AC19: =I19/AB19 -> 0.66129032 | AD19: =L19/I19 -> 74.74216 | AE19: 74 | AF19: 184 | AG19: 258 | AH19: 60628 | AI19: =L19-AH19 -> 3725
A20: 7 | B20: =A20-$G$4 -> 3 | C20: 45943 | D20: 26 Top Gun: Maverick in Concert | G20: 45949.583 | H20: Specials/Film | I20: =P20+X20 -> 650 | J20: =IF(R20="Too early",R20,R20+X20) -> 1666.6667 | K20: =IF(J20="Too early",J20,J20/AB20) -> 1.2800819 | L20: =T20+Y20 -> 48516 | M20: =U20+Z20 -> 103496 | N20: =L20/M20 -> 0.46877174 | O20: =IF($J20="Too early",J20,J20*AD20/M20) -> 1.2019788 | P20: 650 | Q20: =(AB20-X20)*0.85 -> 1106.7 | R20: =IF(B20<7,(P20/VLOOKUP(B20,'Sales Pacing'!$A$23:$E$36,2)),"Too early") -> 1666.6667 | S20: =IF(R20="Too early","Too early",R20/Q20) -> 1.5059787 | T20: 48516 | U20: 103496 | V20: =IF(T20>0,T20/U20,"") -> 0.46877174 | W20: =IF($R20="Too early",R20,R20*AD20/U20) -> 1.2019788 | AA20: =IF(Y20>0,Y20/Z20,"") | AB20: 1302 | AC20: =I20/AB20 -> 0.49923195 | AD20: =L20/I20 -> 74.64 | AE20: 38 | AF20: 149 | AG20: 187 | AH20: 44494 | AI20: =L20-AH20 -> 4022
A21: 8 | B21: =A21-$G$4 -> 4 | C21: 45950 | D21: 26 The Lodger | G21: 45952.792 | H21: Specials/Film | I21: =P21+X21 -> 216 | J21: =IF(R21="Too early",R21,R21+X21) -> 654.54545 | K21: =IF(J21="Too early",J21,J21/AB21) -> 0.50272308 | L21: =T21+Y21 -> 11006 | M21: =U21+Z21 -> 50000 | N21: =L21/M21 -> 0.22012 | O21: =IF($J21="Too early",J21,J21*AD21/M21) -> 0.6670303 | P21: 216 | Q21: =(AB21-X21)*0.85 -> 1106.7 | R21: =IF(B21<7,(P21/VLOOKUP(B21,'Sales Pacing'!$A$23:$E$36,2)),"Too early") -> 654.54545 | S21: =IF(R21="Too early","Too early",R21/Q21) -> 0.59143892 | T21: 11006 | U21: 50000 | V21: =IF(T21>0,T21/U21,"") -> 0.22012 | W21: =IF($R21="Too early",R21,R21*AD21/U21) -> 0.6670303 | AA21: =IF(Y21>0,Y21/Z21,"") | AB21: 1302 | AC21: =I21/AB21 -> 0.16589862 | AD21: =L21/I21 -> 50.953704 | AE21: 5 | AF21: 78 | AG21: 83 | AH21: 10588 | AI21: =L21-AH21 -> 418
A22: 8 | B22: =A22-$G$4 -> 4 | C22: 45950 | D22: 26 PS2 90s Mixtape | G22: 45954.833 | H22: Pops | I22: =P22+X22 -> 829 | J22: =IF(R22="Too early",R22,R22+X22) -> 1074.6667 | K22: =IF(J22="Too early",J22,J22/AB22) -> 0.67589099 | L22: =T22+Y22 -> 58685.9 | M22: =U22+Z22 -> 92333 | N22: =L22/M22 -> 0.63558966 | O22: =IF($J22="Too early",J22,J22*AD22/M22) -> 0.82394092 | P22: 121 | Q22: =(AB22-X22)*0.85 -> 749.7 | R22: =IF(B22<7,(P22/VLOOKUP(B22,'Sales Pacing'!$A$23:$E$36,2)),"Too early") -> 366.66667 | S22: =IF(R22="Too early","Too early",R22/Q22) -> 0.48908452 | T22: 7406 | U22: 53333 | V22: =IF(T22>0,T22/U22,"") -> 0.13886337 | W22: =IF($R22="Too early",R22,R22*AD22/U22) -> 0.4866925 | X22: 708 | Y22: 51279.9 | Z22: 39000 | AA22: =IF(Y22>0,Y22/Z22,"") -> 1.3148692 | AB22: 1590 | AC22: =I22/AB22 -> 0.52138365 | AD22: =L22/I22 -> 70.791194 | AE22: 7 | AF22: 350 | AG22: 357 | AH22: 57609.1 | AI22: =L22-AH22 -> 1076.8
A23: 8 | B23: =A23-$G$4 -> 4 | C23: 45950 | D23: 26 PS2 90s Mixtape | G23: 45955.833 | H23: Pops | I23: =P23+X23 -> 787 | J23: =IF(R23="Too early",R23,R23+X23) -> 1107.7879 | K23: =IF(J23="Too early",J23,J23/AB23) -> 0.69672194 | L23: =T23+Y23 -> 54528.8 | M23: =U23+Z23 -> 92333 | N23: =L23/M23 -> 0.59056675 | O23: =IF($J23="Too early",J23,J23*AD23/M23) -> 0.83128677 | P23: 158 | Q23: =(AB23-X23)*0.85 -> 816.85 | R23: =IF(B23<7,(P23/VLOOKUP(B23,'Sales Pacing'!$A$23:$E$36,2)),"Too early") -> 478.78788 | S23: =IF(R23="Too early","Too early",R23/Q23) -> 0.58613929 | T23: 9368 | U23: 53333 | V23: =IF(T23>0,T23/U23,"") -> 0.1756511 | W23: =IF($R23="Too early",R23,R23*AD23/U23) -> 0.6220114 | X23: 629 | Y23: 45160.8 | Z23: 39000 | AA23: =IF(Y23>0,Y23/Z23,"") -> 1.1579692 | AB23: 1590 | AC23: =I23/AB23 -> 0.49496855 | AD23: =L23/I23 -> 69.286912 | AE23: 11 | AF23: 320 | AG23: 311 | AH23: 52382.8 | AI23: =L23-AH23 -> 2146
A24: 8 | B24: =A24-$G$4 -> 4 | C24: 45950 | D24: 26 PS2 90s Mixtape | G24: 45956.583 | H24: Pops | I24: =P24+X24 -> 501 | J24: =IF(R24="Too early",R24,R24+X24) -> 742.60606 | K24: =IF(J24="Too early",J24,J24/AB24) -> 0.46704784 | L24: =T24+Y24 -> 33546.5 | M24: =U24+Z24 -> 92333 | N24: =L24/M24 -> 0.36332081 | O24: =IF($J24="Too early",J24,J24*AD24/M24) -> 0.5385314 | P24: 119 | Q24: =(AB24-X24)*0.85 -> 1026.8 | R24: =IF(B24<7,(P24/VLOOKUP(B24,'Sales Pacing'!$A$23:$E$36,2)),"Too early") -> 360.60606 | S24: =IF(R24="Too early","Too early",R24/Q24) -> 0.35119406 | T24: 7648 | U24: 53333 | V24: =IF(T24>0,T24/U24,"") -> 0.1434009 | W24: =IF($R24="Too early",R24,R24*AD24/U24) -> 0.45273753 | X24: 382 | Y24: 25898.5 | Z24: 39000 | AA24: =IF(Y24>0,Y24/Z24,"") -> 0.6640641 | AB24: 1590 | AC24: =I24/AB24 -> 0.31509434 | AD24: =L24/I24 -> 66.959082 | AE24: 6 | AF24: 209 | AG24: 203 | AH24: 31818.5 | AI24: =L24-AH24 -> 1728
A25: 9 | B25: =A25-$G$4 -> 5 | C25: 45957 | D25: 26 On-Stage 1 George Li | G25: 45959.833 | H25: On Stage | I25: =P25+X25 -> 25 | J25: =IF(R25="Too early",R25,R25+X25) -> 83.333333 | K25: =IF(J25="Too early",J25,J25/AB25) -> 0.83333333 | L25: =T25+Y25 -> 2800 | M25: 11200 | N25: =L25/M25 -> 0.25 | O25: =IF($J25="Too early",J25,J25*AD25/M25) -> 0.83333333 | P25: 25 | Q25: =(AB25-X25)*0.85 -> 85 | R25: =IF(B25<7,(P25/VLOOKUP(B25,'Sales Pacing'!$A$23:$E$36,2)),"Too early") -> 83.333333 | S25: =IF(R25="Too early","Too early",R25/Q25) -> 0.98039216 | T25: 2800 | U25: 11200 | V25: =IF(T25>0,T25/U25,"") -> 0.25 | W25: =IF($R25="Too early",R25,R25*AD25/U25) -> 0.83333333 | AA25: =IF(Y25>0,Y25/Z25,"") | AB25: 100 | AC25: =I25/AB25 -> 0.25 | AD25: =L25/I25 -> 112 | AE25: 0 | AF25: 11 | AG25: 11 | AH25: 2800 | AI25: =L25-AH25 -> 0
A26: 9 | B26: =A26-$G$4 -> 5 | C26: 45957 | D26: 26 CS02 Rachmaninoff Cele Pt 1 | G26: 45961.833 | H26: Classical | I26: =P26+X26 -> 479 | J26: =IF(R26="Too early",R26,R26+X26) -> 798.66667 | K26: =IF(J26="Too early",J26,J26/AB26) -> 0.55733892 | L26: =T26+Y26 -> 31327 | M26: =U26+Z26 -> 52000 | N26: =L26/M26 -> 0.60244231 | O26: =IF($J26="Too early",J26,J26*AD26/M26) -> 1.0044897 | P26: 137 | Q26: =(AB26-X26)*0.85 -> 927.35 | R26: =IF(B26<7,(P26/VLOOKUP(B26,'Sales Pacing'!$A$23:$E$36,2)),"Too early") -> 456.66667 | S26: =IF(R26="Too early","Too early",R26/Q26) -> 0.49244262 | T26: 7526 | U26: 22000 | V26: =IF(T26>0,T26/U26,"") -> 0.34209091 | W26: =IF($R26="Too early",R26,R26*AD26/U26) -> 1.3575628 | X26: 342 | Y26: 23801 | Z26: 30000 | AA26: =IF(Y26>0,Y26/Z26,"") -> 0.79336667 | AB26: 1433 | AC26: =I26/AB26 -> 0.33426378 | AD26: =L26/I26 -> 65.400835 | AE26: 10 | AF26: 222 | AG26: 232 | AH26: 30757 | AI26: =L26-AH26 -> 570
A27: 9 | B27: =A27-$G$4 -> 5 | C27: 45957 | D27: 26 CS02 Rachmaninoff Cele Pt 1 | G27: 45962.833 | H27: Classical | I27: =P27+X27 -> 964 | J27: =IF(R27="Too early",R27,R27+X27) -> 1911.3333 | K27: =IF(J27="Too early",J27,J27/AB27) -> 1.3337986 | L27: =T27+Y27 -> 60170 | M27: =U27+Z27 -> 86500 | N27: =L27/M27 -> 0.69560694 | O27: =IF($J27="Too early",J27,J27*AD27/M27) -> 1.3791875 | P27: 406 | Q27: =(AB27-X27)*0.85 -> 743.75 | R27: =IF(B27<7,(P27/VLOOKUP(B27,'Sales Pacing'!$A$23:$E$36,2)),"Too early") -> 1353.3333 | S27: =IF(R27="Too early","Too early",R27/Q27) -> 1.8196078 | T27: 23689 | U27: 31500 | V27: =IF(T27>0,T27/U27,"") -> 0.75203175 | W27: =IF($R27="Too early",R27,R27*AD27/U27) -> 2.6816198 | X27: 558 | Y27: 36481 | Z27: 55000 | AA27: =IF(Y27>0,Y27/Z27,"") -> 0.66329091 | AB27: 1433 | AC27: =I27/AB27 -> 0.67271458 | AD27: =L27/I27 -> 62.417012 | AE27: 26 | AF27: 397 | AG27: 423 | AH27: 57693 | AI27: =L27-AH27 -> 2477
A28: 9 | B28: =A28-$G$4 -> 5 | C28: 45957 | D28: 26 CS02 Rachmaninoff Cele Pt 1 | G28: 45963.583 | H28: Classical | I28: =P28+X28 -> 852 | J28: =IF(R28="Too early",R28,R28+X28) -> 1531 | K28: =IF(J28="Too early",J28,J28/AB28) -> 1.068388 | L28: =T28+Y28 -> 53260.1 | M28: =U28+Z28 -> 86500 | N28: =L28/M28 -> 0.6157237 | O28: =IF($J28="Too early",J28,J28*AD28/M28) -> 1.1064237 | P28: 291 | Q28: =(AB28-X28)*0.85 -> 741.2 | R28: =IF(B28<7,(P28/VLOOKUP(B28,'Sales Pacing'!$A$23:$E$36,2)),"Too early") -> 970 | S28: =IF(R28="Too early","Too early",R28/Q28) -> 1.3086886 | T28: 17068 | U28: 31500 | V28: =IF(T28>0,T28/U28,"") -> 0.54184127 | W28: =IF($R28="Too early",R28,R28*AD28/U28) -> 1.9249682 | X28: 561 | Y28: 36192.1 | Z28: 55000 | AA28: =IF(Y28>0,Y28/Z28,"") -> 0.65803818 | AB28: 1433 | AC28: =I28/AB28 -> 0.59455687 | AD28: =L28/I28 -> 62.511854 | AE28: 17 | AF28: 407 | AG28: 424 | AH28: 51432.1 | AI28: =L28-AH28 -> 1828
A29: 10 | B29: =A29-$G$4 -> 6 | C29: 45964 | D29: 26 FS2 Carnival of the Animals | G29: 45970.583 | H29: Family | I29: =P29+X29 -> 465 | J29: =IF(R29="Too early",R29,R29+X29) -> 892.18519 | K29: =IF(J29="Too early",J29,J29/AB29) -> 0.6862963 | L29: =T29+Y29 -> 11301 | M29: =U29+Z29 -> 19500 | N29: =L29/M29 -> 0.57953846 | O29: =IF($J29="Too early",J29,J29*AD29/M29) -> 1.1119476 | P29: 158 | Q29: =(AB29-X29)*0.85 -> 844.05 | R29: =IF(B29<7,(P29/VLOOKUP(B29,'Sales Pacing'!$A$23:$E$36,2)),"Too early") -> 585.18519 | S29: =IF(R29="Too early","Too early",R29/Q29) -> 0.6933063 | T29: 4465 | U29: 10000 | V29: =IF(T29>0,T29/U29,"") -> 0.4465 | W29: =IF($R29="Too early",R29,R29*AD29/U29) -> 1.4221888 | X29: 307 | Y29: 6836 | Z29: 9500 | AA29: =IF(Y29>0,Y29/Z29,"") -> 0.71957895 | AB29: 1300 | AC29: =I29/AB29 -> 0.35769231 | AD29: =L29/I29 -> 24.303226 | AE29: 9 | AF29: 103 | AG29: 112 | AH29: 10703 | AI29: =L29-AH29 -> 598
A30: 11 | B30: =A30-$G$4 -> 7 | C30: 45971 | D30: OPEN | I30: =P30+X30 -> 0 | J30: =IF(R30="Too early",R30,R30+X30) -> Too early | L30: =T30+Y30 -> 0 | M30: =U30+Z30 -> 0 | N30: =L30/M30 -> #DIV/0! | R30: =IF(B30<7,(P30/VLOOKUP(B30,'Sales Pacing'!$A$23:$E$36,2)),"Too early") -> Too early | V30: =IF(T30>0,T30/U30,"") | AA30: N/A | AC30: =I30/AB30 -> #DIV/0! | AD30: =L30/I30 -> #DIV/0! | AH30: 0
A31: 12 | B31: =A31-$G$4 -> 8 | C31: 45978 | D31: 26 CS03 Matthias and Mahler 7 | G31: 45982.833 | H31: Classical | I31: =P31+X31 -> 446 | J31: =IF(R31="Too early",R31,R31+X31) -> Too early | K31: =IF(J31="Too early",J31,J31/AB31) -> Too early | L31: =T31+Y31 -> 29373 | M31: =U31+Z31 -> 40000 | N31: =L31/M31 -> 0.734325 | O31: =IF($J31="Too early",J31,J31*AD31/M31) -> Too early | P31: 79 | Q31: =(AB31-X31)*0.85 -> 1039.55 | R31: =IF(B31<7,(P31/VLOOKUP(B31,'Sales Pacing'!$A$23:$E$36,2)),"Too early") -> Too early | S31: =IF(R31="Too early","Too early",R31/Q31) -> Too early | T31: 4025 | U31: 15000 | V31: =IF(T31>0,T31/U31,"") -> 0.26833333 | W31: =IF($R31="Too early",R31,R31*AD31/U31) -> Too early | X31: 367 | Y31: 25348 | Z31: 25000 | AA31: =IF(Y31>0,Y31/Z31,"") -> 1.01392 | AB31: 1590 | AC31: =I31/AB31 -> 0.28050314 | AD31: =L31/I31 -> 65.858744 | AE31: 1 | AF31: 221 | AG31: 222 | AH31: 29114 | AI31: =L31-AH31 -> 259
A32: 12 | B32: =A32-$G$4 -> 8 | C32: 45978 | D32: 26 CS03 Matthias and Mahler 7 | G32: 45983.833 | H32: Classical | I32: =P32+X32 -> 705 | J32: =IF(R32="Too early",R32,R32+X32) -> Too early | K32: =IF(J32="Too early",J32,J32/AB32) -> Too early | L32: =T32+Y32 -> 47252.9 | M32: =U32+Z32 -> 66500 | N32: =L32/M32 -> 0.71056992 | O32: =IF($J32="Too early",J32,J32*AD32/M32) -> Too early | P32: 122 | Q32: =(AB32-X32)*0.85 -> 855.95 | R32: =IF(B32<7,(P32/VLOOKUP(B32,'Sales Pacing'!$A$23:$E$36,2)),"Too early") -> Too early | S32: =IF(R32="Too early","Too early",R32/Q32) -> Too early | T32: 7546 | U32: 11500 | V32: =IF(T32>0,T32/U32,"") -> 0.65617391 | W32: =IF($R32="Too early",R32,R32*AD32/U32) -> Too early | X32: 583 | Y32: 39706.9 | Z32: 55000 | AA32: =IF(Y32>0,Y32/Z32,"") -> 0.72194364 | AB32: 1590 | AC32: =I32/AB32 -> 0.44339623 | AD32: =L32/I32 -> 67.02539 | AE32: 4 | AF32: 347 | AG32: 351 | AH32: 47477.9 | AI32: =L32-AH32 -> -225
A33: 12 | B33: =A33-$G$4 -> 8 | C33: 45978 | D33: 26 CS03 Matthias and Mahler 7 | G33: 45984.583 | H33: Classical | I33: =P33+X33 -> 722 | J33: =IF(R33="Too early",R33,R33+X33) -> Too early | K33: =IF(J33="Too early",J33,J33/AB33) -> Too early | L33: =T33+Y33 -> 46768.2 | M33: =U33+Z33 -> 66500 | N33: =L33/M33 -> 0.7032812 | O33: =IF($J33="Too early",J33,J33*AD33/M33) -> Too early | P33: 100 | Q33: =(AB33-X33)*0.85 -> 822.8 | R33: =IF(B33<7,(P33/VLOOKUP(B33,'Sales Pacing'!$A$23:$E$36,2)),"Too early") -> Too early | S33: =IF(R33="Too early","Too early",R33/Q33) -> Too early | T33: 6613 | U33: 11500 | V33: =IF(T33>0,T33/U33,"") -> 0.57504348 | W33: =IF($R33="Too early",R33,R33*AD33/U33) -> Too early | X33: 622 | Y33: 40155.2 | Z33: 55000 | AA33: =IF(Y33>0,Y33/Z33,"") -> 0.73009455 | AB33: 1590 | AC33: =I33/AB33 -> 0.45408805 | AD33: =L33/I33 -> 64.7759 | AE33: 3 | AF33: 391 | AG33: 394 | AH33: 46613.2 | AI33: =L33-AH33 -> 155
A34: 13 | B34: =A34-$G$4 -> 9 | C34: 45985 | D34: 26 Elf™ in Concert | G34: 45989.792 | H34: Specials/Film | I34: =P34+X34 -> 327 | J34: =IF(R34="Too early",R34,R34+X34) -> Too early | K34: =IF(J34="Too early",J34,J34/AB34) -> Too early | L34: =T34+Y34 -> 22459 | M34: =U34+Z34 -> 107500 | N34: =L34/M34 -> 0.20892093 | O34: =IF($J34="Too early",J34,J34*AD34/M34) -> Too early | P34: 327 | Q34: =(AB34-X34)*0.85 -> 1106.7 | R34: =IF(B34<7,(P34/VLOOKUP(B34,'Sales Pacing'!$A$23:$E$36,2)),"Too early") -> Too early | S34: =IF(R34="Too early","Too early",R34/Q34) -> Too early | T34: 22459 | U34: 107500 | V34: =IF(T34>0,T34/U34,"") -> 0.20892093 | W34: =IF($R34="Too early",R34,R34*AD34/U34) -> Too early | AA34: =IF(Y34>0,Y34/Z34,"") | AB34: 1302 | AC34: =I34/AB34 -> 0.25115207 | AD34: =L34/I34 -> 68.681957 | AE34: 17 | AF34: 45 | AG34: 62 | AH34: 20977.6 | AI34: =L34-AH34 -> 1481.4
A35: 13 | B35: =A35-$G$4 -> 9 | C35: 45985 | D35: 26 Elf™ in Concert | G35: 45990.542 | H35: Specials/Film | I35: =P35+X35 -> 374 | J35: =IF(R35="Too early",R35,R35+X35) -> Too early | K35: =IF(J35="Too early",J35,J35/AB35) -> Too early | L35: =T35+Y35 -> 24726.6 | M35: =U35+Z35 -> 107500 | N35: =L35/M35 -> 0.23001488 | O35: =IF($J35="Too early",J35,J35*AD35/M35) -> Too early | P35: 374 | Q35: =(AB35-X35)*0.85 -> 1106.7 | R35: =IF(B35<7,(P35/VLOOKUP(B35,'Sales Pacing'!$A$23:$E$36,2)),"Too early") -> Too early | S35: =IF(R35="Too early","Too early",R35/Q35) -> Too early | T35: 24726.6 | U35: 107500 | V35: =IF(T35>0,T35/U35,"") -> 0.23001488 | W35: =IF($R35="Too early",R35,R35*AD35/U35) -> Too early | AA35: =IF(Y35>0,Y35/Z35,"") | AB35: 1302 | AC35: =I35/AB35 -> 0.28725038 | AD35: =L35/I35 -> 66.113904 | AE35: 22 | AF35: 53 | AG35: 75 | AH35: 24414.6 | AI35: =L35-AH35 -> 312
A36: 13 | B36: =A36-$G$4 -> 9 | C36: 45985 | D36: 26 Elf™ in Concert | G36: 45990.792 | H36: Specials/Film | I36: =P36+X36 -> 303 | J36: =IF(R36="Too early",R36,R36+X36) -> Too early | K36: =IF(J36="Too early",J36,J36/AB36) -> Too early | L36: =T36+Y36 -> 20120 | M36: =U36+Z36 -> 107500 | N36: =L36/M36 -> 0.18716279 | O36: =IF($J36="Too early",J36,J36*AD36/M36) -> Too early | P36: 303 | Q36: =(AB36-X36)*0.85 -> 1106.7 | R36: =IF(B36<7,(P36/VLOOKUP(B36,'Sales Pacing'!$A$23:$E$36,2)),"Too early") -> Too early | S36: =IF(R36="Too early","Too early",R36/Q36) -> Too early | T36: 20120 | U36: 107500 | V36: =IF(T36>0,T36/U36,"") -> 0.18716279 | W36: =IF($R36="Too early",R36,R36*AD36/U36) -> Too early | AA36: =IF(Y36>0,Y36/Z36,"") | AB36: 1302 | AC36: =I36/AB36 -> 0.23271889 | AD36: =L36/I36 -> 66.40264 | AE36: 12 | AF36: 56 | AG36: 68 | AH36: 19000 | AI36: =L36-AH36 -> 1120
A37: 13 | B37: =A37-$G$4 -> 9 | C37: 45985 | D37: 26 Elf™ in Concert | G37: 45991.583 | H37: Specials/Film | I37: =P37+X37 -> 524 | J37: =IF(R37="Too early",R37,R37+X37) -> Too early | K37: =IF(J37="Too early",J37,J37/AB37) -> Too early | L37: =T37+Y37 -> 36614.6 | M37: =U37+Z37 -> 107500 | N37: =L37/M37 -> 0.34060093 | O37: =IF($J37="Too early",J37,J37*AD37/M37) -> Too early | P37: 524 | Q37: =(AB37-X37)*0.85 -> 1106.7 | R37: =IF(B37<7,(P37/VLOOKUP(B37,'Sales Pacing'!$A$23:$E$36,2)),"Too early") -> Too early | S37: =IF(R37="Too early","Too early",R37/Q37) -> Too early | T37: 36614.6 | U37: 107500 | V37: =IF(T37>0,T37/U37,"") -> 0.34060093 | W37: =IF($R37="Too early",R37,R37*AD37/U37) -> Too early | AA37: =IF(Y37>0,Y37/Z37,"") | AB37: 1302 | AC37: =I37/AB37 -> 0.40245776 | AD37: =L37/I37 -> 69.875191 | AE37: 21 | AF37: 88 | AG37: 109 | AH37: 34569.6 | AI37: =L37-AH37 -> 2045
A38: 14 | B38: =A38-$G$4 -> 10 | C38: 45992 | D38: 26 Handel's Messiah | G38: 45996.792 | H38: Holiday | I38: =P38+X38 -> 373 | J38: =IF(R38="Too early",R38,R38+X38) -> Too early | K38: =IF(J38="Too early",J38,J38/AB38) -> Too early | L38: =T38+Y38 -> 19843.5 | M38: =U38+Z38 -> 78333 | N38: =L38/M38 -> 0.25332235 | O38: =IF($J38="Too early",J38,J38*AD38/M38) -> Too early | P38: 373 | Q38: =(AB38-X38)*0.85 -> 1218.05 | R38: =IF(B38<7,(P38/VLOOKUP(B38,'Sales Pacing'!$A$23:$E$36,2)),"Too early") -> Too early | S38: =IF(R38="Too early","Too early",R38/Q38) -> Too early | T38: 19843.5 | U38: 78333 | V38: =IF(T38>0,T38/U38,"") -> 0.25332235 | W38: =IF($R38="Too early",R38,R38*AD38/U38) -> Too early | AA38: =IF(Y38>0,Y38/Z38,"") | AB38: 1433 | AC38: =I38/AB38 -> 0.26029309 | AD38: =L38/I38 -> 53.199732 | AE38: 19 | AF38: 86 | AG38: 105 | AH38: 18853.5 | AI38: =L38-AH38 -> 990
A39: 14 | B39: =A39-$G$4 -> 10 | C39: 45992 | D39: 26 Handel's Messiah | G39: 45997.792 | H39: Holiday | I39: =P39+X39 -> 378 | J39: =IF(R39="Too early",R39,R39+X39) -> Too early | K39: =IF(J39="Too early",J39,J39/AB39) -> Too early | L39: =T39+Y39 -> 22606.5 | M39: =U39+Z39 -> 78334 | N39: =L39/M39 -> 0.28859116 | O39: =IF($J39="Too early",J39,J39*AD39/M39) -> Too early | P39: 378 | Q39: =(AB39-X39)*0.85 -> 1218.05 | R39: =IF(B39<7,(P39/VLOOKUP(B39,'Sales Pacing'!$A$23:$E$36,2)),"Too early") -> Too early | S39: =IF(R39="Too early","Too early",R39/Q39) -> Too early | T39: 22606.5 | U39: 78334 | V39: =IF(T39>0,T39/U39,"") -> 0.28859116 | W39: =IF($R39="Too early",R39,R39*AD39/U39) -> Too early | AA39: =IF(Y39>0,Y39/Z39,"") | AB39: 1433 | AC39: =I39/AB39 -> 0.26378227 | AD39: =L39/I39 -> 59.805556 | AE39: 20 | AF39: 95 | AG39: 115 | AH39: 22001.5 | AI39: =L39-AH39 -> 605
A40: 14 | B40: =A40-$G$4 -> 10 | C40: 45992 | D40: 26 Handel's Messiah | G40: 45998.583 | H40: Holiday | I40: =P40+X40 -> 425 | J40: =IF(R40="Too early",R40,R40+X40) -> Too early | K40: =IF(J40="Too early",J40,J40/AB40) -> Too early | L40: =T40+Y40 -> 22602.5 | M40: =U40+Z40 -> 78333 | N40: =L40/M40 -> 0.28854378 | O40: =IF($J40="Too early",J40,J40*AD40/M40) -> Too early | P40: 425 | Q40: =(AB40-X40)*0.85 -> 1218.05 | R40: =IF(B40<7,(P40/VLOOKUP(B40,'Sales Pacing'!$A$23:$E$36,2)),"Too early") -> Too early | S40: =IF(R40="Too early","Too early",R40/Q40) -> Too early | T40: 22602.5 | U40: 78333 | V40: =IF(T40>0,T40/U40,"") -> 0.28854378 | W40: =IF($R40="Too early",R40,R40*AD40/U40) -> Too early | AA40: =IF(Y40>0,Y40/Z40,"") | AB40: 1433 | AC40: =I40/AB40 -> 0.2965806 | AD40: =L40/I40 -> 53.182353 | AE40: 26 | AF40: 105 | AG40: 131 | AH40: 21652.5 | AI40: =L40-AH40 -> 950
A41: 15 | B41: =A41-$G$4 -> 11 | C41: 45999 | D41: 26 Leslie Odom Jr.: Christmas | G41: 46003.792 | H41: Specials | I41: =P41+X41 -> 1049 | J41: =IF(R41="Too early",R41,R41+X41) -> Too early | K41: =IF(J41="Too early",J41,J41/AB41) -> Too early | L41: =T41+Y41 -> 107292 | M41: =U41+Z41 -> 150000 | N41: =L41/M41 -> 0.71528 | O41: =IF($J41="Too early",J41,J41*AD41/M41) -> Too early | P41: 1049 | Q41: =(AB41-X41)*0.85 -> 1351.5 | R41: =IF(B41<7,(P41/VLOOKUP(B41,'Sales Pacing'!$A$23:$E$36,2)),"Too early") -> Too early | S41: =IF(R41="Too early","Too early",R41/Q41) -> Too early | T41: 107292 | U41: 150000 | V41: =IF(T41>0,T41/U41,"") -> 0.71528 | W41: =IF($R41="Too early",R41,R41*AD41/U41) -> Too early | AA41: =IF(Y41>0,Y41/Z41,"") | AB41: 1590 | AC41: =I41/AB41 -> 0.65974843 | AD41: =L41/I41 -> 102.28027 | AE41: 87 | AF41: 264 | AG41: 351 | AH41: 103427 | AI41: =L41-AH41 -> 3865
A42: 15 | B42: =A42-$G$4 -> 11 | C42: 45999 | D42: 26 Leslie Odom Jr.: Christmas | G42: 46004.792 | H42: Specials | I42: =P42+X42 -> 1285 | J42: =IF(R42="Too early",R42,R42+X42) -> Too early | K42: =IF(J42="Too early",J42,J42/AB42) -> Too early | L42: =T42+Y42 -> 127498.5 | M42: =U42+Z42 -> 150000 | N42: =L42/M42 -> 0.84999 | O42: =IF($J42="Too early",J42,J42*AD42/M42) -> Too early | P42: 1285 | Q42: =(AB42-X42)*0.85 -> 1351.5 | R42: =IF(B42<7,(P42/VLOOKUP(B42,'Sales Pacing'!$A$23:$E$36,2)),"Too early") -> Too early | S42: =IF(R42="Too early","Too early",R42/Q42) -> Too early | T42: 127498.5 | U42: 150000 | V42: =IF(T42>0,T42/U42,"") -> 0.84999 | W42: =IF($R42="Too early",R42,R42*AD42/U42) -> Too early | AA42: =IF(Y42>0,Y42/Z42,"") | AB42: 1590 | AC42: =I42/AB42 -> 0.8081761 | AD42: =L42/I42 -> 99.220623 | AE42: 128 | AF42: 291 | AG42: 419 | AH42: 123198 | AI42: =L42-AH42 -> 4300.5
A43: 16 | B43: =A43-$G$4 -> 12 | C43: 46006 | D43: 26 Christmas Festival | G43: 46009.792 | H43: Holiday | I43: =P43+X43 -> 224 | J43: =IF(R43="Too early",R43,R43+X43) -> Too early | K43: =IF(J43="Too early",J43,J43/AB43) -> Too early | L43: =T43+Y43 -> 13589 | M43: =U43+Z43 -> 75833 | N43: =L43/M43 -> 0.17919639 | O43: =IF($J43="Too early",J43,J43*AD43/M43) -> Too early | P43: 224 | Q43: =(AB43-X43)*0.85 -> 1218.05 | R43: =IF(B43<7,(P43/VLOOKUP(B43,'Sales Pacing'!$A$23:$E$36,2)),"Too early") -> Too early | S43: =IF(R43="Too early","Too early",R43/Q43) -> Too early | T43: 13589 | U43: 75833 | V43: =IF(T43>0,T43/U43,"") -> 0.17919639 | W43: =IF($R43="Too early",R43,R43*AD43/U43) -> Too early | AA43: =IF(Y43>0,Y43/Z43,"") | AB43: 1433 | AC43: =I43/AB43 -> 0.15631542 | AD43: =L43/I43 -> 60.665179 | AH43: 13189 | AI43: =L43-AH43 -> 400
A44: 16 | B44: =A44-$G$4 -> 12 | C44: 46006 | D44: 26 Christmas Festival | G44: 46010.792 | H44: Holiday | I44: =P44+X44 -> 200 | J44: =IF(R44="Too early",R44,R44+X44) -> Too early | K44: =IF(J44="Too early",J44,J44/AB44) -> Too early | L44: =T44+Y44 -> 12059.5 | M44: =U44+Z44 -> 75833 | N44: =L44/M44 -> 0.15902707 | O44: =IF($J44="Too early",J44,J44*AD44/M44) -> Too early | P44: 200 | Q44: =(AB44-X44)*0.85 -> 1218.05 | R44: =IF(B44<7,(P44/VLOOKUP(B44,'Sales Pacing'!$A$23:$E$36,2)),"Too early") -> Too early | S44: =IF(R44="Too early","Too early",R44/Q44) -> Too early | T44: 12059.5 | U44: 75833 | V44: =IF(T44>0,T44/U44,"") -> 0.15902707 | W44: =IF($R44="Too early",R44,R44*AD44/U44) -> Too early | AA44: =IF(Y44>0,Y44/Z44,"") | AB44: 1433 | AC44: =I44/AB44 -> 0.13956734 | AD44: =L44/I44 -> 60.2975 | AH44: 11666.5 | AI44: =L44-AH44 -> 393
A45: 16 | B45: =A45-$G$4 -> 12 | C45: 46006 | D45: 26 Christmas Festival | G45: 46011.542 | H45: Holiday | I45: =P45+X45 -> 369 | J45: =IF(R45="Too early",R45,R45+X45) -> Too early | K45: =IF(J45="Too early",J45,J45/AB45) -> Too early | L45: =T45+Y45 -> 22722.5 | M45: =U45+Z45 -> 75833 | N45: =L45/M45 -> 0.29963868 | O45: =IF($J45="Too early",J45,J45*AD45/M45) -> Too early | P45: 369 | Q45: =(AB45-X45)*0.85 -> 1218.05 | R45: =IF(B45<7,(P45/VLOOKUP(B45,'Sales Pacing'!$A$23:$E$36,2)),"Too early") -> Too early | S45: =IF(R45="Too early","Too early",R45/Q45) -> Too early | T45: 22722.5 | U45: 75833 | V45: =IF(T45>0,T45/U45,"") -> 0.29963868 | W45: =IF($R45="Too early",R45,R45*AD45/U45) -> Too early | AA45: =IF(Y45>0,Y45/Z45,"") | AB45: 1433 | AC45: =I45/AB45 -> 0.25750174 | AD45: =L45/I45 -> 61.578591 | AH45: 21404.5 | AI45: =L45-AH45 -> 1318
A46: 16 | B46: =A46-$G$4 -> 12 | C46: 46006 | D46: 26 Christmas Festival | G46: 46011.792 | H46: Holiday | I46: =P46+X46 -> 263 | J46: =IF(R46="Too early",R46,R46+X46) -> Too early | K46: =IF(J46="Too early",J46,J46/AB46) -> Too early | L46: =T46+Y46 -> 16417 | M46: =U46+Z46 -> 75833 | N46: =L46/M46 -> 0.21648886 | O46: =IF($J46="Too early",J46,J46*AD46/M46) -> Too early | P46: 263 | Q46: =(AB46-X46)*0.85 -> 1218.05 | R46: =IF(B46<7,(P46/VLOOKUP(B46,'Sales Pacing'!$A$23:$E$36,2)),"Too early") -> Too early | S46: =IF(R46="Too early","Too early",R46/Q46) -> Too early | T46: 16417 | U46: 75833 | V46: =IF(T46>0,T46/U46,"") -> 0.21648886 | W46: =IF($R46="Too early",R46,R46*AD46/U46) -> Too early | AA46: =IF(Y46>0,Y46/Z46,"") | AB46: 1433 | AC46: =I46/AB46 -> 0.18353105 | AD46: =L46/I46 -> 62.422053 | AH46: 13817 | AI46: =L46-AH46 -> 2600
A47: 16 | B47: =A47-$G$4 -> 12 | C47: 46006 | D47: 26 Christmas Festival | G47: 46012.583 | H47: Holiday | I47: =P47+X47 -> 616 | J47: =IF(R47="Too early",R47,R47+X47) -> Too early | K47: =IF(J47="Too early",J47,J47/AB47) -> Too early | L47: =T47+Y47 -> 25193 | M47: =U47+Z47 -> 88284 | N47: =L47/M47 -> 0.28536315 | O47: =IF($J47="Too early",J47,J47*AD47/M47) -> Too early | P47: 315 | Q47: =(AB47-X47)*0.85 -> 962.2 | R47: =IF(B47<7,(P47/VLOOKUP(B47,'Sales Pacing'!$A$23:$E$36,2)),"Too early") -> Too early | S47: =IF(R47="Too early","Too early",R47/Q47) -> Too early | T47: 18516 | U47: 75834 | V47: =IF(T47>0,T47/U47,"") -> 0.24416489 | W47: =IF($R47="Too early",R47,R47*AD47/U47) -> Too early | X47: 301 | Y47: 6677 | Z47: 12450 | AA47: =IF(Y47>0,Y47/Z47,"") -> 0.53630522 | AB47: 1433 | AC47: =I47/AB47 -> 0.42986741 | AD47: =L47/I47 -> 40.897727 | AH47: 23553 | AI47: =L47-AH47 -> 1640
A48: 16 | B48: =A48-$G$4 -> 12 | C48: 46006 | D48: 26 Christmas Festival | G48: 46012.792 | H48: Holiday | I48: =P48+X48 -> 148 | J48: =IF(R48="Too early",R48,R48+X48) -> Too early | K48: =IF(J48="Too early",J48,J48/AB48) -> Too early | L48: =T48+Y48 -> 8641 | M48: =U48+Z48 -> 75834 | N48: =L48/M48 -> 0.11394625 | O48: =IF($J48="Too early",J48,J48*AD48/M48) -> Too early | P48: 148 | Q48: =(AB48-X48)*0.85 -> 1218.05 | R48: =IF(B48<7,(P48/VLOOKUP(B48,'Sales Pacing'!$A$23:$E$36,2)),"Too early") -> Too early | S48: =IF(R48="Too early","Too early",R48/Q48) -> Too early | T48: 8641 | U48: 75834 | V48: =IF(T48>0,T48/U48,"") -> 0.11394625 | W48: =IF($R48="Too early",R48,R48*AD48/U48) -> Too early | AA48: =IF(Y48>0,Y48/Z48,"") | AB48: 1433 | AC48: =I48/AB48 -> 0.10327983 | AD48: =L48/I48 -> 58.385135 | AH48: 7896 | AI48: =L48-AH48 -> 745
A49: 17 | B49: =A49-$G$4 -> 13 | C49: 46013 | D49: 26 It's a Wonderful Life | G49: 46014.792 | H49: Specials/Film | I49: =P49+X49 -> 885 | J49: =IF(R49="Too early",R49,R49+X49) -> Too early | K49: =IF(J49="Too early",J49,J49/AB49) -> Too early | L49: =T49+Y49 -> 69185.6 | M49: =U49+Z49 -> 100000 | N49: =L49/M49 -> 0.691856 | O49: =IF($J49="Too early",J49,J49*AD49/M49) -> Too early | P49: 885 | Q49: =(AB49-X49)*0.85 -> 1106.7 | R49: =IF(B49<7,(P49/VLOOKUP(B49,'Sales Pacing'!$A$23:$E$36,2)),"Too early") -> Too early | S49: =IF(R49="Too early","Too early",R49/Q49) -> Too early | T49: 69185.6 | U49: 100000 | V49: =IF(T49>0,T49/U49,"") -> 0.691856 | W49: =IF($R49="Too early",R49,R49*AD49/U49) -> Too early | AA49: =IF(Y49>0,Y49/Z49,"") | AB49: 1302 | AC49: =I49/AB49 -> 0.6797235 | AD49: =L49/I49 -> 78.175819 | AH49: 66653.6 | AI49: =L49-AH49 -> 2532
A50: 17 | B50: =A50-$G$4 -> 13 | C50: 46013 | D50: 26 It's a Wonderful Life | G50: 46015.458 | H50: Specials/Film | I50: =P50+X50 -> 221 | J50: =IF(R50="Too early",R50,R50+X50) -> Too early | K50: =IF(J50="Too early",J50,J50/AB50) -> Too early | L50: =T50+Y50 -> 15120.4 | M50: =U50+Z50 -> 100000 | N50: =L50/M50 -> 0.151204 | O50: =IF($J50="Too early",J50,J50*AD50/M50) -> Too early | P50: 221 | Q50: =(AB50-X50)*0.85 -> 1106.7 | R50: =IF(B50<7,(P50/VLOOKUP(B50,'Sales Pacing'!$A$23:$E$36,2)),"Too early") -> Too early | S50: =IF(R50="Too early","Too early",R50/Q50) -> Too early | T50: 15120.4 | U50: 100000 | V50: =IF(T50>0,T50/U50,"") -> 0.151204 | W50: =IF($R50="Too early",R50,R50*AD50/U50) -> Too early | AA50: =IF(Y50>0,Y50/Z50,"") | AB50: 1302 | AC50: =I50/AB50 -> 0.16973886 | AD50: =L50/I50 -> 68.4181 | AH50: 14364.4 | AI50: =L50-AH50 -> 756
A51: 18 | B51: =A51-$G$4 -> 14 | C51: 46020 | D51: OPEN | I51: =P51+X51 -> 0 | J51: =IF(R51="Too early",R51,R51+X51) -> Too early | L51: =T51+Y51 -> 0 | M51: =U51+Z51 -> 0 | N51: =L51/M51 -> #DIV/0! | R51: =IF(B51<7,(P51/VLOOKUP(B51,'Sales Pacing'!$A$23:$E$36,2)),"Too early") -> Too early | V51: =IF(T51>0,T51/U51,"") | AA51: N/A | AC51: =I51/AB51 -> #DIV/0! | AD51: =L51/I51 -> #DIV/0! | AH51: 0
A52: 19 | B52: =A52-$G$4 -> 15 | C52: 46027 | D52: 26 CS04 Brahms' Fourth Symphony | G52: 46031.833 | H52: Classical | I52: =P52+X52 -> 604 | J52: =IF(R52="Too early",R52,R52+X52) -> Too early | K52: =IF(J52="Too early",J52,J52/AB52) -> Too early | L52: =T52+Y52 -> 39771 | M52: =U52+Z52 -> 54999 | N52: =L52/M52 -> 0.72312224 | O52: =IF($J52="Too early",J52,J52*AD52/M52) -> Too early | P52: 31 | Q52: =(AB52-X52)*0.85 -> 864.45 | R52: =IF(B52<7,(P52/VLOOKUP(B52,'Sales Pacing'!$A$23:$E$36,2)),"Too early") -> Too early | S52: =IF(R52="Too early","Too early",R52/Q52) -> Too early | T52: 1334 | U52: 21666 | V52: =IF(T52>0,T52/U52,"") -> 0.061571125 | W52: =IF($R52="Too early",R52,R52*AD52/U52) -> Too early | X52: 573 | Y52: 38437 | Z52: 33333 | AA52: =IF(Y52>0,Y52/Z52,"") -> 1.1531215 | AB52: 1590 | AC52: =I52/AB52 -> 0.37987421 | AD52: =L52/I52 -> 65.846026 | AH52: 39591 | AI52: =L52-AH52 -> 180
A53: 19 | B53: =A53-$G$4 -> 15 | C53: 46027 | D53: 27 CS04 Brahms' Fourth Symphony | G53: 46032.833 | H53: Classical | I53: =P53+X53 -> 630 | J53: =IF(R53="Too early",R53,R53+X53) -> Too early | K53: =IF(J53="Too early",J53,J53/AB53) -> Too early | L53: =T53+Y53 -> 40664 | M53: =U53+Z53 -> 54999 | N53: =L53/M53 -> 0.7393589 | O53: =IF($J53="Too early",J53,J53*AD53/M53) -> Too early | P53: 73 | Q53: =(AB53-X53)*0.85 -> 878.05 | R53: =IF(B53<7,(P53/VLOOKUP(B53,'Sales Pacing'!$A$23:$E$36,2)),"Too early") -> Too early | S53: =IF(R53="Too early","Too early",R53/Q53) -> Too early | T53: 4273 | U53: 21666 | V53: =IF(T53>0,T53/U53,"") -> 0.19722145 | W53: =IF($R53="Too early",R53,R53*AD53/U53) -> Too early | X53: 557 | Y53: 36391 | Z53: 33333 | AA53: =IF(Y53>0,Y53/Z53,"") -> 1.0917409 | AB53: 1590 | AC53: =I53/AB53 -> 0.39622642 | AD53: =L53/I53 -> 64.546032 | AH53: 40128 | AI53: =L53-AH53 -> 536
A54: 19 | B54: =A54-$G$4 -> 15 | C54: 46027 | D54: 28 CS04 Brahms' Fourth Symphony | G54: 46033.583 | H54: Classical | I54: =P54+X54 -> 626 | J54: =IF(R54="Too early",R54,R54+X54) -> Too early | K54: =IF(J54="Too early",J54,J54/AB54) -> Too early | L54: =T54+Y54 -> 39937.5 | M54: =U54+Z54 -> 55000 | N54: =L54/M54 -> 0.72613636 | O54: =IF($J54="Too early",J54,J54*AD54/M54) -> Too early | P54: 55 | Q54: =(AB54-X54)*0.85 -> 866.15 | R54: =IF(B54<7,(P54/VLOOKUP(B54,'Sales Pacing'!$A$23:$E$36,2)),"Too early") -> Too early | S54: =IF(R54="Too early","Too early",R54/Q54) -> Too early | T54: 3188 | U54: 21666 | V54: =IF(T54>0,T54/U54,"") -> 0.14714299 | W54: =IF($R54="Too early",R54,R54*AD54/U54) -> Too early | X54: 571 | Y54: 36749.5 | Z54: 33334 | AA54: =IF(Y54>0,Y54/Z54,"") -> 1.102463 | AB54: 1590 | AC54: =I54/AB54 -> 0.39371069 | AD54: =L54/I54 -> 63.797923 | AH54: 39791.5 | AI54: =L54-AH54 -> 146
A55: 20 | B55: =A55-$G$4 -> 16 | C55: 46034 | D55: 26 CS05 Pines of Rome & Bruch | G55: 46038.833 | H55: Classical | I55: =P55+X55 -> 419 | J55: =IF(R55="Too early",R55,R55+X55) -> Too early | K55: =IF(J55="Too early",J55,J55/AB55) -> Too early | L55: =T55+Y55 -> 28302 | M55: =U55+Z55 -> 60000 | N55: =L55/M55 -> 0.4717 | O55: =IF($J55="Too early",J55,J55*AD55/M55) -> Too early | P55: 51 | Q55: =(AB55-X55)*0.85 -> 1038.7 | R55: =IF(B55<7,(P55/VLOOKUP(B55,'Sales Pacing'!$A$23:$E$36,2)),"Too early") -> Too early | S55: =IF(R55="Too early","Too early",R55/Q55) -> Too early | T55: 2960 | U55: 30000 | V55: =IF(T55>0,T55/U55,"") -> 0.098666667 | W55: =IF($R55="Too early",R55,R55*AD55/U55) -> Too early | X55: 368 | Y55: 25342 | Z55: 30000 | AA55: =IF(Y55>0,Y55/Z55,"") -> 0.84473333 | AB55: 1590 | AC55: =I55/AB55 -> 0.26352201 | AD55: =L55/I55 -> 67.546539 | AH55: 28243 | AI55: =L55-AH55 -> 59
A56: 20 | B56: =A56-$G$4 -> 16 | C56: 46034 | D56: 26 CS05 Pines of Rome & Bruch | G56: 46039.833 | H56: Classical | I56: =P56+X56 -> 726 | J56: =IF(R56="Too early",R56,R56+X56) -> Too early | K56: =IF(J56="Too early",J56,J56/AB56) -> Too early | L56: =T56+Y56 -> 47864.9 | M56: =U56+Z56 -> 75000 | N56: =L56/M56 -> 0.63819867 | O56: =IF($J56="Too early",J56,J56*AD56/M56) -> Too early | P56: 126 | Q56: =(AB56-X56)*0.85 -> 841.5 | R56: =IF(B56<7,(P56/VLOOKUP(B56,'Sales Pacing'!$A$23:$E$36,2)),"Too early") -> Too early | S56: =IF(R56="Too early","Too early",R56/Q56) -> Too early | T56: 7358 | U56: 20000 | V56: =IF(T56>0,T56/U56,"") -> 0.3679 | W56: =IF($R56="Too early",R56,R56*AD56/U56) -> Too early | X56: 600 | Y56: 40506.9 | Z56: 55000 | AA56: =IF(Y56>0,Y56/Z56,"") -> 0.73648909 | AB56: 1590 | AC56: =I56/AB56 -> 0.45660377 | AD56: =L56/I56 -> 65.929614 | AH56: 47394.9 | AI56: =L56-AH56 -> 470
A57: 20 | B57: =A57-$G$4 -> 16 | C57: 46034 | D57: 26 CS05 Pines of Rome & Bruch | G57: 46040.583 | H57: Classical | I57: =P57+X57 -> 701 | J57: =IF(R57="Too early",R57,R57+X57) -> Too early | K57: =IF(J57="Too early",J57,J57/AB57) -> Too early | L57: =T57+Y57 -> 44947.2 | M57: =U57+Z57 -> 75000 | N57: =L57/M57 -> 0.599296 | O57: =IF($J57="Too early",J57,J57*AD57/M57) -> Too early | P57: 93 | Q57: =(AB57-X57)*0.85 -> 834.7 | R57: =IF(B57<7,(P57/VLOOKUP(B57,'Sales Pacing'!$A$23:$E$36,2)),"Too early") -> Too early | S57: =IF(R57="Too early","Too early",R57/Q57) -> Too early | T57: 5931 | U57: 20000 | V57: =IF(T57>0,T57/U57,"") -> 0.29655 | W57: =IF($R57="Too early",R57,R57*AD57/U57) -> Too early | X57: 608 | Y57: 39016.2 | Z57: 55000 | AA57: =IF(Y57>0,Y57/Z57,"") -> 0.70938545 | AB57: 1590 | AC57: =I57/AB57 -> 0.4408805 | AD57: =L57/I57 -> 64.118688 | AH57: 44600.2 | AI57: =L57-AH57 -> 347
A58: 21 | B58: =A58-$G$4 -> 17 | C58: 46041 | D58: 26 Indiana Jones: Raiders Lost | G58: 46044.792 | H58: Specials/Film | I58: =P58+X58 -> 131 | J58: =IF(R58="Too early",R58,R58+X58) -> Too early | K58: =IF(J58="Too early",J58,J58/AB58) -> Too early | L58: =T58+Y58 -> 7965 | M58: =U58+Z58 -> 90000 | N58: =L58/M58 -> 0.0885 | O58: =IF($J58="Too early",J58,J58*AD58/M58) -> Too early | P58: 131 | Q58: =(AB58-X58)*0.85 -> 1106.7 | R58: =IF(B58<7,(P58/VLOOKUP(B58,'Sales Pacing'!$A$23:$E$36,2)),"Too early") -> Too early | S58: =IF(R58="Too early","Too early",R58/Q58) -> Too early | T58: 7965 | U58: 90000 | V58: =IF(T58>0,T58/U58,"") -> 0.0885 | W58: =IF($R58="Too early",R58,R58*AD58/U58) -> Too early | AA58: =IF(Y58>0,Y58/Z58,"") | AB58: 1302 | AC58: =I58/AB58 -> 0.10061444 | AD58: =L58/I58 -> 60.801527 | AH58: 7410 | AI58: =L58-AH58 -> 555
A59: 21 | B59: =A59-$G$4 -> 17 | C59: 46041 | D59: 26 Indiana Jones: Raiders Lost | G59: 46045.792 | H59: Specials/Film | I59: =P59+X59 -> 306 | J59: =IF(R59="Too early",R59,R59+X59) -> Too early | K59: =IF(J59="Too early",J59,J59/AB59) -> Too early | L59: =T59+Y59 -> 22141.9 | M59: =U59+Z59 -> 90000 | N59: =L59/M59 -> 0.24602111 | O59: =IF($J59="Too early",J59,J59*AD59/M59) -> Too early | P59: 306 | Q59: =(AB59-X59)*0.85 -> 1106.7 | R59: =IF(B59<7,(P59/VLOOKUP(B59,'Sales Pacing'!$A$23:$E$36,2)),"Too early") -> Too early | S59: =IF(R59="Too early","Too early",R59/Q59) -> Too early | T59: 22141.9 | U59: 90000 | V59: =IF(T59>0,T59/U59,"") -> 0.24602111 | W59: =IF($R59="Too early",R59,R59*AD59/U59) -> Too early | AA59: =IF(Y59>0,Y59/Z59,"") | AB59: 1302 | AC59: =I59/AB59 -> 0.23502304 | AD59: =L59/I59 -> 72.35915 | AH59: 21481.9 | AI59: =L59-AH59 -> 660
A60: 21 | B60: =A60-$G$4 -> 17 | C60: 46041 | D60: 26 Indiana Jones: Raiders Lost | G60: 46046.792 | H60: Specials/Film | I60: =P60+X60 -> 501 | J60: =IF(R60="Too early",R60,R60+X60) -> Too early | K60: =IF(J60="Too early",J60,J60/AB60) -> Too early | L60: =T60+Y60 -> 36718.1 | M60: =U60+Z60 -> 90000 | N60: =L60/M60 -> 0.40797889 | O60: =IF($J60="Too early",J60,J60*AD60/M60) -> Too early | P60: 501 | Q60: =(AB60-X60)*0.85 -> 1106.7 | R60: =IF(B60<7,(P60/VLOOKUP(B60,'Sales Pacing'!$A$23:$E$36,2)),"Too early") -> Too early | S60: =IF(R60="Too early","Too early",R60/Q60) -> Too early | T60: 36718.1 | U60: 90000 | V60: =IF(T60>0,T60/U60,"") -> 0.40797889 | W60: =IF($R60="Too early",R60,R60*AD60/U60) -> Too early | AA60: =IF(Y60>0,Y60/Z60,"") | AB60: 1302 | AC60: =I60/AB60 -> 0.38479263 | AD60: =L60/I60 -> 73.289621 | AH60: 34988.1 | AI60: =L60-AH60 -> 1730
A61: 21 | B61: =A61-$G$4 -> 17 | C61: 46041 | D61: 26 Indiana Jones: Raiders Lost | G61: 46047.583 | H61: Specials/Film | I61: =P61+X61 -> 384 | J61: =IF(R61="Too early",R61,R61+X61) -> Too early | K61: =IF(J61="Too early",J61,J61/AB61) -> Too early | L61: =T61+Y61 -> 26947.1 | M61: =U61+Z61 -> 90000 | N61: =L61/M61 -> 0.29941222 | O61: =IF($J61="Too early",J61,J61*AD61/M61) -> Too early | P61: 384 | Q61: =(AB61-X61)*0.85 -> 1106.7 | R61: =IF(B61<7,(P61/VLOOKUP(B61,'Sales Pacing'!$A$23:$E$36,2)),"Too early") -> Too early | S61: =IF(R61="Too early","Too early",R61/Q61) -> Too early | T61: 26947.1 | U61: 90000 | V61: =IF(T61>0,T61/U61,"") -> 0.29941222 | W61: =IF($R61="Too early",R61,R61*AD61/U61) -> Too early | AA61: =IF(Y61>0,Y61/Z61,"") | AB61: 1302 | AC61: =I61/AB61 -> 0.29493088 | AD61: =L61/I61 -> 70.17474 | AH61: 26457.1 | AI61: =L61-AH61 -> 490
A62: 22 | B62: =A62-$G$4 -> 18 | C62: 46048 | D62: 26 CS06 Beethoven+ | G62: 46052.833 | H62: Classical | I62: =P62+X62 -> 435 | J62: =IF(R62="Too early",R62,R62+X62) -> Too early | K62: =IF(J62="Too early",J62,J62/AB62) -> Too early | L62: =T62+Y62 -> 28716 | M62: =U62+Z62 -> 54000 | N62: =L62/M62 -> 0.53177778 | O62: =IF($J62="Too early",J62,J62*AD62/M62) -> Too early | P62: 71 | Q62: =(AB62-X62)*0.85 -> 1042.1 | R62: =IF(B62<7,(P62/VLOOKUP(B62,'Sales Pacing'!$A$23:$E$36,2)),"Too early") -> Too early | S62: =IF(R62="Too early","Too early",R62/Q62) -> Too early | T62: 3847 | U62: 24000 | V62: =IF(T62>0,T62/U62,"") -> 0.16029167 | W62: =IF($R62="Too early",R62,R62*AD62/U62) -> Too early | X62: 364 | Y62: 24869 | Z62: 30000 | AA62: =IF(Y62>0,Y62/Z62,"") -> 0.82896667 | AB62: 1590 | AC62: =I62/AB62 -> 0.27358491 | AD62: =L62/I62 -> 66.013793 | AH62: 28368 | AI62: =L62-AH62 -> 348
A63: 22 | B63: =A63-$G$4 -> 18 | C63: 46048 | D63: 26 CS06 Beethoven+ | G63: 46053.833 | H63: Classical | I63: =P63+X63 -> 692 | J63: =IF(R63="Too early",R63,R63+X63) -> Too early | K63: =IF(J63="Too early",J63,J63/AB63) -> Too early | L63: =T63+Y63 -> 45477.9 | M63: =U63+Z63 -> 75000 | N63: =L63/M63 -> 0.606372 | O63: =IF($J63="Too early",J63,J63*AD63/M63) -> Too early | P63: 94 | Q63: =(AB63-X63)*0.85 -> 843.2 | R63: =IF(B63<7,(P63/VLOOKUP(B63,'Sales Pacing'!$A$23:$E$36,2)),"Too early") -> Too early | S63: =IF(R63="Too early","Too early",R63/Q63) -> Too early | T63: 5569 | U63: 20000 | V63: =IF(T63>0,T63/U63,"") -> 0.27845 | W63: =IF($R63="Too early",R63,R63*AD63/U63) -> Too early | X63: 598 | Y63: 39908.9 | Z63: 55000 | AA63: =IF(Y63>0,Y63/Z63,"") -> 0.72561636 | AB63: 1590 | AC63: =I63/AB63 -> 0.43522013 | AD63: =L63/I63 -> 65.719509 | AH63: 45500.9 | AI63: =L63-AH63 -> -23
A64: 22 | B64: =A64-$G$4 -> 18 | C64: 46048 | D64: 26 CS06 Beethoven+ | G64: 46054.583 | H64: Classical | I64: =P64+X64 -> 681 | J64: =IF(R64="Too early",R64,R64+X64) -> Too early | K64: =IF(J64="Too early",J64,J64/AB64) -> Too early | L64: =T64+Y64 -> 43667.2 | M64: =U64+Z64 -> 75000 | N64: =L64/M64 -> 0.58222933 | O64: =IF($J64="Too early",J64,J64*AD64/M64) -> Too early | P64: 72 | Q64: =(AB64-X64)*0.85 -> 833.85 | R64: =IF(B64<7,(P64/VLOOKUP(B64,'Sales Pacing'!$A$23:$E$36,2)),"Too early") -> Too early | S64: =IF(R64="Too early","Too early",R64/Q64) -> Too early | T64: 4644 | U64: 20000 | V64: =IF(T64>0,T64/U64,"") -> 0.2322 | W64: =IF($R64="Too early",R64,R64*AD64/U64) -> Too early | X64: 609 | Y64: 39023.2 | Z64: 55000 | AA64: =IF(Y64>0,Y64/Z64,"") -> 0.70951273 | AB64: 1590 | AC64: =I64/AB64 -> 0.42830189 | AD64: =L64/I64 -> 64.122173 | AH64: 43394.2 | AI64: =L64-AH64 -> 273
A65: 23 | B65: =A65-$G$4 -> 19 | C65: 46055 | D65: 26 On-Stage 2 Leila Josefowicz | G65: 46058.833 | H65: On Stage | I65: =P65+X65 -> 19 | J65: =IF(R65="Too early",R65,R65+X65) -> Too early | K65: =IF(J65="Too early",J65,J65/AB65) -> Too early | L65: =T65+Y65 -> 1960 | M65: 9000 | N65: =L65/M65 -> 0.21777778 | O65: =IF($J65="Too early",J65,J65*AD65/M65) -> Too early | P65: 19 | Q65: =(AB65-X65)*0.85 -> 85 | R65: =IF(B65<7,(P65/VLOOKUP(B65,'Sales Pacing'!$A$23:$E$36,2)),"Too early") -> Too early | S65: =IF(R65="Too early","Too early",R65/Q65) -> Too early | T65: 1960 | U65: 9000 | V65: =IF(T65>0,T65/U65,"") -> 0.21777778 | W65: =IF($R65="Too early",R65,R65*AD65/U65) -> Too early | AA65: =IF(Y65>0,Y65/Z65,"") | AB65: 100 | AC65: =I65/AB65 -> 0.19 | AD65: =L65/I65 -> 103.15789 | AH65: 1960 | AI65: =L65-AH65 -> 0
A66: 23 | B66: =A66-$G$4 -> 19 | C66: 46055 | D66: 26 CS07 Prokofiev's Fifth Symphony | G66: 46059.833 | H66: Classical | I66: =P66+X66 -> 624 | J66: =IF(R66="Too early",R66,R66+X66) -> Too early | K66: =IF(J66="Too early",J66,J66/AB66) -> Too early | L66: =T66+Y66 -> 40003 | M66: =U66+Z66 -> 46666 | N66: =L66/M66 -> 0.85721939 | O66: =IF($J66="Too early",J66,J66*AD66/M66) -> Too early | P66: 62 | Q66: =(AB66-X66)*0.85 -> 873.8 | R66: =IF(B66<7,(P66/VLOOKUP(B66,'Sales Pacing'!$A$23:$E$36,2)),"Too early") -> Too early | S66: =IF(R66="Too early","Too early",R66/Q66) -> Too early | T66: 2540 | U66: 13333 | V66: =IF(T66>0,T66/U66,"") -> 0.19050476 | W66: =IF($R66="Too early",R66,R66*AD66/U66) -> Too early | X66: 562 | Y66: 37463 | Z66: 33333 | AA66: =IF(Y66>0,Y66/Z66,"") -> 1.1239012 | AB66: 1590 | AC66: =I66/AB66 -> 0.39245283 | AD66: =L66/I66 -> 64.107372 | AH66: 39823 | AI66: =L66-AH66 -> 180
A67: 23 | B67: =A67-$G$4 -> 19 | C67: 46055 | D67: 27 CS07 Prokofiev's Fifth Symphony | G67: 46060.833 | H67: Classical | I67: =P67+X67 -> 608 | J67: =IF(R67="Too early",R67,R67+X67) -> Too early | K67: =IF(J67="Too early",J67,J67/AB67) -> Too early | L67: =T67+Y67 -> 38795.2 | M67: =U67+Z67 -> 46666 | N67: =L67/M67 -> 0.83133759 | O67: =IF($J67="Too early",J67,J67*AD67/M67) -> Too early | P67: 49 | Q67: =(AB67-X67)*0.85 -> 876.35 | R67: =IF(B67<7,(P67/VLOOKUP(B67,'Sales Pacing'!$A$23:$E$36,2)),"Too early") -> Too early | S67: =IF(R67="Too early","Too early",R67/Q67) -> Too early | T67: 2478 | U67: 13333 | V67: =IF(T67>0,T67/U67,"") -> 0.18585465 | W67: =IF($R67="Too early",R67,R67*AD67/U67) -> Too early | X67: 559 | Y67: 36317.2 | Z67: 33333 | AA67: =IF(Y67>0,Y67/Z67,"") -> 1.0895269 | AB67: 1590 | AC67: =I67/AB67 -> 0.38238994 | AD67: =L67/I67 -> 63.807895 | AH67: 38606.2 | AI67: =L67-AH67 -> 189
A68: 23 | B68: =A68-$G$4 -> 19 | C68: 46055 | D68: 28 CS07 Prokofiev's Fifth Symphony | G68: 46061.583 | H68: Classical | I68: =P68+X68 -> 606 | J68: =IF(R68="Too early",R68,R68+X68) -> Too early | K68: =IF(J68="Too early",J68,J68/AB68) -> Too early | L68: =T68+Y68 -> 38109.1 | M68: =U68+Z68 -> 46667 | N68: =L68/M68 -> 0.81661774 | O68: =IF($J68="Too early",J68,J68*AD68/M68) -> Too early | P68: 44 | Q68: =(AB68-X68)*0.85 -> 873.8 | R68: =IF(B68<7,(P68/VLOOKUP(B68,'Sales Pacing'!$A$23:$E$36,2)),"Too early") -> Too early | S68: =IF(R68="Too early","Too early",R68/Q68) -> Too early | T68: 1922 | U68: 13333 | V68: =IF(T68>0,T68/U68,"") -> 0.1441536 | W68: =IF($R68="Too early",R68,R68*AD68/U68) -> Too early | X68: 562 | Y68: 36187.1 | Z68: 33334 | AA68: =IF(Y68>0,Y68/Z68,"") -> 1.0855913 | AB68: 1590 | AC68: =I68/AB68 -> 0.38113208 | AD68: =L68/I68 -> 62.886304 | AH68: 38063.1 | AI68: =L68-AH68 -> 46
A69: 24 | B69: =A69-$G$4 -> 20 | C69: 46062 | D69: 26 Chris Thile | G69: 46065.792 | H69: Specials | I69: =P69+X69 -> 340 | J69: =IF(R69="Too early",R69,R69+X69) -> Too early | K69: =IF(J69="Too early",J69,J69/AB69) -> Too early | L69: =T69+Y69 -> 30162 | M69: =U69+Z69 -> 128900 | N69: =L69/M69 -> 0.23399535 | O69: =IF($J69="Too early",J69,J69*AD69/M69) -> Too early | P69: 340 | Q69: =(AB69-X69)*0.85 -> 1351.5 | R69: =IF(B69<7,(P69/VLOOKUP(B69,'Sales Pacing'!$A$23:$E$36,2)),"Too early") -> Too early | S69: =IF(R69="Too early","Too early",R69/Q69) -> Too early | T69: 30162 | U69: 128900 | V69: =IF(T69>0,T69/U69,"") -> 0.23399535 | W69: =IF($R69="Too early",R69,R69*AD69/U69) -> Too early | AA69: =IF(Y69>0,Y69/Z69,"") | AB69: 1590 | AC69: =I69/AB69 -> 0.21383648 | AD69: =L69/I69 -> 88.711765 | AH69: 27005 | AI69: =L69-AH69 -> 3157
A70: 24 | B70: =A70-$G$4 -> 20 | C70: 46062 | D70: 26 PS3 She's Got Soul | G70: 46066.833 | H70: Pops | I70: =P70+X70 -> 789 | J70: =IF(R70="Too early",R70,R70+X70) -> Too early | K70: =IF(J70="Too early",J70,J70/AB70) -> Too early | L70: =T70+Y70 -> 56081.1 | M70: =U70+Z70 -> 94666 | N70: =L70/M70 -> 0.59241016 | O70: =IF($J70="Too early",J70,J70*AD70/M70) -> Too early | P70: 66 | Q70: =(AB70-X70)*0.85 -> 736.95 | R70: =IF(B70<7,(P70/VLOOKUP(B70,'Sales Pacing'!$A$23:$E$36,2)),"Too early") -> Too early | S70: =IF(R70="Too early","Too early",R70/Q70) -> Too early | T70: 4067 | U70: 53333 | V70: =IF(T70>0,T70/U70,"") -> 0.076256727 | W70: =IF($R70="Too early",R70,R70*AD70/U70) -> Too early | X70: 723 | Y70: 52014.1 | Z70: 41333 | AA70: =IF(Y70>0,Y70/Z70,"") -> 1.2584158 | AB70: 1590 | AC70: =I70/AB70 -> 0.49622642 | AD70: =L70/I70 -> 71.078707 | AH70: 55909.1 | AI70: =L70-AH70 -> 172
A71: 24 | B71: =A71-$G$4 -> 20 | C71: 46062 | D71: 26 PS3 She's Got Soul | G71: 46067.833 | H71: Pops | I71: =P71+X71 -> 709 | J71: =IF(R71="Too early",R71,R71+X71) -> Too early | K71: =IF(J71="Too early",J71,J71/AB71) -> Too early | L71: =T71+Y71 -> 50062.8 | M71: =U71+Z71 -> 94667 | N71: =L71/M71 -> 0.52883053 | O71: =IF($J71="Too early",J71,J71*AD71/M71) -> Too early | P71: 46 | Q71: =(AB71-X71)*0.85 -> 787.95 | R71: =IF(B71<7,(P71/VLOOKUP(B71,'Sales Pacing'!$A$23:$E$36,2)),"Too early") -> Too early | S71: =IF(R71="Too early","Too early",R71/Q71) -> Too early | T71: 2151 | U71: 53333 | V71: =IF(T71>0,T71/U71,"") -> 0.040331502 | W71: =IF($R71="Too early",R71,R71*AD71/U71) -> Too early | X71: 663 | Y71: 47911.8 | Z71: 41334 | AA71: =IF(Y71>0,Y71/Z71,"") -> 1.1591378 | AB71: 1590 | AC71: =I71/AB71 -> 0.44591195 | AD71: =L71/I71 -> 70.610437 | AH71: 50570.8 | AI71: =L71-AH71 -> -508
A72: 24 | B72: =A72-$G$4 -> 20 | C72: 46062 | D72: 26 PS3 She's Got Soul | G72: 46068.583 | H72: Pops | I72: =P72+X72 -> 448 | J72: =IF(R72="Too early",R72,R72+X72) -> Too early | K72: =IF(J72="Too early",J72,J72/AB72) -> Too early | L72: =T72+Y72 -> 30213.3 | M72: =U72+Z72 -> 94666 | N72: =L72/M72 -> 0.31915683 | O72: =IF($J72="Too early",J72,J72*AD72/M72) -> Too early | P72: 63 | Q72: =(AB72-X72)*0.85 -> 1024.25 | R72: =IF(B72<7,(P72/VLOOKUP(B72,'Sales Pacing'!$A$23:$E$36,2)),"Too early") -> Too early | S72: =IF(R72="Too early","Too early",R72/Q72) -> Too early | T72: 3982 | U72: 53333 | V72: =IF(T72>0,T72/U72,"") -> 0.074662967 | W72: =IF($R72="Too early",R72,R72*AD72/U72) -> Too early | X72: 385 | Y72: 26231.3 | Z72: 41333 | AA72: =IF(Y72>0,Y72/Z72,"") -> 0.63463334 | AB72: 1590 | AC72: =I72/AB72 -> 0.28176101 | AD72: =L72/I72 -> 67.440402 | AH72: 29655.3 | AI72: =L72-AH72 -> 558
A73: 25 | B73: =A73-$G$4 -> 21 | C73: 46069 | D73: 26 Harry Potter 2: Chamber | G73: 46072.792 | H73: Specials/Film | I73: =P73+X73 -> 134 | J73: =IF(R73="Too early",R73,R73+X73) -> Too early | K73: =IF(J73="Too early",J73,J73/AB73) -> Too early | L73: =T73+Y73 -> 9551.5 | M73: =U73+Z73 -> 111250 | N73: =L73/M73 -> 0.08585618 | O73: =IF($J73="Too early",J73,J73*AD73/M73) -> Too early | P73: 134 | Q73: =(AB73-X73)*0.85 -> 1106.7 | R73: =IF(B73<7,(P73/VLOOKUP(B73,'Sales Pacing'!$A$23:$E$36,2)),"Too early") -> Too early | S73: =IF(R73="Too early","Too early",R73/Q73) -> Too early | T73: 9551.5 | U73: 111250 | V73: =IF(T73>0,T73/U73,"") -> 0.08585618 | W73: =IF($R73="Too early",R73,R73*AD73/U73) -> Too early | AA73: =IF(Y73>0,Y73/Z73,"") | AB73: 1302 | AC73: =I73/AB73 -> 0.10291859 | AD73: =L73/I73 -> 71.279851 | AH73: 9361.5 | AI73: =L73-AH73 -> 190
A74: 25 | B74: =A74-$G$4 -> 21 | C74: 46069 | D74: 26 Harry Potter 2: Chamber | G74: 46073.792 | H74: Specials/Film | I74: =P74+X74 -> 245 | J74: =IF(R74="Too early",R74,R74+X74) -> Too early | K74: =IF(J74="Too early",J74,J74/AB74) -> Too early | L74: =T74+Y74 -> 17743 | M74: =U74+Z74 -> 111250 | N74: =L74/M74 -> 0.15948764 | O74: =IF($J74="Too early",J74,J74*AD74/M74) -> Too early | P74: 245 | Q74: =(AB74-X74)*0.85 -> 1106.7 | R74: =IF(B74<7,(P74/VLOOKUP(B74,'Sales Pacing'!$A$23:$E$36,2)),"Too early") -> Too early | S74: =IF(R74="Too early","Too early",R74/Q74) -> Too early | T74: 17743 | U74: 111250 | V74: =IF(T74>0,T74/U74,"") -> 0.15948764 | W74: =IF($R74="Too early",R74,R74*AD74/U74) -> Too early | AA74: =IF(Y74>0,Y74/Z74,"") | AB74: 1302 | AC74: =I74/AB74 -> 0.18817204 | AD74: =L74/I74 -> 72.420408 | AH74: 17663 | AI74: =L74-AH74 -> 80
A75: 25 | B75: =A75-$G$4 -> 21 | C75: 46069 | D75: 26 Harry Potter 2: Chamber | G75: 46074.792 | H75: Specials/Film | I75: =P75+X75 -> 444 | J75: =IF(R75="Too early",R75,R75+X75) -> Too early | K75: =IF(J75="Too early",J75,J75/AB75) -> Too early | L75: =T75+Y75 -> 33393 | M75: =U75+Z75 -> 111250 | N75: =L75/M75 -> 0.3001618 | O75: =IF($J75="Too early",J75,J75*AD75/M75) -> Too early | P75: 444 | Q75: =(AB75-X75)*0.85 -> 1106.7 | R75: =IF(B75<7,(P75/VLOOKUP(B75,'Sales Pacing'!$A$23:$E$36,2)),"Too early") -> Too early | S75: =IF(R75="Too early","Too early",R75/Q75) -> Too early | T75: 33393 | U75: 111250 | V75: =IF(T75>0,T75/U75,"") -> 0.3001618 | W75: =IF($R75="Too early",R75,R75*AD75/U75) -> Too early | AA75: =IF(Y75>0,Y75/Z75,"") | AB75: 1302 | AC75: =I75/AB75 -> 0.34101382 | AD75: =L75/I75 -> 75.209459 | AH75: 31515 | AI75: =L75-AH75 -> 1878
A76: 25 | B76: =A76-$G$4 -> 21 | C76: 46069 | D76: 26 Harry Potter 2: Chamber | G76: 46075.583 | H76: Specials/Film | I76: =P76+X76 -> 505 | J76: =IF(R76="Too early",R76,R76+X76) -> Too early | K76: =IF(J76="Too early",J76,J76/AB76) -> Too early | L76: =T76+Y76 -> 34032.5 | M76: =U76+Z76 -> 111250 | N76: =L76/M76 -> 0.30591011 | O76: =IF($J76="Too early",J76,J76*AD76/M76) -> Too early | P76: 505 | Q76: =(AB76-X76)*0.85 -> 1106.7 | R76: =IF(B76<7,(P76/VLOOKUP(B76,'Sales Pacing'!$A$23:$E$36,2)),"Too early") -> Too early | S76: =IF(R76="Too early","Too early",R76/Q76) -> Too early | T76: 34032.5 | U76: 111250 | V76: =IF(T76>0,T76/U76,"") -> 0.30591011 | W76: =IF($R76="Too early",R76,R76*AD76/U76) -> Too early | AA76: =IF(Y76>0,Y76/Z76,"") | AB76: 1302 | AC76: =I76/AB76 -> 0.38786482 | AD76: =L76/I76 -> 67.391089 | AH76: 33792.5 | AI76: =L76-AH76 -> 240
A77: 26 | B77: =A77-$G$4 -> 22 | C77: 46076 | D77: 26 FS3 Philharmonia Fantastique | G77: 46082.583 | H77: Family | I77: =P77+X77 -> 357 | J77: =IF(R77="Too early",R77,R77+X77) -> Too early | K77: =IF(J77="Too early",J77,J77/AB77) -> Too early | L77: =T77+Y77 -> 8297 | M77: =U77+Z77 -> 19500 | N77: =L77/M77 -> 0.42548718 | O77: =IF($J77="Too early",J77,J77*AD77/M77) -> Too early | P77: 50 | Q77: =(AB77-X77)*0.85 -> 845.75 | R77: =IF(B77<7,(P77/VLOOKUP(B77,'Sales Pacing'!$A$23:$E$36,2)),"Too early") -> Too early | S77: =IF(R77="Too early","Too early",R77/Q77) -> Too early | T77: 1461 | U77: 10000 | V77: =IF(T77>0,T77/U77,"") -> 0.1461 | W77: =IF($R77="Too early",R77,R77*AD77/U77) -> Too early | X77: 307 | Y77: 6836 | Z77: 9500 | AA77: =IF(Y77>0,Y77/Z77,"") -> 0.71957895 | AB77: 1302 | AC77: =I77/AB77 -> 0.27419355 | AD77: =L77/I77 -> 23.240896 | AH77: 8100 | AI77: =L77-AH77 -> 197
A78: 27 | B78: =A78-$G$4 -> 23 | C78: 46083 | D78: OPEN | I78: =P78+X78 -> 0 | J78: =IF(R78="Too early",R78,R78+X78) -> Too early | L78: =T78+Y78 -> 0 | M78: =U78+Z78 -> 0 | N78: =L78/M78 -> #DIV/0! | R78: =IF(B78<7,(P78/VLOOKUP(B78,'Sales Pacing'!$A$23:$E$36,2)),"Too early") -> Too early | V78: =IF(T78>0,T78/U78,"") | AA78: N/A | AC78: =I78/AB78 -> #DIV/0! | AD78: =L78/I78 -> #DIV/0! | AH78: 0
A79: 28 | B79: =A79-$G$4 -> 24 | C79: 46090 | D79: 26 CS08 Saint-Saëns & Strauss | G79: 46094.833 | H79: Classical | I79: =P79+X79 -> 626 | J79: =IF(R79="Too early",R79,R79+X79) -> Too early | K79: =IF(J79="Too early",J79,J79/AB79) -> Too early | L79: =T79+Y79 -> 41199 | M79: =U79+Z79 -> 54999 | N79: =L79/M79 -> 0.74908635 | O79: =IF($J79="Too early",J79,J79*AD79/M79) -> Too early | P79: 53 | Q79: =(AB79-X79)*0.85 -> 864.45 | R79: =IF(B79<7,(P79/VLOOKUP(B79,'Sales Pacing'!$A$23:$E$36,2)),"Too early") -> Too early | S79: =IF(R79="Too early","Too early",R79/Q79) -> Too early | T79: 2862 | U79: 18333 | V79: =IF(T79>0,T79/U79,"") -> 0.15611193 | W79: =IF($R79="Too early",R79,R79*AD79/U79) -> Too early | X79: 573 | Y79: 38337 | Z79: 36666 | AA79: =IF(Y79>0,Y79/Z79,"") -> 1.0455736 | AB79: 1590 | AC79: =I79/AB79 -> 0.39371069 | AD79: =L79/I79 -> 65.813099 | AH79: 40846 | AI79: =L79-AH79 -> 353
A80: 28 | B80: =A80-$G$4 -> 24 | C80: 46090 | D80: 26 CS08 Saint-Saëns & Strauss | G80: 46095.833 | H80: Classical | I80: =P80+X80 -> 623 | J80: =IF(R80="Too early",R80,R80+X80) -> Too early | K80: =IF(J80="Too early",J80,J80/AB80) -> Too early | L80: =T80+Y80 -> 39776.2 | M80: =U80+Z80 -> 55000 | N80: =L80/M80 -> 0.72320364 | O80: =IF($J80="Too early",J80,J80*AD80/M80) -> Too early | P80: 61 | Q80: =(AB80-X80)*0.85 -> 873.8 | R80: =IF(B80<7,(P80/VLOOKUP(B80,'Sales Pacing'!$A$23:$E$36,2)),"Too early") -> Too early | S80: =IF(R80="Too early","Too early",R80/Q80) -> Too early | T80: 3360 | U80: 18333 | V80: =IF(T80>0,T80/U80,"") -> 0.18327606 | W80: =IF($R80="Too early",R80,R80*AD80/U80) -> Too early | X80: 562 | Y80: 36416.2 | Z80: 36667 | AA80: =IF(Y80>0,Y80/Z80,"") -> 0.99316006 | AB80: 1590 | AC80: =I80/AB80 -> 0.3918239 | AD80: =L80/I80 -> 63.846228 | AH80: 39753.2 | AI80: =L80-AH80 -> 23
A81: 28 | B81: =A81-$G$4 -> 24 | C81: 46090 | D81: 26 CS08 Saint-Saëns & Strauss | G81: 46096.583 | H81: Classical | I81: =P81+X81 -> 649 | J81: =IF(R81="Too early",R81,R81+X81) -> Too early | K81: =IF(J81="Too early",J81,J81/AB81) -> Too early | L81: =T81+Y81 -> 41376.1 | M81: =U81+Z81 -> 55000 | N81: =L81/M81 -> 0.75229273 | O81: =IF($J81="Too early",J81,J81*AD81/M81) -> Too early | P81: 76 | Q81: =(AB81-X81)*0.85 -> 864.45 | R81: =IF(B81<7,(P81/VLOOKUP(B81,'Sales Pacing'!$A$23:$E$36,2)),"Too early") -> Too early | S81: =IF(R81="Too early","Too early",R81/Q81) -> Too early | T81: 4624 | U81: 18333 | V81: =IF(T81>0,T81/U81,"") -> 0.25222277 | W81: =IF($R81="Too early",R81,R81*AD81/U81) -> Too early | X81: 573 | Y81: 36752.1 | Z81: 36667 | AA81: =IF(Y81>0,Y81/Z81,"") -> 1.0023209 | AB81: 1590 | AC81: =I81/AB81 -> 0.4081761 | AD81: =L81/I81 -> 63.753621 | AH81: 41030.1 | AI81: =L81-AH81 -> 346
A82: 29 | B82: =A82-$G$4 -> 25 | C82: 46097 | D82: OPEN | I82: =P82+X82 -> 0 | J82: =IF(R82="Too early",R82,R82+X82) -> Too early | L82: =T82+Y82 -> 0 | M82: =U82+Z82 -> 0 | N82: =L82/M82 -> #DIV/0! | R82: =IF(B82<7,(P82/VLOOKUP(B82,'Sales Pacing'!$A$23:$E$36,2)),"Too early") -> Too early | V82: =IF(T82>0,T82/U82,"") | AA82: N/A | AC82: =I82/AB82 -> #DIV/0! | AD82: =L82/I82 -> #DIV/0! | AH82: 0
A83: 30 | B83: =A83-$G$4 -> 26 | C83: 46104 | D83: Final Symphony | G83: 46106 | H83: Specials | I83: =P83+X83 -> 86 | J83: =IF(R83="Too early",R83,R83+X83) -> Too early | K83: =IF(J83="Too early",J83,J83/AB83) -> Too early | L83: =T83+Y83 -> 5437 | M83: =U83+Z83 -> 84109 | N83: =L83/M83 -> 0.064642309 | O83: =IF($J83="Too early",J83,J83*AD83/M83) -> Too early | P83: 86 | Q83: =(AB83-X83)*0.85 -> 1351.5 | R83: =IF(B83<7,(P83/VLOOKUP(B83,'Sales Pacing'!$A$23:$E$36,2)),"Too early") -> Too early | S83: =IF(R83="Too early","Too early",R83/Q83) -> Too early | T83: 5437 | U83: 84109 | V83: =IF(T83>0,T83/U83,"") -> 0.064642309 | W83: =IF($R83="Too early",R83,R83*AD83/U83) -> Too early | AB83: 1590 | AC83: =I83/AB83 -> 0.05408805 | AD83: =L83/I83 -> 63.22093 | AH83: 5437 | AI83: =L83-AH83 -> 0
A84: 30 | B84: =A84-$G$4 -> 26 | C84: 46104 | D84: Final Symphony | G84: 46107 | H84: Specials | I84: =P84+X84 -> 87 | J84: =IF(R84="Too early",R84,R84+X84) -> Too early | K84: =IF(J84="Too early",J84,J84/AB84) -> Too early | L84: =T84+Y84 -> 5027.5 | M84: =U84+Z84 -> 84109 | N84: =L84/M84 -> 0.059773627 | O84: =IF($J84="Too early",J84,J84*AD84/M84) -> Too early | P84: 87 | Q84: =(AB84-X84)*0.85 -> 1351.5 | R84: =IF(B84<7,(P84/VLOOKUP(B84,'Sales Pacing'!$A$23:$E$36,2)),"Too early") -> Too early | S84: =IF(R84="Too early","Too early",R84/Q84) -> Too early | T84: 5027.5 | U84: 84109 | V84: =IF(T84>0,T84/U84,"") -> 0.059773627 | W84: =IF($R84="Too early",R84,R84*AD84/U84) -> Too early | AB84: 1590 | AC84: =I84/AB84 -> 0.054716981 | AD84: =L84/I84 -> 57.787356 | AH84: 5027.5 | AI84: =L84-AH84 -> 0
A85: 30 | B85: =A85-$G$4 -> 26 | C85: 46104 | D85: 26 PS4 Billy Joel & Elton John | G85: 46108.833 | H85: Pops | I85: =P85+X85 -> 903 | J85: =IF(R85="Too early",R85,R85+X85) -> Too early | K85: =IF(J85="Too early",J85,J85/AB85) -> Too early | L85: =T85+Y85 -> 64363.1 | M85: =U85+Z85 -> 94666 | N85: =L85/M85 -> 0.67989669 | O85: =IF($J85="Too early",J85,J85*AD85/M85) -> Too early | P85: 164 | Q85: =(AB85-X85)*0.85 -> 723.35 | R85: =IF(B85<7,(P85/VLOOKUP(B85,'Sales Pacing'!$A$23:$E$36,2)),"Too early") -> Too early | S85: =IF(R85="Too early","Too early",R85/Q85) -> Too early | T85: 11069 | U85: 53333 | V85: =IF(T85>0,T85/U85,"") -> 0.20754505 | W85: =IF($R85="Too early",R85,R85*AD85/U85) -> Too early | X85: 739 | Y85: 53294.1 | Z85: 41333 | AA85: =IF(Y85>0,Y85/Z85,"") -> 1.2893838 | AB85: 1590 | AC85: =I85/AB85 -> 0.56792453 | AD85: =L85/I85 -> 71.276966 | AH85: 64129.1 | AI85: =L85-AH85 -> 234
A86: 30 | B86: =A86-$G$4 -> 26 | C86: 46104 | D86: 26 PS4 Billy Joel & Elton John | G86: 46109.833 | H86: Pops | I86: =P86+X86 -> 855 | J86: =IF(R86="Too early",R86,R86+X86) -> Too early | K86: =IF(J86="Too early",J86,J86/AB86) -> Too early | L86: =T86+Y86 -> 61452.8 | M86: =U86+Z86 -> 94667 | N86: =L86/M86 -> 0.64914701 | O86: =IF($J86="Too early",J86,J86*AD86/M86) -> Too early | P86: 185 | Q86: =(AB86-X86)*0.85 -> 782 | R86: =IF(B86<7,(P86/VLOOKUP(B86,'Sales Pacing'!$A$23:$E$36,2)),"Too early") -> Too early | S86: =IF(R86="Too early","Too early",R86/Q86) -> Too early | T86: 13007 | U86: 53333 | V86: =IF(T86>0,T86/U86,"") -> 0.24388277 | W86: =IF($R86="Too early",R86,R86*AD86/U86) -> Too early | X86: 670 | Y86: 48445.8 | Z86: 41334 | AA86: =IF(Y86>0,Y86/Z86,"") -> 1.1720569 | AB86: 1590 | AC86: =I86/AB86 -> 0.53773585 | AD86: =L86/I86 -> 71.87462 | AH86: 60900.8 | AI86: =L86-AH86 -> 552
A87: 30 | B87: =A87-$G$4 -> 26 | C87: 46104 | D87: 26 PS4 Billy Joel & Elton John | G87: 46110.583 | H87: Pops | I87: =P87+X87 -> 619 | J87: =IF(R87="Too early",R87,R87+X87) -> Too early | K87: =IF(J87="Too early",J87,J87/AB87) -> Too early | L87: =T87+Y87 -> 43141.6 | M87: =U87+Z87 -> 94666 | N87: =L87/M87 -> 0.45572434 | O87: =IF($J87="Too early",J87,J87*AD87/M87) -> Too early | P87: 230 | Q87: =(AB87-X87)*0.85 -> 1020.85 | R87: =IF(B87<7,(P87/VLOOKUP(B87,'Sales Pacing'!$A$23:$E$36,2)),"Too early") -> Too early | S87: =IF(R87="Too early","Too early",R87/Q87) -> Too early | T87: 16690 | U87: 53333 | V87: =IF(T87>0,T87/U87,"") -> 0.31293946 | W87: =IF($R87="Too early",R87,R87*AD87/U87) -> Too early | X87: 389 | Y87: 26451.6 | Z87: 41333 | AA87: =IF(Y87>0,Y87/Z87,"") -> 0.63996323 | AB87: 1590 | AC87: =I87/AB87 -> 0.38930818 | AD87: =L87/I87 -> 69.695638 | AH87: 41992.6 | AI87: =L87-AH87 -> 1149
A88: 31 | B88: =A88-$G$4 -> 27 | C88: 46111 | D88: OPEN | I88: =P88+X88 -> 0 | J88: =IF(R88="Too early",R88,R88+X88) -> Too early | L88: =T88+Y88 -> 0 | M88: =U88+Z88 -> 0 | N88: =L88/M88 -> #DIV/0! | R88: =IF(B88<7,(P88/VLOOKUP(B88,'Sales Pacing'!$A$23:$E$36,2)),"Too early") -> Too early | V88: =IF(T88>0,T88/U88,"") | AA88: N/A | AC88: =I88/AB88 -> #DIV/0! | AD88: =L88/I88 -> #DIV/0! | AH88: 0
A89: 32 | B89: =A89-$G$4 -> 28 | C89: 46118 | D89: 26 CS09 Midsummer Night's Dream | G89: 46122.833 | H89: Classical | I89: =P89+X89 -> 420 | J89: =IF(R89="Too early",R89,R89+X89) -> Too early | K89: =IF(J89="Too early",J89,J89/AB89) -> Too early | L89: =T89+Y89 -> 28125 | M89: =U89+Z89 -> 52000 | N89: =L89/M89 -> 0.54086538 | O89: =IF($J89="Too early",J89,J89*AD89/M89) -> Too early | P89: 52 | Q89: =(AB89-X89)*0.85 -> 905.25 | R89: =IF(B89<7,(P89/VLOOKUP(B89,'Sales Pacing'!$A$23:$E$36,2)),"Too early") -> Too early | S89: =IF(R89="Too early","Too early",R89/Q89) -> Too early | T89: 2411 | U89: 22000 | V89: =IF(T89>0,T89/U89,"") -> 0.10959091 | W89: =IF($R89="Too early",R89,R89*AD89/U89) -> Too early | X89: 368 | Y89: 25714 | Z89: 30000 | AA89: =IF(Y89>0,Y89/Z89,"") -> 0.85713333 | AB89: 1433 | AC89: =I89/AB89 -> 0.29309142 | AD89: =L89/I89 -> 66.964286 | AH89: 27729 | AI89: =L89-AH89 -> 396
A90: 32 | B90: =A90-$G$4 -> 28 | C90: 46118 | D90: 26 CS09 Midsummer Night's Dream | G90: 46123.833 | H90: Classical | I90: =P90+X90 -> 662 | J90: =IF(R90="Too early",R90,R90+X90) -> Too early | K90: =IF(J90="Too early",J90,J90/AB90) -> Too early | L90: =T90+Y90 -> 41374 | M90: =U90+Z90 -> 74000 | N90: =L90/M90 -> 0.55910811 | O90: =IF($J90="Too early",J90,J90*AD90/M90) -> Too early | P90: 97 | Q90: =(AB90-X90)*0.85 -> 737.8 | R90: =IF(B90<7,(P90/VLOOKUP(B90,'Sales Pacing'!$A$23:$E$36,2)),"Too early") -> Too early | S90: =IF(R90="Too early","Too early",R90/Q90) -> Too early | T90: 5001 | U90: 24000 | V90: =IF(T90>0,T90/U90,"") -> 0.208375 | W90: =IF($R90="Too early",R90,R90*AD90/U90) -> Too early | X90: 565 | Y90: 36373 | Z90: 50000 | AA90: =IF(Y90>0,Y90/Z90,"") -> 0.72746 | AB90: 1433 | AC90: =I90/AB90 -> 0.4619679 | AD90: =L90/I90 -> 62.498489 | AH90: 41302 | AI90: =L90-AH90 -> 72
A91: 32 | B91: =A91-$G$4 -> 28 | C91: 46118 | D91: 26 CS09 Midsummer Night's Dream | G91: 46124.583 | H91: Classical | I91: =P91+X91 -> 642 | J91: =IF(R91="Too early",R91,R91+X91) -> Too early | K91: =IF(J91="Too early",J91,J91/AB91) -> Too early | L91: =T91+Y91 -> 39965.1 | M91: =U91+Z91 -> 74000 | N91: =L91/M91 -> 0.54006892 | O91: =IF($J91="Too early",J91,J91*AD91/M91) -> Too early | P91: 70 | Q91: =(AB91-X91)*0.85 -> 731.85 | R91: =IF(B91<7,(P91/VLOOKUP(B91,'Sales Pacing'!$A$23:$E$36,2)),"Too early") -> Too early | S91: =IF(R91="Too early","Too early",R91/Q91) -> Too early | T91: 3060 | U91: 24000 | V91: =IF(T91>0,T91/U91,"") -> 0.1275 | W91: =IF($R91="Too early",R91,R91*AD91/U91) -> Too early | X91: 572 | Y91: 36905.1 | Z91: 50000 | AA91: =IF(Y91>0,Y91/Z91,"") -> 0.738102 | AB91: 1433 | AC91: =I91/AB91 -> 0.44801117 | AD91: =L91/I91 -> 62.250935 | AH91: 39738.1 | AI91: =L91-AH91 -> 227
A92: 33 | B92: =A92-$G$4 -> 29 | C92: 46125 | D92: 26 CS10 Farrenc/Dvorák/Schuman | G92: 46129.833 | H92: Classical | I92: =P92+X92 -> 609 | J92: =IF(R92="Too early",R92,R92+X92) -> Too early | K92: =IF(J92="Too early",J92,J92/AB92) -> Too early | L92: =T92+Y92 -> 39973 | M92: =U92+Z92 -> 46666 | N92: =L92/M92 -> 0.85657652 | O92: =IF($J92="Too early",J92,J92*AD92/M92) -> Too early | P92: 31 | Q92: =(AB92-X92)*0.85 -> 860.2 | R92: =IF(B92<7,(P92/VLOOKUP(B92,'Sales Pacing'!$A$23:$E$36,2)),"Too early") -> Too early | S92: =IF(R92="Too early","Too early",R92/Q92) -> Too early | T92: 1099 | U92: 13333 | V92: =IF(T92>0,T92/U92,"") -> 0.082427061 | W92: =IF($R92="Too early",R92,R92*AD92/U92) -> Too early | X92: 578 | Y92: 38874 | Z92: 33333 | AA92: =IF(Y92>0,Y92/Z92,"") -> 1.1662317 | AB92: 1590 | AC92: =I92/AB92 -> 0.38301887 | AD92: =L92/I92 -> 65.63711 | AH92: 39793 | AI92: =L92-AH92 -> 180
A93: 33 | B93: =A93-$G$4 -> 29 | C93: 46125 | D93: 26 CS10 Farrenc/Dvorák/Schuman | G93: 46130.833 | H93: Classical | I93: =P93+X93 -> 624 | J93: =IF(R93="Too early",R93,R93+X93) -> Too early | K93: =IF(J93="Too early",J93,J93/AB93) -> Too early | L93: =T93+Y93 -> 41660.9 | M93: =U93+Z93 -> 46666 | N93: =L93/M93 -> 0.89274632 | O93: =IF($J93="Too early",J93,J93*AD93/M93) -> Too early | P93: 32 | Q93: =(AB93-X93)*0.85 -> 848.3 | R93: =IF(B93<7,(P93/VLOOKUP(B93,'Sales Pacing'!$A$23:$E$36,2)),"Too early") -> Too early | S93: =IF(R93="Too early","Too early",R93/Q93) -> Too early | T93: 1399 | U93: 13333 | V93: =IF(T93>0,T93/U93,"") -> 0.10492762 | W93: =IF($R93="Too early",R93,R93*AD93/U93) -> Too early | X93: 592 | Y93: 40261.9 | Z93: 33333 | AA93: =IF(Y93>0,Y93/Z93,"") -> 1.2078691 | AB93: 1590 | AC93: =I93/AB93 -> 0.39245283 | AD93: =L93/I93 -> 66.764263 | AH93: 41723.9 | AI93: =L93-AH93 -> -63
A94: 33 | B94: =A94-$G$4 -> 29 | C94: 46125 | D94: 26 CS10 Farrenc/Dvorák/Schuman | G94: 46131.583 | H94: Classical | I94: =P94+X94 -> 659 | J94: =IF(R94="Too early",R94,R94+X94) -> Too early | K94: =IF(J94="Too early",J94,J94/AB94) -> Too early | L94: =T94+Y94 -> 41694.2 | M94: =U94+Z94 -> 46667 | N94: =L94/M94 -> 0.89344076 | O94: =IF($J94="Too early",J94,J94*AD94/M94) -> Too early | P94: 40 | Q94: =(AB94-X94)*0.85 -> 825.35 | R94: =IF(B94<7,(P94/VLOOKUP(B94,'Sales Pacing'!$A$23:$E$36,2)),"Too early") -> Too early | S94: =IF(R94="Too early","Too early",R94/Q94) -> Too early | T94: 1731 | U94: 13333 | V94: =IF(T94>0,T94/U94,"") -> 0.12982825 | W94: =IF($R94="Too early",R94,R94*AD94/U94) -> Too early | X94: 619 | Y94: 39963.2 | Z94: 33334 | AA94: =IF(Y94>0,Y94/Z94,"") -> 1.198872 | AB94: 1590 | AC94: =I94/AB94 -> 0.41446541 | AD94: =L94/I94 -> 63.268892 | AH94: 41460.2 | AI94: =L94-AH94 -> 234
A95: 34 | B95: =A95-$G$4 -> 30 | C95: 46132 | D95: OPEN | I95: =P95+X95 -> 0 | J95: =IF(R95="Too early",R95,R95+X95) -> Too early | L95: =T95+Y95 -> 0 | M95: =U95+Z95 -> 0 | N95: =L95/M95 -> #DIV/0! | R95: =IF(B95<7,(P95/VLOOKUP(B95,'Sales Pacing'!$A$23:$E$36,2)),"Too early") -> Too early | V95: =IF(T95>0,T95/U95,"") | AA95: N/A | AC95: =I95/AB95 -> #DIV/0! | AD95: =L95/I95 -> #DIV/0! | AH95: 0
A96: 35 | B96: =A96-$G$4 -> 31 | C96: 46139 | D96: OPEN | I96: =P96+X96 -> 0 | J96: =IF(R96="Too early",R96,R96+X96) -> Too early | L96: =T96+Y96 -> 0 | M96: =U96+Z96 -> 0 | N96: =L96/M96 -> #DIV/0! | R96: =IF(B96<7,(P96/VLOOKUP(B96,'Sales Pacing'!$A$23:$E$36,2)),"Too early") -> Too early | V96: =IF(T96>0,T96/U96,"") | AA96: N/A | AC96: =I96/AB96 -> #DIV/0! | AD96: =L96/I96 -> #DIV/0! | AH96: 0
A97: 36 | B97: =A97-$G$4 -> 32 | C97: 46146 | D97: 26 CS11 Grieg's Piano Concerto | G97: 46150.833 | H97: Classical | I97: =P97+X97 -> 424 | J97: =IF(R97="Too early",R97,R97+X97) -> Too early | K97: =IF(J97="Too early",J97,J97/AB97) -> Too early | L97: =T97+Y97 -> 28112 | M97: =U97+Z97 -> 45000 | N97: =L97/M97 -> 0.62471111 | O97: =IF($J97="Too early",J97,J97*AD97/M97) -> Too early | P97: 50 | Q97: =(AB97-X97)*0.85 -> 1033.6 | R97: =IF(B97<7,(P97/VLOOKUP(B97,'Sales Pacing'!$A$23:$E$36,2)),"Too early") -> Too early | S97: =IF(R97="Too early","Too early",R97/Q97) -> Too early | T97: 2349 | U97: 20000 | V97: =IF(T97>0,T97/U97,"") -> 0.11745 | W97: =IF($R97="Too early",R97,R97*AD97/U97) -> Too early | X97: 374 | Y97: 25763 | Z97: 25000 | AA97: =IF(Y97>0,Y97/Z97,"") -> 1.03052 | AB97: 1590 | AC97: =I97/AB97 -> 0.26666667 | AD97: =L97/I97 -> 66.301887 | AH97: 27937 | AI97: =L97-AH97 -> 175
A98: 36 | B98: =A98-$G$4 -> 32 | C98: 46146 | D98: 26 CS11 Grieg's Piano Concerto | G98: 46151.833 | H98: Classical | I98: =P98+X98 -> 689 | J98: =IF(R98="Too early",R98,R98+X98) -> Too early | K98: =IF(J98="Too early",J98,J98/AB98) -> Too early | L98: =T98+Y98 -> 45719.9 | M98: =U98+Z98 -> 65000 | N98: =L98/M98 -> 0.70338308 | O98: =IF($J98="Too early",J98,J98*AD98/M98) -> Too early | P98: 89 | Q98: =(AB98-X98)*0.85 -> 841.5 | R98: =IF(B98<7,(P98/VLOOKUP(B98,'Sales Pacing'!$A$23:$E$36,2)),"Too early") -> Too early | S98: =IF(R98="Too early","Too early",R98/Q98) -> Too early | T98: 5356 | U98: 17500 | V98: =IF(T98>0,T98/U98,"") -> 0.30605714 | W98: =IF($R98="Too early",R98,R98*AD98/U98) -> Too early | X98: 600 | Y98: 40363.9 | Z98: 47500 | AA98: =IF(Y98>0,Y98/Z98,"") -> 0.84976632 | AB98: 1590 | AC98: =I98/AB98 -> 0.43333333 | AD98: =L98/I98 -> 66.356894 | AH98: 45768.9 | AI98: =L98-AH98 -> -49
A99: 36 | B99: =A99-$G$4 -> 32 | C99: 46146 | D99: 26 CS11 Grieg's Piano Concerto | G99: 46152.583 | H99: Classical | I99: =P99+X99 -> 680 | J99: =IF(R99="Too early",R99,R99+X99) -> Too early | K99: =IF(J99="Too early",J99,J99/AB99) -> Too early | L99: =T99+Y99 -> 43281.2 | M99: =U99+Z99 -> 65000 | N99: =L99/M99 -> 0.66586462 | O99: =IF($J99="Too early",J99,J99*AD99/M99) -> Too early | P99: 69 | Q99: =(AB99-X99)*0.85 -> 832.15 | R99: =IF(B99<7,(P99/VLOOKUP(B99,'Sales Pacing'!$A$23:$E$36,2)),"Too early") -> Too early | S99: =IF(R99="Too early","Too early",R99/Q99) -> Too early | T99: 3734 | U99: 17500 | V99: =IF(T99>0,T99/U99,"") -> 0.21337143 | W99: =IF($R99="Too early",R99,R99*AD99/U99) -> Too early | X99: 611 | Y99: 39547.2 | Z99: 47500 | AA99: =IF(Y99>0,Y99/Z99,"") -> 0.83257263 | AB99: 1590 | AC99: =I99/AB99 -> 0.42767296 | AD99: =L99/I99 -> 63.648824 | AH99: 42812.2 | AI99: =L99-AH99 -> 469
A100: 37 | B100: =A100-$G$4 -> 33 | C100: 46153 | D100: 26 PS5 Dolly Parton's Threads | G100: 46157.833 | H100: Pops | I100: =P100+X100 -> 809 | J100: =IF(R100="Too early",R100,R100+X100) -> Too early | K100: =IF(J100="Too early",J100,J100/AB100) -> Too early | L100: =T100+Y100 -> 67940 | M100: =U100+Z100 -> 103333 | N100: =L100/M100 -> 0.65748599 | O100: =IF($J100="Too early",J100,J100*AD100/M100) -> Too early | P100: 71 | Q100: =(AB100-X100)*0.85 -> 479.4 | R100: =IF(B100<7,(P100/VLOOKUP(B100,'Sales Pacing'!$A$23:$E$36,2)),"Too early") -> Too early | S100: =IF(R100="Too early","Too early",R100/Q100) -> Too early | T100: 5507 | U100: 60000 | V100: =IF(T100>0,T100/U100,"") -> 0.091783333 | W100: =IF($R100="Too early",R100,R100*AD100/U100) -> Too early | X100: 738 | Y100: 62433 | Z100: 43333 | AA100: =IF(Y100>0,Y100/Z100,"") -> 1.4407726 | AB100: 1302 | AC100: =I100/AB100 -> 0.62135177 | AD100: =L100/I100 -> 83.980222 | AH100: 67716 | AI100: =L100-AH100 -> 224
...

Sheet PS1 Journey
B1: # weeks out
A2: Single Tickets | B2: 5 | C2: 4 | D2: 3 | E2: 2 | F2: 1 | G2: 0 | L2: Estimates Only | P2: Historical Data
A3: PS1 Journey | B3: 45880 | C3: 45887 | D3: 45894 | E3: 45901 | F3: 45908 | G3: 45915 | H3: # Single Tickets to sell out 100% | I3: Projected OCC% | K3: # Weeks Until Performance | L3: 10 | M3: 9 | N3: 8 | O3: 7 | P3: 6 | Q3: 5 | R3: 4 | S3: 3 | T3: 2 | U3: 1 | V3: 0
A4: 9/19/2025 Sales (Fri) | B4: 60 | C4: 160 | D4: 205 | E4: 262 | F4: 311 | G4: 390 | H4: ='Performances by Week'!AB10-'Performances by Week'!X10 -> 975 | I4: ='Performances by Week'!K10 -> #N/A | K4: Classical | L4: 0.15 | M4: 0.18 | N4: 0.21 | O4: 0.24 | P4: 0.27 | Q4: 0.3 | R4: 0.33 | S4: 0.39 | T4: 0.46 | U4: 0.59 | V4: 1
A5: 9/20/2025 Sales (Sat) | B5: 63 | C5: 206 | D5: 250 | E5: 294 | F5: 360 | G5: 422 | H5: ='Performances by Week'!AB11-'Performances by Week'!X11 -> 1076 | I5: ='Performances by Week'!K11 -> #N/A | K5: Pops | L5: 0.15 | M5: 0.18 | N5: 0.21 | O5: 0.24 | P5: 0.27 | Q5: 0.3 | R5: 0.33 | S5: 0.39 | T5: 0.46 | U5: 0.59 | V5: 1
A6: 9/21/2025 Sales (Sun) | B6: 57 | C6: 219 | D6: 296 | E6: 322 | F6: 444 | G6: 516 | H6: ='Performances by Week'!AB12-'Performances by Week'!X12 -> 1246 | I6: ='Performances by Week'!K12 -> #N/A | K6: Specials | L6: 0.15 | M6: 0.18 | N6: 0.21 | O6: 0.24 | P6: 0.27 | Q6: 0.3 | R6: 0.33 | S6: 0.39 | T6: 0.46 | U6: 0.59 | V6: 1
A7: Pace for 85% OCC | B7: =$H$7*$H$10*Q5 -> 280.245 | C7: =$H$7*$H$10*R5 -> 308.2695 | D7: =$H$7*$H$10*S5 -> 364.3185 | E7: =$H$7*$H$10*T5 -> 429.709 | F7: =$H$7*$H$10*U5 -> 551.1485 | G7: =$H$7*$H$10*V5 -> 934.15 | H7: =AVERAGE(H4:H6) -> 1099 | K7: Other | L7: 0.15 | M7: 0.18 | N7: 0.21 | O7: 0.24 | P7: 0.27 | Q7: 0.3 | R7: 0.33 | S7: 0.39 | T7: 0.46 | U7: 0.59 | V7: 1
A8: Avg/Show vs Target Pace: | B8: =IF(B4>0,AVERAGE(B4:B6)-B7,"TBD") -> -220.245 | C8: =IF(C4>0,AVERAGE(C4:C6)-C7,"TBD") -> -113.2695 | D8: =IF(D4>0,AVERAGE(D4:D6)-D7,"TBD") -> -113.98517 | E8: =IF(E4>0,AVERAGE(E4:E6)-E7,"TBD") -> -137.04233 | F8: =IF(F4>0,AVERAGE(F4:F6)-F7,"TBD") -> -179.48183 | G8: =IF(G4>0,AVERAGE(G4:G6)-G7,"TBD") -> -491.48333
H9: OCC Target
H10: 0.85

Sheet CS1 Appalachian
B1: # weeks out
A2: Single Tickets | B2: 8 | C2: 7 | D2: 6 | E2: 5 | F2: 4 | G2: 3 | H2: 2 | I2: 1 | J2: 0 | O2: Estimates Only | S2: Historical Data
A3: CS1 Appalachian | B3: 45880 | C3: 45887 | D3: 45894 | E3: 45901 | F3: 45908 | G3: 45915 | H3: 45922 | I3: 45929 | J3: 45936 | K3: # Single Tickets to sell out 100% | L3: Projected OCC% | N3: # Weeks Until Performance | O3: 10 | P3: 9 | Q3: 8 | R3: 7 | S3: 6 | T3: 5 | U3: 4 | V3: 3 | W3: 2 | X3: 1 | Y3: 0
A4: 10/10/2025 Sales (Fri) | B4: 60 | C4: 100 | D4: 106 | E4: 135 | F4: 193 | G4: 212 | H4: 238 | K4: =1433-543 -> 890 | L4: ='Performances by Week'!K15 -> 0.74204314 | N4: Classical | O4: 0.15 | P4: 0.18 | Q4: 0.21 | R4: 0.24 | S4: 0.27 | T4: 0.3 | U4: 0.33 | V4: 0.39 | W4: 0.46 | X4: 0.59 | Y4: 1
A5: 10/11/2025 Sales (Sat) | B5: 63 | C5: 98 | D5: 115 | E5: 130 | F5: 179 | G5: 225 | H5: 258 | K5: =1433-581 -> 852 | L5: ='Performances by Week'!K16 -> 0.83619042 | N5: Pops | O5: 0.15 | P5: 0.18 | Q5: 0.21 | R5: 0.24 | S5: 0.27 | T5: 0.3 | U5: 0.33 | V5: 0.39 | W5: 0.46 | X5: 0.59 | Y5: 1
A6: 10/12/2025 Sales (Sun) | B6: 57 | C6: 137 | D6: 154 | E6: 174 | F6: 239 | G6: 295 | H6: 328 | K6: =1433-613 -> 820 | L6: ='Performances by Week'!K17 -> 0.95048393 | N6: Specials | O6: 0.15 | P6: 0.18 | Q6: 0.21 | R6: 0.24 | S6: 0.27 | T6: 0.3 | U6: 0.33 | V6: 0.39 | W6: 0.46 | X6: 0.59 | Y6: 1
A7: Pace for 85% OCC | B7: =$K$7*$K$10*Q4 -> 151.725 | C7: =$K$7*$K$10*R4 -> 173.4 | D7: =$K$7*$K$10*S4 -> 195.075 | E7: =$K$7*$K$10*T4 -> 216.75 | F7: =$K$7*$K$10*U4 -> 238.425 | G7: =$K$7*$K$10*V4 -> 281.775 | H7: =$K$7*$K$10*W4 -> 332.35 | I7: =$K$7*$K$10*X4 -> 426.275 | J7: =$K$7*$K$10*Y4 -> 722.5 | K7: 850 | N7: Other | O7: 0.15 | P7: 0.18 | Q7: 0.21 | R7: 0.24 | S7: 0.27 | T7: 0.3 | U7: 0.33 | V7: 0.39 | W7: 0.46 | X7: 0.59 | Y7: 1
A8: Avg/Show vs Target Pace: | B8: =IF(B4>0,AVERAGE(B4:B6)-B7,"TBD") -> -91.725 | C8: =IF(C4>0,AVERAGE(C4:C6)-C7,"TBD") -> -61.733333 | D8: =IF(D4>0,AVERAGE(D4:D6)-D7,"TBD") -> -70.075 | E8: =IF(E4>0,AVERAGE(E4:E6)-E7,"TBD") -> -70.416667 | F8: =IF(F4>0,AVERAGE(F4:F6)-F7,"TBD") -> -34.758333 | G8: =IF(G4>0,AVERAGE(G4:G6)-G7,"TBD") -> -37.775 | H8: =IF(H4>0,AVERAGE(H4:H6)-H7,"TBD") -> -57.683333 | I8: =IF(I4>0,AVERAGE(I4:I6)-I7,"TBD") -> TBD | J8: =IF(J4>0,AVERAGE(J4:J6)-J7,"TBD") -> TBD
K9: OCC Target
K10: 0.85

Sheet PS2 90s Mixtape
B1: # Weeks Out | Q1: Estimates Only | U1: Historical Data
A2: Single Tickets | B2: 10 | C2: 9 | D2: 8 | E2: 7 | F2: 6 | G2: 5 | H2: 4 | I2: 3 | J2: 2 | K2: 1 | L2: 0 | P2: # Weeks Until Performance | Q2: 10 | R2: 9 | S2: 8 | T2: 7 | U2: 6 | V2: 5 | W2: 4 | X2: 3 | Y2: 2 | Z2: 1 | AA2: 0
A3: PS2 90s Mixtape (Name?) | B3: 45880 | C3: 45887 | D3: 45894 | E3: 45901 | F3: 45908 | G3: 45915 | H3: 45922 | I3: 45929 | J3: 45936 | K3: 45943 | L3: 45950 | M3: # Single Tickets to sell out 100% | N3: Projected OCC% | P3: Classical | Q3: 0.15 | R3: 0.18 | S3: 0.21 | T3: 0.24 | U3: 0.27 | V3: 0.3 | W3: 0.33 | X3: 0.39 | Y3: 0.46 | Z3: 0.59 | AA3: 1
A4: 10/24/2025 Sales (Fri) | B4: 60 | C4: 64 | D4: 68 | E4: 74 | F4: 80 | G4: 92 | M4: ='Performances by Week'!AB22-'Performances by Week'!X22 -> 882 | N4: ='Performances by Week'!K22 -> 0.67589099 | P4: Pops | Q4: 0.15 | R4: 0.18 | S4: 0.21 | T4: 0.24 | U4: 0.27 | V4: 0.3 | W4: 0.33 | X4: 0.39 | Y4: 0.46 | Z4: 0.59 | AA4: 1
A5: 10/25/2025 Sales (Sat) | B5: 63 | C5: 63 | D5: 73 | E5: 93 | F5: 106 | G5: 114 | M5: ='Performances by Week'!AB23-'Performances by Week'!X23 -> 961 | N5: ='Performances by Week'!K23 -> 0.69672194 | P5: Specials | Q5: 0.15 | R5: 0.18 | S5: 0.21 | T5: 0.24 | U5: 0.27 | V5: 0.3 | W5: 0.33 | X5: 0.39 | Y5: 0.46 | Z5: 0.59 | AA5: 1
A6: 10/26/2025 Sales (Sun) | B6: 57 | C6: 59 | D6: 66 | E6: 74 | F6: 76 | G6: 87 | M6: ='Performances by Week'!AB24-'Performances by Week'!X24 -> 1208 | N6: ='Performances by Week'!K24 -> 0.46704784 | P6: Other | Q6: 0.15 | R6: 0.18 | S6: 0.21 | T6: 0.24 | U6: 0.27 | V6: 0.3 | W6: 0.33 | X6: 0.39 | Y6: 0.46 | Z6: 0.59 | AA6: 1
A7: Pace for 85% OCC | B7: =$M$7*$M$10*Q4 -> 129.6675 | C7: =$M$7*$M$10*R4 -> 155.601 | D7: =$M$7*$M$10*S4 -> 181.5345 | E7: =$M$7*$M$10*T4 -> 207.468 | F7: =$M$7*$M$10*U4 -> 233.4015 | G7: =$M$7*$M$10*V4 -> 259.335 | H7: =$M$7*$M$10*W4 -> 285.2685 | I7: =$M$7*$M$10*X4 -> 337.1355 | ... L7: =$M$7*$M$10*AA4 -> 864.45 | M7: =AVERAGE(M4:M6) -> 1017
A8: Avg/Show vs Target Pace: | B8: =IF(B4>0,AVERAGE(B4:B6)-B7,"TBD") -> -69.6675 | C8: =IF(C4>0,AVERAGE(C4:C6)-C7,"TBD") -> -93.601 | D8: =IF(D4>0,AVERAGE(D4:D6)-D7,"TBD") -> -112.5345 | E8: =IF(E4>0,AVERAGE(E4:E6)-E7,"TBD") -> -127.13467 | F8: =IF(F4>0,AVERAGE(F4:F6)-F7,"TBD") -> -146.06817 | G8: =IF(G4>0,AVERAGE(G4:G6)-G7,"TBD") -> -161.66833 | H8: =IF(H4>0,AVERAGE(H4:H6)-H7,"TBD") -> TBD | I8: =IF(I4>0,AVERAGE(I4:I6)-I7,"TBD") -> TBD | ... L8: =IF(L4>0,AVERAGE(L4:L6)-L7,"TBD") -> TBD
M9: OCC Target
M10: 0.85

Sheet MFSB
A1: Single Tickets | B1: 3 | C1: 2 | D1: 1 | E1: 0 | L1: Single Tickets
A2: MFSB | B2: 45880 | C2: 45887 | D2: 45894 | E2: 45901 | F2: # Single Tickets to sell out 100% | K2: # Weeks Until Performance | L2: Classical | M2: Pops | N2: Specials | O2: Other
A3: 9/2/2025 Sales (Tue) | B3: 754 | C3: 915 | D3: 1013 | E3: 1096 | G3: =E3/F5 -> 0.84178187
A4: 9/3/2025 Sales (Wed) | B4: 651 | C4: 826 | D4: 926 | E4: 1027 | G4: =E4/F5 -> 0.78878648 | K4: 0 | L4: 1 | M4: 1 | N4: 1 | O4: 1
A5: Pace for 85% OCC | B5: =$F$5*$G$5*N7 -> 431.613 | C5: =$F$5*$G$5*N6 -> 509.082 | D5: =$F$5*$G$5*N5 -> 652.953 | E5: =$F$5*$G$5*N4 -> 1106.7 | F5: 1302 | G5: 0.85 | K5: 1 | L5: 0.59 | M5: 0.59 | N5: 0.59 | O5: 0.59
K6: 2 | L6: 0.46 | M6: 0.46 | N6: 0.46 | O6: 0.46
K7: 3 | L7: 0.39 | M7: 0.39 | N7: 0.39 | O7: 0.39
K8: 4 | L8: 0.33 | M8: 0.33 | N8: 0.33 | O8: 0.33
K9: 5 | L9: 0.3 | M9: 0.3 | N9: 0.3 | O9: 0.3
K10: 6 | L10: 0.27 | M10: 0.27 | N10: 0.27 | O10: 0.27

Sheet CS2 Rachmaninoff
D1: # weeks out
A2: Single Tickets | B2: 10 | C2: 9 | D2: 8 | E2: 7 | F2: 6 | G2: 5 | H2: 4 | I2: 3 | J2: 2 | K2: 1 | L2: 0 | Q2: Estimates Only | U2: Historical Data
A3: CS2 Rachmaninoff | B3: 45887 | C3: 45894 | D3: 45901 | E3: 45908 | F3: 45915 | G3: 45922 | H3: 45929 | I3: 45936 | J3: 45943 | K3: 45950 | L3: 45957 | M3: # Single Tickets to sell out 100% | N3: Projected OCC% | P3: # Weeks Until Performance | Q3: 10 | R3: 9 | S3: 8 | T3: 7 | U3: 6 | V3: 5 | W3: 4 | X3: 3 | Y3: 2 | Z3: 1 | AA3: 0
A4: 10/31/2025 Sales (Fri, Piazza) | B4: 87 | C4: 93 | D4: 102 | E4: 106 | F4: 111 | G4: 124 | M4: ='Performances by Week'!AB26-'Performances by Week'!X26 -> 1091 | N4: ='Performances by Week'!K26 -> 0.55733892 | P4: Classical | Q4: 0.15 | R4: 0.18 | S4: 0.21 | T4: 0.24 | U4: 0.27 | V4: 0.3 | W4: 0.33 | X4: 0.39 | Y4: 0.46 | Z4: 0.59 | AA4: 1
A5: 11/01/2025 Sales (Sat) | B5: 192 | C5: 209 | D5: 256 | E5: 310 | F5: 340 | G5: 382 | M5: ='Performances by Week'!AB27-'Performances by Week'!X27 -> 875 | N5: ='Performances by Week'!K27 -> 1.3337986 | P5: Pops | Q5: 0.15 | R5: 0.18 | S5: 0.21 | T5: 0.24 | U5: 0.27 | V5: 0.3 | W5: 0.33 | X5: 0.39 | Y5: 0.46 | Z5: 0.59 | AA5: 1
A6: 11/02/2025 Sales (Sun) | B6: 138 | C6: 165 | D6: 187 | E6: 219 | F6: 232 | G6: 267 | M6: ='Performances by Week'!AB28-'Performances by Week'!X28 -> 872 | N6: ='Performances by Week'!K28 -> 1.068388 | P6: Specials | Q6: 0.15 | R6: 0.18 | S6: 0.21 | T6: 0.24 | U6: 0.27 | V6: 0.3 | W6: 0.33 | X6: 0.39 | Y6: 0.46 | Z6: 0.59 | AA6: 1
A7: Pace for 85% OCC | B7: =$M$7*$M$10*Q4 -> 120.615 | C7: =$M$7*$M$10*R4 -> 144.738 | D7: =$M$7*$M$10*S4 -> 168.861 | E7: =$M$7*$M$10*T4 -> 192.984 | F7: =$M$7*$M$10*U4 -> 217.107 | G7: =$M$7*$M$10*V4 -> 241.23 | H7: =$M$7*$M$10*W4 -> 265.353 | I7: =$M$7*$M$10*X4 -> 313.599 | ... L7: =$M$7*$M$10*AA4 -> 804.1 | M7: =AVERAGE(M4:M6) -> 946 | P7: Other | Q7: 0.15 | R7: 0.18 | S7: 0.21 | T7: 0.24 | U7: 0.27 | V7: 0.3 | W7: 0.33 | X7: 0.39 | Y7: 0.46 | Z7: 0.59 | AA7: 1
A8: Avg/Show vs Target Pace: | B8: =IF(B4>0,AVERAGE(B4:B6)-B7,"TBD") -> 18.385 | C8: =IF(C4>0,AVERAGE(C4:C6)-C7,"TBD") -> 10.928667 | D8: =IF(D4>0,AVERAGE(D4:D6)-D7,"TBD") -> 12.805667 | E8: =IF(E4>0,AVERAGE(E4:E6)-E7,"TBD") -> 18.682667 | F8: =IF(F4>0,AVERAGE(F4:F6)-F7,"TBD") -> 10.559667 | G8: =IF(G4>0,AVERAGE(G4:G6)-G7,"TBD") -> 16.436667 | H8: =IF(H4>0,AVERAGE(H4:H6)-H7,"TBD") -> TBD | I8: =IF(I4>0,AVERAGE(I4:I6)-I7,"TBD") -> TBD | ... L8: =IF(L4>0,AVERAGE(L4:L6)-L7,"TBD") -> TBD
M9: OCC Target
M10: 0.85

Sheet CS3 Mahler
D1: # weeks out
A2: Single Tickets | B2: 10 | C2: 9 | D2: 8 | E2: 7 | F2: 6 | G2: 5 | H2: 4 | I2: 3 | J2: 2 | K2: 1 | L2: 0 | Q2: Estimates Only | U2: Historical Data
A3: CS3 Mahler | B3: 45908 | C3: 45915 | D3: 45922 | E3: 45929 | F3: 45936 | G3: 45943 | H3: 45950 | I3: 45957 | J3: 45964 | K3: 45971 | L3: 45978 | M3: # Single Tickets to sell out 100% | N3: Projected OCC% | P3: # Weeks Until Performance | Q3: 10 | R3: 9 | S3: 8 | T3: 7 | U3: 6 | V3: 5 | W3: 4 | X3: 3 | Y3: 2 | Z3: 1 | AA3: 0
A4: 11/21/2025 Sales (Fri, Piazza) | B4: 55 | C4: 60 | D4: 66 | M4: ='Performances by Week'!AB31-'Performances by Week'!X31 -> 1223 | N4: ='Performances by Week'!K31 -> Too early | P4: Classical | Q4: 0.15 | R4: 0.18 | S4: 0.21 | T4: 0.24 | U4: 0.27 | V4: 0.3 | W4: 0.33 | X4: 0.39 | Y4: 0.46 | Z4: 0.59 | AA4: 1
A5: 11/22/2025 Sales (Sat) | B5: 95 | C5: 110 | D5: 114 | M5: ='Performances by Week'!AB32-'Performances by Week'!X32 -> 1007 | N5: ='Performances by Week'!K32 -> Too early | P5: Pops | Q5: 0.15 | R5: 0.18 | S5: 0.21 | T5: 0.24 | U5: 0.27 | V5: 0.3 | W5: 0.33 | X5: 0.39 | Y5: 0.46 | Z5: 0.59 | AA5: 1
A6: 11/23/2025 Sales (Sun) | B6: 75 | C6: 81 | D6: 83 | M6: ='Performances by Week'!AB33-'Performances by Week'!X33 -> 968 | N6: ='Performances by Week'!K33 -> Too early | P6: Specials | Q6: 0.15 | R6: 0.18 | S6: 0.21 | T6: 0.24 | U6: 0.27 | V6: 0.3 | W6: 0.33 | X6: 0.39 | Y6: 0.46 | Z6: 0.59 | AA6: 1
A7: Pace for 85% OCC | B7: =$M$7*$M$10*Q4 -> 135.915 | C7: =$M$7*$M$10*R4 -> 163.098 | D7: =$M$7*$M$10*S4 -> 190.281 | E7: =$M$7*$M$10*T4 -> 217.464 | F7: =$M$7*$M$10*U4 -> 244.647 | G7: =$M$7*$M$10*V4 -> 271.83 | H7: =$M$7*$M$10*W4 -> 299.013 | I7: =$M$7*$M$10*X4 -> 353.379 | ... L7: =$M$7*$M$10*AA4 -> 906.1 | M7: =AVERAGE(M4:M6) -> 1066 | P7: Other | Q7: 0.15 | R7: 0.18 | S7: 0.21 | T7: 0.24 | U7: 0.27 | V7: 0.3 | W7: 0.33 | X7: 0.39 | Y7: 0.46 | Z7: 0.59 | AA7: 1
A8: Avg/Show vs Target Pace: | B8: =IF(B4>0,AVERAGE(B4:B6)-B7,"TBD") -> -60.915 | C8: =IF(C4>0,AVERAGE(C4:C6)-C7,"TBD") -> -79.431333 | D8: =IF(D4>0,AVERAGE(D4:D6)-D7,"TBD") -> -102.61433 | E8: =IF(E4>0,AVERAGE(E4:E6)-E7,"TBD") -> TBD | F8: =IF(F4>0,AVERAGE(F4:F6)-F7,"TBD") -> TBD | G8: =IF(G4>0,AVERAGE(G4:G6)-G7,"TBD") -> TBD | H8: =IF(H4>0,AVERAGE(H4:H6)-H7,"TBD") -> TBD | I8: =IF(I4>0,AVERAGE(I4:I6)-I7,"TBD") -> TBD | ... L8: =IF(L4>0,AVERAGE(L4:L6)-L7,"TBD") -> TBD
M9: OCC Target
M10: 0.85

Sheet Elf
D1: # weeks out
A2: Single Tickets | B2: 10 | C2: 9 | D2: 8 | E2: 7 | F2: 6 | G2: 5 | H2: 4 | I2: 3 | J2: 2 | K2: 1 | L2: 0 | Q2: Estimates Only | U2: Historical Data
A3: Elf in Concert | B3: 45915 | C3: 45922 | D3: 45929 | E3: 45936 | F3: 45943 | G3: 45950 | H3: 45957 | I3: 45964 | J3: 45971 | K3: 45978 | L3: 45985 | M3: # Single Tickets to sell out 100% | N3: Projected OCC% | P3: # Weeks Until Performance | Q3: 10 | R3: 9 | S3: 8 | T3: 7 | U3: 6 | V3: 5 | W3: 4 | X3: 3 | Y3: 2 | Z3: 1 | AA3: 0
A4: 11/28/2025 (Fri) | B4: 306 | C4: 323 | M4: ='Performances by Week'!AB34-'Performances by Week'!X34 -> 1302 | N4: ='Performances by Week'!K34 -> Too early | P4: Classical | Q4: 0.15 | R4: 0.18 | S4: 0.21 | T4: 0.24 | U4: 0.27 | V4: 0.3 | W4: 0.33 | X4: 0.39 | Y4: 0.46 | Z4: 0.59 | AA4: 1
A5: 11/29/2025 (Sat 1) | B5: 370 | C5: 374 | M5: ='Performances by Week'!AB35-'Performances by Week'!X35 -> 1302 | N5: ='Performances by Week'!K35 -> Too early | P5: Pops | Q5: 0.15 | R5: 0.18 | S5: 0.21 | T5: 0.24 | U5: 0.27 | V5: 0.3 | W5: 0.33 | X5: 0.39 | Y5: 0.46 | Z5: 0.59 | AA5: 1
A6: 11/29/2025 (Sat 2) | B6: 283 | C6: 303 | M6: ='Performances by Week'!AB36-'Performances by Week'!X36 -> 1302 | N6: ='Performances by Week'!K36 -> Too early | P6: Specials | Q6: 0.15 | R6: 0.18 | S6: 0.21 | T6: 0.24 | U6: 0.27 | V6: 0.3 | W6: 0.33 | X6: 0.39 | Y6: 0.46 | Z6: 0.59 | AA6: 1
A7: 11/30/2025 (Sun) | B7: 483 | C7: 514 | M7: ='Performances by Week'!AB37-'Performances by Week'!X37 -> 1302 | N7: ='Performances by Week'!K37 -> Too early | P7: Other | Q7: 0.15 | R7: 0.18 | S7: 0.21 | T7: 0.24 | U7: 0.27 | V7: 0.3 | W7: 0.33 | X7: 0.39 | Y7: 0.46 | Z7: 0.59 | AA7: 1
A8: Pace for 85% OCC | B8: =$M$8*$M$13*Q6 -> 166.005 | C8: =$M$8*$M$13*R6 -> 199.206 | D8: =$M$8*$M$13*S6 -> 232.407 | E8: =$M$8*$M$13*T6 -> 265.608 | F8: =$M$8*$M$13*U6 -> 298.809 | G8: =$M$8*$M$13*V6 -> 332.01 | H8: =$M$8*$M$13*W6 -> 365.211 | I8: =$M$8*$M$13*X6 -> 431.613 | ... L8: =$M$8*$M$13*AA6 -> 1106.7 | M8: =AVERAGE(M4:M7) -> 1302
A9: Home Alone 2024 | B9: =AVERAGE(B32:B35) -> 480.5 | C9: =AVERAGE(C32:C35) -> 532.5 | D9: =AVERAGE(D32:D35) -> 570.5 | E9: =AVERAGE(E32:E35) -> 607.5 | F9: =AVERAGE(F32:F35) -> 645.75 | G9: =AVERAGE(G32:G35) -> 720 | H9: =AVERAGE(H32:H35) -> 836.5 | I9: =AVERAGE(I32:I35) -> 956.75 | ... L9: =AVERAGE(L32:L35) -> 1293.25
A10: Muppet XMas 2023 | B10: =AVERAGE(B43:B44) -> 943.5 | C10: =AVERAGE(C43:C44) -> 992.5 | D10: =AVERAGE(D43:D44) -> 1056 | E10: =AVERAGE(E43:E44) -> 1088 | F10: =AVERAGE(F43:F44) -> 1158 | G10: =AVERAGE(G43:G44) -> 1220 | H10: =AVERAGE(H43:H44) -> 1242.5 | I10: =AVERAGE(I43:I44) -> 1259.5 | ... L10: =AVERAGE(L43:L44) -> 1288.5
A11: Avg/Show vs 2024 Pace: | B11: =IF(B4>0,AVERAGE(B4:B7)-B9,"TBD") -> -120 | C11: =IF(C4>0,AVERAGE(C4:C7)-C9,"TBD") -> -154 | D11: =IF(D4>0,AVERAGE(D4:D7)-D9,"TBD") -> TBD | E11: =IF(E4>0,AVERAGE(E4:E7)-E9,"TBD") -> TBD | F11: =IF(F4>0,AVERAGE(F4:F7)-F9,"TBD") -> TBD | G11: =IF(G4>0,AVERAGE(G4:G7)-G9,"TBD") -> TBD | H11: =IF(H4>0,AVERAGE(H4:H7)-H9,"TBD") -> TBD | I11: =IF(I4>0,AVERAGE(I4:I7)-I9,"TBD") -> TBD | ... L11: =IF(L4>0,AVERAGE(L4:L7)-L9,"TBD") -> TBD
M12: OCC Target
M13: 0.85
A30: Single Tickets | B30: 10 | C30: 9 | D30: 8 | E30: 7 | F30: 6 | G30: 5 | H30: 4 | I30: 3 | J30: 2 | K30: 1 | L30: 0
A31: Home Alone | B31: 45551 | C31: 45558 | D31: 45565 | E31: 45572 | F31: 45579 | G31: 45586 | H31: 45593 | I31: 45600 | J31: 45607 | K31: 45614 | L31: 45621 | M31: # Single Tickets to sell out 100% | N31: Final Occupancy Sold %
A32: 11/29/2024 Sales (Friday) | B32: 395 | C32: 422 | D32: 451 | E32: 488 | F32: 518 | G32: 591 | H32: 667 | I32: 754 | J32: 913 | K32: 1165 | L32: 1276 | M32: 1342 | N32: 0.9664
A33: 11/30/2024, 2pm (Saturday) | B33: 604 | C33: 669 | D33: 701 | E33: 735 | F33: 763 | G33: 832 | H33: 955 | I33: 1040 | J33: 1229 | K33: 1269 | L33: 1301 | M33: 1342 | N33: 0.9873
A34: 11/30/2024, 8pm (Saturday) | B34: 302 | C34: 353 | D34: 391 | E34: 422 | F34: 454 | G34: 500 | H34: 657 | I34: 813 | J34: 988 | K34: 1200 | L34: 1301 | M34: 1342 | N34: 0.9836
A35: 12/01/2024 Sales (Sunday) | B35: 621 | C35: 686 | D35: 739 | E35: 785 | F35: 848 | G35: 957 | H35: 1067 | I35: 1220 | J35: 1269 | K35: 1275 | L35: 1295 | M35: 1342 | N35: 0.9813
A36: Pace for 85% OCC
A37: Avg/Show vs Target Pace:
M38: OCC Target
M39: 0.85
A41: Single Tickets | B41: 10 | C41: 9 | D41: 8 | E41: 7 | F41: 6 | G41: 5 | H41: 4 | I41: 3 | J41: 2 | K41: 1 | L41: 0
A42: A Muppet Christmas Carol | B42: 45194 | C42: 45201 | D42: 45208 | E42: 45215 | F42: 45222 | G42: 45229 | H42: 45236 | I42: 45243 | J42: 45250 | K42: 45988 | L42: 45995 | M42: # Single Tickets to sell out 100% | N42: Final Occupancy Sold %
A43: 12/08/2023 Sales (Friday) | B43: 844 | C43: 894 | D43: 980 | E43: 1010 | F43: 1104 | G43: 1218 | H43: 1244 | I43: 1264 | J43: 1268 | K43: 1279 | L43: 1289 | M43: 1334 | N43: 0.9962
A44: 12/09/2023, 1pm Sales (Saturday) | B44: 1043 | C44: 1091 | D44: 1132 | E44: 1166 | F44: 1212 | G44: 1222 | H44: 1241 | I44: 1255 | J44: 1265 | K44: 1270 | L44: 1288 | M44: 1334 | N44: 0.979
A45: Pace for 85% OCC
A46: Avg/Show vs Target Pace:
M47: OCC Target
M48: 0.85

Sheet Messiah
D1: # weeks out
A2: Single Tickets | B2: 10 | C2: 9 | D2: 8 | E2: 7 | F2: 6 | G2: 5 | H2: 4 | I2: 3 | J2: 2 | K2: 1 | L2: 0 | Q2: Estimates Only | U2: Historical Data
A3: Handel's Messiah | B3: 45922 | C3: 45929 | D3: 45936 | E3: 45943 | F3: 45950 | G3: 45957 | H3: 45964 | I3: 45971 | J3: 45978 | K3: 45985 | L3: 45992 | M3: # Single Tickets to sell out 100% | N3: Projected OCC% | P3: # Weeks Until Performance | Q3: 10 | R3: 9 | S3: 8 | T3: 7 | U3: 6 | V3: 5 | W3: 4 | X3: 3 | Y3: 2 | Z3: 1 | AA3: 0
A4: 12/5/2025 (Fri) | B4: 369 | M4: ='Performances by Week'!AB38-'Performances by Week'!X38 -> 1433 | N4: ='Performances by Week'!K38 -> Too early | P4: Classical | Q4: 0.15 | R4: 0.18 | S4: 0.21 | T4: 0.24 | U4: 0.27 | V4: 0.3 | W4: 0.33 | X4: 0.39 | Y4: 0.46 | Z4: 0.59 | AA4: 1
A5: 12/6/2025 (Sat) | B5: 369 | M5: ='Performances by Week'!AB39-'Performances by Week'!X39 -> 1433 | N5: ='Performances by Week'!K39 -> Too early | P5: Pops | Q5: 0.15 | R5: 0.18 | S5: 0.21 | T5: 0.24 | U5: 0.27 | V5: 0.3 | W5: 0.33 | X5: 0.39 | Y5: 0.46 | Z5: 0.59 | AA5: 1
A6: 12/7/2025 (Sun) | B6: 410 | M6: ='Performances by Week'!AB40-'Performances by Week'!X40 -> 1433 | N6: ='Performances by Week'!K40 -> Too early | P6: Specials | Q6: 0.15 | R6: 0.18 | S6: 0.21 | T6: 0.24 | U6: 0.27 | V6: 0.3 | W6: 0.33 | X6: 0.39 | Y6: 0.46 | Z6: 0.59 | AA6: 1
A7: Pace for 85% OCC | B7: =$M$7*$M$12*Q6 -> 182.7075 | C7: =$M$7*$M$12*R6 -> 219.249 | D7: =$M$7*$M$12*S6 -> 255.7905 | E7: =$M$7*$M$12*T6 -> 292.332 | F7: =$M$7*$M$12*U6 -> 328.8735 | G7: =$M$7*$M$12*V6 -> 365.415 | H7: =$M$7*$M$12*W6 -> 401.9565 | I7: =$M$7*$M$12*X6 -> 475.0395 | ... L7: =$M$7*$M$12*AA6 -> 1218.05 | M7: =AVERAGE(M4:M6) -> 1433 | P7: Other | Q7: 0.15 | R7: 0.18 | S7: 0.21 | T7: 0.24 | U7: 0.27 | V7: 0.3 | W7: 0.33 | X7: 0.39 | Y7: 0.46 | Z7: 0.59 | AA7: 1
A8: Messiah 2024 | B8: =AVERAGE(B31:B33) -> 300.33333 | C8: =AVERAGE(C31:C33) -> 322.33333 | D8: =AVERAGE(D31:D33) -> 360 | E8: =AVERAGE(E31:E33) -> 395.66667 | F8: =AVERAGE(F31:F33) -> 431 | G8: =AVERAGE(G31:G33) -> 486.33333 | H8: =AVERAGE(H31:H33) -> 568.33333 | I8: =AVERAGE(I31:I33) -> 667 | ... L8: =AVERAGE(L31:L33) -> 1146
A9: Messiah 2023 | B9: =AVERAGE(B41:B43) -> 338 | C9: =AVERAGE(C41:C43) -> 372 | D9: =AVERAGE(D41:D43) -> 411 | E9: =AVERAGE(E41:E43) -> 447.33333 | F9: =AVERAGE(F41:F43) -> 494.66667 | G9: =AVERAGE(G41:G43) -> 557 | H9: =AVERAGE(H41:H43) -> 657.66667 | I9: =AVERAGE(I41:I43) -> 738.33333 | ... L9: =AVERAGE(L41:L43) -> 1180.3333
A10: Avg/Show vs Target Pace: | B10: =IF(B4>0,AVERAGE(B4:B6)-B8,"TBD") -> 82.333333 | C10: =IF(C4>0,AVERAGE(C4:C6)-C8,"TBD") -> TBD | D10: =IF(D4>0,AVERAGE(D4:D6)-D8,"TBD") -> TBD | E10: =IF(E4>0,AVERAGE(E4:E6)-E8,"TBD") -> TBD | F10: =IF(F4>0,AVERAGE(F4:F6)-F8,"TBD") -> TBD | G10: =IF(G4>0,AVERAGE(G4:G6)-G8,"TBD") -> TBD | H10: =IF(H4>0,AVERAGE(H4:H6)-H8,"TBD") -> TBD | I10: =IF(I4>0,AVERAGE(I4:I6)-I8,"TBD") -> TBD | ... L10: =IF(L4>0,AVERAGE(L4:L6)-L8,"TBD") -> TBD
M11: OCC Target
M12: 0.85
A29: Single Tickets | B29: 10 | C29: 9 | D29: 8 | E29: 7 | F29: 6 | G29: 5 | H29: 4 | I29: 3 | J29: 2 | K29: 1 | L29: 0
A30: Handel's Messiah | B30: 45558 | C30: 45565 | D30: 45572 | E30: 45579 | F30: 45586 | G30: 45593 | H30: 45600 | I30: 45607 | J30: 45614 | K30: 45621 | L30: 45628 | M30: # Single Tickets to sell out 100% | N30: Final Occupancy Sold %
A31: 12/06/2024 Sales (Friday) | B31: 269 | C31: 295 | D31: 314 | E31: 335 | F31: 385 | G31: 425 | H31: 522 | I31: 615 | J31: 771 | K31: 912 | L31: 1078 | M31: 1450 | N31: 0.8834
A32: 12/07/2024 Sales (Saturday) | B32: 318 | C32: 333 | D32: 368 | E32: 392 | F32: 424 | G32: 483 | H32: 549 | I32: 660 | J32: 751 | K32: 918 | L32: 1127 | M32: 1450 | N32: 0.9662
A33: 12/08/2024 Sales (Sunday) | B33: 314 | C33: 339 | D33: 398 | E33: 460 | F33: 484 | G33: 551 | H33: 634 | I33: 726 | J33: 849 | K33: 1033 | L33: 1233 | M33: 1450 | N33: 0.9751
A34: Pace for 85% OCC
A35: Avg/Show vs Target Pace:
M36: OCC Target
M37: 0.85
A39: Single Tickets | B39: 10 | C39: 9 | D39: 8 | E39: 7 | F39: 6 | G39: 5 | H39: 4 | I39: 3 | J39: 2 | K39: 1 | L39: 0
A40: Handel's Messiah | B40: 45187 | C40: 45194 | D40: 45201 | E40: 45208 | F40: 45215 | G40: 45222 | H40: 45229 | I40: 45236 | J40: 45243 | K40: 45250 | L40: 45988 | M40: # Single Tickets to sell out 100% | N40: Final Occupancy Sold %
A41: 12/01/2023 Sales (Friday) | B41: 292 | C41: 312 | D41: 345 | E41: 367 | F41: 421 | G41: 468 | H41: 562 | I41: 635 | J41: 855 | K41: 992 | L41: 1129 | M41: 1450 | N41: 0.9434
A42: 12/02/2023 Sales (Saturday) | B42: 345 | C42: 396 | D42: 439 | E42: 495 | F42: 538 | G42: 590 | H42: 693 | I42: 784 | J42: 929 | K42: 1043 | L42: 1153 | M42: 1450 | N42: 0.991
A43: 12/03/2023 Sales (Sunday) | B43: 377 | C43: 408 | D43: 449 | E43: 480 | F43: 525 | G43: 613 | H43: 718 | I43: 796 | J43: 945 | K43: 1105 | L43: 1259 | M43: 1450 | N43: 1
A44: Avg/Show vs Target Pace:
M45: OCC Target
M46: 0.85

Sheet XMas Festival
D1: # weeks out
A2: Single Tickets | B2: 10 | C2: 9 | D2: 8 | E2: 7 | F2: 6 | G2: 5 | H2: 4 | I2: 3 | J2: 2 | K2: 1 | L2: 0 | Q2: Estimates Only | U2: Historical Data
A3: Christmas Festival | B3: 45936 | C3: 45943 | D3: 45950 | E3: 45957 | F3: 45964 | G3: 45971 | H3: 45978 | I3: 45985 | J3: 45992 | K3: 45999 | L3: 46006 | M3: # Single Tickets to sell out 100% | N3: Projected OCC% | P3: # Weeks Until Performance | Q3: 10 | R3: 9 | S3: 8 | T3: 7 | U3: 6 | V3: 5 | W3: 4 | X3: 3 | Y3: 2 | Z3: 1 | AA3: 0
A4: 12/18/2025 (Thu) | M4: ='Performances by Week'!AB43-'Performances by Week'!X43 -> 1433 | N4: ='Performances by Week'!K43 -> Too early | P4: Classical | Q4: 0.15 | R4: 0.18 | S4: 0.21 | T4: 0.24 | U4: 0.27 | V4: 0.3 | W4: 0.33 | X4: 0.39 | Y4: 0.46 | Z4: 0.59 | AA4: 1
A5: 12/19/2025 (Fri) | M5: ='Performances by Week'!AB44-'Performances by Week'!X44 -> 1433 | N5: ='Performances by Week'!K44 -> Too early | P5: Pops | Q5: 0.15 | R5: 0.18 | S5: 0.21 | T5: 0.24 | U5: 0.27 | V5: 0.3 | W5: 0.33 | X5: 0.39 | Y5: 0.46 | Z5: 0.59 | AA5: 1
A6: 12/20/2025 (Sat 1) | M6: ='Performances by Week'!AB45-'Performances by Week'!X45 -> 1433 | N6: ='Performances by Week'!K45 -> Too early | P6: Specials | Q6: 0.15 | R6: 0.18 | S6: 0.21 | T6: 0.24 | U6: 0.27 | V6: 0.3 | W6: 0.33 | X6: 0.39 | Y6: 0.46 | Z6: 0.59 | AA6: 1
A7: 12/20/2025 (Sat 2) | M7: ='Performances by Week'!AB46-'Performances by Week'!X46 -> 1433 | N7: ='Performances by Week'!K46 -> Too early | P7: Other | Q7: 0.15 | R7: 0.18 | S7: 0.21 | T7: 0.24 | U7: 0.27 | V7: 0.3 | W7: 0.33 | X7: 0.39 | Y7: 0.46 | Z7: 0.59 | AA7: 1
A8: 12/21/2025 (Sun 1) | M8: ='Performances by Week'!AB47-'Performances by Week'!X47 -> 1132 | N8: ='Performances by Week'!K47 -> Too early
A9: 12/21/2025 (Sun 2) | M9: ='Performances by Week'!AB48-'Performances by Week'!X48 -> 1433 | N9: ='Performances by Week'!K48 -> Too early
A10: Pace for 85% OCC | B10: =$M$10*$M$15*Q6 -> 176.31125 | C10: =$M$10*$M$15*R6 -> 211.5735 | D10: =$M$10*$M$15*S6 -> 246.83575 | E10: =$M$10*$M$15*T6 -> 282.098 | F10: =$M$10*$M$15*U6 -> 317.36025 | G10: =$M$10*$M$15*V6 -> 352.6225 | H10: =$M$10*$M$15*W6 -> 387.88475 | I10: =$M$10*$M$15*X6 -> 458.40925 | ... L10: =$M$10*$M$15*AA6 -> 1175.4083 | M10: =AVERAGE(M4:M9) -> 1382.8333
A11: XMas 2024 | B11: =AVERAGE(B34:B39) -> 261.33333 | C11: =AVERAGE(C34:C39) -> 282.66667 | D11: =AVERAGE(D34:D39) -> 315.5 | E11: =AVERAGE(E34:E39) -> 360.16667 | F11: =AVERAGE(F34:F39) -> 412.16667 | G11: =AVERAGE(G34:G39) -> 494.33333 | H11: =AVERAGE(H34:H39) -> 597.83333 | I11: =AVERAGE(I34:I39) -> 699.5 | ... L11: =AVERAGE(L34:L39) -> 1111.3333
A12: XMas 2023 | B12: =AVERAGE(B45:B50) -> 349.16667 | C12: =AVERAGE(C45:C50) -> 378.16667 | D12: =AVERAGE(D45:D50) -> 414.66667 | E12: =AVERAGE(E45:E50) -> 459.16667 | F12: =AVERAGE(F45:F50) -> 530.83333 | G12: =AVERAGE(G45:G50) -> 599.66667 | H12: =AVERAGE(H45:H50) -> 709 | I12: =AVERAGE(I45:I50) -> 795.5 | ... L12: =AVERAGE(L45:L50) -> 1105.8333
A13: Avg/Show vs Target Pace: | B13: =IF(B4>0,AVERAGE(B4:B9)-B10,"TBD") -> TBD | C13: =IF(C4>0,AVERAGE(C4:C9)-C10,"TBD") -> TBD | D13: =IF(D4>0,AVERAGE(D4:D9)-D10,"TBD") -> TBD | E13: =IF(E4>0,AVERAGE(E4:E9)-E10,"TBD") -> TBD | F13: =IF(F4>0,AVERAGE(F4:F9)-F10,"TBD") -> TBD | G13: =IF(G4>0,AVERAGE(G4:G9)-G10,"TBD") -> TBD | H13: =IF(H4>0,AVERAGE(H4:H9)-H10,"TBD") -> TBD | I13: =IF(I4>0,AVERAGE(I4:I9)-I10,"TBD") -> TBD | ... L13: =IF(L4>0,AVERAGE(L4:L9)-L10,"TBD") -> TBD
M14: OCC Target
M15: 0.85
A32: Single Tickets | B32: 10 | C32: 9 | D32: 8 | E32: 7 | F32: 6 | G32: 5 | H32: 4 | I32: 3 | J32: 2 | K32: 1 | L32: 0
A33: Christmas Festival | B33: 45572 | C33: 45579 | D33: 45586 | E33: 45593 | F33: 45600 | G33: 45607 | H33: 45614 | I33: 45621 | J33: 45628 | K33: 45635 | L33: 45642 | M33: # Single Tickets to sell out 100% | N33: Final Occupancy Sold %
A34: 12/19/2024 Sales (Thursday) | B34: 261 | C34: 267 | D34: 297 | E34: 341 | F34: 395 | G34: 447 | H34: 602 | I34: 693 | J34: 750 | K34: 932 | L34: 1069 | M34: 1446 | N34: 0.7897
A35: 12/20/2024 Sales (Friday) | B35: 206 | C35: 216 | D35: 256 | E35: 310 | F35: 370 | G35: 432 | H35: 509 | I35: 605 | J35: 732 | K35: 848 | L35: 1052 | M35: 1476 | N35: 0.8741
A36: 12/21/2024, 1pm Sales (Saturday) | B36: 349 | C36: 398 | D36: 427 | E36: 464 | F36: 526 | G36: 606 | H36: 670 | I36: 745 | J36: 848 | K36: 1034 | L36: 1180 | M36: 1476 | N36: 0.8934
A37: 12/21/2024, 7pm Sales (Saturday) | B37: 276 | C37: 294 | D37: 340 | E37: 375 | F37: 400 | G37: 480 | H37: 584 | I37: 715 | J37: 844 | K37: 995 | L37: 1184 | M37: 1476 | N37: 0.9591
A38: 12/22/2024, 2pm Sales (Sunday) | B38: 302 | C38: 336 | D38: 363 | E38: 411 | F38: 486 | G38: 624 | H38: 730 | I38: 857 | J38: 986 | K38: 1089 | L38: 1104 | M38: 1168 | N38: 0.9412
A39: 12/22/2024, 7pm Sales (Sunday) | B39: 174 | C39: 185 | D39: 210 | E39: 260 | F39: 296 | G39: 377 | H39: 492 | I39: 582 | J39: 677 | K39: 833 | L39: 1079 | M39: 1476 | N39: 0.9751
M40: OCC Target
M41: 0.85
A43: Single Tickets | B43: 10 | C43: 9 | D43: 8 | E43: 7 | F43: 6 | G43: 5 | H43: 4 | I43: 3 | J43: 2 | K43: 1 | L43: 0
A44: Christmas Festival | B44: 45201 | C44: 45208 | D44: 45215 | E44: 45222 | F44: 45229 | G44: 45236 | H44: 45243 | I44: 45250 | J44: 45988 | K44: 45995 | L44: 46002 | M44: # Single Tickets to sell out 100% | N44: Final Occupancy Sold %
A45: 12/14/2023 Sales (Thursday) | B45: 279 | C45: 293 | D45: 309 | E45: 348 | F45: 410 | G45: 485 | H45: 540 | I45: 608 | J45: 674 | K45: 793 | L45: 912 | M45: 1446 | N45: 0.7627
A46: 12/15/2023 Sales (Friday) | B46: 288 | C46: 332 | D46: 391 | E46: 435 | F46: 536 | G46: 605 | H46: 744 | I46: 845 | J46: 942 | K46: 1068 | L46: 1230 | M46: 1446 | N46: 0.9273
A47: 12/16/2023, 1pm Sales (Saturday) | B47: 506 | C47: 529 | D47: 575 | E47: 625 | F47: 741 | G47: 835 | H47: 972 | I47: 1097 | J47: 1175 | K47: 1315 | L47: 1382 | M47: 1446 | N47: 0.9723
A48: 12/16/2023, 7pm Sales (Saturday) | B48: 396 | C48: 417 | D48: 462 | E48: 520 | F48: 554 | G48: 619 | H48: 806 | I48: 887 | J48: 965 | K48: 1139 | L48: 1312 | M48: 1446 | N48: 0.9764
A49: 12/17/2023, 2pm Sales (Sunday) | B49: 442 | C49: 467 | D49: 499 | E49: 559 | F49: 648 | G49: 712 | H49: 800 | I49: 857 | J49: 866 | K49: 903 | L49: 925 | M49: 969 | N49: 0.9917
A50: 12/17/2023, 7pm Sales (Sunday) | B50: 184 | C50: 231 | D50: 252 | E50: 268 | F50: 296 | G50: 342 | H50: 392 | I50: 479 | J50: 584 | K50: 729 | L50: 874 | M50: 1446 | N50: 0.9702

Sheet Subscriptions
B1: KANSAS CITY SYMPHONY | E1: Update all fields in Blue each week | J1: 100%+ of FY26 Goal
B2: 2025-26 Subscriptions | E2: We expect 50% of Total by Week 5 | J2: 90-99% of FY26 Goal | N2: Classical | S2: FY26 Budget - Classical
E3: We expect 90% of Total by Week 10/11 | J3: <90% of FY26 Goal | N3: 0.72 | O3: % of total subscriptions | S3: Units | T3: Revenue
O4: =O8/S8*S4 -> 190.76952 | P4: =P8/O8*O4 -> 67934.779 | Q4: =Q8/S8*S4 -> 2954.7347 | R4: =R8/Q8*Q4 -> 1567065.2 | S4: =T4/(T8/S8) -> 3145.5043 | T4: 1635000 | U4: Total
B5: FY26 Sales - Classical | O5: =O9/S9*S5 -> 8.6708651 | P5: =P9/O9*O5 -> 2639.1544 | Q5: =Q9/S9*S5 -> 267.83339 | R5: =R9/Q9*Q5 -> 147753.15 | S5: =T5/(T8/S8) -> 276.50425 | T5: =T4-T8 -> 143724 | U5: Difference vs FY25
C6: New | F6: Renewals | I6: Total | N6: FY25 Actuals - Classical
A7: Weeks On Sale | C7: Actual Units | D7: Proj | E7: Actual Rev | F7: Actual Units | G7: Proj | H7: Actual Rev | I7: Actual Units | J7: Proj | K7: Actual Rev | L7: W/W Change | O7: New Units | P7: New Revenue | Q7: Renewal Units | R7: Renewal Revenue | S7: Total Units | T7: Total Revenue | U7: Change
A8: Projected Total | I8: =I16 -> 2456 | K8: =K16 -> 1408430 | N8: Final | O8: =O21 -> 174 | P8: =P21 -> 61963 | Q8: =Q21 -> 2695 | R8: =R21 -> 1429313 | S8: =S21 -> 2869 | T8: =T21 -> 1491276
A9: 1 | B9: 45747 | C9: 30 | D9: =C9/'Sales Pacing'!B3 -> 713.33333 | E9: 16220 | F9: 898 | G9: =F9/'Sales Pacing'!E3 -> 3554.0218 | H9: 527973 | I9: =C9+F9 -> 928 | J9: =D9+G9 -> 4267.3552 | K9: =E9+H9 -> 544193 | N9: 45383 | O9: 27 | P9: 8218 | Q9: 834 | R9: 460085 | S9: =O9+Q9 -> 861 | T9: =P9+R9 -> 468303
A10: 2 | B10: 45754 | C10: 39 | D10: =C10/'Sales Pacing'!B4 -> 642 | E10: 21024 | F10: 1136 | G10: =F10/'Sales Pacing'!E4 -> 3593.8233 | H10: 652031 | I10: =C10+F10 -> 1175 | J10: =D10+G10 -> 4235.8233 | K10: =E10+H10 -> 673055 | L10: =IF(K10>0,K10-K9,0) -> 128862 | N10: =N9+7 -> 45390 | O10: 32 | P10: 12068 | Q10: 1194 | R10: 655718 | S10: =O10+Q10 -> 1226 | T10: =P10+R10 -> 667786 | U10: =IF(T10>0,T10-T9,0) -> 199483
A11: 3 | B11: 45761 | C11: 50 | D11: =C11/'Sales Pacing'!B5 -> 455.31915 | E11: 27424 | F11: 1387 | G11: =F11/'Sales Pacing'!E5 -> 3529.55 | H11: 817109 | I11: =C11+F11 -> 1437 | J11: =D11+G11 -> 3984.8691 | K11: =E11+H11 -> 844533 | L11: =IF(K11>0,K11-K10,0) -> 171478 | N11: =N10+7 -> 45397 | O11: 36 | P11: 13657 | Q11: 1434 | R11: 789833 | S11: =O11+Q11 -> 1470 | T11: =P11+R11 -> 803490 | U11: =IF(T11>0,T11-T10,0) -> 135704
A12: 4 | B12: 45768 | C12: 76 | D12: =C12/'Sales Pacing'!B6 -> 591.41818 | E12: 40984 | F12: 1739 | G12: =F12/'Sales Pacing'!E6 -> 3653.0333 | H12: 1005395 | I12: =C12+F12 -> 1815 | J12: =D12+G12 -> 4244.4515 | K12: =E12+H12 -> 1046379 | L12: =IF(K12>0,K12-K11,0) -> 201846 | N12: =N11+7 -> 45404 | O12: 45 | P12: 17584 | Q12: 1789 | R12: 976040 | S12: =O12+Q12 -> 1834 | T12: =P12+R12 -> 993624 | U12: =IF(T12>0,T12-T11,0) -> 190134
A13: 5 | B13: =B12+7 -> 45775 | C13: 112 | D13: =C13/'Sales Pacing'!B7 -> 684.8 | E13: 54163 | F13: 2160 | G13: =F13/'Sales Pacing'!E7 -> 3788.4885 | H13: 1232817 | I13: =C13+F13 -> 2272 | J13: =D13+G13 -> 4473.2885 | K13: =E13+H13 -> 1286980 | L13: =IF(K13>0,K13-K12,0) -> 240601 | N13: =N12+7 -> 45411 | O13: 47 | P13: 17987 | Q13: 2005 | R13: 1080463 | S13: =O13+Q13 -> 2052 | T13: =P13+R13 -> 1098450 | U13: =IF(T13>0,T13-T12,0) -> 104826
A14: 6 | B14: =B13+7 -> 45782 | C14: 121 | D14: =C14/'Sales Pacing'!B8 -> 533.89691 | E14: 58153 | F14: 2252 | G14: =F14/'Sales Pacing'!E8 -> 3121.3817 | H14: 1294295 | I14: =C14+F14 -> 2373 | J14: =D14+G14 -> 3655.2787 | K14: =E14+H14 -> 1352448 | L14: =IF(K14>0,K14-K13,0) -> 65468 | N14: =N13+7 -> 45418 | O14: 70 | P14: 26832 | Q14: 2362 | R14: 1271615 | S14: =O14+Q14 -> 2432 | T14: =P14+R14 -> 1298447 | U14: =IF(T14>0,T14-T13,0) -> 199997
A15: 7 | B15: =B14+7 -> 45789 | C15: 122 | D15: =C15/'Sales Pacing'!B9 -> 404.77519 | E15: 59763 | F15: 2293 | G15: =F15/'Sales Pacing'!E9 -> 2534.0926 | H15: 1322554 | I15: =C15+F15 -> 2415 | J15: =D15+G15 -> 2938.8678 | K15: =E15+H15 -> 1382317 | L15: =IF(K15>0,K15-K14,0) -> 29869 | N15: =N14+7 -> 45425 | O15: 76 | P15: 28802 | Q15: 2443 | R15: 1319275 | S15: =O15+Q15 -> 2519 | T15: =P15+R15 -> 1348077 | U15: =IF(T15>0,T15-T14,0) -> 49630
A16: 8 | B16: =B15+7 -> 45796 | C16: 134 | D16: =C16/'Sales Pacing'!B10 -> 382.34667 | E16: 63528 | F16: 2322 | G16: =F16/'Sales Pacing'!E10 -> 2473.787 | H16: 1344902 | I16: =C16+F16 -> 2456 | J16: =D16+G16 -> 2856.1337 | K16: =E16+H16 -> 1408430 | L16: =IF(K16>0,K16-K15,0) -> 26113 | N16: =N15+7 -> 45432 | O16: 85 | P16: 30752 | Q16: 2473 | R16: 1329297 | S16: =O16+Q16 -> 2558 | T16: =P16+R16 -> 1360049 | U16: =IF(T16>0,T16-T15,0) -> 11972
A17: 9 | B17: =B16+7 -> 45803 | C17: 146 | D17: =C17/'Sales Pacing'!B11 -> 369.75148 | E17: 67946 | F17: 2345 | G17: =F17/'Sales Pacing'!E11 -> 2468.3763 | H17: 1357272 | I17: =C17+F17 -> 2491 | J17: =D17+G17 -> 2838.1277 | K17: =E17+H17 -> 1425218 | L17: =IF(K17>0,K17-K16,0) -> 16788 | N17: =N16+7 -> 45439 | O17: 91 | P17: 32154 | Q17: 2513 | R17: 1344658 | S17: =O17+Q17 -> 2604 | T17: =P17+R17 -> 1376812 | U17: =IF(T17>0,T17-T16,0) -> 16763
A18: 10 | B18: =B17+7 -> 45810 | C18: 165 | D18: =C18/'Sales Pacing'!B12 -> 377.64706 | E18: 75744 | F18: 2369 | G18: =F18/'Sales Pacing'!E12 -> 2461.486 | H18: 1380368 | I18: =C18+F18 -> 2534 | J18: =D18+G18 -> 2839.1331 | K18: =E18+H18 -> 1456112 | L18: =IF(K18>0,K18-K17,0) -> 30894 | N18: =N17+7 -> 45446 | O18: 94 | P18: 32854 | Q18: 2608 | R18: 1391277 | S18: =O18+Q18 -> 2702 | T18: =P18+R18 -> 1424131 | U18: =IF(T18>0,T18-T17,0) -> 47319
A19: 11 | B19: =B18+7 -> 45817 | C19: 186 | D19: =C19/'Sales Pacing'!B13 -> 396.0597 | E19: 89633 | F19: 2384 | G19: =F19/'Sales Pacing'!E13 -> 2469.1125 | H19: 1390065 | I19: =C19+F19 -> 2570 | J19: =D19+G19 -> 2865.1722 | K19: =E19+H19 -> 1479698 | L19: =IF(K19>0,K19-K18,0) -> 23586 | N19: =N18+7 -> 45453 | O19: 95 | P19: 33169 | Q19: 2628 | R19: 1398365 | S19: =O19+Q19 -> 2723 | T19: =P19+R19 -> 1431534 | U19: =IF(T19>0,T19-T18,0) -> 7403
A20: 12 | B20: =B19+7 -> 45824 | C20: 205 | D20: =C20/'Sales Pacing'!B14 -> 404.3318 | E20: 94753 | F20: 2413 | G20: =F20/'Sales Pacing'!E14 -> 2491.1434 | H20: 1408181 | I20: =C20+F20 -> 2618 | J20: =D20+G20 -> 2895.4752 | K20: =E20+H20 -> 1502934 | L20: =IF(K20>0,K20-K19,0) -> 23236 | N20: =N19+7 -> 45460 | O20: 103 | P20: 35745 | Q20: 2655 | R20: 1411925 | S20: =O20+Q20 -> 2758 | T20: =P20+R20 -> 1447670 | U20: =IF(T20>0,T20-T19,0) -> 16136
A21: 13+ | B21: 45922 | C21: 320 | D21: =C21/'Sales Pacing'!B15 -> 320 | E21: 141042 | F21: 2427 | G21: =F21/'Sales Pacing'!E15 -> 2427 | H21: 1411610 | I21: =C21+F21 -> 2747 | J21: =D21+G21 -> 2747 | K21: =E21+H21 -> 1552652 | L21: =IF(K21>0,K21-K20,0) -> 49718 | N21: Rest of Season | O21: 174 | P21: 61963 | Q21: 2695 | R21: 1429313 | S21: =O21+Q21 -> 2869 | T21: =P21+R21 -> 1491276 | U21: =IF(T21>0,T21-T20,0) -> 43606
I22: vs. FY26 Goal | J22: =J21/$S$4 -> 0.8733099 | K22: =K21/$T$4 -> 0.94963425
B23: 25-26 Churn | C23: #
B24: =(1-F21/S8) -> 0.15406065 | C24: =S8-F21 -> 442 | E24: 3rd Classical mailer drops 22nd/23rd of August | N24: Pops | S24: FY26 Budget - Pops
N25: 0.26 | O25: % of total subscriptions | S25: Units | T25: Revenue
O26: =O30/S30*S26 -> 240.07343 | P26: =P30/O30*O26 -> 69318.269 | Q26: =Q30/S30*S26 -> 1547.1399 | R26: =R30/Q30*Q26 -> 549681.73 | S26: =T26/(T30/S30) -> 1787.2133 | T26: 619000 | U26: Total
B27: FY26 Sales - Pops | O27: =O31/S31*S27 -> 3.2060949 | P27: =P31/O31*O27 -> 1038.7747 | Q27: =Q31/S31*S27 -> 109.00723 | R27: =R31/Q31*Q27 -> 44362.735 | S27: =T27/(T30/S30) -> 112.21332 | T27: =T26-T30 -> 38865 | U27: Difference vs FY25
C28: New | F28: Renewals | I28: Total | N28: FY25 Actuals - Pops
C29: Actual Units | D29: Proj | E29: Actual Rev | F29: Actual Units | G29: Proj | H29: Actual Rev | I29: Actual Units | J29: Proj | K29: Actual Rev | L29: W/W Change | O29: New Units | P29: New Revenue | Q29: Renewal Units | R29: Renewal Revenue | S29: Total Units | T29: Total Revenue | U29: Change
A30: Projected Total | I30: =I38 -> 1561 | K30: =K38 -> 591188 | N30: Final | O30: =O43 -> 225 | P30: =P43 -> 64966 | Q30: =Q43 -> 1450 | R30: =R43 -> 515169 | S30: =S43 -> 1675 | T30: =T43 -> 580135
A31: 1 | B31: 45747 | C31: 38 | D31: =C31/'Sales Pacing'!C3 -> 1048.1667 | E31: 13163 | F31: 636 | G31: =F31/'Sales Pacing'!F3 -> 5546.3927 | H31: 258782 | I31: =C31+F31 -> 674 | J31: =D31+G31 -> 6594.5593 | K31: =E31+H31 -> 271945 | N31: 45383 | O31: 2 | P31: 648 | Q31: 68 | R31: 27674 | S31: =O31+Q31 -> 70 | T31: =P31+R31 -> 28322
A32: 2 | B32: 45754 | C32: 44 | D32: =C32/'Sales Pacing'!C4 -> 606.83333 | E32: 14651 | F32: 785 | G32: =F32/'Sales Pacing'!F4 -> 3783.5789 | H32: 312531 | I32: =C32+F32 -> 829 | J32: =D32+G32 -> 4390.4122 | K32: =E32+H32 -> 327182 | L32: =IF(K32>0,K32-K31,0) -> 55237 | N32: =N31+7 -> 45390 | O32: 54 | P32: 17576 | Q32: 181 | R32: 68648 | S32: =O32+Q32 -> 235 | T32: =P32+R32 -> 86224 | U32: =IF(T32>0,T32-T31,0) -> 57902
A33: 3 | B33: 45761 | C33: 54 | D33: =C33/'Sales Pacing'!C5 -> 616.34483 | E33: 19061 | F33: 893 | G33: =F33/'Sales Pacing'!F5 -> 3135.2144 | H33: 353304 | I33: =C33+F33 -> 947 | J33: =D33+G33 -> 3751.5592 | K33: =E33+H33 -> 372365 | L33: =IF(K33>0,K33-K32,0) -> 45183 | N33: =N32+7 -> 45397 | O33: 66 | P33: 20302 | Q33: 283 | R33: 105425 | S33: =O33+Q33 -> 349 | T33: =P33+R33 -> 125727 | U33: =IF(T33>0,T33-T32,0) -> 39503
A34: 4 | B34: 45768 | C34: 60 | D34: =C34/'Sales Pacing'!C6 -> 484.39024 | E34: 20782 | F34: 1067 | G34: =F34/'Sales Pacing'!F6 -> 2921.075 | H34: 417996 | I34: =C34+F34 -> 1127 | J34: =D34+G34 -> 3405.4653 | K34: =E34+H34 -> 438778 | L34: =IF(K34>0,K34-K33,0) -> 66413 | N34: =N33+7 -> 45404 | O34: 86 | P34: 26557 | Q34: 389 | R34: 146108 | S34: =O34+Q34 -> 475 | T34: =P34+R34 -> 172665 | U34: =IF(T34>0,T34-T33,0) -> 46938
A35: 5 | B35: =B34+7 -> 45775 | C35: 118 | D35: =C35/'Sales Pacing'!C7 -> 566.05797 | E35: 38918 | F35: 1300 | G35: =F35/'Sales Pacing'!F7 -> 2887.9509 | H35: 502867 | I35: =C35+F35 -> 1418 | J35: =D35+G35 -> 3454.0088 | K35: =E35+H35 -> 541785 | L35: =IF(K35>0,K35-K34,0) -> 103007 | N35: =N34+7 -> 45411 | O35: 86 | P35: 26557 | Q35: 476 | R35: 178054 | S35: =O35+Q35 -> 562 | T35: =P35+R35 -> 204611 | U35: =IF(T35>0,T35-T34,0) -> 31946
A36: 6 | B36: =B35+7 -> 45782 | C36: 157 | D36: =C36/'Sales Pacing'!C8 -> 683.77632 | E36: 51765 | F36: 1358 | G36: =F36/'Sales Pacing'!F8 -> 2121.6398 | H36: 522161 | I36: =C36+F36 -> 1515 | J36: =D36+G36 -> 2805.4161 | K36: =E36+H36 -> 573926 | L36: =IF(K36>0,K36-K35,0) -> 32141 | N36: =N35+7 -> 45418 | O36: 98 | P36: 31472 | Q36: 806 | R36: 294720 | S36: =O36+Q36 -> 904 | T36: =P36+R36 -> 326192 | U36: =IF(T36>0,T36-T35,0) -> 121581
A37: 7 | B37: =B36+7 -> 45789 | C37: 165 | D37: =C37/'Sales Pacing'!C9 -> 593.6413 | E37: 54301 | F37: 1365 | G37: =F37/'Sales Pacing'!F9 -> 1717.375 | H37: 525805 | I37: =C37+F37 -> 1530 | J37: =D37+G37 -> 2311.0163 | K37: =E37+H37 -> 580106 | L37: =IF(K37>0,K37-K36,0) -> 6180 | N37: =N36+7 -> 45425 | O37: 113 | P37: 36672 | Q37: 1031 | R37: 372369 | S37: =O37+Q37 -> 1144 | T37: =P37+R37 -> 409041 | U37: =IF(T37>0,T37-T36,0) -> 82849
A38: 8 | B38: =B37+7 -> 45796 | C38: 199 | D38: =C38/'Sales Pacing'!C10 -> 639.50485 | E38: 65018 | F38: 1362 | G38: =F38/'Sales Pacing'!F10 -> 1532.8471 | H38: 526170 | I38: =C38+F38 -> 1561 | J38: =D38+G38 -> 2172.3519 | K38: =E38+H38 -> 591188 | L38: =IF(K38>0,K38-K37,0) -> 11082 | N38: =N37+7 -> 45432 | O38: 127 | P38: 40518 | Q38: 1267 | R38: 452816 | S38: =O38+Q38 -> 1394 | T38: =P38+R38 -> 493334 | U38: =IF(T38>0,T38-T37,0) -> 84293
A39: 9 | B39: =B38+7 -> 45803 | C39: 220 | D39: =C39/'Sales Pacing'!C11 -> 568.90625 | E39: 73218 | F39: 1368 | G39: =F39/'Sales Pacing'!F11 -> 1451.7935 | H39: 531352 | I39: =C39+F39 -> 1588 | J39: =D39+G39 -> 2020.6998 | K39: =E39+H39 -> 604570 | L39: =IF(K39>0,K39-K38,0) -> 13382 | N39: =N38+7 -> 45439 | O39: 160 | P39: 48485 | Q39: 1395 | R39: 497335 | S39: =O39+Q39 -> 1555 | T39: =P39+R39 -> 545820 | U39: =IF(T39>0,T39-T38,0) -> 52486
A40: 10 | B40: =B39+7 -> 45810 | C40: 239 | D40: =C40/'Sales Pacing'!C12 -> 557.10563 | E40: 80035 | F40: 1374 | G40: =F40/'Sales Pacing'!F12 -> 1439.2578 | H40: 536728 | I40: =C40+F40 -> 1613 | J40: =D40+G40 -> 1996.3634 | K40: =E40+H40 -> 616763 | L40: =IF(K40>0,K40-K39,0) -> 12193 | N40: =N39+7 -> 45446 | O40: 172 | P40: 51234 | Q40: 1411 | R40: 502695 | S40: =O40+Q40 -> 1583 | T40: =P40+R40 -> 553929 | U40: =IF(T40>0,T40-T39,0) -> 8109
A41: 11 | B41: =B40+7 -> 45817 | C41: 255 | D41: =C41/'Sales Pacing'!C13 -> 530.84906 | E41: 89633 | F41: 1407 | G41: =F41/'Sales Pacing'!F13 -> 1457.5735 | H41: 540393 | I41: =C41+F41 -> 1662 | J41: =D41+G41 -> 1988.4225 | K41: =E41+H41 -> 630026 | L41: =IF(K41>0,K41-K40,0) -> 13263 | N41: =N40+7 -> 45453 | O41: 187 | P41: 55826 | Q41: 1418 | R41: 505550 | S41: =O41+Q41 -> 1605 | T41: =P41+R41 -> 561376 | U41: =IF(T41>0,T41-T40,0) -> 7447
A42: 12 | B42: =B41+7 -> 45824 | C42: 270 | D42: =C42/'Sales Pacing'!C14 -> 470.36842 | E42: 90711 | F42: 1383 | G42: =F42/'Sales Pacing'!F14 -> 1420.054 | H42: 543160 | I42: =C42+F42 -> 1653 | J42: =D42+G42 -> 1890.4224 | K42: =E42+H42 -> 633871 | L42: =IF(K42>0,K42-K41,0) -> 3845 | N42: =N41+7 -> 45460 | O42: 193 | P42: 57355 | Q42: 1434 | R42: 510568 | S42: =O42+Q42 -> 1627 | T42: =P42+R42 -> 567923 | U42: =IF(T42>0,T42-T41,0) -> 6547
A43: 13+ | B43: 45922 | C43: 377 | D43: =C43/'Sales Pacing'!C15 -> 377 | E43: 117930 | F43: 1409 | G43: =F43/'Sales Pacing'!F15 -> 1409 | H43: 544870 | I43: =C43+F43 -> 1786 | J43: =D43+G43 -> 1786 | K43: =E43+H43 -> 662800 | L43: =IF(K43>0,K43-K42,0) -> 28929 | N43: Rest of Season | O43: 225 | P43: 64966 | Q43: 1450 | R43: 515169 | S43: =O43+Q43 -> 1675 | T43: =P43+R43 -> 580135 | U43: =IF(T43>0,T43-T42,0) -> 12212
I44: vs. FY26 Goal | J44: =J43/$S$26 -> 0.99932111 | K44: =K43/$T$26 -> 1.0707593
B45: 25-26 Churn | C45: #
B46: =(1-F43/S30) -> 0.15880597 | C46: =S30-F43 -> 266
A48: Future Improvements:
A49: Give true renewal rates
A50: Show renewals by customer cohort
A51: Add Family subscriptions (2%)

Sheet Summary (Draft)
B2: Overall Season | G2: # Tickets Sold | H2: Projected Tickets Sold | I2: Projected Occupancy (% +GYR) | J2: Total Revenue | K2: BUDGET | L2: Projected Revenue vs Budget (% +GYR)
B3: ALL CONCERTS | G3: ='Performances by Week'!I126 -> 0 | H3: ='Performances by Week'!J126 -> 0 | I3: ='Performances by Week'!K126 -> 0 | J3: ='Performances by Week'!L126 -> 0 | K3: ='Performances by Week'!M126 -> 6268640 | L3: ='Performances by Week'!O126
B5: Season Attendance By Ticket Type | G5: # Tickets Sold | H5: Projected Tickets Sold | J5: Total Revenue | K5: BUDGET | L5: Projected Revenue vs Budget (% +GYR)
B6: All Subscriptions | G6: ='Performances by Week'!X126 -> 0 | J6: ='Performances by Week'!Y126 -> 0 | K6: ='Performances by Week'!Z126 -> 2169893 | L6: ='Performances by Week'!AA126
B7: All Single Tickets | G7: ='Performances by Week'!P126 -> 0 | H7: ='Performances by Week'!R126 -> 0 | J7: ='Performances by Week'!T126 -> 0 | K7: ='Performances by Week'!U126 -> 3973690 | L7: ='Performances by Week'!W126
B9: Concert Attendance By Performance Type | G9: # Tickets Sold | H9: Projected Tickets Sold | I9: Projected Occupancy (% +GYR) | J9: Total Revenue | K9: BUDGET | L9: Projected Revenue vs Budget (% +GYR)
B10: CLASSICAL TRADITIONAL TOTAL | G10: ='Performances by Week'!I119 -> 0 | H10: ='Performances by Week'!J119 -> 0 | I10: ='Performances by Week'!K119 -> 0 | J10: ='Performances by Week'!L119 -> 0 | K10: ='Performances by Week'!M119 -> 2139000 | L10: ='Performances by Week'!O119
B11: SYMPHONIC PIAZZA TOTAL | G11: ='Performances by Week'!I120 -> 0 | H11: ='Performances by Week'!J120 -> 0 | I11: ='Performances by Week'!K120 -> 0 | J11: ='Performances by Week'!L120 -> 0 | K11: ='Performances by Week'!M120 -> 363000 | L11: ='Performances by Week'!O120
B12: POPS TOTAL | G12: ='Performances by Week'!I121 -> 0 | H12: ='Performances by Week'!J121 -> 0 | I12: ='Performances by Week'!K121 -> 0 | J12: ='Performances by Week'!L121 -> 0 | K12: ='Performances by Week'!M121 -> 1457000 | L12: ='Performances by Week'!O121
B13: FAMILY SERIES TOTAL | G13: ='Performances by Week'!I122 -> 0 | H13: ='Performances by Week'!J122 -> 0 | I13: ='Performances by Week'!K122 -> 0 | J13: ='Performances by Week'!L122 -> 0 | K13: ='Performances by Week'!M122 -> 525950 | L13: ='Performances by Week'!O122
B14: FILM TOTAL | G14: ='Performances by Week'!I123 -> 0 | H14: ='Performances by Week'!J123 -> 0 | I14: ='Performances by Week'!K123 -> 0 | J14: ='Performances by Week'!L123 -> 0 | K14: ='Performances by Week'!M123 -> 1745490 | L14: ='Performances by Week'!O123
B15: ON STAGE CONCERTS TOTAL | G15: ='Performances by Week'!I124 -> 0 | H15: ='Performances by Week'!J124 -> 0 | I15: ='Performances by Week'!K124 -> 0 | J15: ='Performances by Week'!L124 -> 0 | K15: ='Performances by Week'!M124 -> 38200 | L15: ='Performances by Week'!O124
B16: OTHER CONCERT TOTAL | G16: ='Performances by Week'!I125 -> 0 | H16: ='Performances by Week'!J125 -> 0 | I16: ='Performances by Week'!K125 -> 0 | J16: ='Performances by Week'!L125 -> 0 | K16: ='Performances by Week'!M125 -> 0 | L16: ='Performances by Week'!O125

Sheet Sub Graphs
A16: Notes: | B16: FY19 was pre-COVID
B17: FY24 was -35% vs FY19, but also Michael Stern's final season so perhaps a one-time boost
B18: FY25 was -47% vs FY19 and -19% vs FY24
B19: FY26 is -4% vs FY25
B20: For FY27, it is important to start sales no later than Week 5 (coordinate with season anouncement) and understand how to boost renewal rate
J27: Notes: | K27: FY19 was pre-COVID
K28: FY24 was -19% vs FY19, but also Michael Stern's final season so perhaps a one-time boost
K29: FY25 was -29% vs FY19 and -12% vs FY24
K30: FY26 is +7% vs FY25, driven by growth in new subs
K31: For FY27, it is important to start sales no later than Week 5 and understand how to continue new sub growth

Sheet Channels (Draft)
A1: MARKETING CHANNEL PERFORMANCE
B2: Owned Marketing Channels | H2: Paid Channels
A3: To start, let’s pull last 12 months of data. | B3: Phone | C3: Direct Mail | D3: Email | E3: Social | F3: In-hall | G3: SEO | H3: SEM | I3: Media | J3: Phone | K3: Total
B4: (Box Office) | E4: (FB, IG, X, other) | F4: (book, posters) | I4: (TV, radio, OOH) | J4: (Bennett)
A5: # Impressions: | D5: 13.7M
A6: calls made, e/mails delivered, etc.
A7: # Engagement: | D7: 4.7M
A8: calls answered, opens, etc.
A9: Engagement rate | D9: 34%
A10: # Actions (Success): | D10: 89k
A11: conversations, clicks, etc.
A12: Action rate | D12: 0.6%
A13: % of total Actions
A15: Channel cost ($, time)
A16: ROI: $/Action
A17: Attributed revenue ($) | J17: ~$220k
A18: ROI: $/channel cost
A20: SALES CHANNEL PERFORMANCE
A21: To start, let’s pull last 12 months of data. | B21: Phone | C21: Website | D21: KCPA | E21: Total
B22: (Box Office)
A23: # Traffic: | C23: 471,563
A24: calls received, visits
A25: % Traffic by Marketing Channel
A26: #, $ Conversions (Success): | C26: 4,547
A27: Conversion rate | C27: 0.94%
A28: % of total Conversions | D28: 15%?
A29: Total Sales Revenue | B29: ~$6,500k? | C29: $877k
A31: Channel cost ($, time)
A32: ROI: $/Conversion
A33: Attributed revenue ($)
A34: ROI: $/channel cost
A36: EXPERIENCE CHANNEL PERFORMANCE
B37: Total
A38: # total attendance
A39: % Repeat:
A40: % returning from prior season
A41: # Frequency:
A42: avg. attendance/customer
A44: Total Revenue, ROI?
A45: Avg. CSAT, NPS
A46: Avg. CLV/attendee
A47: # high CLV VIPs

Sheet Sales Pacing
B1: New Subs | E1: Renewal Subs
A2: # Weeks On Sale | B2: Classical | C2: Pops | E2: Classical | F2: Pops
A3: 1 | B3: 0.042056075 | C3: 0.036253776 | E3: 0.25267149 | F3: 0.11466913
A4: 2 | B4: 0.060747664 | C4: 0.072507553 | E4: 0.3160979 | F4: 0.20747552
A5: 3 | B5: 0.10981308 | C5: 0.087613293 | E5: 0.39296794 | F5: 0.28482901
A6: 4 | B6: 0.12850467 | C6: 0.12386707 | E6: 0.47604274 | F6: 0.36527648
A7: 5 | B7: 0.1635514 | C7: 0.20845921 | E7: 0.57014822 | F7: 0.45014616
A8: 6 | B8: 0.22663551 | C8: 0.22960725 | E8: 0.72147535 | F8: 0.64007095
A9: 7 | B9: 0.30140187 | C9: 0.27794562 | E9: 0.90486039 | F9: 0.79481765
A10: 8 | B10: 0.35046729 | C10: 0.31117825 | E10: 0.93864185 | F10: 0.88854264
A11: 9 | B11: 0.39485981 | C11: 0.38670695 | E11: 0.95001724 | F11: 0.94228277
A12: 10 | B12: 0.43691589 | C12: 0.42900302 | E12: 0.96242675 | F12: 0.95465872
A13: 11 | B13: 0.46962617 | C13: 0.48036254 | E13: 0.96552913 | F13: 0.96530297
A14: 12 | B14: 0.50700935 | C14: 0.57401813 | E14: 0.96863151 | F14: 0.97390663
A15: 13+ | B15: 1 | C15: 1 | E15: 1 | F15: 1
B21: Single Tickets
A22: # Weeks Until Performance | B22: Classical | C22: Pops | D22: Specials | E22: Other
A23: 0 | B23: 1 | C23: 1 | D23: 1 | E23: 1
A24: 1 | B24: 0.59 | C24: 0.59 | D24: 0.59 | E24: 0.59
A25: 2 | B25: 0.46 | C25: 0.46 | D25: 0.46 | E25: 0.46
A26: 3 | B26: 0.39 | C26: 0.39 | D26: 0.39 | E26: 0.39
A27: 4 | B27: 0.33 | C27: 0.33 | D27: 0.33 | E27: 0.33
A28: 5 | B28: 0.3 | C28: 0.3 | D28: 0.3 | E28: 0.3
A29: 6 | B29: 0.27 | C29: 0.27 | D29: 0.27 | E29: 0.27
A30: 7
A31: 8
A32: 9
A33: 10
A34: 11
A35: 12
A36: 13+
A38: Future Improvements:
A39: Extend data for single ticket sales beyond 6 weeks
A40: Differentiate single ticket sales by performance type
A41: Improve pacing data (always)

Sheet Email Reporting
A1: EMAILS SENT | B1: DELIVERIES | C1: OPENS | D1: CLICK RATE
A2: 9/21 Journey KBYG SUN | B2: 348 | C2: 258 (74.1%) | D2: 103 (29.6%) | J2: AVERAGE OPEN RATE: | K2: 0.37
A3: 9/20 Journey KBYG SAT | B3: 398 | C3: 287 (72.1%) | D3: 104 (26.1%) | J3: AVERAGE CLICK RATE: | K3: 0.02
A4: 9/19 Journey KBYG FRI | B4: 417 | C4: 289 (69.3%) | D4: 101 (24.2%)
A5: 9/18 90s Standalone Email | B5: 95170 | C5: 33,599 (35.3%) | D5: 341 (0.4%)
A6: 9/16 Weekly Concert Promo | B6: 93715 | C6: 34,837 (37.2%) | D6: 729 (0.8%)
A7: 9/15 CS2 Standalone Email | B7: 93796 | C7: 34,769 (37.1%) | D7: 342 (0.4%)
A8: 9/10 Journey Giveaway | B8: 95517 | C8: 34,249 (35.9%) | D8: 751 (1%)
A9: 9/9 Weekly Concert Promo | B9: 93965 | C9: 35,513 (37.8%) | D9: 780 (1%)
A10: 9/5 CS1 BOGO Pops Buyers | B10: 4488 | C10: 2,377 (53%) | D10: 100 (2.2%) - 33 respond (98 tickets)
A11: 9/5 CS1 Morgan Freeman Buyers | B11: 1008 | C11: 588 (58.3%) | D11: 33 (3.3%) - 33 respond (98 tickets)
A12: 9/4 CS1 Matthias Video | B12: 95604 | C12: 35,461 (37.1%) | D12: 1,460 (1.5%)
A13: 9/4 Journey BOGO Promo | B13: 2721 | C13: 1,164 (42.8%) | D13: 54 (2%) - 15 respond (41 tickets)
A14: 9/3 Morgan Freeman KBYG | B14: 376 | C14: 306 (81.4%) | D14: 129 (34.3%)
A15: 9/2 Morgan Freeman KBYG | B15: 426 | C15: 354 (83.1%) | D15: 152 (35.7%)
... A18: 8/20 Bi-weekly Merchandise Email | B18: 95473 | C18: 35,125 (37%) | D18: 754 (1%)
A19: 8/12 Music of Journey Promo | B19: 94241 | C19: 35,743 (37.9%) | D19: 577 0.6% | E19: https://conta.cc/4mdHLVC
A20: 8/6 Bi-weekly Merchandise Email | B20: 94322 | C20: 36,401 (38.6%) | D20: 937 (1%) | E20: https://conta.cc/3Hoy3k2
A21: 7/21 La Nuit Sombre Matthias Video | B21: 95893 | C21: 35,531 (37.1%) | D21: 491 (0.5%)
A22: 7/23 Morgan Freeman Promo | B22: 96012 | C22: 35,064 (36.5%) | D22: 769 (0.8%)
A23: 7/15 Single Ticket On Sale Announcement | B23: 95831 | C23: 35,285 (37.2%) | D23: 1,708 (2%)
A24: 7/8 Leslie Odom Jr. Promo | B24: 94927 | C24: 35, 660 (37.6%) | D24: 550 (0.6%)
A25: Tuesday 7/1 Holiday Presentations On Sale | B25: 95059 | C25: 35039 (36.9%) | D25: 822 (0.9%) | E25: Header: 64, Elf in Concert: 473, Handel's Messiah: 390, LOJ: 110, Christmas Festival: 144, Wonderful Life: 129
A26: Tuesday 6/25 Special Presentations On Sale | B26: 95219 | C26: 35,617 (37%) | D26: 1,469 (2%) | E26: Full lineup: 248, Morgan Freeman: 438, Chicken Fried: 456, Top Gun: 559, Lodger: 100, Indiana Jones: 204, Chris Thile: 134, Harry Potter: 139, Final Symphony: 74, Ben Rector: 108, On Stage George: 45, On Stage Leila: 53, On Stage Gil: 37, On Stage 38
A27: Tuesday 6/17 Mark Your Calendar | B27: 104371 | C27: 37,343 (39%) | D27: 1,999 (2%)
A28: Monday 6/9 Mobile Music Box June Concert | B28: 95,460 | C28: 36,052 (38%) | D28: 594 (1%)
A29: Wednesday 6/4 CS14 Student Rush Promo | B29: 174 | C29: 77 (44%) | D29: 0
A30: Wednesday 6/4 CS14 Student Rush Promo | B30: 174 | C30: 77 (44%) | D30: 0
A31: Wednesday 6/4 CS14 Student Pass Promo | B31: 80 | C31: 38 (47%) | D31: 1
A32: Wednesday 6/4 CS14 BOGO Promo | B32: 4954 | C32: 2,165 (44%) | D32: 65 (1%)
A33: Wednesday 6/4 Four Larks Subscriber Early Access | B33: 2185 | C33: 1,452 (66.5%) | D33: 135 (6.2%)
A34: Friday 6/6 Four Lark Public On-Sale | B34: 96846 | C34: 35,136 (36%) | D34: 616 (0.6%)

Sheet Social Reporting
A1: DATE | B1: Social Post | C1: Views | D1: Engagement
A2: 45919 | B2: CS2 Graphic FB | C2: 1.6K reach | D2: 13 interactions
A3: 45919 | B3: CS2 Graphic IG | C3: 682 reach | D3: 13 interactions
A4: 45918 | B4: Orchestra Games Reel FB | C4: 1.2K reach | D4: 16 interactions
A5: 45918 | B5: Orchestra Games Reel IG | C5: 707 reach | D5: 31 interactions
A6: 45917 | B6: CS1 Graphic FB | C6: 1.7K reach | D6: 16 interactions
A7: 45917 | B7: CS1 Graphic IG | C7: 611 reach | D7: 22 interactions
A8: 45916 | B8: Journey musician feature IG | C8: 779 reach | D8: 17 interactions
A9: 45916 | B9: Journey musician feature FB | C9: 763 reach | D9: 12 interactions
A10: 45915 | B10: 90s Graphic FB | C10: 1.5K reach | D10: 7 interactions
A11: 45915 | B11: 90s Graphic IG | C11: 1.1K reach | D11: 18 interactions
A12: 45913 | B12: CS1 Mike G reel FB | C12: 2.7K reach | D12: 60 interactions
A13: 45913 | B13: CS1 Mike G reel IG | C13: 1.2K reach | D13: 51 interactions
... A25: 45902 | B25: KC Star Matthias article reshare FB | C25: 1.7K reach | D25: 42 interactions
A27: DATE | B27: Meta Ads | C27: Views | D27: Engagement
A28: 9/12-9/25 | B28: Top Gun Ad | C28: 83,913 reach, 154,220 impressions | D28: 3,352 link clicks
A29: 9/18-10/2 | B29: 90s Mixtape Ad | C29: 31,593 reach, 53,149 impressions | D29: 718 link clicks
A30: 9/4 - 9/18 | B30: CS1 Video Ad | C30: 33,438 reach, 63,806 impressions | D30: 2,410 link clicks
A40: 45898 | B40: Chicken Fried Rock FB Reel | C40: 1.4K reach | D40: 13 interactions, 2 shares
A41: 45898 | B41: Chicken Fried Rock IG Reel | C41: 1.1K reach | D41: 42 interactions, 3 shares
A42: 45897 | B42: ProAm post FB | C42: 3.7K reach | D42: 24 interactions, 13 shares
A43: 45897 | B43: ProAm post IG | C43: 1.3K reach | D43: 35 interactions, 6 shares
A44: 45896 | B44: MMB FB Reel | C44: 1.3K reach | D44: 16 interactions
A45: 45896 | B45: MMB IG Reel | C45: 1.1K reach | D45: 32 interactions
A46: 45895 | B46: New musician welcome FB | C46: 14.9K reach | D46: 223 interactions, 26 comments, 10 shares
A47: 45895 | B47: New musician welcome IG | C47: 9.1K reach | D47: 515 interactions, 7 comments, 64 shares
A48: 45891 | B48: Chicken Fried IG | C48: 1625 | D48: 11 interactions
A49: 45891 | B49: Chicken Fried FB | C49: 2570 | D49: 15 interactions, 6 link clicks
A50: 45890 | B50: Journey Reel IG | C50: 1005 | D50: 16 interactions
A51: 45890 | B51: Journey Reel FB | C51: 813 | D51: 12 interactions
A52: 45883 | B52: KC Blues Society Video IG | C52: 966 | D52: 32 interactions
A53: 45883 | B53: KC Blues Society Video FB | C53: 1895 | D53: 19 interactions, 61 link clicks
A54: 45881 | B54: CS1 Nora Video IG | C54: 3290 | D54: 42 interactions
A55: 45881 | B55: CS1 Nora Video FB | C55: 1785 | D55: 42 interactions
A56: 45876 | B56: Orchestra Games IG | C56: 2394 | D56: 54 interactions
A57: 45876 | B57: Orchestra Games FB | C57: 1879 | D57: 15 interactions, 2 link clicks
A58: 45876 | B58: Morgan Freeman interview reshare FB | C58: 2731 | D58: 52 interactions, 53 link clicks
A59: 45875 | B59: Nora Intro IG | C59: 3331 | D59: 65 interactions
... A84: 45856 | B84: Music is for Everyone YT | C84: 32 | D84: 1 interaction
B86: Meta Ads
A87: 45832 | B87: Specials/Films ad | C87: 1k impressions | D87: 18 clicks
A88: 45838 | B88: Morgan Freeman video | C88: 22k impressions | D88: 1234 link clicks
A89: 45841 | B89: Holiday concerts ad | C89: 68k impressions | D89: 1011 link clicks

Sheet Website Reporting
A1: Timeframe: August 11-18
A2: ECOMMERCE PURCHASES: 877 | B2: WEBSITE REVENUE: $74,429 | C2: # OF ITEMS
A3: Morgan Freeman | B3: 18052 | C3: 164
A4: Music of Journey | B4: 8322 | C4: 66
A5: Top Gun | B5: 7065 | C5: 86
A6: Leslie Odom Jr. | B6: 4084.5 | C6: 54
A7: Indiana Jones | B7: 3441 | C7: 38
A8: Elf in Concert | B8: 2892 | C8: 44
A9: Harry Potter | B9: 2521 | C9: 29
A10: It's a wonderful life | B10: 2454 | C10: 52
A12: Timeframe: July 20-July 28
A13: ECOMMERCE PURCHASES: 973 | B13: WEBSITE REVENUE: $67,220 | C13: # OF ITEMS
A14: Leslie Odom Jr. | B14: 17681 | C14: 161
A15: Morgan Freeman | B15: 7995 | C15: 64
A16: Top Gun | B16: 5293 | C16: 64
A17: 2025/26 COY Package | B17: 4084 | C17: 54
A18: It's a wonderful life | B18: 2684 | C18: 31
A19: Elf in Concert | B19: 2343 | C19: 26
A20: Christmas Festival | B20: 2341 | C20: 38
A21: La nuit sombre | B21: 2308 | C21: 49
A22: Harry Potter 2 | B22: 2030 | C22: 26
A23: Indiana Jones | B23: 2004 | C23: 26
A27: Timeframe: July 20-July 28
A28: ECOMMERCE PURCHASES: 1,718 | B28: WEBSITE REVENUE: $115,644 | C28: # OF ITEMS
A29: Morgan Freeman | B29: 27675 | C29: 215
A30: Top Gun | B30: 9650 | C30: 116
A31: It's a wonderful life | B31: 8677 | C31: 104
A32: Leslie Odom Jr. | B32: 9110 | C32: 84
A33: Elf in Concert | B33: 5110 | C33: 80
A34: 2025/26 COY Package | B34: 5435 | C34: 73
A35: Harry Potter 2 | B35: 5145 | C35: 61
A36: 2025/26 Sunday Masterworks | B36: 4200 | C36: 56
A37: Handel's Messiah | B37: 2970 | C37: 55
A43: Timeframe: July 14-July 20
A44: ECOMMERCE PURCHASES: 3,027 | B44: WEBSITE REVENUE: $188,688 | C44: # OF ITEMS
A45: Top Gun | B45: 19205 | C45: 234
A46: Morgan Freeman | B46: 16175 | C46: 130
A47: Leslie Odom Jr. | B47: 14107 | C47: 139
A48: Indiana Jones | B48: 12729 | C48: 186
A49: Billy Joel + Elton John | B49: 11391 | C49: 149
A50: Elf | B50: 11075 | C50: 168
A51: Harry Potter | B51: 10715 | C51: 155
A52: It's a wonderful life | B52: 9126 | C52: 129
A53: Music of Journey | B53: 6150 | C53: 91
A54: Ben Rector | B54: 6140 | C54: 60
A56: Traffic Acquistion
A57: SOURCE | B57: SESSIONS
A58: Organic Search
A59: Direct
A60: Paid Social
A61: Referral
A62: Organic Social

Sheet Grassroots Flyer Locations
A1: MF Location | B1: MF Staff Member | C1: Date Posted | E1: CF Location | F1: CF Staff Member | G1: Date Posted | I1: Fam Location | J1: Fam Staff Member | K1: Date Posted
A2: Mildreds (NO CORKBOARD)
A3: Pizza Shuttle | B3: Stephen, Sarah and Adeca | C3: 45870
A4: The Bauer Gallery | B4: Stephen, Sarah and Adeca | C4: 45870
A5: Bizz and Weezy's | B5: Stephen, Sarah and Adeca | C5: 45870
A6: The Sewing Labs | B6: Sarah | C6: 45875
A7: Filling Station - Midtown | B7: Hannah | C7: 45875
A8: Good Karma Coffee Shop | B8: Hannah | C8: 45875

Sheet Board
M1: Revised 9.17.25
A3: TICKET SALES REPORT as of 9/17/2025 | E3: SINGLE TICKETS | I3: SUBSCRIPTION TICKETS | L3: TOTAL SALES (Singles + Subs) | O3: Hall Data
A4: SERIES | D4: DATE(S) | E4: BUDGET | F4: ACTUAL | G4: VS. BUDGET | H4: # SOLD | I4: BUDGET | J4: ACTUAL | K4: # SOLD | L4: BUDGET | M4: ACTUAL | N4: # SOLD | O4: CAP | P4: CAP SOLD | Q4: ATP
A5: CLASSICAL TRADITIONAL
A6: CS1 | B6: Appalachian Spring | D6: Oct 10-12 | E6: =SUM('Performances by Week'!U15:U17) -> 49998 | F6: =SUM('Performances by Week'!T15:T17) -> 53339 | G6: =F6-E6 -> 3341 | H6: =SUM('Performances by Week'!P15:P17) -> 895 | I6: =SUM('Performances by Week'!Z15:Z17) -> 100000 | J6: =SUM('Performances by Week'!Y15:Y17) -> 111230.7 | K6: =SUM('Performances by Week'!X15:X17) -> 1678 | L6: =SUM(E6,I6) -> 149998 | M6: =SUM(F6,J6) -> 164569.7 | N6: =SUM(H6,K6) -> 2573 | O6: =SUM('Performances by Week'!AB15:AB17) -> 4299 | P6: =N6/O6 -> 0.59851128 | Q6: =M6/N6 -> 63.960241
A7: CS2 | B7: Rachmaninoff Cele Pt 1 (SP) | D7: Oct 31-Nov 2 | E7: =SUM('Performances by Week'!U26:U28) -> 85000 | F7: =SUM('Performances by Week'!T26:T28) -> 48283 | G7: =F7-E7 -> -36717 | H7: =SUM('Performances by Week'!P26:P28) -> 834 | I7: =SUM('Performances by Week'!Z26:Z28) -> 140000 | J7: =SUM('Performances by Week'!Y26:Y28) -> 96474.1 | K7: =SUM('Performances by Week'!X26:X28) -> 1461 | L7: =SUM(E7,I7) -> 225000 | M7: =SUM(F7,J7) -> 144757.1 | N7: =SUM(H7,K7) -> 2295 | O7: =SUM('Performances by Week'!AB26:AB28) -> 4299 | P7: =N7/O7 -> 0.53384508 | Q7: =M7/N7 -> 63.074989
A8: CS3 | B8: Matthias and Mahler (SP) | D8: Nov 21-23 | E8: =SUM('Performances by Week'!U31:U33) -> 38000 | F8: =SUM('Performances by Week'!T31:T33) -> 18184 | G8: =F8-E8 -> -19816 | H8: =SUM('Performances by Week'!P31:P33) -> 301 | I8: =SUM('Performances by Week'!Z31:Z33) -> 135000 | J8: =SUM('Performances by Week'!Y31:Y33) -> 105210.1 | K8: =SUM('Performances by Week'!X31:X33) -> 1572 | L8: =SUM(E8,I8) -> 173000 | M8: =SUM(F8,J8) -> 123394.1 | N8: =SUM(H8,K8) -> 1873 | O8: =SUM('Performances by Week'!AB31:AB33) -> 4770 | P8: =N8/O8 -> 0.39266247 | Q8: =M8/N8 -> 65.880459
A9: CS4 | B9: Brahms' Fourth Symphony | D9: Jan 9-11 | E9: =SUM('Performances by Week'!U52:U54) -> 64998 | F9: =SUM('Performances by Week'!T52:T54) -> 8795 | G9: =F9-E9 -> -56203 | H9: =SUM('Performances by Week'!P52:P54) -> 159 | I9: =SUM('Performances by Week'!Z52:Z54) -> 100000 | J9: =SUM('Performances by Week'!Y52:Y54) -> 111577.5 | K9: =SUM('Performances by Week'!X52:X54) -> 1701 | L9: =SUM(E9,I9) -> 164998 | M9: =SUM(F9,J9) -> 120372.5 | N9: =SUM(H9,K9) -> 1860 | O9: =SUM('Performances by Week'!AB52:AB54) -> 4770 | P9: =N9/O9 -> 0.38993711 | Q9: =M9/N9 -> 64.716398
A10: CS5 | B10: Pines of Rome & Bruch (SP) | D10: Jan 16-18 | E10: =SUM('Performances by Week'!U55:U57) -> 70000 | F10: =SUM('Performances by Week'!T55:T57) -> 16249 | G10: =F10-E10 -> -53751 | H10: =SUM('Performances by Week'!P55:P57) -> 270 | I10: =SUM('Performances by Week'!Z55:Z57) -> 140000 | J10: =SUM('Performances by Week'!Y55:Y57) -> 104865.1 | K10: =SUM('Performances by Week'!X55:X57) -> 1576 | L10: =SUM(E10,I10) -> 210000 | M10: =SUM(F10,J10) -> 121114.1 | N10: =SUM(H10,K10) -> 1846 | O10: =SUM('Performances by Week'!AB55:AB57) -> 4770 | P10: =N10/O10 -> 0.3870021 | Q10: =M10/N10 -> 65.608938
A11: CS6 | B11: Beethoven+ (SP) | D11: Jan 30-Feb 1 | E11: =SUM('Performances by Week'!U62:U64) -> 64000 | F11: =SUM('Performances by Week'!T62:T64) -> 14060 | G11: =F11-E11 -> -49940 | H11: =SUM('Performances by Week'!P62:P64) -> 237 | I11: =SUM('Performances by Week'!Z62:Z64) -> 140000 | J11: =SUM('Performances by Week'!Y62:Y64) -> 103801.1 | K11: =SUM('Performances by Week'!X62:X64) -> 1571 | L11: =SUM(E11,I11) -> 204000 | M11: =SUM(F11,J11) -> 117861.1 | N11: =SUM(H11,K11) -> 1808 | O11: =SUM('Performances by Week'!AB62:AB64) -> 4770 | P11: =N11/O11 -> 0.37903564 | Q11: =M11/N11 -> 65.188662
A12: CS7 | B12: Prokofiev's Fifth Symphony | D12: Feb 6-8 | E12: =SUM('Performances by Week'!U66:U68) -> 39999 | F12: =SUM('Performances by Week'!T66:T68) -> 6940 | G12: =F12-E12 -> -33059 | H12: =SUM('Performances by Week'!P66:P68) -> 155 | I12: =SUM('Performances by Week'!Z66:Z68) -> 100000 | J12: =SUM('Performances by Week'!Y66:Y68) -> 109967.3 | K12: =SUM('Performances by Week'!X66:X68) -> 1683 | L12: =SUM(E12,I12) -> 139999 | M12: =SUM(F12,J12) -> 116907.3 | N12: =SUM(H12,K12) -> 1838 | O12: =SUM('Performances by Week'!AB66:AB68) -> 4770 | P12: =N12/O12 -> 0.38532495 | Q12: =M12/N12 -> 63.605713
A13: CS8 | B13: Saint-Saëns & Strauss | D13: Mar 13-15 | E13: =SUM('Performances by Week'!U79:U81) -> 54999 | F13: =SUM('Performances by Week'!T79:T81) -> 10846 | G13: =F13-E13 -> -44153 | H13: =SUM('Performances by Week'!P79:P81) -> 190 | I13: =SUM('Performances by Week'!Z79:Z81) -> 110000 | J13: =SUM('Performances by Week'!Y79:Y81) -> 111505.3 | K13: =SUM('Performances by Week'!X79:X81) -> 1708 | L13: =SUM(E13,I13) -> 164999 | M13: =SUM(F13,J13) -> 122351.3 | N13: =SUM(H13,K13) -> 1898 | O13: =SUM('Performances by Week'!AB79:AB81) -> 4770 | P13: =N13/O13 -> 0.39790356 | Q13: =M13/N13 -> 64.463277
A14: CS9 | B14: Midsummer Night's Dream (SP) | D14: Apr 10-12 | E14: =SUM('Performances by Week'!U89:U91) -> 70000 | F14: =SUM('Performances by Week'!T89:T91) -> 10472 | G14: =F14-E14 -> -59528 | H14: =SUM('Performances by Week'!P89:P91) -> 219 | I14: =SUM('Performances by Week'!Z89:Z91) -> 130000 | J14: =SUM('Performances by Week'!Y89:Y91) -> 98992.1 | K14: =SUM('Performances by Week'!X89:X91) -> 1505 | L14: =SUM(E14,I14) -> 200000 | M14: =SUM(F14,J14) -> 109464.1 | N14: =SUM(H14,K14) -> 1724 | O14: =SUM('Performances by Week'!AB89:AB91) -> 4299 | P14: =N14/O14 -> 0.40102349 | Q14: =M14/N14 -> 63.494258
A15: CS10 | B15: Farrenc/Dvorak/Schuman | D15: Apr 17-19 | E15: =SUM('Performances by Week'!U92:U94) -> 39999 | F15: =SUM('Performances by Week'!T92:T94) -> 4229 | G15: =F15-E15 -> -35770 | H15: =SUM('Performances by Week'!P92:P94) -> 103 | I15: =SUM('Performances by Week'!Z92:Z94) -> 100000 | J15: =SUM('Performances by Week'!Y92:Y94) -> 119099.1 | K15: =SUM('Performances by Week'!X92:X94) -> 1789 | L15: =SUM(E15,I15) -> 139999 | M15: =SUM(F15,J15) -> 123328.1 | N15: =SUM(H15,K15) -> 1892 | O15: =SUM('Performances by Week'!AB92:AB94) -> 4770 | P15: =N15/O15 -> 0.3966457 | Q15: =M15/N15 -> 65.183985
A16: CS11 | B16: Grieg's Piano Concerto (SP) | D16: May 8-10 | E16: =SUM('Performances by Week'!U97:U99) -> 55000 | F16: =SUM('Performances by Week'!T97:T99) -> 11439 | G16: =F16-E16 -> -43561 | H16: =SUM('Performances by Week'!P97:P99) -> 208 | I16: =SUM('Performances by Week'!Z97:Z99) -> 120000 | J16: =SUM('Performances by Week'!Y97:Y99) -> 105674.1 | K16: =SUM('Performances by Week'!X97:X99) -> 1585 | L16: =SUM(E16,I16) -> 175000 | M16: =SUM(F16,J16) -> 117113.1 | N16: =SUM(H16,K16) -> 1793 | O16: =SUM('Performances by Week'!AB97:AB99) -> 4770 | P16: =N16/O16 -> 0.37589099 | Q16: =M16/N16 -> 65.316843
A17: CS12 | B17: Gil Shaham Plays Brahm's 4th | D17: May 29-31 | E17: =SUM('Performances by Week'!U107:U109) -> 60000 | F17: =SUM('Performances by Week'!T107:T109) -> 6544 | G17: =F17-E17 -> -53456 | H17: =SUM('Performances by Week'!P107:P109) -> 162 | I17: =SUM('Performances by Week'!Z107:Z109) -> 95000 | J17: =SUM('Performances by Week'!Y107:Y109) -> 112084.5 | K17: =SUM('Performances by Week'!X107:X109) -> 1713 | L17: =SUM(E17,I17) -> 155000 | M17: =SUM(F17,J17) -> 118628.5 | N17: =SUM(H17,K17) -> 1875 | O17: =SUM('Performances by Week'!AB107:AB109) -> 4770 | P17: =N17/O17 -> 0.39308176 | Q17: =M17/N17 -> 63.268533
A18: CS13 | B18: Rachmaninoff Cele Pt 2 | D18: Jun 5-7 | E18: =SUM('Performances by Week'!U111:U113) -> 90000 | F18: =SUM('Performances by Week'!T111:T113) -> 13110 | G18: =F18-E18 -> -76890 | H18: =SUM('Performances by Week'!P111:P113) -> 225 | I18: =SUM('Performances by Week'!Z111:Z113) -> 110000 | J18: =SUM('Performances by Week'!Y111:Y113) -> 119909.5 | K18: =SUM('Performances by Week'!X111:X113) -> 1809 | L18: =SUM(E18,I18) -> 200000 | M18: =SUM(F18,J18) -> 133019.5 | N18: =SUM(H18,K18) -> 2034 | O18: =SUM('Performances by Week'!AB111:AB113) -> 4770 | P18: =N18/O18 -> 0.42641509 | Q18: =M18/N18 -> 65.397984
A19: CS14 | B19: Rhapsody in Blue (SP) | D19: Jun 19-21 | E19: =SUM('Performances by Week'!U115:U117) -> 85000 | F19: =SUM('Performances by Week'!T115:T117) -> 30540 | G19: =F19-E19 -> -54460 | H19: =SUM('Performances by Week'!P115:P117) -> 518 | I19: =SUM('Performances by Week'!Z115:Z117) -> 115000 | J19: =SUM('Performances by Week'!Y115:Y117) -> 101226 | K19: =SUM('Performances by Week'!X115:X117) -> 1538 | L19: =SUM(E19,I19) -> 200000 | M19: =SUM(F19,J19) -> 131766 | N19: =SUM(H19,K19) -> 2056 | O19: =SUM('Performances by Week'!AB115:AB117) -> 4770 | P19: =N19/O19 -> 0.43102725 | Q19: =M19/N19 -> 64.088521
A20: CLASSICAL TRADITIONAL TOTAL | E20: =SUM(E6:E19) -> 866993 | F20: =SUM(F6:F19) -> 253030 | G20: =F20-E20 -> -613963 | H20: =SUM(H6:H19) -> 4476 | I20: =SUM(I6:I19) -> 1635000 | J20: =SUM(J6:J19) -> 1511616.5 | K20: =SUM(K6:K19) -> 22889 | L20: =SUM(L6:L19) -> 2501993 | M20: =SUM(F20,J20) -> 1764646.5 | N20: =SUM(N6:N19) -> 27365 | O20: =SUM(O6:O19) -> 65367 | P20: =N20/O20 -> 0.41863631 | Q20: =M20/N20 -> 64.485529
A22: SYMPHONIC PIAZZA
A23: Piazza CS2 | B23: =B7 -> Rachmaninoff Cele Pt 1 (SP) | D23: Oct 31 | E23: ='Performances by Week'!$U$26 -> 22000 | F23: ='Performances by Week'!$T$26 -> 7526 | G23: =F23-E23 -> -14474 | H23: ='Performances by Week'!$P$26 -> 137 | I23: ='Performances by Week'!$Z$26 -> 30000 | J23: ='Performances by Week'!$Y$26 -> 23801 | K23: ='Performances by Week'!$X$26 -> 342 | L23: =SUM(E23,I23) -> 52000 | M23: =SUM(F23,J23) -> 31327 | N23: =SUM(H23,K23) -> 479 | O23: ='Performances by Week'!$AB$115 -> 1590 | P23: =N23/O23 -> 0.30125786 | Q23: =M23/N23 -> 65.400835
A24: Piazza CS3 | B24: =B8 -> Matthias and Mahler (SP) | D24: Nov 21 | E24: ='Performances by Week'!$U$31 -> 15000 | F24: ='Performances by Week'!$T$31 -> 4025 | G24: =F24-E24 -> -10975 | H24: ='Performances by Week'!$P$31 -> 79 | I24: ='Performances by Week'!$Z$31 -> 25000 | J24: ='Performances by Week'!$Y$31 -> 25348 | K24: ='Performances by Week'!$X$31 -> 367 | L24: =SUM(E24,I24) -> 40000 | M24: =SUM(F24,J24) -> 29373 | N24: =SUM(H24,K24) -> 446 | O24: ='Performances by Week'!$AB$31 -> 1590 | P24: =N24/O24 -> 0.28050314 | Q24: =M24/N24 -> 65.858744
A25: Piazza CS5 | B25: =B10 -> Pines of Rome & Bruch (SP) | D25: Jan 16 | E25: ='Performances by Week'!$U$55 -> 30000 | F25: ='Performances by Week'!$T$55 -> 2960 | G25: =F25-E25 -> -27040 | H25: ='Performances by Week'!$P$55 -> 51 | I25: ='Performances by Week'!$Z$55 -> 30000 | J25: ='Performances by Week'!$Y$55 -> 25342 | K25: ='Performances by Week'!$X$55 -> 368 | L25: =SUM(E25,I25) -> 60000 | M25: =SUM(F25,J25) -> 28302 | N25: =SUM(H25,K25) -> 419 | O25: ='Performances by Week'!$AB$55 -> 1590 | P25: =N25/O25 -> 0.26352201 | Q25: =M25/N25 -> 67.546539
A26: Piazza CS6 | B26: =B11 -> Beethoven+ (SP) | D26: Jan 30 | E26: ='Performances by Week'!$U$62 -> 24000 | F26: ='Performances by Week'!$T$62 -> 3847 | G26: =F26-E26 -> -20153 | H26: ='Performances by Week'!$P$62 -> 71 | I26: ='Performances by Week'!$Z$62 -> 30000 | J26: ='Performances by Week'!$Y$62 -> 24869 | K26: ='Performances by Week'!$X$62 -> 364 | L26: =SUM(E26,I26) -> 54000 | M26: =SUM(F26,J26) -> 28716 | N26: =SUM(H26,K26) -> 435 | O26: ='Performances by Week'!$AB$62 -> 1590 | P26: =N26/O26 -> 0.27358491 | Q26: =M26/N26 -> 66.013793
A27: Piazza CS9 | B27: =B14 -> Midsummer Night's Dream (SP) | D27: Apr 10 | E27: ='Performances by Week'!$U$89 -> 22000 | F27: ='Performances by Week'!$T$89 -> 2411 | G27: =F27-E27 -> -19589 | H27: ='Performances by Week'!$P$89 -> 52 | I27: ='Performances by Week'!$Z$89 -> 30000 | J27: ='Performances by Week'!$Y$89 -> 25714 | K27: ='Performances by Week'!$X$89 -> 368 | L27: =SUM(E27,I27) -> 52000 | M27: =SUM(F27,J27) -> 28125 | N27: =SUM(H27,K27) -> 420 | O27: ='Performances by Week'!$AB$89 -> 1433 | P27: =N27/O27 -> 0.29309142 | Q27: =M27/N27 -> 66.964286
A28: Piazza CS11 | B28: =B16 -> Grieg's Piano Concerto (SP) | D28: May 8 | E28: ='Performances by Week'!$U$97 -> 20000 | F28: ='Performances by Week'!$T$97 -> 2349 | G28: =F28-E28 -> -17651 | H28: ='Performances by Week'!$P$97 -> 50 | I28: ='Performances by Week'!$Z$97 -> 25000 | J28: ='Performances by Week'!$Y$97 -> 25763 | K28: ='Performances by Week'!$X$97 -> 374 | L28: =SUM(E28,I28) -> 45000 | M28: =SUM(F28,J28) -> 28112 | N28: =SUM(H28,K28) -> 424 | O28: ='Performances by Week'!$AB$97 -> 1590 | P28: =N28/O28 -> 0.26666667 | Q28: =M28/N28 -> 66.301887
A29: Piazza CS14 | B29: =B19 -> Rhapsody in Blue (SP) | D29: Jun 19 | E29: ='Performances by Week'!$U$115 -> 30000 | F29: ='Performances by Week'!$T$115 -> 6390 | G29: =F29-E29 -> -23610 | H29: ='Performances by Week'!$P$115 -> 111 | I29: ='Performances by Week'!$Z$115 -> 30000 | J29: ='Performances by Week'!$Y$115 -> 26279 | K29: ='Performances by Week'!$X$115 -> 380 | L29: =SUM(E29,I29) -> 60000 | M29: =SUM(F29,J29) -> 32669 | N29: =SUM(H29,K29) -> 491 | O29: ='Performances by Week'!$AB$115 -> 1590 | P29: =N29/O29 -> 0.30880503 | Q29: =M29/N29 -> 66.535642
A30: SYMPHONIC PIAZZA TOTAL | E30: =SUM(E23:E29) -> 163000 | F30: =SUM(F23:F29) -> 29508 | G30: =SUM(G23:G29) -> -133492 | H30: =SUM(H23:H29) -> 551 | I30: =SUM(I23:I29) -> 200000 | J30: =SUM(J23:J29) -> 177116 | K30: =SUM(K23:K29) -> 2563 | L30: =SUM(L23:L29) -> 363000 | ... O30: =SUM(O23:O29) -> 10973 | P30: =N30/O30 -> 0.28378748 | Q30: =M30/N30 -> 66.353243
A32: POPS
A33: PS1 | B33: Music of Journey | D33: Sep 19-21 | E33: =SUM('Performances by Week'!$U$10:$U$12) -> 177999 | F33: =SUM('Performances by Week'!$T$10:$T$12) -> 106172 | G33: =F33-E33 -> -71827 | H33: =SUM('Performances by Week'!$P$10:$P$12) -> 1733 | I33: =SUM('Performances by Week'!$Z$10:$Z$12) -> 124000 | J33: =SUM('Performances by Week'!$Y$10:$Y$12) -> 108064.7 | K33: =SUM('Performances by Week'!$X$10:$X$12) -> 1473 | L33: =SUM(E33,I33) -> 301999 | M33: =SUM(F33,J33) -> 214236.7 | N33: =SUM(H33,K33) -> 3206 | O33: =SUM('Performances by Week'!$AB$10:$AB$12) -> 4770 | P33: =N33/O33 -> 0.6721174 | Q33: =M33/N33 -> 66.823674
A34: PS2 | B34: 90s Mixtape | D34: Oct 24-26 | E34: =SUM('Performances by Week'!$U$22:$U$24) -> 159999 | F34: =SUM('Performances by Week'!$T$22:$T$24) -> 24422 | G34: =F34-E34 -> -135577 | H34: =SUM('Performances by Week'!$P$22:$P$24) -> 398 | I34: =SUM('Performances by Week'!$Z$22:$Z$24) -> 117000 | J34: =SUM('Performances by Week'!$Y$22:$Y$24) -> 122339.2 | K34: =SUM('Performances by Week'!$X$22:$X$24) -> 1719 | L34: =SUM(E34,I34) -> 276999 | M34: =SUM(F34,J34) -> 146761.2 | N34: =SUM(H34,K34) -> 2117 | O34: =SUM('Performances by Week'!$AB$22:$AB$24) -> 4770 | P34: =N34/O34 -> 0.44381551 | Q34: =M34/N34 -> 69.325083
A35: PS3 | B35: She's Got Soul | D35: Feb 13-15 | E35: =SUM('Performances by Week'!$U$70:$U$72) -> 159999 | F35: =SUM('Performances by Week'!$T$70:$T$72) -> 10200 | G35: =F35-E35 -> -149799 | H35: =SUM('Performances by Week'!$P$70:$P$72) -> 175 | I35: =SUM('Performances by Week'!$Z$70:$Z$72) -> 124000 | J35: =SUM('Performances by Week'!$Y$70:$Y$72) -> 126157.2 | K35: =SUM('Performances by Week'!$X$70:$X$72) -> 1771 | L35: =SUM(E35,I35) -> 283999 | M35: =SUM(F35,J35) -> 136357.2 | N35: =SUM(H35,K35) -> 1946 | O35: =SUM('Performances by Week'!$AB$70:$AB$72) -> 4770 | P35: =N35/O35 -> 0.40796646 | Q35: =M35/N35 -> 70.070504
A36: PS4 | B36: Billy Joel & Elton John | D36: Mar 27-29 | E36: =SUM('Performances by Week'!$U$85:$U$87) -> 159999 | F36: =SUM('Performances by Week'!$T$85:$T$87) -> 40766 | G36: =F36-E36 -> -119233 | H36: =SUM('Performances by Week'!$P$85:$P$87) -> 579 | I36: =SUM('Performances by Week'!$Z$85:$Z$87) -> 124000 | J36: =SUM('Performances by Week'!$Y$85:$Y$87) -> 128191.5 | K36: =SUM('Performances by Week'!$X$85:$X$87) -> 1798 | L36: =SUM(E36,I36) -> 283999 | M36: =SUM(F36,J36) -> 168957.5 | N36: =SUM(H36,K36) -> 2377 | O36: =SUM('Performances by Week'!$AB$85:$AB$87) -> 4770 | P36: =N36/O36 -> 0.49832285 | Q36: =M36/N36 -> 71.080143
A37: PS5 | B37: Dolly Parton's Threads | D37: May 15-17 | E37: =SUM('Performances by Week'!$U$100:$U$102) -> 180000 | F37: =SUM('Performances by Week'!$T$100:$T$102) -> 19555 | G37: =F37-E37 -> -160445 | H37: =SUM('Performances by Week'!$P$100:$P$102) -> 256 | I37: =SUM('Performances by Week'!$Z$100:$Z$102) -> 130000 | J37: =SUM('Performances by Week'!$Y$100:$Y$102) -> 150672 | K37: =SUM('Performances by Week'!$X$100:$X$102) -> 1801 | L37: =SUM(E37,I37) -> 310000 | M37: =SUM(F37,J37) -> 170227 | N37: =SUM(H37,K37) -> 2057 | O37: =SUM('Performances by Week'!$AB$100:$AB$102) -> 3906 | P37: =N37/O37 -> 0.5266257 | Q37: =M37/N37 -> 82.754983
A38: POPS TOTAL | E38: =SUM(E33:E37) -> 837996 | F38: =SUM(F33:F37) -> 201115 | G38: =SUM(G33:G37) -> -636881 | H38: =SUM(H33:H37) -> 3141 | I38: =SUM(I33:I37) -> 619000 | J38: =SUM(J33:J37) -> 635424.6 | K38: =SUM(K33:K37) -> 8562 | L38: =SUM(L33:L37) -> 1456996 | ... O38: =SUM(O33:O37) -> 22986 | P38: =N38/O38 -> 0.509136 | Q38: =M38/N38 -> 71.480783
A40: FAMILY
A41: FS1 | B41: The Orchestra Games | D41: Sep 28 | E41: ='Performances by Week'!$U$13 -> 10000 | F41: ='Performances by Week'!$T$13 -> 8917 | G41: =F41-E41 -> -1083 | H41: ='Performances by Week'!$P$13 -> 343 | I41: ='Performances by Week'!$Z$13 -> 9500 | J41: ='Performances by Week'!$Y$13 -> 5217 | K41: ='Performances by Week'!$X$13 -> 196 | L41: =SUM(E41,I41) -> 19500 | M41: =SUM(F41,J41) -> 14134 | N41: =SUM(H41,K41) -> 539 | O41: ='Performances by Week'!$AB$13 -> 1302 | P41: =N41/O41 -> 0.41397849 | Q41: =M41/N41 -> 26.222635
A42: FS2 | B42: Carnival of the Animals | D42: Nov 9 | E42: ='Performances by Week'!$U$29 -> 10000 | F42: ='Performances by Week'!$T$29 -> 4465 | G42: =F42-E42 -> -5535 | H42: ='Performances by Week'!$P$29 -> 158 | I42: ='Performances by Week'!$Z$29 -> 9500 | J42: ='Performances by Week'!$Y$29 -> 6836 | K42: ='Performances by Week'!$X$29 -> 307 | L42: =SUM(E42,I42) -> 19500 | M42: =SUM(F42,J42) -> 11301 | N42: =SUM(H42,K42) -> 465 | O42: ='Performances by Week'!$AB$29 -> 1300 | P42: =N42/O42 -> 0.35769231 | Q42: =M42/N42 -> 24.303226
A43: Holiday | B43: Christmas Festival | D43: Dec 18-21 | E43: =SUM('Performances by Week'!$U$43:$U$48) -> 455000 | F43: =SUM('Performances by Week'!$T$43:$T$48) -> 91945 | G43: =F43-E43 -> -363055 | H43: =SUM('Performances by Week'!$P$43:$P$48) -> 1519 | I43: =SUM('Performances by Week'!$Z$43:$Z$48) -> 12450 | J43: =SUM('Performances by Week'!$Y$43:$Y$48) -> 6677 | K43: =SUM('Performances by Week'!$X$43:$X$48) -> 301 | L43: =SUM(E43,I43) -> 467450 | M43: =SUM(F43,J43) -> 98622 | N43: =SUM(H43,K43) -> 1820 | O43: =SUM('Performances by Week'!$AB$43:$AB$48) -> 8598 | P43: =N43/O43 -> 0.21167713 | Q43: =M43/N43 -> 54.187912
A44: FS3 | B44: Philharmonia Fantastique | D44: Mar 1 | E44: ='Performances by Week'!$U$77 -> 10000 | F44: ='Performances by Week'!$T$77 -> 1461 | G44: =F44-E44 -> -8539 | H44: ='Performances by Week'!$P$77 -> 50 | I44: ='Performances by Week'!$Z$77 -> 9500 | J44: ='Performances by Week'!$Y$77 -> 6836 | K44: ='Performances by Week'!$X$77 -> 307 | L44: =SUM(E44,I44) -> 19500 | M44: =SUM(F44,J44) -> 8297 | N44: =SUM(H44,K44) -> 357 | O44: ='Performances by Week'!$AB$77 -> 1302 | P44: =N44/O44 -> 0.27419355 | Q44: =M44/N44 -> 23.240896
A45: FAMILY SERIES TOTAL | E45: =SUM(E41:E44) -> 485000 | F45: =SUM(F41:F44) -> 106788 | G45: =F45-E45 -> -378212 | H45: =SUM(H41:H44) -> 2070 | I45: =SUM(I41:I44) -> 40950 | J45: =SUM(J41:J44) -> 25566 | K45: =SUM(K41:K44) -> 1111 | L45: =SUM(L41:L44) -> 525950 | M45: =SUM(M41:M44) -> 132354 | N45: =SUM(N41:N44) -> 3181 | O45: =SUM(O41:O44) -> 12502 | P45: =N45/O45 -> 0.25443929 | Q45: =M45/N45 -> 41.607671
A47: FILM
A48: Top Gun: Maverick in Concert | D48: Oct 17-19 | E48: =SUM('Performances by Week'!$U$18:$U$20) -> 310490 | F48: =SUM('Performances by Week'!$T$18:$T$20) -> 166434.5 | G48: =F48-E48 -> -144055.5 | H48: =SUM('Performances by Week'!$P$18:$P$20) -> 2227 | I48: $ - | J48: $ - | K48: - | L48: =SUM(E48,I48) -> 310490 | M48: =SUM(F48,J48) -> 166434.5 | N48: =SUM(H48,K48) -> 2227 | O48: =SUM('Performances by Week'!$AB$18:$AB$20) -> 3906 | P48: =N48/O48 -> 0.57014849 | Q48: =M48/N48 -> 74.734845
A49: The Lodger | D49: Oct 22 | E49: ='Performances by Week'!$U$21 -> 50000 | F49: ='Performances by Week'!$T$21 -> 11006 | G49: =F49-E49 -> -38994 | H49: ='Performances by Week'!$P$21 -> 216 | I49: $ - | J49: $ - | K49: - | L49: =SUM(E49,I49) -> 50000 | M49: =SUM(F49,J49) -> 11006 | N49: =SUM(H49,K49) -> 216 | O49: ='Performances by Week'!$AB$21 -> 1302 | P49: =N49/O49 -> 0.16589862 | Q49: =M49/N49 -> 50.953704
A50: Elf™ in Concert | D50: Nov 28-30 | E50: =SUM('Performances by Week'!$U$34:$U$37) -> 430000 | F50: =SUM('Performances by Week'!$T$34:$T$37) -> 103920.2 | G50: =F50-E50 -> -326079.8 | H50: =SUM('Performances by Week'!$P$34:$P$37) -> 1528 | I50: $ - | J50: $ - | K50: - | L50: =SUM(E50,I50) -> 430000 | M50: =SUM(F50,J50) -> 103920.2 | N50: =SUM(H50,K50) -> 1528 | O50: =SUM('Performances by Week'!$AB$34:$AB$37) -> 5208 | P50: =N50/O50 -> 0.29339478 | Q50: =M50/N50 -> 68.010602
A51: It's a Wonderful Life | D51: Dec 23-24 | E51: =SUM('Performances by Week'!$U$49:$U$50) -> 200000 | F51: =SUM('Performances by Week'!$T$49:$T$50) -> 84306 | G51: =F51-E51 -> -115694 | H51: =SUM('Performances by Week'!$P$49:$P$50) -> 1106 | I51: $ - | J51: $ - | K51: - | L51: =SUM(E51,I51) -> 200000 | M51: =SUM(F51,J51) -> 84306 | N51: =SUM(H51,K51) -> 1106 | O51: =SUM('Performances by Week'!$AB$49:$AB$50) -> 2604 | P51: =N51/O51 -> 0.42473118 | Q51: =M51/N51 -> 76.22604
A52: Indiana Jones: Raiders Lost | D52: Jan 22-25 | E52: =SUM('Performances by Week'!$U$58:$U$61) -> 360000 | F52: =SUM('Performances by Week'!$T$58:$T$61) -> 93772.1 | G52: =F52-E52 -> -266227.9 | H52: =SUM('Performances by Week'!$P$58:$P$61) -> 1322 | I52: $ - | J52: $ - | K52: - | L52: =SUM(E52,I52) -> 360000 | M52: =SUM(F52,J52) -> 93772.1 | N52: =SUM(H52,K52) -> 1322 | O52: =SUM('Performances by Week'!$AB$58:$AB$61) -> 5208 | P52: =N52/O52 -> 0.25384025 | Q52: =M52/N52 -> 70.931997
A53: Harry Potter 2: Chamber | D53: Feb 19-22 | E53: =SUM('Performances by Week'!$U$73:$U$76) -> 445000 | F53: =SUM('Performances by Week'!$T$73:$T$76) -> 94720 | G53: =F53-E53 -> -350280 | H53: =SUM('Performances by Week'!$P$73:$P$76) -> 1328 | I53: $ - | J53: $ - | K53: - | L53: =SUM(E53,I53) -> 445000 | M53: =SUM(F53,J53) -> 94720 | N53: =SUM(H53,K53) -> 1328 | O53: =SUM('Performances by Week'!$AB$73:$AB$76) -> 5208 | P53: =N53/O53 -> 0.25499232 | Q53: =M53/N53 -> 71.325301
A54: FILM TOTAL | E54: =SUM(E48:E53) -> 1795490 | F54: =SUM(F48:F53) -> 554158.8 | G54: =SUM(G48:G53) -> -1241331.2 | H54: =SUM(H48:H53) -> 7727 | I54: $ - | J54: $ - | K54: - | L54: =SUM(L48:L53) -> 1795490 | M54: =SUM(M48:M53) -> 554158.8 | N54: =SUM(N48:N53) -> 7727 | O54: =SUM(O48:O53) -> 23436 | P54: =N54/O54 -> 0.32970643 | Q54: =M54/N54 -> 71.717199
A56: ON STAGE
A57: George Li | D57: Oct 29 | E57: ='Performances by Week'!$U$25 -> 11200 | F57: ='Performances by Week'!$T$25 -> 2800 | G57: =F57-E57 -> -8400 | H57: ='Performances by Week'!$P$25 -> 25 | I57: $ - | J57: $ - | K57: - | L57: =SUM(E57,I57) -> 11200 | M57: =SUM(F57,J57) -> 2800 | N57: =SUM(H57,K57) -> 25 | O57: ='Performances by Week'!$AB$25 -> 100 | P57: =N57/O57 -> 0.25 | Q57: =M57/N57 -> 112
A58: Leila Josefowicz | D58: Feb 5 | E58: ='Performances by Week'!$U$65 -> 9000 | F58: ='Performances by Week'!$T$65 -> 1960 | G58: =F58-E58 -> -7040 | H58: ='Performances by Week'!$P$65 -> 19 | I58: $ - | J58: $ - | K58: - | L58: =SUM(E58,I58) -> 9000 | M58: =SUM(F58,J58) -> 1960 | N58: =SUM(H58,K58) -> 19 | O58: ='Performances by Week'!$AB$65 -> 100 | P58: =N58/O58 -> 0.19 | Q58: =M58/N58 -> 103.15789
A59: Gil Shaham | D59: May 28 | E59: ='Performances by Week'!$U$106 -> 9000 | F59: ='Performances by Week'!$T$106 -> 1680 | G59: =F59-E59 -> -7320 | H59: ='Performances by Week'!$P$106 -> 17 | I59: $ - | J59: $ - | K59: - | L59: =SUM(E59,I59) -> 9000 | M59: =SUM(F59,J59) -> 1680 | N59: =SUM(H59,K59) -> 17 | O59: ='Performances by Week'!$AB$106 -> 100 | P59: =N59/O59 -> 0.17 | Q59: =M59/N59 -> 98.823529
A60: Yefim Bronfman | D60: Jun 4 | E60: ='Performances by Week'!$U$110 -> 9000 | F60: ='Performances by Week'!$T$110 -> 2100 | G60: =F60-E60 -> -6900 | H60: ='Performances by Week'!$P$110 -> 20 | I60: $ - | J60: $ - | K60: - | L60: =SUM(E60,I60) -> 9000 | M60: =SUM(F60,J60) -> 2100 | N60: =SUM(H60,K60) -> 20 | O60: ='Performances by Week'!$AB$110 -> 100 | P60: =N60/O60 -> 0.2 | Q60: =M60/N60 -> 105
A61: ON STAGE CONCERTS TOTAL | E61: =SUM(E57:E60) -> 38200 | F61: =SUM(F57:F60) -> 8540 | G61: =SUM(G57:G60) -> -29660 | H61: =SUM(H57:H60) -> 81 | I61: $ - | J61: $ - | K61: - | L61: =SUM(L57:L60) -> 38200 | M61: =SUM(M57:M60) -> 8540 | N61: =SUM(N57:N60) -> 81 | O61: =SUM(O57:O60) -> 400 | P61: =N61/O61 -> 0.2025 | Q61: =M61/N61 -> 105.4321
A63: OTHER CONCERTS
A64: Morgan Freeman Symphonic Blues | D64: Sep 2-3 | E64: =SUM('Performances by Week'!$U$6:$U$7) -> 306946 | F64: =SUM('Performances by Week'!$T$6:$T$7) -> 272084 | G64: =F64-E64 -> -34862 | H64: =SUM('Performances by Week'!$P$6:$P$7) -> 2317 | I64: $ - | J64: $ - | L64: =SUM(E64,I64) -> 306946 | M64: =SUM(F64,J64) -> 272084 | N64: =SUM(H64,K64) -> 2317 | O64: =SUM('Performances by Week'!$AB$6:$AB$7) -> 2604 | P64: =N64/O64 -> 0.88978495 | Q64: =M64/N64 -> 117.42943
A65: La Nuit Sombre (Four Larks) | D65: Sep 5 | E65: ='Performances by Week'!$U$8 -> 15000 | F65: ='Performances by Week'!$T$8 -> 20005 | G65: =F65-E65 -> 5005 | H65: ='Performances by Week'!$P$8 -> 699 | I65: $ - | J65: $ - | L65: =SUM(E65,I65) -> 15000 | M65: =SUM(F65,J65) -> 20005 | N65: =SUM(H65,K65) -> 699 | O65: ='Performances by Week'!$AB$8 -> 600 | P65: =N65/O65 -> 1.165 | Q65: =M65/N65 -> 28.619456
A66: Handel's Messiah | D66: Dec 5-7 | E66: =SUM('Performances by Week'!$U$38:$U$40) -> 235000 | F66: =SUM('Performances by Week'!$T$38:$T$40) -> 65052.5 | G66: =F66-E66 -> -169947.5 | H66: =SUM('Performances by Week'!$P$38:$P$40) -> 1176 | I66: $ - | J66: $ - | K66: - | L66: =SUM(E66,I66) -> 235000 | M66: =SUM(F66,J66) -> 65052.5 | N66: =SUM(H66,K66) -> 1176 | O66: =SUM('Performances by Week'!$AB$38:$AB$40) -> 4299 | P66: =N66/O66 -> 0.27355199 | Q66: =M66/N66 -> 55.316752
A67: Leslie Odom Jr.: Christmas | D67: Dec 12-13 | E67: =SUM('Performances by Week'!$U$41:$U$42) -> 300000 | F67: =SUM('Performances by Week'!$T$41:$T$42) -> 234790.5 | G67: =F67-E67 -> -65209.5 | H67: =SUM('Performances by Week'!$P$41:$P$42) -> 2334 | I67: $ - | J67: $ - | K67: - | L67: =SUM(E67,I67) -> 300000 | M67: =SUM(F67,J67) -> 234790.5 | N67: =SUM(H67,K67) -> 2334 | O67: =SUM('Performances by Week'!$AB$41:$AB$42) -> 3180 | P67: =N67/O67 -> 0.73396226 | Q67: =M67/N67 -> 100.59576
A68: Chris Thile | D68: Feb 12 | E68: ='Performances by Week'!$U$69 -> 128900 | F68: ='Performances by Week'!$T$69 -> 30162 | G68: =F68-E68 -> -98738 | H68: ='Performances by Week'!$P$69 -> 340 | I68: $ - | J68: $ - | K68: - | L68: =SUM(E68,I68) -> 128900 | M68: =SUM(F68,J68) -> 30162 | N68: =SUM(H68,K68) -> 340 | O68: ='Performances by Week'!$AB$69 -> 1590 | P68: =N68/O68 -> 0.21383648 | Q68: =M68/N68 -> 88.711765
A69: Final Symphony | D69: Mar 25-26 | E69: =SUM('Performances by Week'!$U$83:$U$84) -> 168218 | F69: =SUM('Performances by Week'!$T$83:$T$84) -> 10464.5 | G69: =F69-E69 -> -157753.5 | H69: =SUM('Performances by Week'!$P$83:$P$84) -> 173 | I69: $ - | J69: $ - | K69: - | L69: =SUM(E69,I69) -> 168218 | M69: =SUM(F69,J69) -> 10464.5 | N69: =SUM(H69,K69) -> 173 | O69: =SUM('Performances by Week'!$AB$83:$AB$84) -> 3180 | P69: =N69/O69 -> 0.054402516 | Q69: =M69/N69 -> 60.488439
A70: Ben Rector | D70: May 21-22 | E70: =SUM('Performances by Week'!$U$104:$U$105) -> 224936 | F70: =SUM('Performances by Week'!$T$104:$T$105) -> 28268 | G70: =F70-E70 -> -196668 | H70: =SUM('Performances by Week'!$P$104:$P$105) -> 317 | L70: =SUM(E70,I70) -> 224936 | M70: =SUM(F70,J70) -> 28268 | N70: =SUM(H70,K70) -> 317 | O70: =SUM('Performances by Week'!$AB$104:$AB$105) -> 3180 | P70: =N70/O70 -> 0.099685535 | Q70: =M70/N70 -> 89.173502
A71: OTHER CONCERT TOTAL | E71: =SUM(E64:E70) -> 1379000 | F71: =SUM(F64:F70) -> 660826.5 | G71: =SUM(G64:G70) -> -718173.5 | H71: =SUM(H64:H70) -> 7356 | I71: $ - | J71: $ - | K71: - | L71: =SUM(L64:L70) -> 1379000 | M71: =SUM(M64:M70) -> 660826.5 | N71: =SUM(N64:N70) -> 7356 | O71: =SUM(O64:O70) -> 18633 | P71: =N71/O71 -> 0.39478345 | Q71: =M71/N71 -> 89.835033
A72: ALL CONCERTS | E72: =SUM(E71,E61,E54,E45,E38,E20) -> 5402679 | F72: =SUM(F71,F61,F54,F45,F38,F20) -> 1784458.3 | G72: =SUM(G71,G61,G54,G45,G38,G20) -> -3618220.7 | H72: =SUM(H71,H61,H54,H45,H38,H20) -> 24851 | I72: =SUM(I71,I61,I54,I45,I38,I20) -> 2294950 | J72: =SUM(J71,J61,J54,J45,J38,J20) -> 2172607.1 | K72: =SUM(K71,K61,K54,K45,K38,K20) -> 32562 | L72: =SUM(L71,L61,L54,L45,L38,L20) -> 7697629 | ... O72: =SUM(O71,O61,O54,O45,O38,O20) -> 143324 | P72: =N72/O72 -> 0.4005819 | Q72: =M72/N72 -> 68.922812
