Workbook

Sheet Performances by Week
E1: Status: | F1: Updated 8.25 | I1: Update all fields in Blue each week | J1: We expect 50% of Single Sales 1 Week Prior | K1: 85%+ occupancy | O1: 95%+ of Budget | R1: Denotes Piazza
K2: 70-85% occupancy | O2: 85-95% of Budget
G3: Week # | K3: <70% occupancy | O3: <85% of Budget
D4: TICKET SALES REPORT as of 8/25/2025 | G4: 0 | I4: TOTAL SALES (Singles + Subs) | P4: Single Tickets | V4: Subscription Tickets | Z4: Hall Data | AC4: Audience Data | AF4: Revenue last week | AG4: Increase over week
A5: Wk # | B5: # Weeks Until Perf | C5: Perf. Week (Mon) | D5: Performance | G5: Performance Date(s) | H5: Performance Type | I5: Actual Tickets Sold | J5: Projected Single Tickets + Actual Subs | K5: Projected Occupancy at Performance | L5: Total Actual Revenue | M5: TOTAL BUDGET | N5: Actual/ Budget % | O5: Projected/ Budget % | P5: Actual Tickets Sold | Q5: Projected Tickets | R5: Actual Revenue | S5: BUDGET | T5: Actual/ Budget % | U5: Projected/ Budget % | V5: Actual Tickets Sold | W5: Actual Revenue | X5: BUDGET | Y5: Actual vs Budget % | Z5: Max CAP | AA5: Actual OCC SOLD | AB5: Single Ticket ATP | AC5: # New HH | AD5: # Ret HH | AE5: # Total HH
A6: 1 | B6: =A6-$G$4 -> 1 | C6: 45901 | D6: 26 Morgan Freeman's Symphonic Blues | G6: 45902.833 | H6: Specials | I6: =P6+V6 -> 1021 | J6: =IF(Q6="Too early",Q6,Q6+V6) -> 1730.5085 | K6: =IF(J6="Too early",J6,J6/Z6) -> 1.3291156 | L6: =R6+W6 -> 121597 | M6: =S6+X6 -> 153473 | N6: =L6/M6 -> 0.79230223 | O6: =IF($J6="Too early",J6,J6*AB6/M6) -> 1.3428851 | P6: 1021 | Q6: =IF(B6<7,(P6/VLOOKUP(B6,'Sales Pacing'!$A$23:$E$36,2)),"Too early") -> 1730.5085 | R6: 121597 | S6: 153473 | T6: =IF(R6>0,R6/S6,"") -> 0.79230223 | U6: =IF($Q6="Too early",Q6,Q6*AB6/S6) -> 1.3428851 | X6: 0 | Y6: =IF(W6>0,W6/X6,"") | Z6: 1302 | AA6: =I6/Z6 -> 0.78417819 | AB6: =L6/I6 -> 119.09598 | AC6: 113 | AD6: 223 | AE6: 336 | AF6: 110902 | AG6: =L6-AF6 -> 10695
A7: 1 | B7: =A7-$G$4 -> 1 | C7: 45901 | D7: 26 Morgan Freeman's Symphonic Blues | G7: 45903.833 | H7: Specials | I7: =P7+V7 -> 932 | J7: =IF(Q7="Too early",Q7,Q7+V7) -> 1579.661 | K7: =IF(J7="Too early",J7,J7/Z7) -> 1.2132573 | L7: =R7+W7 -> 111049 | M7: =S7+X7 -> 153473 | N7: =L7/M7 -> 0.72357353 | O7: =IF($J7="Too early",J7,J7*AB7/M7) -> 1.2263958 | P7: 932 | Q7: =IF(B7<7,(P7/VLOOKUP(B7,'Sales Pacing'!$A$23:$E$36,2)),"Too early") -> 1579.661 | R7: 111049 | S7: 153473 | T7: =IF(R7>0,R7/S7,"") -> 0.72357353 | U7: =IF($Q7="Too early",Q7,Q7*AB7/S7) -> 1.2263958 | X7: 0 | Y7: =IF(W7>0,W7/X7,"") | Z7: 1302 | AA7: =I7/Z7 -> 0.71582181 | AB7: =L7/I7 -> 119.15129 | AC7: 95 | AD7: 187 | AE7: 282 | AF7: 100649 | AG7: =L7-AF7 -> 10400
A8: 1 | B8: =A8-$G$4 -> 1 | C8: 45901 | D8: 26 La nuit sombre | G8: 45905.833 | H8: Specials | I8: =P8+V8 -> 625 | J8: =IF(Q8="Too early",Q8,Q8+V8) -> 1059.322 | K8: =IF(J8="Too early",J8,J8/Z8) -> 1.7655367 | L8: =R8+W8 -> 17555 | M8: =S8+X8 -> 15000 | N8: =L8/M8 -> 1.1703333 | O8: =IF($J8="Too early",J8,J8*AB8/M8) -> 1.9836158 | P8: 625 | Q8: =IF(B8<7,(P8/VLOOKUP(B8,'Sales Pacing'!$A$23:$E$36,2)),"Too early") -> 1059.322 | R8: 17555 | S8: 15000 | T8: =IF(R8>0,R8/S8,"") -> 1.1703333 | U8: =IF($Q8="Too early",Q8,Q8*AB8/S8) -> 1.9836158 | X8: 0 | Y8: =IF(W8>0,W8/X8,"") | Z8: 600 | AA8: =I8/Z8 -> 1.0416667 | AB8: =L8/I8 -> 28.088 | AC8: 59 | AD8: 185 | AE8: 244 | AF8: 16435 | AG8: =L8-AF8 -> 1120
A9: 2 | B9: =A9-$G$4 -> 2 | C9: 45908 | D9: OPEN - Recording Week | I9: =P9+V9 -> 0 | J9: =IF(Q9="Too early",Q9,Q9+V9) -> 0 | N9: =L9/M9 -> #DIV/0! | Q9: =IF(B9<7,(P9/VLOOKUP(B9,'Sales Pacing'!$A$23:$E$36,2)),"Too early") -> 0 | T9: =IF(R9>0,R9/S9,"") | Y9: N/A | AA9: =I9/Z9 -> #DIV/0!
A10: 3 | B10: =A10-$G$4 -> 3 | C10: 45915 | D10: 26 PS1 Music of Journey | G10: 45919.833 | H10: Pops | I10: =P10+V10 -> 904 | J10: =IF(Q10="Too early",Q10,Q10+V10) -> 1234.0256 | K10: =IF(J10="Too early",J10,J10/Z10) -> 0.77611676 | L10: =R10+W10 -> 63589.3 | M10: =S10+X10 -> 100666 | N10: =L10/M10 -> 0.63168597 | O10: =IF($J10="Too early",J10,J10*AB10/M10) -> 0.86229722 | P10: 211 | Q10: =IF(B10<7,(P10/VLOOKUP(B10,'Sales Pacing'!$A$23:$E$36,2)),"Too early") -> 541.02564 | R10: 13694 | S10: 59333 | T10: =IF(R10>0,R10/S10,"") -> 0.23079905 | U10: =IF($Q10="Too early",Q10,Q10*AB10/S10) -> 0.64141211 | V10: 693 | W10: 49895.3 | X10: 41333 | Y10: =IF(W10>0,W10/X10,"") -> 1.2071541 | Z10: 1590 | AA10: =I10/Z10 -> 0.56855346 | AB10: =L10/I10 -> 70.342146 | AC10: 10 | AD10: 355 | AE10: 365 | AF10: 61035.1 | AG10: =L10-AF10 -> 2554.2
A11: 3 | B11: =A11-$G$4 -> 3 | C11: 45915 | D11: 26 PS1 Music of Journey | G11: 45920.833 | H11: Pops | I11: =P11+V11 -> 868 | J11: =IF(Q11="Too early",Q11,Q11+V11) -> 1265.2821 | K11: =IF(J11="Too early",J11,J11/Z11) -> 0.79577488 | L11: =R11+W11 -> 62401.3 | M11: =S11+X11 -> 100667 | N11: =L11/M11 -> 0.61987841 | O11: =IF($J11="Too early",J11,J11*AB11/M11) -> 0.90359565 | P11: 254 | Q11: =IF(B11<7,(P11/VLOOKUP(B11,'Sales Pacing'!$A$23:$E$36,2)),"Too early") -> 651.28205 | R11: 17508 | S11: 59333 | T11: =IF(R11>0,R11/S11,"") -> 0.29508031 | U11: =IF($Q11="Too early",Q11,Q11*AB11/S11) -> 0.78912666 | V11: 614 | W11: 44893.3 | X11: 41334 | Y11: =IF(W11>0,W11/X11,"") -> 1.0861107 | Z11: 1590 | AA11: =I11/Z11 -> 0.54591195 | AB11: =L11/I11 -> 71.890899 | AC11: 20 | AD11: 314 | AE11: 334 | AF11: 60302.5 | AG11: =L11-AF11 -> 2098.8
A12: 3 | B12: =A12-$G$4 -> 3 | C12: 45915 | D12: 26 PS1 Music of Journey | G12: 45921.583 | H12: Pops | I12: =P12+V12 -> 678 | J12: =IF(Q12="Too early",Q12,Q12+V12) -> 1153.4872 | K12: =IF(J12="Too early",J12,J12/Z12) -> 0.72546363 | L12: =R12+W12 -> 45027.8 | M12: =S12+X12 -> 100666 | N12: =L12/M12 -> 0.44729899 | O12: =IF($J12="Too early",J12,J12*AB12/M12) -> 0.76099358 | P12: 304 | Q12: =IF(B12<7,(P12/VLOOKUP(B12,'Sales Pacing'!$A$23:$E$36,2)),"Too early") -> 779.48718 | R12: 19552 | S12: 59333 | T12: =IF(R12>0,R12/S12,"") -> 0.32952994 | U12: =IF($Q12="Too early",Q12,Q12*AB12/S12) -> 0.87249652 | V12: 374 | W12: 25475.8 | X12: 41333 | Y12: =IF(W12>0,W12/X12,"") -> 0.61635497 | Z12: 1590 | AA12: =I12/Z12 -> 0.42641509 | AB12: =L12/I12 -> 66.412684 | AC12: 16 | AD12: 223 | AE12: 239 | AF12: 40030.8 | AG12: =L12-AF12 -> 4997
A13: 4 | B13: =A13-$G$4 -> 4 | C13: 45922 | D13: 26 FS1 The Orchestra Games | G13: 45928.583 | H13: Family | I13: =P13+V13 -> 429 | J13: =IF(Q13="Too early",Q13,Q13+V13) -> 707.15152 | K13: =IF(J13="Too early",J13,J13/Z13) -> 0.54312712 | L13: =R13+W13 -> 11177 | M13: =S13+X13 -> 19500 | N13: =L13/M13 -> 0.57317949 | O13: =IF($J13="Too early",J13,J13*AB13/M13) -> 0.94481292 | P13: 137 | Q13: =IF(B13<7,(P13/VLOOKUP(B13,'Sales Pacing'!$A$23:$E$36,2)),"Too early") -> 415.15152 | R13: 4687 | S13: 10000 | T13: =IF(R13>0,R13/S13,"") -> 0.4687 | U13: =IF($Q13="Too early",Q13,Q13*AB13/S13) -> 1.0816197 | V13: 292 | W13: 6490 | X13: 9500 | Y13: =IF(W13>0,W13/X13,"") -> 0.68315789 | Z13: 1302 | AA13: =I13/Z13 -> 0.32949309 | AB13: =L13/I13 -> 26.053613 | AC13: 15 | AD13: 88 | AE13: 103 | AF13: 10625 | AG13: =L13-AF13 -> 552
A14: 5 | B14: =A14-$G$4 -> 5 | C14: 45929 | D14: Chicken Fried | G14: 45934 | H14: Specials | I14: =P14+V14 -> 150 | J14: =IF(Q14="Too early",Q14,Q14+V14) -> 500 | K14: =IF(J14="Too early",J14,J14/Z14) -> 0.31446541 | L14: =R14+W14 -> 10596 | M14: =S14+X14 -> 58000 | N14: =L14/M14 -> 0.18268966 | O14: =IF($J14="Too early",J14,J14*AB14/M14) -> 0.60896552 | P14: 150 | Q14: =IF(B14<7,(P14/VLOOKUP(B14,'Sales Pacing'!$A$23:$E$36,2)),"Too early") -> 500 | R14: 10596 | S14: 58000 | T14: =IF(R14>0,R14/S14,"") -> 0.18268966 | U14: =IF($Q14="Too early",Q14,Q14*AB14/S14) -> 0.60896552 | Y14: =IF(W14>0,W14/X14,"") | Z14: 1590 | AA14: =I14/Z14 -> 0.094339623 | AB14: =L14/I14 -> 70.64 | AC14: 6 | AD14: 40 | AE14: 46 | AF14: 9094 | AG14: =L14-AF14 -> 1502
A15: 6 | B15: =A15-$G$4 -> 6 | C15: 45936 | D15: 26 CS01 Appalachian Spring | G15: 45940.833 | H15: Classical | I15: =P15+V15 -> 662 | J15: =IF(Q15="Too early",Q15,Q15+V15) -> 983.74074 | K15: =IF(J15="Too early",J15,J15/Z15) -> 0.6864904 | L15: =R15+W15 -> 43762.3 | M15: 100000 | N15: =L15/M15 -> 0.437623 | O15: =IF($J15="Too early",J15,J15*AB15/M15) -> 0.65031356 | P15: 119 | Q15: =IF(B15<7,(P15/VLOOKUP(B15,'Sales Pacing'!$A$23:$E$36,2)),"Too early") -> 440.74074 | R15: 7327 | S15: 16666 | T15: =IF(R15>0,R15/S15,"") -> 0.43963759 | U15: =IF($Q15="Too early",Q15,Q15*AB15/S15) -> 1.7482115 | V15: 543 | W15: 36435.3 | X15: 33333 | Y15: =IF(W15>0,W15/X15,"") -> 1.0930699 | Z15: 1433 | AA15: =I15/Z15 -> 0.4619679 | AB15: =L15/I15 -> 66.106193 | AC15: 7 | AD15: 323 | AE15: 330 | AF15: 43678.3 | AG15: =L15-AF15 -> 84
A16: 6 | B16: =A16-$G$4 -> 6 | C16: 45936 | D16: 26 CS01 Appalachian Spring | G16: 45941.833 | H16: Classical | I16: =P16+V16 -> 724 | J16: =IF(Q16="Too early",Q16,Q16+V16) -> 1110.6296 | K16: =IF(J16="Too early",J16,J16/Z16) -> 0.77503812 | L16: =R16+W16 -> 48541.1 | M16: 100000 | N16: =L16/M16 -> 0.485411 | O16: =IF($J16="Too early",J16,J16*AB16/M16) -> 0.74462961 | P16: 143 | Q16: =IF(B16<7,(P16/VLOOKUP(B16,'Sales Pacing'!$A$23:$E$36,2)),"Too early") -> 529.62963 | R16: 8845 | S16: 16666 | T16: =IF(R16>0,R16/S16,"") -> 0.53072123 | U16: =IF($Q16="Too early",Q16,Q16*AB16/S16) -> 2.1306492 | V16: 581 | W16: 39696.1 | X16: 33333 | Y16: =IF(W16>0,W16/X16,"") -> 1.1908949 | Z16: 1433 | AA16: =I16/Z16 -> 0.50523378 | AB16: =L16/I16 -> 67.045718 | AC16: 411 | AD16: 342 | AE16: 353 | AF16: 47426.6 | AG16: =L16-AF16 -> 1114.5
A17: 6 | B17: =A17-$G$4 -> 6 | C17: 45936 | D17: 26 CS01 Appalachian Spring | G17: 45942.583 | H17: Classical | I17: =P17+V17 -> 791 | J17: =IF(Q17="Too early",Q17,Q17+V17) -> 1272.2593 | K17: =IF(J17="Too early",J17,J17/Z17) -> 0.88782921 | L17: =R17+W17 -> 51198.6 | M17: 100000 | N17: =L17/M17 -> 0.511986 | O17: =IF($J17="Too early",J17,J17*AB17/M17) -> 0.8234879 | P17: 178 | Q17: =IF(B17<7,(P17/VLOOKUP(B17,'Sales Pacing'!$A$23:$E$36,2)),"Too early") -> 659.25926 | R17: 11452 | S17: 16666 | T17: =IF(R17>0,R17/S17,"") -> 0.68714749 | U17: =IF($Q17="Too early",Q17,Q17*AB17/S17) -> 2.560392 | V17: 613 | W17: 39746.6 | X17: 33334 | Y17: =IF(W17>0,W17/X17,"") -> 1.1923742 | Z17: 1433 | AA17: =I17/Z17 -> 0.55198883 | AB17: =L17/I17 -> 64.726422 | AC17: 8 | AD17: 402 | AE17: 410 | AF17: 49731.6 | AG17: =L17-AF17 -> 1467
A18: 7 | B18: =A18-$G$4 -> 7 | C18: 45943 | D18: 26 Top Gun: Maverick in Concert | G18: 45947.792 | H18: Specials/Film | I18: =P18+V18 -> 546 | J18: =IF(Q18="Too early",Q18,Q18+V18) -> Too early | K18: =IF(J18="Too early",J18,J18/Z18) -> Too early | L18: =R18+W18 -> 41731.5 | M18: =S18+X18 -> 103497 | N18: =L18/M18 -> 0.40321459 | O18: =IF($J18="Too early",J18,J18*AB18/M18) -> Too early | P18: 546 | Q18: =IF(B18<7,(P18/VLOOKUP(B18,'Sales Pacing'!$A$23:$E$36,2)),"Too early") -> Too early | R18: 41731.5 | S18: 103497 | T18: =IF(R18>0,R18/S18,"") -> 0.40321459 | U18: =IF($Q18="Too early",Q18,Q18*AB18/S18) -> Too early | Y18: =IF(W18>0,W18/X18,"") | Z18: 1302 | AA18: =I18/Z19 -> 0.41935484 | AB18: =L18/I18 -> 76.431319 | AF18: 38186 | AG18: =L18-AF18 -> 3545.5
A19: 7 | B19: =A19-$G$4 -> 7 | C19: 45943 | D19: 26 Top Gun: Maverick in Concert | G19: 45948.792 | H19: Specials/Film | I19: =P19+V19 -> 661 | J19: =IF(Q19="Too early",Q19,Q19+V19) -> Too early | K19: =IF(J19="Too early",J19,J19/Z19) -> Too early | L19: =R19+W19 -> 50068 | M19: =S19+X19 -> 103497 | N19: =L19/M19 -> 0.48376281 | O19: =IF($J19="Too early",J19,J19*AB19/M19) -> Too early | P19: 661 | Q19: =IF(B19<7,(P19/VLOOKUP(B19,'Sales Pacing'!$A$23:$E$36,2)),"Too early") -> Too early | R19: 50068 | S19: 103497 | T19: =IF(R19>0,R19/S19,"") -> 0.48376281 | U19: =IF($Q19="Too early",Q19,Q19*AB19/S19) -> Too early | Y19: =IF(W19>0,W19/X19,"") | Z19: 1302 | AA19: =I19/Z19 -> 0.50768049 | AB19: =L19/I19 -> 75.74584 | AF19: 47838 | AG19: =L19-AF19 -> 2230
A20: 7 | B20: =A20-$G$4 -> 7 | C20: 45943 | D20: 26 Top Gun: Maverick in Concert | G20: 45949.583 | H20: Specials/Film | I20: =P20+V20 -> 473 | J20: =IF(Q20="Too early",Q20,Q20+V20) -> Too early | K20: =IF(J20="Too early",J20,J20/Z20) -> Too early | L20: =R20+W20 -> 36255 | M20: =S20+X20 -> 103496 | N20: =L20/M20 -> 0.35030339 | O20: =IF($J20="Too early",J20,J20*AB20/M20) -> Too early | P20: 473 | Q20: =IF(B20<7,(P20/VLOOKUP(B20,'Sales Pacing'!$A$23:$E$36,2)),"Too early") -> Too early | R20: 36255 | S20: 103496 | T20: =IF(R20>0,R20/S20,"") -> 0.35030339 | U20: =IF($Q20="Too early",Q20,Q20*AB20/S20) -> Too early | Y20: =IF(W20>0,W20/X20,"") | Z20: 1302 | AA20: =I20/Z20 -> 0.36328725 | AB20: =L20/I20 -> 76.649049 | AF20: 34131 | AG20: =L20-AF20 -> 2124
A21: 8 | B21: =A21-$G$4 -> 8 | C21: 45950 | D21: 26 The Lodger | G21: 45952.792 | H21: Specials/Film | I21: =P21+V21 -> 187 | J21: =IF(Q21="Too early",Q21,Q21+V21) -> Too early | K21: =IF(J21="Too early",J21,J21/Z21) -> Too early | L21: =R21+W21 -> 9513 | M21: =S21+X21 -> 50000 | N21: =L21/M21 -> 0.19026 | O21: =IF($J21="Too early",J21,J21*AB21/M21) -> Too early | P21: 187 | Q21: =IF(B21<7,(P21/VLOOKUP(B21,'Sales Pacing'!$A$23:$E$36,2)),"Too early") -> Too early | R21: 9513 | S21: 50000 | T21: =IF(R21>0,R21/S21,"") -> 0.19026 | U21: =IF($Q21="Too early",Q21,Q21*AB21/S21) -> Too early | Y21: =IF(W21>0,W21/X21,"") | Z21: 1302 | AA21: =I21/Z21 -> 0.14362519 | AB21: =L21/I21 -> 50.871658 | AF21: 9284 | AG21: =L21-AF21 -> 229
A22: 8 | B22: =A22-$G$4 -> 8 | C22: 45950 | D22: 26 PS2 Night of Symphonic 90s | G22: 45954.833 | H22: Pops | I22: =P22+V22 -> 783 | J22: =IF(Q22="Too early",Q22,Q22+V22) -> Too early | K22: =IF(J22="Too early",J22,J22/Z22) -> Too early | L22: =R22+W22 -> 55866.3 | M22: =S22+X22 -> 92333 | N22: =L22/M22 -> 0.60505236 | O22: =IF($J22="Too early",J22,J22*AB22/M22) -> Too early | P22: 70 | Q22: =IF(B22<7,(P22/VLOOKUP(B22,'Sales Pacing'!$A$23:$E$36,2)),"Too early") -> Too early | R22: 4060 | S22: 53333 | T22: =IF(R22>0,R22/S22,"") -> 0.076125476 | U22: =IF($Q22="Too early",Q22,Q22*AB22/S22) -> Too early | V22: 713 | W22: 51806.3 | X22: 39000 | Y22: =IF(W22>0,W22/X22,"") -> 1.3283667 | Z22: 1590 | AA22: =I22/Z22 -> 0.49245283 | AB22: =L22/I22 -> 71.349042 | AF22: 55899.1 | AG22: =L22-AF22 -> -32.8
A23: 8 | B23: =A23-$G$4 -> 8 | C23: 45950 | D23: 26 PS2 Night of Symphonic 90s | G23: 45955.833 | H23: Pops | I23: =P23+V23 -> 703 | J23: =IF(Q23="Too early",Q23,Q23+V23) -> Too early | K23: =IF(J23="Too early",J23,J23/Z23) -> Too early | L23: =R23+W23 -> 50141.3 | M23: =S23+X23 -> 92333 | N23: =L23/M23 -> 0.54304853 | O23: =IF($J23="Too early",J23,J23*AB23/M23) -> Too early | P23: 66 | Q23: =IF(B23<7,(P23/VLOOKUP(B23,'Sales Pacing'!$A$23:$E$36,2)),"Too early") -> Too early | R23: 3760 | S23: 53333 | T23: =IF(R23>0,R23/S23,"") -> 0.070500441 | U23: =IF($Q23="Too early",Q23,Q23*AB23/S23) -> Too early | V23: 637 | W23: 46381.3 | X23: 39000 | Y23: =IF(W23>0,W23/X23,"") -> 1.1892641 | Z23: 1590 | AA23: =I23/Z23 -> 0.44213836 | AB23: =L23/I23 -> 71.324751 | AF23: 50410.5 | AG23: =L23-AF23 -> -269.2
A24: 8 | B24: =A24-$G$4 -> 8 | C24: 45950 | D24: 26 PS2 Night of Symphonic 90s | G24: 45956.583 | H24: Pops | I24: =P24+V24 -> 450 | J24: =IF(Q24="Too early",Q24,Q24+V24) -> Too early | K24: =IF(J24="Too early",J24,J24/Z24) -> Too early | L24: =R24+W24 -> 33121.5 | M24: =S24+X24 -> 92333 | N24: =L24/M24 -> 0.3587179 | O24: =IF($J24="Too early",J24,J24*AB24/M24) -> Too early | P24: 68 | Q24: =IF(B24<7,(P24/VLOOKUP(B24,'Sales Pacing'!$A$23:$E$36,2)),"Too early") -> Too early | R24: 7092 | S24: 53333 | T24: =IF(R24>0,R24/S24,"") -> 0.13297583 | U24: =IF($Q24="Too early",Q24,Q24*AB24/S24) -> Too early | V24: 382 | W24: 26029.5 | X24: 39000 | Y24: =IF(W24>0,W24/X24,"") -> 0.66742308 | Z24: 1590 | AA24: =I24/Z24 -> 0.28301887 | AB24: =L24/I24 -> 73.603333 | AF24: 32829.5 | AG24: =L24-AF24 -> 292
A25: 9 | B25: =A25-$G$4 -> 9 | C25: 45957 | D25: 26 On-Stage 1 | G25: 45959.833 | H25: On Stage | I25: =P25+V25 -> 23 | J25: =IF(Q25="Too early",Q25,Q25+V25) -> Too early | K25: =IF(J25="Too early",J25,J25/Z25) -> Too early | L25: =R25+W25 -> 2520 | M25: 11200 | N25: =L25/M25 -> 0.225 | O25: =IF($J25="Too early",J25,J25*AB25/M25) -> Too early | P25: 23 | Q25: =IF(B25<7,(P25/VLOOKUP(B25,'Sales Pacing'!$A$23:$E$36,2)),"Too early") -> Too early | R25: 2520 | S25: 11200 | T25: =IF(R25>0,R25/S25,"") -> 0.225 | U25: =IF($Q25="Too early",Q25,Q25*AB25/S25) -> Too early | Y25: =IF(W25>0,W25/X25,"") | Z25: 100 | AA25: =I25/Z25 -> 0.23 | AB25: =L25/I25 -> 109.56522 | AF25: 2520 | AG25: =L25-AF25 -> 0
A26: 9 | B26: =A26-$G$4 -> 9 | C26: 45957 | D26: 26 CS02 Rachmaninoff Cele Pt 1 | G26: 45961.833 | H26: Classical | I26: =P26+V26 -> 460 | J26: =IF(Q26="Too early",Q26,Q26+V26) -> Too early | K26: =IF(J26="Too early",J26,J26/Z26) -> Too early | L26: =R26+W26 -> 30054 | M26: =S26+X26 -> 52000 | N26: =L26/M26 -> 0.57796154 | O26: =IF($J26="Too early",J26,J26*AB26/M26) -> Too early | P26: 102 | Q26: =IF(B26<7,(P26/VLOOKUP(B26,'Sales Pacing'!$A$23:$E$36,2)),"Too early") -> Too early | R26: 5125 | S26: 22000 | T26: =IF(R26>0,R26/S26,"") -> 0.23295455 | U26: =IF($Q26="Too early",Q26,Q26*AB26/S26) -> Too early | V26: 358 | W26: 24929 | X26: 30000 | Y26: =IF(W26>0,W26/X26,"") -> 0.83096667 | Z26: 1433 | AA26: =I26/Z26 -> 0.32100488 | AB26: =L26/I26 -> 65.334783 | AF26: 29912 | AG26: =L26-AF26 -> 142
A27: 9 | B27: =A27-$G$4 -> 9 | C27: 45957 | D27: 26 CS02 Rachmaninoff Cele Pt 1 | G27: 45962.833 | H27: Classical | I27: =P27+V27 -> 799 | J27: =IF(Q27="Too early",Q27,Q27+V27) -> Too early | K27: =IF(J27="Too early",J27,J27/Z27) -> Too early | L27: =R27+W27 -> 52200 | M27: =S27+X27 -> 86500 | N27: =L27/M27 -> 0.60346821 | O27: =IF($J27="Too early",J27,J27*AB27/M27) -> Too early | P27: 229 | Q27: =IF(B27<7,(P27/VLOOKUP(B27,'Sales Pacing'!$A$23:$E$36,2)),"Too early") -> Too early | R27: 14935 | S27: 31500 | T27: =IF(R27>0,R27/S27,"") -> 0.47412698 | U27: =IF($Q27="Too early",Q27,Q27*AB27/S27) -> Too early | V27: 570 | W27: 37265 | X27: 55000 | Y27: =IF(W27>0,W27/X27,"") -> 0.67754545 | Z27: 1433 | AA27: =I27/Z27 -> 0.55757153 | AB27: =L27/I27 -> 65.331665 | AF27: 51076.8 | AG27: =L27-AF27 -> 1123.2
A28: 9 | B28: =A28-$G$4 -> 9 | C28: 45957 | D28: 26 CS02 Rachmaninoff Cele Pt 1 | G28: 45963.583 | H28: Classical | I28: =P28+V28 -> 734 | J28: =IF(Q28="Too early",Q28,Q28+V28) -> Too early | K28: =IF(J28="Too early",J28,J28/Z28) -> Too early | L28: =R28+W28 -> 46474.1 | M28: =S28+X28 -> 86500 | N28: =L28/M28 -> 0.53727283 | O28: =IF($J28="Too early",J28,J28*AB28/M28) -> Too early | P28: 185 | Q28: =IF(B28<7,(P28/VLOOKUP(B28,'Sales Pacing'!$A$23:$E$36,2)),"Too early") -> Too early | R28: 10688 | S28: 31500 | T28: =IF(R28>0,R28/S28,"") -> 0.33930159 | U28: =IF($Q28="Too early",Q28,Q28*AB28/S28) -> Too early | V28: 549 | W28: 35786.1 | X28: 55000 | Y28: =IF(W28>0,W28/X28,"") -> 0.65065636 | Z28: 1433 | AA28: =I28/Z28 -> 0.51221214 | AB28: =L28/I28 -> 63.316213 | AF28: 44684.7 | AG28: =L28-AF28 -> 1789.4
A29: 10 | B29: =A29-$G$4 -> 10 | C29: 45964 | D29: 26 FS2 Carnival of the Animals | G29: 45970.583 | H29: Family | I29: =P29+V29 -> 433 | J29: =IF(Q29="Too early",Q29,Q29+V29) -> Too early | K29: =IF(J29="Too early",J29,J29/Z29) -> Too early | L29: =R29+W29 -> 11089 | M29: =S29+X29 -> 19500 | N29: =L29/M29 -> 0.56866667 | O29: =IF($J29="Too early",J29,J29*AB29/M29) -> Too early | P29: 137 | Q29: =IF(B29<7,(P29/VLOOKUP(B29,'Sales Pacing'!$A$23:$E$36,2)),"Too early") -> Too early | R29: 4543 | S29: 10000 | T29: =IF(R29>0,R29/S29,"") -> 0.4543 | U29: =IF($Q29="Too early",Q29,Q29*AB29/S29) -> Too early | V29: 296 | W29: 6546 | X29: 9500 | Y29: =IF(W29>0,W29/X29,"") -> 0.68905263 | Z29: 1300 | AA29: =I29/Z29 -> 0.33307692 | AB29: =L29/I29 -> 25.6097 | AF29: 9445 | AG29: =L29-AF29 -> 1644
A30: 11 | B30: =A30-$G$4 -> 11 | C30: 45971 | D30: OPEN | I30: =P30+V30 -> 0 | J30: =IF(Q30="Too early",Q30,Q30+V30) -> Too early | L30: =R30+W30 -> 0 | M30: =S30+X30 -> 0 | N30: =L30/M30 -> #DIV/0! | Q30: =IF(B30<7,(P30/VLOOKUP(B30,'Sales Pacing'!$A$23:$E$36,2)),"Too early") -> Too early | T30: =IF(R30>0,R30/S30,"") | Y30: N/A | AA30: =I30/Z30 -> #DIV/0! | AB30: =L30/I30 -> #DIV/0! | AF30: 0
A31: 12 | B31: =A31-$G$4 -> 12 | C31: 45978 | D31: 26 CS03 Matthias and Mahler 7 | G31: 45982.833 | H31: Classical | I31: =P31+V31 -> 424 | J31: =IF(Q31="Too early",Q31,Q31+V31) -> Too early | K31: =IF(J31="Too early",J31,J31/Z31) -> Too early | L31: =R31+W31 -> 28545 | M31: =S31+X31 -> 40000 | N31: =L31/M31 -> 0.713625 | O31: =IF($J31="Too early",J31,J31*AB31/M31) -> Too early | P31: 57 | Q31: =IF(B31<7,(P31/VLOOKUP(B31,'Sales Pacing'!$A$23:$E$36,2)),"Too early") -> Too early | R31: 2943 | S31: 15000 | T31: =IF(R31>0,R31/S31,"") -> 0.1962 | U31: =IF($Q31="Too early",Q31,Q31*AB31/S31) -> Too early | V31: 367 | W31: 25602 | X31: 25000 | Y31: =IF(W31>0,W31/X31,"") -> 1.02408 | Z31: 1590 | AA31: =I31/Z31 -> 0.26666667 | AB31: =L31/I31 -> 67.323113 | AF31: 28545 | AG31: =L31-AF31 -> 0
A32: 12 | B32: =A32-$G$4 -> 12 | C32: 45978 | D32: 26 CS03 Matthias and Mahler 7 | G32: 45983.833 | H32: Classical | I32: =P32+V32 -> 651 | J32: =IF(Q32="Too early",Q32,Q32+V32) -> Too early | K32: =IF(J32="Too early",J32,J32/Z32) -> Too early | L32: =R32+W32 -> 44302.9 | M32: =S32+X32 -> 66500 | N32: =L32/M32 -> 0.66620902 | O32: =IF($J32="Too early",J32,J32*AB32/M32) -> Too early | P32: 75 | Q32: =IF(B32<7,(P32/VLOOKUP(B32,'Sales Pacing'!$A$23:$E$36,2)),"Too early") -> Too early | R32: 4681 | S32: 11500 | T32: =IF(R32>0,R32/S32,"") -> 0.40704348 | U32: =IF($Q32="Too early",Q32,Q32*AB32/S32) -> Too early | V32: 576 | W32: 39621.9 | X32: 55000 | Y32: =IF(W32>0,W32/X32,"") -> 0.72039818 | Z32: 1590 | AA32: =I32/Z32 -> 0.40943396 | AB32: =L32/I32 -> 68.05361 | AF32: 44221.4 | AG32: =L32-AF32 -> 81.5
A33: 12 | B33: =A33-$G$4 -> 12 | C33: 45978 | D33: 26 CS03 Matthias and Mahler 7 | G33: 45984.583 | H33: Classical | I33: =P33+V33 -> 705 | J33: =IF(Q33="Too early",Q33,Q33+V33) -> Too early | K33: =IF(J33="Too early",J33,J33/Z33) -> Too early | L33: =R33+W33 -> 45933.2 | M33: =S33+X33 -> 66500 | N33: =L33/M33 -> 0.69072481 | O33: =IF($J33="Too early",J33,J33*AB33/M33) -> Too early | P33: 84 | Q33: =IF(B33<7,(P33/VLOOKUP(B33,'Sales Pacing'!$A$23:$E$36,2)),"Too early") -> Too early | R33: 5769 | S33: 11500 | T33: =IF(R33>0,R33/S33,"") -> 0.50165217 | U33: =IF($Q33="Too early",Q33,Q33*AB33/S33) -> Too early | V33: 621 | W33: 40164.2 | X33: 55000 | Y33: =IF(W33>0,W33/X33,"") -> 0.73025818 | Z33: 1590 | AA33: =I33/Z33 -> 0.44339623 | AB33: =L33/I33 -> 65.153475 | AF33: 45373.2 | AG33: =L33-AF33 -> 560
A34: 13 | B34: =A34-$G$4 -> 13 | C34: 45985 | D34: 26 Elf™ in Concert | G34: 45989.792 | H34: Specials/Film | I34: =P34+V34 -> 272 | J34: =IF(Q34="Too early",Q34,Q34+V34) -> Too early | K34: =IF(J34="Too early",J34,J34/Z34) -> Too early | L34: =R34+W34 -> 18219 | M34: =S34+X34 -> 107500 | N34: =L34/M34 -> 0.16947907 | O34: =IF($J34="Too early",J34,J34*AB34/M34) -> Too early | P34: 272 | Q34: =IF(B34<7,(P34/VLOOKUP(B34,'Sales Pacing'!$A$23:$E$36,2)),"Too early") -> Too early | R34: 18219 | S34: 107500 | T34: =IF(R34>0,R34/S34,"") -> 0.16947907 | U34: =IF($Q34="Too early",Q34,Q34*AB34/S34) -> Too early | Y34: =IF(W34>0,W34/X34,"") | Z34: 1302 | AA34: =I34/Z34 -> 0.20890937 | AB34: =L34/I34 -> 66.981618 | AF34: 18219 | AG34: =L34-AF34 -> 0
A35: 13 | B35: =A35-$G$4 -> 13 | C35: 45985 | D35: 26 Elf™ in Concert | G35: 45990.542 | H35: Specials/Film | I35: =P35+V35 -> 250 | J35: =IF(Q35="Too early",Q35,Q35+V35) -> Too early | K35: =IF(J35="Too early",J35,J35/Z35) -> Too early | L35: =R35+W35 -> 16760 | M35: =S35+X35 -> 107500 | N35: =L35/M35 -> 0.15590698 | O35: =IF($J35="Too early",J35,J35*AB35/M35) -> Too early | P35: 250 | Q35: =IF(B35<7,(P35/VLOOKUP(B35,'Sales Pacing'!$A$23:$E$36,2)),"Too early") -> Too early | R35: 16760 | S35: 107500 | T35: =IF(R35>0,R35/S35,"") -> 0.15590698 | U35: =IF($Q35="Too early",Q35,Q35*AB35/S35) -> Too early | Y35: =IF(W35>0,W35/X35,"") | Z35: 1302 | AA35: =I35/Z35 -> 0.19201229 | AB35: =L35/I35 -> 67.04 | AF35: 15032 | AG35: =L35-AF35 -> 1728
A36: 13 | B36: =A36-$G$4 -> 13 | C36: 45985 | D36: 26 Elf™ in Concert | G36: 45990.792 | H36: Specials/Film | I36: =P36+V36 -> 242 | J36: =IF(Q36="Too early",Q36,Q36+V36) -> Too early | K36: =IF(J36="Too early",J36,J36/Z36) -> Too early | L36: =R36+W36 -> 15945 | M36: =S36+X36 -> 107500 | N36: =L36/M36 -> 0.14832558 | O36: =IF($J36="Too early",J36,J36*AB36/M36) -> Too early | P36: 242 | Q36: =IF(B36<7,(P36/VLOOKUP(B36,'Sales Pacing'!$A$23:$E$36,2)),"Too early") -> Too early | R36: 15945 | S36: 107500 | T36: =IF(R36>0,R36/S36,"") -> 0.14832558 | U36: =IF($Q36="Too early",Q36,Q36*AB36/S36) -> Too early | Y36: =IF(W36>0,W36/X36,"") | Z36: 1302 | AA36: =I36/Z36 -> 0.1858679 | AB36: =L36/I36 -> 65.88843 | AF36: 14394 | AG36: =L36-AF36 -> 1551
A37: 13 | B37: =A37-$G$4 -> 13 | C37: 45985 | D37: 26 Elf™ in Concert | G37: 45991.583 | H37: Specials/Film | I37: =P37+V37 -> 408 | J37: =IF(Q37="Too early",Q37,Q37+V37) -> Too early | K37: =IF(J37="Too early",J37,J37/Z37) -> Too early | L37: =R37+W37 -> 29095 | M37: =S37+X37 -> 107500 | N37: =L37/M37 -> 0.27065116 | O37: =IF($J37="Too early",J37,J37*AB37/M37) -> Too early | P37: 408 | Q37: =IF(B37<7,(P37/VLOOKUP(B37,'Sales Pacing'!$A$23:$E$36,2)),"Too early") -> Too early | R37: 29095 | S37: 107500 | T37: =IF(R37>0,R37/S37,"") -> 0.27065116 | U37: =IF($Q37="Too early",Q37,Q37*AB37/S37) -> Too early | Y37: =IF(W37>0,W37/X37,"") | Z37: 1302 | AA37: =I37/Z37 -> 0.31336406 | AB37: =L37/I37 -> 71.311275 | AF37: 28457 | AG37: =L37-AF37 -> 638
A38: 14 | B38: =A38-$G$4 -> 14 | C38: 45992 | D38: 26 Handel's Messiah | G38: 45996.792 | H38: Holiday | I38: =P38+V38 -> 285 | J38: =IF(Q38="Too early",Q38,Q38+V38) -> Too early | K38: =IF(J38="Too early",J38,J38/Z38) -> Too early | L38: =R38+W38 -> 14705.5 | M38: =S38+X38 -> 78333 | N38: =L38/M38 -> 0.18773059 | O38: =IF($J38="Too early",J38,J38*AB38/M38) -> Too early | P38: 285 | Q38: =IF(B38<7,(P38/VLOOKUP(B38,'Sales Pacing'!$A$23:$E$36,2)),"Too early") -> Too early | R38: 14705.5 | S38: 78333 | T38: =IF(R38>0,R38/S38,"") -> 0.18773059 | U38: =IF($Q38="Too early",Q38,Q38*AB38/S38) -> Too early | Y38: =IF(W38>0,W38/X38,"") | Z38: 1433 | AA38: =I38/Z38 -> 0.19888346 | AB38: =L38/I38 -> 51.598246 | AF38: 13735 | AG38: =L38-AF38 -> 970.5
A39: 14 | B39: =A39-$G$4 -> 14 | C39: 45992 | D39: 26 Handel's Messiah | G39: 45997.792 | H39: Holiday | I39: =P39+V39 -> 312 | J39: =IF(Q39="Too early",Q39,Q39+V39) -> Too early | K39: =IF(J39="Too early",J39,J39/Z39) -> Too early | L39: =R39+W39 -> 18906.5 | M39: =S39+X39 -> 78334 | N39: =L39/M39 -> 0.24135752 | O39: =IF($J39="Too early",J39,J39*AB39/M39) -> Too early | P39: 312 | Q39: =IF(B39<7,(P39/VLOOKUP(B39,'Sales Pacing'!$A$23:$E$36,2)),"Too early") -> Too early | R39: 18906.5 | S39: 78334 | T39: =IF(R39>0,R39/S39,"") -> 0.24135752 | U39: =IF($Q39="Too early",Q39,Q39*AB39/S39) -> Too early | Y39: =IF(W39>0,W39/X39,"") | Z39: 1433 | AA39: =I39/Z39 -> 0.21772505 | AB39: =L39/I39 -> 60.597756 | AF39: 17711 | AG39: =L39-AF39 -> 1195.5
A40: 14 | B40: =A40-$G$4 -> 14 | C40: 45992 | D40: 26 Handel's Messiah | G40: 45998.583 | H40: Holiday | I40: =P40+V40 -> 304 | J40: =IF(Q40="Too early",Q40,Q40+V40) -> Too early | K40: =IF(J40="Too early",J40,J40/Z40) -> Too early | L40: =R40+W40 -> 16445 | M40: =S40+X40 -> 78333 | N40: =L40/M40 -> 0.20993706 | O40: =IF($J40="Too early",J40,J40*AB40/M40) -> Too early | P40: 304 | Q40: =IF(B40<7,(P40/VLOOKUP(B40,'Sales Pacing'!$A$23:$E$36,2)),"Too early") -> Too early | R40: 16445 | S40: 78333 | T40: =IF(R40>0,R40/S40,"") -> 0.20993706 | U40: =IF($Q40="Too early",Q40,Q40*AB40/S40) -> Too early | Y40: =IF(W40>0,W40/X40,"") | Z40: 1433 | AA40: =I40/Z40 -> 0.21214236 | AB40: =L40/I40 -> 54.095395 | AF40: 15287 | AG40: =L40-AF40 -> 1158
A41: 15 | B41: =A41-$G$4 -> 15 | C41: 45999 | D41: 26 Leslie Odom Jr.: Christmas | G41: 46003.792 | H41: Specials | I41: =P41+V41 -> 906 | J41: =IF(Q41="Too early",Q41,Q41+V41) -> Too early | K41: =IF(J41="Too early",J41,J41/Z41) -> Too early | L41: =R41+W41 -> 93212 | M41: =S41+X41 -> 150000 | N41: =L41/M41 -> 0.62141333 | O41: =IF($J41="Too early",J41,J41*AB41/M41) -> Too early | P41: 906 | Q41: =IF(B41<7,(P41/VLOOKUP(B41,'Sales Pacing'!$A$23:$E$36,2)),"Too early") -> Too early | R41: 93212 | S41: 150000 | T41: =IF(R41>0,R41/S41,"") -> 0.62141333 | U41: =IF($Q41="Too early",Q41,Q41*AB41/S41) -> Too early | Y41: =IF(W41>0,W41/X41,"") | Z41: 1590 | AA41: =I41/Z41 -> 0.56981132 | AB41: =L41/I41 -> 102.883 | AF41: 84030 | AG41: =L41-AF41 -> 9182
A42: 15 | B42: =A42-$G$4 -> 15 | C42: 45999 | D42: 26 Leslie Odom Jr.: Christmas | G42: 46004.792 | H42: Specials | I42: =P42+V42 -> 1102 | J42: =IF(Q42="Too early",Q42,Q42+V42) -> Too early | K42: =IF(J42="Too early",J42,J42/Z42) -> Too early | L42: =R42+W42 -> 111247 | M42: =S42+X42 -> 150000 | N42: =L42/M42 -> 0.74164667 | O42: =IF($J42="Too early",J42,J42*AB42/M42) -> Too early | P42: 1102 | Q42: =IF(B42<7,(P42/VLOOKUP(B42,'Sales Pacing'!$A$23:$E$36,2)),"Too early") -> Too early | R42: 111247 | S42: 150000 | T42: =IF(R42>0,R42/S42,"") -> 0.74164667 | U42: =IF($Q42="Too early",Q42,Q42*AB42/S42) -> Too early | Y42: =IF(W42>0,W42/X42,"") | Z42: 1590 | AA42: =I42/Z42 -> 0.69308176 | AB42: =L42/I42 -> 100.95009 | AF42: 107694 | AG42: =L42-AF42 -> 3553
A43: 16 | B43: =A43-$G$4 -> 16 | C43: 46006 | D43: 26 Christmas Festival | G43: 46009.792 | H43: Holiday | I43: =P43+V43 -> 205 | J43: =IF(Q43="Too early",Q43,Q43+V43) -> Too early | K43: =IF(J43="Too early",J43,J43/Z43) -> Too early | L43: =R43+W43 -> 12314 | M43: =S43+X43 -> 75833 | N43: =L43/M43 -> 0.16238313 | O43: =IF($J43="Too early",J43,J43*AB43/M43) -> Too early | P43: 205 | Q43: =IF(B43<7,(P43/VLOOKUP(B43,'Sales Pacing'!$A$23:$E$36,2)),"Too early") -> Too early | R43: 12314 | S43: 75833 | T43: =IF(R43>0,R43/S43,"") -> 0.16238313 | U43: =IF($Q43="Too early",Q43,Q43*AB43/S43) -> Too early | Y43: =IF(W43>0,W43/X43,"") | Z43: 1433 | AA43: =I43/Z43 -> 0.14305652 | AB43: =L43/I43 -> 60.068293 | AF43: 10629 | AG43: =L43-AF43 -> 1685
A44: 16 | B44: =A44-$G$4 -> 16 | C44: 46006 | D44: 26 Christmas Festival | G44: 46010.792 | H44: Holiday | I44: =P44+V44 -> 176 | J44: =IF(Q44="Too early",Q44,Q44+V44) -> Too early | K44: =IF(J44="Too early",J44,J44/Z44) -> Too early | L44: =R44+W44 -> 10536.5 | M44: =S44+X44 -> 75833 | N44: =L44/M44 -> 0.13894347 | O44: =IF($J44="Too early",J44,J44*AB44/M44) -> Too early | P44: 176 | Q44: =IF(B44<7,(P44/VLOOKUP(B44,'Sales Pacing'!$A$23:$E$36,2)),"Too early") -> Too early | R44: 10536.5 | S44: 75833 | T44: =IF(R44>0,R44/S44,"") -> 0.13894347 | U44: =IF($Q44="Too early",Q44,Q44*AB44/S44) -> Too early | Y44: =IF(W44>0,W44/X44,"") | Z44: 1433 | AA44: =I44/Z44 -> 0.12281926 | AB44: =L44/I44 -> 59.866477 | AF44: 10266 | AG44: =L44-AF44 -> 270.5
A45: 16 | B45: =A45-$G$4 -> 16 | C45: 46006 | D45: 26 Christmas Festival | G45: 46011.542 | H45: Holiday | I45: =P45+V45 -> 309 | J45: =IF(Q45="Too early",Q45,Q45+V45) -> Too early | K45: =IF(J45="Too early",J45,J45/Z45) -> Too early | L45: =R45+W45 -> 19202.5 | M45: =S45+X45 -> 75833 | N45: =L45/M45 -> 0.25322089 | O45: =IF($J45="Too early",J45,J45*AB45/M45) -> Too early | P45: 309 | Q45: =IF(B45<7,(P45/VLOOKUP(B45,'Sales Pacing'!$A$23:$E$36,2)),"Too early") -> Too early | R45: 19202.5 | S45: 75833 | T45: =IF(R45>0,R45/S45,"") -> 0.25322089 | U45: =IF($Q45="Too early",Q45,Q45*AB45/S45) -> Too early | Y45: =IF(W45>0,W45/X45,"") | Z45: 1433 | AA45: =I45/Z45 -> 0.21563154 | AB45: =L45/I45 -> 62.144013 | AF45: 17862 | AG45: =L45-AF45 -> 1340.5
A46: 16 | B46: =A46-$G$4 -> 16 | C46: 46006 | D46: 26 Christmas Festival | G46: 46011.792 | H46: Holiday | I46: =P46+V46 -> 188 | J46: =IF(Q46="Too early",Q46,Q46+V46) -> Too early | K46: =IF(J46="Too early",J46,J46/Z46) -> Too early | L46: =R46+W46 -> 11774.5 | M46: =S46+X46 -> 75833 | N46: =L46/M46 -> 0.15526881 | O46: =IF($J46="Too early",J46,J46*AB46/M46) -> Too early | P46: 188 | Q46: =IF(B46<7,(P46/VLOOKUP(B46,'Sales Pacing'!$A$23:$E$36,2)),"Too early") -> Too early | R46: 11774.5 | S46: 75833 | T46: =IF(R46>0,R46/S46,"") -> 0.15526881 | U46: =IF($Q46="Too early",Q46,Q46*AB46/S46) -> Too early | Y46: =IF(W46>0,W46/X46,"") | Z46: 1433 | AA46: =I46/Z46 -> 0.1311933 | AB46: =L46/I46 -> 62.630319 | AF46: 11104 | AG46: =L46-AF46 -> 670.5
A47: 16 | B47: =A47-$G$4 -> 16 | C47: 46006 | D47: 26 Christmas Festival | G47: 46012.583 | H47: Holiday | I47: =P47+V47 -> 639 | J47: =IF(Q47="Too early",Q47,Q47+V47) -> Too early | K47: =IF(J47="Too early",J47,J47/Z47) -> Too early | L47: =R47+W47 -> 20010 | M47: =S47+X47 -> 88284 | N47: =L47/M47 -> 0.22665489 | O47: =IF($J47="Too early",J47,J47*AB47/M47) -> Too early | P47: 343 | Q47: =IF(B47<7,(P47/VLOOKUP(B47,'Sales Pacing'!$A$23:$E$36,2)),"Too early") -> Too early | R47: 13464 | S47: 75834 | T47: =IF(R47>0,R47/S47,"") -> 0.17754569 | U47: =IF($Q47="Too early",Q47,Q47*AB47/S47) -> Too early | V47: 296 | W47: 6546 | X47: 12450 | Y47: =IF(W47>0,W47/X47,"") -> 0.52578313 | Z47: 1433 | AA47: =I47/Z47 -> 0.44591766 | AB47: =L47/I47 -> 31.314554 | AF47: 18644 | AG47: =L47-AF47 -> 1366
A48: 16 | B48: =A48-$G$4 -> 16 | C48: 46006 | D48: 26 Christmas Festival | G48: 46012.792 | H48: Holiday | I48: =P48+V48 -> 115 | J48: =IF(Q48="Too early",Q48,Q48+V48) -> Too early | K48: =IF(J48="Too early",J48,J48/Z48) -> Too early | L48: =R48+W48 -> 6226 | M48: =S48+X48 -> 75834 | N48: =L48/M48 -> 0.082100377 | O48: =IF($J48="Too early",J48,J48*AB48/M48) -> Too early | P48: 115 | Q48: =IF(B48<7,(P48/VLOOKUP(B48,'Sales Pacing'!$A$23:$E$36,2)),"Too early") -> Too early | R48: 6226 | S48: 75834 | T48: =IF(R48>0,R48/S48,"") -> 0.082100377 | U48: =IF($Q48="Too early",Q48,Q48*AB48/S48) -> Too early | Y48: =IF(W48>0,W48/X48,"") | Z48: 1433 | AA48: =I48/Z48 -> 0.080251221 | AB48: =L48/I48 -> 54.13913 | AF48: 5259 | AG48: =L48-AF48 -> 967
A49: 17 | B49: =A49-$G$4 -> 17 | C49: 46013 | D49: 26 It's a Wonderful Life | G49: 46014.792 | H49: Specials/Film | I49: =P49+V49 -> 739 | J49: =IF(Q49="Too early",Q49,Q49+V49) -> Too early | K49: =IF(J49="Too early",J49,J49/Z49) -> Too early | L49: =R49+W49 -> 56307.6 | M49: =S49+X49 -> 100000 | N49: =L49/M49 -> 0.563076 | O49: =IF($J49="Too early",J49,J49*AB49/M49) -> Too early | P49: 739 | Q49: =IF(B49<7,(P49/VLOOKUP(B49,'Sales Pacing'!$A$23:$E$36,2)),"Too early") -> Too early | R49: 56307.6 | S49: 100000 | T49: =IF(R49>0,R49/S49,"") -> 0.563076 | U49: =IF($Q49="Too early",Q49,Q49*AB49/S49) -> Too early | Y49: =IF(W49>0,W49/X49,"") | Z49: 1302 | AA49: =I49/Z49 -> 0.56758833 | AB49: =L49/I49 -> 76.194317 | AF49: 54169 | AG49: =L49-AF49 -> 2138.6
A50: 17 | B50: =A50-$G$4 -> 17 | C50: 46013 | D50: 26 It's a Wonderful Life | G50: 46015.458 | H50: Specials/Film | I50: =P50+V50 -> 185 | J50: =IF(Q50="Too early",Q50,Q50+V50) -> Too early | K50: =IF(J50="Too early",J50,J50/Z50) -> Too early | L50: =R50+W50 -> 12668.8 | M50: =S50+X50 -> 100000 | N50: =L50/M50 -> 0.126688 | O50: =IF($J50="Too early",J50,J50*AB50/M50) -> Too early | P50: 185 | Q50: =IF(B50<7,(P50/VLOOKUP(B50,'Sales Pacing'!$A$23:$E$36,2)),"Too early") -> Too early | R50: 12668.8 | S50: 100000 | T50: =IF(R50>0,R50/S50,"") -> 0.126688 | U50: =IF($Q50="Too early",Q50,Q50*AB50/S50) -> Too early | Y50: =IF(W50>0,W50/X50,"") | Z50: 1302 | AA50: =I50/Z50 -> 0.14208909 | AB50: =L50/I50 -> 68.48 | AF50: 11770 | AG50: =L50-AF50 -> 898.8
A51: 18 | B51: =A51-$G$4 -> 18 | C51: 46020 | D51: OPEN | I51: =P51+V51 -> 0 | J51: =IF(Q51="Too early",Q51,Q51+V51) -> Too early | L51: =R51+W51 -> 0 | M51: =S51+X51 -> 0 | N51: =L51/M51 -> #DIV/0! | Q51: =IF(B51<7,(P51/VLOOKUP(B51,'Sales Pacing'!$A$23:$E$36,2)),"Too early") -> Too early | T51: =IF(R51>0,R51/S51,"") | Y51: N/A | AA51: =I51/Z51 -> #DIV/0! | AB51: =L51/I51 -> #DIV/0! | AF51: 0
A52: 19 | B52: =A52-$G$4 -> 19 | C52: 46027 | D52: 26 CS04 Brahms' Fourth Symphony | G52: 46031.833 | H52: Classical | I52: =P52+V52 -> 592 | J52: =IF(Q52="Too early",Q52,Q52+V52) -> Too early | K52: =IF(J52="Too early",J52,J52/Z52) -> Too early | L52: =R52+W52 -> 39270.3 | M52: =S52+X52 -> 54999 | N52: =L52/M52 -> 0.71401844 | O52: =IF($J52="Too early",J52,J52*AB52/M52) -> Too early | P52: 23 | Q52: =IF(B52<7,(P52/VLOOKUP(B52,'Sales Pacing'!$A$23:$E$36,2)),"Too early") -> Too early | R52: 866 | S52: 21666 | T52: =IF(R52>0,R52/S52,"") -> 0.039970461 | U52: =IF($Q52="Too early",Q52,Q52*AB52/S52) -> Too early | V52: 569 | W52: 38404.3 | X52: 33333 | Y52: =IF(W52>0,W52/X52,"") -> 1.1521405 | Z52: 1590 | AA52: =I52/Z52 -> 0.37232704 | AB52: =L52/I52 -> 66.334966 | AF52: 39270.3 | AG52: =L52-AF52 -> 0
A53: 19 | B53: =A53-$G$4 -> 19 | C53: 46027 | D53: 27 CS04 Brahms' Fourth Symphony | G53: 46032.833 | H53: Classical | I53: =P53+V53 -> 606 | J53: =IF(Q53="Too early",Q53,Q53+V53) -> Too early | K53: =IF(J53="Too early",J53,J53/Z53) -> Too early | L53: =R53+W53 -> 38930 | M53: =S53+X53 -> 54999 | N53: =L53/M53 -> 0.70783105 | O53: =IF($J53="Too early",J53,J53*AB53/M53) -> Too early | P53: 46 | Q53: =IF(B53<7,(P53/VLOOKUP(B53,'Sales Pacing'!$A$23:$E$36,2)),"Too early") -> Too early | R53: 2309 | S53: 21666 | T53: =IF(R53>0,R53/S53,"") -> 0.10657251 | U53: =IF($Q53="Too early",Q53,Q53*AB53/S53) -> Too early | V53: 560 | W53: 36621 | X53: 33333 | Y53: =IF(W53>0,W53/X53,"") -> 1.098641 | Z53: 1590 | AA53: =I53/Z53 -> 0.38113208 | AB53: =L53/I53 -> 64.240924 | AF53: 38441.8 | AG53: =L53-AF53 -> 488.2
A54: 19 | B54: =A54-$G$4 -> 19 | C54: 46027 | D54: 28 CS04 Brahms' Fourth Symphony | G54: 46033.583 | H54: Classical | I54: =P54+V54 -> 602 | J54: =IF(Q54="Too early",Q54,Q54+V54) -> Too early | K54: =IF(J54="Too early",J54,J54/Z54) -> Too early | L54: =R54+W54 -> 38853.5 | M54: =S54+X54 -> 55000 | N54: =L54/M54 -> 0.70642727 | O54: =IF($J54="Too early",J54,J54*AB54/M54) -> Too early | P54: 45 | Q54: =IF(B54<7,(P54/VLOOKUP(B54,'Sales Pacing'!$A$23:$E$36,2)),"Too early") -> Too early | R54: 2590 | S54: 21666 | T54: =IF(R54>0,R54/S54,"") -> 0.11954214 | U54: =IF($Q54="Too early",Q54,Q54*AB54/S54) -> Too early | V54: 557 | W54: 36263.5 | X54: 33334 | Y54: =IF(W54>0,W54/X54,"") -> 1.0878832 | Z54: 1590 | AA54: =I54/Z54 -> 0.37861635 | AB54: =L54/I54 -> 64.540698 | AF54: 38579.1 | AG54: =L54-AF54 -> 274.4
A55: 20 | B55: =A55-$G$4 -> 20 | C55: 46034 | D55: 26 CS05 Pines of Rome & Bruch | G55: 46038.833 | H55: Classical | I55: =P55+V55 -> 409 | J55: =IF(Q55="Too early",Q55,Q55+V55) -> Too early | K55: =IF(J55="Too early",J55,J55/Z55) -> Too early | L55: =R55+W55 -> 28064 | M55: =S55+X55 -> 60000 | N55: =L55/M55 -> 0.46773333 | O55: =IF($J55="Too early",J55,J55*AB55/M55) -> Too early | P55: 43 | Q55: =IF(B55<7,(P55/VLOOKUP(B55,'Sales Pacing'!$A$23:$E$36,2)),"Too early") -> Too early | R55: 2632 | S55: 30000 | T55: =IF(R55>0,R55/S55,"") -> 0.087733333 | U55: =IF($Q55="Too early",Q55,Q55*AB55/S55) -> Too early | V55: 366 | W55: 25432 | X55: 30000 | Y55: =IF(W55>0,W55/X55,"") -> 0.84773333 | Z55: 1590 | AA55: =I55/Z55 -> 0.2572327 | AB55: =L55/I55 -> 68.616137 | AF55: 27996 | AG55: =L55-AF55 -> 68
A56: 20 | B56: =A56-$G$4 -> 20 | C56: 46034 | D56: 26 CS05 Pines of Rome & Bruch | G56: 46039.833 | H56: Classical | I56: =P56+V56 -> 683 | J56: =IF(Q56="Too early",Q56,Q56+V56) -> Too early | K56: =IF(J56="Too early",J56,J56/Z56) -> Too early | L56: =R56+W56 -> 45570.9 | M56: =S56+X56 -> 75000 | N56: =L56/M56 -> 0.607612 | O56: =IF($J56="Too early",J56,J56*AB56/M56) -> Too early | P56: 96 | Q56: =IF(B56<7,(P56/VLOOKUP(B56,'Sales Pacing'!$A$23:$E$36,2)),"Too early") -> Too early | R56: 5503 | S56: 20000 | T56: =IF(R56>0,R56/S56,"") -> 0.27515 | U56: =IF($Q56="Too early",Q56,Q56*AB56/S56) -> Too early | V56: 587 | W56: 40067.9 | X56: 55000 | Y56: =IF(W56>0,W56/X56,"") -> 0.72850727 | Z56: 1590 | AA56: =I56/Z56 -> 0.42955975 | AB56: =L56/I56 -> 66.721669 | AF56: 44908.4 | AG56: =L56-AF56 -> 662.5
A57: 20 | B57: =A57-$G$4 -> 20 | C57: 46034 | D57: 26 CS05 Pines of Rome & Bruch | G57: 46040.583 | H57: Classical | I57: =P57+V57 -> 686 | J57: =IF(Q57="Too early",Q57,Q57+V57) -> Too early | K57: =IF(J57="Too early",J57,J57/Z57) -> Too early | L57: =R57+W57 -> 43967.2 | M57: =S57+X57 -> 75000 | N57: =L57/M57 -> 0.58622933 | O57: =IF($J57="Too early",J57,J57*AB57/M57) -> Too early | P57: 80 | Q57: =IF(B57<7,(P57/VLOOKUP(B57,'Sales Pacing'!$A$23:$E$36,2)),"Too early") -> Too early | R57: 5029 | S57: 20000 | T57: =IF(R57>0,R57/S57,"") -> 0.25145 | U57: =IF($Q57="Too early",Q57,Q57*AB57/S57) -> Too early | V57: 606 | W57: 38938.2 | X57: 55000 | Y57: =IF(W57>0,W57/X57,"") -> 0.70796727 | Z57: 1590 | AA57: =I57/Z57 -> 0.43144654 | AB57: =L57/I57 -> 64.092128 | AF57: 43743.2 | AG57: =L57-AF57 -> 224
A58: 21 | B58: =A58-$G$4 -> 21 | C58: 46041 | D58: 26 Indiana Jones: Raiders Lost | G58: 46044.792 | H58: Specials/Film | I58: =P58+V58 -> 119 | J58: =IF(Q58="Too early",Q58,Q58+V58) -> Too early | K58: =IF(J58="Too early",J58,J58/Z58) -> Too early | L58: =R58+W58 -> 7049 | M58: =S58+X58 -> 90000 | N58: =L58/M58 -> 0.078322222 | O58: =IF($J58="Too early",J58,J58*AB58/M58) -> Too early | P58: 119 | Q58: =IF(B58<7,(P58/VLOOKUP(B58,'Sales Pacing'!$A$23:$E$36,2)),"Too early") -> Too early | R58: 7049 | S58: 90000 | T58: =IF(R58>0,R58/S58,"") -> 0.078322222 | U58: =IF($Q58="Too early",Q58,Q58*AB58/S58) -> Too early | Y58: =IF(W58>0,W58/X58,"") | Z58: 1302 | AA58: =I58/Z58 -> 0.091397849 | AB58: =L58/I58 -> 59.235294 | AF58: 6949 | AG58: =L58-AF58 -> 100
A59: 21 | B59: =A59-$G$4 -> 21 | C59: 46041 | D59: 26 Indiana Jones: Raiders Lost | G59: 46045.792 | H59: Specials/Film | I59: =P59+V59 -> 293 | J59: =IF(Q59="Too early",Q59,Q59+V59) -> Too early | K59: =IF(J59="Too early",J59,J59/Z59) -> Too early | L59: =R59+W59 -> 21081.9 | M59: =S59+X59 -> 90000 | N59: =L59/M59 -> 0.23424333 | O59: =IF($J59="Too early",J59,J59*AB59/M59) -> Too early | P59: 293 | Q59: =IF(B59<7,(P59/VLOOKUP(B59,'Sales Pacing'!$A$23:$E$36,2)),"Too early") -> Too early | R59: 21081.9 | S59: 90000 | T59: =IF(R59>0,R59/S59,"") -> 0.23424333 | U59: =IF($Q59="Too early",Q59,Q59*AB59/S59) -> Too early | Y59: =IF(W59>0,W59/X59,"") | Z59: 1302 | AA59: =I59/Z59 -> 0.2250384 | AB59: =L59/I59 -> 71.951877 | AF59: 19900 | AG59: =L59-AF59 -> 1181.9
A60: 21 | B60: =A60-$G$4 -> 21 | C60: 46041 | D60: 26 Indiana Jones: Raiders Lost | G60: 46046.792 | H60: Specials/Film | I60: =P60+V60 -> 435 | J60: =IF(Q60="Too early",Q60,Q60+V60) -> Too early | K60: =IF(J60="Too early",J60,J60/Z60) -> Too early | L60: =R60+W60 -> 31818.1 | M60: =S60+X60 -> 90000 | N60: =L60/M60 -> 0.35353444 | O60: =IF($J60="Too early",J60,J60*AB60/M60) -> Too early | P60: 435 | Q60: =IF(B60<7,(P60/VLOOKUP(B60,'Sales Pacing'!$A$23:$E$36,2)),"Too early") -> Too early | R60: 31818.1 | S60: 90000 | T60: =IF(R60>0,R60/S60,"") -> 0.35353444 | U60: =IF($Q60="Too early",Q60,Q60*AB60/S60) -> Too early | Y60: =IF(W60>0,W60/X60,"") | Z60: 1302 | AA60: =I60/Z60 -> 0.33410138 | AB60: =L60/I60 -> 73.145057 | AF60: 31343 | AG60: =L60-AF60 -> 475.1
A61: 21 | B61: =A61-$G$4 -> 21 | C61: 46041 | D61: 26 Indiana Jones: Raiders Lost | G61: 46047.583 | H61: Specials/Film | I61: =P61+V61 -> 331 | J61: =IF(Q61="Too early",Q61,Q61+V61) -> Too early | K61: =IF(J61="Too early",J61,J61/Z61) -> Too early | L61: =R61+W61 -> 22975.6 | M61: =S61+X61 -> 90000 | N61: =L61/M61 -> 0.25528444 | O61: =IF($J61="Too early",J61,J61*AB61/M61) -> Too early | P61: 331 | Q61: =IF(B61<7,(P61/VLOOKUP(B61,'Sales Pacing'!$A$23:$E$36,2)),"Too early") -> Too early | R61: 22975.6 | S61: 90000 | T61: =IF(R61>0,R61/S61,"") -> 0.25528444 | U61: =IF($Q61="Too early",Q61,Q61*AB61/S61) -> Too early | Y61: =IF(W61>0,W61/X61,"") | Z61: 1302 | AA61: =I61/Z61 -> 0.25422427 | AB61: =L61/I61 -> 69.412689 | AF61: 22301 | AG61: =L61-AF61 -> 674.6
A62: 22 | B62: =A62-$G$4 -> 22 | C62: 46048 | D62: 26 CS06 Beethoven+ | G62: 46052.833 | H62: Classical | I62: =P62+V62 -> 419 | J62: =IF(Q62="Too early",Q62,Q62+V62) -> Too early | K62: =IF(J62="Too early",J62,J62/Z62) -> Too early | L62: =R62+W62 -> 28258 | M62: =S62+X62 -> 54000 | N62: =L62/M62 -> 0.5232963 | O62: =IF($J62="Too early",J62,J62*AB62/M62) -> Too early | P62: 55 | Q62: =IF(B62<7,(P62/VLOOKUP(B62,'Sales Pacing'!$A$23:$E$36,2)),"Too early") -> Too early | R62: 3097 | S62: 24000 | T62: =IF(R62>0,R62/S62,"") -> 0.12904167 | U62: =IF($Q62="Too early",Q62,Q62*AB62/S62) -> Too early | V62: 364 | W62: 25161 | X62: 30000 | Y62: =IF(W62>0,W62/X62,"") -> 0.8387 | Z62: 1590 | AA62: =I62/Z62 -> 0.26352201 | AB62: =L62/I62 -> 67.441527 | AF62: 28360 | AG62: =L62-AF62 -> -102
A63: 22 | B63: =A63-$G$4 -> 22 | C63: 46048 | D63: 26 CS06 Beethoven+ | G63: 46053.833 | H63: Classical | I63: =P63+V63 -> 653 | J63: =IF(Q63="Too early",Q63,Q63+V63) -> Too early | K63: =IF(J63="Too early",J63,J63/Z63) -> Too early | L63: =R63+W63 -> 43482.9 | M63: =S63+X63 -> 75000 | N63: =L63/M63 -> 0.579772 | O63: =IF($J63="Too early",J63,J63*AB63/M63) -> Too early | P63: 65 | Q63: =IF(B63<7,(P63/VLOOKUP(B63,'Sales Pacing'!$A$23:$E$36,2)),"Too early") -> Too early | R63: 3808 | S63: 20000 | T63: =IF(R63>0,R63/S63,"") -> 0.1904 | U63: =IF($Q63="Too early",Q63,Q63*AB63/S63) -> Too early | V63: 588 | W63: 39674.9 | X63: 55000 | Y63: =IF(W63>0,W63/X63,"") -> 0.72136182 | Z63: 1590 | AA63: =I63/Z63 -> 0.41069182 | AB63: =L63/I63 -> 66.589433 | AF63: 43043.4 | AG63: =L63-AF63 -> 439.5
A64: 22 | B64: =A64-$G$4 -> 22 | C64: 46048 | D64: 26 CS06 Beethoven+ | G64: 46054.583 | H64: Classical | I64: =P64+V64 -> 658 | J64: =IF(Q64="Too early",Q64,Q64+V64) -> Too early | K64: =IF(J64="Too early",J64,J64/Z64) -> Too early | L64: =R64+W64 -> 41792.2 | M64: =S64+X64 -> 75000 | N64: =L64/M64 -> 0.55722933 | O64: =IF($J64="Too early",J64,J64*AB64/M64) -> Too early | P64: 52 | Q64: =IF(B64<7,(P64/VLOOKUP(B64,'Sales Pacing'!$A$23:$E$36,2)),"Too early") -> Too early | R64: 2972 | S64: 20000 | T64: =IF(R64>0,R64/S64,"") -> 0.1486 | U64: =IF($Q64="Too early",Q64,Q64*AB64/S64) -> Too early | V64: 606 | W64: 38820.2 | X64: 55000 | Y64: =IF(W64>0,W64/X64,"") -> 0.70582182 | Z64: 1590 | AA64: =I64/Z64 -> 0.41383648 | AB64: =L64/I64 -> 63.513982 | AF64: 41906.2 | AG64: =L64-AF64 -> -114
A65: 23 | B65: =A65-$G$4 -> 23 | C65: 46055 | D65: 26 On-Stage 2 | G65: 46058.833 | H65: On Stage | I65: =P65+V65 -> 19 | J65: =IF(Q65="Too early",Q65,Q65+V65) -> Too early | K65: =IF(J65="Too early",J65,J65/Z65) -> Too early | L65: =R65+W65 -> 1960 | M65: 9000 | N65: =L65/M65 -> 0.21777778 | O65: =IF($J65="Too early",J65,J65*AB65/M65) -> Too early | P65: 19 | Q65: =IF(B65<7,(P65/VLOOKUP(B65,'Sales Pacing'!$A$23:$E$36,2)),"Too early") -> Too early | R65: 1960 | S65: 9000 | T65: =IF(R65>0,R65/S65,"") -> 0.21777778 | U65: =IF($Q65="Too early",Q65,Q65*AB65/S65) -> Too early | Y65: =IF(W65>0,W65/X65,"") | Z65: 100 | AA65: =I65/Z65 -> 0.19 | AB65: =L65/I65 -> 103.15789 | AF65: 1960 | AG65: =L65-AF65 -> 0
A66: 23 | B66: =A66-$G$4 -> 23 | C66: 46055 | D66: 26 CS07 Prokofiev's Fifth Symphony | G66: 46059.833 | H66: Classical | I66: =P66+V66 -> 597 | J66: =IF(Q66="Too early",Q66,Q66+V66) -> Too early | K66: =IF(J66="Too early",J66,J66/Z66) -> Too early | L66: =R66+W66 -> 39385.3 | M66: =S66+X66 -> 46666 | N66: =L66/M66 -> 0.84398277 | O66: =IF($J66="Too early",J66,J66*AB66/M66) -> Too early | P66: 36 | Q66: =IF(B66<7,(P66/VLOOKUP(B66,'Sales Pacing'!$A$23:$E$36,2)),"Too early") -> Too early | R66: 1794 | S66: 13333 | T66: =IF(R66>0,R66/S66,"") -> 0.13455336 | U66: =IF($Q66="Too early",Q66,Q66*AB66/S66) -> Too early | V66: 561 | W66: 37591.3 | X66: 33333 | Y66: =IF(W66>0,W66/X66,"") -> 1.1277503 | Z66: 1590 | AA66: =I66/Z66 -> 0.3754717 | AB66: =L66/I66 -> 65.972027 | AF66: 39385.3 | AG66: =L66-AF66 -> 0
A67: 23 | B67: =A67-$G$4 -> 23 | C67: 46055 | D67: 27 CS07 Prokofiev's Fifth Symphony | G67: 46060.833 | H67: Classical | I67: =P67+V67 -> 604 | J67: =IF(Q67="Too early",Q67,Q67+V67) -> Too early | K67: =IF(J67="Too early",J67,J67/Z67) -> Too early | L67: =R67+W67 -> 38740.2 | M67: =S67+X67 -> 46666 | N67: =L67/M67 -> 0.830159 | O67: =IF($J67="Too early",J67,J67*AB67/M67) -> Too early | P67: 42 | Q67: =IF(B67<7,(P67/VLOOKUP(B67,'Sales Pacing'!$A$23:$E$36,2)),"Too early") -> Too early | R67: 2063 | S67: 13333 | T67: =IF(R67>0,R67/S67,"") -> 0.15472887 | U67: =IF($Q67="Too early",Q67,Q67*AB67/S67) -> Too early | V67: 562 | W67: 36677.2 | X67: 33333 | Y67: =IF(W67>0,W67/X67,"") -> 1.100327 | Z67: 1590 | AA67: =I67/Z67 -> 0.37987421 | AB67: =L67/I67 -> 64.139404 | AF67: 38633 | AG67: =L67-AF67 -> 107.2
A68: 23 | B68: =A68-$G$4 -> 23 | C68: 46055 | D68: 28 CS07 Prokofiev's Fifth Symphony | G68: 46061.583 | H68: Classical | I68: =P68+V68 -> 586 | J68: =IF(Q68="Too early",Q68,Q68+V68) -> Too early | K68: =IF(J68="Too early",J68,J68/Z68) -> Too early | L68: =R68+W68 -> 37115.1 | M68: =S68+X68 -> 46667 | N68: =L68/M68 -> 0.79531789 | O68: =IF($J68="Too early",J68,J68*AB68/M68) -> Too early | P68: 38 | Q68: =IF(B68<7,(P68/VLOOKUP(B68,'Sales Pacing'!$A$23:$E$36,2)),"Too early") -> Too early | R68: 1414 | S68: 13333 | T68: =IF(R68>0,R68/S68,"") -> 0.10605265 | U68: =IF($Q68="Too early",Q68,Q68*AB68/S68) -> Too early | V68: 548 | W68: 35701.1 | X68: 33334 | Y68: =IF(W68>0,W68/X68,"") -> 1.0710116 | Z68: 1590 | AA68: =I68/Z68 -> 0.36855346 | AB68: =L68/I68 -> 63.336348 | AF68: 36686.7 | AG68: =L68-AF68 -> 428.4
A69: 24 | B69: =A69-$G$4 -> 24 | C69: 46062 | D69: 26 Chris Thile | G69: 46065.792 | H69: Specials | I69: =P69+V69 -> 300 | J69: =IF(Q69="Too early",Q69,Q69+V69) -> Too early | K69: =IF(J69="Too early",J69,J69/Z69) -> Too early | L69: =R69+W69 -> 26522 | M69: =S69+X69 -> 128900 | N69: =L69/M69 -> 0.2057564 | O69: =IF($J69="Too early",J69,J69*AB69/M69) -> Too early | P69: 300 | Q69: =IF(B69<7,(P69/VLOOKUP(B69,'Sales Pacing'!$A$23:$E$36,2)),"Too early") -> Too early | R69: 26522 | S69: 128900 | T69: =IF(R69>0,R69/S69,"") -> 0.2057564 | U69: =IF($Q69="Too early",Q69,Q69*AB69/S69) -> Too early | Y69: =IF(W69>0,W69/X69,"") | Z69: 1590 | AA69: =I69/Z69 -> 0.18867925 | AB69: =L69/I69 -> 88.406667 | AF69: 25984 | AG69: =L69-AF69 -> 538
A70: 24 | B70: =A70-$G$4 -> 24 | C70: 46062 | D70: 26 PS3 She's Got Soul | G70: 46066.833 | H70: Pops | I70: =P70+V70 -> 769 | J70: =IF(Q70="Too early",Q70,Q70+V70) -> Too early | K70: =IF(J70="Too early",J70,J70/Z70) -> Too early | L70: =R70+W70 -> 54995.3 | M70: =S70+X70 -> 94666 | N70: =L70/M70 -> 0.58094036 | O70: =IF($J70="Too early",J70,J70*AB70/M70) -> Too early | P70: 54 | Q70: =IF(B70<7,(P70/VLOOKUP(B70,'Sales Pacing'!$A$23:$E$36,2)),"Too early") -> Too early | R70: 3320 | S70: 53333 | T70: =IF(R70>0,R70/S70,"") -> 0.062250389 | U70: =IF($Q70="Too early",Q70,Q70*AB70/S70) -> Too early | V70: 715 | W70: 51675.3 | X70: 41333 | Y70: =IF(W70>0,W70/X70,"") -> 1.250219 | Z70: 1590 | AA70: =I70/Z70 -> 0.4836478 | AB70: =L70/I70 -> 71.515345 | AF70: 54898.1 | AG70: =L70-AF70 -> 97.2
A71: 24 | B71: =A71-$G$4 -> 24 | C71: 46062 | D71: 26 PS3 She's Got Soul | G71: 46067.833 | H71: Pops | I71: =P71+V71 -> 696 | J71: =IF(Q71="Too early",Q71,Q71+V71) -> Too early | K71: =IF(J71="Too early",J71,J71/Z71) -> Too early | L71: =R71+W71 -> 49744.3 | M71: =S71+X71 -> 94667 | N71: =L71/M71 -> 0.52546611 | O71: =IF($J71="Too early",J71,J71*AB71/M71) -> Too early | P71: 42 | Q71: =IF(B71<7,(P71/VLOOKUP(B71,'Sales Pacing'!$A$23:$E$36,2)),"Too early") -> Too early | R71: 1935 | S71: 53333 | T71: =IF(R71>0,R71/S71,"") -> 0.036281477 | U71: =IF($Q71="Too early",Q71,Q71*AB71/S71) -> Too early | V71: 654 | W71: 47809.3 | X71: 41334 | Y71: =IF(W71>0,W71/X71,"") -> 1.156658 | Z71: 1590 | AA71: =I71/Z71 -> 0.43773585 | AB71: =L71/I71 -> 71.471695 | AF71: 49803.5 | AG71: =L71-AF71 -> -59.2
A72: 24 | B72: =A72-$G$4 -> 24 | C72: 46062 | D72: 26 PS3 She's Got Soul | G72: 46068.583 | H72: Pops | I72: =P72+V72 -> 432 | J72: =IF(Q72="Too early",Q72,Q72+V72) -> Too early | K72: =IF(J72="Too early",J72,J72/Z72) -> Too early | L72: =R72+W72 -> 29295.3 | M72: =S72+X72 -> 94666 | N72: =L72/M72 -> 0.30945957 | O72: =IF($J72="Too early",J72,J72*AB72/M72) -> Too early | P72: 51 | Q72: =IF(B72<7,(P72/VLOOKUP(B72,'Sales Pacing'!$A$23:$E$36,2)),"Too early") -> Too early | R72: 3277 | S72: 53333 | T72: =IF(R72>0,R72/S72,"") -> 0.061444134 | U72: =IF($Q72="Too early",Q72,Q72*AB72/S72) -> Too early | V72: 381 | W72: 26018.3 | X72: 41333 | Y72: =IF(W72>0,W72/X72,"") -> 0.62948008 | Z72: 1590 | AA72: =I72/Z72 -> 0.27169811 | AB72: =L72/I72 -> 67.813194 | AF72: 28718.3 | AG72: =L72-AF72 -> 577
A73: 25 | B73: =A73-$G$4 -> 25 | C73: 46069 | D73: 26 Harry Potter 2: Chamber | G73: 46072.792 | H73: Specials/Film | I73: =P73+V73 -> 124 | J73: =IF(Q73="Too early",Q73,Q73+V73) -> Too early | K73: =IF(J73="Too early",J73,J73/Z73) -> Too early | L73: =R73+W73 -> 8681.5 | M73: =S73+X73 -> 111250 | N73: =L73/M73 -> 0.078035955 | O73: =IF($J73="Too early",J73,J73*AB73/M73) -> Too early | P73: 124 | Q73: =IF(B73<7,(P73/VLOOKUP(B73,'Sales Pacing'!$A$23:$E$36,2)),"Too early") -> Too early | R73: 8681.5 | S73: 111250 | T73: =IF(R73>0,R73/S73,"") -> 0.078035955 | U73: =IF($Q73="Too early",Q73,Q73*AB73/S73) -> Too early | Y73: =IF(W73>0,W73/X73,"") | Z73: 1302 | AA73: =I73/Z73 -> 0.095238095 | AB73: =L73/I73 -> 70.012097 | AF73: 7356 | AG73: =L73-AF73 -> 1325.5
A74: 25 | B74: =A74-$G$4 -> 25 | C74: 46069 | D74: 26 Harry Potter 2: Chamber | G74: 46073.792 | H74: Specials/Film | I74: =P74+V74 -> 229 | J74: =IF(Q74="Too early",Q74,Q74+V74) -> Too early | K74: =IF(J74="Too early",J74,J74/Z74) -> Too early | L74: =R74+W74 -> 16868 | M74: =S74+X74 -> 111250 | N74: =L74/M74 -> 0.15162247 | O74: =IF($J74="Too early",J74,J74*AB74/M74) -> Too early | P74: 229 | Q74: =IF(B74<7,(P74/VLOOKUP(B74,'Sales Pacing'!$A$23:$E$36,2)),"Too early") -> Too early | R74: 16868 | S74: 111250 | T74: =IF(R74>0,R74/S74,"") -> 0.15162247 | U74: =IF($Q74="Too early",Q74,Q74*AB74/S74) -> Too early | Y74: =IF(W74>0,W74/X74,"") | Z74: 1302 | AA74: =I74/Z74 -> 0.17588326 | AB74: =L74/I74 -> 73.659389 | AF74: 16088 | AG74: =L74-AF74 -> 780
A75: 25 | B75: =A75-$G$4 -> 25 | C75: 46069 | D75: 26 Harry Potter 2: Chamber | G75: 46074.792 | H75: Specials/Film | I75: =P75+V75 -> 341 | J75: =IF(Q75="Too early",Q75,Q75+V75) -> Too early | K75: =IF(J75="Too early",J75,J75/Z75) -> Too early | L75: =R75+W75 -> 25816 | M75: =S75+X75 -> 111250 | N75: =L75/M75 -> 0.23205393 | O75: =IF($J75="Too early",J75,J75*AB75/M75) -> Too early | P75: 341 | Q75: =IF(B75<7,(P75/VLOOKUP(B75,'Sales Pacing'!$A$23:$E$36,2)),"Too early") -> Too early | R75: 25816 | S75: 111250 | T75: =IF(R75>0,R75/S75,"") -> 0.23205393 | U75: =IF($Q75="Too early",Q75,Q75*AB75/S75) -> Too early | Y75: =IF(W75>0,W75/X75,"") | Z75: 1302 | AA75: =I75/Z75 -> 0.26190476 | AB75: =L75/I75 -> 75.706745 | AF75: 24079 | AG75: =L75-AF75 -> 1737
A76: 25 | B76: =A76-$G$4 -> 25 | C76: 46069 | D76: 26 Harry Potter 2: Chamber | G76: 46075.583 | H76: Specials/Film | I76: =P76+V76 -> 397 | J76: =IF(Q76="Too early",Q76,Q76+V76) -> Too early | K76: =IF(J76="Too early",J76,J76/Z76) -> Too early | L76: =R76+W76 -> 28069 | M76: =S76+X76 -> 111250 | N76: =L76/M76 -> 0.25230562 | O76: =IF($J76="Too early",J76,J76*AB76/M76) -> Too early | P76: 397 | Q76: =IF(B76<7,(P76/VLOOKUP(B76,'Sales Pacing'!$A$23:$E$36,2)),"Too early") -> Too early | R76: 28069 | S76: 111250 | T76: =IF(R76>0,R76/S76,"") -> 0.25230562 | U76: =IF($Q76="Too early",Q76,Q76*AB76/S76) -> Too early | Y76: =IF(W76>0,W76/X76,"") | Z76: 1302 | AA76: =I76/Z76 -> 0.30491551 | AB76: =L76/I76 -> 70.702771 | AF76: 26759 | AG76: =L76-AF76 -> 1310
A77: 26 | B77: =A77-$G$4 -> 26 | C77: 46076 | D77: 26 FS3 Philharmonia Fantastique | G77: 46082.583 | H77: Family | I77: =P77+V77 -> 333 | J77: =IF(Q77="Too early",Q77,Q77+V77) -> Too early | K77: =IF(J77="Too early",J77,J77/Z77) -> Too early | L77: =R77+W77 -> 7842 | M77: =S77+X77 -> 19500 | N77: =L77/M77 -> 0.40215385 | O77: =IF($J77="Too early",J77,J77*AB77/M77) -> Too early | P77: 37 | Q77: =IF(B77<7,(P77/VLOOKUP(B77,'Sales Pacing'!$A$23:$E$36,2)),"Too early") -> Too early | R77: 1386 | S77: 10000 | T77: =IF(R77>0,R77/S77,"") -> 0.1386 | U77: =IF($Q77="Too early",Q77,Q77*AB77/S77) -> Too early | V77: 296 | W77: 6456 | X77: 9500 | Y77: =IF(W77>0,W77/X77,"") -> 0.67957895 | Z77: 1302 | AA77: =I77/Z77 -> 0.25576037 | AB77: =L77/I77 -> 23.54955 | AF77: 7902 | AG77: =L77-AF77 -> -60
A78: 27 | B78: =A78-$G$4 -> 27 | C78: 46083 | D78: OPEN | I78: =P78+V78 -> 0 | J78: =IF(Q78="Too early",Q78,Q78+V78) -> Too early | L78: =R78+W78 -> 0 | M78: =S78+X78 -> 0 | N78: =L78/M78 -> #DIV/0! | Q78: =IF(B78<7,(P78/VLOOKUP(B78,'Sales Pacing'!$A$23:$E$36,2)),"Too early") -> Too early | T78: =IF(R78>0,R78/S78,"") | Y78: N/A | AA78: =I78/Z78 -> #DIV/0! | AB78: =L78/I78 -> #DIV/0! | AF78: 0
A79: 28 | B79: =A79-$G$4 -> 28 | C79: 46090 | D79: 26 CS08 Saint-Saëns & Strauss | G79: 46094.833 | H79: Classical | I79: =P79+V79 -> 609 | J79: =IF(Q79="Too early",Q79,Q79+V79) -> Too early | K79: =IF(J79="Too early",J79,J79/Z79) -> Too early | L79: =R79+W79 -> 40282.3 | M79: =S79+X79 -> 54999 | N79: =L79/M79 -> 0.73241877 | O79: =IF($J79="Too early",J79,J79*AB79/M79) -> Too early | P79: 40 | Q79: =IF(B79<7,(P79/VLOOKUP(B79,'Sales Pacing'!$A$23:$E$36,2)),"Too early") -> Too early | R79: 1914 | S79: 18333 | T79: =IF(R79>0,R79/S79,"") -> 0.1044019 | U79: =IF($Q79="Too early",Q79,Q79*AB79/S79) -> Too early | V79: 569 | W79: 38368.3 | X79: 36666 | Y79: =IF(W79>0,W79/X79,"") -> 1.0464272 | Z79: 1590 | AA79: =I79/Z79 -> 0.38301887 | AB79: =L79/I79 -> 66.144992 | AF79: 40253.3 | AG79: =L79-AF79 -> 29
A80: 28 | B80: =A80-$G$4 -> 28 | C80: 46090 | D80: 26 CS08 Saint-Saëns & Strauss | G80: 46095.833 | H80: Classical | I80: =P80+V80 -> 610 | J80: =IF(Q80="Too early",Q80,Q80+V80) -> Too early | K80: =IF(J80="Too early",J80,J80/Z80) -> Too early | L80: =R80+W80 -> 39045.2 | M80: =S80+X80 -> 55000 | N80: =L80/M80 -> 0.70991273 | O80: =IF($J80="Too early",J80,J80*AB80/M80) -> Too early | P80: 47 | Q80: =IF(B80<7,(P80/VLOOKUP(B80,'Sales Pacing'!$A$23:$E$36,2)),"Too early") -> Too early | R80: 2397 | S80: 18333 | T80: =IF(R80>0,R80/S80,"") -> 0.13074783 | U80: =IF($Q80="Too early",Q80,Q80*AB80/S80) -> Too early | V80: 563 | W80: 36648.2 | X80: 36667 | Y80: =IF(W80>0,W80/X80,"") -> 0.99948728 | Z80: 1590 | AA80: =I80/Z80 -> 0.3836478 | AB80: =L80/I80 -> 64.008525 | AF80: 39104 | AG80: =L80-AF80 -> -58.8
A81: 28 | B81: =A81-$G$4 -> 28 | C81: 46090 | D81: 26 CS08 Saint-Saëns & Strauss | G81: 46096.583 | H81: Classical | I81: =P81+V81 -> 618 | J81: =IF(Q81="Too early",Q81,Q81+V81) -> Too early | K81: =IF(J81="Too early",J81,J81/Z81) -> Too early | L81: =R81+W81 -> 39633.1 | M81: =S81+X81 -> 55000 | N81: =L81/M81 -> 0.72060182 | O81: =IF($J81="Too early",J81,J81*AB81/M81) -> Too early | P81: 61 | Q81: =IF(B81<7,(P81/VLOOKUP(B81,'Sales Pacing'!$A$23:$E$36,2)),"Too early") -> Too early | R81: 3601 | S81: 18333 | T81: =IF(R81>0,R81/S81,"") -> 0.19642175 | U81: =IF($Q81="Too early",Q81,Q81*AB81/S81) -> Too early | V81: 557 | W81: 36032.1 | X81: 36667 | Y81: =IF(W81>0,W81/X81,"") -> 0.9826847 | Z81: 1590 | AA81: =I81/Z81 -> 0.38867925 | AB81: =L81/I81 -> 64.13123 | AF81: 38389.7 | AG81: =L81-AF81 -> 1243.4
A82: 29 | B82: =A82-$G$4 -> 29 | C82: 46097 | D82: OPEN | I82: =P82+V82 -> 0 | J82: =IF(Q82="Too early",Q82,Q82+V82) -> Too early | L82: =R82+W82 -> 0 | M82: =S82+X82 -> 0 | N82: =L82/M82 -> #DIV/0! | Q82: =IF(B82<7,(P82/VLOOKUP(B82,'Sales Pacing'!$A$23:$E$36,2)),"Too early") -> Too early | T82: =IF(R82>0,R82/S82,"") | Y82: N/A | AA82: =I82/Z82 -> #DIV/0! | AB82: =L82/I82 -> #DIV/0! | AF82: 0
A83: 30 | B83: =A83-$G$4 -> 30 | C83: 46104 | D83: Final Symphony | G83: 46106 | H83: Specials | I83: =P83+V83 -> 75 | J83: =IF(Q83="Too early",Q83,Q83+V83) -> Too early | K83: =IF(J83="Too early",J83,J83/Z83) -> Too early | L83: =R83+W83 -> 4422 | M83: =S83+X83 -> 84109 | N83: =L83/M83 -> 0.052574635 | O83: =IF($J83="Too early",J83,J83*AB83/M83) -> Too early | P83: 75 | Q83: =IF(B83<7,(P83/VLOOKUP(B83,'Sales Pacing'!$A$23:$E$36,2)),"Too early") -> Too early | R83: 4422 | S83: 84109 | T83: =IF(R83>0,R83/S83,"") -> 0.052574635 | U83: =IF($Q83="Too early",Q83,Q83*AB83/S83) -> Too early | Z83: 1590 | AA83: =I83/Z83 -> 0.047169811 | AB83: =L83/I83 -> 58.96 | AF83: 4187 | AG83: =L83-AF83 -> 235
A84: 30 | B84: =A84-$G$4 -> 30 | C84: 46104 | D84: Final Symphony | G84: 46107 | H84: Specials | I84: =P84+V84 -> 81 | J84: =IF(Q84="Too early",Q84,Q84+V84) -> Too early | K84: =IF(J84="Too early",J84,J84/Z84) -> Too early | L84: =R84+W84 -> 4417.5 | M84: =S84+X84 -> 84109 | N84: =L84/M84 -> 0.052521133 | O84: =IF($J84="Too early",J84,J84*AB84/M84) -> Too early | P84: 81 | Q84: =IF(B84<7,(P84/VLOOKUP(B84,'Sales Pacing'!$A$23:$E$36,2)),"Too early") -> Too early | R84: 4417.5 | S84: 84109 | T84: =IF(R84>0,R84/S84,"") -> 0.052521133 | U84: =IF($Q84="Too early",Q84,Q84*AB84/S84) -> Too early | Z84: 1590 | AA84: =I84/Z84 -> 0.050943396 | AB84: =L84/I84 -> 54.537037 | AF84: 4287 | AG84: =L84-AF84 -> 130.5
A85: 30 | B85: =A85-$G$4 -> 30 | C85: 46104 | D85: 26 PS4 Billy Joel & Elton John | G85: 46108.833 | H85: Pops | I85: =P85+V85 -> 872 | J85: =IF(Q85="Too early",Q85,Q85+V85) -> Too early | K85: =IF(J85="Too early",J85,J85/Z85) -> Too early | L85: =R85+W85 -> 62459.3 | M85: =S85+X85 -> 94666 | N85: =L85/M85 -> 0.65978598 | O85: =IF($J85="Too early",J85,J85*AB85/M85) -> Too early | P85: 141 | Q85: =IF(B85<7,(P85/VLOOKUP(B85,'Sales Pacing'!$A$23:$E$36,2)),"Too early") -> Too early | R85: 9504 | S85: 53333 | T85: =IF(R85>0,R85/S85,"") -> 0.17820111 | U85: =IF($Q85="Too early",Q85,Q85*AB85/S85) -> Too early | V85: 731 | W85: 52955.3 | X85: 41333 | Y85: =IF(W85>0,W85/X85,"") -> 1.2811869 | Z85: 1590 | AA85: =I85/Z85 -> 0.54842767 | AB85: =L85/I85 -> 71.627638 | AF85: 62169.1 | AG85: =L85-AF85 -> 290.2
A86: 30 | B86: =A86-$G$4 -> 30 | C86: 46104 | D86: 26 PS4 Billy Joel & Elton John | G86: 46109.833 | H86: Pops | I86: =P86+V86 -> 805 | J86: =IF(Q86="Too early",Q86,Q86+V86) -> Too early | K86: =IF(J86="Too early",J86,J86/Z86) -> Too early | L86: =R86+W86 -> 58280.3 | M86: =S86+X86 -> 94667 | N86: =L86/M86 -> 0.6156348 | O86: =IF($J86="Too early",J86,J86*AB86/M86) -> Too early | P86: 148 | Q86: =IF(B86<7,(P86/VLOOKUP(B86,'Sales Pacing'!$A$23:$E$36,2)),"Too early") -> Too early | R86: 10309 | S86: 53333 | T86: =IF(R86>0,R86/S86,"") -> 0.19329496 | U86: =IF($Q86="Too early",Q86,Q86*AB86/S86) -> Too early | V86: 657 | W86: 47971.3 | X86: 41334 | Y86: =IF(W86>0,W86/X86,"") -> 1.1605772 | Z86: 1590 | AA86: =I86/Z86 -> 0.50628931 | AB86: =L86/I86 -> 72.397888 | AF86: 58377.5 | AG86: =L86-AF86 -> -97.2
A87: 30 | B87: =A87-$G$4 -> 30 | C87: 46104 | D87: 26 PS4 Billy Joel & Elton John | G87: 46110.583 | H87: Pops | I87: =P87+V87 -> 568 | J87: =IF(Q87="Too early",Q87,Q87+V87) -> Too early | K87: =IF(J87="Too early",J87,J87/Z87) -> Too early | L87: =R87+W87 -> 39383.6 | M87: =S87+X87 -> 94666 | N87: =L87/M87 -> 0.41602687 | O87: =IF($J87="Too early",J87,J87*AB87/M87) -> Too early | P87: 183 | Q87: =IF(B87<7,(P87/VLOOKUP(B87,'Sales Pacing'!$A$23:$E$36,2)),"Too early") -> Too early | R87: 13173 | S87: 53333 | T87: =IF(R87>0,R87/S87,"") -> 0.24699529 | U87: =IF($Q87="Too early",Q87,Q87*AB87/S87) -> Too early | V87: 385 | W87: 26210.6 | X87: 41333 | Y87: =IF(W87>0,W87/X87,"") -> 0.63413253 | Z87: 1590 | AA87: =I87/Z87 -> 0.3572327 | AB87: =L87/I87 -> 69.337324 | AF87: 38146.6 | AG87: =L87-AF87 -> 1237
A88: 31 | B88: =A88-$G$4 -> 31 | C88: 46111 | D88: OPEN | I88: =P88+V88 -> 0 | J88: =IF(Q88="Too early",Q88,Q88+V88) -> Too early | L88: =R88+W88 -> 0 | M88: =S88+X88 -> 0 | N88: =L88/M88 -> #DIV/0! | Q88: =IF(B88<7,(P88/VLOOKUP(B88,'Sales Pacing'!$A$23:$E$36,2)),"Too early") -> Too early | T88: =IF(R88>0,R88/S88,"") | Y88: N/A | AA88: =I88/Z88 -> #DIV/0! | AB88: =L88/I88 -> #DIV/0! | AF88: 0
A89: 32 | B89: =A89-$G$4 -> 32 | C89: 46118 | D89: 26 CS09 Midsummer Night's Dream | G89: 46122.833 | H89: Classical | I89: =P89+V89 -> 410 | J89: =IF(Q89="Too early",Q89,Q89+V89) -> Too early | K89: =IF(J89="Too early",J89,J89/Z89) -> Too early | L89: =R89+W89 -> 27555 | M89: =S89+X89 -> 52000 | N89: =L89/M89 -> 0.52990385 | O89: =IF($J89="Too early",J89,J89*AB89/M89) -> Too early | P89: 43 | Q89: =IF(B89<7,(P89/VLOOKUP(B89,'Sales Pacing'!$A$23:$E$36,2)),"Too early") -> Too early | R89: 1736 | S89: 22000 | T89: =IF(R89>0,R89/S89,"") -> 0.078909091 | U89: =IF($Q89="Too early",Q89,Q89*AB89/S89) -> Too early | V89: 367 | W89: 25819 | X89: 30000 | Y89: =IF(W89>0,W89/X89,"") -> 0.86063333 | Z89: 1433 | AA89: =I89/Z89 -> 0.28611305 | AB89: =L89/I89 -> 67.207317 | AF89: 27453 | AG89: =L89-AF89 -> 102
A90: 32 | B90: =A90-$G$4 -> 32 | C90: 46118 | D90: 26 CS09 Midsummer Night's Dream | G90: 46123.833 | H90: Classical | I90: =P90+V90 -> 643 | J90: =IF(Q90="Too early",Q90,Q90+V90) -> Too early | K90: =IF(J90="Too early",J90,J90/Z90) -> Too early | L90: =R90+W90 -> 40572 | M90: =S90+X90 -> 74000 | N90: =L90/M90 -> 0.54827027 | O90: =IF($J90="Too early",J90,J90*AB90/M90) -> Too early | P90: 79 | Q90: =IF(B90<7,(P90/VLOOKUP(B90,'Sales Pacing'!$A$23:$E$36,2)),"Too early") -> Too early | R90: 4133 | S90: 24000 | T90: =IF(R90>0,R90/S90,"") -> 0.17220833 | U90: =IF($Q90="Too early",Q90,Q90*AB90/S90) -> Too early | V90: 564 | W90: 36439 | X90: 50000 | Y90: =IF(W90>0,W90/X90,"") -> 0.72878 | Z90: 1433 | AA90: =I90/Z90 -> 0.448709 | AB90: =L90/I90 -> 63.097978 | AF90: 40320.8 | AG90: =L90-AF90 -> 251.2
A91: 32 | B91: =A91-$G$4 -> 32 | C91: 46118 | D91: 26 CS09 Midsummer Night's Dream | G91: 46124.583 | H91: Classical | I91: =P91+V91 -> 610 | J91: =IF(Q91="Too early",Q91,Q91+V91) -> Too early | K91: =IF(J91="Too early",J91,J91/Z91) -> Too early | L91: =R91+W91 -> 38332.1 | M91: =S91+X91 -> 74000 | N91: =L91/M91 -> 0.51800135 | O91: =IF($J91="Too early",J91,J91*AB91/M91) -> Too early | P91: 55 | Q91: =IF(B91<7,(P91/VLOOKUP(B91,'Sales Pacing'!$A$23:$E$36,2)),"Too early") -> Too early | R91: 2188 | S91: 24000 | T91: =IF(R91>0,R91/S91,"") -> 0.091166667 | U91: =IF($Q91="Too early",Q91,Q91*AB91/S91) -> Too early | V91: 555 | W91: 36144.1 | X91: 50000 | Y91: =IF(W91>0,W91/X91,"") -> 0.722882 | Z91: 1433 | AA91: =I91/Z91 -> 0.42568039 | AB91: =L91/I91 -> 62.839508 | AF91: 38109.7 | AG91: =L91-AF91 -> 222.4
A92: 33 | B92: =A92-$G$4 -> 33 | C92: 46125 | D92: 26 CS10 Farrenc/Dvorák/Schuman | G92: 46129.833 | H92: Classical | I92: =P92+V92 -> 598 | J92: =IF(Q92="Too early",Q92,Q92+V92) -> Too early | K92: =IF(J92="Too early",J92,J92/Z92) -> Too early | L92: =R92+W92 -> 39568.3 | M92: =S92+X92 -> 46666 | N92: =L92/M92 -> 0.84790426 | O92: =IF($J92="Too early",J92,J92*AB92/M92) -> Too early | P92: 26 | Q92: =IF(B92<7,(P92/VLOOKUP(B92,'Sales Pacing'!$A$23:$E$36,2)),"Too early") -> Too early | R92: 893 | S92: 13333 | T92: =IF(R92>0,R92/S92,"") -> 0.066976674 | U92: =IF($Q92="Too early",Q92,Q92*AB92/S92) -> Too early | V92: 572 | W92: 38675.3 | X92: 33333 | Y92: =IF(W92>0,W92/X92,"") -> 1.1602706 | Z92: 1590 | AA92: =I92/Z92 -> 0.37610063 | AB92: =L92/I92 -> 66.167726 | AF92: 39568.3 | AG92: =L92-AF92 -> 0
A93: 33 | B93: =A93-$G$4 -> 33 | C93: 46125 | D93: 26 CS10 Farrenc/Dvorák/Schuman | G93: 46130.833 | H93: Classical | I93: =P93+V93 -> 610 | J93: =IF(Q93="Too early",Q93,Q93+V93) -> Too early | K93: =IF(J93="Too early",J93,J93/Z93) -> Too early | L93: =R93+W93 -> 41088.9 | M93: =S93+X93 -> 46666 | N93: =L93/M93 -> 0.88048901 | O93: =IF($J93="Too early",J93,J93*AB93/M93) -> Too early | P93: 22 | Q93: =IF(B93<7,(P93/VLOOKUP(B93,'Sales Pacing'!$A$23:$E$36,2)),"Too early") -> Too early | R93: 799 | S93: 13333 | T93: =IF(R93>0,R93/S93,"") -> 0.059926498 | U93: =IF($Q93="Too early",Q93,Q93*AB93/S93) -> Too early | V93: 588 | W93: 40289.9 | X93: 33333 | Y93: =IF(W93>0,W93/X93,"") -> 1.2087091 | Z93: 1590 | AA93: =I93/Z93 -> 0.3836478 | AB93: =L93/I93 -> 67.358852 | AF93: 41085.4 | AG93: =L93-AF93 -> 3.5
A94: 33 | B94: =A94-$G$4 -> 33 | C94: 46125 | D94: 26 CS10 Farrenc/Dvorák/Schuman | G94: 46131.583 | H94: Classical | I94: =P94+V94 -> 648 | J94: =IF(Q94="Too early",Q94,Q94+V94) -> Too early | K94: =IF(J94="Too early",J94,J94/Z94) -> Too early | L94: =R94+W94 -> 40994.2 | M94: =S94+X94 -> 46667 | N94: =L94/M94 -> 0.87844087 | O94: =IF($J94="Too early",J94,J94*AB94/M94) -> Too early | P94: 33 | Q94: =IF(B94<7,(P94/VLOOKUP(B94,'Sales Pacing'!$A$23:$E$36,2)),"Too early") -> Too early | R94: 1275 | S94: 13333 | T94: =IF(R94>0,R94/S94,"") -> 0.095627391 | U94: =IF($Q94="Too early",Q94,Q94*AB94/S94) -> Too early | V94: 615 | W94: 39719.2 | X94: 33334 | Y94: =IF(W94>0,W94/X94,"") -> 1.1915522 | Z94: 1590 | AA94: =I94/Z94 -> 0.40754717 | AB94: =L94/I94 -> 63.262654 | AF94: 40785.2 | AG94: =L94-AF94 -> 209
A95: 34 | B95: =A95-$G$4 -> 34 | C95: 46132 | D95: OPEN | I95: =P95+V95 -> 0 | J95: =IF(Q95="Too early",Q95,Q95+V95) -> Too early | L95: =R95+W95 -> 0 | M95: =S95+X95 -> 0 | N95: =L95/M95 -> #DIV/0! | Q95: =IF(B95<7,(P95/VLOOKUP(B95,'Sales Pacing'!$A$23:$E$36,2)),"Too early") -> Too early | T95: =IF(R95>0,R95/S95,"") | Y95: N/A | AA95: =I95/Z95 -> #DIV/0! | AB95: =L95/I95 -> #DIV/0! | AF95: 0
A96: 35 | B96: =A96-$G$4 -> 35 | C96: 46139 | D96: OPEN | I96: =P96+V96 -> 0 | J96: =IF(Q96="Too early",Q96,Q96+V96) -> Too early | L96: =R96+W96 -> 0 | M96: =S96+X96 -> 0 | N96: =L96/M96 -> #DIV/0! | Q96: =IF(B96<7,(P96/VLOOKUP(B96,'Sales Pacing'!$A$23:$E$36,2)),"Too early") -> Too early | T96: =IF(R96>0,R96/S96,"") | Y96: N/A | AA96: =I96/Z96 -> #DIV/0! | AB96: =L96/I96 -> #DIV/0! | AF96: 0
A97: 36 | B97: =A97-$G$4 -> 36 | C97: 46146 | D97: 26 CS11 Grieg's Piano Concerto | G97: 46150.833 | H97: Classical | I97: =P97+V97 -> 415 | J97: =IF(Q97="Too early",Q97,Q97+V97) -> Too early | K97: =IF(J97="Too early",J97,J97/Z97) -> Too early | L97: =R97+W97 -> 27961 | M97: =S97+X97 -> 45000 | N97: =L97/M97 -> 0.62135556 | O97: =IF($J97="Too early",J97,J97*AB97/M97) -> Too early | P97: 44 | Q97: =IF(B97<7,(P97/VLOOKUP(B97,'Sales Pacing'!$A$23:$E$36,2)),"Too early") -> Too early | R97: 2131 | S97: 20000 | T97: =IF(R97>0,R97/S97,"") -> 0.10655 | U97: =IF($Q97="Too early",Q97,Q97*AB97/S97) -> Too early | V97: 371 | W97: 25830 | X97: 25000 | Y97: =IF(W97>0,W97/X97,"") -> 1.0332 | Z97: 1590 | AA97: =I97/Z97 -> 0.26100629 | AB97: =L97/I97 -> 67.375904 | AF97: 27961 | AG97: =L97-AF97 -> 0
A98: 36 | B98: =A98-$G$4 -> 36 | C98: 46146 | D98: 26 CS11 Grieg's Piano Concerto | G98: 46151.833 | H98: Classical | I98: =P98+V98 -> 660 | J98: =IF(Q98="Too early",Q98,Q98+V98) -> Too early | K98: =IF(J98="Too early",J98,J98/Z98) -> Too early | L98: =R98+W98 -> 44069.9 | M98: =S98+X98 -> 65000 | N98: =L98/M98 -> 0.67799846 | O98: =IF($J98="Too early",J98,J98*AB98/M98) -> Too early | P98: 71 | Q98: =IF(B98<7,(P98/VLOOKUP(B98,'Sales Pacing'!$A$23:$E$36,2)),"Too early") -> Too early | R98: 4083 | S98: 17500 | T98: =IF(R98>0,R98/S98,"") -> 0.23331429 | U98: =IF($Q98="Too early",Q98,Q98*AB98/S98) -> Too early | V98: 589 | W98: 39986.9 | X98: 47500 | Y98: =IF(W98>0,W98/X98,"") -> 0.84182947 | Z98: 1590 | AA98: =I98/Z98 -> 0.41509434 | AB98: =L98/I98 -> 66.772576 | AF98: 43689.4 | AG98: =L98-AF98 -> 380.5
A99: 36 | B99: =A99-$G$4 -> 36 | C99: 46146 | D99: 26 CS11 Grieg's Piano Concerto | G99: 46152.583 | H99: Classical | I99: =P99+V99 -> 666 | J99: =IF(Q99="Too early",Q99,Q99+V99) -> Too early | K99: =IF(J99="Too early",J99,J99/Z99) -> Too early | L99: =R99+W99 -> 42307.2 | M99: =S99+X99 -> 65000 | N99: =L99/M99 -> 0.65088 | O99: =IF($J99="Too early",J99,J99*AB99/M99) -> Too early | P99: 55 | Q99: =IF(B99<7,(P99/VLOOKUP(B99,'Sales Pacing'!$A$23:$E$36,2)),"Too early") -> Too early | R99: 2861 | S99: 17500 | T99: =IF(R99>0,R99/S99,"") -> 0.16348571 | U99: =IF($Q99="Too early",Q99,Q99*AB99/S99) -> Too early | V99: 611 | W99: 39446.2 | X99: 47500 | Y99: =IF(W99>0,W99/X99,"") -> 0.83044632 | Z99: 1590 | AA99: =I99/Z99 -> 0.41886792 | AB99: =L99/I99 -> 63.524324 | AF99: 41626.2 | AG99: =L99-AF99 -> 681
A100: 37 | B100: =A100-$G$4 -> 37 | C100: 46153 | D100: 26 PS5 Dolly Parton's Threads | G100: 46157.833 | H100: Pops | I100: =P100+V100 -> 793 | J100: =IF(Q100="Too early",Q100,Q100+V100) -> Too early | K100: =IF(J100="Too early",J100,J100/Z100) -> Too early | L100: =R100+W100 -> 66870 | M100: =S100+X100 -> 103333 | N100: =L100/M100 -> 0.64713112 | O100: =IF($J100="Too early",J100,J100*AB100/M100) -> Too early | P100: 61 | Q100: =IF(B100<7,(P100/VLOOKUP(B100,'Sales Pacing'!$A$23:$E$36,2)),"Too early") -> Too early | R100: 4667 | S100: 60000 | T100: =IF(R100>0,R100/S100,"") -> 0.077783333 | U100: =IF($Q100="Too early",Q100,Q100*AB100/S100) -> Too early | V100: 732 | W100: 62203 | X100: 43333 | Y100: =IF(W100>0,W100/X100,"") -> 1.4354649 | Z100: 1302 | AA100: =I100/Z100 -> 0.60906298 | AB100: =L100/I100 -> 84.325347 | AF100: 66532 | AG100: =L100-AF100 -> 338
...

Sheet Subscriptions
B1: KANSAS CITY SYMPHONY | E1: Update all fields in Blue each week | J1: 100%+ of FY26 Goal
B2: 2025-26 Subscriptions | E2: We expect 50% of Total by Week 5 | J2: 90-99% of FY26 Goal | N2: Classical | S2: FY26 Budget - Classical
E3: We expect 90% of Total by Week 10/11 | J3: <90% of FY26 Goal | N3: 0.72 | O3: % of total subscriptions | S3: Units | T3: Revenue
O4: =O8/S8*S4 -> 190.76952 | P4: =P8/O8*O4 -> 67934.779 | Q4: =Q8/S8*S4 -> 2954.7347 | R4: =R8/Q8*Q4 -> 1567065.2 | S4: =T4/(T8/S8) -> 3145.5043 | T4: 1635000 | U4: Total
B5: FY26 Sales - Classical | O5: =O9/S9*S5 -> 8.6708651 | P5: =P9/O9*O5 -> 2639.1544 | Q5: =Q9/S9*S5 -> 267.83339 | R5: =R9/Q9*Q5 -> 147753.15 | S5: =T5/(T8/S8) -> 276.50425 | T5: =T4-T8 -> 143724 | U5: Difference vs FY25
C6: New | F6: Renewals | I6: Total | N6: FY25 Actuals - Classical
A7: Weeks On Sale | C7: Actual Units | D7: Proj | E7: Actual Rev | F7: Actual Units | G7: Proj | H7: Actual Rev | I7: Actual Units | J7: Proj | K7: Actual Rev | L7: W/W Change | O7: New Units | P7: New Revenue | Q7: Renewal Units | R7: Renewal Revenue | S7: Total Units | T7: Total Revenue | U7: Change
A8: Projected Total | I8: =I16 -> 2456 | K8: =K16 -> 1408430 | N8: Final | O8: =O21 -> 174 | P8: =P21 -> 61963 | Q8: =Q21 -> 2695 | R8: =R21 -> 1429313 | S8: =S21 -> 2869 | T8: =T21 -> 1491276
A9: 1 | B9: 45747 | C9: 30 | D9: =C9/'Sales Pacing'!B3 -> 713.33333 | E9: 16220 | F9: 898 | G9: =F9/'Sales Pacing'!E3 -> 3554.0218 | H9: 527973 | I9: =C9+F9 -> 928 | J9: =D9+G9 -> 4267.3552 | K9: =E9+H9 -> 544193 | N9: 45383 | O9: 27 | P9: 8218 | Q9: 834 | R9: 460085 | S9: =O9+Q9 -> 861 | T9: =P9+R9 -> 468303
A10: 2 | B10: 45754 | C10: 39 | D10: =C10/'Sales Pacing'!B4 -> 642 | E10: 21024 | F10: 1136 | G10: =F10/'Sales Pacing'!E4 -> 3593.8233 | H10: 652031 | I10: =C10+F10 -> 1175 | J10: =D10+G10 -> 4235.8233 | K10: =E10+H10 -> 673055 | L10: =IF(K10>0,K10-K9,0) -> 128862 | N10: =N9+7 -> 45390 | O10: 32 | P10: 12068 | Q10: 1194 | R10: 655718 | S10: =O10+Q10 -> 1226 | T10: =P10+R10 -> 667786 | U10: =IF(T10>0,T10-T9,0) -> 199483
A11: 3 | B11: 45761 | C11: 50 | D11: =C11/'Sales Pacing'!B5 -> 455.31915 | E11: 27424 | F11: 1387 | G11: =F11/'Sales Pacing'!E5 -> 3529.55 | H11: 817109 | I11: =C11+F11 -> 1437 | J11: =D11+G11 -> 3984.8691 | K11: =E11+H11 -> 844533 | L11: =IF(K11>0,K11-K10,0) -> 171478 | N11: =N10+7 -> 45397 | O11: 36 | P11: 13657 | Q11: 1434 | R11: 789833 | S11: =O11+Q11 -> 1470 | T11: =P11+R11 -> 803490 | U11: =IF(T11>0,T11-T10,0) -> 135704
A12: 4 | B12: 45768 | C12: 76 | D12: =C12/'Sales Pacing'!B6 -> 591.41818 | E12: 40984 | F12: 1739 | G12: =F12/'Sales Pacing'!E6 -> 3653.0333 | H12: 1005395 | I12: =C12+F12 -> 1815 | J12: =D12+G12 -> 4244.4515 | K12: =E12+H12 -> 1046379 | L12: =IF(K12>0,K12-K11,0) -> 201846 | N12: =N11+7 -> 45404 | O12: 45 | P12: 17584 | Q12: 1789 | R12: 976040 | S12: =O12+Q12 -> 1834 | T12: =P12+R12 -> 993624 | U12: =IF(T12>0,T12-T11,0) -> 190134
A13: 5 | B13: =B12+7 -> 45775 | C13: 112 | D13: =C13/'Sales Pacing'!B7 -> 684.8 | E13: 54163 | F13: 2160 | G13: =F13/'Sales Pacing'!E7 -> 3788.4885 | H13: 1232817 | I13: =C13+F13 -> 2272 | J13: =D13+G13 -> 4473.2885 | K13: =E13+H13 -> 1286980 | L13: =IF(K13>0,K13-K12,0) -> 240601 | N13: =N12+7 -> 45411 | O13: 47 | P13: 17987 | Q13: 2005 | R13: 1080463 | S13: =O13+Q13 -> 2052 | T13: =P13+R13 -> 1098450 | U13: =IF(T13>0,T13-T12,0) -> 104826
A14: 6 | B14: =B13+7 -> 45782 | C14: 121 | D14: =C14/'Sales Pacing'!B8 -> 533.89691 | E14: 58153 | F14: 2252 | G14: =F14/'Sales Pacing'!E8 -> 3121.3817 | H14: 1294295 | I14: =C14+F14 -> 2373 | J14: =D14+G14 -> 3655.2787 | K14: =E14+H14 -> 1352448 | L14: =IF(K14>0,K14-K13,0) -> 65468 | N14: =N13+7 -> 45418 | O14: 70 | P14: 26832 | Q14: 2362 | R14: 1271615 | S14: =O14+Q14 -> 2432 | T14: =P14+R14 -> 1298447 | U14: =IF(T14>0,T14-T13,0) -> 199997
A15: 7 | B15: =B14+7 -> 45789 | C15: 122 | D15: =C15/'Sales Pacing'!B9 -> 404.77519 | E15: 59763 | F15: 2293 | G15: =F15/'Sales Pacing'!E9 -> 2534.0926 | H15: 1322554 | I15: =C15+F15 -> 2415 | J15: =D15+G15 -> 2938.8678 | K15: =E15+H15 -> 1382317 | L15: =IF(K15>0,K15-K14,0) -> 29869 | N15: =N14+7 -> 45425 | O15: 76 | P15: 28802 | Q15: 2443 | R15: 1319275 | S15: =O15+Q15 -> 2519 | T15: =P15+R15 -> 1348077 | U15: =IF(T15>0,T15-T14,0) -> 49630
A16: 8 | B16: =B15+7 -> 45796 | C16: 134 | D16: =C16/'Sales Pacing'!B10 -> 382.34667 | E16: 63528 | F16: 2322 | G16: =F16/'Sales Pacing'!E10 -> 2473.787 | H16: 1344902 | I16: =C16+F16 -> 2456 | J16: =D16+G16 -> 2856.1337 | K16: =E16+H16 -> 1408430 | L16: =IF(K16>0,K16-K15,0) -> 26113 | N16: =N15+7 -> 45432 | O16: 85 | P16: 30752 | Q16: 2473 | R16: 1329297 | S16: =O16+Q16 -> 2558 | T16: =P16+R16 -> 1360049 | U16: =IF(T16>0,T16-T15,0) -> 11972
A17: 9 | B17: =B16+7 -> 45803 | C17: 146 | D17: =C17/'Sales Pacing'!B11 -> 369.75148 | E17: 67946 | F17: 2345 | G17: =F17/'Sales Pacing'!E11 -> 2468.3763 | H17: 1357272 | I17: =C17+F17 -> 2491 | J17: =D17+G17 -> 2838.1277 | K17: =E17+H17 -> 1425218 | L17: =IF(K17>0,K17-K16,0) -> 16788 | N17: =N16+7 -> 45439 | O17: 91 | P17: 32154 | Q17: 2513 | R17: 1344658 | S17: =O17+Q17 -> 2604 | T17: =P17+R17 -> 1376812 | U17: =IF(T17>0,T17-T16,0) -> 16763
A18: 10 | B18: =B17+7 -> 45810 | C18: 165 | D18: =C18/'Sales Pacing'!B12 -> 377.64706 | E18: 75744 | F18: 2369 | G18: =F18/'Sales Pacing'!E12 -> 2461.486 | H18: 1380368 | I18: =C18+F18 -> 2534 | J18: =D18+G18 -> 2839.1331 | K18: =E18+H18 -> 1456112 | L18: =IF(K18>0,K18-K17,0) -> 30894 | N18: =N17+7 -> 45446 | O18: 94 | P18: 32854 | Q18: 2608 | R18: 1391277 | S18: =O18+Q18 -> 2702 | T18: =P18+R18 -> 1424131 | U18: =IF(T18>0,T18-T17,0) -> 47319
A19: 11 | B19: =B18+7 -> 45817 | C19: 186 | D19: =C19/'Sales Pacing'!B13 -> 396.0597 | E19: 89633 | F19: 2384 | G19: =F19/'Sales Pacing'!E13 -> 2469.1125 | H19: 1390065 | I19: =C19+F19 -> 2570 | J19: =D19+G19 -> 2865.1722 | K19: =E19+H19 -> 1479698 | L19: =IF(K19>0,K19-K18,0) -> 23586 | N19: =N18+7 -> 45453 | O19: 95 | P19: 33169 | Q19: 2628 | R19: 1398365 | S19: =O19+Q19 -> 2723 | T19: =P19+R19 -> 1431534 | U19: =IF(T19>0,T19-T18,0) -> 7403
A20: 12 | B20: =B19+7 -> 45824 | C20: 205 | D20: =C20/'Sales Pacing'!B14 -> 404.3318 | E20: 94753 | F20: 2413 | G20: =F20/'Sales Pacing'!E14 -> 2491.1434 | H20: 1408181 | I20: =C20+F20 -> 2618 | J20: =D20+G20 -> 2895.4752 | K20: =E20+H20 -> 1502934 | L20: =IF(K20>0,K20-K19,0) -> 23236 | N20: =N19+7 -> 45460 | O20: 103 | P20: 35745 | Q20: 2655 | R20: 1411925 | S20: =O20+Q20 -> 2758 | T20: =P20+R20 -> 1447670 | U20: =IF(T20>0,T20-T19,0) -> 16136
A21: 13+ | B21: 45894 | C21: 271 | D21: =C21/'Sales Pacing'!B15 -> 271 | E21: 124427 | F21: 2424 | G21: =F21/'Sales Pacing'!E15 -> 2424 | H21: 1409643 | I21: =C21+F21 -> 2695 | J21: =D21+G21 -> 2695 | K21: =E21+H21 -> 1534070 | L21: =IF(K21>0,K21-K20,0) -> 31136 | N21: Rest of Season | O21: 174 | P21: 61963 | Q21: 2695 | R21: 1429313 | S21: =O21+Q21 -> 2869 | T21: =P21+R21 -> 1491276 | U21: =IF(T21>0,T21-T20,0) -> 43606
I22: vs. FY26 Goal | J22: =J21/$S$4 -> 0.85677837 | K22: =K21/$T$4 -> 0.93826911
B23: 25-26 Renewal as % of 24-25 Total
B24: =F15/S8 -> 0.79923318 | E24: 3rd Classical mailer drops 22nd/23rd of August | N24: Pops | S24: FY26 Budget - Pops
N25: 0.26 | O25: % of total subscriptions | S25: Units | T25: Revenue
O26: =O30/S30*S26 -> 240.07343 | P26: =P30/O30*O26 -> 69318.269 | Q26: =Q30/S30*S26 -> 1547.1399 | R26: =R30/Q30*Q26 -> 549681.73 | S26: =T26/(T30/S30) -> 1787.2133 | T26: 619000 | U26: Total
B27: FY26 Sales - Pops | O27: =O31/S31*S27 -> 3.2060949 | P27: =P31/O31*O27 -> 1038.7747 | Q27: =Q31/S31*S27 -> 109.00723 | R27: =R31/Q31*Q27 -> 44362.735 | S27: =T27/(T30/S30) -> 112.21332 | T27: =T26-T30 -> 38865 | U27: Difference vs FY25
C28: New | F28: Renewals | I28: Total | N28: FY25 Actuals - Pops
C29: Actual Units | D29: Proj | E29: Actual Rev | F29: Actual Units | G29: Proj | H29: Actual Rev | I29: Actual Units | J29: Proj | K29: Actual Rev | L29: W/W Change | O29: New Units | P29: New Revenue | Q29: Renewal Units | R29: Renewal Revenue | S29: Total Units | T29: Total Revenue | U29: Change
A30: Projected Total | I30: =I38 -> 1561 | K30: =K38 -> 591188 | N30: Final | O30: =O43 -> 225 | P30: =P43 -> 64966 | Q30: =Q43 -> 1450 | R30: =R43 -> 515169 | S30: =S43 -> 1675 | T30: =T43 -> 580135
A31: 1 | B31: 45747 | C31: 38 | D31: =C31/'Sales Pacing'!C3 -> 1048.1667 | E31: 13163 | F31: 636 | G31: =F31/'Sales Pacing'!F3 -> 5546.3927 | H31: 258782 | I31: =C31+F31 -> 674 | J31: =D31+G31 -> 6594.5593 | K31: =E31+H31 -> 271945 | N31: 45383 | O31: 2 | P31: 648 | Q31: 68 | R31: 27674 | S31: =O31+Q31 -> 70 | T31: =P31+R31 -> 28322
A32: 2 | B32: 45754 | C32: 44 | D32: =C32/'Sales Pacing'!C4 -> 606.83333 | E32: 14651 | F32: 785 | G32: =F32/'Sales Pacing'!F4 -> 3783.5789 | H32: 312531 | I32: =C32+F32 -> 829 | J32: =D32+G32 -> 4390.4122 | K32: =E32+H32 -> 327182 | L32: =IF(K32>0,K32-K31,0) -> 55237 | N32: =N31+7 -> 45390 | O32: 54 | P32: 17576 | Q32: 181 | R32: 68648 | S32: =O32+Q32 -> 235 | T32: =P32+R32 -> 86224 | U32: =IF(T32>0,T32-T31,0) -> 57902
A33: 3 | B33: 45761 | C33: 54 | D33: =C33/'Sales Pacing'!C5 -> 616.34483 | E33: 19061 | F33: 893 | G33: =F33/'Sales Pacing'!F5 -> 3135.2144 | H33: 353304 | I33: =C33+F33 -> 947 | J33: =D33+G33 -> 3751.5592 | K33: =E33+H33 -> 372365 | L33: =IF(K33>0,K33-K32,0) -> 45183 | N33: =N32+7 -> 45397 | O33: 66 | P33: 20302 | Q33: 283 | R33: 105425 | S33: =O33+Q33 -> 349 | T33: =P33+R33 -> 125727 | U33: =IF(T33>0,T33-T32,0) -> 39503
A34: 4 | B34: 45768 | C34: 60 | D34: =C34/'Sales Pacing'!C6 -> 484.39024 | E34: 20782 | F34: 1067 | G34: =F34/'Sales Pacing'!F6 -> 2921.075 | H34: 417996 | I34: =C34+F34 -> 1127 | J34: =D34+G34 -> 3405.4653 | K34: =E34+H34 -> 438778 | L34: =IF(K34>0,K34-K33,0) -> 66413 | N34: =N33+7 -> 45404 | O34: 86 | P34: 26557 | Q34: 389 | R34: 146108 | S34: =O34+Q34 -> 475 | T34: =P34+R34 -> 172665 | U34: =IF(T34>0,T34-T33,0) -> 46938
A35: 5 | B35: =B34+7 -> 45775 | C35: 118 | D35: =C35/'Sales Pacing'!C7 -> 566.05797 | E35: 38918 | F35: 1300 | G35: =F35/'Sales Pacing'!F7 -> 2887.9509 | H35: 502867 | I35: =C35+F35 -> 1418 | J35: =D35+G35 -> 3454.0088 | K35: =E35+H35 -> 541785 | L35: =IF(K35>0,K35-K34,0) -> 103007 | N35: =N34+7 -> 45411 | O35: 86 | P35: 26557 | Q35: 476 | R35: 178054 | S35: =O35+Q35 -> 562 | T35: =P35+R35 -> 204611 | U35: =IF(T35>0,T35-T34,0) -> 31946
A36: 6 | B36: =B35+7 -> 45782 | C36: 157 | D36: =C36/'Sales Pacing'!C8 -> 683.77632 | E36: 51765 | F36: 1358 | G36: =F36/'Sales Pacing'!F8 -> 2121.6398 | H36: 522161 | I36: =C36+F36 -> 1515 | J36: =D36+G36 -> 2805.4161 | K36: =E36+H36 -> 573926 | L36: =IF(K36>0,K36-K35,0) -> 32141 | N36: =N35+7 -> 45418 | O36: 98 | P36: 31472 | Q36: 806 | R36: 294720 | S36: =O36+Q36 -> 904 | T36: =P36+R36 -> 326192 | U36: =IF(T36>0,T36-T35,0) -> 121581
A37: 7 | B37: =B36+7 -> 45789 | C37: 165 | D37: =C37/'Sales Pacing'!C9 -> 593.6413 | E37: 54301 | F37: 1365 | G37: =F37/'Sales Pacing'!F9 -> 1717.375 | H37: 525805 | I37: =C37+F37 -> 1530 | J37: =D37+G37 -> 2311.0163 | K37: =E37+H37 -> 580106 | L37: =IF(K37>0,K37-K36,0) -> 6180 | N37: =N36+7 -> 45425 | O37: 113 | P37: 36672 | Q37: 1031 | R37: 372369 | S37: =O37+Q37 -> 1144 | T37: =P37+R37 -> 409041 | U37: =IF(T37>0,T37-T36,0) -> 82849
A38: 8 | B38: =B37+7 -> 45796 | C38: 199 | D38: =C38/'Sales Pacing'!C10 -> 639.50485 | E38: 65018 | F38: 1362 | G38: =F38/'Sales Pacing'!F10 -> 1532.8471 | H38: 526170 | I38: =C38+F38 -> 1561 | J38: =D38+G38 -> 2172.3519 | K38: =E38+H38 -> 591188 | L38: =IF(K38>0,K38-K37,0) -> 11082 | N38: =N37+7 -> 45432 | O38: 127 | P38: 40518 | Q38: 1267 | R38: 452816 | S38: =O38+Q38 -> 1394 | T38: =P38+R38 -> 493334 | U38: =IF(T38>0,T38-T37,0) -> 84293
A39: 9 | B39: =B38+7 -> 45803 | C39: 220 | D39: =C39/'Sales Pacing'!C11 -> 568.90625 | E39: 73218 | F39: 1368 | G39: =F39/'Sales Pacing'!F11 -> 1451.7935 | H39: 531352 | I39: =C39+F39 -> 1588 | J39: =D39+G39 -> 2020.6998 | K39: =E39+H39 -> 604570 | L39: =IF(K39>0,K39-K38,0) -> 13382 | N39: =N38+7 -> 45439 | O39: 160 | P39: 48485 | Q39: 1395 | R39: 497335 | S39: =O39+Q39 -> 1555 | T39: =P39+R39 -> 545820 | U39: =IF(T39>0,T39-T38,0) -> 52486
A40: 10 | B40: =B39+7 -> 45810 | C40: 239 | D40: =C40/'Sales Pacing'!C12 -> 557.10563 | E40: 80035 | F40: 1374 | G40: =F40/'Sales Pacing'!F12 -> 1439.2578 | H40: 536728 | I40: =C40+F40 -> 1613 | J40: =D40+G40 -> 1996.3634 | K40: =E40+H40 -> 616763 | L40: =IF(K40>0,K40-K39,0) -> 12193 | N40: =N39+7 -> 45446 | O40: 172 | P40: 51234 | Q40: 1411 | R40: 502695 | S40: =O40+Q40 -> 1583 | T40: =P40+R40 -> 553929 | U40: =IF(T40>0,T40-T39,0) -> 8109
A41: 11 | B41: =B40+7 -> 45817 | C41: 255 | D41: =C41/'Sales Pacing'!C13 -> 530.84906 | E41: 89633 | F41: 1407 | G41: =F41/'Sales Pacing'!F13 -> 1457.5735 | H41: 540393 | I41: =C41+F41 -> 1662 | J41: =D41+G41 -> 1988.4225 | K41: =E41+H41 -> 630026 | L41: =IF(K41>0,K41-K40,0) -> 13263 | N41: =N40+7 -> 45453 | O41: 187 | P41: 55826 | Q41: 1418 | R41: 505550 | S41: =O41+Q41 -> 1605 | T41: =P41+R41 -> 561376 | U41: =IF(T41>0,T41-T40,0) -> 7447
A42: 12 | B42: =B41+7 -> 45824 | C42: 270 | D42: =C42/'Sales Pacing'!C14 -> 470.36842 | E42: 90711 | F42: 1383 | G42: =F42/'Sales Pacing'!F14 -> 1420.054 | H42: 543160 | I42: =C42+F42 -> 1653 | J42: =D42+G42 -> 1890.4224 | K42: =E42+H42 -> 633871 | L42: =IF(K42>0,K42-K41,0) -> 3845 | N42: =N41+7 -> 45460 | O42: 193 | P42: 57355 | Q42: 1434 | R42: 510568 | S42: =O42+Q42 -> 1627 | T42: =P42+R42 -> 567923 | U42: =IF(T42>0,T42-T41,0) -> 6547
A43: 13+ | B43: 45894 | C43: 348 | D43: =C43/'Sales Pacing'!C15 -> 348 | E43: 111393 | F43: 1409 | G43: =F43/'Sales Pacing'!F15 -> 1409 | H43: 544870 | I43: =C43+F43 -> 1757 | J43: =D43+G43 -> 1757 | K43: =E43+H43 -> 656263 | L43: =IF(K43>0,K43-K42,0) -> 22392 | N43: Rest of Season | O43: 225 | P43: 64966 | Q43: 1450 | R43: 515169 | S43: =O43+Q43 -> 1675 | T43: =P43+R43 -> 580135 | U43: =IF(T43>0,T43-T42,0) -> 12212
I44: vs. FY26 Goal | J44: =J43/$S$26 -> 0.98309473 | K44: =K43/$T$26 -> 1.0601987
B45: 25-26 Renewal as % of 24-25 Total
B46: =F37/S30 -> 0.81492537
A48: Future Improvements:
A49: Give true renewal rates
A50: Show renewals by customer cohort
A51: Add Family subscriptions (2%)

Sheet Channels (Draft)
A1: MARKETING CHANNEL PERFORMANCE
B2: Owned Marketing Channels | H2: Paid Channels
A3: To start, let’s pull last 12 months of data. | B3: Phone | C3: Direct Mail | D3: Email | E3: Social | F3: In-hall | G3: SEO | H3: SEM | I3: Media | J3: Phone | K3: Total
B4: (Box Office) | E4: (FB, IG, X, other) | F4: (book, posters) | I4: (TV, radio, OOH) | J4: (Bennett)
A5: # Impressions: | D5: 13.7M
A6: calls made, e/mails delivered, etc.
A7: # Engagement: | D7: 4.7M
A8: calls answered, opens, etc.
A9: Engagement rate | D9: 34%
A10: # Actions (Success): | D10: 89k
A11: conversations, clicks, etc.
A12: Action rate | D12: 0.6%
A13: % of total Actions
A15: Channel cost ($, time)
A16: ROI: $/Action
A17: Attributed revenue ($) | J17: ~$220k
A18: ROI: $/channel cost
A20: SALES CHANNEL PERFORMANCE
A21: To start, let’s pull last 12 months of data. | B21: Phone | C21: Website | D21: KCPA | E21: Total
B22: (Box Office)
A23: # Traffic: | C23: 471,563
A24: calls received, visits
A25: % Traffic by Marketing Channel
A26: #, $ Conversions (Success): | C26: 4,547
A27: Conversion rate | C27: 0.94%
A28: % of total Conversions | D28: 15%?
A29: Total Sales Revenue | B29: ~$6,500k? | C29: $877k
A31: Channel cost ($, time)
A32: ROI: $/Conversion
A33: Attributed revenue ($)
A34: ROI: $/channel cost
A36: EXPERIENCE CHANNEL PERFORMANCE
B37: Total
A38: # total attendance
A39: % Repeat:
A40: % returning from prior season
A41: # Frequency:
A42: avg. attendance/customer
A44: Total Revenue, ROI?
A45: Avg. CSAT, NPS
A46: Avg. CLV/attendee
A47: # high CLV VIPs

Sheet Sales Pacing
B1: New Subs | E1: Renewal Subs
A2: # Weeks On Sale | B2: Classical | C2: Pops | E2: Classical | F2: Pops
A3: 1 | B3: 0.042056075 | C3: 0.036253776 | E3: 0.25267149 | F3: 0.11466913
A4: 2 | B4: 0.060747664 | C4: 0.072507553 | E4: 0.3160979 | F4: 0.20747552
A5: 3 | B5: 0.10981308 | C5: 0.087613293 | E5: 0.39296794 | F5: 0.28482901
A6: 4 | B6: 0.12850467 | C6: 0.12386707 | E6: 0.47604274 | F6: 0.36527648
A7: 5 | B7: 0.1635514 | C7: 0.20845921 | E7: 0.57014822 | F7: 0.45014616
A8: 6 | B8: 0.22663551 | C8: 0.22960725 | E8: 0.72147535 | F8: 0.64007095
A9: 7 | B9: 0.30140187 | C9: 0.27794562 | E9: 0.90486039 | F9: 0.79481765
A10: 8 | B10: 0.35046729 | C10: 0.31117825 | E10: 0.93864185 | F10: 0.88854264
A11: 9 | B11: 0.39485981 | C11: 0.38670695 | E11: 0.95001724 | F11: 0.94228277
A12: 10 | B12: 0.43691589 | C12: 0.42900302 | E12: 0.96242675 | F12: 0.95465872
A13: 11 | B13: 0.46962617 | C13: 0.48036254 | E13: 0.96552913 | F13: 0.96530297
A14: 12 | B14: 0.50700935 | C14: 0.57401813 | E14: 0.96863151 | F14: 0.97390663
A15: 13+ | B15: 1 | C15: 1 | E15: 1 | F15: 1
B21: Single Tickets
A22: # Weeks Until Performance | B22: Classical | C22: Pops | D22: Specials | E22: Other
A23: 0 | B23: 1 | C23: 1 | D23: 1 | E23: 1
A24: 1 | B24: 0.59 | C24: 0.59 | D24: 0.59 | E24: 0.59
A25: 2 | B25: 0.46 | C25: 0.46 | D25: 0.46 | E25: 0.46
A26: 3 | B26: 0.39 | C26: 0.39 | D26: 0.39 | E26: 0.39
A27: 4 | B27: 0.33 | C27: 0.33 | D27: 0.33 | E27: 0.33
A28: 5 | B28: 0.3 | C28: 0.3 | D28: 0.3 | E28: 0.3
A29: 6 | B29: 0.27 | C29: 0.27 | D29: 0.27 | E29: 0.27
A30: 7
A31: 8
A32: 9
A33: 10
A34: 11
A35: 12
A36: 13+
A38: Future Improvements:
A39: Extend data for single ticket sales beyond 6 weeks
A40: Differentiate single ticket sales by performance type
A41: Improve pacing data (always)

Sheet Summary (Draft)
B2: Overall Season | G2: # Tickets Sold | H2: Projected Tickets Sold | I2: Projected Occupancy (% +GYR) | J2: Total Revenue | K2: BUDGET | L2: Projected Revenue vs Budget (% +GYR)
B3: ALL CONCERTS | G3: ='Performances by Week'!I126 -> 0 | H3: ='Performances by Week'!J126 -> 0 | I3: ='Performances by Week'!K126 -> 0 | J3: ='Performances by Week'!L126 -> 0 | K3: ='Performances by Week'!M126 -> 6268640 | L3: ='Performances by Week'!O126
B5: Season Attendance By Ticket Type | G5: # Tickets Sold | H5: Projected Tickets Sold | J5: Total Revenue | K5: BUDGET | L5: Projected Revenue vs Budget (% +GYR)
B6: All Subscriptions | G6: ='Performances by Week'!V126 -> 0 | J6: ='Performances by Week'!W126 -> 0 | K6: ='Performances by Week'!X126 -> 2169893 | L6: ='Performances by Week'!Y126
B7: All Single Tickets | G7: ='Performances by Week'!P126 -> 0 | H7: ='Performances by Week'!Q126 -> 0 | J7: ='Performances by Week'!R126 -> 0 | K7: ='Performances by Week'!S126 -> 3973690 | L7: ='Performances by Week'!U126
B9: Concert Attendance By Performance Type | G9: # Tickets Sold | H9: Projected Tickets Sold | I9: Projected Occupancy (% +GYR) | J9: Total Revenue | K9: BUDGET | L9: Projected Revenue vs Budget (% +GYR)
B10: CLASSICAL TRADITIONAL TOTAL | G10: ='Performances by Week'!I119 -> 0 | H10: ='Performances by Week'!J119 -> 0 | I10: ='Performances by Week'!K119 -> 0 | J10: ='Performances by Week'!L119 -> 0 | K10: ='Performances by Week'!M119 -> 2139000 | L10: ='Performances by Week'!O119
B11: SYMPHONIC PIAZZA TOTAL | G11: ='Performances by Week'!I120 -> 0 | H11: ='Performances by Week'!J120 -> 0 | I11: ='Performances by Week'!K120 -> 0 | J11: ='Performances by Week'!L120 -> 0 | K11: ='Performances by Week'!M120 -> 363000 | L11: ='Performances by Week'!O120
B12: POPS TOTAL | G12: ='Performances by Week'!I121 -> 0 | H12: ='Performances by Week'!J121 -> 0 | I12: ='Performances by Week'!K121 -> 0 | J12: ='Performances by Week'!L121 -> 0 | K12: ='Performances by Week'!M121 -> 1457000 | L12: ='Performances by Week'!O121
B13: FAMILY SERIES TOTAL | G13: ='Performances by Week'!I122 -> 0 | H13: ='Performances by Week'!J122 -> 0 | I13: ='Performances by Week'!K122 -> 0 | J13: ='Performances by Week'!L122 -> 0 | K13: ='Performances by Week'!M122 -> 525950 | L13: ='Performances by Week'!O122
B14: FILM TOTAL | G14: ='Performances by Week'!I123 -> 0 | H14: ='Performances by Week'!J123 -> 0 | I14: ='Performances by Week'!K123 -> 0 | J14: ='Performances by Week'!L123 -> 0 | K14: ='Performances by Week'!M123 -> 1745490 | L14: ='Performances by Week'!O123
B15: ON STAGE CONCERTS TOTAL | G15: ='Performances by Week'!I124 -> 0 | H15: ='Performances by Week'!J124 -> 0 | I15: ='Performances by Week'!K124 -> 0 | J15: ='Performances by Week'!L124 -> 0 | K15: ='Performances by Week'!M124 -> 38200 | L15: ='Performances by Week'!O124
B16: OTHER CONCERT TOTAL | G16: ='Performances by Week'!I125 -> 0 | H16: ='Performances by Week'!J125 -> 0 | I16: ='Performances by Week'!K125 -> 0 | J16: ='Performances by Week'!L125 -> 0 | K16: ='Performances by Week'!M125 -> 0 | L16: ='Performances by Week'!O125

Sheet Social Reporting
A1: DATE | B1: Social Post | C1: Views | D1: Engagement
A2: 45891 | B2: Chicken Fried IG | C2: 1625 | D2: 11 interactions
A3: 45891 | B3: Chicken Fried FB | C3: 2570 | D3: 15 interactions, 6 link clicks
A4: 45890 | B4: Journey Reel IG | C4: 1005 | D4: 16 interactions
A5: 45890 | B5: Journey Reel FB | C5: 813 | D5: 12 interactions
A6: 45883 | B6: KC Blues Society Video IG | C6: 966 | D6: 32 interactions
A7: 45883 | B7: KC Blues Society Video FB | C7: 1895 | D7: 19 interactions, 61 link clicks
A8: 45881 | B8: CS1 Nora Video IG | C8: 3290 | D8: 42 interactions
A9: 45881 | B9: CS1 Nora Video FB | C9: 1785 | D9: 42 interactions
A10: 45876 | B10: Orchestra Games IG | C10: 2394 | D10: 54 interactions
A11: 45876 | B11: Orchestra Games FB | C11: 1879 | D11: 15 interactions, 2 link clicks
A12: 45876 | B12: Morgan Freeman interview reshare FB | C12: 2731 | D12: 52 interactions, 53 link clicks
A13: 45875 | B13: Nora Intro IG | C13: 3331 | D13: 65 interactions
... A16: 45874 | B16: Journey Graphic FB | C16: 4997 | D16: 28 interactions, 22 link clicks
B18: Meta Ads
A19: 7/30-8/13 | B19: Morgan Freeman video | C19: 88,119 impressions | D19: 3,269 link clicks
A20: Ends 8/22 | B20: Music of Journey | C20: 56,165 impressions | D20: 3,537 link clicks
A24: 45870 | B24: La Nuit Sombre video IG Reel | C24: 953 | D24: 46 interactions
A25: 45870 | B25: La Nuit Sombre video FB Reel | C25: 1105 | D25: 14 interactions
A26: 45860 | B26: La Nuit Sombre Price Increase FB | C26: 3465 | D26: 19 interactions, 9 link clicks
A27: 45860 | B27: La Nuit Sombre Price Increase IG | C27: 1537 | D27: 19 interactions, 11 link clicks
A28: 45865 | B28: Music is for Everyone FB Reel | C28: 563 | D28: 13 interactions
A29: 45865 | B29: Music is for Everyone IG Reel | C29: 1735 | D29: 36 interactions
A30: 45865 | B30: Music is for Everyone TikTok | C30: 256 | D30: 16 interactions
A31: 45853 | B31: Are you single? FB Reel | C31: 1641 | D31: 22 interactions
A32: 45853 | B32: Are you single? IG Reel | C32: 4321 | D32: 170 interactions
A33: 45853 | B33: Are you single? TikTok | C33: 1013 | D33: 45 interactions
A34: 45853 | B34: Are you single? YT | C34: 1115 | D34: 16 interactions
A35: 45854 | B35: Single Tickets Graphic FB | C35: 3157 | D35: 26 interactions
... A45: 45856 | B45: Music is for Everyone YT | C45: 32 | D45: 1 interaction
B47: Meta Ads
A48: 45832 | B48: Specials/Films ad | C48: 1k impressions | D48: 18 clicks
A49: 45838 | B49: Morgan Freeman video | C49: 22k impressions | D49: 1234 link clicks
A50: 45841 | B50: Holiday concerts ad | C50: 68k impressions | D50: 1011 link clicks

Sheet Email Reporting
A1: EMAILS SENT | B1: DELIVERIES | C1: OPENS | D1: CLICK RATE
A2: 8/20 Bi-weekly Merchandise Email | B2: 95473 | C2: 35,125 (37%) | D2: 754 (1%)
A3: 8/12 Music of Journey Promo | B3: 94241 | C3: 35,743 (37.9%) | D3: 577 0.6% | E3: https://conta.cc/4mdHLVC
A4: 8/6 Bi-weekly Merchandise Email | B4: 94322 | C4: 36,401 (38.6%) | D4: 937 (1%) | E4: https://conta.cc/3Hoy3k2
A5: 7/21 La Nuit Sombre Matthias Video | B5: 95893 | C5: 35,531 (37.1%) | D5: 491 (0.5%)
A6: 7/23 Morgan Freeman Promo | B6: 96012 | C6: 35,064 (36.5%) | D6: 769 (0.8%)
A7: 7/15 Single Ticket On Sale Announcement | B7: 95831 | C7: 35,285 (37.2%) | D7: 1,708 (2%)
A8: 7/8 Leslie Odom Jr. Promo | B8: 94927 | C8: 35, 660 (37.6%) | D8: 550 (0.6%)
A9: Tuesday 7/1 Holiday Presentations On Sale | B9: 95059 | C9: 35039 (36.9%) | D9: 822 (0.9%) | E9: Header: 64, Elf in Concert: 473, Handel's Messiah: 390, LOJ: 110, Christmas Festival: 144, Wonderful Life: 129
A10: Tuesday 6/25 Special Presentations On Sale | B10: 95219 | C10: 35,617 (37%) | D10: 1,469 (2%) | E10: Full lineup: 248, Morgan Freeman: 438, Chicken Fried: 456, Top Gun: 559, Lodger: 100, Indiana Jones: 204, Chris Thile: 134, Harry Potter: 139, Final Symphony: 74, Ben Rector: 108, On Stage George: 45, On Stage Leila: 53, On Stage Gil: 37, On Stage 38
A11: Tuesday 6/17 Mark Your Calendar | B11: 104371 | C11: 37,343 (39%) | D11: 1,999 (2%)
A12: Monday 6/9 Mobile Music Box June Concert | B12: 95,460 | C12: 36,052 (38%) | D12: 594 (1%)
A13: Wednesday 6/4 CS14 Student Rush Promo | B13: 174 | C13: 77 (44%) | D13: 0
A14: Wednesday 6/4 CS14 Student Rush Promo | B14: 174 | C14: 77 (44%) | D14: 0
A15: Wednesday 6/4 CS14 Student Pass Promo | B15: 80 | C15: 38 (47%) | D15: 1 | J15: AVERAGE OPEN RATE: | K15: 0.37
A16: Wednesday 6/4 CS14 BOGO Promo | B16: 4954 | C16: 2,165 (44%) | D16: 65 (1%)
A17: Wednesday 6/4 Four Larks Subscriber Early Access | B17: 2185 | C17: 1,452 (66.5%) | D17: 135 (6.2%) | J17: AVERAGE CLICK RATE: | K17: 0.02
A18: Friday 6/6 Four Lark Public On-Sale | B18: 96846 | C18: 35,136 (36%) | D18: 616 (0.6%)

Sheet Website Reporting
A1: Timeframe: August 11-18
A2: ECOMMERCE PURCHASES: 877 | B2: WEBSITE REVENUE: $74,429 | C2: # OF ITEMS
A3: Morgan Freeman | B3: 18052 | C3: 164
A4: Music of Journey | B4: 8322 | C4: 66
A5: Top Gun | B5: 7065 | C5: 86
A6: Leslie Odom Jr. | B6: 4084.5 | C6: 54
A7: Indiana Jones | B7: 3441 | C7: 38
A8: Elf in Concert | B8: 2892 | C8: 44
A9: Harry Potter | B9: 2521 | C9: 29
A10: It's a wonderful life | B10: 2454 | C10: 52
A12: Timeframe: July 20-July 28
A13: ECOMMERCE PURCHASES: 973 | B13: WEBSITE REVENUE: $67,220 | C13: # OF ITEMS
A14: Leslie Odom Jr. | B14: 17681 | C14: 161
A15: Morgan Freeman | B15: 7995 | C15: 64
A16: Top Gun | B16: 5293 | C16: 64
A17: 2025/26 COY Package | B17: 4084 | C17: 54
A18: It's a wonderful life | B18: 2684 | C18: 31
A19: Elf in Concert | B19: 2343 | C19: 26
A20: Christmas Festival | B20: 2341 | C20: 38
A21: La nuit sombre | B21: 2308 | C21: 49
A22: Harry Potter 2 | B22: 2030 | C22: 26
A23: Indiana Jones | B23: 2004 | C23: 26
A27: Timeframe: July 20-July 28
A28: ECOMMERCE PURCHASES: 1,718 | B28: WEBSITE REVENUE: $115,644 | C28: # OF ITEMS
A29: Morgan Freeman | B29: 27675 | C29: 215
A30: Top Gun | B30: 9650 | C30: 116
A31: It's a wonderful life | B31: 8677 | C31: 104
A32: Leslie Odom Jr. | B32: 9110 | C32: 84
A33: Elf in Concert | B33: 5110 | C33: 80
A34: 2025/26 COY Package | B34: 5435 | C34: 73
A35: Harry Potter 2 | B35: 5145 | C35: 61
A36: 2025/26 Sunday Masterworks | B36: 4200 | C36: 56
A37: Handel's Messiah | B37: 2970 | C37: 55
A43: Timeframe: July 14-July 20
A44: ECOMMERCE PURCHASES: 3,027 | B44: WEBSITE REVENUE: $188,688 | C44: # OF ITEMS
A45: Top Gun | B45: 19205 | C45: 234
A46: Morgan Freeman | B46: 16175 | C46: 130
A47: Leslie Odom Jr. | B47: 14107 | C47: 139
A48: Indiana Jones | B48: 12729 | C48: 186
A49: Billy Joel + Elton John | B49: 11391 | C49: 149
A50: Elf | B50: 11075 | C50: 168
A51: Harry Potter | B51: 10715 | C51: 155
A52: It's a wonderful life | B52: 9126 | C52: 129
A53: Music of Journey | B53: 6150 | C53: 91
A54: Ben Rector | B54: 6140 | C54: 60
A56: Traffic Acquistion
A57: SOURCE | B57: SESSIONS
A58: Organic Search
A59: Direct
A60: Paid Social
A61: Referral
A62: Organic Social
