Workbook

Sheet Performances by Week
E1: Status: | F1: Updated 10/27 | H1: Denotes Piazza | I1: Update all fields in Blue each week | J1: We expect 50% of Single Sales 1 Week Prior | K1: 85%+ occupancy | V1: 100%+ of Target
K2: 70-85% occupancy | V2: 90-99% of Target
G3: Week # | K3: <70% occupancy | V3: <90% of Target
D4: TICKET SALES REPORT as of 10/27/2025 | G4: 9 | I4: TOTAL SALES (Singles + Subs) | S4: Single Tickets | AC4: Subscription Tickets | AG4: Hall Data | AJ4: Audience Data | AM4: Revenue last week | AN4: Increase over week
A5: Wk # | B5: # Weeks Until Perf | C5: Perf. Week (Mon) | D5: Performance | G5: Performance Date(s) | H5: Performance Type | I5: % OCC Target | J5: Actual OCC SOLD | K5: Actual Total Tickets Sold | L5: Total Actual Revenue | M5: TOTAL BUDGET | N5: Actual - Budget | O5: Projected Total OCC at Performance | P5: Projected Total Tickets Sold | Q5: Projected Total Revenue | R5: Projected- Budget | S5: Actual Single Tickets Sold | T5: Maximum Single Ticket Capacity | U5: Target Single Tickets for % OCC Target | V5: Projected Single Tickets | W5: Projected Single Ticket Revenue | X5: Projected Single Tickets vs % OCC Target | Y5: Actual Revenue | Z5: BUDGET | AA5: Actual/ Budget % | AB5: Projected/ Budget % | AC5: Actual Sub Tickets Sold | AD5: Actual Revenue | AE5: BUDGET | AF5: Actual vs Budget % | AG5: Max CAP | AH5: Single Ticket ATP | AI5: # New HH | AJ5: # Ret HH | AK5: # Total HH
A6: 1 | B6: =A6-$G$4 -> -8 | C6: 45901 | D6: 26 Morgan Freeman's Symphonic Blues | G6: 45902.833 | H6: Specials | I6: 0.85 | J6: =K6/AG6 -> 0.89093702 | K6: =S6+AC6 -> 1160 | L6: =Y6+AD6 -> 137698 | M6: =Z6+AE6 -> 153473 | N6: =L6-M6 -> -15775 | O6: =IF(P6="Too early",P6,P6/AG6) -> #N/A | P6: =IF(V6="Too early",V6,V6+AC6) -> #N/A | Q6: =AD6+V6*AH6 -> #N/A | R6: =IF(V6="Too early",V6,Q6-M6) -> #N/A | S6: 1160 | T6: =AG6-AC6 -> 1302 | U6: =(AG6-AC6)*I6 -> 1106.7 | V6: =IF(B6<11,MIN((S6/VLOOKUP(B6,'Sales Pacing'!$A$23:$E$36,2)),T6),"Too early") -> #N/A | W6: =Q6-AD6 -> #N/A | X6: =IF(V6="Too early","Too early",V6/U6) -> #N/A | Y6: 137698 | Z6: 153473 | AA6: =IF(Y6>0,Y6/Z6,"") -> 0.89721319 | AB6: =IF($V6="Too early",V6,V6*AH6/Z6) -> #N/A | AE6: 0 | AF6: =IF(AD6>0,AD6/AE6,"") | AG6: 1302 | AH6: =Y6/S6 -> 118.70517 | AI6: 228 | AJ6: 295 | AK6: 523 | AL6: 137698 | AM6: =L6-AL6 -> 0
A7: 1 | B7: =A7-$G$4 -> -8 | C7: 45901 | D7: 26 Morgan Freeman's Symphonic Blues | G7: 45903.833 | H7: Specials | I7: 0.85 | J7: =K7/AG7 -> 0.87480799 | K7: =S7+AC7 -> 1139 | L7: =Y7+AD7 -> 134386 | M7: =Z7+AE7 -> 153474 | N7: =L7-M7 -> -19088 | O7: =IF(P7="Too early",P7,P7/AG7) -> #N/A | P7: =IF(V7="Too early",V7,V7+AC7) -> #N/A | Q7: =AD7+V7*AH7 -> #N/A | R7: =IF(V7="Too early",V7,Q7-M7) -> #N/A | S7: 1139 | T7: =AG7-AC7 -> 1302 | U7: =(AG7-AC7)*I7 -> 1106.7 | V7: =IF(B7<11,MIN((S7/VLOOKUP(B7,'Sales Pacing'!$A$23:$E$36,2)),T7),"Too early") -> #N/A | W7: =Q7-AD7 -> #N/A | X7: =IF(V7="Too early","Too early",V7/U7) -> #N/A | Y7: 134386 | Z7: 153474 | AA7: =IF(Y7>0,Y7/Z7,"") -> 0.87562714 | AB7: =IF($V7="Too early",V7,V7*AH7/Z7) -> #N/A | AE7: 0 | AF7: =IF(AD7>0,AD7/AE7,"") | AG7: 1302 | AH7: =Y7/S7 -> 117.98595 | AI7: 227 | AJ7: 289 | AK7: 516 | AL7: 134386 | AM7: =L7-AL7 -> 0
A8: 1 | B8: =A8-$G$4 -> -8 | C8: 45901 | D8: 26 La nuit sombre | G8: 45905.833 | H8: Specials | I8: 0.85 | J8: =K8/AG8 -> 1.165 | K8: =S8+AC8 -> 699 | L8: =Y8+AD8 -> 20005 | M8: =Z8+AE8 -> 55000 | N8: =L8-M8 -> -34995 | O8: =IF(P8="Too early",P8,P8/AG8) -> #N/A | P8: =IF(V8="Too early",V8,V8+AC8) -> #N/A | Q8: =AD8+V8*AH8 -> #N/A | R8: =IF(V8="Too early",V8,Q8-M8) -> #N/A | S8: 699 | T8: =AG8-AC8 -> 600 | U8: =(AG8-AC8)*I8 -> 510 | V8: =IF(B8<11,MIN((S8/VLOOKUP(B8,'Sales Pacing'!$A$23:$E$36,2)),T8),"Too early") -> #N/A | W8: =Q8-AD8 -> #N/A | X8: =IF(V8="Too early","Too early",V8/U8) -> #N/A | Y8: 20005 | Z8: 55000 | AA8: =IF(Y8>0,Y8/Z8,"") -> 0.36372727 | AB8: =IF($V8="Too early",V8,V8*AH8/Z8) -> #N/A | AE8: 0 | AF8: =IF(AD8>0,AD8/AE8,"") | AG8: 600 | AH8: =Y8/S8 -> 28.619456 | AI8: 86 | AJ8: 209 | AK8: 295 | AL8: 20005 | AM8: =L8-AL8 -> 0
A9: 2 | B9: =A9-$G$4 -> -7 | C9: 45908 | D9: OPEN - Recording Week | J9: =K9/AG9 -> #DIV/0! | K9: =S9+AC9 -> 0 | P9: =IF(V9="Too early",V9,V9+AC9) -> #N/A | Q9: =AD9+V9*AH9 -> #N/A | R9: =IF(V9="Too early",V9,Q9-M9) -> #N/A | T9: =AG9-AC9 -> 0 | U9: =(AG9-AC9)*I9 -> 0 | V9: =IF(B9<11,MIN((S9/VLOOKUP(B9,'Sales Pacing'!$A$23:$E$36,2)),T9),"Too early") -> #N/A | W9: =Q9-AD9 -> #N/A | AA9: =IF(Y9>0,Y9/Z9,"") | AF9: N/A
A10: 3 | B10: =A10-$G$4 -> -6 | C10: 45915 | D10: 26 PS1 Music of Journey | G10: 45919.833 | H10: Pops | I10: 0.85 | J10: =K10/AG10 -> 0.70880503 | K10: =S10+AC10 -> 1127 | L10: =Y10+AD10 -> 75282.6 | M10: =Z10+AE10 -> 100666 | N10: =L10-M10 -> -25383.4 | O10: =IF(P10="Too early",P10,P10/AG10) -> #N/A | P10: =IF(V10="Too early",V10,V10+AC10) -> #N/A | Q10: =AD10+V10*AH10 -> #N/A | R10: =IF(V10="Too early",V10,Q10-M10) -> #N/A | S10: =508+4 -> 512 | T10: =AG10-AC10 -> 975 | U10: =(AG10-AC10)*I10 -> 828.75 | V10: =IF(B10<11,MIN((S10/VLOOKUP(B10,'Sales Pacing'!$A$23:$E$36,2)),T10),"Too early") -> #N/A | W10: =Q10-AD10 -> #N/A | X10: =IF(V10="Too early","Too early",V10/U10) -> #N/A | Y10: =29619+295 -> 29914 | Z10: 59333 | AA10: =IF(Y10>0,Y10/Z10,"") -> 0.50417137 | AB10: =IF($V10="Too early",V10,V10*AH10/Z10) -> #N/A | AC10: 615 | AD10: 45368.6 | AE10: 41333 | AF10: =IF(AD10>0,AD10/AE10,"") -> 1.0976363 | AG10: 1590 | AH10: =Y10/S10 -> 58.425781 | AI10: 67 | AJ10: 416 | AK10: 483 | AL10: 71854.6 | AM10: =L10-AL10 -> 3428
A11: 3 | B11: =A11-$G$4 -> -6 | C11: 45915 | D11: 26 PS1 Music of Journey | G11: 45920.833 | H11: Pops | I11: 0.85 | J11: =K11/AG11 -> 0.67169811 | K11: =S11+AC11 -> 1068 | L11: =Y11+AD11 -> 74220.3 | M11: =Z11+AE11 -> 100667 | N11: =L11-M11 -> -26446.7 | O11: =IF(P11="Too early",P11,P11/AG11) -> #N/A | P11: =IF(V11="Too early",V11,V11+AC11) -> #N/A | Q11: =AD11+V11*AH11 -> #N/A | R11: =IF(V11="Too early",V11,Q11-M11) -> #N/A | S11: =550+4 -> 554 | T11: =AG11-AC11 -> 1076 | U11: =(AG11-AC11)*I11 -> 914.6 | V11: =IF(B11<11,MIN((S11/VLOOKUP(B11,'Sales Pacing'!$A$23:$E$36,2)),T11),"Too early") -> #N/A | W11: =Q11-AD11 -> #N/A | X11: =IF(V11="Too early","Too early",V11/U11) -> #N/A | Y11: =35384+288 -> 35672 | Z11: 59333 | AA11: =IF(Y11>0,Y11/Z11,"") -> 0.60121686 | AB11: =IF($V11="Too early",V11,V11*AH11/Z11) -> #N/A | AC11: 514 | AD11: 38548.3 | AE11: 41334 | AF11: =IF(AD11>0,AD11/AE11,"") -> 0.93260512 | AG11: 1590 | AH11: =Y11/S11 -> 64.389892 | AI11: 78 | AJ11: 376 | AK11: 454 | AL11: 70013.3 | AM11: =L11-AL11 -> 4207
A12: 3 | B12: =A12-$G$4 -> -6 | C12: 45915 | D12: 26 PS1 Music of Journey | G12: 45921.583 | H12: Pops | I12: 0.85 | J12: =K12/AG12 -> 0.63018868 | K12: =S12+AC12 -> 1002 | L12: =Y12+AD12 -> 63946.8 | M12: =Z12+AE12 -> 100667 | N12: =L12-M12 -> -36720.2 | O12: =IF(P12="Too early",P12,P12/AG12) -> #N/A | P12: =IF(V12="Too early",V12,V12+AC12) -> #N/A | Q12: =AD12+V12*AH12 -> #N/A | R12: =IF(V12="Too early",V12,Q12-M12) -> #N/A | S12: =656+2 -> 658 | T12: =AG12-AC12 -> 1246 | U12: =(AG12-AC12)*I12 -> 1059.1 | V12: =IF(B12<11,MIN((S12/VLOOKUP(B12,'Sales Pacing'!$A$23:$E$36,2)),T12),"Too early") -> #N/A | W12: =Q12-AD12 -> #N/A | X12: =IF(V12="Too early","Too early",V12/U12) -> #N/A | Y12: =39634+165 -> 39799 | Z12: 59334 | AA12: =IF(Y12>0,Y12/Z12,"") -> 0.67076213 | AB12: =IF($V12="Too early",V12,V12*AH12/Z12) -> #N/A | AC12: 344 | AD12: 24147.8 | AE12: 41333 | AF12: =IF(AD12>0,AD12/AE12,"") -> 0.58422568 | AG12: 1590 | AH12: =Y12/S12 -> 60.484802 | AI12: 74 | AJ12: 286 | AK12: 360 | AL12: 56072.3 | AM12: =L12-AL12 -> 7874.5
A13: 4 | B13: =A13-$G$4 -> -5 | C13: 45922 | D13: 26 FS1 The Orchestra Games | G13: 45928.583 | H13: Family | I13: 0.5 | J13: =K13/AG13 -> 0.55376344 | K13: =S13+AC13 -> 721 | L13: =Y13+AD13 -> 16696 | M13: =Z13+AE13 -> 19500 | N13: =L13-M13 -> -2804 | O13: =IF(P13="Too early",P13,P13/AG13) -> #N/A | P13: =IF(V13="Too early",V13,V13+AC13) -> #N/A | Q13: =IF(V13="Too early",V13,AD13+V13*AH13) -> #N/A | R13: =IF(V13="Too early",V13,Q13-M13) -> #N/A | S13: 503 | T13: =AG13-AC13 -> 1084 | U13: =(AG13-AC13)*I13 -> 542 | V13: =IF(B13<11,MIN((S13/VLOOKUP(B13,'Sales Pacing'!$A$23:$E$36,2)),T13),"Too early") -> #N/A | W13: =Q13-AD13 -> #N/A | X13: =IF(V13="Too early","Too early",V13/U13) -> #N/A | Y13: 10721 | Z13: 10000 | AA13: =IF(Y13>0,Y13/Z13,"") -> 1.0721 | AB13: =IF($V13="Too early",V13,V13*AH13/Z13) -> #N/A | AC13: 218 | AD13: 5975 | AE13: 9500 | AF13: =IF(AD13>0,AD13/AE13,"") -> 0.62894737 | AG13: 1302 | AH13: =Y13/S13 -> 21.314115 | AI13: 21 | AJ13: 104 | AK13: 125 | AL13: 12684 | AM13: =L13-AL13 -> 4012
A14: 5 | B14: =A14-$G$4 -> -4 | C14: 45929 | D14: OPEN - was Chicken Fried | J14: =K14/AG14 -> #DIV/0! | Q14: =IF(V14="Too early",V14,AD14+V14*AH14) -> #N/A | R14: =IF(V14="Too early",V14,Q14-M14) -> #N/A | T14: =AG14-AC14 -> 0 | U14: =(AG14-AC14)*I14 -> 0 | V14: =IF(B14<11,MIN((S14/VLOOKUP(B14,'Sales Pacing'!$A$23:$E$36,2)),T14),"Too early") -> #N/A | W14: =Q14-AD14 -> #N/A
A15: 6 | B15: =A15-$G$4 -> -3 | C15: 45936 | D15: 26 CS01 Appalachian Spring | G15: 45940.833 | H15: Classical | I15: 0.85 | J15: =K15/AG15 -> 0.75575715 | K15: =S15+AC15 -> 1083 | L15: =Y15+AD15 -> 62663 | M15: =Z15+AE15 -> 50000 | N15: =L15-M15 -> 12663 | O15: =IF(P15="Too early",P15,P15/AG15) -> #N/A | P15: =IF(V15="Too early",V15,V15+AC15) -> #N/A | Q15: =IF(V15="Too early",V15,AD15+V15*AH15) -> #N/A | R15: =IF(V15="Too early",V15,Q15-M15) -> #N/A | S15: =623+17 -> 640 | T15: =AG15-AC15 -> 990 | U15: =(AG15-AC15)*I15 -> 841.5 | V15: =IF(B15<11,MIN((S15/VLOOKUP(B15,'Sales Pacing'!$A$23:$E$36,2)),T15),"Too early") -> #N/A | W15: =Q15-AD15 -> #N/A | X15: =IF(V15="Too early","Too early",V15/U15) -> #N/A | Y15: =31125+1209 -> 32334 | Z15: 16667 | AA15: =IF(Y15>0,Y15/Z15,"") -> 1.9400012 | AB15: =IF($V15="Too early",V15,V15*AH15/Z15) -> #N/A | AC15: 443 | AD15: 30329 | AE15: 33333 | AF15: =IF(AD15>0,AD15/AE15,"") -> 0.9098791 | AG15: 1433 | AH15: =Y15/S15 -> 50.521875 | AI15: 13 | AJ15: 370 | AK15: 383 | AL15: 47640 | AM15: =L15-AL15 -> 15023
A16: 6 | B16: =A16-$G$4 -> -3 | C16: 45936 | D16: 26 CS01 Appalachian Spring | G16: 45941.833 | H16: Classical | I16: 0.85 | J16: =K16/AG16 -> 0.78157711 | K16: =S16+AC16 -> 1120 | L16: =Y16+AD16 -> 67352.7 | M16: =Z16+AE16 -> 50000 | N16: =L16-M16 -> 17352.7 | O16: =IF(P16="Too early",P16,P16/AG16) -> #N/A | P16: =IF(V16="Too early",V16,V16+AC16) -> #N/A | Q16: =IF(V16="Too early",V16,AD16+V16*AH16) -> #N/A | R16: =IF(V16="Too early",V16,Q16-M16) -> #N/A | S16: =628+28 -> 656 | T16: =AG16-AC16 -> 969 | U16: =(AG16-AC16)*I16 -> 823.65 | V16: =IF(B16<11,MIN((S16/VLOOKUP(B16,'Sales Pacing'!$A$23:$E$36,2)),T16),"Too early") -> #N/A | W16: =Q16-AD16 -> #N/A | X16: =IF(V16="Too early","Too early",V16/U16) -> #N/A | Y16: =32749+1801 -> 34550 | Z16: 16667 | AA16: =IF(Y16>0,Y16/Z16,"") -> 2.0729585 | AB16: =IF($V16="Too early",V16,V16*AH16/Z16) -> #N/A | AC16: 464 | AD16: 32802.7 | AE16: 33333 | AF16: =IF(AD16>0,AD16/AE16,"") -> 0.98409084 | AG16: 1433 | AH16: =Y16/S16 -> 52.667683 | AI16: 21 | AJ16: 386 | AK16: 407 | AL16: 55614.1 | AM16: =L16-AL16 -> 11738.6
A17: 6 | B17: =A17-$G$4 -> -3 | C17: 45936 | D17: 26 CS01 Appalachian Spring | G17: 45942.583 | H17: Classical | I17: 0.85 | J17: =K17/AG17 -> 0.86461968 | K17: =S17+AC17 -> 1239 | L17: =Y17+AD17 -> 72775.2 | M17: =Z17+AE17 -> 50000 | N17: =L17-M17 -> 22775.2 | O17: =IF(P17="Too early",P17,P17/AG17) -> #N/A | P17: =IF(V17="Too early",V17,V17+AC17) -> #N/A | Q17: =IF(V17="Too early",V17,AD17+V17*AH17) -> #N/A | R17: =IF(V17="Too early",V17,Q17-M17) -> #N/A | S17: =708+19 -> 727 | T17: =AG17-AC17 -> 921 | U17: =(AG17-AC17)*I17 -> 782.85 | V17: =IF(B17<11,MIN((S17/VLOOKUP(B17,'Sales Pacing'!$A$23:$E$36,2)),T17),"Too early") -> #N/A | W17: =Q17-AD17 -> #N/A | X17: =IF(V17="Too early","Too early",V17/U17) -> #N/A | Y17: =37234+1325 -> 38559 | Z17: 16666 | AA17: =IF(Y17>0,Y17/Z17,"") -> 2.3136325 | AB17: =IF($V17="Too early",V17,V17*AH17/Z17) -> #N/A | AC17: 512 | AD17: 34216.2 | AE17: 33334 | AF17: =IF(AD17>0,AD17/AE17,"") -> 1.0264655 | AG17: 1433 | AH17: =Y17/S17 -> 53.038514 | AI17: 17 | AJ17: 455 | AK17: 472 | AL17: 57932.6 | AM17: =L17-AL17 -> 14842.6
A18: 7 | B18: =A18-$G$4 -> -2 | C18: 45943 | D18: 26 Top Gun: Maverick in Concert | G18: 45947.792 | H18: Specials/Film | I18: 0.85 | J18: =K18/AG18 -> 0.87034277 | K18: =S18+AC18 -> 1168 | L18: =Y18+AD18 -> 87476 | M18: =Z18+AE18 -> 103497 | N18: =L18-M18 -> -16021 | O18: =IF(P18="Too early",P18,P18/AG18) -> #N/A | P18: =IF(V18="Too early",V18,V18+AC18) -> #N/A | Q18: =IF(V18="Too early",V18,AD18+V18*AH18) -> #N/A | R18: =IF(V18="Too early",V18,Q18-M18) -> #N/A | S18: =1162+6 -> 1168 | T18: =AG18-AC18 -> 1342 | U18: =(AG18-AC18)*I18 -> 1140.7 | V18: =IF(B18<11,MIN((S18/VLOOKUP(B18,'Sales Pacing'!$A$23:$E$36,2)),T18),"Too early") -> #N/A | W18: =Q18-AD18 -> #N/A | X18: =IF(V18="Too early","Too early",V18/U18) -> #N/A | Y18: =87153+323 -> 87476 | Z18: 103497 | AA18: =IF(Y18>0,Y18/Z18,"") -> 0.84520324 | AB18: =IF($V18="Too early",V18,V18*AH18/Z18) -> #N/A | AF18: =IF(AD18>0,AD18/AE18,"") | AG18: 1342 | AH18: =Y18/S18 -> 74.893836 | AI18: 51 | AJ18: 179 | AK18: 230 | AL18: 48750 | AM18: =L18-AL18 -> 38726
A19: 7 | B19: =A19-$G$4 -> -2 | C19: 45943 | D19: 26 Top Gun: Maverick in Concert | G19: 45948.792 | H19: Specials/Film | I19: 0.85 | J19: =K19/AG19 -> 0.9538003 | K19: =S19+AC19 -> 1280 | L19: =Y19+AD19 -> 97657 | M19: =Z19+AE19 -> 103497 | N19: =L19-M19 -> -5840 | O19: =IF(P19="Too early",P19,P19/AG19) -> #N/A | P19: =IF(V19="Too early",V19,V19+AC19) -> #N/A | Q19: =IF(V19="Too early",V19,AD19+V19*AH19) -> #N/A | R19: =IF(V19="Too early",V19,Q19-M19) -> #N/A | S19: =1268+12 -> 1280 | T19: =AG19-AC19 -> 1342 | U19: =(AG19-AC19)*I19 -> 1140.7 | V19: =IF(B19<11,MIN((S19/VLOOKUP(B19,'Sales Pacing'!$A$23:$E$36,2)),T19),"Too early") -> #N/A | W19: =Q19-AD19 -> #N/A | X19: =IF(V19="Too early","Too early",V19/U19) -> #N/A | Y19: =96649+1008 -> 97657 | Z19: 103497 | AA19: =IF(Y19>0,Y19/Z19,"") -> 0.94357324 | AB19: =IF($V19="Too early",V19,V19*AH19/Z19) -> #N/A | AF19: =IF(AD19>0,AD19/AE19,"") | AG19: 1342 | AH19: =Y19/S19 -> 76.294531 | AI19: 74 | AJ19: 184 | AK19: 258 | AL19: 60628 | AM19: =L19-AL19 -> 37029
A20: 7 | B20: =A20-$G$4 -> -2 | C20: 45943 | D20: 26 Top Gun: Maverick in Concert | G20: 45949.583 | H20: Specials/Film | I20: 0.85 | J20: =K20/AG20 -> 0.74217586 | K20: =S20+AC20 -> 996 | L20: =Y20+AD20 -> 78145 | M20: =Z20+AE20 -> 103496 | N20: =L20-M20 -> -25351 | O20: =IF(P20="Too early",P20,P20/AG20) -> #N/A | P20: =IF(V20="Too early",V20,V20+AC20) -> #N/A | Q20: =IF(V20="Too early",V20,AD20+V20*AH20) -> #N/A | R20: =IF(V20="Too early",V20,Q20-M20) -> #N/A | S20: =982+14 -> 996 | T20: =AG20-AC20 -> 1342 | U20: =(AG20-AC20)*I20 -> 1140.7 | V20: =IF(B20<11,MIN((S20/VLOOKUP(B20,'Sales Pacing'!$A$23:$E$36,2)),T20),"Too early") -> #N/A | W20: =Q20-AD20 -> #N/A | X20: =IF(V20="Too early","Too early",V20/U20) -> #N/A | Y20: =77074+1071 -> 78145 | Z20: 103496 | AA20: =IF(Y20>0,Y20/Z20,"") -> 0.75505334 | AB20: =IF($V20="Too early",V20,V20*AH20/Z20) -> #N/A | AF20: =IF(AD20>0,AD20/AE20,"") | AG20: 1342 | AH20: =Y20/S20 -> 78.458835 | AI20: 38 | AJ20: 149 | AK20: 187 | AL20: 44494 | AM20: =L20-AL20 -> 33651
A21: 8 | B21: =A21-$G$4 -> -1 | C21: 45950 | D21: 26 The Lodger | G21: 45952.792 | H21: Specials/Film | I21: 0.5 | J21: =K21/AG21 -> 0.28092399 | K21: =S21+AC21 -> 377 | L21: =Y21+AD21 -> 19285 | M21: =Z21+AE21 -> 50000 | N21: =L21-M21 -> -30715 | O21: =IF(P21="Too early",P21,P21/AG21) -> #N/A | P21: =IF(V21="Too early",V21,V21+AC21) -> #N/A | Q21: =IF(V21="Too early",V21,AD21+V21*AH21) -> #N/A | R21: =IF(V21="Too early",V21,Q21-M21) -> #N/A | S21: =375+2 -> 377 | T21: =AG21-AC21 -> 1342 | U21: =(AG21-AC21)*I21 -> 671 | V21: =IF(B21<11,MIN((S21/VLOOKUP(B21,'Sales Pacing'!$A$23:$E$36,2)),T21),"Too early") -> #N/A | W21: =Q21-AD21 -> #N/A | X21: =IF(V21="Too early","Too early",V21/U21) -> #N/A | Y21: 19285 | Z21: 50000 | AA21: =IF(Y21>0,Y21/Z21,"") -> 0.3857 | AB21: =IF($V21="Too early",V21,V21*AH21/Z21) -> #N/A | AF21: =IF(AD21>0,AD21/AE21,"") | AG21: 1342 | AH21: =Y21/S21 -> 51.153846 | AI21: 5 | AJ21: 78 | AK21: 83 | AL21: 10588 | AM21: =L21-AL21 -> 8697
A22: 8 | B22: =A22-$G$4 -> -1 | C22: 45950 | D22: 26 PS2 90s Mixtape | G22: 45954.833 | H22: Pops | I22: 0.85 | J22: =K22/AG22 -> 0.57026858 | K22: =S22+AC22 -> 913 | L22: =Y22+AD22 -> 63970 | M22: =Z22+AE22 -> 92333 | N22: =L22-M22 -> -28363 | O22: =IF(P22="Too early",P22,P22/AG22) -> #N/A | P22: =IF(V22="Too early",V22,V22+AC22) -> #N/A | Q22: =IF(V22="Too early",V22,AD22+V22*AH22) -> #N/A | R22: =IF(V22="Too early",V22,Q22-M22) -> #N/A | S22: =271+6 -> 277 | T22: =AG22-AC22 -> 965 | U22: =(AG22-AC22)*I22 -> 820.25 | V22: =IF(B22<11,MIN((S22/VLOOKUP(B22,'Sales Pacing'!$A$23:$E$36,2)),T22),"Too early") -> #N/A | W22: =Q22-AD22 -> #N/A | X22: =IF(V22="Too early","Too early",V22/U22) -> #N/A | Y22: =16908+370 -> 17278 | Z22: 53333 | AA22: =IF(Y22>0,Y22/Z22,"") -> 0.32396452 | AB22: =IF($V22="Too early",V22,V22*AH22/Z22) -> #N/A | AC22: 636 | AD22: 46692 | AE22: 39000 | AF22: =IF(AD22>0,AD22/AE22,"") -> 1.1972308 | AG22: 1601 | AH22: =Y22/S22 -> 62.375451 | AI22: 7 | AJ22: 350 | AK22: 357 | AL22: 57609.1 | AM22: =L22-AL22 -> 6360.9
A23: 8 | B23: =A23-$G$4 -> -1 | C23: 45950 | D23: 26 PS2 90s Mixtape | G23: 45955.833 | H23: Pops | I23: 0.85 | J23: =K23/AG23 -> 0.64022486 | K23: =S23+AC23 -> 1025 | L23: =Y23+AD23 -> 63357 | M23: =Z23+AE23 -> 92333 | N23: =L23-M23 -> -28976 | O23: =IF(P23="Too early",P23,P23/AG23) -> #N/A | P23: =IF(V23="Too early",V23,V23+AC23) -> #N/A | Q23: =IF(V23="Too early",V23,AD23+V23*AH23) -> #N/A | R23: =IF(V23="Too early",V23,Q23-M23) -> #N/A | S23: =488+3 -> 491 | T23: =AG23-AC23 -> 1067 | U23: =(AG23-AC23)*I23 -> 906.95 | V23: =IF(B23<11,MIN((S23/VLOOKUP(B23,'Sales Pacing'!$A$23:$E$36,2)),T23),"Too early") -> #N/A | W23: =Q23-AD23 -> #N/A | X23: =IF(V23="Too early","Too early",V23/U23) -> #N/A | Y23: =24042+217 -> 24259 | Z23: 53333 | AA23: =IF(Y23>0,Y23/Z23,"") -> 0.45485909 | AB23: =IF($V23="Too early",V23,V23*AH23/Z23) -> #N/A | AC23: 534 | AD23: 39098 | AE23: 39000 | AF23: =IF(AD23>0,AD23/AE23,"") -> 1.0025128 | AG23: 1601 | AH23: =Y23/S23 -> 49.407332 | AI23: 11 | AJ23: 320 | AK23: 311 | AL23: 52382.8 | AM23: =L23-AL23 -> 10974.2
A24: 8 | B24: =A24-$G$4 -> -1 | C24: 45950 | D24: 26 PS2 90s Mixtape | G24: 45956.583 | H24: Pops | I24: 0.85 | J24: =K24/AG24 -> 0.5321674 | K24: =S24+AC24 -> 852 | L24: =Y24+AD24 -> 44080 | M24: =Z24+AE24 -> 92334 | N24: =L24-M24 -> -48254 | O24: =IF(P24="Too early",P24,P24/AG24) -> #N/A | P24: =IF(V24="Too early",V24,V24+AC24) -> #N/A | Q24: =IF(V24="Too early",V24,AD24+V24*AH24) -> #N/A | R24: =IF(V24="Too early",V24,Q24-M24) -> #N/A | S24: =515+4 -> 519 | T24: =AG24-AC24 -> 1268 | U24: =(AG24-AC24)*I24 -> 1077.8 | V24: =IF(B24<11,MIN((S24/VLOOKUP(B24,'Sales Pacing'!$A$23:$E$36,2)),T24),"Too early") -> #N/A | W24: =Q24-AD24 -> #N/A | X24: =IF(V24="Too early","Too early",V24/U24) -> #N/A | Y24: =20477+360 -> 20837 | Z24: 53334 | AA24: =IF(Y24>0,Y24/Z24,"") -> 0.39068887 | AB24: =IF($V24="Too early",V24,V24*AH24/Z24) -> #N/A | AC24: 333 | AD24: 23243 | AE24: 39000 | AF24: =IF(AD24>0,AD24/AE24,"") -> 0.59597436 | AG24: 1601 | AH24: =Y24/S24 -> 40.148362 | AI24: 6 | AJ24: 209 | AK24: 203 | AL24: 31818.5 | AM24: =L24-AL24 -> 12261.5
A25: 9 | B25: =A25-$G$4 -> 0 | C25: 45957 | D25: 26 On-Stage 1 George Li | G25: 45959.833 | H25: On Stage | I25: 0.85 | J25: =K25/AG25 -> 0.38 | K25: =S25+AC25 -> 38 | L25: =Y25+AD25 -> 4620 | M25: 11200 | N25: =L25-M25 -> -6580 | O25: =IF(P25="Too early",P25,P25/AG25) -> 0.38 | P25: =IF(V25="Too early",V25,V25+AC25) -> 38 | Q25: =IF(V25="Too early",V25,AD25+V25*AH25) -> 4620 | R25: =IF(V25="Too early",V25,Q25-M25) -> -6580 | S25: 38 | T25: =AG25-AC25 -> 100 | U25: =(AG25-AC25)*I25 -> 85 | V25: =IF(B25<11,MIN((S25/VLOOKUP(B25,'Sales Pacing'!$A$23:$E$36,2)),T25),"Too early") -> 38 | W25: =Q25-AD25 -> 4620 | X25: =IF(V25="Too early","Too early",V25/U25) -> 0.44705882 | Y25: 4620 | Z25: 11200 | AA25: =IF(Y25>0,Y25/Z25,"") -> 0.4125 | AB25: =IF($V25="Too early",V25,V25*AH25/Z25) -> 0.4125 | AF25: =IF(AD25>0,AD25/AE25,"") | AG25: 100 | AH25: =Y25/S25 -> 121.57895 | AI25: 0 | AJ25: 11 | AK25: 11 | AL25: 2800 | AM25: =L25-AL25 -> 1820
A26: 9 | B26: =A26-$G$4 -> 0 | C26: 45957 | D26: 26 CS02 Rachmaninoff Cele Pt 1 | G26: 45961.833 | H26: Classical | I26: 0.5 | J26: =K26/AG26 -> 0.44 | K26: =S26+AC26 -> 638 | L26: =Y26+AD26 -> 37062 | M26: =Z26+AE26 -> 52000 | N26: =L26-M26 -> -14938 | O26: =IF(P26="Too early",P26,P26/AG26) -> 0.44 | P26: =IF(V26="Too early",V26,V26+AC26) -> 638 | Q26: =IF(V26="Too early",V26,AD26+V26*AH26) -> 37062 | R26: =IF(V26="Too early",V26,Q26-M26) -> -14938 | S26: =316+14 -> 330 | T26: =AG26-AC26 -> 1142 | U26: =(AG26-AC26)*I26 -> 571 | V26: =IF(B26<11,MIN((S26/VLOOKUP(B26,'Sales Pacing'!$A$23:$E$36,2)),T26),"Too early") -> 330 | W26: =Q26-AD26 -> 15733 | X26: =IF(V26="Too early","Too early",V26/U26) -> 0.57793345 | Y26: =14842+891 -> 15733 | Z26: 22000 | AA26: =IF(Y26>0,Y26/Z26,"") -> 0.71513636 | AB26: =IF($V26="Too early",V26,V26*AH26/Z26) -> 0.71513636 | AC26: 308 | AD26: 21329 | AE26: 30000 | AF26: =IF(AD26>0,AD26/AE26,"") -> 0.71096667 | AG26: 1450 | AH26: =Y26/S26 -> 47.675758 | AI26: 10 | AJ26: 222 | AK26: 232 | AL26: 30757 | AM26: =L26-AL26 -> 6305
A27: 9 | B27: =A27-$G$4 -> 0 | C27: 45957 | D27: 26 CS02 Rachmaninoff Cele Pt 1 | G27: 45962.833 | H27: Classical | I27: 0.85 | J27: =K27/AG27 -> 0.90965517 | K27: =S27+AC27 -> 1319 | L27: =Y27+AD27 -> 77243 | M27: =Z27+AE27 -> 86500 | N27: =L27-M27 -> -9257 | O27: =IF(P27="Too early",P27,P27/AG27) -> 0.90965517 | P27: =IF(V27="Too early",V27,V27+AC27) -> 1319 | Q27: =IF(V27="Too early",V27,AD27+V27*AH27) -> 77243 | R27: =IF(V27="Too early",V27,Q27-M27) -> -9257 | S27: =790+22 -> 812 | T27: =AG27-AC27 -> 943 | U27: =(AG27-AC27)*I27 -> 801.55 | V27: =IF(B27<11,MIN((S27/VLOOKUP(B27,'Sales Pacing'!$A$23:$E$36,2)),T27),"Too early") -> 812 | W27: =Q27-AD27 -> 43676 | X27: =IF(V27="Too early","Too early",V27/U27) -> 1.0130372 | Y27: =42354+1322 -> 43676 | Z27: 31500 | AA27: =IF(Y27>0,Y27/Z27,"") -> 1.3865397 | AB27: =IF($V27="Too early",V27,V27*AH27/Z27) -> 1.3865397 | AC27: 507 | AD27: 33567 | AE27: 55000 | AF27: =IF(AD27>0,AD27/AE27,"") -> 0.61030909 | AG27: 1450 | AH27: =Y27/S27 -> 53.788177 | AI27: 26 | AJ27: 397 | AK27: 423 | AL27: 57693 | AM27: =L27-AL27 -> 19550
A28: 9 | B28: =A28-$G$4 -> 0 | C28: 45957 | D28: 26 CS02 Rachmaninoff Cele Pt 1 | G28: 45963.583 | H28: Classical | I28: 0.85 | J28: =K28/AG28 -> 0.77862069 | K28: =S28+AC28 -> 1129 | L28: =Y28+AD28 -> 68813 | M28: =Z28+AE28 -> 86500 | N28: =L28-M28 -> -17687 | O28: =IF(P28="Too early",P28,P28/AG28) -> 0.77862069 | P28: =IF(V28="Too early",V28,V28+AC28) -> 1129 | Q28: =IF(V28="Too early",V28,AD28+V28*AH28) -> 68813 | R28: =IF(V28="Too early",V28,Q28-M28) -> -17687 | S28: =568+25 -> 593 | T28: =AG28-AC28 -> 914 | U28: =(AG28-AC28)*I28 -> 776.9 | V28: =IF(B28<11,MIN((S28/VLOOKUP(B28,'Sales Pacing'!$A$23:$E$36,2)),T28),"Too early") -> 593 | W28: =Q28-AD28 -> 34069 | X28: =IF(V28="Too early","Too early",V28/U28) -> 0.76329 | Y28: =32590+1479 -> 34069 | Z28: 31500 | AA28: =IF(Y28>0,Y28/Z28,"") -> 1.0815556 | AB28: =IF($V28="Too early",V28,V28*AH28/Z28) -> 1.0815556 | AC28: 536 | AD28: 34744 | AE28: 55000 | AF28: =IF(AD28>0,AD28/AE28,"") -> 0.63170909 | AG28: 1450 | AH28: =Y28/S28 -> 57.451939 | AI28: 17 | AJ28: 407 | AK28: 424 | AL28: 51432.1 | AM28: =L28-AL28 -> 17380.9
A29: 10 | B29: =A29-$G$4 -> 1 | C29: 45964 | D29: 26 FS2 Carnival of the Animals | G29: 45970.583 | H29: Family | I29: 0.5 | J29: =K29/AG29 -> 0.42391304 | K29: =S29+AC29 -> 585 | L29: =Y29+AD29 -> 15626 | M29: =Z29+AE29 -> 19500 | N29: =L29-M29 -> -3874 | O29: =IF(P29="Too early",P29,P29/AG29) -> 0.55282486 | P29: =IF(V29="Too early",V29,V29+AC29) -> 762.89831 | Q29: =IF(V29="Too early",V29,AD29+V29*AH29) -> 21207.559 | R29: =IF(V29="Too early",V29,Q29-M29) -> 1707.5593 | S29: =252+4 -> 256 | T29: =AG29-AC29 -> 1051 | U29: =(AG29-AC29)*I29 -> 525.5 | V29: =IF(B29<11,MIN((S29/VLOOKUP(B29,'Sales Pacing'!$A$23:$E$36,2)),T29),"Too early") -> 433.89831 | W29: =Q29-AD29 -> 13613.559 | X29: =IF(V29="Too early","Too early",V29/U29) -> 0.82568659 | Y29: =7888+144 -> 8032 | Z29: 10000 | AA29: =IF(Y29>0,Y29/Z29,"") -> 0.8032 | AB29: =IF($V29="Too early",V29,V29*AH29/Z29) -> 1.3613559 | AC29: 329 | AD29: 7594 | AE29: 9500 | AF29: =IF(AD29>0,AD29/AE29,"") -> 0.79936842 | AG29: 1380 | AH29: =Y29/S29 -> 31.375 | AI29: 9 | AJ29: 103 | AK29: 112 | AL29: 10703 | AM29: =L29-AL29 -> 4923
A30: 11 | B30: =A30-$G$4 -> 2 | C30: 45971 | D30: OPEN | J30: =K30/AG30 -> #DIV/0! | K30: =S30+AC30 -> 0 | L30: =Y30+AD30 -> 0 | M30: =Z30+AE30 -> 0 | P30: =IF(V30="Too early",V30,V30+AC30) -> 0 | Q30: =IF(V30="Too early",V30,AD30+V30*AH30) -> #DIV/0! | R30: =IF(V30="Too early",V30,Q30-M30) -> #DIV/0! | T30: =AG30-AC30 -> 0 | U30: =(AG30-AC30)*I30 -> 0 | V30: =IF(B30<7,(S30/VLOOKUP(B30,'Sales Pacing'!$A$23:$E$36,2)),"Too early") -> 0 | W30: =Q30-AD30 -> #DIV/0! | AA30: =IF(Y30>0,Y30/Z30,"") | AF30: N/A | AH30: =Y30/S30 -> #DIV/0! | AL30: 0
A31: 12 | B31: =A31-$G$4 -> 3 | C31: 45978 | D31: 26 CS03 Matthias and Mahler 7 | G31: 45982.833 | H31: Classical | I31: 0.5 | J31: =K31/AG31 -> 0.33416304 | K31: =S31+AC31 -> 537 | L31: =Y31+AD31 -> 34142 | M31: =Z31+AE31 -> 40000 | N31: =L31-M31 -> -5858 | O31: =IF(P31="Too early",P31,P31/AG31) -> 0.5093581 | P31: =IF(V31="Too early",V31,V31+AC31) -> 818.53846 | Q31: =IF(V31="Too early",V31,AD31+V31*AH31) -> 48775.744 | R31: =IF(V31="Too early",V31,Q31-M31) -> 8775.7436 | S31: =167+13 -> 180 | T31: =AG31-AC31 -> 1250 | U31: =(AG31-AC31)*I31 -> 625 | V31: =IF(B31<11,MIN((S31/VLOOKUP(B31,'Sales Pacing'!$A$23:$E$36,2)),T31),"Too early") -> 461.53846 | W31: =Q31-AD31 -> 23989.744 | X31: =IF(V31="Too early","Too early",V31/U31) -> 0.73846154 | Y31: =8573+783 -> 9356 | Z31: 15000 | AA31: =IF(Y31>0,Y31/Z31,"") -> 0.62373333 | AB31: =IF($V31="Too early",V31,V31*AH31/Z31) -> 1.5993162 | AC31: 357 | AD31: 24786 | AE31: 25000 | AF31: =IF(AD31>0,AD31/AE31,"") -> 0.99144 | AG31: 1607 | AH31: =Y31/S31 -> 51.977778 | AI31: 1 | AJ31: 221 | AK31: 222 | AL31: 29114 | AM31: =L31-AL31 -> 5028
A32: 12 | B32: =A32-$G$4 -> 3 | C32: 45978 | D32: 26 CS03 Matthias and Mahler 7 | G32: 45983.833 | H32: Classical | I32: 0.85 | J32: =K32/AG32 -> 0.50342253 | K32: =S32+AC32 -> 809 | L32: =Y32+AD32 -> 52590 | M32: =Z32+AE32 -> 66500 | N32: =L32-M32 -> -13910 | O32: =IF(P32="Too early",P32,P32/AG32) -> 0.73214941 | P32: =IF(V32="Too early",V32,V32+AC32) -> 1176.5641 | Q32: =IF(V32="Too early",V32,AD32+V32*AH32) -> 73522.385 | R32: =IF(V32="Too early",V32,Q32-M32) -> 7022.3846 | S32: =225+10 -> 235 | T32: =AG32-AC32 -> 1033 | U32: =(AG32-AC32)*I32 -> 878.05 | V32: =IF(B32<11,MIN((S32/VLOOKUP(B32,'Sales Pacing'!$A$23:$E$36,2)),T32),"Too early") -> 602.5641 | W32: =Q32-AD32 -> 34315.385 | X32: =IF(V32="Too early","Too early",V32/U32) -> 0.68625261 | Y32: =12689+694 -> 13383 | Z32: 11500 | AA32: =IF(Y32>0,Y32/Z32,"") -> 1.1637391 | AB32: =IF($V32="Too early",V32,V32*AH32/Z32) -> 2.9839465 | AC32: 574 | AD32: 39207 | AE32: 55000 | AF32: =IF(AD32>0,AD32/AE32,"") -> 0.71285455 | AG32: 1607 | AH32: =Y32/S32 -> 56.948936 | AI32: 4 | AJ32: 347 | AK32: 351 | AL32: 47477.9 | AM32: =L32-AL32 -> 5112.1
A33: 12 | B33: =A33-$G$4 -> 3 | C33: 45978 | D33: 26 CS03 Matthias and Mahler 7 | G33: 45984.583 | H33: Classical | I33: 0.85 | J33: =K33/AG33 -> 0.48911014 | K33: =S33+AC33 -> 786 | L33: =Y33+AD33 -> 50274 | M33: =Z33+AE33 -> 66500 | N33: =L33-M33 -> -16226 | O33: =IF(P33="Too early",P33,P33/AG33) -> 0.67209165 | P33: =IF(V33="Too early",V33,V33+AC33) -> 1080.0513 | Q33: =IF(V33="Too early",V33,AD33+V33*AH33) -> 68447.308 | R33: =IF(V33="Too early",V33,Q33-M33) -> 1947.3077 | S33: =172+16 -> 188 | T33: =AG33-AC33 -> 1009 | U33: =(AG33-AC33)*I33 -> 857.65 | V33: =IF(B33<11,MIN((S33/VLOOKUP(B33,'Sales Pacing'!$A$23:$E$36,2)),T33),"Too early") -> 482.05128 | W33: =Q33-AD33 -> 29792.308 | X33: =IF(V33="Too early","Too early",V33/U33) -> 0.56206061 | Y33: =10778+841 -> 11619 | Z33: 11500 | AA33: =IF(Y33>0,Y33/Z33,"") -> 1.0103478 | AB33: =IF($V33="Too early",V33,V33*AH33/Z33) -> 2.5906355 | AC33: 598 | AD33: 38655 | AE33: 55000 | AF33: =IF(AD33>0,AD33/AE33,"") -> 0.70281818 | AG33: 1607 | AH33: =Y33/S33 -> 61.803191 | AI33: 3 | AJ33: 391 | AK33: 394 | AL33: 46613.2 | AM33: =L33-AL33 -> 3660.8
A34: 13 | B34: =A34-$G$4 -> 4 | C34: 45985 | D34: 26 Elf™ in Concert | G34: 45989.792 | H34: Specials/Film | I34: 0.85 | J34: =K34/AG34 -> 0.57603687 | K34: =S34+AC34 -> 750 | L34: =Y34+AD34 -> 52612 | M34: =Z34+AE34 -> 107500 | N34: =L34-M34 -> -54888 | O34: =IF(P34="Too early",P34,P34/AG34) -> 1 | P34: =IF(V34="Too early",V34,V34+AC34) -> 1302 | Q34: =IF(V34="Too early",V34,AD34+V34*AH34) -> 91334.432 | R34: =IF(V34="Too early",V34,Q34-M34) -> -16165.568 | S34: =746+4 -> 750 | T34: =AG34-AC34 -> 1302 | U34: =(AG34-AC34)*I34 -> 1106.7 | V34: =IF(B34<11,MIN((S34/VLOOKUP(B34,'Sales Pacing'!$A$23:$E$36,2)),T34),"Too early") -> 1302 | W34: =Q34-AD34 -> 91334.432 | X34: =IF(V34="Too early","Too early",V34/U34) -> 1.1764706 | Y34: =52269+343 -> 52612 | Z34: 107500 | AA34: =IF(Y34>0,Y34/Z34,"") -> 0.48941395 | AB34: =IF($V34="Too early",V34,V34*AH34/Z34) -> 0.84962262 | AF34: =IF(AD34>0,AD34/AE34,"") | AG34: 1302 | AH34: =Y34/S34 -> 70.149333 | AI34: 17 | AJ34: 45 | AK34: 62 | AL34: 20977.6 | AM34: =L34-AL34 -> 31634.4
A35: 13 | B35: =A35-$G$4 -> 4 | C35: 45985 | D35: 26 Elf™ in Concert | G35: 45990.542 | H35: Specials/Film | I35: 0.85 | J35: =K35/AG35 -> 0.56912442 | K35: =S35+AC35 -> 741 | L35: =Y35+AD35 -> 50110 | M35: =Z35+AE35 -> 107500 | N35: =L35-M35 -> -57390 | O35: =IF(P35="Too early",P35,P35/AG35) -> 1 | P35: =IF(V35="Too early",V35,V35+AC35) -> 1302 | Q35: =IF(V35="Too early",V35,AD35+V35*AH35) -> 88047.53 | R35: =IF(V35="Too early",V35,Q35-M35) -> -19452.47 | S35: =741 -> 741 | T35: =AG35-AC35 -> 1302 | U35: =(AG35-AC35)*I35 -> 1106.7 | V35: =IF(B35<11,MIN((S35/VLOOKUP(B35,'Sales Pacing'!$A$23:$E$36,2)),T35),"Too early") -> 1302 | W35: =Q35-AD35 -> 88047.53 | X35: =IF(V35="Too early","Too early",V35/U35) -> 1.1764706 | Y35: 50110 | Z35: 107500 | AA35: =IF(Y35>0,Y35/Z35,"") -> 0.46613953 | AB35: =IF($V35="Too early",V35,V35*AH35/Z35) -> 0.81904679 | AF35: =IF(AD35>0,AD35/AE35,"") | AG35: 1302 | AH35: =Y35/S35 -> 67.624831 | AI35: 22 | AJ35: 53 | AK35: 75 | AL35: 24414.6 | AM35: =L35-AL35 -> 25695.4
A36: 13 | B36: =A36-$G$4 -> 4 | C36: 45985 | D36: 26 Elf™ in Concert | G36: 45990.792 | H36: Specials/Film | I36: 0.85 | J36: =K36/AG36 -> 0.4969278 | K36: =S36+AC36 -> 647 | L36: =Y36+AD36 -> 45552 | M36: =Z36+AE36 -> 107500 | N36: =L36-M36 -> -61948 | O36: =IF(P36="Too early",P36,P36/AG36) -> 1 | P36: =IF(V36="Too early",V36,V36+AC36) -> 1302 | Q36: =IF(V36="Too early",V36,AD36+V36*AH36) -> 91667.24 | R36: =IF(V36="Too early",V36,Q36-M36) -> -15832.76 | S36: 647 | T36: =AG36-AC36 -> 1302 | U36: =(AG36-AC36)*I36 -> 1106.7 | V36: =IF(B36<11,MIN((S36/VLOOKUP(B36,'Sales Pacing'!$A$23:$E$36,2)),T36),"Too early") -> 1302 | W36: =Q36-AD36 -> 91667.24 | X36: =IF(V36="Too early","Too early",V36/U36) -> 1.1764706 | Y36: 45552 | Z36: 107500 | AA36: =IF(Y36>0,Y36/Z36,"") -> 0.42373953 | AB36: =IF($V36="Too early",V36,V36*AH36/Z36) -> 0.85271851 | AF36: =IF(AD36>0,AD36/AE36,"") | AG36: 1302 | AH36: =Y36/S36 -> 70.404946 | AI36: 12 | AJ36: 56 | AK36: 68 | AL36: 19000 | AM36: =L36-AL36 -> 26552
A37: 13 | B37: =A37-$G$4 -> 4 | C37: 45985 | D37: 26 Elf™ in Concert | G37: 45991.583 | H37: Specials/Film | I37: 0.85 | J37: =K37/AG37 -> 0.66589862 | K37: =S37+AC37 -> 867 | L37: =Y37+AD37 -> 60390 | M37: =Z37+AE37 -> 107500 | N37: =L37-M37 -> -47110 | O37: =IF(P37="Too early",P37,P37/AG37) -> 1 | P37: =IF(V37="Too early",V37,V37+AC37) -> 1302 | Q37: =IF(V37="Too early",V37,AD37+V37*AH37) -> 90689.481 | R37: =IF(V37="Too early",V37,Q37-M37) -> -16810.519 | S37: =857+10 -> 867 | T37: =AG37-AC37 -> 1302 | U37: =(AG37-AC37)*I37 -> 1106.7 | V37: =IF(B37<11,MIN((S37/VLOOKUP(B37,'Sales Pacing'!$A$23:$E$36,2)),T37),"Too early") -> 1302 | W37: =Q37-AD37 -> 90689.481 | X37: =IF(V37="Too early","Too early",V37/U37) -> 1.1764706 | Y37: 60390 | Z37: 107500 | AA37: =IF(Y37>0,Y37/Z37,"") -> 0.56176744 | AB37: =IF($V37="Too early",V37,V37*AH37/Z37) -> 0.84362308 | AF37: =IF(AD37>0,AD37/AE37,"") | AG37: 1302 | AH37: =Y37/S37 -> 69.653979 | AI37: 21 | AJ37: 88 | AK37: 109 | AL37: 34569.6 | AM37: =L37-AL37 -> 25820.4
A38: 14 | B38: =A38-$G$4 -> 5 | C38: 45992 | D38: 26 Handel's Messiah | G38: 45996.792 | H38: Holiday | I38: 0.85 | J38: =K38/AG38 -> 0.43628809 | K38: =S38+AC38 -> 630 | L38: =Y38+AD38 -> 33156 | M38: =Z38+AE38 -> 78333 | N38: =L38-M38 -> -45177 | O38: =IF(P38="Too early",P38,P38/AG38) -> 1 | P38: =IF(V38="Too early",V38,V38+AC38) -> 1444 | Q38: =IF(V38="Too early",V38,AD38+V38*AH38) -> 75995.657 | R38: =IF(V38="Too early",V38,Q38-M38) -> -2337.3429 | S38: =626+4 -> 630 | T38: =AG38-AC38 -> 1444 | U38: =(AG38-AC38)*I38 -> 1227.4 | V38: =IF(B38<11,MIN((S38/VLOOKUP(B38,'Sales Pacing'!$A$23:$E$36,2)),T38),"Too early") -> 1444 | W38: =Q38-AD38 -> 75995.657 | X38: =IF(V38="Too early","Too early",V38/U38) -> 1.1764706 | Y38: =32850+306 -> 33156 | Z38: 78333 | AA38: =IF(Y38>0,Y38/Z38,"") -> 0.42326989 | AB38: =IF($V38="Too early",V38,V38*AH38/Z38) -> 0.97016145 | AF38: =IF(AD38>0,AD38/AE38,"") | AG38: 1444 | AH38: =Y38/S38 -> 52.628571 | AI38: 19 | AJ38: 86 | AK38: 105 | AL38: 18853.5 | AM38: =L38-AL38 -> 14302.5
A39: 14 | B39: =A39-$G$4 -> 5 | C39: 45992 | D39: 26 Handel's Messiah | G39: 45997.792 | H39: Holiday | I39: 0.85 | J39: =K39/AG39 -> 0.46052632 | K39: =S39+AC39 -> 665 | L39: =Y39+AD39 -> 35973 | M39: =Z39+AE39 -> 78334 | N39: =L39-M39 -> -42361 | O39: =IF(P39="Too early",P39,P39/AG39) -> 1 | P39: =IF(V39="Too early",V39,V39+AC39) -> 1444 | Q39: =IF(V39="Too early",V39,AD39+V39*AH39) -> 78112.8 | R39: =IF(V39="Too early",V39,Q39-M39) -> -221.2 | S39: =656+9 -> 665 | T39: =AG39-AC39 -> 1444 | U39: =(AG39-AC39)*I39 -> 1227.4 | V39: =IF(B39<11,MIN((S39/VLOOKUP(B39,'Sales Pacing'!$A$23:$E$36,2)),T39),"Too early") -> 1444 | W39: =Q39-AD39 -> 78112.8 | X39: =IF(V39="Too early","Too early",V39/U39) -> 1.1764706 | Y39: =35501+472 -> 35973 | Z39: 78334 | AA39: =IF(Y39>0,Y39/Z39,"") -> 0.45922588 | AB39: =IF($V39="Too early",V39,V39*AH39/Z39) -> 0.99717619 | AF39: =IF(AD39>0,AD39/AE39,"") | AG39: 1444 | AH39: =Y39/S39 -> 54.094737 | AI39: 20 | AJ39: 95 | AK39: 115 | AL39: 22001.5 | AM39: =L39-AL39 -> 13971.5
A40: 14 | B40: =A40-$G$4 -> 5 | C40: 45992 | D40: 26 Handel's Messiah | G40: 45998.583 | H40: Holiday | I40: 0.85 | J40: =K40/AG40 -> 0.49099723 | K40: =S40+AC40 -> 709 | L40: =Y40+AD40 -> 38151 | M40: =Z40+AE40 -> 78333 | N40: =L40-M40 -> -40182 | O40: =IF(P40="Too early",P40,P40/AG40) -> 1 | P40: =IF(V40="Too early",V40,V40+AC40) -> 1444 | Q40: =IF(V40="Too early",V40,AD40+V40*AH40) -> 77701.049 | R40: =IF(V40="Too early",V40,Q40-M40) -> -631.95063 | S40: =695+14 -> 709 | T40: =AG40-AC40 -> 1444 | U40: =(AG40-AC40)*I40 -> 1227.4 | V40: =IF(B40<11,MIN((S40/VLOOKUP(B40,'Sales Pacing'!$A$23:$E$36,2)),T40),"Too early") -> 1444 | W40: =Q40-AD40 -> 77701.049 | X40: =IF(V40="Too early","Too early",V40/U40) -> 1.1764706 | Y40: =37495+656 -> 38151 | Z40: 78333 | AA40: =IF(Y40>0,Y40/Z40,"") -> 0.48703612 | AB40: =IF($V40="Too early",V40,V40*AH40/Z40) -> 0.99193251 | AF40: =IF(AD40>0,AD40/AE40,"") | AG40: 1444 | AH40: =Y40/S40 -> 53.809591 | AI40: 26 | AJ40: 105 | AK40: 131 | AL40: 21652.5 | AM40: =L40-AL40 -> 16498.5
A41: 15 | B41: =A41-$G$4 -> 6 | C41: 45999 | D41: 26 Leslie Odom Jr.: Christmas | G41: 46003.792 | H41: Specials | I41: 0.85 | J41: =K41/AG41 -> 0.78427673 | K41: =S41+AC41 -> 1247 | L41: =Y41+AD41 -> 125125 | M41: =Z41+AE41 -> 150000 | N41: =L41-M41 -> -24875 | O41: =IF(P41="Too early",P41,P41/AG41) -> 1 | P41: =IF(V41="Too early",V41,V41+AC41) -> 1590 | Q41: =IF(V41="Too early",V41,AD41+V41*AH41) -> 159541.9 | R41: =IF(V41="Too early",V41,Q41-M41) -> 9541.9006 | S41: =1245+2 -> 1247 | T41: =AG41-AC41 -> 1590 | U41: =(AG41-AC41)*I41 -> 1351.5 | V41: =IF(B41<11,MIN((S41/VLOOKUP(B41,'Sales Pacing'!$A$23:$E$36,2)),T41),"Too early") -> 1590 | W41: =Q41-AD41 -> 159541.9 | X41: =IF(V41="Too early","Too early",V41/U41) -> 1.1764706 | Y41: =125125 -> 125125 | Z41: 150000 | AA41: =IF(Y41>0,Y41/Z41,"") -> 0.83416667 | AB41: =IF($V41="Too early",V41,V41*AH41/Z41) -> 1.0636127 | AF41: =IF(AD41>0,AD41/AE41,"") | AG41: 1590 | AH41: =Y41/S41 -> 100.34082 | AI41: 87 | AJ41: 264 | AK41: 351 | AL41: 103427 | AM41: =L41-AL41 -> 21698
A42: 15 | B42: =A42-$G$4 -> 6 | C42: 45999 | D42: 26 Leslie Odom Jr.: Christmas | G42: 46004.792 | H42: Specials | I42: 0.85 | J42: =K42/AG42 -> 0.91006289 | K42: =S42+AC42 -> 1447 | L42: =Y42+AD42 -> 140904 | M42: =Z42+AE42 -> 150000 | N42: =L42-M42 -> -9096 | O42: =IF(P42="Too early",P42,P42/AG42) -> 1 | P42: =IF(V42="Too early",V42,V42+AC42) -> 1590 | Q42: =IF(V42="Too early",V42,AD42+V42*AH42) -> 154828.86 | R42: =IF(V42="Too early",V42,Q42-M42) -> 4828.8597 | S42: =1443+4 -> 1447 | T42: =AG42-AC42 -> 1590 | U42: =(AG42-AC42)*I42 -> 1351.5 | V42: =IF(B42<11,MIN((S42/VLOOKUP(B42,'Sales Pacing'!$A$23:$E$36,2)),T42),"Too early") -> 1590 | W42: =Q42-AD42 -> 154828.86 | X42: =IF(V42="Too early","Too early",V42/U42) -> 1.1764706 | Y42: =140904 -> 140904 | Z42: 150000 | AA42: =IF(Y42>0,Y42/Z42,"") -> 0.93936 | AB42: =IF($V42="Too early",V42,V42*AH42/Z42) -> 1.0321924 | AF42: =IF(AD42>0,AD42/AE42,"") | AG42: 1590 | AH42: =Y42/S42 -> 97.376641 | AI42: 128 | AJ42: 291 | AK42: 419 | AL42: 123198 | AM42: =L42-AL42 -> 17706
A43: 16 | B43: =A43-$G$4 -> 7 | C43: 46006 | D43: 26 Christmas Festival | G43: 46009.792 | H43: Holiday | I43: 0.85 | J43: =K43/AG43 -> 0.23866015 | K43: =S43+AC43 -> 342 | L43: =Y43+AD43 -> 20480 | M43: =Z43+AE43 -> 75833 | N43: =L43-M43 -> -55353 | O43: =IF(P43="Too early",P43,P43/AG43) -> 0.99441731 | P43: =IF(V43="Too early",V43,V43+AC43) -> 1425 | Q43: =IF(V43="Too early",V43,AD43+V43*AH43) -> 85333.333 | R43: =IF(V43="Too early",V43,Q43-M43) -> 9500.3333 | S43: =334+8 -> 342 | T43: =AG43-AC43 -> 1433 | U43: =(AG43-AC43)*I43 -> 1218.05 | V43: =IF(B43<11,MIN((S43/VLOOKUP(B43,'Sales Pacing'!$A$23:$E$36,2)),T43),"Too early") -> 1425 | W43: =Q43-AD43 -> 85333.333 | X43: =IF(V43="Too early","Too early",V43/U43) -> 1.1699027 | Y43: =20039+441 -> 20480 | Z43: 75833 | AA43: =IF(Y43>0,Y43/Z43,"") -> 0.27006712 | AB43: =IF($V43="Too early",V43,V43*AH43/Z43) -> 1.1252797 | AF43: =IF(AD43>0,AD43/AE43,"") | AG43: 1433 | AH43: =Y43/S43 -> 59.883041 | AL43: 13189 | AM43: =L43-AL43 -> 7291
A44: 16 | B44: =A44-$G$4 -> 7 | C44: 46006 | D44: 26 Christmas Festival | G44: 46010.792 | H44: Holiday | I44: 0.85 | J44: =K44/AG44 -> 0.24424285 | K44: =S44+AC44 -> 350 | L44: =Y44+AD44 -> 21602 | M44: =Z44+AE44 -> 75833 | N44: =L44-M44 -> -54231 | O44: =IF(P44="Too early",P44,P44/AG44) -> 1 | P44: =IF(V44="Too early",V44,V44+AC44) -> 1433 | Q44: =IF(V44="Too early",V44,AD44+V44*AH44) -> 88444.76 | R44: =IF(V44="Too early",V44,Q44-M44) -> 12611.76 | S44: =348+2 -> 350 | T44: =AG44-AC44 -> 1433 | U44: =(AG44-AC44)*I44 -> 1218.05 | V44: =IF(B44<11,MIN((S44/VLOOKUP(B44,'Sales Pacing'!$A$23:$E$36,2)),T44),"Too early") -> 1433 | W44: =Q44-AD44 -> 88444.76 | X44: =IF(V44="Too early","Too early",V44/U44) -> 1.1764706 | Y44: =21503+99 -> 21602 | Z44: 75833 | AA44: =IF(Y44>0,Y44/Z44,"") -> 0.28486279 | AB44: =IF($V44="Too early",V44,V44*AH44/Z44) -> 1.1663097 | AF44: =IF(AD44>0,AD44/AE44,"") | AG44: 1433 | AH44: =Y44/S44 -> 61.72 | AL44: 11666.5 | AM44: =L44-AL44 -> 9935.5
A45: 16 | B45: =A45-$G$4 -> 7 | C45: 46006 | D45: 26 Christmas Festival | G45: 46011.542 | H45: Holiday | I45: 0.85 | J45: =K45/AG45 -> 0.36775994 | K45: =S45+AC45 -> 527 | L45: =Y45+AD45 -> 31952 | M45: =Z45+AE45 -> 75833 | N45: =L45-M45 -> -43881 | O45: =IF(P45="Too early",P45,P45/AG45) -> 1 | P45: =IF(V45="Too early",V45,V45+AC45) -> 1433 | Q45: =IF(V45="Too early",V45,AD45+V45*AH45) -> 86882.763 | R45: =IF(V45="Too early",V45,Q45-M45) -> 11049.763 | S45: =519+8 -> 527 | T45: =AG45-AC45 -> 1433 | U45: =(AG45-AC45)*I45 -> 1218.05 | V45: =IF(B45<11,MIN((S45/VLOOKUP(B45,'Sales Pacing'!$A$23:$E$36,2)),T45),"Too early") -> 1433 | W45: =Q45-AD45 -> 86882.763 | X45: =IF(V45="Too early","Too early",V45/U45) -> 1.1764706 | Y45: =31520+432 -> 31952 | Z45: 75833 | AA45: =IF(Y45>0,Y45/Z45,"") -> 0.42134691 | AB45: =IF($V45="Too early",V45,V45*AH45/Z45) -> 1.1457118 | AF45: =IF(AD45>0,AD45/AE45,"") | AG45: 1433 | AH45: =Y45/S45 -> 60.629981 | AL45: 21404.5 | AM45: =L45-AL45 -> 10547.5
A46: 16 | B46: =A46-$G$4 -> 7 | C46: 46006 | D46: 26 Christmas Festival | G46: 46011.792 | H46: Holiday | I46: 0.85 | J46: =K46/AG46 -> 0.26099093 | K46: =S46+AC46 -> 374 | L46: =Y46+AD46 -> 23759 | M46: =Z46+AE46 -> 75833 | N46: =L46-M46 -> -52074 | O46: =IF(P46="Too early",P46,P46/AG46) -> 1 | P46: =IF(V46="Too early",V46,V46+AC46) -> 1433 | Q46: =IF(V46="Too early",V46,AD46+V46*AH46) -> 91033.816 | R46: =IF(V46="Too early",V46,Q46-M46) -> 15200.816 | S46: =365+9 -> 374 | T46: =AG46-AC46 -> 1433 | U46: =(AG46-AC46)*I46 -> 1218.05 | V46: =IF(B46<11,MIN((S46/VLOOKUP(B46,'Sales Pacing'!$A$23:$E$36,2)),T46),"Too early") -> 1433 | W46: =Q46-AD46 -> 91033.816 | X46: =IF(V46="Too early","Too early",V46/U46) -> 1.1764706 | Y46: =23134+625 -> 23759 | Z46: 75833 | AA46: =IF(Y46>0,Y46/Z46,"") -> 0.31330687 | AB46: =IF($V46="Too early",V46,V46*AH46/Z46) -> 1.2004512 | AF46: =IF(AD46>0,AD46/AE46,"") | AG46: 1433 | AH46: =Y46/S46 -> 63.526738 | AL46: 13817 | AM46: =L46-AL46 -> 9942
A47: 16 | B47: =A47-$G$4 -> 7 | C47: 46006 | D47: 26 Christmas Festival | G47: 46012.583 | H47: Holiday | I47: 0.85 | J47: =K47/AG47 -> 0.54501047 | K47: =S47+AC47 -> 781 | L47: =Y47+AD47 -> 34319 | M47: =Z47+AE47 -> 88284 | N47: =L47-M47 -> -53965 | O47: =IF(P47="Too early",P47,P47/AG47) -> 1 | P47: =IF(V47="Too early",V47,V47+AC47) -> 1433 | Q47: =IF(V47="Too early",V47,AD47+V47*AH47) -> 72225.944 | R47: =IF(V47="Too early",V47,Q47-M47) -> -16058.056 | S47: =457+9 -> 466 | T47: =AG47-AC47 -> 1118 | U47: =(AG47-AC47)*I47 -> 950.3 | V47: =IF(B47<11,MIN((S47/VLOOKUP(B47,'Sales Pacing'!$A$23:$E$36,2)),T47),"Too early") -> 1118 | W47: =Q47-AD47 -> 64999.944 | X47: =IF(V47="Too early","Too early",V47/U47) -> 1.1764706 | Y47: =26775+318 -> 27093 | Z47: 75834 | AA47: =IF(Y47>0,Y47/Z47,"") -> 0.35726719 | AB47: =IF($V47="Too early",V47,V47*AH47/Z47) -> 0.85713459 | AC47: 315 | AD47: 7226 | AE47: 12450 | AF47: =IF(AD47>0,AD47/AE47,"") -> 0.58040161 | AG47: 1433 | AH47: =Y47/S47 -> 58.139485 | AL47: 23553 | AM47: =L47-AL47 -> 10766
A48: 16 | B48: =A48-$G$4 -> 7 | C48: 46006 | D48: 26 Christmas Festival | G48: 46012.792 | H48: Holiday | I48: 0.85 | J48: =K48/AG48 -> 0.17934403 | K48: =S48+AC48 -> 257 | L48: =Y48+AD48 -> 13613 | M48: =Z48+AE48 -> 75834 | N48: =L48-M48 -> -62221 | O48: =IF(P48="Too early",P48,P48/AG48) -> 0.74726681 | P48: =IF(V48="Too early",V48,V48+AC48) -> 1070.8333 | Q48: =IF(V48="Too early",V48,AD48+V48*AH48) -> 56720.833 | R48: =IF(V48="Too early",V48,Q48-M48) -> -19113.167 | S48: =255+2 -> 257 | T48: =AG48-AC48 -> 1433 | U48: =(AG48-AC48)*I48 -> 1218.05 | V48: =IF(B48<11,MIN((S48/VLOOKUP(B48,'Sales Pacing'!$A$23:$E$36,2)),T48),"Too early") -> 1070.8333 | W48: =Q48-AD48 -> 56720.833 | X48: =IF(V48="Too early","Too early",V48/U48) -> 0.87913742 | Y48: =13469+144 -> 13613 | Z48: 75834 | AA48: =IF(Y48>0,Y48/Z48,"") -> 0.17951051 | AB48: =IF($V48="Too early",V48,V48*AH48/Z48) -> 0.74796046 | AF48: =IF(AD48>0,AD48/AE48,"") | AG48: 1433 | AH48: =Y48/S48 -> 52.968872 | AL48: 7896 | AM48: =L48-AL48 -> 5717
A49: 17 | B49: =A49-$G$4 -> 8 | C49: 46013 | D49: 26 It's a Wonderful Life | G49: 46014.792 | H49: Specials/Film | I49: 0.85 | J49: =K49/AG49 -> 0.91781874 | K49: =S49+AC49 -> 1195 | L49: =Y49+AD49 -> 100155 | M49: =Z49+AE49 -> 100000 | N49: =L49-M49 -> 155 | O49: =IF(P49="Too early",P49,P49/AG49) -> 1 | P49: =IF(V49="Too early",V49,V49+AC49) -> 1302 | Q49: =IF(V49="Too early",V49,AD49+V49*AH49) -> 109122.85 | R49: =IF(V49="Too early",V49,Q49-M49) -> 9122.8536 | S49: =1191+4 -> 1195 | T49: =AG49-AC49 -> 1302 | U49: =(AG49-AC49)*I49 -> 1106.7 | V49: =IF(B49<11,MIN((S49/VLOOKUP(B49,'Sales Pacing'!$A$23:$E$36,2)),T49),"Too early") -> 1302 | W49: =Q49-AD49 -> 109122.85 | X49: =IF(V49="Too early","Too early",V49/U49) -> 1.1764706 | Y49: 100155 | Z49: 100000 | AA49: =IF(Y49>0,Y49/Z49,"") -> 1.00155 | AB49: =IF($V49="Too early",V49,V49*AH49/Z49) -> 1.0912285 | AF49: =IF(AD49>0,AD49/AE49,"") | AG49: 1302 | AH49: =Y49/S49 -> 83.811715 | AL49: 66653.6 | AM49: =L49-AL49 -> 33501.4
A50: 17 | B50: =A50-$G$4 -> 8 | C50: 46013 | D50: 26 It's a Wonderful Life | G50: 46015.458 | H50: Specials/Film | I50: 0.85 | J50: =K50/AG50 -> 0.29723502 | K50: =S50+AC50 -> 387 | L50: =Y50+AD50 -> 28140 | M50: =Z50+AE50 -> 100000 | N50: =L50-M50 -> -71860 | O50: =IF(P50="Too early",P50,P50/AG50) -> 1 | P50: =IF(V50="Too early",V50,V50+AC50) -> 1302 | Q50: =IF(V50="Too early",V50,AD50+V50*AH50) -> 94672.558 | R50: =IF(V50="Too early",V50,Q50-M50) -> -5327.4419 | S50: =385+2 -> 387 | T50: =AG50-AC50 -> 1302 | U50: =(AG50-AC50)*I50 -> 1106.7 | V50: =IF(B50<11,MIN((S50/VLOOKUP(B50,'Sales Pacing'!$A$23:$E$36,2)),T50),"Too early") -> 1302 | W50: =Q50-AD50 -> 94672.558 | X50: =IF(V50="Too early","Too early",V50/U50) -> 1.1764706 | Y50: 28140 | Z50: 100000 | AA50: =IF(Y50>0,Y50/Z50,"") -> 0.2814 | AB50: =IF($V50="Too early",V50,V50*AH50/Z50) -> 0.94672558 | AF50: =IF(AD50>0,AD50/AE50,"") | AG50: 1302 | AH50: =Y50/S50 -> 72.713178 | AL50: 14364.4 | AM50: =L50-AL50 -> 13775.6
A51: 18 | B51: =A51-$G$4 -> 9 | C51: 46020 | D51: OPEN | J51: =K51/AG51 -> #DIV/0! | K51: =S51+AC51 -> 0 | L51: =Y51+AD51 -> 0 | M51: =Z51+AE51 -> 0 | P51: =IF(V51="Too early",V51,V51+AC51) -> 0 | Q51: =IF(V51="Too early",V51,AD51+V51*AH51) -> #DIV/0! | R51: =IF(V51="Too early",V51,Q51-M51) -> #DIV/0! | T51: =AG51-AC51 -> 0 | U51: =(AG51-AC51)*I51 -> 0 | V51: =IF(B51<11,MIN((S51/VLOOKUP(B51,'Sales Pacing'!$A$23:$E$36,2)),T51),"Too early") -> 0 | W51: =Q51-AD51 -> #DIV/0! | AA51: =IF(Y51>0,Y51/Z51,"") | AF51: N/A | AH51: =Y51/S51 -> #DIV/0! | AL51: 0
A52: 19 | B52: =A52-$G$4 -> 10 | C52: 46027 | D52: 26 CS04 Brahms' Fourth Symphony | G52: 46031.833 | H52: Classical | I52: 0.85 | J52: =K52/AG52 -> 0.39119497 | K52: =S52+AC52 -> 622 | L52: =Y52+AD52 -> 40404 | M52: =Z52+AE52 -> 54999 | N52: =L52-M52 -> -14595 | O52: =IF(P52="Too early",P52,P52/AG52) -> 0.60146751 | P52: =IF(V52="Too early",V52,V52+AC52) -> 956.33333 | Q52: =IF(V52="Too early",V52,AD52+V52*AH52) -> 54372.333 | R52: =IF(V52="Too early",V52,Q52-M52) -> -626.66667 | S52: =54+5 -> 59 | T52: =AG52-AC52 -> 1027 | U52: =(AG52-AC52)*I52 -> 872.95 | V52: =IF(B52<11,MIN((S52/VLOOKUP(B52,'Sales Pacing'!$A$23:$E$36,2)),T52),"Too early") -> 393.33333 | W52: =Q52-AD52 -> 16433.333 | X52: =IF(V52="Too early","Too early",V52/U52) -> 0.45057945 | Y52: =2238+227 -> 2465 | Z52: 21666 | AA52: =IF(Y52>0,Y52/Z52,"") -> 0.11377273 | AB52: =IF($V52="Too early",V52,V52*AH52/Z52) -> 0.75848488 | AC52: 563 | AD52: 37939 | AE52: 33333 | AF52: =IF(AD52>0,AD52/AE52,"") -> 1.1381814 | AG52: 1590 | AH52: =Y52/S52 -> 41.779661 | AL52: 39591 | AM52: =L52-AL52 -> 813
A53: 19 | B53: =A53-$G$4 -> 10 | C53: 46027 | D53: 27 CS04 Brahms' Fourth Symphony | G53: 46032.833 | H53: Classical | I53: 0.85 | J53: =K53/AG53 -> 0.41194969 | K53: =S53+AC53 -> 655 | L53: =Y53+AD53 -> 41616 | M53: =Z53+AE53 -> 54999 | N53: =L53-M53 -> -13383 | O53: =IF(P53="Too early",P53,P53/AG53) -> 0.77903564 | P53: =IF(V53="Too early",V53,V53+AC53) -> 1238.6667 | Q53: =IF(V53="Too early",V53,AD53+V53*AH53) -> 71581.333 | R53: =IF(V53="Too early",V53,Q53-M53) -> 16582.333 | S53: =89+14 -> 103 | T53: =AG53-AC53 -> 1038 | U53: =(AG53-AC53)*I53 -> 882.3 | V53: =IF(B53<11,MIN((S53/VLOOKUP(B53,'Sales Pacing'!$A$23:$E$36,2)),T53),"Too early") -> 686.66667 | W53: =Q53-AD53 -> 35253.333 | X53: =IF(V53="Too early","Too early",V53/U53) -> 0.77826892 | Y53: =4317+971 -> 5288 | Z53: 21666 | AA53: =IF(Y53>0,Y53/Z53,"") -> 0.24406905 | AB53: =IF($V53="Too early",V53,V53*AH53/Z53) -> 1.627127 | AC53: 552 | AD53: 36328 | AE53: 33333 | AF53: =IF(AD53>0,AD53/AE53,"") -> 1.0898509 | AG53: 1590 | AH53: =Y53/S53 -> 51.339806 | AL53: 40128 | AM53: =L53-AL53 -> 1488
A54: 19 | B54: =A54-$G$4 -> 10 | C54: 46027 | D54: 28 CS04 Brahms' Fourth Symphony | G54: 46033.583 | H54: Classical | I54: 0.85 | J54: =K54/AG54 -> 0.40628931 | K54: =S54+AC54 -> 646 | L54: =Y54+AD54 -> 40616 | M54: =Z54+AE54 -> 55002 | N54: =L54-M54 -> -14386 | O54: =IF(P54="Too early",P54,P54/AG54) -> 0.68784067 | P54: =IF(V54="Too early",V54,V54+AC54) -> 1093.6667 | Q54: =IF(V54="Too early",V54,AD54+V54*AH54) -> 63044.667 | R54: =IF(V54="Too early",V54,Q54-M54) -> 8042.6667 | S54: =72+7 -> 79 | T54: =AG54-AC54 -> 1023 | U54: =(AG54-AC54)*I54 -> 869.55 | V54: =IF(B54<11,MIN((S54/VLOOKUP(B54,'Sales Pacing'!$A$23:$E$36,2)),T54),"Too early") -> 526.66667 | W54: =Q54-AD54 -> 26386.667 | X54: =IF(V54="Too early","Too early",V54/U54) -> 0.60567727 | Y54: =3599+359 -> 3958 | Z54: 21668 | AA54: =IF(Y54>0,Y54/Z54,"") -> 0.18266568 | AB54: =IF($V54="Too early",V54,V54*AH54/Z54) -> 1.2177712 | AC54: 567 | AD54: 36658 | AE54: 33334 | AF54: =IF(AD54>0,AD54/AE54,"") -> 1.099718 | AG54: 1590 | AH54: =Y54/S54 -> 50.101266 | AL54: 39791.5 | AM54: =L54-AL54 -> 824.5
A55: 20 | B55: =A55-$G$4 -> 11 | C55: 46034 | D55: 26 CS05 Pines of Rome & Bruch | G55: 46038.833 | H55: Classical | I55: 0.85 | J55: =K55/AG55 -> 0.26352201 | K55: =S55+AC55 -> 419 | L55: =Y55+AD55 -> 28302 | M55: =Z55+AE55 -> 60000 | N55: =L55-M55 -> -31698 | O55: =IF(P55="Too early",P55,P55/AG55) -> Too early | P55: =IF(V55="Too early",V55,V55+AC55) -> Too early | Q55: =IF(V55="Too early",V55,AD55+V55*AH55) -> Too early | R55: =IF(V55="Too early",V55,Q55-M55) -> Too early | S55: 51 | T55: =AG55-AC55 -> 1222 | U55: =(AG55-AC55)*I55 -> 1038.7 | V55: =IF(B55<11,MIN((S55/VLOOKUP(B55,'Sales Pacing'!$A$23:$E$36,2)),T55),"Too early") -> Too early | W55: =Q55-AD55 -> #VALUE! | X55: =IF(V55="Too early","Too early",V55/U55) -> Too early | Y55: 2960 | Z55: 30000 | AA55: =IF(Y55>0,Y55/Z55,"") -> 0.098666667 | AB55: =IF($V55="Too early",V55,V55*AH55/Z55) -> Too early | AC55: 368 | AD55: 25342 | AE55: 30000 | AF55: =IF(AD55>0,AD55/AE55,"") -> 0.84473333 | AG55: 1590 | AH55: =Y55/S55 -> 58.039216 | AL55: 28243 | AM55: =L55-AL55 -> 59
A56: 20 | B56: =A56-$G$4 -> 11 | C56: 46034 | D56: 26 CS05 Pines of Rome & Bruch | G56: 46039.833 | H56: Classical | I56: 0.85 | J56: =K56/AG56 -> 0.45660377 | K56: =S56+AC56 -> 726 | L56: =Y56+AD56 -> 47864.9 | M56: =Z56+AE56 -> 75000 | N56: =L56-M56 -> -27135.1 | O56: =IF(P56="Too early",P56,P56/AG56) -> Too early | P56: =IF(V56="Too early",V56,V56+AC56) -> Too early | Q56: =IF(V56="Too early",V56,AD56+V56*AH56) -> Too early | R56: =IF(V56="Too early",V56,Q56-M56) -> Too early | S56: 126 | T56: =AG56-AC56 -> 990 | U56: =(AG56-AC56)*I56 -> 841.5 | V56: =IF(B56<11,MIN((S56/VLOOKUP(B56,'Sales Pacing'!$A$23:$E$36,2)),T56),"Too early") -> Too early | W56: =Q56-AD56 -> #VALUE! | X56: =IF(V56="Too early","Too early",V56/U56) -> Too early | Y56: 7358 | Z56: 20000 | AA56: =IF(Y56>0,Y56/Z56,"") -> 0.3679 | AB56: =IF($V56="Too early",V56,V56*AH56/Z56) -> Too early | AC56: 600 | AD56: 40506.9 | AE56: 55000 | AF56: =IF(AD56>0,AD56/AE56,"") -> 0.73648909 | AG56: 1590 | AH56: =Y56/S56 -> 58.396825 | AL56: 47394.9 | AM56: =L56-AL56 -> 470
A57: 20 | B57: =A57-$G$4 -> 11 | C57: 46034 | D57: 26 CS05 Pines of Rome & Bruch | G57: 46040.583 | H57: Classical | I57: 0.85 | J57: =K57/AG57 -> 0.4408805 | K57: =S57+AC57 -> 701 | L57: =Y57+AD57 -> 44947.2 | M57: =Z57+AE57 -> 75000 | N57: =L57-M57 -> -30052.8 | O57: =IF(P57="Too early",P57,P57/AG57) -> Too early | P57: =IF(V57="Too early",V57,V57+AC57) -> Too early | Q57: =IF(V57="Too early",V57,AD57+V57*AH57) -> Too early | R57: =IF(V57="Too early",V57,Q57-M57) -> Too early | S57: 93 | T57: =AG57-AC57 -> 982 | U57: =(AG57-AC57)*I57 -> 834.7 | V57: =IF(B57<11,MIN((S57/VLOOKUP(B57,'Sales Pacing'!$A$23:$E$36,2)),T57),"Too early") -> Too early | W57: =Q57-AD57 -> #VALUE! | X57: =IF(V57="Too early","Too early",V57/U57) -> Too early | Y57: 5931 | Z57: 20000 | AA57: =IF(Y57>0,Y57/Z57,"") -> 0.29655 | AB57: =IF($V57="Too early",V57,V57*AH57/Z57) -> Too early | AC57: 608 | AD57: 39016.2 | AE57: 55000 | AF57: =IF(AD57>0,AD57/AE57,"") -> 0.70938545 | AG57: 1590 | AH57: =Y57/S57 -> 63.774194 | AL57: 44600.2 | AM57: =L57-AL57 -> 347
A58: 21 | B58: =A58-$G$4 -> 12 | C58: 46041 | D58: 26 Indiana Jones: Raiders Lost | G58: 46044.792 | H58: Specials/Film | I58: 0.85 | J58: =K58/AG58 -> 0.10061444 | K58: =S58+AC58 -> 131 | L58: =Y58+AD58 -> 7965 | M58: =Z58+AE58 -> 90000 | N58: =L58-M58 -> -82035 | O58: =IF(P58="Too early",P58,P58/AG58) -> Too early | P58: =IF(V58="Too early",V58,V58+AC58) -> Too early | Q58: =IF(V58="Too early",V58,AD58+V58*AH58) -> Too early | R58: =IF(V58="Too early",V58,Q58-M58) -> Too early | S58: 131 | T58: =AG58-AC58 -> 1302 | U58: =(AG58-AC58)*I58 -> 1106.7 | V58: =IF(B58<11,MIN((S58/VLOOKUP(B58,'Sales Pacing'!$A$23:$E$36,2)),T58),"Too early") -> Too early | W58: =Q58-AD58 -> #VALUE! | X58: =IF(V58="Too early","Too early",V58/U58) -> Too early | Y58: 7965 | Z58: 90000 | AA58: =IF(Y58>0,Y58/Z58,"") -> 0.0885 | AB58: =IF($V58="Too early",V58,V58*AH58/Z58) -> Too early | AF58: =IF(AD58>0,AD58/AE58,"") | AG58: 1302 | AH58: =Y58/S58 -> 60.801527 | AL58: 7410 | AM58: =L58-AL58 -> 555
A59: 21 | B59: =A59-$G$4 -> 12 | C59: 46041 | D59: 26 Indiana Jones: Raiders Lost | G59: 46045.792 | H59: Specials/Film | I59: 0.85 | J59: =K59/AG59 -> 0.23502304 | K59: =S59+AC59 -> 306 | L59: =Y59+AD59 -> 22141.9 | M59: =Z59+AE59 -> 90000 | N59: =L59-M59 -> -67858.1 | O59: =IF(P59="Too early",P59,P59/AG59) -> Too early | P59: =IF(V59="Too early",V59,V59+AC59) -> Too early | Q59: =IF(V59="Too early",V59,AD59+V59*AH59) -> Too early | R59: =IF(V59="Too early",V59,Q59-M59) -> Too early | S59: 306 | T59: =AG59-AC59 -> 1302 | U59: =(AG59-AC59)*I59 -> 1106.7 | V59: =IF(B59<11,MIN((S59/VLOOKUP(B59,'Sales Pacing'!$A$23:$E$36,2)),T59),"Too early") -> Too early | W59: =Q59-AD59 -> #VALUE! | X59: =IF(V59="Too early","Too early",V59/U59) -> Too early | Y59: 22141.9 | Z59: 90000 | AA59: =IF(Y59>0,Y59/Z59,"") -> 0.24602111 | AB59: =IF($V59="Too early",V59,V59*AH59/Z59) -> Too early | AF59: =IF(AD59>0,AD59/AE59,"") | AG59: 1302 | AH59: =Y59/S59 -> 72.35915 | AL59: 21481.9 | AM59: =L59-AL59 -> 660
A60: 21 | B60: =A60-$G$4 -> 12 | C60: 46041 | D60: 26 Indiana Jones: Raiders Lost | G60: 46046.792 | H60: Specials/Film | I60: 0.85 | J60: =K60/AG60 -> 0.38479263 | K60: =S60+AC60 -> 501 | L60: =Y60+AD60 -> 36718.1 | M60: =Z60+AE60 -> 90000 | N60: =L60-M60 -> -53281.9 | O60: =IF(P60="Too early",P60,P60/AG60) -> Too early | P60: =IF(V60="Too early",V60,V60+AC60) -> Too early | Q60: =IF(V60="Too early",V60,AD60+V60*AH60) -> Too early | R60: =IF(V60="Too early",V60,Q60-M60) -> Too early | S60: 501 | T60: =AG60-AC60 -> 1302 | U60: =(AG60-AC60)*I60 -> 1106.7 | V60: =IF(B60<11,MIN((S60/VLOOKUP(B60,'Sales Pacing'!$A$23:$E$36,2)),T60),"Too early") -> Too early | W60: =Q60-AD60 -> #VALUE! | X60: =IF(V60="Too early","Too early",V60/U60) -> Too early | Y60: 36718.1 | Z60: 90000 | AA60: =IF(Y60>0,Y60/Z60,"") -> 0.40797889 | AB60: =IF($V60="Too early",V60,V60*AH60/Z60) -> Too early | AF60: =IF(AD60>0,AD60/AE60,"") | AG60: 1302 | AH60: =Y60/S60 -> 73.289621 | AL60: 34988.1 | AM60: =L60-AL60 -> 1730
A61: 21 | B61: =A61-$G$4 -> 12 | C61: 46041 | D61: 26 Indiana Jones: Raiders Lost | G61: 46047.583 | H61: Specials/Film | I61: 0.85 | J61: =K61/AG61 -> 0.29493088 | K61: =S61+AC61 -> 384 | L61: =Y61+AD61 -> 26947.1 | M61: =Z61+AE61 -> 90000 | N61: =L61-M61 -> -63052.9 | O61: =IF(P61="Too early",P61,P61/AG61) -> Too early | P61: =IF(V61="Too early",V61,V61+AC61) -> Too early | Q61: =IF(V61="Too early",V61,AD61+V61*AH61) -> Too early | R61: =IF(V61="Too early",V61,Q61-M61) -> Too early | S61: 384 | T61: =AG61-AC61 -> 1302 | U61: =(AG61-AC61)*I61 -> 1106.7 | V61: =IF(B61<11,MIN((S61/VLOOKUP(B61,'Sales Pacing'!$A$23:$E$36,2)),T61),"Too early") -> Too early | W61: =Q61-AD61 -> #VALUE! | X61: =IF(V61="Too early","Too early",V61/U61) -> Too early | Y61: 26947.1 | Z61: 90000 | AA61: =IF(Y61>0,Y61/Z61,"") -> 0.29941222 | AB61: =IF($V61="Too early",V61,V61*AH61/Z61) -> Too early | AF61: =IF(AD61>0,AD61/AE61,"") | AG61: 1302 | AH61: =Y61/S61 -> 70.17474 | AL61: 26457.1 | AM61: =L61-AL61 -> 490
A62: 22 | B62: =A62-$G$4 -> 13 | C62: 46048 | D62: 26 CS06 Beethoven+ | G62: 46052.833 | H62: Classical | I62: 0.85 | J62: =K62/AG62 -> 0.27358491 | K62: =S62+AC62 -> 435 | L62: =Y62+AD62 -> 28716 | M62: =Z62+AE62 -> 54000 | N62: =L62-M62 -> -25284 | O62: =IF(P62="Too early",P62,P62/AG62) -> Too early | P62: =IF(V62="Too early",V62,V62+AC62) -> Too early | Q62: =IF(V62="Too early",V62,AD62+V62*AH62) -> Too early | R62: =IF(V62="Too early",V62,Q62-M62) -> Too early | S62: 71 | T62: =AG62-AC62 -> 1226 | U62: =(AG62-AC62)*I62 -> 1042.1 | V62: =IF(B62<11,MIN((S62/VLOOKUP(B62,'Sales Pacing'!$A$23:$E$36,2)),T62),"Too early") -> Too early | W62: =Q62-AD62 -> #VALUE! | X62: =IF(V62="Too early","Too early",V62/U62) -> Too early | Y62: 3847 | Z62: 24000 | AA62: =IF(Y62>0,Y62/Z62,"") -> 0.16029167 | AB62: =IF($V62="Too early",V62,V62*AH62/Z62) -> Too early | AC62: 364 | AD62: 24869 | AE62: 30000 | AF62: =IF(AD62>0,AD62/AE62,"") -> 0.82896667 | AG62: 1590 | AH62: =Y62/S62 -> 54.183099 | AL62: 28368 | AM62: =L62-AL62 -> 348
A63: 22 | B63: =A63-$G$4 -> 13 | C63: 46048 | D63: 26 CS06 Beethoven+ | G63: 46053.833 | H63: Classical | I63: 0.85 | J63: =K63/AG63 -> 0.43522013 | K63: =S63+AC63 -> 692 | L63: =Y63+AD63 -> 45477.9 | M63: =Z63+AE63 -> 75000 | N63: =L63-M63 -> -29522.1 | O63: =IF(P63="Too early",P63,P63/AG63) -> Too early | P63: =IF(V63="Too early",V63,V63+AC63) -> Too early | Q63: =IF(V63="Too early",V63,AD63+V63*AH63) -> Too early | R63: =IF(V63="Too early",V63,Q63-M63) -> Too early | S63: 94 | T63: =AG63-AC63 -> 992 | U63: =(AG63-AC63)*I63 -> 843.2 | V63: =IF(B63<11,MIN((S63/VLOOKUP(B63,'Sales Pacing'!$A$23:$E$36,2)),T63),"Too early") -> Too early | W63: =Q63-AD63 -> #VALUE! | X63: =IF(V63="Too early","Too early",V63/U63) -> Too early | Y63: 5569 | Z63: 20000 | AA63: =IF(Y63>0,Y63/Z63,"") -> 0.27845 | AB63: =IF($V63="Too early",V63,V63*AH63/Z63) -> Too early | AC63: 598 | AD63: 39908.9 | AE63: 55000 | AF63: =IF(AD63>0,AD63/AE63,"") -> 0.72561636 | AG63: 1590 | AH63: =Y63/S63 -> 59.244681 | AL63: 45500.9 | AM63: =L63-AL63 -> -23
A64: 22 | B64: =A64-$G$4 -> 13 | C64: 46048 | D64: 26 CS06 Beethoven+ | G64: 46054.583 | H64: Classical | I64: 0.85 | J64: =K64/AG64 -> 0.42830189 | K64: =S64+AC64 -> 681 | L64: =Y64+AD64 -> 43667.2 | M64: =Z64+AE64 -> 75000 | N64: =L64-M64 -> -31332.8 | O64: =IF(P64="Too early",P64,P64/AG64) -> Too early | P64: =IF(V64="Too early",V64,V64+AC64) -> Too early | Q64: =IF(V64="Too early",V64,AD64+V64*AH64) -> Too early | R64: =IF(V64="Too early",V64,Q64-M64) -> Too early | S64: 72 | T64: =AG64-AC64 -> 981 | U64: =(AG64-AC64)*I64 -> 833.85 | V64: =IF(B64<11,MIN((S64/VLOOKUP(B64,'Sales Pacing'!$A$23:$E$36,2)),T64),"Too early") -> Too early | W64: =Q64-AD64 -> #VALUE! | X64: =IF(V64="Too early","Too early",V64/U64) -> Too early | Y64: 4644 | Z64: 20000 | AA64: =IF(Y64>0,Y64/Z64,"") -> 0.2322 | AB64: =IF($V64="Too early",V64,V64*AH64/Z64) -> Too early | AC64: 609 | AD64: 39023.2 | AE64: 55000 | AF64: =IF(AD64>0,AD64/AE64,"") -> 0.70951273 | AG64: 1590 | AH64: =Y64/S64 -> 64.5 | AL64: 43394.2 | AM64: =L64-AL64 -> 273
A65: 23 | B65: =A65-$G$4 -> 14 | C65: 46055 | D65: 26 On-Stage 2 Leila Josefowicz | G65: 46058.833 | H65: On Stage | I65: 0.85 | J65: =K65/AG65 -> 0.19 | K65: =S65+AC65 -> 19 | L65: =Y65+AD65 -> 1960 | M65: 9000 | N65: =L65-M65 -> -7040 | O65: =IF(P65="Too early",P65,P65/AG65) -> Too early | P65: =IF(V65="Too early",V65,V65+AC65) -> Too early | Q65: =IF(V65="Too early",V65,AD65+V65*AH65) -> Too early | R65: =IF(V65="Too early",V65,Q65-M65) -> Too early | S65: 19 | T65: =AG65-AC65 -> 100 | U65: =(AG65-AC65)*I65 -> 85 | V65: =IF(B65<11,MIN((S65/VLOOKUP(B65,'Sales Pacing'!$A$23:$E$36,2)),T65),"Too early") -> Too early | W65: =Q65-AD65 -> #VALUE! | X65: =IF(V65="Too early","Too early",V65/U65) -> Too early | Y65: 1960 | Z65: 9000 | AA65: =IF(Y65>0,Y65/Z65,"") -> 0.21777778 | AB65: =IF($V65="Too early",V65,V65*AH65/Z65) -> Too early | AF65: =IF(AD65>0,AD65/AE65,"") | AG65: 100 | AH65: =Y65/S65 -> 103.15789 | AL65: 1960 | AM65: =L65-AL65 -> 0
A66: 23 | B66: =A66-$G$4 -> 14 | C66: 46055 | D66: 26 CS07 Prokofiev's Fifth Symphony | G66: 46059.833 | H66: Classical | I66: 0.85 | J66: =K66/AG66 -> 0.39245283 | K66: =S66+AC66 -> 624 | L66: =Y66+AD66 -> 40003 | M66: =Z66+AE66 -> 46666 | N66: =L66-M66 -> -6663 | O66: =IF(P66="Too early",P66,P66/AG66) -> Too early | P66: =IF(V66="Too early",V66,V66+AC66) -> Too early | Q66: =IF(V66="Too early",V66,AD66+V66*AH66) -> Too early | R66: =IF(V66="Too early",V66,Q66-M66) -> Too early | S66: 62 | T66: =AG66-AC66 -> 1028 | U66: =(AG66-AC66)*I66 -> 873.8 | V66: =IF(B66<11,MIN((S66/VLOOKUP(B66,'Sales Pacing'!$A$23:$E$36,2)),T66),"Too early") -> Too early | W66: =Q66-AD66 -> #VALUE! | X66: =IF(V66="Too early","Too early",V66/U66) -> Too early | Y66: 2540 | Z66: 13333 | AA66: =IF(Y66>0,Y66/Z66,"") -> 0.19050476 | AB66: =IF($V66="Too early",V66,V66*AH66/Z66) -> Too early | AC66: 562 | AD66: 37463 | AE66: 33333 | AF66: =IF(AD66>0,AD66/AE66,"") -> 1.1239012 | AG66: 1590 | AH66: =Y66/S66 -> 40.967742 | AL66: 39823 | AM66: =L66-AL66 -> 180
A67: 23 | B67: =A67-$G$4 -> 14 | C67: 46055 | D67: 27 CS07 Prokofiev's Fifth Symphony | G67: 46060.833 | H67: Classical | I67: 0.85 | J67: =K67/AG67 -> 0.38238994 | K67: =S67+AC67 -> 608 | L67: =Y67+AD67 -> 38795.2 | M67: =Z67+AE67 -> 46666 | N67: =L67-M67 -> -7870.8 | O67: =IF(P67="Too early",P67,P67/AG67) -> Too early | P67: =IF(V67="Too early",V67,V67+AC67) -> Too early | Q67: =IF(V67="Too early",V67,AD67+V67*AH67) -> Too early | R67: =IF(V67="Too early",V67,Q67-M67) -> Too early | S67: 49 | T67: =AG67-AC67 -> 1031 | U67: =(AG67-AC67)*I67 -> 876.35 | V67: =IF(B67<11,MIN((S67/VLOOKUP(B67,'Sales Pacing'!$A$23:$E$36,2)),T67),"Too early") -> Too early | W67: =Q67-AD67 -> #VALUE! | X67: =IF(V67="Too early","Too early",V67/U67) -> Too early | Y67: 2478 | Z67: 13333 | AA67: =IF(Y67>0,Y67/Z67,"") -> 0.18585465 | AB67: =IF($V67="Too early",V67,V67*AH67/Z67) -> Too early | AC67: 559 | AD67: 36317.2 | AE67: 33333 | AF67: =IF(AD67>0,AD67/AE67,"") -> 1.0895269 | AG67: 1590 | AH67: =Y67/S67 -> 50.571429 | AL67: 38606.2 | AM67: =L67-AL67 -> 189
A68: 23 | B68: =A68-$G$4 -> 14 | C68: 46055 | D68: 28 CS07 Prokofiev's Fifth Symphony | G68: 46061.583 | H68: Classical | I68: 0.85 | J68: =K68/AG68 -> 0.38113208 | K68: =S68+AC68 -> 606 | L68: =Y68+AD68 -> 38109.1 | M68: =Z68+AE68 -> 46668 | N68: =L68-M68 -> -8558.9 | O68: =IF(P68="Too early",P68,P68/AG68) -> Too early | P68: =IF(V68="Too early",V68,V68+AC68) -> Too early | Q68: =IF(V68="Too early",V68,AD68+V68*AH68) -> Too early | R68: =IF(V68="Too early",V68,Q68-M68) -> Too early | S68: 44 | T68: =AG68-AC68 -> 1028 | U68: =(AG68-AC68)*I68 -> 873.8 | V68: =IF(B68<11,MIN((S68/VLOOKUP(B68,'Sales Pacing'!$A$23:$E$36,2)),T68),"Too early") -> Too early | W68: =Q68-AD68 -> #VALUE! | X68: =IF(V68="Too early","Too early",V68/U68) -> Too early | Y68: 1922 | Z68: 13334 | AA68: =IF(Y68>0,Y68/Z68,"") -> 0.14414279 | AB68: =IF($V68="Too early",V68,V68*AH68/Z68) -> Too early | AC68: 562 | AD68: 36187.1 | AE68: 33334 | AF68: =IF(AD68>0,AD68/AE68,"") -> 1.0855913 | AG68: 1590 | AH68: =Y68/S68 -> 43.681818 | AL68: 38063.1 | AM68: =L68-AL68 -> 46
A69: 24 | B69: =A69-$G$4 -> 15 | C69: 46062 | D69: 26 Chris Thile | G69: 46065.792 | H69: Specials | I69: 0.85 | J69: =K69/AG69 -> 0.21383648 | K69: =S69+AC69 -> 340 | L69: =Y69+AD69 -> 30162 | M69: =Z69+AE69 -> 128900 | N69: =L69-M69 -> -98738 | O69: =IF(P69="Too early",P69,P69/AG69) -> Too early | P69: =IF(V69="Too early",V69,V69+AC69) -> Too early | Q69: =IF(V69="Too early",V69,AD69+V69*AH69) -> Too early | R69: =IF(V69="Too early",V69,Q69-M69) -> Too early | S69: 340 | T69: =AG69-AC69 -> 1590 | U69: =(AG69-AC69)*I69 -> 1351.5 | V69: =IF(B69<11,MIN((S69/VLOOKUP(B69,'Sales Pacing'!$A$23:$E$36,2)),T69),"Too early") -> Too early | W69: =Q69-AD69 -> #VALUE! | X69: =IF(V69="Too early","Too early",V69/U69) -> Too early | Y69: 30162 | Z69: 128900 | AA69: =IF(Y69>0,Y69/Z69,"") -> 0.23399535 | AB69: =IF($V69="Too early",V69,V69*AH69/Z69) -> Too early | AF69: =IF(AD69>0,AD69/AE69,"") | AG69: 1590 | AH69: =Y69/S69 -> 88.711765 | AL69: 27005 | AM69: =L69-AL69 -> 3157
A70: 24 | B70: =A70-$G$4 -> 15 | C70: 46062 | D70: 26 PS3 She's Got Soul | G70: 46066.833 | H70: Pops | I70: 0.85 | J70: =K70/AG70 -> 0.49622642 | K70: =S70+AC70 -> 789 | L70: =Y70+AD70 -> 56081.1 | M70: =Z70+AE70 -> 94666 | N70: =L70-M70 -> -38584.9 | O70: =IF(P70="Too early",P70,P70/AG70) -> Too early | P70: =IF(V70="Too early",V70,V70+AC70) -> Too early | Q70: =IF(V70="Too early",V70,AD70+V70*AH70) -> Too early | R70: =IF(V70="Too early",V70,Q70-M70) -> Too early | S70: 66 | T70: =AG70-AC70 -> 867 | U70: =(AG70-AC70)*I70 -> 736.95 | V70: =IF(B70<11,MIN((S70/VLOOKUP(B70,'Sales Pacing'!$A$23:$E$36,2)),T70),"Too early") -> Too early | W70: =Q70-AD70 -> #VALUE! | X70: =IF(V70="Too early","Too early",V70/U70) -> Too early | Y70: 4067 | Z70: 53333 | AA70: =IF(Y70>0,Y70/Z70,"") -> 0.076256727 | AB70: =IF($V70="Too early",V70,V70*AH70/Z70) -> Too early | AC70: 723 | AD70: 52014.1 | AE70: 41333 | AF70: =IF(AD70>0,AD70/AE70,"") -> 1.2584158 | AG70: 1590 | AH70: =Y70/S70 -> 61.621212 | AL70: 55909.1 | AM70: =L70-AL70 -> 172
A71: 24 | B71: =A71-$G$4 -> 15 | C71: 46062 | D71: 26 PS3 She's Got Soul | G71: 46067.833 | H71: Pops | I71: 0.85 | J71: =K71/AG71 -> 0.44591195 | K71: =S71+AC71 -> 709 | L71: =Y71+AD71 -> 50062.8 | M71: =Z71+AE71 -> 94667 | N71: =L71-M71 -> -44604.2 | O71: =IF(P71="Too early",P71,P71/AG71) -> Too early | P71: =IF(V71="Too early",V71,V71+AC71) -> Too early | Q71: =IF(V71="Too early",V71,AD71+V71*AH71) -> Too early | R71: =IF(V71="Too early",V71,Q71-M71) -> Too early | S71: 46 | T71: =AG71-AC71 -> 927 | U71: =(AG71-AC71)*I71 -> 787.95 | V71: =IF(B71<11,MIN((S71/VLOOKUP(B71,'Sales Pacing'!$A$23:$E$36,2)),T71),"Too early") -> Too early | W71: =Q71-AD71 -> #VALUE! | X71: =IF(V71="Too early","Too early",V71/U71) -> Too early | Y71: 2151 | Z71: 53333 | AA71: =IF(Y71>0,Y71/Z71,"") -> 0.040331502 | AB71: =IF($V71="Too early",V71,V71*AH71/Z71) -> Too early | AC71: 663 | AD71: 47911.8 | AE71: 41334 | AF71: =IF(AD71>0,AD71/AE71,"") -> 1.1591378 | AG71: 1590 | AH71: =Y71/S71 -> 46.76087 | AL71: 50570.8 | AM71: =L71-AL71 -> -508
A72: 24 | B72: =A72-$G$4 -> 15 | C72: 46062 | D72: 26 PS3 She's Got Soul | G72: 46068.583 | H72: Pops | I72: 0.85 | J72: =K72/AG72 -> 0.28176101 | K72: =S72+AC72 -> 448 | L72: =Y72+AD72 -> 30213.3 | M72: =Z72+AE72 -> 94667 | N72: =L72-M72 -> -64453.7 | O72: =IF(P72="Too early",P72,P72/AG72) -> Too early | P72: =IF(V72="Too early",V72,V72+AC72) -> Too early | Q72: =IF(V72="Too early",V72,AD72+V72*AH72) -> Too early | R72: =IF(V72="Too early",V72,Q72-M72) -> Too early | S72: 63 | T72: =AG72-AC72 -> 1205 | U72: =(AG72-AC72)*I72 -> 1024.25 | V72: =IF(B72<11,MIN((S72/VLOOKUP(B72,'Sales Pacing'!$A$23:$E$36,2)),T72),"Too early") -> Too early | W72: =Q72-AD72 -> #VALUE! | X72: =IF(V72="Too early","Too early",V72/U72) -> Too early | Y72: 3982 | Z72: 53334 | AA72: =IF(Y72>0,Y72/Z72,"") -> 0.074661567 | AB72: =IF($V72="Too early",V72,V72*AH72/Z72) -> Too early | AC72: 385 | AD72: 26231.3 | AE72: 41333 | AF72: =IF(AD72>0,AD72/AE72,"") -> 0.63463334 | AG72: 1590 | AH72: =Y72/S72 -> 63.206349 | AL72: 29655.3 | AM72: =L72-AL72 -> 558
A73: 25 | B73: =A73-$G$4 -> 16 | C73: 46069 | D73: 26 Harry Potter 2: Chamber | G73: 46072.792 | H73: Specials/Film | I73: 0.85 | J73: =K73/AG73 -> 0.10291859 | K73: =S73+AC73 -> 134 | L73: =Y73+AD73 -> 9551.5 | M73: =Z73+AE73 -> 111250 | N73: =L73-M73 -> -101698.5 | O73: =IF(P73="Too early",P73,P73/AG73) -> Too early | P73: =IF(V73="Too early",V73,V73+AC73) -> Too early | Q73: =IF(V73="Too early",V73,AD73+V73*AH73) -> Too early | R73: =IF(V73="Too early",V73,Q73-M73) -> Too early | S73: 134 | T73: =AG73-AC73 -> 1302 | U73: =(AG73-AC73)*I73 -> 1106.7 | V73: =IF(B73<11,MIN((S73/VLOOKUP(B73,'Sales Pacing'!$A$23:$E$36,2)),T73),"Too early") -> Too early | W73: =Q73-AD73 -> #VALUE! | X73: =IF(V73="Too early","Too early",V73/U73) -> Too early | Y73: 9551.5 | Z73: 111250 | AA73: =IF(Y73>0,Y73/Z73,"") -> 0.08585618 | AB73: =IF($V73="Too early",V73,V73*AH73/Z73) -> Too early | AF73: =IF(AD73>0,AD73/AE73,"") | AG73: 1302 | AH73: =Y73/S73 -> 71.279851 | AL73: 9361.5 | AM73: =L73-AL73 -> 190
A74: 25 | B74: =A74-$G$4 -> 16 | C74: 46069 | D74: 26 Harry Potter 2: Chamber | G74: 46073.792 | H74: Specials/Film | I74: 0.85 | J74: =K74/AG74 -> 0.18817204 | K74: =S74+AC74 -> 245 | L74: =Y74+AD74 -> 17743 | M74: =Z74+AE74 -> 111250 | N74: =L74-M74 -> -93507 | O74: =IF(P74="Too early",P74,P74/AG74) -> Too early | P74: =IF(V74="Too early",V74,V74+AC74) -> Too early | Q74: =IF(V74="Too early",V74,AD74+V74*AH74) -> Too early | R74: =IF(V74="Too early",V74,Q74-M74) -> Too early | S74: 245 | T74: =AG74-AC74 -> 1302 | U74: =(AG74-AC74)*I74 -> 1106.7 | V74: =IF(B74<11,MIN((S74/VLOOKUP(B74,'Sales Pacing'!$A$23:$E$36,2)),T74),"Too early") -> Too early | W74: =Q74-AD74 -> #VALUE! | X74: =IF(V74="Too early","Too early",V74/U74) -> Too early | Y74: 17743 | Z74: 111250 | AA74: =IF(Y74>0,Y74/Z74,"") -> 0.15948764 | AB74: =IF($V74="Too early",V74,V74*AH74/Z74) -> Too early | AF74: =IF(AD74>0,AD74/AE74,"") | AG74: 1302 | AH74: =Y74/S74 -> 72.420408 | AL74: 17663 | AM74: =L74-AL74 -> 80
A75: 25 | B75: =A75-$G$4 -> 16 | C75: 46069 | D75: 26 Harry Potter 2: Chamber | G75: 46074.792 | H75: Specials/Film | I75: 0.85 | J75: =K75/AG75 -> 0.34101382 | K75: =S75+AC75 -> 444 | L75: =Y75+AD75 -> 33393 | M75: =Z75+AE75 -> 111250 | N75: =L75-M75 -> -77857 | O75: =IF(P75="Too early",P75,P75/AG75) -> Too early | P75: =IF(V75="Too early",V75,V75+AC75) -> Too early | Q75: =IF(V75="Too early",V75,AD75+V75*AH75) -> Too early | R75: =IF(V75="Too early",V75,Q75-M75) -> Too early | S75: 444 | T75: =AG75-AC75 -> 1302 | U75: =(AG75-AC75)*I75 -> 1106.7 | V75: =IF(B75<11,MIN((S75/VLOOKUP(B75,'Sales Pacing'!$A$23:$E$36,2)),T75),"Too early") -> Too early | W75: =Q75-AD75 -> #VALUE! | X75: =IF(V75="Too early","Too early",V75/U75) -> Too early | Y75: 33393 | Z75: 111250 | AA75: =IF(Y75>0,Y75/Z75,"") -> 0.3001618 | AB75: =IF($V75="Too early",V75,V75*AH75/Z75) -> Too early | AF75: =IF(AD75>0,AD75/AE75,"") | AG75: 1302 | AH75: =Y75/S75 -> 75.209459 | AL75: 31515 | AM75: =L75-AL75 -> 1878
A76: 25 | B76: =A76-$G$4 -> 16 | C76: 46069 | D76: 26 Harry Potter 2: Chamber | G76: 46075.583 | H76: Specials/Film | I76: 0.85 | J76: =K76/AG76 -> 0.38786482 | K76: =S76+AC76 -> 505 | L76: =Y76+AD76 -> 34032.5 | M76: =Z76+AE76 -> 111250 | N76: =L76-M76 -> -77217.5 | O76: =IF(P76="Too early",P76,P76/AG76) -> Too early | P76: =IF(V76="Too early",V76,V76+AC76) -> Too early | Q76: =IF(V76="Too early",V76,AD76+V76*AH76) -> Too early | R76: =IF(V76="Too early",V76,Q76-M76) -> Too early | S76: 505 | T76: =AG76-AC76 -> 1302 | U76: =(AG76-AC76)*I76 -> 1106.7 | V76: =IF(B76<11,MIN((S76/VLOOKUP(B76,'Sales Pacing'!$A$23:$E$36,2)),T76),"Too early") -> Too early | W76: =Q76-AD76 -> #VALUE! | X76: =IF(V76="Too early","Too early",V76/U76) -> Too early | Y76: 34032.5 | Z76: 111250 | AA76: =IF(Y76>0,Y76/Z76,"") -> 0.30591011 | AB76: =IF($V76="Too early",V76,V76*AH76/Z76) -> Too early | AF76: =IF(AD76>0,AD76/AE76,"") | AG76: 1302 | AH76: =Y76/S76 -> 67.391089 | AL76: 33792.5 | AM76: =L76-AL76 -> 240
A77: 26 | B77: =A77-$G$4 -> 17 | C77: 46076 | D77: 26 FS3 Philharmonia Fantastique | G77: 46082.583 | H77: Family | I77: 0.5 | J77: =K77/AG77 -> 0.27419355 | K77: =S77+AC77 -> 357 | L77: =Y77+AD77 -> 8297 | M77: =Z77+AE77 -> 19500 | N77: =L77-M77 -> -11203 | O77: =IF(P77="Too early",P77,P77/AG77) -> Too early | P77: =IF(V77="Too early",V77,V77+AC77) -> Too early | Q77: =IF(V77="Too early",V77,AD77+V77*AH77) -> Too early | R77: =IF(V77="Too early",V77,Q77-M77) -> Too early | S77: 50 | T77: =AG77-AC77 -> 995 | U77: =(AG77-AC77)*I77 -> 497.5 | V77: =IF(B77<11,MIN((S77/VLOOKUP(B77,'Sales Pacing'!$A$23:$E$36,2)),T77),"Too early") -> Too early | W77: =Q77-AD77 -> #VALUE! | X77: =IF(V77="Too early","Too early",V77/U77) -> Too early | Y77: 1461 | Z77: 10000 | AA77: =IF(Y77>0,Y77/Z77,"") -> 0.1461 | AB77: =IF($V77="Too early",V77,V77*AH77/Z77) -> Too early | AC77: 307 | AD77: 6836 | AE77: 9500 | AF77: =IF(AD77>0,AD77/AE77,"") -> 0.71957895 | AG77: 1302 | AH77: =Y77/S77 -> 29.22 | AL77: 8100 | AM77: =L77-AL77 -> 197
A78: 27 | B78: =A78-$G$4 -> 18 | C78: 46083 | D78: OPEN | J78: =K78/AG78 -> #DIV/0! | K78: =S78+AC78 -> 0 | L78: =Y78+AD78 -> 0 | M78: =Z78+AE78 -> 0 | P78: =IF(V78="Too early",V78,V78+AC78) -> Too early | Q78: =IF(V78="Too early",V78,AD78+V78*AH78) -> Too early | R78: =IF(V78="Too early",V78,Q78-M78) -> Too early | T78: =AG78-AC78 -> 0 | U78: =(AG78-AC78)*I78 -> 0 | V78: =IF(B78<11,MIN((S78/VLOOKUP(B78,'Sales Pacing'!$A$23:$E$36,2)),T78),"Too early") -> Too early | W78: =Q78-AD78 -> #VALUE! | AA78: =IF(Y78>0,Y78/Z78,"") | AF78: N/A | AH78: =Y78/S78 -> #DIV/0! | AL78: 0
A79: 28 | B79: =A79-$G$4 -> 19 | C79: 46090 | D79: 26 CS08 Saint-Saëns & Strauss | G79: 46094.833 | H79: Classical | I79: 0.85 | J79: =K79/AG79 -> 0.39371069 | K79: =S79+AC79 -> 626 | L79: =Y79+AD79 -> 41199 | M79: =Z79+AE79 -> 54999 | N79: =L79-M79 -> -13800 | O79: =IF(P79="Too early",P79,P79/AG79) -> Too early | P79: =IF(V79="Too early",V79,V79+AC79) -> Too early | Q79: =IF(V79="Too early",V79,AD79+V79*AH79) -> Too early | R79: =IF(V79="Too early",V79,Q79-M79) -> Too early | S79: 53 | T79: =AG79-AC79 -> 1017 | U79: =(AG79-AC79)*I79 -> 864.45 | V79: =IF(B79<11,MIN((S79/VLOOKUP(B79,'Sales Pacing'!$A$23:$E$36,2)),T79),"Too early") -> Too early | W79: =Q79-AD79 -> #VALUE! | X79: =IF(V79="Too early","Too early",V79/U79) -> Too early | Y79: 2862 | Z79: 18333 | AA79: =IF(Y79>0,Y79/Z79,"") -> 0.15611193 | AB79: =IF($V79="Too early",V79,V79*AH79/Z79) -> Too early | AC79: 573 | AD79: 38337 | AE79: 36666 | AF79: =IF(AD79>0,AD79/AE79,"") -> 1.0455736 | AG79: 1590 | AH79: =Y79/S79 -> 54 | AL79: 40846 | AM79: =L79-AL79 -> 353
A80: 28 | B80: =A80-$G$4 -> 19 | C80: 46090 | D80: 26 CS08 Saint-Saëns & Strauss | G80: 46095.833 | H80: Classical | I80: 0.85 | J80: =K80/AG80 -> 0.3918239 | K80: =S80+AC80 -> 623 | L80: =Y80+AD80 -> 39776.2 | M80: =Z80+AE80 -> 55000 | N80: =L80-M80 -> -15223.8 | O80: =IF(P80="Too early",P80,P80/AG80) -> Too early | P80: =IF(V80="Too early",V80,V80+AC80) -> Too early | Q80: =IF(V80="Too early",V80,AD80+V80*AH80) -> Too early | R80: =IF(V80="Too early",V80,Q80-M80) -> Too early | S80: 61 | T80: =AG80-AC80 -> 1028 | U80: =(AG80-AC80)*I80 -> 873.8 | V80: =IF(B80<11,MIN((S80/VLOOKUP(B80,'Sales Pacing'!$A$23:$E$36,2)),T80),"Too early") -> Too early | W80: =Q80-AD80 -> #VALUE! | X80: =IF(V80="Too early","Too early",V80/U80) -> Too early | Y80: 3360 | Z80: 18333 | AA80: =IF(Y80>0,Y80/Z80,"") -> 0.18327606 | AB80: =IF($V80="Too early",V80,V80*AH80/Z80) -> Too early | AC80: 562 | AD80: 36416.2 | AE80: 36667 | AF80: =IF(AD80>0,AD80/AE80,"") -> 0.99316006 | AG80: 1590 | AH80: =Y80/S80 -> 55.081967 | AL80: 39753.2 | AM80: =L80-AL80 -> 23
A81: 28 | B81: =A81-$G$4 -> 19 | C81: 46090 | D81: 26 CS08 Saint-Saëns & Strauss | G81: 46096.583 | H81: Classical | I81: 0.85 | J81: =K81/AG81 -> 0.4081761 | K81: =S81+AC81 -> 649 | L81: =Y81+AD81 -> 41376.1 | M81: =Z81+AE81 -> 55001 | N81: =L81-M81 -> -13624.9 | O81: =IF(P81="Too early",P81,P81/AG81) -> Too early | P81: =IF(V81="Too early",V81,V81+AC81) -> Too early | Q81: =IF(V81="Too early",V81,AD81+V81*AH81) -> Too early | R81: =IF(V81="Too early",V81,Q81-M81) -> Too early | S81: 76 | T81: =AG81-AC81 -> 1017 | U81: =(AG81-AC81)*I81 -> 864.45 | V81: =IF(B81<11,MIN((S81/VLOOKUP(B81,'Sales Pacing'!$A$23:$E$36,2)),T81),"Too early") -> Too early | W81: =Q81-AD81 -> #VALUE! | X81: =IF(V81="Too early","Too early",V81/U81) -> Too early | Y81: 4624 | Z81: 18334 | AA81: =IF(Y81>0,Y81/Z81,"") -> 0.25220901 | AB81: =IF($V81="Too early",V81,V81*AH81/Z81) -> Too early | AC81: 573 | AD81: 36752.1 | AE81: 36667 | AF81: =IF(AD81>0,AD81/AE81,"") -> 1.0023209 | AG81: 1590 | AH81: =Y81/S81 -> 60.842105 | AL81: 41030.1 | AM81: =L81-AL81 -> 346
A82: 29 | B82: =A82-$G$4 -> 20 | C82: 46097 | D82: OPEN | J82: =K82/AG82 -> #DIV/0! | K82: =S82+AC82 -> 0 | L82: =Y82+AD82 -> 0 | M82: =Z82+AE82 -> 0 | P82: =IF(V82="Too early",V82,V82+AC82) -> Too early | Q82: =IF(V82="Too early",V82,AD82+V82*AH82) -> Too early | R82: =IF(V82="Too early",V82,Q82-M82) -> Too early | T82: =AG82-AC82 -> 0 | U82: =(AG82-AC82)*I82 -> 0 | V82: =IF(B82<11,MIN((S82/VLOOKUP(B82,'Sales Pacing'!$A$23:$E$36,2)),T82),"Too early") -> Too early | W82: =Q82-AD82 -> #VALUE! | AA82: =IF(Y82>0,Y82/Z82,"") | AF82: N/A | AH82: =Y82/S82 -> #DIV/0! | AL82: 0
A83: 30 | B83: =A83-$G$4 -> 21 | C83: 46104 | D83: Final Symphony | G83: 46106 | H83: Specials | I83: 0.85 | J83: =K83/AG83 -> 0.05408805 | K83: =S83+AC83 -> 86 | L83: =Y83+AD83 -> 5437 | M83: =Z83+AE83 -> 84109 | N83: =L83-M83 -> -78672 | O83: =IF(P83="Too early",P83,P83/AG83) -> Too early | P83: =IF(V83="Too early",V83,V83+AC83) -> Too early | Q83: =IF(V83="Too early",V83,AD83+V83*AH83) -> Too early | R83: =IF(V83="Too early",V83,Q83-M83) -> Too early | S83: 86 | T83: =AG83-AC83 -> 1590 | U83: =(AG83-AC83)*I83 -> 1351.5 | V83: =IF(B83<11,MIN((S83/VLOOKUP(B83,'Sales Pacing'!$A$23:$E$36,2)),T83),"Too early") -> Too early | W83: =Q83-AD83 -> #VALUE! | X83: =IF(V83="Too early","Too early",V83/U83) -> Too early | Y83: 5437 | Z83: 84109 | AA83: =IF(Y83>0,Y83/Z83,"") -> 0.064642309 | AB83: =IF($V83="Too early",V83,V83*AH83/Z83) -> Too early | AG83: 1590 | AH83: =Y83/S83 -> 63.22093 | AL83: 5437 | AM83: =L83-AL83 -> 0
A84: 30 | B84: =A84-$G$4 -> 21 | C84: 46104 | D84: Final Symphony | G84: 46107 | H84: Specials | I84: 0.85 | J84: =K84/AG84 -> 0.054716981 | K84: =S84+AC84 -> 87 | L84: =Y84+AD84 -> 5027.5 | M84: =Z84+AE84 -> 84109 | N84: =L84-M84 -> -79081.5 | O84: =IF(P84="Too early",P84,P84/AG84) -> Too early | P84: =IF(V84="Too early",V84,V84+AC84) -> Too early | Q84: =IF(V84="Too early",V84,AD84+V84*AH84) -> Too early | R84: =IF(V84="Too early",V84,Q84-M84) -> Too early | S84: 87 | T84: =AG84-AC84 -> 1590 | U84: =(AG84-AC84)*I84 -> 1351.5 | V84: =IF(B84<11,MIN((S84/VLOOKUP(B84,'Sales Pacing'!$A$23:$E$36,2)),T84),"Too early") -> Too early | W84: =Q84-AD84 -> #VALUE! | X84: =IF(V84="Too early","Too early",V84/U84) -> Too early | Y84: 5027.5 | Z84: 84109 | AA84: =IF(Y84>0,Y84/Z84,"") -> 0.059773627 | AB84: =IF($V84="Too early",V84,V84*AH84/Z84) -> Too early | AG84: 1590 | AH84: =Y84/S84 -> 57.787356 | AL84: 5027.5 | AM84: =L84-AL84 -> 0
A85: 30 | B85: =A85-$G$4 -> 21 | C85: 46104 | D85: 26 PS4 Billy Joel & Elton John | G85: 46108.833 | H85: Pops | I85: 0.85 | J85: =K85/AG85 -> 0.56792453 | K85: =S85+AC85 -> 903 | L85: =Y85+AD85 -> 64363.1 | M85: =Z85+AE85 -> 94666 | N85: =L85-M85 -> -30302.9 | O85: =IF(P85="Too early",P85,P85/AG85) -> Too early | P85: =IF(V85="Too early",V85,V85+AC85) -> Too early | Q85: =IF(V85="Too early",V85,AD85+V85*AH85) -> Too early | R85: =IF(V85="Too early",V85,Q85-M85) -> Too early | S85: 164 | T85: =AG85-AC85 -> 851 | U85: =(AG85-AC85)*I85 -> 723.35 | V85: =IF(B85<11,MIN((S85/VLOOKUP(B85,'Sales Pacing'!$A$23:$E$36,2)),T85),"Too early") -> Too early | W85: =Q85-AD85 -> #VALUE! | X85: =IF(V85="Too early","Too early",V85/U85) -> Too early | Y85: 11069 | Z85: 53333 | AA85: =IF(Y85>0,Y85/Z85,"") -> 0.20754505 | AB85: =IF($V85="Too early",V85,V85*AH85/Z85) -> Too early | AC85: 739 | AD85: 53294.1 | AE85: 41333 | AF85: =IF(AD85>0,AD85/AE85,"") -> 1.2893838 | AG85: 1590 | AH85: =Y85/S85 -> 67.493902 | AL85: 64129.1 | AM85: =L85-AL85 -> 234
A86: 30 | B86: =A86-$G$4 -> 21 | C86: 46104 | D86: 26 PS4 Billy Joel & Elton John | G86: 46109.833 | H86: Pops | I86: 0.85 | J86: =K86/AG86 -> 0.53773585 | K86: =S86+AC86 -> 855 | L86: =Y86+AD86 -> 61452.8 | M86: =Z86+AE86 -> 94667 | N86: =L86-M86 -> -33214.2 | O86: =IF(P86="Too early",P86,P86/AG86) -> Too early | P86: =IF(V86="Too early",V86,V86+AC86) -> Too early | Q86: =IF(V86="Too early",V86,AD86+V86*AH86) -> Too early | R86: =IF(V86="Too early",V86,Q86-M86) -> Too early | S86: 185 | T86: =AG86-AC86 -> 920 | U86: =(AG86-AC86)*I86 -> 782 | V86: =IF(B86<11,MIN((S86/VLOOKUP(B86,'Sales Pacing'!$A$23:$E$36,2)),T86),"Too early") -> Too early | W86: =Q86-AD86 -> #VALUE! | X86: =IF(V86="Too early","Too early",V86/U86) -> Too early | Y86: 13007 | Z86: 53333 | AA86: =IF(Y86>0,Y86/Z86,"") -> 0.24388277 | AB86: =IF($V86="Too early",V86,V86*AH86/Z86) -> Too early | AC86: 670 | AD86: 48445.8 | AE86: 41334 | AF86: =IF(AD86>0,AD86/AE86,"") -> 1.1720569 | AG86: 1590 | AH86: =Y86/S86 -> 70.308108 | AL86: 60900.8 | AM86: =L86-AL86 -> 552
A87: 30 | B87: =A87-$G$4 -> 21 | C87: 46104 | D87: 26 PS4 Billy Joel & Elton John | G87: 46110.583 | H87: Pops | I87: 0.85 | J87: =K87/AG87 -> 0.38930818 | K87: =S87+AC87 -> 619 | L87: =Y87+AD87 -> 43141.6 | M87: =Z87+AE87 -> 94667 | N87: =L87-M87 -> -51525.4 | O87: =IF(P87="Too early",P87,P87/AG87) -> Too early | P87: =IF(V87="Too early",V87,V87+AC87) -> Too early | Q87: =IF(V87="Too early",V87,AD87+V87*AH87) -> Too early | R87: =IF(V87="Too early",V87,Q87-M87) -> Too early | S87: 230 | T87: =AG87-AC87 -> 1201 | U87: =(AG87-AC87)*I87 -> 1020.85 | V87: =IF(B87<11,MIN((S87/VLOOKUP(B87,'Sales Pacing'!$A$23:$E$36,2)),T87),"Too early") -> Too early | W87: =Q87-AD87 -> #VALUE! | X87: =IF(V87="Too early","Too early",V87/U87) -> Too early | Y87: 16690 | Z87: 53334 | AA87: =IF(Y87>0,Y87/Z87,"") -> 0.31293359 | AB87: =IF($V87="Too early",V87,V87*AH87/Z87) -> Too early | AC87: 389 | AD87: 26451.6 | AE87: 41333 | AF87: =IF(AD87>0,AD87/AE87,"") -> 0.63996323 | AG87: 1590 | AH87: =Y87/S87 -> 72.565217 | AL87: 41992.6 | AM87: =L87-AL87 -> 1149
A88: 31 | B88: =A88-$G$4 -> 22 | C88: 46111 | D88: OPEN | J88: =K88/AG88 -> #DIV/0! | K88: =S88+AC88 -> 0 | L88: =Y88+AD88 -> 0 | M88: =Z88+AE88 -> 0 | P88: =IF(V88="Too early",V88,V88+AC88) -> Too early | Q88: =IF(V88="Too early",V88,AD88+V88*AH88) -> Too early | R88: =IF(V88="Too early",V88,Q88-M88) -> Too early | T88: =AG88-AC88 -> 0 | U88: =(AG88-AC88)*I88 -> 0 | V88: =IF(B88<11,MIN((S88/VLOOKUP(B88,'Sales Pacing'!$A$23:$E$36,2)),T88),"Too early") -> Too early | W88: =Q88-AD88 -> #VALUE! | AA88: =IF(Y88>0,Y88/Z88,"") | AF88: N/A | AH88: =Y88/S88 -> #DIV/0! | AL88: 0
A89: 32 | B89: =A89-$G$4 -> 23 | C89: 46118 | D89: 26 CS09 Midsummer Night's Dream | G89: 46122.833 | H89: Classical | I89: 0.5 | J89: =K89/AG89 -> 0.29309142 | K89: =S89+AC89 -> 420 | L89: =Y89+AD89 -> 28125 | M89: =Z89+AE89 -> 52000 | N89: =L89-M89 -> -23875 | O89: =IF(P89="Too early",P89,P89/AG89) -> Too early | P89: =IF(V89="Too early",V89,V89+AC89) -> Too early | Q89: =IF(V89="Too early",V89,AD89+V89*AH89) -> Too early | R89: =IF(V89="Too early",V89,Q89-M89) -> Too early | S89: 52 | T89: =AG89-AC89 -> 1065 | U89: =(AG89-AC89)*I89 -> 532.5 | V89: =IF(B89<11,MIN((S89/VLOOKUP(B89,'Sales Pacing'!$A$23:$E$36,2)),T89),"Too early") -> Too early | W89: =Q89-AD89 -> #VALUE! | X89: =IF(V89="Too early","Too early",V89/U89) -> Too early | Y89: 2411 | Z89: 22000 | AA89: =IF(Y89>0,Y89/Z89,"") -> 0.10959091 | AB89: =IF($V89="Too early",V89,V89*AH89/Z89) -> Too early | AC89: 368 | AD89: 25714 | AE89: 30000 | AF89: =IF(AD89>0,AD89/AE89,"") -> 0.85713333 | AG89: 1433 | AH89: =Y89/S89 -> 46.365385 | AL89: 27729 | AM89: =L89-AL89 -> 396
A90: 32 | B90: =A90-$G$4 -> 23 | C90: 46118 | D90: 26 CS09 Midsummer Night's Dream | G90: 46123.833 | H90: Classical | I90: 0.85 | J90: =K90/AG90 -> 0.4619679 | K90: =S90+AC90 -> 662 | L90: =Y90+AD90 -> 41374 | M90: =Z90+AE90 -> 74000 | N90: =L90-M90 -> -32626 | O90: =IF(P90="Too early",P90,P90/AG90) -> Too early | P90: =IF(V90="Too early",V90,V90+AC90) -> Too early | Q90: =IF(V90="Too early",V90,AD90+V90*AH90) -> Too early | R90: =IF(V90="Too early",V90,Q90-M90) -> Too early | S90: 97 | T90: =AG90-AC90 -> 868 | U90: =(AG90-AC90)*I90 -> 737.8 | V90: =IF(B90<11,MIN((S90/VLOOKUP(B90,'Sales Pacing'!$A$23:$E$36,2)),T90),"Too early") -> Too early | W90: =Q90-AD90 -> #VALUE! | X90: =IF(V90="Too early","Too early",V90/U90) -> Too early | Y90: 5001 | Z90: 24000 | AA90: =IF(Y90>0,Y90/Z90,"") -> 0.208375 | AB90: =IF($V90="Too early",V90,V90*AH90/Z90) -> Too early | AC90: 565 | AD90: 36373 | AE90: 50000 | AF90: =IF(AD90>0,AD90/AE90,"") -> 0.72746 | AG90: 1433 | AH90: =Y90/S90 -> 51.556701 | AL90: 41302 | AM90: =L90-AL90 -> 72
A91: 32 | B91: =A91-$G$4 -> 23 | C91: 46118 | D91: 26 CS09 Midsummer Night's Dream | G91: 46124.583 | H91: Classical | I91: 0.85 | J91: =K91/AG91 -> 0.44801117 | K91: =S91+AC91 -> 642 | L91: =Y91+AD91 -> 39965.1 | M91: =Z91+AE91 -> 74000 | N91: =L91-M91 -> -34034.9 | O91: =IF(P91="Too early",P91,P91/AG91) -> Too early | P91: =IF(V91="Too early",V91,V91+AC91) -> Too early | Q91: =IF(V91="Too early",V91,AD91+V91*AH91) -> Too early | R91: =IF(V91="Too early",V91,Q91-M91) -> Too early | S91: 70 | T91: =AG91-AC91 -> 861 | U91: =(AG91-AC91)*I91 -> 731.85 | V91: =IF(B91<11,MIN((S91/VLOOKUP(B91,'Sales Pacing'!$A$23:$E$36,2)),T91),"Too early") -> Too early | W91: =Q91-AD91 -> #VALUE! | X91: =IF(V91="Too early","Too early",V91/U91) -> Too early | Y91: 3060 | Z91: 24000 | AA91: =IF(Y91>0,Y91/Z91,"") -> 0.1275 | AB91: =IF($V91="Too early",V91,V91*AH91/Z91) -> Too early | AC91: 572 | AD91: 36905.1 | AE91: 50000 | AF91: =IF(AD91>0,AD91/AE91,"") -> 0.738102 | AG91: 1433 | AH91: =Y91/S91 -> 43.714286 | AL91: 39738.1 | AM91: =L91-AL91 -> 227
A92: 33 | B92: =A92-$G$4 -> 24 | C92: 46125 | D92: 26 CS10 Farrenc/Dvorák/Schuman | G92: 46129.833 | H92: Classical | I92: 0.85 | J92: =K92/AG92 -> 0.38301887 | K92: =S92+AC92 -> 609 | L92: =Y92+AD92 -> 39973 | M92: =Z92+AE92 -> 46666 | N92: =L92-M92 -> -6693 | O92: =IF(P92="Too early",P92,P92/AG92) -> Too early | P92: =IF(V92="Too early",V92,V92+AC92) -> Too early | Q92: =IF(V92="Too early",V92,AD92+V92*AH92) -> Too early | R92: =IF(V92="Too early",V92,Q92-M92) -> Too early | S92: 31 | T92: =AG92-AC92 -> 1012 | U92: =(AG92-AC92)*I92 -> 860.2 | V92: =IF(B92<11,MIN((S92/VLOOKUP(B92,'Sales Pacing'!$A$23:$E$36,2)),T92),"Too early") -> Too early | W92: =Q92-AD92 -> #VALUE! | X92: =IF(V92="Too early","Too early",V92/U92) -> Too early | Y92: 1099 | Z92: 13333 | AA92: =IF(Y92>0,Y92/Z92,"") -> 0.082427061 | AB92: =IF($V92="Too early",V92,V92*AH92/Z92) -> Too early | AC92: 578 | AD92: 38874 | AE92: 33333 | AF92: =IF(AD92>0,AD92/AE92,"") -> 1.1662317 | AG92: 1590 | AH92: =Y92/S92 -> 35.451613 | AL92: 39793 | AM92: =L92-AL92 -> 180
A93: 33 | B93: =A93-$G$4 -> 24 | C93: 46125 | D93: 26 CS10 Farrenc/Dvorák/Schuman | G93: 46130.833 | H93: Classical | I93: 0.85 | J93: =K93/AG93 -> 0.39245283 | K93: =S93+AC93 -> 624 | L93: =Y93+AD93 -> 41660.9 | M93: =Z93+AE93 -> 46666 | N93: =L93-M93 -> -5005.1 | O93: =IF(P93="Too early",P93,P93/AG93) -> Too early | P93: =IF(V93="Too early",V93,V93+AC93) -> Too early | Q93: =IF(V93="Too early",V93,AD93+V93*AH93) -> Too early | R93: =IF(V93="Too early",V93,Q93-M93) -> Too early | S93: 32 | T93: =AG93-AC93 -> 998 | U93: =(AG93-AC93)*I93 -> 848.3 | V93: =IF(B93<11,MIN((S93/VLOOKUP(B93,'Sales Pacing'!$A$23:$E$36,2)),T93),"Too early") -> Too early | W93: =Q93-AD93 -> #VALUE! | X93: =IF(V93="Too early","Too early",V93/U93) -> Too early | Y93: 1399 | Z93: 13333 | AA93: =IF(Y93>0,Y93/Z93,"") -> 0.10492762 | AB93: =IF($V93="Too early",V93,V93*AH93/Z93) -> Too early | AC93: 592 | AD93: 40261.9 | AE93: 33333 | AF93: =IF(AD93>0,AD93/AE93,"") -> 1.2078691 | AG93: 1590 | AH93: =Y93/S93 -> 43.71875 | AL93: 41723.9 | AM93: =L93-AL93 -> -63
A94: 33 | B94: =A94-$G$4 -> 24 | C94: 46125 | D94: 26 CS10 Farrenc/Dvorák/Schuman | G94: 46131.583 | H94: Classical | I94: 0.85 | J94: =K94/AG94 -> 0.41446541 | K94: =S94+AC94 -> 659 | L94: =Y94+AD94 -> 41694.2 | M94: =Z94+AE94 -> 46668 | N94: =L94-M94 -> -4973.8 | O94: =IF(P94="Too early",P94,P94/AG94) -> Too early | P94: =IF(V94="Too early",V94,V94+AC94) -> Too early | Q94: =IF(V94="Too early",V94,AD94+V94*AH94) -> Too early | R94: =IF(V94="Too early",V94,Q94-M94) -> Too early | S94: 40 | T94: =AG94-AC94 -> 971 | U94: =(AG94-AC94)*I94 -> 825.35 | V94: =IF(B94<11,MIN((S94/VLOOKUP(B94,'Sales Pacing'!$A$23:$E$36,2)),T94),"Too early") -> Too early | W94: =Q94-AD94 -> #VALUE! | X94: =IF(V94="Too early","Too early",V94/U94) -> Too early | Y94: 1731 | Z94: 13334 | AA94: =IF(Y94>0,Y94/Z94,"") -> 0.12981851 | AB94: =IF($V94="Too early",V94,V94*AH94/Z94) -> Too early | AC94: 619 | AD94: 39963.2 | AE94: 33334 | AF94: =IF(AD94>0,AD94/AE94,"") -> 1.198872 | AG94: 1590 | AH94: =Y94/S94 -> 43.275 | AL94: 41460.2 | AM94: =L94-AL94 -> 234
A95: 34 | B95: =A95-$G$4 -> 25 | C95: 46132 | D95: OPEN | J95: =K95/AG95 -> #DIV/0! | K95: =S95+AC95 -> 0 | L95: =Y95+AD95 -> 0 | M95: =Z95+AE95 -> 0 | P95: =IF(V95="Too early",V95,V95+AC95) -> Too early | Q95: =IF(V95="Too early",V95,AD95+V95*AH95) -> Too early | R95: =IF(V95="Too early",V95,Q95-M95) -> Too early | T95: =AG95-AC95 -> 0 | U95: =(AG95-AC95)*I95 -> 0 | V95: =IF(B95<11,MIN((S95/VLOOKUP(B95,'Sales Pacing'!$A$23:$E$36,2)),T95),"Too early") -> Too early | W95: =Q95-AD95 -> #VALUE! | AA95: =IF(Y95>0,Y95/Z95,"") | AF95: N/A | AH95: =Y95/S95 -> #DIV/0! | AL95: 0
A96: 35 | B96: =A96-$G$4 -> 26 | C96: 46139 | D96: OPEN | J96: =K96/AG96 -> #DIV/0! | K96: =S96+AC96 -> 0 | L96: =Y96+AD96 -> 0 | M96: =Z96+AE96 -> 0 | P96: =IF(V96="Too early",V96,V96+AC96) -> Too early | Q96: =IF(V96="Too early",V96,AD96+V96*AH96) -> Too early | R96: =IF(V96="Too early",V96,Q96-M96) -> Too early | T96: =AG96-AC96 -> 0 | U96: =(AG96-AC96)*I96 -> 0 | V96: =IF(B96<11,MIN((S96/VLOOKUP(B96,'Sales Pacing'!$A$23:$E$36,2)),T96),"Too early") -> Too early | W96: =Q96-AD96 -> #VALUE! | AA96: =IF(Y96>0,Y96/Z96,"") | AF96: N/A | AH96: =Y96/S96 -> #DIV/0! | AL96: 0
A97: 36 | B97: =A97-$G$4 -> 27 | C97: 46146 | D97: 26 CS11 Grieg's Piano Concerto | G97: 46150.833 | H97: Classical | I97: 0.5 | J97: =K97/AG97 -> 0.26666667 | K97: =S97+AC97 -> 424 | L97: =Y97+AD97 -> 28112 | M97: =Z97+AE97 -> 45000 | N97: =L97-M97 -> -16888 | O97: =IF(P97="Too early",P97,P97/AG97) -> Too early | P97: =IF(V97="Too early",V97,V97+AC97) -> Too early | Q97: =IF(V97="Too early",V97,AD97+V97*AH97) -> Too early | R97: =IF(V97="Too early",V97,Q97-M97) -> Too early | S97: 50 | T97: =AG97-AC97 -> 1216 | U97: =(AG97-AC97)*I97 -> 608 | V97: =IF(B97<11,MIN((S97/VLOOKUP(B97,'Sales Pacing'!$A$23:$E$36,2)),T97),"Too early") -> Too early | W97: =Q97-AD97 -> #VALUE! | X97: =IF(V97="Too early","Too early",V97/U97) -> Too early | Y97: 2349 | Z97: 20000 | AA97: =IF(Y97>0,Y97/Z97,"") -> 0.11745 | AB97: =IF($V97="Too early",V97,V97*AH97/Z97) -> Too early | AC97: 374 | AD97: 25763 | AE97: 25000 | AF97: =IF(AD97>0,AD97/AE97,"") -> 1.03052 | AG97: 1590 | AH97: =Y97/S97 -> 46.98 | AL97: 27937 | AM97: =L97-AL97 -> 175
A98: 36 | B98: =A98-$G$4 -> 27 | C98: 46146 | D98: 26 CS11 Grieg's Piano Concerto | G98: 46151.833 | H98: Classical | I98: 0.85 | J98: =K98/AG98 -> 0.43333333 | K98: =S98+AC98 -> 689 | L98: =Y98+AD98 -> 45719.9 | M98: =Z98+AE98 -> 65000 | N98: =L98-M98 -> -19280.1 | O98: =IF(P98="Too early",P98,P98/AG98) -> Too early | P98: =IF(V98="Too early",V98,V98+AC98) -> Too early | Q98: =IF(V98="Too early",V98,AD98+V98*AH98) -> Too early | R98: =IF(V98="Too early",V98,Q98-M98) -> Too early | S98: 89 | T98: =AG98-AC98 -> 990 | U98: =(AG98-AC98)*I98 -> 841.5 | V98: =IF(B98<11,MIN((S98/VLOOKUP(B98,'Sales Pacing'!$A$23:$E$36,2)),T98),"Too early") -> Too early | W98: =Q98-AD98 -> #VALUE! | X98: =IF(V98="Too early","Too early",V98/U98) -> Too early | Y98: 5356 | Z98: 17500 | AA98: =IF(Y98>0,Y98/Z98,"") -> 0.30605714 | AB98: =IF($V98="Too early",V98,V98*AH98/Z98) -> Too early | AC98: 600 | AD98: 40363.9 | AE98: 47500 | AF98: =IF(AD98>0,AD98/AE98,"") -> 0.84976632 | AG98: 1590 | AH98: =Y98/S98 -> 60.179775 | AL98: 45768.9 | AM98: =L98-AL98 -> -49
A99: 36 | B99: =A99-$G$4 -> 27 | C99: 46146 | D99: 26 CS11 Grieg's Piano Concerto | G99: 46152.583 | H99: Classical | I99: 0.85 | J99: =K99/AG99 -> 0.42767296 | K99: =S99+AC99 -> 680 | L99: =Y99+AD99 -> 43281.2 | M99: =Z99+AE99 -> 65000 | N99: =L99-M99 -> -21718.8 | O99: =IF(P99="Too early",P99,P99/AG99) -> Too early | P99: =IF(V99="Too early",V99,V99+AC99) -> Too early | Q99: =IF(V99="Too early",V99,AD99+V99*AH99) -> Too early | R99: =IF(V99="Too early",V99,Q99-M99) -> Too early | S99: 69 | T99: =AG99-AC99 -> 979 | U99: =(AG99-AC99)*I99 -> 832.15 | V99: =IF(B99<11,MIN((S99/VLOOKUP(B99,'Sales Pacing'!$A$23:$E$36,2)),T99),"Too early") -> Too early | W99: =Q99-AD99 -> #VALUE! | X99: =IF(V99="Too early","Too early",V99/U99) -> Too early | Y99: 3734 | Z99: 17500 | AA99: =IF(Y99>0,Y99/Z99,"") -> 0.21337143 | AB99: =IF($V99="Too early",V99,V99*AH99/Z99) -> Too early | AC99: 611 | AD99: 39547.2 | AE99: 47500 | AF99: =IF(AD99>0,AD99/AE99,"") -> 0.83257263 | AG99: 1590 | AH99: =Y99/S99 -> 54.115942 | AL99: 42812.2 | AM99: =L99-AL99 -> 469
A100: 37 | B100: =A100-$G$4 -> 28 | C100: 46153 | D100: 26 PS5 Dolly Parton's Threads | G100: 46157.833 | H100: Pops | I100: 0.85 | J100: =K100/AG100 -> 0.62135177 | K100: =S100+AC100 -> 809 | L100: =Y100+AD100 -> 67940 | M100: =Z100+AE100 -> 103333 | N100: =L100-M100 -> -35393 | O100: =IF(P100="Too early",P100,P100/AG100) -> Too early | P100: =IF(V100="Too early",V100,V100+AC100) -> Too early | Q100: =IF(V100="Too early",V100,AD100+V100*AH100) -> Too early | R100: =IF(V100="Too early",V100,Q100-M100) -> Too early | S100: 71 | T100: =AG100-AC100 -> 564 | U100: =(AG100-AC100)*I100 -> 479.4 | V100: =IF(B100<11,MIN((S100/VLOOKUP(B100,'Sales Pacing'!$A$23:$E$36,2)),T100),"Too early") -> Too early | W100: =Q100-AD100 -> #VALUE! | X100: =IF(V100="Too early","Too early",V100/U100) -> Too early | Y100: 5507 | Z100: 60000 | AA100: =IF(Y100>0,Y100/Z100,"") -> 0.091783333 | AB100: =IF($V100="Too early",V100,V100*AH100/Z100) -> Too early | AC100: 738 | AD100: 62433 | AE100: 43333 | AF100: =IF(AD100>0,AD100/AE100,"") -> 1.4407726 | AG100: 1302 | AH100: =Y100/S100 -> 77.56338 | AL100: 67716 | AM100: =L100-AL100 -> 224
...

Sheet PS1 Journey
B1: # weeks out
A2: Single Tickets | B2: 5 | C2: 4 | D2: 3 | E2: 2 | F2: 1 | G2: 0 | L2: Estimates Only | P2: Historical Data
A3: PS1 Journey | B3: 45880 | C3: 45887 | D3: 45894 | E3: 45901 | F3: 45908 | G3: 45915 | H3: # Single Tickets to sell out 100% | I3: Projected OCC% | K3: # Weeks Until Performance | L3: 10 | M3: 9 | N3: 8 | O3: 7 | P3: 6 | Q3: 5 | R3: 4 | S3: 3 | T3: 2 | U3: 1 | V3: 0
A4: 9/19/2025 Sales (Fri) | B4: 60 | C4: 160 | D4: 205 | E4: 262 | F4: 311 | G4: 390 | H4: ='Performances by Week'!AG10-'Performances by Week'!AC10 -> 975 | I4: ='Performances by Week'!O10 -> #N/A | K4: Classical | L4: 0.15 | M4: 0.18 | N4: 0.21 | O4: 0.24 | P4: 0.27 | Q4: 0.3 | R4: 0.33 | S4: 0.39 | T4: 0.46 | U4: 0.59 | V4: 1
A5: 9/20/2025 Sales (Sat) | B5: 63 | C5: 206 | D5: 250 | E5: 294 | F5: 360 | G5: 422 | H5: ='Performances by Week'!AG11-'Performances by Week'!AC11 -> 1076 | I5: ='Performances by Week'!O11 -> #N/A | K5: Pops | L5: 0.15 | M5: 0.18 | N5: 0.21 | O5: 0.24 | P5: 0.27 | Q5: 0.3 | R5: 0.33 | S5: 0.39 | T5: 0.46 | U5: 0.59 | V5: 1
A6: 9/21/2025 Sales (Sun) | B6: 57 | C6: 219 | D6: 296 | E6: 322 | F6: 444 | G6: 516 | H6: ='Performances by Week'!AG12-'Performances by Week'!AC12 -> 1246 | I6: ='Performances by Week'!O12 -> #N/A | K6: Specials | L6: 0.15 | M6: 0.18 | N6: 0.21 | O6: 0.24 | P6: 0.27 | Q6: 0.3 | R6: 0.33 | S6: 0.39 | T6: 0.46 | U6: 0.59 | V6: 1
A7: Pace for 85% OCC | B7: =$H$7*$H$10*Q5 -> 280.245 | C7: =$H$7*$H$10*R5 -> 308.2695 | D7: =$H$7*$H$10*S5 -> 364.3185 | E7: =$H$7*$H$10*T5 -> 429.709 | F7: =$H$7*$H$10*U5 -> 551.1485 | G7: =$H$7*$H$10*V5 -> 934.15 | H7: =AVERAGE(H4:H6) -> 1099 | K7: Other | L7: 0.15 | M7: 0.18 | N7: 0.21 | O7: 0.24 | P7: 0.27 | Q7: 0.3 | R7: 0.33 | S7: 0.39 | T7: 0.46 | U7: 0.59 | V7: 1
A8: Avg/Show vs Target Pace: | B8: =IF(B4>0,AVERAGE(B4:B6)-B7,"TBD") -> -220.245 | C8: =IF(C4>0,AVERAGE(C4:C6)-C7,"TBD") -> -113.2695 | D8: =IF(D4>0,AVERAGE(D4:D6)-D7,"TBD") -> -113.98517 | E8: =IF(E4>0,AVERAGE(E4:E6)-E7,"TBD") -> -137.04233 | F8: =IF(F4>0,AVERAGE(F4:F6)-F7,"TBD") -> -179.48183 | G8: =IF(G4>0,AVERAGE(G4:G6)-G7,"TBD") -> -491.48333
H9: OCC Target
H10: 0.85
I12: Final Sales: | J12: Sep 15-21 Sales | K12: % of Total
I13: 511 | J13: =I13-G4 -> 121 | K13: =J13/I13 -> 0.23679061
I14: 550 | J14: =I14-G5 -> 128 | K14: =J14/I14 -> 0.23272727
I15: 662 | J15: =I15-G6 -> 146 | K15: =J15/I15 -> 0.22054381

Sheet CS1 Appalachian
B1: # weeks out
A2: Single Tickets | B2: 8 | C2: 7 | D2: 6 | E2: 5 | F2: 4 | G2: 3 | H2: 2 | I2: 1 | J2: 0 | O2: Estimates Only | S2: Historical Data
A3: CS1 Appalachian | B3: 45880 | C3: 45887 | D3: 45894 | E3: 45901 | F3: 45908 | G3: 45915 | H3: 45922 | I3: 45929 | J3: 45936 | K3: # Single Tickets to sell out 100% | L3: Projected Total OCC% | N3: # Weeks Until Performance | O3: 10 | P3: 9 | Q3: 8 | R3: 7 | S3: 6 | T3: 5 | U3: 4 | V3: 3 | W3: 2 | X3: 1 | Y3: 0
A4: 10/10/2025 Sales (Fri) | B4: 60 | C4: 100 | D4: 106 | E4: 135 | F4: 193 | G4: 212 | H4: 238 | I4: 326 | J4: 418 | K4: =1433-543 -> 890 | L4: ='Performances by Week'!O15 -> #N/A | N4: Classical | O4: 0.15 | P4: 0.18 | Q4: 0.21 | R4: 0.24 | S4: 0.27 | T4: 0.3 | U4: 0.33 | V4: 0.39 | W4: 0.46 | X4: 0.59 | Y4: 1
A5: 10/11/2025 Sales (Sat) | B5: 63 | C5: 98 | D5: 115 | E5: 130 | F5: 179 | G5: 225 | H5: 258 | I5: 355 | J5: 429 | K5: =1433-581 -> 852 | L5: ='Performances by Week'!O16 -> #N/A | N5: Pops | O5: 0.15 | P5: 0.18 | Q5: 0.21 | R5: 0.24 | S5: 0.27 | T5: 0.3 | U5: 0.33 | V5: 0.39 | W5: 0.46 | X5: 0.59 | Y5: 1
A6: 10/12/2025 Sales (Sun) | B6: 57 | C6: 137 | D6: 154 | E6: 174 | F6: 239 | G6: 295 | H6: 328 | I6: 430 | J6: 565 | K6: =1433-613 -> 820 | L6: ='Performances by Week'!O17 -> #N/A | N6: Specials | O6: 0.15 | P6: 0.18 | Q6: 0.21 | R6: 0.24 | S6: 0.27 | T6: 0.3 | U6: 0.33 | V6: 0.39 | W6: 0.46 | X6: 0.59 | Y6: 1
A7: Pace for 85% OCC | B7: =$K$7*$K$12*Q4 -> 151.725 | C7: =$K$7*$K$12*R4 -> 173.4 | D7: =$K$7*$K$12*S4 -> 195.075 | E7: =$K$7*$K$12*T4 -> 216.75 | F7: =$K$7*$K$12*U4 -> 238.425 | G7: =$K$7*$K$12*V4 -> 281.775 | H7: =$K$7*$K$12*W4 -> 332.35 | I7: =$K$7*$K$12*X4 -> 426.275 | J7: =$K$7*$K$12*Y4 -> 722.5 | K7: 850 | N7: Other | O7: 0.15 | P7: 0.18 | Q7: 0.21 | R7: 0.24 | S7: 0.27 | T7: 0.3 | U7: 0.33 | V7: 0.39 | W7: 0.46 | X7: 0.59 | Y7: 1
A8: Weekly new sales needed for Target Pace | C8: =C7-B7 -> 21.675 | D8: =D7-C7 -> 21.675 | E8: =E7-D7 -> 21.675 | F8: =F7-E7 -> 21.675 | G8: =G7-F7 -> 43.35 | H8: =H7-G7 -> 50.575 | I8: =I7-H7 -> 93.925 | J8: =J7-I7 -> 296.225
A9: Actual Weekly Sales | C9: =IF(C4="","Too early",AVERAGE(C4:C6)-AVERAGE(B4:B6)) -> 51.666667 | D9: =IF(D4="","Too early",AVERAGE(D4:D6)-AVERAGE(C4:C6)) -> 13.333333 | E9: =IF(E4="","Too early",AVERAGE(E4:E6)-AVERAGE(D4:D6)) -> 21.333333 | F9: =IF(F4="","Too early",AVERAGE(F4:F6)-AVERAGE(E4:E6)) -> 57.333333 | G9: =IF(G4="","Too early",AVERAGE(G4:G6)-AVERAGE(F4:F6)) -> 40.333333 | H9: =IF(H4="","Too early",AVERAGE(H4:H6)-AVERAGE(G4:G6)) -> 30.666667 | I9: =IF(I4="","Too early",AVERAGE(I4:I6)-AVERAGE(H4:H6)) -> 95.666667 | J9: =IF(J4="","Too early",AVERAGE(J4:J6)-AVERAGE(I4:I6)) -> 100.33333
A10: Avg/Show vs Target Pace: | B10: =IF(B4>0,AVERAGE(B4:B6)-B7,"TBD") -> -91.725 | C10: =IF(C4>0,AVERAGE(C4:C6)-C7,"TBD") -> -61.733333 | D10: =IF(D4>0,AVERAGE(D4:D6)-D7,"TBD") -> -70.075 | E10: =IF(E4>0,AVERAGE(E4:E6)-E7,"TBD") -> -70.416667 | F10: =IF(F4>0,AVERAGE(F4:F6)-F7,"TBD") -> -34.758333 | G10: =IF(G4>0,AVERAGE(G4:G6)-G7,"TBD") -> -37.775 | H10: =IF(H4>0,AVERAGE(H4:H6)-H7,"TBD") -> -57.683333 | I10: =IF(I4>0,AVERAGE(I4:I6)-I7,"TBD") -> -55.941667 | J10: =IF(J4>0,AVERAGE(J4:J6)-J7,"TBD") -> -251.83333
K11: OCC Target
K12: 0.85

Sheet PS2 90s Mixtape
B1: # Weeks Out | Q1: Estimates Only | U1: Historical Data
A2: Single Tickets | B2: 10 | C2: 9 | D2: 8 | E2: 7 | F2: 6 | G2: 5 | H2: 4 | I2: 3 | J2: 2 | K2: 1 | L2: 0 | P2: # Weeks Until Performance | Q2: 10 | R2: 9 | S2: 8 | T2: 7 | U2: 6 | V2: 5 | W2: 4 | X2: 3 | Y2: 2 | Z2: 1 | AA2: 0
A3: PS2 90s Mixtape (Name?) | B3: 45880 | C3: 45887 | D3: 45894 | E3: 45901 | F3: 45908 | G3: 45915 | H3: 45922 | I3: 45929 | J3: 45936 | K3: 45943 | L3: 45950 | M3: # Single Tickets to sell out 100% | N3: Projected OCC% | P3: Classical | Q3: 0.15 | R3: 0.18 | S3: 0.21 | T3: 0.24 | U3: 0.27 | V3: 0.3 | W3: 0.33 | X3: 0.39 | Y3: 0.46 | Z3: 0.59 | AA3: 1
A4: 10/24/2025 Sales (Fri) | B4: 60 | C4: 64 | D4: 68 | E4: 74 | F4: 80 | G4: 92 | H4: 115 | I4: 145 | J4: 166 | K4: 193 | L4: 222 | M4: ='Performances by Week'!AG22-'Performances by Week'!AC22 -> 965 | N4: ='Performances by Week'!O22 -> #N/A | P4: Pops | Q4: 0.15 | R4: 0.18 | S4: 0.21 | T4: 0.24 | U4: 0.27 | V4: 0.3 | W4: 0.33 | X4: 0.39 | Y4: 0.46 | Z4: 0.59 | AA4: 1
A5: 10/25/2025 Sales (Sat) | B5: 63 | C5: 63 | D5: 73 | E5: 93 | F5: 106 | G5: 114 | H5: 155 | I5: 190 | J5: 218 | K5: 257 | L5: 306 | M5: ='Performances by Week'!AG23-'Performances by Week'!AC23 -> 1067 | N5: ='Performances by Week'!O23 -> #N/A | P5: Specials | Q5: 0.15 | R5: 0.18 | S5: 0.21 | T5: 0.24 | U5: 0.27 | V5: 0.3 | W5: 0.33 | X5: 0.39 | Y5: 0.46 | Z5: 0.59 | AA5: 1
A6: 10/26/2025 Sales (Sun) | B6: 57 | C6: 59 | D6: 66 | E6: 74 | F6: 76 | G6: 87 | H6: 110 | I6: 163 | J6: 181 | K6: 209 | L6: 251 | M6: ='Performances by Week'!AG24-'Performances by Week'!AC24 -> 1268 | N6: ='Performances by Week'!O24 -> #N/A | P6: Other | Q6: 0.15 | R6: 0.18 | S6: 0.21 | T6: 0.24 | U6: 0.27 | V6: 0.3 | W6: 0.33 | X6: 0.39 | Y6: 0.46 | Z6: 0.59 | AA6: 1
A7: Pace for 85% OCC | B7: =$M$7*$M$12*Q4 -> 140.25 | C7: =$M$7*$M$12*R4 -> 168.3 | D7: =$M$7*$M$12*S4 -> 196.35 | E7: =$M$7*$M$12*T4 -> 224.4 | F7: =$M$7*$M$12*U4 -> 252.45 | G7: =$M$7*$M$12*V4 -> 280.5 | H7: =$M$7*$M$12*W4 -> 308.55 | I7: =$M$7*$M$12*X4 -> 364.65 | ... L7: =$M$7*$M$12*AA4 -> 935 | M7: =AVERAGE(M4:M6) -> 1100
A8: Weekly new sales needed for Target Pace | C8: =C7-B7 -> 28.05 | D8: =D7-C7 -> 28.05 | E8: =E7-D7 -> 28.05 | F8: =F7-E7 -> 28.05 | G8: =G7-F7 -> 28.05 | H8: =H7-G7 -> 28.05 | I8: =I7-H7 -> 56.1 | J8: =J7-I7 -> 65.45 | ... L8: =L7-K7 -> 383.35
A9: Actual Weekly Sales | C9: =IF(C4="","Too early",AVERAGE(C4:C6)-AVERAGE(B4:B6)) -> 2 | D9: =IF(D4="","Too early",AVERAGE(D4:D6)-AVERAGE(C4:C6)) -> 7 | E9: =IF(E4="","Too early",AVERAGE(E4:E6)-AVERAGE(D4:D6)) -> 11.333333 | F9: =IF(F4="","Too early",AVERAGE(F4:F6)-AVERAGE(E4:E6)) -> 7 | G9: =IF(G4="","Too early",AVERAGE(G4:G6)-AVERAGE(F4:F6)) -> 10.333333 | H9: =IF(H4="","Too early",AVERAGE(H4:H6)-AVERAGE(G4:G6)) -> 29 | I9: =IF(I4="","Too early",AVERAGE(I4:I6)-AVERAGE(H4:H6)) -> 39.333333 | J9: =IF(J4="","Too early",AVERAGE(J4:J6)-AVERAGE(I4:I6)) -> 22.333333 | ... L9: =IF(L4="","Too early",AVERAGE(L4:L6)-AVERAGE(K4:K6)) -> 40
A10: Avg/Show vs Target Pace: | B10: =IF(B4>0,AVERAGE(B4:B6)-B7,"TBD") -> -80.25 | C10: =IF(C4>0,AVERAGE(C4:C6)-C7,"TBD") -> -106.3 | D10: =IF(D4>0,AVERAGE(D4:D6)-D7,"TBD") -> -127.35 | E10: =IF(E4>0,AVERAGE(E4:E6)-E7,"TBD") -> -144.06667 | F10: =IF(F4>0,AVERAGE(F4:F6)-F7,"TBD") -> -165.11667 | G10: =IF(G4>0,AVERAGE(G4:G6)-G7,"TBD") -> -182.83333 | H10: =IF(H4>0,AVERAGE(H4:H6)-H7,"TBD") -> -181.88333 | I10: =IF(I4>0,AVERAGE(I4:I6)-I7,"TBD") -> -198.65 | ... L10: =IF(L4>0,AVERAGE(L4:L6)-L7,"TBD") -> -675.33333
M11: OCC Target
M12: 0.85

Sheet MFSB
A1: Single Tickets | B1: 3 | C1: 2 | D1: 1 | E1: 0 | L1: Single Tickets
A2: MFSB | B2: 45880 | C2: 45887 | D2: 45894 | E2: 45901 | F2: # Single Tickets to sell out 100% | K2: # Weeks Until Performance | L2: Classical | M2: Pops | N2: Specials | O2: Other
A3: 9/2/2025 Sales (Tue) | B3: 754 | C3: 915 | D3: 1013 | E3: 1096 | G3: =E3/F5 -> 0.84178187
A4: 9/3/2025 Sales (Wed) | B4: 651 | C4: 826 | D4: 926 | E4: 1027 | G4: =E4/F5 -> 0.78878648 | K4: 0 | L4: 1 | M4: 1 | N4: 1 | O4: 1
A5: Pace for 85% OCC | B5: =$F$5*$G$5*N7 -> 431.613 | C5: =$F$5*$G$5*N6 -> 509.082 | D5: =$F$5*$G$5*N5 -> 652.953 | E5: =$F$5*$G$5*N4 -> 1106.7 | F5: 1302 | G5: 0.85 | K5: 1 | L5: 0.59 | M5: 0.59 | N5: 0.59 | O5: 0.59
K6: 2 | L6: 0.46 | M6: 0.46 | N6: 0.46 | O6: 0.46
K7: 3 | L7: 0.39 | M7: 0.39 | N7: 0.39 | O7: 0.39
K8: 4 | L8: 0.33 | M8: 0.33 | N8: 0.33 | O8: 0.33
K9: 5 | L9: 0.3 | M9: 0.3 | N9: 0.3 | O9: 0.3
K10: 6 | L10: 0.27 | M10: 0.27 | N10: 0.27 | O10: 0.27

Sheet CS2 Rachmaninoff
D1: # weeks out
A2: Single Tickets | B2: 10 | C2: 9 | D2: 8 | E2: 7 | F2: 6 | G2: 5 | H2: 4 | I2: 3 | J2: 2 | K2: 1 | L2: 0 | Q2: Estimates Only | U2: Historical Data
A3: CS2 Rachmaninoff | B3: 45887 | C3: 45894 | D3: 45901 | E3: 45908 | F3: 45915 | G3: 45922 | H3: 45929 | I3: 45936 | J3: 45943 | K3: 45950 | L3: 45957 | M3: # Single Tickets to sell out 100% | N3: Projected OCC% | P3: # Weeks Until Performance | Q3: 10 | R3: 9 | S3: 8 | T3: 7 | U3: 6 | V3: 5 | W3: 4 | X3: 3 | Y3: 2 | Z3: 1 | AA3: 0
A4: 10/31/2025 Sales (Fri, Piazza) | B4: 87 | C4: 93 | D4: 102 | E4: 106 | F4: 111 | G4: 124 | H4: 144 | I4: 183 | J4: 234 | K4: 291 | M4: ='Performances by Week'!AG26-'Performances by Week'!AC26 -> 1142 | N4: ='Performances by Week'!O26 -> 0.44 | P4: Classical | Q4: 0.15 | R4: 0.18 | S4: 0.21 | T4: 0.24 | U4: 0.27 | V4: 0.3 | W4: 0.33 | X4: 0.39 | Y4: 0.46 | Z4: 0.59 | AA4: 1
A5: 11/01/2025 Sales (Sat) | B5: 192 | C5: 209 | D5: 256 | E5: 310 | F5: 340 | G5: 382 | H5: 446 | I5: 527 | J5: 648 | K5: 715 | M5: ='Performances by Week'!AG27-'Performances by Week'!AC27 -> 943 | N5: ='Performances by Week'!O27 -> 0.90965517 | P5: Pops | Q5: 0.15 | R5: 0.18 | S5: 0.21 | T5: 0.24 | U5: 0.27 | V5: 0.3 | W5: 0.33 | X5: 0.39 | Y5: 0.46 | Z5: 0.59 | AA5: 1
A6: 11/02/2025 Sales (Sun) | B6: 138 | C6: 165 | D6: 187 | E6: 219 | F6: 232 | G6: 267 | H6: 309 | I6: 358 | J6: 432 | K6: 516 | M6: ='Performances by Week'!AG28-'Performances by Week'!AC28 -> 914 | N6: ='Performances by Week'!O28 -> 0.77862069 | P6: Specials | Q6: 0.15 | R6: 0.18 | S6: 0.21 | T6: 0.24 | U6: 0.27 | V6: 0.3 | W6: 0.33 | X6: 0.39 | Y6: 0.46 | Z6: 0.59 | AA6: 1
A7: Pace for 85% OCC | B7: =$M$7*$M$12*Q4 -> 127.4575 | C7: =$M$7*$M$12*R4 -> 152.949 | D7: =$M$7*$M$12*S4 -> 178.4405 | E7: =$M$7*$M$12*T4 -> 203.932 | F7: =$M$7*$M$12*U4 -> 229.4235 | G7: =$M$7*$M$12*V4 -> 254.915 | H7: =$M$7*$M$12*W4 -> 280.4065 | I7: =$M$7*$M$12*X4 -> 331.3895 | ... L7: =$M$7*$M$12*AA4 -> 849.71667 | M7: =AVERAGE(M4:M6) -> 999.66667 | P7: Other | Q7: 0.15 | R7: 0.18 | S7: 0.21 | T7: 0.24 | U7: 0.27 | V7: 0.3 | W7: 0.33 | X7: 0.39 | Y7: 0.46 | Z7: 0.59 | AA7: 1
A8: Weekly new sales needed for Target Pace | C8: =C7-B7 -> 25.4915 | D8: =D7-C7 -> 25.4915 | E8: =E7-D7 -> 25.4915 | F8: =F7-E7 -> 25.4915 | G8: =G7-F7 -> 25.4915 | H8: =H7-G7 -> 25.4915 | I8: =I7-H7 -> 50.983 | J8: =J7-I7 -> 59.480167 | ... L8: =L7-K7 -> 348.38383
A9: Actual Weekly Sales | C9: =IF(C4="","Too early",AVERAGE(C4:C7)-AVERAGE(B4:B7)) -> 18.872875 | D9: =IF(D4="","Too early",AVERAGE(D4:D7)-AVERAGE(C4:C7)) -> 25.872875 | E9: =IF(E4="","Too early",AVERAGE(E4:E7)-AVERAGE(D4:D7)) -> 28.872875 | F9: =IF(F4="","Too early",AVERAGE(F4:F7)-AVERAGE(E4:E7)) -> 18.372875 | G9: =IF(G4="","Too early",AVERAGE(G4:G7)-AVERAGE(F4:F7)) -> 28.872875 | H9: =IF(H4="","Too early",AVERAGE(H4:H7)-AVERAGE(G4:G7)) -> 37.872875 | I9: =IF(I4="","Too early",AVERAGE(I4:I7)-AVERAGE(H4:H7)) -> 54.99575 | J9: =IF(J4="","Too early",AVERAGE(J4:J7)-AVERAGE(I4:I7)) -> 76.370042 | ... L9: =IF(L4="","Too early",AVERAGE(L4:L7)-AVERAGE(K4:K7)) -> Too early
A10: Avg/Show vs Target Pace: | B10: =IF(B4>0,AVERAGE(B4:B6)-B7,"TBD") -> 11.5425 | C10: =IF(C4>0,AVERAGE(C4:C6)-C7,"TBD") -> 2.7176667 | D10: =IF(D4>0,AVERAGE(D4:D6)-D7,"TBD") -> 3.2261667 | E10: =IF(E4>0,AVERAGE(E4:E6)-E7,"TBD") -> 7.7346667 | F10: =IF(F4>0,AVERAGE(F4:F6)-F7,"TBD") -> -1.7568333 | G10: =IF(G4>0,AVERAGE(G4:G6)-G7,"TBD") -> 2.7516667 | H10: =IF(H4>0,AVERAGE(H4:H6)-H7,"TBD") -> 19.260167 | I10: =IF(I4>0,AVERAGE(I4:I6)-I7,"TBD") -> 24.6105 | ... L10: =IF(L4>0,AVERAGE(L4:L6)-L7,"TBD") -> TBD
M11: OCC Target
M12: 0.85

Sheet CS3 Mahler 7
D1: # weeks out
A2: Single Tickets | B2: 10 | C2: 9 | D2: 8 | E2: 7 | F2: 6 | G2: 5 | H2: 4 | I2: 3 | J2: 2 | K2: 1 | L2: 0 | Q2: Estimates Only | U2: Historical Data
A3: CS3 Mahler | B3: 45908 | C3: 45915 | D3: 45922 | E3: 45929 | F3: 45936 | G3: 45943 | H3: 45950 | I3: 45957 | J3: 45964 | K3: 45971 | L3: 45978 | M3: # Single Tickets to sell out 100% | N3: Projected OCC% | P3: # Weeks Until Performance | Q3: 10 | R3: 9 | S3: 8 | T3: 7 | U3: 6 | V3: 5 | W3: 4 | X3: 3 | Y3: 2 | Z3: 1 | AA3: 0
A4: 11/21/2025 Sales (Fri, Piazza) | B4: 55 | C4: 60 | D4: 66 | E4: 75 | F4: 83 | G4: 113 | H4: 138 | I4: 180 | M4: ='[1]Performances by Week'!AC31-'[1]Performances by Week'!Y31 -> 1210 | N4: ='[1]Performances by Week'!K31 -> 0.39622642 | P4: Classical | Q4: 0.15 | R4: 0.18 | S4: 0.21 | T4: 0.24 | U4: 0.27 | V4: 0.3 | W4: 0.33 | X4: 0.39 | Y4: 0.46 | Z4: 0.59 | AA4: 1
A5: 11/22/2025 Sales (Sat) | B5: 95 | C5: 110 | D5: 114 | E5: 143 | F5: 160 | G5: 189 | H5: 209 | I5: 235 | M5: ='[1]Performances by Week'!AC32-'[1]Performances by Week'!Y32 -> 999 | N5: ='[1]Performances by Week'!K32 -> 0.67987421 | P5: Pops | Q5: 0.15 | R5: 0.18 | S5: 0.21 | T5: 0.24 | U5: 0.27 | V5: 0.3 | W5: 0.33 | X5: 0.39 | Y5: 0.46 | Z5: 0.59 | AA5: 1
A6: 11/23/2025 Sales (Sun) | B6: 75 | C6: 81 | D6: 83 | E6: 93 | F6: 99 | G6: 141 | H6: 167 | I6: 188 | M6: ='[1]Performances by Week'!AC33-'[1]Performances by Week'!Y33 -> 955 | N6: ='[1]Performances by Week'!K33 -> 0.59433962 | P6: Specials | Q6: 0.15 | R6: 0.18 | S6: 0.21 | T6: 0.24 | U6: 0.27 | V6: 0.3 | W6: 0.33 | X6: 0.39 | Y6: 0.46 | Z6: 0.59 | AA6: 1
A7: Pace for 85% OCC | B7: =$M$7*$M$12*Q4 -> 134.47 | C7: =$M$7*$M$12*R4 -> 161.364 | D7: =$M$7*$M$12*S4 -> 188.258 | E7: =$M$7*$M$12*T4 -> 215.152 | F7: =$M$7*$M$12*U4 -> 242.046 | G7: =$M$7*$M$12*V4 -> 268.94 | H7: =$M$7*$M$12*W4 -> 295.834 | I7: =$M$7*$M$12*X4 -> 349.622 | ... L7: =$M$7*$M$12*AA4 -> 896.46667 | M7: =AVERAGE(M4:M6) -> 1054.6667 | P7: Other | Q7: 0.15 | R7: 0.18 | S7: 0.21 | T7: 0.24 | U7: 0.27 | V7: 0.3 | W7: 0.33 | X7: 0.39 | Y7: 0.46 | Z7: 0.59 | AA7: 1
A8: Weekly new sales needed for Target Pace | C8: =C7-B7 -> 26.894 | D8: =D7-C7 -> 26.894 | E8: =E7-D7 -> 26.894 | F8: =F7-E7 -> 26.894 | G8: =G7-F7 -> 26.894 | H8: =H7-G7 -> 26.894 | I8: =I7-H7 -> 53.788 | J8: =J7-I7 -> 62.752667 | ... L8: =L7-K7 -> 367.55133
A9: Actual Weekly Sales | C9: =IF(C4="","Too early",AVERAGE(C4:C7)-AVERAGE(B4:B7)) -> 13.2235 | D9: =IF(D4="","Too early",AVERAGE(D4:D7)-AVERAGE(C4:C7)) -> 9.7235 | E9: =IF(E4="","Too early",AVERAGE(E4:E7)-AVERAGE(D4:D7)) -> 18.7235 | F9: =IF(F4="","Too early",AVERAGE(F4:F7)-AVERAGE(E4:E7)) -> 14.4735 | G9: =IF(G4="","Too early",AVERAGE(G4:G7)-AVERAGE(F4:F7)) -> 31.9735 | H9: =IF(H4="","Too early",AVERAGE(H4:H7)-AVERAGE(G4:G7)) -> 24.4735 | I9: =IF(I4="","Too early",AVERAGE(I4:I7)-AVERAGE(H4:H7)) -> 35.697 | J9: =IF(J4="","Too early",AVERAGE(J4:J7)-AVERAGE(I4:I7)) -> Too early | ... L9: =IF(L4="","Too early",AVERAGE(L4:L7)-AVERAGE(K4:K7)) -> Too early
A10: Avg/Show vs Target Pace: | B10: =IF(B4>0,AVERAGE(B4:B6)-B7,"TBD") -> -59.47 | C10: =IF(C4>0,AVERAGE(C4:C6)-C7,"TBD") -> -77.697333 | D10: =IF(D4>0,AVERAGE(D4:D6)-D7,"TBD") -> -100.59133 | E10: =IF(E4>0,AVERAGE(E4:E6)-E7,"TBD") -> -111.48533 | F10: =IF(F4>0,AVERAGE(F4:F6)-F7,"TBD") -> -128.046 | G10: =IF(G4>0,AVERAGE(G4:G6)-G7,"TBD") -> -121.27333 | H10: =IF(H4>0,AVERAGE(H4:H6)-H7,"TBD") -> -124.50067 | I10: =IF(I4>0,AVERAGE(I4:I6)-I7,"TBD") -> -148.622 | ... L10: =IF(L4>0,AVERAGE(L4:L6)-L7,"TBD") -> TBD
M11: OCC Target
M12: 0.85

Sheet Elf
D1: # weeks out
A2: Single Tickets | B2: 10 | C2: 9 | D2: 8 | E2: 7 | F2: 6 | G2: 5 | H2: 4 | I2: 3 | J2: 2 | K2: 1 | L2: 0 | Q2: Estimates Only | U2: Historical Data
A3: Elf in Concert | B3: 45915 | C3: 45922 | D3: 45929 | E3: 45936 | F3: 45943 | G3: 45950 | H3: 45957 | I3: 45964 | J3: 45971 | K3: 45978 | L3: 45985 | M3: # Single Tickets to sell out 100% | N3: Projected OCC% | P3: # Weeks Until Performance | Q3: 10 | R3: 9 | S3: 8 | T3: 7 | U3: 6 | V3: 5 | W3: 4 | X3: 3 | Y3: 2 | Z3: 1 | AA3: 0
A4: 11/28/2025 (Fri) | B4: 306 | C4: 323 | D4: 339 | E4: 420 | F4: 464 | G4: 622 | H4: 750 | M4: ='Performances by Week'!AG34-'Performances by Week'!AC34 -> 1302 | N4: ='Performances by Week'!O34 -> 1 | P4: Classical | Q4: 0.15 | R4: 0.18 | S4: 0.21 | T4: 0.24 | U4: 0.27 | V4: 0.3 | W4: 0.33 | X4: 0.39 | Y4: 0.46 | Z4: 0.59 | AA4: 1
A5: 11/29/2025 (Sat 1) | B5: 370 | C5: 374 | D5: 414 | E5: 462 | F5: 532 | G5: 598 | H5: 741 | M5: ='Performances by Week'!AG35-'Performances by Week'!AC35 -> 1302 | N5: ='Performances by Week'!O35 -> 1 | P5: Pops | Q5: 0.15 | R5: 0.18 | S5: 0.21 | T5: 0.24 | U5: 0.27 | V5: 0.3 | W5: 0.33 | X5: 0.39 | Y5: 0.46 | Z5: 0.59 | AA5: 1
A6: 11/29/2025 (Sat 2) | B6: 283 | C6: 303 | D6: 329 | E6: 381 | F6: 416 | G6: 483 | H6: 647 | M6: ='Performances by Week'!AG36-'Performances by Week'!AC36 -> 1302 | N6: ='Performances by Week'!O36 -> 1 | P6: Specials | Q6: 0.15 | R6: 0.18 | S6: 0.21 | T6: 0.24 | U6: 0.27 | V6: 0.3 | W6: 0.33 | X6: 0.39 | Y6: 0.46 | Z6: 0.59 | AA6: 1
A7: 11/30/2025 (Sun) | B7: 483 | C7: 514 | D7: 542 | E7: 594 | F7: 651 | G7: 745 | H7: 867 | M7: ='Performances by Week'!AG37-'Performances by Week'!AC37 -> 1302 | N7: ='Performances by Week'!O37 -> 1 | P7: Other | Q7: 0.15 | R7: 0.18 | S7: 0.21 | T7: 0.24 | U7: 0.27 | V7: 0.3 | W7: 0.33 | X7: 0.39 | Y7: 0.46 | Z7: 0.59 | AA7: 1
A8: Pace for 85% OCC | B8: =$M$8*$M$15*Q6 -> 166.005 | C8: =$M$8*$M$15*R6 -> 199.206 | D8: =$M$8*$M$15*S6 -> 232.407 | E8: =$M$8*$M$15*T6 -> 265.608 | F8: =$M$8*$M$15*U6 -> 298.809 | G8: =$M$8*$M$15*V6 -> 332.01 | H8: =$M$8*$M$15*W6 -> 365.211 | I8: =$M$8*$M$15*X6 -> 431.613 | ... L8: =$M$8*$M$15*AA6 -> 1106.7 | M8: =AVERAGE(M4:M7) -> 1302
A9: Home Alone 2024 | B9: =AVERAGE(B34:B37) -> 480.5 | C9: =AVERAGE(C34:C37) -> 532.5 | D9: =AVERAGE(D34:D37) -> 570.5 | E9: =AVERAGE(E34:E37) -> 607.5 | F9: =AVERAGE(F34:F37) -> 645.75 | G9: =AVERAGE(G34:G37) -> 720 | H9: =AVERAGE(H34:H37) -> 836.5 | I9: =AVERAGE(I34:I37) -> 956.75 | ... L9: =AVERAGE(L34:L37) -> 1293.25 | M9: Target Pace
A10: Muppet XMas 2023 | B10: =AVERAGE(B45:B46) -> 943.5 | C10: =AVERAGE(C45:C46) -> 992.5 | D10: =AVERAGE(D45:D46) -> 1056 | E10: =AVERAGE(E45:E46) -> 1088 | F10: =AVERAGE(F45:F46) -> 1158 | G10: =AVERAGE(G45:G46) -> 1220 | H10: =AVERAGE(H45:H46) -> 1242.5 | I10: =AVERAGE(I45:I46) -> 1259.5 | ... L10: =AVERAGE(L45:L46) -> 1288.5
A11: Weekly new sales needed for Target Pace | C11: =C9-B9 -> 52 | D11: =D9-C9 -> 38 | E11: =E9-D9 -> 37 | F11: =F9-E9 -> 38.25 | G11: =G9-F9 -> 74.25 | H11: =H9-G9 -> 116.5 | I11: =I9-H9 -> 120.25 | J11: =J9-I9 -> 143 | ... L11: =L9-K9 -> 66
A12: Actual Weekly Sales | C12: =IF(C4="","Too early",AVERAGE(C4:C7)-AVERAGE(B4:B7)) -> 18 | D12: =IF(D4="","Too early",AVERAGE(D4:D7)-AVERAGE(C4:C7)) -> 27.5 | E12: =IF(E4="","Too early",AVERAGE(E4:E7)-AVERAGE(D4:D7)) -> 58.25 | F12: =IF(F4="","Too early",AVERAGE(F4:F7)-AVERAGE(E4:E7)) -> 51.5 | G12: =IF(G4="","Too early",AVERAGE(G4:G7)-AVERAGE(F4:F7)) -> 96.25 | H12: =IF(H4="","Too early",AVERAGE(H4:H7)-AVERAGE(G4:G7)) -> 139.25 | I12: =IF(I4="","Too early",AVERAGE(I4:I7)-AVERAGE(H4:H7)) -> Too early | J12: =IF(J4="","Too early",AVERAGE(J4:J7)-AVERAGE(I4:I7)) -> Too early | ... L12: =IF(L4="","Too early",AVERAGE(L4:L7)-AVERAGE(K4:K7)) -> Too early
A13: Avg/Show vs Target Pace: | B13: =IF(B5>0,AVERAGE(B4:B7)-B9,"TBD") -> -120 | C13: =IF(C5>0,AVERAGE(C4:C7)-C9,"TBD") -> -154 | D13: =IF(D5>0,AVERAGE(D4:D7)-D9,"TBD") -> -164.5 | E13: =IF(E5>0,AVERAGE(E4:E7)-E9,"TBD") -> -143.25 | F13: =IF(F5>0,AVERAGE(F4:F7)-F9,"TBD") -> -130 | G13: =IF(G5>0,AVERAGE(G4:G7)-G9,"TBD") -> -108 | H13: =IF(H5>0,AVERAGE(H4:H7)-H9,"TBD") -> -85.25 | I13: =IF(I5>0,AVERAGE(I4:I7)-I9,"TBD") -> TBD | ... L13: =IF(L5>0,AVERAGE(L4:L7)-L9,"TBD") -> TBD
M14: OCC Target
M15: 0.85
A32: Single Tickets | B32: 10 | C32: 9 | D32: 8 | E32: 7 | F32: 6 | G32: 5 | H32: 4 | I32: 3 | J32: 2 | K32: 1 | L32: 0
A33: Home Alone | B33: 45551 | C33: 45558 | D33: 45565 | E33: 45572 | F33: 45579 | G33: 45586 | H33: 45593 | I33: 45600 | J33: 45607 | K33: 45614 | L33: 45621 | M33: # Single Tickets to sell out 100% | N33: Final Occupancy Sold %
A34: 11/29/2024 Sales (Friday) | B34: 395 | C34: 422 | D34: 451 | E34: 488 | F34: 518 | G34: 591 | H34: 667 | I34: 754 | J34: 913 | K34: 1165 | L34: 1276 | M34: 1342 | N34: 0.9664
A35: 11/30/2024, 2pm (Saturday) | B35: 604 | C35: 669 | D35: 701 | E35: 735 | F35: 763 | G35: 832 | H35: 955 | I35: 1040 | J35: 1229 | K35: 1269 | L35: 1301 | M35: 1342 | N35: 0.9873
A36: 11/30/2024, 8pm (Saturday) | B36: 302 | C36: 353 | D36: 391 | E36: 422 | F36: 454 | G36: 500 | H36: 657 | I36: 813 | J36: 988 | K36: 1200 | L36: 1301 | M36: 1342 | N36: 0.9836
A37: 12/01/2024 Sales (Sunday) | B37: 621 | C37: 686 | D37: 739 | E37: 785 | F37: 848 | G37: 957 | H37: 1067 | I37: 1220 | J37: 1269 | K37: 1275 | L37: 1295 | M37: 1342 | N37: 0.9813
A38: Pace for 85% OCC | B38: =AVERAGE(B34:B37) -> 480.5 | C38: =AVERAGE(C34:C37) -> 532.5 | D38: =AVERAGE(D34:D37) -> 570.5 | E38: =AVERAGE(E34:E37) -> 607.5 | F38: =AVERAGE(F34:F37) -> 645.75 | G38: =AVERAGE(G34:G37) -> 720 | H38: =AVERAGE(H34:H37) -> 836.5 | I38: =AVERAGE(I34:I37) -> 956.75 | ... L38: =AVERAGE(L34:L37) -> 1293.25
A39: Avg/Show vs Target Pace: | B39: =B38/$L$38 -> 0.37154456 | C39: =C38/$L$38 -> 0.41175333 | D39: =D38/$L$38 -> 0.44113667 | E39: =E38/$L$38 -> 0.46974676 | F39: =F38/$L$38 -> 0.49932341 | G39: =G38/$L$38 -> 0.5567369 | H39: =H38/$L$38 -> 0.64682003 | I39: =I38/$L$38 -> 0.73980282 | ... K39: =K38/$L$38 -> 0.94896578 | L39: =L38/$L38 -> 1
M40: OCC Target
M41: 0.85
A43: Single Tickets | B43: 10 | C43: 9 | D43: 8 | E43: 7 | F43: 6 | G43: 5 | H43: 4 | I43: 3 | J43: 2 | K43: 1 | L43: 0
A44: A Muppet Christmas Carol | B44: 45194 | C44: 45201 | D44: 45208 | E44: 45215 | F44: 45222 | G44: 45229 | H44: 45236 | I44: 45243 | J44: 45250 | K44: 45988 | L44: 45995 | M44: # Single Tickets to sell out 100% | N44: Final Occupancy Sold %
A45: 12/08/2023 Sales (Friday) | B45: 844 | C45: 894 | D45: 980 | E45: 1010 | F45: 1104 | G45: 1218 | H45: 1244 | I45: 1264 | J45: 1268 | K45: 1279 | L45: 1289 | M45: 1334 | N45: 0.9962
A46: 12/09/2023, 1pm Sales (Saturday) | B46: 1043 | C46: 1091 | D46: 1132 | E46: 1166 | F46: 1212 | G46: 1222 | H46: 1241 | I46: 1255 | J46: 1265 | K46: 1270 | L46: 1288 | M46: 1334 | N46: 0.979
A47: Pace for 85% OCC
A48: Avg/Show vs Target Pace:
M49: OCC Target
M50: 0.85

Sheet Messiah
D1: # weeks out
A2: Single Tickets | B2: 10 | C2: 9 | D2: 8 | E2: 7 | F2: 6 | G2: 5 | H2: 4 | I2: 3 | J2: 2 | K2: 1 | L2: 0 | Q2: Estimates Only | U2: Historical Data
A3: Handel's Messiah | B3: 45922 | C3: 45929 | D3: 45936 | E3: 45943 | F3: 45950 | G3: 45957 | H3: 45964 | I3: 45971 | J3: 45978 | K3: 45985 | L3: 45992 | M3: # Single Tickets to sell out 100% | N3: Projected OCC% | P3: # Weeks Until Performance | Q3: 10 | R3: 9 | S3: 8 | T3: 7 | U3: 6 | V3: 5 | W3: 4 | X3: 3 | Y3: 2 | Z3: 1 | AA3: 0
A4: 12/5/2025 (Fri) | B4: 369 | C4: 395 | D4: 435 | E4: 491 | F4: 557 | G4: 630 | M4: ='Performances by Week'!AG38-'Performances by Week'!AC38 -> 1444 | N4: ='Performances by Week'!O38 -> 1 | P4: Classical | Q4: 0.15 | R4: 0.18 | S4: 0.21 | T4: 0.24 | U4: 0.27 | V4: 0.3 | W4: 0.33 | X4: 0.39 | Y4: 0.46 | Z4: 0.59 | AA4: 1
A5: 12/6/2025 (Sat) | B5: 369 | C5: 386 | D5: 421 | E5: 483 | F5: 526 | G5: 665 | M5: ='Performances by Week'!AG39-'Performances by Week'!AC39 -> 1444 | N5: ='Performances by Week'!O39 -> 1 | P5: Pops | Q5: 0.15 | R5: 0.18 | S5: 0.21 | T5: 0.24 | U5: 0.27 | V5: 0.3 | W5: 0.33 | X5: 0.39 | Y5: 0.46 | Z5: 0.59 | AA5: 1
A6: 12/7/2025 (Sun) | B6: 410 | C6: 443 | D6: 474 | E6: 573 | F6: 624 | G6: 709 | M6: ='Performances by Week'!AG40-'Performances by Week'!AC40 -> 1444 | N6: ='Performances by Week'!O40 -> 1 | P6: Specials | Q6: 0.15 | R6: 0.18 | S6: 0.21 | T6: 0.24 | U6: 0.27 | V6: 0.3 | W6: 0.33 | X6: 0.39 | Y6: 0.46 | Z6: 0.59 | AA6: 1
A7: Pace for 85% OCC | B7: =$M$7*$M$14*Q6 -> 184.11 | C7: =$M$7*$M$14*R6 -> 220.932 | D7: =$M$7*$M$14*S6 -> 257.754 | E7: =$M$7*$M$14*T6 -> 294.576 | F7: =$M$7*$M$14*U6 -> 331.398 | G7: =$M$7*$M$14*V6 -> 368.22 | H7: =$M$7*$M$14*W6 -> 405.042 | I7: =$M$7*$M$14*X6 -> 478.686 | ... L7: =$M$7*$M$14*AA6 -> 1227.4 | M7: =AVERAGE(M4:M6) -> 1444 | P7: Other | Q7: 0.15 | R7: 0.18 | S7: 0.21 | T7: 0.24 | U7: 0.27 | V7: 0.3 | W7: 0.33 | X7: 0.39 | Y7: 0.46 | Z7: 0.59 | AA7: 1
A8: Messiah 2024 | B8: =AVERAGE(B33:B35) -> 300.33333 | C8: =AVERAGE(C33:C35) -> 322.33333 | D8: =AVERAGE(D33:D35) -> 360 | E8: =AVERAGE(E33:E35) -> 395.66667 | F8: =AVERAGE(F33:F35) -> 431 | G8: =AVERAGE(G33:G35) -> 486.33333 | H8: =AVERAGE(H33:H35) -> 568.33333 | I8: =AVERAGE(I33:I35) -> 667 | ... L8: =AVERAGE(L33:L35) -> 1146 | M8: Target Pace
A9: Messiah 2023 | B9: =AVERAGE(B43:B45) -> 338 | C9: =AVERAGE(C43:C45) -> 372 | D9: =AVERAGE(D43:D45) -> 411 | E9: =AVERAGE(E43:E45) -> 447.33333 | F9: =AVERAGE(F43:F45) -> 494.66667 | G9: =AVERAGE(G43:G45) -> 557 | H9: =AVERAGE(H43:H45) -> 657.66667 | I9: =AVERAGE(I43:I45) -> 738.33333 | ... L9: =AVERAGE(L43:L45) -> 1180.3333
A10: Weekly new sales needed for Target Pace | C10: =C8-B8 -> 22 | D10: =D8-C8 -> 37.666667 | E10: =E8-D8 -> 35.666667 | F10: =F8-E8 -> 35.333333 | G10: =G8-F8 -> 55.333333 | H10: =H8-G8 -> 82 | I10: =I8-H8 -> 98.666667 | J10: =J8-I8 -> 123.33333 | ... L10: =L8-K8 -> 191.66667
A11: Actual Weekly Sales | C11: =AVERAGE(C4:C6)-AVERAGE(B4:B6) -> 25.333333 | D11: =IF(D4="","Too early",AVERAGE(D4:D6)-AVERAGE(C4:C6)) -> 35.333333 | E11: =IF(E4="","Too early",AVERAGE(E4:E6)-AVERAGE(D4:D6)) -> 72.333333 | F11: =IF(F4="","Too early",AVERAGE(F4:F6)-AVERAGE(E4:E6)) -> 53.333333 | G11: =IF(G4="","Too early",AVERAGE(G4:G6)-AVERAGE(F4:F6)) -> 99 | H11: =IF(H4="","Too early",AVERAGE(H4:H6)-AVERAGE(G4:G6)) -> Too early | I11: =IF(I4="","Too early",AVERAGE(I4:I6)-AVERAGE(H4:H6)) -> Too early | J11: =IF(J4="","Too early",AVERAGE(J4:J6)-AVERAGE(I4:I6)) -> Too early | K11: =IF(K4="","Too early",AVERAGE(K4:K6)-AVERAGE(J4:J6)) -> Too early | L11: =IF(L4="","Too early",AVERAGE(L4:L6)-AVERAGE(K4:K6)) -> Too early
A12: Avg/Show vs Target Pace: | B12: =IF(B4>0,AVERAGE(B4:B6)-B8,"TBD") -> 82.333333 | C12: =IF(C4>0,AVERAGE(C4:C6)-C8,"TBD") -> 85.666667 | D12: =IF(D4>0,AVERAGE(D4:D6)-D8,"TBD") -> 83.333333 | E12: =IF(E4>0,AVERAGE(E4:E6)-E8,"TBD") -> 120 | F12: =IF(F4>0,AVERAGE(F4:F6)-F8,"TBD") -> 138 | G12: =IF(G4>0,AVERAGE(G4:G6)-G8,"TBD") -> 181.66667 | H12: =IF(H4>0,AVERAGE(H4:H6)-H8,"TBD") -> TBD | I12: =IF(I4>0,AVERAGE(I4:I6)-I8,"TBD") -> TBD | ... L12: =IF(L4>0,AVERAGE(L4:L6)-L8,"TBD") -> TBD
M13: OCC Target
M14: 0.85
A31: Single Tickets | B31: 10 | C31: 9 | D31: 8 | E31: 7 | F31: 6 | G31: 5 | H31: 4 | I31: 3 | J31: 2 | K31: 1 | L31: 0
A32: Handel's Messiah | B32: 45558 | C32: 45565 | D32: 45572 | E32: 45579 | F32: 45586 | G32: 45593 | H32: 45600 | I32: 45607 | J32: 45614 | K32: 45621 | L32: 45628 | M32: # Single Tickets to sell out 100% | N32: Final Occupancy Sold %
A33: 12/06/2024 Sales (Friday) | B33: 269 | C33: 295 | D33: 314 | E33: 335 | F33: 385 | G33: 425 | H33: 522 | I33: 615 | J33: 771 | K33: 912 | L33: 1078 | M33: 1450 | N33: 0.8834
A34: 12/07/2024 Sales (Saturday) | B34: 318 | C34: 333 | D34: 368 | E34: 392 | F34: 424 | G34: 483 | H34: 549 | I34: 660 | J34: 751 | K34: 918 | L34: 1127 | M34: 1450 | N34: 0.9662
A35: 12/08/2024 Sales (Sunday) | B35: 314 | C35: 339 | D35: 398 | E35: 460 | F35: 484 | G35: 551 | H35: 634 | I35: 726 | J35: 849 | K35: 1033 | L35: 1233 | M35: 1450 | N35: 0.9751
A36: Pace for 85% OCC
A37: Avg/Show vs Target Pace:
M38: OCC Target
M39: 0.85
A41: Single Tickets | B41: 10 | C41: 9 | D41: 8 | E41: 7 | F41: 6 | G41: 5 | H41: 4 | I41: 3 | J41: 2 | K41: 1 | L41: 0
A42: Handel's Messiah | B42: 45187 | C42: 45194 | D42: 45201 | E42: 45208 | F42: 45215 | G42: 45222 | H42: 45229 | I42: 45236 | J42: 45243 | K42: 45250 | L42: 45988 | M42: # Single Tickets to sell out 100% | N42: Final Occupancy Sold %
A43: 12/01/2023 Sales (Friday) | B43: 292 | C43: 312 | D43: 345 | E43: 367 | F43: 421 | G43: 468 | H43: 562 | I43: 635 | J43: 855 | K43: 992 | L43: 1129 | M43: 1450 | N43: 0.9434
A44: 12/02/2023 Sales (Saturday) | B44: 345 | C44: 396 | D44: 439 | E44: 495 | F44: 538 | G44: 590 | H44: 693 | I44: 784 | J44: 929 | K44: 1043 | L44: 1153 | M44: 1450 | N44: 0.991
A45: 12/03/2023 Sales (Sunday) | B45: 377 | C45: 408 | D45: 449 | E45: 480 | F45: 525 | G45: 613 | H45: 718 | I45: 796 | J45: 945 | K45: 1105 | L45: 1259 | M45: 1450 | N45: 1
A46: Avg/Show vs Target Pace:
M47: OCC Target
M48: 0.85

Sheet XMas Festival
D1: # weeks out
A2: Single Tickets | B2: 10 | C2: 9 | D2: 8 | E2: 7 | F2: 6 | G2: 5 | H2: 4 | I2: 3 | J2: 2 | K2: 1 | L2: 0 | Q2: Estimates Only | U2: Historical Data
A3: Christmas Festival | B3: 45936 | C3: 45943 | D3: 45950 | E3: 45957 | F3: 45964 | G3: 45971 | H3: 45978 | I3: 45985 | J3: 45992 | K3: 45999 | L3: 46006 | M3: # Single Tickets to sell out 100% | N3: Projected OCC% | P3: # Weeks Until Performance | Q3: 10 | R3: 9 | S3: 8 | T3: 7 | U3: 6 | V3: 5 | W3: 4 | X3: 3 | Y3: 2 | Z3: 1 | AA3: 0
A4: 12/18/2025 (Thu) | B4: 244 | C4: 266 | D4: 295 | E4: 342 | M4: ='Performances by Week'!AG43-'Performances by Week'!AC43 -> 1433 | N4: ='Performances by Week'!O43 -> 0.99441731 | P4: Classical | Q4: 0.15 | R4: 0.18 | S4: 0.21 | T4: 0.24 | U4: 0.27 | V4: 0.3 | W4: 0.33 | X4: 0.39 | Y4: 0.46 | Z4: 0.59 | AA4: 1
A5: 12/19/2025 (Fri) | B5: 225 | C5: 243 | D5: 302 | E5: 350 | M5: ='Performances by Week'!AG44-'Performances by Week'!AC44 -> 1433 | N5: ='Performances by Week'!O44 -> 1 | P5: Pops | Q5: 0.15 | R5: 0.18 | S5: 0.21 | T5: 0.24 | U5: 0.27 | V5: 0.3 | W5: 0.33 | X5: 0.39 | Y5: 0.46 | Z5: 0.59 | AA5: 1
A6: 12/20/2025 (Sat 1) | B6: 391 | C6: 413 | D6: 468 | E6: 527 | M6: ='Performances by Week'!AG45-'Performances by Week'!AC45 -> 1433 | N6: ='Performances by Week'!O45 -> 1 | P6: Specials | Q6: 0.15 | R6: 0.18 | S6: 0.21 | T6: 0.24 | U6: 0.27 | V6: 0.3 | W6: 0.33 | X6: 0.39 | Y6: 0.46 | Z6: 0.59 | AA6: 1
A7: 12/20/2025 (Sat 2) | B7: 296 | C7: 325 | D7: 358 | E7: 374 | M7: ='Performances by Week'!AG46-'Performances by Week'!AC46 -> 1433 | N7: ='Performances by Week'!O46 -> 1 | P7: Other | Q7: 0.15 | R7: 0.18 | S7: 0.21 | T7: 0.24 | U7: 0.27 | V7: 0.3 | W7: 0.33 | X7: 0.39 | Y7: 0.46 | Z7: 0.59 | AA7: 1
A8: 12/21/2025 (Sun 1) | B8: 353 | C8: 376 | D8: 414 | E8: 466 | M8: ='Performances by Week'!AG47-'Performances by Week'!AC47 -> 1118 | N8: ='Performances by Week'!O47 -> 1
A9: 12/21/2025 (Sun 2) | B9: 152 | C9: 216 | D9: 238 | E9: 257 | M9: ='Performances by Week'!AG48-'Performances by Week'!AC48 -> 1433 | N9: ='Performances by Week'!O48 -> 0.74726681
A10: Pace for 85% OCC | B10: =$M$10*$M$17*Q6 -> 176.01375 | C10: =$M$10*$M$17*R6 -> 211.2165 | D10: =$M$10*$M$17*S6 -> 246.41925 | E10: =$M$10*$M$17*T6 -> 281.622 | F10: =$M$10*$M$17*U6 -> 316.82475 | G10: =$M$10*$M$17*V6 -> 352.0275 | H10: =$M$10*$M$17*W6 -> 387.23025 | I10: =$M$10*$M$17*X6 -> 457.63575 | ... L10: =$M$10*$M$17*AA6 -> 1173.425 | M10: =AVERAGE(M4:M9) -> 1380.5
A11: XMas 2024 | B11: =AVERAGE(B36:B41) -> 261.33333 | C11: =AVERAGE(C36:C41) -> 282.66667 | D11: =AVERAGE(D36:D41) -> 315.5 | E11: =AVERAGE(E36:E41) -> 360.16667 | F11: =AVERAGE(F36:F41) -> 412.16667 | G11: =AVERAGE(G36:G41) -> 494.33333 | H11: =AVERAGE(H36:H41) -> 597.83333 | I11: =AVERAGE(I36:I41) -> 699.5 | ... L11: =AVERAGE(L36:L41) -> 1111.3333 | M11: Target Pace
A12: XMas 2023 | B12: =AVERAGE(B47:B52) -> 349.16667 | C12: =AVERAGE(C47:C52) -> 378.16667 | D12: =AVERAGE(D47:D52) -> 414.66667 | E12: =AVERAGE(E47:E52) -> 459.16667 | F12: =AVERAGE(F47:F52) -> 530.83333 | G12: =AVERAGE(G47:G52) -> 599.66667 | H12: =AVERAGE(H47:H52) -> 709 | I12: =AVERAGE(I47:I52) -> 795.5 | ... L12: =AVERAGE(L47:L52) -> 1105.8333
A13: Weekly new sales needed for Target Pace | C13: =C11-B11 -> 21.333333 | D13: =D11-C11 -> 32.833333 | E13: =E11-D11 -> 44.666667 | F13: =F11-E11 -> 52 | G13: =G11-F11 -> 82.166667 | H13: =H11-G11 -> 103.5 | I13: =I11-H11 -> 101.66667 | J13: =J11-I11 -> 106.66667 | ... L13: =L11-K11 -> 156.16667
A14: Actual Weekly Sales | C14: =IF(C7="","Too early",AVERAGE(C7:C9)-AVERAGE(B7:B9)) -> 38.666667 | D14: =IF(D7="","Too early",AVERAGE(D7:D9)-AVERAGE(C7:C9)) -> 31 | E14: =IF(E7="","Too early",AVERAGE(E7:E9)-AVERAGE(D7:D9)) -> 29 | F14: =IF(F7="","Too early",AVERAGE(F7:F9)-AVERAGE(E7:E9)) -> Too early | G14: =IF(G7="","Too early",AVERAGE(G7:G9)-AVERAGE(F7:F9)) -> Too early | H14: =IF(H7="","Too early",AVERAGE(H7:H9)-AVERAGE(G7:G9)) -> Too early | I14: =IF(I7="","Too early",AVERAGE(I7:I9)-AVERAGE(H7:H9)) -> Too early | J14: =IF(J7="","Too early",AVERAGE(J7:J9)-AVERAGE(I7:I9)) -> Too early | ... L14: =IF(L7="","Too early",AVERAGE(L7:L9)-AVERAGE(K7:K9)) -> Too early
A15: Avg/Show vs Target Pace: | B15: =IF(B4>0,AVERAGE(B4:B9)-B10,"TBD") -> 100.81958 | C15: =IF(C4>0,AVERAGE(C4:C9)-C10,"TBD") -> 95.2835 | D15: =IF(D4>0,AVERAGE(D4:D9)-D10,"TBD") -> 99.414083 | E15: =IF(E4>0,AVERAGE(E4:E9)-E10,"TBD") -> 104.378 | F15: =IF(F4>0,AVERAGE(F4:F9)-F10,"TBD") -> TBD | G15: =IF(G4>0,AVERAGE(G4:G9)-G10,"TBD") -> TBD | H15: =IF(H4>0,AVERAGE(H4:H9)-H10,"TBD") -> TBD | I15: =IF(I4>0,AVERAGE(I4:I9)-I10,"TBD") -> TBD | ... L15: =IF(L4>0,AVERAGE(L4:L9)-L10,"TBD") -> TBD
M16: OCC Target
M17: 0.85
A34: Single Tickets | B34: 10 | C34: 9 | D34: 8 | E34: 7 | F34: 6 | G34: 5 | H34: 4 | I34: 3 | J34: 2 | K34: 1 | L34: 0
A35: Christmas Festival | B35: 45572 | C35: 45579 | D35: 45586 | E35: 45593 | F35: 45600 | G35: 45607 | H35: 45614 | I35: 45621 | J35: 45628 | K35: 45635 | L35: 45642 | M35: # Single Tickets to sell out 100% | N35: Final Occupancy Sold %
A36: 12/19/2024 Sales (Thursday) | B36: 261 | C36: 267 | D36: 297 | E36: 341 | F36: 395 | G36: 447 | H36: 602 | I36: 693 | J36: 750 | K36: 932 | L36: 1069 | M36: 1446 | N36: 0.7897
A37: 12/20/2024 Sales (Friday) | B37: 206 | C37: 216 | D37: 256 | E37: 310 | F37: 370 | G37: 432 | H37: 509 | I37: 605 | J37: 732 | K37: 848 | L37: 1052 | M37: 1476 | N37: 0.8741
A38: 12/21/2024, 1pm Sales (Saturday) | B38: 349 | C38: 398 | D38: 427 | E38: 464 | F38: 526 | G38: 606 | H38: 670 | I38: 745 | J38: 848 | K38: 1034 | L38: 1180 | M38: 1476 | N38: 0.8934
A39: 12/21/2024, 7pm Sales (Saturday) | B39: 276 | C39: 294 | D39: 340 | E39: 375 | F39: 400 | G39: 480 | H39: 584 | I39: 715 | J39: 844 | K39: 995 | L39: 1184 | M39: 1476 | N39: 0.9591
A40: 12/22/2024, 2pm Sales (Sunday) | B40: 302 | C40: 336 | D40: 363 | E40: 411 | F40: 486 | G40: 624 | H40: 730 | I40: 857 | J40: 986 | K40: 1089 | L40: 1104 | M40: 1168 | N40: 0.9412
A41: 12/22/2024, 7pm Sales (Sunday) | B41: 174 | C41: 185 | D41: 210 | E41: 260 | F41: 296 | G41: 377 | H41: 492 | I41: 582 | J41: 677 | K41: 833 | L41: 1079 | M41: 1476 | N41: 0.9751
M42: OCC Target
M43: 0.85
A45: Single Tickets | B45: 10 | C45: 9 | D45: 8 | E45: 7 | F45: 6 | G45: 5 | H45: 4 | I45: 3 | J45: 2 | K45: 1 | L45: 0
A46: Christmas Festival | B46: 45201 | C46: 45208 | D46: 45215 | E46: 45222 | F46: 45229 | G46: 45236 | H46: 45243 | I46: 45250 | J46: 45988 | K46: 45995 | L46: 46002 | M46: # Single Tickets to sell out 100% | N46: Final Occupancy Sold %
A47: 12/14/2023 Sales (Thursday) | B47: 279 | C47: 293 | D47: 309 | E47: 348 | F47: 410 | G47: 485 | H47: 540 | I47: 608 | J47: 674 | K47: 793 | L47: 912 | M47: 1446 | N47: 0.7627
A48: 12/15/2023 Sales (Friday) | B48: 288 | C48: 332 | D48: 391 | E48: 435 | F48: 536 | G48: 605 | H48: 744 | I48: 845 | J48: 942 | K48: 1068 | L48: 1230 | M48: 1446 | N48: 0.9273
A49: 12/16/2023, 1pm Sales (Saturday) | B49: 506 | C49: 529 | D49: 575 | E49: 625 | F49: 741 | G49: 835 | H49: 972 | I49: 1097 | J49: 1175 | K49: 1315 | L49: 1382 | M49: 1446 | N49: 0.9723
A50: 12/16/2023, 7pm Sales (Saturday) | B50: 396 | C50: 417 | D50: 462 | E50: 520 | F50: 554 | G50: 619 | H50: 806 | I50: 887 | J50: 965 | K50: 1139 | L50: 1312 | M50: 1446 | N50: 0.9764
A51: 12/17/2023, 2pm Sales (Sunday) | B51: 442 | C51: 467 | D51: 499 | E51: 559 | F51: 648 | G51: 712 | H51: 800 | I51: 857 | J51: 866 | K51: 903 | L51: 925 | M51: 969 | N51: 0.9917
A52: 12/17/2023, 7pm Sales (Sunday) | B52: 184 | C52: 231 | D52: 252 | E52: 268 | F52: 296 | G52: 342 | H52: 392 | I52: 479 | J52: 584 | K52: 729 | L52: 874 | M52: 1446 | N52: 0.9702

Sheet Subscriptions
B1: KANSAS CITY SYMPHONY | E1: Update all fields in Blue each week | J1: 100%+ of FY26 Goal
B2: 2025-26 Subscriptions | E2: We expect 50% of Total by Week 5 | J2: 90-99% of FY26 Goal | N2: Classical | S2: FY26 Budget - Classical
E3: We expect 90% of Total by Week 10/11 | J3: <90% of FY26 Goal | N3: 0.72 | O3: % of total subscriptions | S3: Units | T3: Revenue
O4: =O8/S8*S4 -> 190.76952 | P4: =P8/O8*O4 -> 67934.779 | Q4: =Q8/S8*S4 -> 2954.7347 | R4: =R8/Q8*Q4 -> 1567065.2 | S4: =T4/(T8/S8) -> 3145.5043 | T4: 1635000 | U4: Total | V4: =T4/S4 -> 519.78947
B5: FY26 Sales - Classical | O5: =O9/S9*S5 -> 8.6708651 | P5: =P9/O9*O5 -> 2639.1544 | Q5: =Q9/S9*S5 -> 267.83339 | R5: =R9/Q9*Q5 -> 147753.15 | S5: =T5/(T8/S8) -> 276.50425 | T5: =T4-T8 -> 143724 | U5: Difference vs FY25
C6: New | F6: Renewals | I6: Total | N6: FY25 Actuals - Classical
A7: Weeks On Sale | C7: Actual Units | D7: Proj | E7: Actual Rev | F7: Actual Units | G7: Proj | H7: Actual Rev | I7: Actual Units | J7: Proj | K7: Actual Rev | L7: W/W Change | O7: New Units | P7: New Revenue | Q7: Renewal Units | R7: Renewal Revenue | S7: Total Units | T7: Total Revenue | U7: Change
A8: Projected Total | I8: =I16 -> 2456 | K8: =K16 -> 1408430 | N8: Final | O8: =O21 -> 174 | P8: =P21 -> 61963 | Q8: =Q21 -> 2695 | R8: =R21 -> 1429313 | S8: =S21 -> 2869 | T8: =T21 -> 1491276
A9: 1 | B9: 45747 | C9: 30 | D9: =C9/'Sales Pacing'!B3 -> 713.33333 | E9: 16220 | F9: 898 | G9: =F9/'Sales Pacing'!E3 -> 3554.0218 | H9: 527973 | I9: =C9+F9 -> 928 | J9: =D9+G9 -> 4267.3552 | K9: =E9+H9 -> 544193 | N9: 45383 | O9: 27 | P9: 8218 | Q9: 834 | R9: 460085 | S9: =O9+Q9 -> 861 | T9: =P9+R9 -> 468303
A10: 2 | B10: 45754 | C10: 39 | D10: =C10/'Sales Pacing'!B4 -> 642 | E10: 21024 | F10: 1136 | G10: =F10/'Sales Pacing'!E4 -> 3593.8233 | H10: 652031 | I10: =C10+F10 -> 1175 | J10: =D10+G10 -> 4235.8233 | K10: =E10+H10 -> 673055 | L10: =IF(K10>0,K10-K9,0) -> 128862 | N10: =N9+7 -> 45390 | O10: 32 | P10: 12068 | Q10: 1194 | R10: 655718 | S10: =O10+Q10 -> 1226 | T10: =P10+R10 -> 667786 | U10: =IF(T10>0,T10-T9,0) -> 199483
A11: 3 | B11: 45761 | C11: 50 | D11: =C11/'Sales Pacing'!B5 -> 455.31915 | E11: 27424 | F11: 1387 | G11: =F11/'Sales Pacing'!E5 -> 3529.55 | H11: 817109 | I11: =C11+F11 -> 1437 | J11: =D11+G11 -> 3984.8691 | K11: =E11+H11 -> 844533 | L11: =IF(K11>0,K11-K10,0) -> 171478 | N11: =N10+7 -> 45397 | O11: 36 | P11: 13657 | Q11: 1434 | R11: 789833 | S11: =O11+Q11 -> 1470 | T11: =P11+R11 -> 803490 | U11: =IF(T11>0,T11-T10,0) -> 135704
A12: 4 | B12: 45768 | C12: 76 | D12: =C12/'Sales Pacing'!B6 -> 591.41818 | E12: 40984 | F12: 1739 | G12: =F12/'Sales Pacing'!E6 -> 3653.0333 | H12: 1005395 | I12: =C12+F12 -> 1815 | J12: =D12+G12 -> 4244.4515 | K12: =E12+H12 -> 1046379 | L12: =IF(K12>0,K12-K11,0) -> 201846 | N12: =N11+7 -> 45404 | O12: 45 | P12: 17584 | Q12: 1789 | R12: 976040 | S12: =O12+Q12 -> 1834 | T12: =P12+R12 -> 993624 | U12: =IF(T12>0,T12-T11,0) -> 190134
A13: 5 | B13: =B12+7 -> 45775 | C13: 112 | D13: =C13/'Sales Pacing'!B7 -> 684.8 | E13: 54163 | F13: 2160 | G13: =F13/'Sales Pacing'!E7 -> 3788.4885 | H13: 1232817 | I13: =C13+F13 -> 2272 | J13: =D13+G13 -> 4473.2885 | K13: =E13+H13 -> 1286980 | L13: =IF(K13>0,K13-K12,0) -> 240601 | N13: =N12+7 -> 45411 | O13: 47 | P13: 17987 | Q13: 2005 | R13: 1080463 | S13: =O13+Q13 -> 2052 | T13: =P13+R13 -> 1098450 | U13: =IF(T13>0,T13-T12,0) -> 104826
A14: 6 | B14: =B13+7 -> 45782 | C14: 121 | D14: =C14/'Sales Pacing'!B8 -> 533.89691 | E14: 58153 | F14: 2252 | G14: =F14/'Sales Pacing'!E8 -> 3121.3817 | H14: 1294295 | I14: =C14+F14 -> 2373 | J14: =D14+G14 -> 3655.2787 | K14: =E14+H14 -> 1352448 | L14: =IF(K14>0,K14-K13,0) -> 65468 | N14: =N13+7 -> 45418 | O14: 70 | P14: 26832 | Q14: 2362 | R14: 1271615 | S14: =O14+Q14 -> 2432 | T14: =P14+R14 -> 1298447 | U14: =IF(T14>0,T14-T13,0) -> 199997
A15: 7 | B15: =B14+7 -> 45789 | C15: 122 | D15: =C15/'Sales Pacing'!B9 -> 404.77519 | E15: 59763 | F15: 2293 | G15: =F15/'Sales Pacing'!E9 -> 2534.0926 | H15: 1322554 | I15: =C15+F15 -> 2415 | J15: =D15+G15 -> 2938.8678 | K15: =E15+H15 -> 1382317 | L15: =IF(K15>0,K15-K14,0) -> 29869 | N15: =N14+7 -> 45425 | O15: 76 | P15: 28802 | Q15: 2443 | R15: 1319275 | S15: =O15+Q15 -> 2519 | T15: =P15+R15 -> 1348077 | U15: =IF(T15>0,T15-T14,0) -> 49630
A16: 8 | B16: =B15+7 -> 45796 | C16: 134 | D16: =C16/'Sales Pacing'!B10 -> 382.34667 | E16: 63528 | F16: 2322 | G16: =F16/'Sales Pacing'!E10 -> 2473.787 | H16: 1344902 | I16: =C16+F16 -> 2456 | J16: =D16+G16 -> 2856.1337 | K16: =E16+H16 -> 1408430 | L16: =IF(K16>0,K16-K15,0) -> 26113 | N16: =N15+7 -> 45432 | O16: 85 | P16: 30752 | Q16: 2473 | R16: 1329297 | S16: =O16+Q16 -> 2558 | T16: =P16+R16 -> 1360049 | U16: =IF(T16>0,T16-T15,0) -> 11972
A17: 9 | B17: =B16+7 -> 45803 | C17: 146 | D17: =C17/'Sales Pacing'!B11 -> 369.75148 | E17: 67946 | F17: 2345 | G17: =F17/'Sales Pacing'!E11 -> 2468.3763 | H17: 1357272 | I17: =C17+F17 -> 2491 | J17: =D17+G17 -> 2838.1277 | K17: =E17+H17 -> 1425218 | L17: =IF(K17>0,K17-K16,0) -> 16788 | N17: =N16+7 -> 45439 | O17: 91 | P17: 32154 | Q17: 2513 | R17: 1344658 | S17: =O17+Q17 -> 2604 | T17: =P17+R17 -> 1376812 | U17: =IF(T17>0,T17-T16,0) -> 16763
A18: 10 | B18: =B17+7 -> 45810 | C18: 165 | D18: =C18/'Sales Pacing'!B12 -> 377.64706 | E18: 75744 | F18: 2369 | G18: =F18/'Sales Pacing'!E12 -> 2461.486 | H18: 1380368 | I18: =C18+F18 -> 2534 | J18: =D18+G18 -> 2839.1331 | K18: =E18+H18 -> 1456112 | L18: =IF(K18>0,K18-K17,0) -> 30894 | N18: =N17+7 -> 45446 | O18: 94 | P18: 32854 | Q18: 2608 | R18: 1391277 | S18: =O18+Q18 -> 2702 | T18: =P18+R18 -> 1424131 | U18: =IF(T18>0,T18-T17,0) -> 47319
A19: 11 | B19: =B18+7 -> 45817 | C19: 186 | D19: =C19/'Sales Pacing'!B13 -> 396.0597 | E19: 89633 | F19: 2384 | G19: =F19/'Sales Pacing'!E13 -> 2469.1125 | H19: 1390065 | I19: =C19+F19 -> 2570 | J19: =D19+G19 -> 2865.1722 | K19: =E19+H19 -> 1479698 | L19: =IF(K19>0,K19-K18,0) -> 23586 | N19: =N18+7 -> 45453 | O19: 95 | P19: 33169 | Q19: 2628 | R19: 1398365 | S19: =O19+Q19 -> 2723 | T19: =P19+R19 -> 1431534 | U19: =IF(T19>0,T19-T18,0) -> 7403
A20: 12 | B20: =B19+7 -> 45824 | C20: 205 | D20: =C20/'Sales Pacing'!B14 -> 404.3318 | E20: 94753 | F20: 2413 | G20: =F20/'Sales Pacing'!E14 -> 2491.1434 | H20: 1408181 | I20: =C20+F20 -> 2618 | J20: =D20+G20 -> 2895.4752 | K20: =E20+H20 -> 1502934 | L20: =IF(K20>0,K20-K19,0) -> 23236 | N20: =N19+7 -> 45460 | O20: 103 | P20: 35745 | Q20: 2655 | R20: 1411925 | S20: =O20+Q20 -> 2758 | T20: =P20+R20 -> 1447670 | U20: =IF(T20>0,T20-T19,0) -> 16136
A21: 13+ | B21: 45936 | C21: 323 | D21: =C21/'Sales Pacing'!B15 -> 323 | E21: 142246.1 | F21: 2432 | G21: =F21/'Sales Pacing'!E15 -> 2432 | H21: 1412928.3 | I21: =C21+F21 -> 2755 | J21: =D21+G21 -> 2755 | K21: =E21+H21 -> 1555174.4 | L21: =IF(K21>0,K21-K20,0) -> 52240.4 | N21: Rest of Season | O21: 174 | P21: 61963 | Q21: 2695 | R21: 1429313 | S21: =O21+Q21 -> 2869 | T21: =P21+R21 -> 1491276 | U21: =IF(T21>0,T21-T20,0) -> 43606
I22: vs. FY26 Goal | J22: =J21/$S$4 -> 0.87585321 | K22: =K21/$T$4 -> 0.951177
B23: 25-26 Churn | C23: #
B24: =(1-F21/S8) -> 0.15231788 | C24: =S8-F21 -> 437 | E24: 3rd Classical mailer drops 22nd/23rd of August | N24: Pops | S24: FY26 Budget - Pops
N25: 0.26 | O25: % of total subscriptions | S25: Units | T25: Revenue
O26: =O30/S30*S26 -> 240.07343 | P26: =P30/O30*O26 -> 69318.269 | Q26: =Q30/S30*S26 -> 1547.1399 | R26: =R30/Q30*Q26 -> 549681.73 | S26: =T26/(T30/S30) -> 1787.2133 | T26: 619000 | U26: Total | V26: =T26/S26 -> 346.34925
B27: FY26 Sales - Pops | O27: =O31/S31*S27 -> 3.2060949 | P27: =P31/O31*O27 -> 1038.7747 | Q27: =Q31/S31*S27 -> 109.00723 | R27: =R31/Q31*Q27 -> 44362.735 | S27: =T27/(T30/S30) -> 112.21332 | T27: =T26-T30 -> 38865 | U27: Difference vs FY25
C28: New | F28: Renewals | I28: Total | N28: FY25 Actuals - Pops
C29: Actual Units | D29: Proj | E29: Actual Rev | F29: Actual Units | G29: Proj | H29: Actual Rev | I29: Actual Units | J29: Proj | K29: Actual Rev | L29: W/W Change | O29: New Units | P29: New Revenue | Q29: Renewal Units | R29: Renewal Revenue | S29: Total Units | T29: Total Revenue | U29: Change
A30: Projected Total | I30: =I38 -> 1561 | K30: =K38 -> 591188 | N30: Final | O30: =O43 -> 225 | P30: =P43 -> 64966 | Q30: =Q43 -> 1450 | R30: =R43 -> 515169 | S30: =S43 -> 1675 | T30: =T43 -> 580135
A31: 1 | B31: 45747 | C31: 38 | D31: =C31/'Sales Pacing'!C3 -> 1048.1667 | E31: 13163 | F31: 636 | G31: =F31/'Sales Pacing'!F3 -> 5546.3927 | H31: 258782 | I31: =C31+F31 -> 674 | J31: =D31+G31 -> 6594.5593 | K31: =E31+H31 -> 271945 | N31: 45383 | O31: 2 | P31: 648 | Q31: 68 | R31: 27674 | S31: =O31+Q31 -> 70 | T31: =P31+R31 -> 28322
A32: 2 | B32: 45754 | C32: 44 | D32: =C32/'Sales Pacing'!C4 -> 606.83333 | E32: 14651 | F32: 785 | G32: =F32/'Sales Pacing'!F4 -> 3783.5789 | H32: 312531 | I32: =C32+F32 -> 829 | J32: =D32+G32 -> 4390.4122 | K32: =E32+H32 -> 327182 | L32: =IF(K32>0,K32-K31,0) -> 55237 | N32: =N31+7 -> 45390 | O32: 54 | P32: 17576 | Q32: 181 | R32: 68648 | S32: =O32+Q32 -> 235 | T32: =P32+R32 -> 86224 | U32: =IF(T32>0,T32-T31,0) -> 57902
A33: 3 | B33: 45761 | C33: 54 | D33: =C33/'Sales Pacing'!C5 -> 616.34483 | E33: 19061 | F33: 893 | G33: =F33/'Sales Pacing'!F5 -> 3135.2144 | H33: 353304 | I33: =C33+F33 -> 947 | J33: =D33+G33 -> 3751.5592 | K33: =E33+H33 -> 372365 | L33: =IF(K33>0,K33-K32,0) -> 45183 | N33: =N32+7 -> 45397 | O33: 66 | P33: 20302 | Q33: 283 | R33: 105425 | S33: =O33+Q33 -> 349 | T33: =P33+R33 -> 125727 | U33: =IF(T33>0,T33-T32,0) -> 39503
A34: 4 | B34: 45768 | C34: 60 | D34: =C34/'Sales Pacing'!C6 -> 484.39024 | E34: 20782 | F34: 1067 | G34: =F34/'Sales Pacing'!F6 -> 2921.075 | H34: 417996 | I34: =C34+F34 -> 1127 | J34: =D34+G34 -> 3405.4653 | K34: =E34+H34 -> 438778 | L34: =IF(K34>0,K34-K33,0) -> 66413 | N34: =N33+7 -> 45404 | O34: 86 | P34: 26557 | Q34: 389 | R34: 146108 | S34: =O34+Q34 -> 475 | T34: =P34+R34 -> 172665 | U34: =IF(T34>0,T34-T33,0) -> 46938
A35: 5 | B35: =B34+7 -> 45775 | C35: 118 | D35: =C35/'Sales Pacing'!C7 -> 566.05797 | E35: 38918 | F35: 1300 | G35: =F35/'Sales Pacing'!F7 -> 2887.9509 | H35: 502867 | I35: =C35+F35 -> 1418 | J35: =D35+G35 -> 3454.0088 | K35: =E35+H35 -> 541785 | L35: =IF(K35>0,K35-K34,0) -> 103007 | N35: =N34+7 -> 45411 | O35: 86 | P35: 26557 | Q35: 476 | R35: 178054 | S35: =O35+Q35 -> 562 | T35: =P35+R35 -> 204611 | U35: =IF(T35>0,T35-T34,0) -> 31946
A36: 6 | B36: =B35+7 -> 45782 | C36: 157 | D36: =C36/'Sales Pacing'!C8 -> 683.77632 | E36: 51765 | F36: 1358 | G36: =F36/'Sales Pacing'!F8 -> 2121.6398 | H36: 522161 | I36: =C36+F36 -> 1515 | J36: =D36+G36 -> 2805.4161 | K36: =E36+H36 -> 573926 | L36: =IF(K36>0,K36-K35,0) -> 32141 | N36: =N35+7 -> 45418 | O36: 98 | P36: 31472 | Q36: 806 | R36: 294720 | S36: =O36+Q36 -> 904 | T36: =P36+R36 -> 326192 | U36: =IF(T36>0,T36-T35,0) -> 121581
A37: 7 | B37: =B36+7 -> 45789 | C37: 165 | D37: =C37/'Sales Pacing'!C9 -> 593.6413 | E37: 54301 | F37: 1365 | G37: =F37/'Sales Pacing'!F9 -> 1717.375 | H37: 525805 | I37: =C37+F37 -> 1530 | J37: =D37+G37 -> 2311.0163 | K37: =E37+H37 -> 580106 | L37: =IF(K37>0,K37-K36,0) -> 6180 | N37: =N36+7 -> 45425 | O37: 113 | P37: 36672 | Q37: 1031 | R37: 372369 | S37: =O37+Q37 -> 1144 | T37: =P37+R37 -> 409041 | U37: =IF(T37>0,T37-T36,0) -> 82849
A38: 8 | B38: =B37+7 -> 45796 | C38: 199 | D38: =C38/'Sales Pacing'!C10 -> 639.50485 | E38: 65018 | F38: 1362 | G38: =F38/'Sales Pacing'!F10 -> 1532.8471 | H38: 526170 | I38: =C38+F38 -> 1561 | J38: =D38+G38 -> 2172.3519 | K38: =E38+H38 -> 591188 | L38: =IF(K38>0,K38-K37,0) -> 11082 | N38: =N37+7 -> 45432 | O38: 127 | P38: 40518 | Q38: 1267 | R38: 452816 | S38: =O38+Q38 -> 1394 | T38: =P38+R38 -> 493334 | U38: =IF(T38>0,T38-T37,0) -> 84293
A39: 9 | B39: =B38+7 -> 45803 | C39: 220 | D39: =C39/'Sales Pacing'!C11 -> 568.90625 | E39: 73218 | F39: 1368 | G39: =F39/'Sales Pacing'!F11 -> 1451.7935 | H39: 531352 | I39: =C39+F39 -> 1588 | J39: =D39+G39 -> 2020.6998 | K39: =E39+H39 -> 604570 | L39: =IF(K39>0,K39-K38,0) -> 13382 | N39: =N38+7 -> 45439 | O39: 160 | P39: 48485 | Q39: 1395 | R39: 497335 | S39: =O39+Q39 -> 1555 | T39: =P39+R39 -> 545820 | U39: =IF(T39>0,T39-T38,0) -> 52486
A40: 10 | B40: =B39+7 -> 45810 | C40: 239 | D40: =C40/'Sales Pacing'!C12 -> 557.10563 | E40: 80035 | F40: 1374 | G40: =F40/'Sales Pacing'!F12 -> 1439.2578 | H40: 536728 | I40: =C40+F40 -> 1613 | J40: =D40+G40 -> 1996.3634 | K40: =E40+H40 -> 616763 | L40: =IF(K40>0,K40-K39,0) -> 12193 | N40: =N39+7 -> 45446 | O40: 172 | P40: 51234 | Q40: 1411 | R40: 502695 | S40: =O40+Q40 -> 1583 | T40: =P40+R40 -> 553929 | U40: =IF(T40>0,T40-T39,0) -> 8109
A41: 11 | B41: =B40+7 -> 45817 | C41: 255 | D41: =C41/'Sales Pacing'!C13 -> 530.84906 | E41: 89633 | F41: 1407 | G41: =F41/'Sales Pacing'!F13 -> 1457.5735 | H41: 540393 | I41: =C41+F41 -> 1662 | J41: =D41+G41 -> 1988.4225 | K41: =E41+H41 -> 630026 | L41: =IF(K41>0,K41-K40,0) -> 13263 | N41: =N40+7 -> 45453 | O41: 187 | P41: 55826 | Q41: 1418 | R41: 505550 | S41: =O41+Q41 -> 1605 | T41: =P41+R41 -> 561376 | U41: =IF(T41>0,T41-T40,0) -> 7447
A42: 12 | B42: =B41+7 -> 45824 | C42: 270 | D42: =C42/'Sales Pacing'!C14 -> 470.36842 | E42: 90711 | F42: 1383 | G42: =F42/'Sales Pacing'!F14 -> 1420.054 | H42: 543160 | I42: =C42+F42 -> 1653 | J42: =D42+G42 -> 1890.4224 | K42: =E42+H42 -> 633871 | L42: =IF(K42>0,K42-K41,0) -> 3845 | N42: =N41+7 -> 45460 | O42: 193 | P42: 57355 | Q42: 1434 | R42: 510568 | S42: =O42+Q42 -> 1627 | T42: =P42+R42 -> 567923 | U42: =IF(T42>0,T42-T41,0) -> 6547
A43: 13+ | B43: 45936 | C43: 388 | D43: =C43/'Sales Pacing'!C15 -> 388 | E43: 121629.9 | F43: 1409 | G43: =F43/'Sales Pacing'!F15 -> 1409 | H43: 544870 | I43: =C43+F43 -> 1797 | J43: =D43+G43 -> 1797 | K43: =E43+H43 -> 666499.9 | L43: =IF(K43>0,K43-K42,0) -> 32628.9 | N43: Rest of Season | O43: 225 | P43: 64966 | Q43: 1450 | R43: 515169 | S43: =O43+Q43 -> 1675 | T43: =P43+R43 -> 580135 | U43: =IF(T43>0,T43-T42,0) -> 12212
I44: vs. FY26 Goal | J44: =J43/$S$26 -> 1.0054759 | K44: =K43/$T$26 -> 1.0767365
B45: 25-26 Churn | C45: #
B46: =(1-F43/S30) -> 0.15880597 | C46: =S30-F43 -> 266
A48: Future Improvements:
A49: Give true renewal rates
A50: Show renewals by customer cohort
A51: Add Family subscriptions (2%)

Sheet Summary (Draft)
B2: Overall Season | G2: # Tickets Sold | H2: Projected Tickets Sold | I2: Projected Occupancy (% +GYR) | J2: Total Revenue | K2: BUDGET | L2: Projected Revenue vs Budget (% +GYR)
B3: ALL CONCERTS | G3: ='Performances by Week'!I126 -> 0 | H3: ='Performances by Week'!J126 -> 0 | I3: ='Performances by Week'!K126 -> 0 | J3: ='Performances by Week'!M126 -> 0 | K3: ='Performances by Week'!O126 -> 6268640 | L3: ='Performances by Week'!Q126
B5: Season Attendance By Ticket Type | G5: # Tickets Sold | H5: Projected Tickets Sold | J5: Total Revenue | K5: BUDGET | L5: Projected Revenue vs Budget (% +GYR)
B6: All Subscriptions | G6: ='Performances by Week'!AB126 -> 0 | J6: ='Performances by Week'!AC126 -> 0 | K6: ='Performances by Week'!AD126 -> 2169893 | L6: ='Performances by Week'!AE126
B7: All Single Tickets | G7: ='Performances by Week'!#REF! -> #REF! | H7: ='Performances by Week'!U126 -> #REF! | J7: ='Performances by Week'!X126 -> 0 | K7: ='Performances by Week'!Y126 -> 3973690 | L7: ='Performances by Week'!AA126
B9: Concert Attendance By Performance Type | G9: # Tickets Sold | H9: Projected Tickets Sold | I9: Projected Occupancy (% +GYR) | J9: Total Revenue | K9: BUDGET | L9: Projected Revenue vs Budget (% +GYR)
B10: CLASSICAL TRADITIONAL TOTAL | G10: ='Performances by Week'!I119 -> 0 | H10: ='Performances by Week'!J119 -> 0 | I10: ='Performances by Week'!K119 -> 0 | J10: ='Performances by Week'!M119 -> 0 | K10: ='Performances by Week'!O119 -> 2139000 | L10: ='Performances by Week'!Q119
B11: SYMPHONIC PIAZZA TOTAL | G11: ='Performances by Week'!I120 -> 0 | H11: ='Performances by Week'!J120 -> 0 | I11: ='Performances by Week'!K120 -> 0 | J11: ='Performances by Week'!M120 -> 0 | K11: ='Performances by Week'!O120 -> 363000 | L11: ='Performances by Week'!Q120
B12: POPS TOTAL | G12: ='Performances by Week'!I121 -> 0 | H12: ='Performances by Week'!J121 -> 0 | I12: ='Performances by Week'!K121 -> 0 | J12: ='Performances by Week'!M121 -> 0 | K12: ='Performances by Week'!O121 -> 1457000 | L12: ='Performances by Week'!Q121
B13: FAMILY SERIES TOTAL | G13: ='Performances by Week'!I122 -> 0 | H13: ='Performances by Week'!J122 -> 0 | I13: ='Performances by Week'!K122 -> 0 | J13: ='Performances by Week'!M122 -> 0 | K13: ='Performances by Week'!O122 -> 525950 | L13: ='Performances by Week'!Q122
B14: FILM TOTAL | G14: ='Performances by Week'!I123 -> 0 | H14: ='Performances by Week'!J123 -> 0 | I14: ='Performances by Week'!K123 -> 0 | J14: ='Performances by Week'!M123 -> 0 | K14: ='Performances by Week'!O123 -> 1745490 | L14: ='Performances by Week'!Q123
B15: ON STAGE CONCERTS TOTAL | G15: ='Performances by Week'!I124 -> 0 | H15: ='Performances by Week'!J124 -> 0 | I15: ='Performances by Week'!K124 -> 0 | J15: ='Performances by Week'!M124 -> 0 | K15: ='Performances by Week'!O124 -> 38200 | L15: ='Performances by Week'!Q124
B16: OTHER CONCERT TOTAL | G16: ='Performances by Week'!I125 -> 0 | H16: ='Performances by Week'!J125 -> 0 | I16: ='Performances by Week'!K125 -> 0 | J16: ='Performances by Week'!M125 -> 0 | K16: ='Performances by Week'!O125 -> 0 | L16: ='Performances by Week'!Q125

Sheet Sub Graphs
A16: Notes: | B16: FY19 was pre-COVID
B17: FY24 was -35% vs FY19, but also Michael Stern's final season so perhaps a one-time boost
B18: FY25 was -47% vs FY19 and -19% vs FY24
B19: FY26 is -4% vs FY25
B20: For FY27, it is important to start sales no later than Week 5 (coordinate with season anouncement) and understand how to boost renewal rate
J27: Notes: | K27: FY19 was pre-COVID
K28: FY24 was -19% vs FY19, but also Michael Stern's final season so perhaps a one-time boost
K29: FY25 was -29% vs FY19 and -12% vs FY24
K30: FY26 is +7% vs FY25, driven by growth in new subs
K31: For FY27, it is important to start sales no later than Week 5 and understand how to continue new sub growth

Sheet Channels (Draft)
A1: MARKETING CHANNEL PERFORMANCE
B2: Owned Marketing Channels | H2: Paid Channels
A3: To start, let’s pull last 12 months of data. | B3: Phone | C3: Direct Mail | D3: Email | E3: Social | F3: In-hall | G3: SEO | H3: SEM | I3: Media | J3: Phone | K3: Total
B4: (Box Office) | E4: (FB, IG, X, other) | F4: (book, posters) | I4: (TV, radio, OOH) | J4: (Bennett)
A5: # Impressions: | D5: 13.7M
A6: calls made, e/mails delivered, etc.
A7: # Engagement: | D7: 4.7M
A8: calls answered, opens, etc.
A9: Engagement rate | D9: 34%
A10: # Actions (Success): | D10: 89k
A11: conversations, clicks, etc.
A12: Action rate | D12: 0.6%
A13: % of total Actions
A15: Channel cost ($, time)
A16: ROI: $/Action
A17: Attributed revenue ($) | J17: ~$220k
A18: ROI: $/channel cost
A20: SALES CHANNEL PERFORMANCE
A21: To start, let’s pull last 12 months of data. | B21: Phone | C21: Website | D21: KCPA | E21: Total
B22: (Box Office)
A23: # Traffic: | C23: 471,563
A24: calls received, visits
A25: % Traffic by Marketing Channel
A26: #, $ Conversions (Success): | C26: 4,547
A27: Conversion rate | C27: 0.94%
A28: % of total Conversions | D28: 15%?
A29: Total Sales Revenue | B29: ~$6,500k? | C29: $877k
A31: Channel cost ($, time)
A32: ROI: $/Conversion
A33: Attributed revenue ($)
A34: ROI: $/channel cost
A36: EXPERIENCE CHANNEL PERFORMANCE
B37: Total
A38: # total attendance
A39: % Repeat:
A40: % returning from prior season
A41: # Frequency:
A42: avg. attendance/customer
A44: Total Revenue, ROI?
A45: Avg. CSAT, NPS
A46: Avg. CLV/attendee
A47: # high CLV VIPs

Sheet Sales Pacing
B1: New Subs | E1: Renewal Subs
A2: # Weeks On Sale | B2: Classical | C2: Pops | E2: Classical | F2: Pops
A3: 1 | B3: 0.042056075 | C3: 0.036253776 | E3: 0.25267149 | F3: 0.11466913
A4: 2 | B4: 0.060747664 | C4: 0.072507553 | E4: 0.3160979 | F4: 0.20747552
A5: 3 | B5: 0.10981308 | C5: 0.087613293 | E5: 0.39296794 | F5: 0.28482901
A6: 4 | B6: 0.12850467 | C6: 0.12386707 | E6: 0.47604274 | F6: 0.36527648
A7: 5 | B7: 0.1635514 | C7: 0.20845921 | E7: 0.57014822 | F7: 0.45014616
A8: 6 | B8: 0.22663551 | C8: 0.22960725 | E8: 0.72147535 | F8: 0.64007095
A9: 7 | B9: 0.30140187 | C9: 0.27794562 | E9: 0.90486039 | F9: 0.79481765
A10: 8 | B10: 0.35046729 | C10: 0.31117825 | E10: 0.93864185 | F10: 0.88854264
A11: 9 | B11: 0.39485981 | C11: 0.38670695 | E11: 0.95001724 | F11: 0.94228277
A12: 10 | B12: 0.43691589 | C12: 0.42900302 | E12: 0.96242675 | F12: 0.95465872
A13: 11 | B13: 0.46962617 | C13: 0.48036254 | E13: 0.96552913 | F13: 0.96530297
A14: 12 | B14: 0.50700935 | C14: 0.57401813 | E14: 0.96863151 | F14: 0.97390663
A15: 13+ | B15: 1 | C15: 1 | E15: 1 | F15: 1
B21: Single Tickets
A22: # Weeks Until Performance | B22: Classical | C22: Pops | D22: Specials | E22: Other | F22: Film | G22: CS (Chuck) | H22: CS2 | I22: CS3
A23: 0 | B23: 1 | C23: 1 | D23: 1 | E23: 1 | F23: 1 | G23: 1 | H23: 1 | I23: 1
A24: 1 | B24: 0.59 | C24: 0.59 | D24: 0.59 | E24: 0.59 | F24: 0.95 | G24: 0.71 | H24: 0.7 | I24: 0.63
A25: 2 | B25: 0.46 | C25: 0.46 | D25: 0.46 | E25: 0.46 | F25: 0.85 | G25: 0.55 | H25: 0.58 | I25: 0.54
A26: 3 | B26: 0.39 | C26: 0.39 | D26: 0.39 | E26: 0.39 | F26: 0.74 | G26: 0.44 | H26: 0.5 | I26: 0.46
A27: 4 | B27: 0.33 | C27: 0.33 | D27: 0.33 | E27: 0.33 | F27: 0.65 | G27: 0.39 | H27: 0.44 | I27: 0.39
A28: 5 | B28: 0.3 | C28: 0.3 | D28: 0.3 | E28: 0.3 | F28: 0.56 | G28: 0.33 | H28: 0.39 | I28: 0.35
A29: 6 | B29: 0.27 | C29: 0.27 | D29: 0.27 | E29: 0.27 | F29: 0.5 | G29: 0.31 | H29: 0.36 | I29: 0.31
A30: 7 | B30: 0.24 | C30: 0.24 | D30: 0.24 | E30: 0.24 | F30: 0.47 | G30: 0.29 | H30: 0.34 | I30: 0.28
A31: 8 | B31: 0.21 | C31: 0.21 | D31: 0.21 | E31: 0.21 | F31: 0.44 | G31: 0.27 | H31: 0.33 | I31: 0.26
A32: 9 | B32: 0.18 | C32: 0.18 | D32: 0.18 | E32: 0.18 | F32: 0.41 | G32: 0.27 | H32: 0.31 | I32: 0.24
A33: 10 | B33: 0.15 | C33: 0.15 | D33: 0.15 | E33: 0.15 | F33: 0.37 | G33: 0.24 | H33: 0.29 | I33: 0.23
A34: 11
A35: 12
A36: 13+
A38: Future Improvements:
A39: Extend data for single ticket sales beyond 6 weeks
A40: Differentiate single ticket sales by performance type
A41: Improve pacing data (always)

Sheet Email Reporting
A1: EMAILS SENT | B1: DELIVERIES | C1: OPENS | D1: CLICK RATE
A2: 9/21 Journey KBYG SUN | B2: 348 | C2: 258 (74.1%) | D2: 103 (29.6%) | J2: AVERAGE OPEN RATE: | K2: 0.37
A3: 9/20 Journey KBYG SAT | B3: 398 | C3: 287 (72.1%) | D3: 104 (26.1%) | J3: AVERAGE CLICK RATE: | K3: 0.02
A4: 9/19 Journey KBYG FRI | B4: 417 | C4: 289 (69.3%) | D4: 101 (24.2%)
A5: 9/18 90s Standalone Email | B5: 95170 | C5: 33,599 (35.3%) | D5: 341 (0.4%)
A6: 9/16 Weekly Concert Promo | B6: 93715 | C6: 34,837 (37.2%) | D6: 729 (0.8%)
A7: 9/15 CS2 Standalone Email | B7: 93796 | C7: 34,769 (37.1%) | D7: 342 (0.4%)
A8: 9/10 Journey Giveaway | B8: 95517 | C8: 34,249 (35.9%) | D8: 751 (1%)
A9: 9/9 Weekly Concert Promo | B9: 93965 | C9: 35,513 (37.8%) | D9: 780 (1%)
A10: 9/5 CS1 BOGO Pops Buyers | B10: 4488 | C10: 2,377 (53%) | D10: 100 (2.2%) - 33 respond (98 tickets)
A11: 9/5 CS1 Morgan Freeman Buyers | B11: 1008 | C11: 588 (58.3%) | D11: 33 (3.3%) - 33 respond (98 tickets)
A12: 9/4 CS1 Matthias Video | B12: 95604 | C12: 35,461 (37.1%) | D12: 1,460 (1.5%)
A13: 9/4 Journey BOGO Promo | B13: 2721 | C13: 1,164 (42.8%) | D13: 54 (2%) - 15 respond (41 tickets)
A14: 9/3 Morgan Freeman KBYG | B14: 376 | C14: 306 (81.4%) | D14: 129 (34.3%)
A15: 9/2 Morgan Freeman KBYG | B15: 426 | C15: 354 (83.1%) | D15: 152 (35.7%)
... A18: 8/20 Bi-weekly Merchandise Email | B18: 95473 | C18: 35,125 (37%) | D18: 754 (1%)
A19: 8/12 Music of Journey Promo | B19: 94241 | C19: 35,743 (37.9%) | D19: 577 0.6% | E19: https://conta.cc/4mdHLVC
A20: 8/6 Bi-weekly Merchandise Email | B20: 94322 | C20: 36,401 (38.6%) | D20: 937 (1%) | E20: https://conta.cc/3Hoy3k2
A21: 7/21 La Nuit Sombre Matthias Video | B21: 95893 | C21: 35,531 (37.1%) | D21: 491 (0.5%)
A22: 7/23 Morgan Freeman Promo | B22: 96012 | C22: 35,064 (36.5%) | D22: 769 (0.8%)
A23: 7/15 Single Ticket On Sale Announcement | B23: 95831 | C23: 35,285 (37.2%) | D23: 1,708 (2%)
A24: 7/8 Leslie Odom Jr. Promo | B24: 94927 | C24: 35, 660 (37.6%) | D24: 550 (0.6%)
A25: Tuesday 7/1 Holiday Presentations On Sale | B25: 95059 | C25: 35039 (36.9%) | D25: 822 (0.9%) | E25: Header: 64, Elf in Concert: 473, Handel's Messiah: 390, LOJ: 110, Christmas Festival: 144, Wonderful Life: 129
A26: Tuesday 6/25 Special Presentations On Sale | B26: 95219 | C26: 35,617 (37%) | D26: 1,469 (2%) | E26: Full lineup: 248, Morgan Freeman: 438, Chicken Fried: 456, Top Gun: 559, Lodger: 100, Indiana Jones: 204, Chris Thile: 134, Harry Potter: 139, Final Symphony: 74, Ben Rector: 108, On Stage George: 45, On Stage Leila: 53, On Stage Gil: 37, On Stage 38
A27: Tuesday 6/17 Mark Your Calendar | B27: 104371 | C27: 37,343 (39%) | D27: 1,999 (2%)
A28: Monday 6/9 Mobile Music Box June Concert | B28: 95,460 | C28: 36,052 (38%) | D28: 594 (1%)
A29: Wednesday 6/4 CS14 Student Rush Promo | B29: 174 | C29: 77 (44%) | D29: 0
A30: Wednesday 6/4 CS14 Student Rush Promo | B30: 174 | C30: 77 (44%) | D30: 0
A31: Wednesday 6/4 CS14 Student Pass Promo | B31: 80 | C31: 38 (47%) | D31: 1
A32: Wednesday 6/4 CS14 BOGO Promo | B32: 4954 | C32: 2,165 (44%) | D32: 65 (1%)
A33: Wednesday 6/4 Four Larks Subscriber Early Access | B33: 2185 | C33: 1,452 (66.5%) | D33: 135 (6.2%)
A34: Friday 6/6 Four Lark Public On-Sale | B34: 96846 | C34: 35,136 (36%) | D34: 616 (0.6%)

Sheet Social Reporting
A1: DATE | B1: Social Post | C1: Views | D1: Engagement
A2: 45919 | B2: CS2 Graphic FB | C2: 1.6K reach | D2: 13 interactions
A3: 45919 | B3: CS2 Graphic IG | C3: 682 reach | D3: 13 interactions
A4: 45918 | B4: Orchestra Games Reel FB | C4: 1.2K reach | D4: 16 interactions
A5: 45918 | B5: Orchestra Games Reel IG | C5: 707 reach | D5: 31 interactions
A6: 45917 | B6: CS1 Graphic FB | C6: 1.7K reach | D6: 16 interactions
A7: 45917 | B7: CS1 Graphic IG | C7: 611 reach | D7: 22 interactions
A8: 45916 | B8: Journey musician feature IG | C8: 779 reach | D8: 17 interactions
A9: 45916 | B9: Journey musician feature FB | C9: 763 reach | D9: 12 interactions
A10: 45915 | B10: 90s Graphic FB | C10: 1.5K reach | D10: 7 interactions
A11: 45915 | B11: 90s Graphic IG | C11: 1.1K reach | D11: 18 interactions
A12: 45913 | B12: CS1 Mike G reel FB | C12: 2.7K reach | D12: 60 interactions
A13: 45913 | B13: CS1 Mike G reel IG | C13: 1.2K reach | D13: 51 interactions
... A25: 45902 | B25: KC Star Matthias article reshare FB | C25: 1.7K reach | D25: 42 interactions
A27: DATE | B27: Meta Ads | C27: Views | D27: Engagement
A28: 9/12-9/25 | B28: Top Gun Ad | C28: 83,913 reach, 154,220 impressions | D28: 3,352 link clicks
A29: 9/18-10/2 | B29: 90s Mixtape Ad | C29: 31,593 reach, 53,149 impressions | D29: 718 link clicks
A30: 9/4 - 9/18 | B30: CS1 Video Ad | C30: 33,438 reach, 63,806 impressions | D30: 2,410 link clicks
A40: 45898 | B40: Chicken Fried Rock FB Reel | C40: 1.4K reach | D40: 13 interactions, 2 shares
A41: 45898 | B41: Chicken Fried Rock IG Reel | C41: 1.1K reach | D41: 42 interactions, 3 shares
A42: 45897 | B42: ProAm post FB | C42: 3.7K reach | D42: 24 interactions, 13 shares
A43: 45897 | B43: ProAm post IG | C43: 1.3K reach | D43: 35 interactions, 6 shares
A44: 45896 | B44: MMB FB Reel | C44: 1.3K reach | D44: 16 interactions
A45: 45896 | B45: MMB IG Reel | C45: 1.1K reach | D45: 32 interactions
A46: 45895 | B46: New musician welcome FB | C46: 14.9K reach | D46: 223 interactions, 26 comments, 10 shares
A47: 45895 | B47: New musician welcome IG | C47: 9.1K reach | D47: 515 interactions, 7 comments, 64 shares
A48: 45891 | B48: Chicken Fried IG | C48: 1625 | D48: 11 interactions
A49: 45891 | B49: Chicken Fried FB | C49: 2570 | D49: 15 interactions, 6 link clicks
A50: 45890 | B50: Journey Reel IG | C50: 1005 | D50: 16 interactions
A51: 45890 | B51: Journey Reel FB | C51: 813 | D51: 12 interactions
A52: 45883 | B52: KC Blues Society Video IG | C52: 966 | D52: 32 interactions
A53: 45883 | B53: KC Blues Society Video FB | C53: 1895 | D53: 19 interactions, 61 link clicks
A54: 45881 | B54: CS1 Nora Video IG | C54: 3290 | D54: 42 interactions
A55: 45881 | B55: CS1 Nora Video FB | C55: 1785 | D55: 42 interactions
A56: 45876 | B56: Orchestra Games IG | C56: 2394 | D56: 54 interactions
A57: 45876 | B57: Orchestra Games FB | C57: 1879 | D57: 15 interactions, 2 link clicks
A58: 45876 | B58: Morgan Freeman interview reshare FB | C58: 2731 | D58: 52 interactions, 53 link clicks
A59: 45875 | B59: Nora Intro IG | C59: 3331 | D59: 65 interactions
... A84: 45856 | B84: Music is for Everyone YT | C84: 32 | D84: 1 interaction
B86: Meta Ads
A87: 45832 | B87: Specials/Films ad | C87: 1k impressions | D87: 18 clicks
A88: 45838 | B88: Morgan Freeman video | C88: 22k impressions | D88: 1234 link clicks
A89: 45841 | B89: Holiday concerts ad | C89: 68k impressions | D89: 1011 link clicks

Sheet Website Reporting
A1: Timeframe: August 11-18
A2: ECOMMERCE PURCHASES: 877 | B2: WEBSITE REVENUE: $74,429 | C2: # OF ITEMS
A3: Morgan Freeman | B3: 18052 | C3: 164
A4: Music of Journey | B4: 8322 | C4: 66
A5: Top Gun | B5: 7065 | C5: 86
A6: Leslie Odom Jr. | B6: 4084.5 | C6: 54
A7: Indiana Jones | B7: 3441 | C7: 38
A8: Elf in Concert | B8: 2892 | C8: 44
A9: Harry Potter | B9: 2521 | C9: 29
A10: It's a wonderful life | B10: 2454 | C10: 52
A12: Timeframe: July 20-July 28
A13: ECOMMERCE PURCHASES: 973 | B13: WEBSITE REVENUE: $67,220 | C13: # OF ITEMS
A14: Leslie Odom Jr. | B14: 17681 | C14: 161
A15: Morgan Freeman | B15: 7995 | C15: 64
A16: Top Gun | B16: 5293 | C16: 64
A17: 2025/26 COY Package | B17: 4084 | C17: 54
A18: It's a wonderful life | B18: 2684 | C18: 31
A19: Elf in Concert | B19: 2343 | C19: 26
A20: Christmas Festival | B20: 2341 | C20: 38
A21: La nuit sombre | B21: 2308 | C21: 49
A22: Harry Potter 2 | B22: 2030 | C22: 26
A23: Indiana Jones | B23: 2004 | C23: 26
A27: Timeframe: July 20-July 28
A28: ECOMMERCE PURCHASES: 1,718 | B28: WEBSITE REVENUE: $115,644 | C28: # OF ITEMS
A29: Morgan Freeman | B29: 27675 | C29: 215
A30: Top Gun | B30: 9650 | C30: 116
A31: It's a wonderful life | B31: 8677 | C31: 104
A32: Leslie Odom Jr. | B32: 9110 | C32: 84
A33: Elf in Concert | B33: 5110 | C33: 80
A34: 2025/26 COY Package | B34: 5435 | C34: 73
A35: Harry Potter 2 | B35: 5145 | C35: 61
A36: 2025/26 Sunday Masterworks | B36: 4200 | C36: 56
A37: Handel's Messiah | B37: 2970 | C37: 55
A43: Timeframe: July 14-July 20
A44: ECOMMERCE PURCHASES: 3,027 | B44: WEBSITE REVENUE: $188,688 | C44: # OF ITEMS
A45: Top Gun | B45: 19205 | C45: 234
A46: Morgan Freeman | B46: 16175 | C46: 130
A47: Leslie Odom Jr. | B47: 14107 | C47: 139
A48: Indiana Jones | B48: 12729 | C48: 186
A49: Billy Joel + Elton John | B49: 11391 | C49: 149
A50: Elf | B50: 11075 | C50: 168
A51: Harry Potter | B51: 10715 | C51: 155
A52: It's a wonderful life | B52: 9126 | C52: 129
A53: Music of Journey | B53: 6150 | C53: 91
A54: Ben Rector | B54: 6140 | C54: 60
A56: Traffic Acquistion
A57: SOURCE | B57: SESSIONS
A58: Organic Search
A59: Direct
A60: Paid Social
A61: Referral
A62: Organic Social

Sheet Grassroots Flyer Locations
A1: MF Location | B1: MF Staff Member | C1: Date Posted | E1: CF Location | F1: CF Staff Member | G1: Date Posted | I1: Fam Location | J1: Fam Staff Member | K1: Date Posted
A2: Mildreds (NO CORKBOARD)
A3: Pizza Shuttle | B3: Stephen, Sarah and Adeca | C3: 45870
A4: The Bauer Gallery | B4: Stephen, Sarah and Adeca | C4: 45870
A5: Bizz and Weezy's | B5: Stephen, Sarah and Adeca | C5: 45870
A6: The Sewing Labs | B6: Sarah | C6: 45875
A7: Filling Station - Midtown | B7: Hannah | C7: 45875
A8: Good Karma Coffee Shop | B8: Hannah | C8: 45875

Sheet Board
M1: Revised 9.17.25
A3: TICKET SALES REPORT as of 9/17/2025 | E3: SINGLE TICKETS | I3: SUBSCRIPTION TICKETS | L3: TOTAL SALES (Singles + Subs) | O3: Hall Data
A4: SERIES | D4: DATE(S) | E4: BUDGET | F4: ACTUAL | G4: VS. BUDGET | H4: # SOLD | I4: BUDGET | J4: ACTUAL | K4: # SOLD | L4: BUDGET | M4: ACTUAL | N4: # SOLD | O4: CAP | P4: CAP SOLD | Q4: ATP
A5: CLASSICAL TRADITIONAL
A6: CS1 | B6: Appalachian Spring | D6: Oct 10-12 | E6: =SUM('Performances by Week'!Z15:Z17) -> 50000 | F6: =SUM('Performances by Week'!Y15:Y17) -> 105443 | G6: =F6-E6 -> 55443 | H6: =SUM('Performances by Week'!S15:S17) -> 2023 | I6: =SUM('Performances by Week'!AE15:AE17) -> 100000 | J6: =SUM('Performances by Week'!AD15:AD17) -> 97347.9 | K6: =SUM('Performances by Week'!AC15:AC17) -> 1419 | L6: =SUM(E6,I6) -> 150000 | M6: =SUM(F6,J6) -> 202790.9 | N6: =SUM(H6,K6) -> 3442 | O6: =SUM('Performances by Week'!AG15:AG17) -> 4299 | P6: =N6/O6 -> 0.80065131 | Q6: =M6/N6 -> 58.916589
A7: CS2 | B7: Rachmaninoff Cele Pt 1 (SP) | D7: Oct 31-Nov 2 | E7: =SUM('Performances by Week'!Z26:Z28) -> 85000 | F7: =SUM('Performances by Week'!Y26:Y28) -> 93478 | G7: =F7-E7 -> 8478 | H7: =SUM('Performances by Week'!S26:S28) -> 1735 | I7: =SUM('Performances by Week'!AE26:AE28) -> 140000 | J7: =SUM('Performances by Week'!AD26:AD28) -> 89640 | K7: =SUM('Performances by Week'!AC26:AC28) -> 1351 | L7: =SUM(E7,I7) -> 225000 | M7: =SUM(F7,J7) -> 183118 | N7: =SUM(H7,K7) -> 3086 | O7: =SUM('Performances by Week'!AG26:AG28) -> 4350 | P7: =N7/O7 -> 0.70942529 | Q7: =M7/N7 -> 59.338302
A8: CS3 | B8: Matthias and Mahler (SP) | D8: Nov 21-23 | E8: =SUM('Performances by Week'!Z31:Z33) -> 38000 | F8: =SUM('Performances by Week'!Y31:Y33) -> 34358 | G8: =F8-E8 -> -3642 | H8: =SUM('Performances by Week'!S31:S33) -> 603 | I8: =SUM('Performances by Week'!AE31:AE33) -> 135000 | J8: =SUM('Performances by Week'!AD31:AD33) -> 102648 | K8: =SUM('Performances by Week'!AC31:AC33) -> 1529 | L8: =SUM(E8,I8) -> 173000 | M8: =SUM(F8,J8) -> 137006 | N8: =SUM(H8,K8) -> 2132 | O8: =SUM('Performances by Week'!AG31:AG33) -> 4821 | P8: =N8/O8 -> 0.4422319 | Q8: =M8/N8 -> 64.261726
A9: CS4 | B9: Brahms' Fourth Symphony | D9: Jan 9-11 | E9: =SUM('Performances by Week'!Z52:Z54) -> 65000 | F9: =SUM('Performances by Week'!Y52:Y54) -> 11711 | G9: =F9-E9 -> -53289 | H9: =SUM('Performances by Week'!S52:S54) -> 241 | I9: =SUM('Performances by Week'!AE52:AE54) -> 100000 | J9: =SUM('Performances by Week'!AD52:AD54) -> 110925 | K9: =SUM('Performances by Week'!AC52:AC54) -> 1682 | L9: =SUM(E9,I9) -> 165000 | M9: =SUM(F9,J9) -> 122636 | N9: =SUM(H9,K9) -> 1923 | O9: =SUM('Performances by Week'!AG52:AG54) -> 4770 | P9: =N9/O9 -> 0.40314465 | Q9: =M9/N9 -> 63.773271
A10: CS5 | B10: Pines of Rome & Bruch (SP) | D10: Jan 16-18 | E10: =SUM('Performances by Week'!Z55:Z57) -> 70000 | F10: =SUM('Performances by Week'!Y55:Y57) -> 16249 | G10: =F10-E10 -> -53751 | H10: =SUM('Performances by Week'!S55:S57) -> 270 | I10: =SUM('Performances by Week'!AE55:AE57) -> 140000 | J10: =SUM('Performances by Week'!AD55:AD57) -> 104865.1 | K10: =SUM('Performances by Week'!AC55:AC57) -> 1576 | L10: =SUM(E10,I10) -> 210000 | M10: =SUM(F10,J10) -> 121114.1 | N10: =SUM(H10,K10) -> 1846 | O10: =SUM('Performances by Week'!AG55:AG57) -> 4770 | P10: =N10/O10 -> 0.3870021 | Q10: =M10/N10 -> 65.608938
A11: CS6 | B11: Beethoven+ (SP) | D11: Jan 30-Feb 1 | E11: =SUM('Performances by Week'!Z62:Z64) -> 64000 | F11: =SUM('Performances by Week'!Y62:Y64) -> 14060 | G11: =F11-E11 -> -49940 | H11: =SUM('Performances by Week'!S62:S64) -> 237 | I11: =SUM('Performances by Week'!AE62:AE64) -> 140000 | J11: =SUM('Performances by Week'!AD62:AD64) -> 103801.1 | K11: =SUM('Performances by Week'!AC62:AC64) -> 1571 | L11: =SUM(E11,I11) -> 204000 | M11: =SUM(F11,J11) -> 117861.1 | N11: =SUM(H11,K11) -> 1808 | O11: =SUM('Performances by Week'!AG62:AG64) -> 4770 | P11: =N11/O11 -> 0.37903564 | Q11: =M11/N11 -> 65.188662
A12: CS7 | B12: Prokofiev's Fifth Symphony | D12: Feb 6-8 | E12: =SUM('Performances by Week'!Z66:Z68) -> 40000 | F12: =SUM('Performances by Week'!Y66:Y68) -> 6940 | G12: =F12-E12 -> -33060 | H12: =SUM('Performances by Week'!S66:S68) -> 155 | I12: =SUM('Performances by Week'!AE66:AE68) -> 100000 | J12: =SUM('Performances by Week'!AD66:AD68) -> 109967.3 | K12: =SUM('Performances by Week'!AC66:AC68) -> 1683 | L12: =SUM(E12,I12) -> 140000 | M12: =SUM(F12,J12) -> 116907.3 | N12: =SUM(H12,K12) -> 1838 | O12: =SUM('Performances by Week'!AG66:AG68) -> 4770 | P12: =N12/O12 -> 0.38532495 | Q12: =M12/N12 -> 63.605713
A13: CS8 | B13: Saint-Saëns & Strauss | D13: Mar 13-15 | E13: =SUM('Performances by Week'!Z79:Z81) -> 55000 | F13: =SUM('Performances by Week'!Y79:Y81) -> 10846 | G13: =F13-E13 -> -44154 | H13: =SUM('Performances by Week'!S79:S81) -> 190 | I13: =SUM('Performances by Week'!AE79:AE81) -> 110000 | J13: =SUM('Performances by Week'!AD79:AD81) -> 111505.3 | K13: =SUM('Performances by Week'!AC79:AC81) -> 1708 | L13: =SUM(E13,I13) -> 165000 | M13: =SUM(F13,J13) -> 122351.3 | N13: =SUM(H13,K13) -> 1898 | O13: =SUM('Performances by Week'!AG79:AG81) -> 4770 | P13: =N13/O13 -> 0.39790356 | Q13: =M13/N13 -> 64.463277
A14: CS9 | B14: Midsummer Night's Dream (SP) | D14: Apr 10-12 | E14: =SUM('Performances by Week'!Z89:Z91) -> 70000 | F14: =SUM('Performances by Week'!Y89:Y91) -> 10472 | G14: =F14-E14 -> -59528 | H14: =SUM('Performances by Week'!S89:S91) -> 219 | I14: =SUM('Performances by Week'!AE89:AE91) -> 130000 | J14: =SUM('Performances by Week'!AD89:AD91) -> 98992.1 | K14: =SUM('Performances by Week'!AC89:AC91) -> 1505 | L14: =SUM(E14,I14) -> 200000 | M14: =SUM(F14,J14) -> 109464.1 | N14: =SUM(H14,K14) -> 1724 | O14: =SUM('Performances by Week'!AG89:AG91) -> 4299 | P14: =N14/O14 -> 0.40102349 | Q14: =M14/N14 -> 63.494258
A15: CS10 | B15: Farrenc/Dvorak/Schuman | D15: Apr 17-19 | E15: =SUM('Performances by Week'!Z92:Z94) -> 40000 | F15: =SUM('Performances by Week'!Y92:Y94) -> 4229 | G15: =F15-E15 -> -35771 | H15: =SUM('Performances by Week'!S92:S94) -> 103 | I15: =SUM('Performances by Week'!AE92:AE94) -> 100000 | J15: =SUM('Performances by Week'!AD92:AD94) -> 119099.1 | K15: =SUM('Performances by Week'!AC92:AC94) -> 1789 | L15: =SUM(E15,I15) -> 140000 | M15: =SUM(F15,J15) -> 123328.1 | N15: =SUM(H15,K15) -> 1892 | O15: =SUM('Performances by Week'!AG92:AG94) -> 4770 | P15: =N15/O15 -> 0.3966457 | Q15: =M15/N15 -> 65.183985
A16: CS11 | B16: Grieg's Piano Concerto (SP) | D16: May 8-10 | E16: =SUM('Performances by Week'!Z97:Z99) -> 55000 | F16: =SUM('Performances by Week'!Y97:Y99) -> 11439 | G16: =F16-E16 -> -43561 | H16: =SUM('Performances by Week'!S97:S99) -> 208 | I16: =SUM('Performances by Week'!AE97:AE99) -> 120000 | J16: =SUM('Performances by Week'!AD97:AD99) -> 105674.1 | K16: =SUM('Performances by Week'!AC97:AC99) -> 1585 | L16: =SUM(E16,I16) -> 175000 | M16: =SUM(F16,J16) -> 117113.1 | N16: =SUM(H16,K16) -> 1793 | O16: =SUM('Performances by Week'!AG97:AG99) -> 4770 | P16: =N16/O16 -> 0.37589099 | Q16: =M16/N16 -> 65.316843
A17: CS12 | B17: Gil Shaham Plays Brahm's 4th | D17: May 29-31 | E17: =SUM('Performances by Week'!Z107:Z109) -> 60000 | F17: =SUM('Performances by Week'!Y107:Y109) -> 6544 | G17: =F17-E17 -> -53456 | H17: =SUM('Performances by Week'!S107:S109) -> 162 | I17: =SUM('Performances by Week'!AE107:AE109) -> 95000 | J17: =SUM('Performances by Week'!AD107:AD109) -> 112084.5 | K17: =SUM('Performances by Week'!AC107:AC109) -> 1713 | L17: =SUM(E17,I17) -> 155000 | M17: =SUM(F17,J17) -> 118628.5 | N17: =SUM(H17,K17) -> 1875 | O17: =SUM('Performances by Week'!AG107:AG109) -> 4770 | P17: =N17/O17 -> 0.39308176 | Q17: =M17/N17 -> 63.268533
A18: CS13 | B18: Rachmaninoff Cele Pt 2 | D18: Jun 5-7 | E18: =SUM('Performances by Week'!Z111:Z113) -> 90000 | F18: =SUM('Performances by Week'!Y111:Y113) -> 13110 | G18: =F18-E18 -> -76890 | H18: =SUM('Performances by Week'!S111:S113) -> 225 | I18: =SUM('Performances by Week'!AE111:AE113) -> 110000 | J18: =SUM('Performances by Week'!AD111:AD113) -> 119909.5 | K18: =SUM('Performances by Week'!AC111:AC113) -> 1809 | L18: =SUM(E18,I18) -> 200000 | M18: =SUM(F18,J18) -> 133019.5 | N18: =SUM(H18,K18) -> 2034 | O18: =SUM('Performances by Week'!AG111:AG113) -> 4770 | P18: =N18/O18 -> 0.42641509 | Q18: =M18/N18 -> 65.397984
A19: CS14 | B19: Rhapsody in Blue (SP) | D19: Jun 19-21 | E19: =SUM('Performances by Week'!Z115:Z117) -> 85000 | F19: =SUM('Performances by Week'!Y115:Y117) -> 30540 | G19: =F19-E19 -> -54460 | H19: =SUM('Performances by Week'!S115:S117) -> 518 | I19: =SUM('Performances by Week'!AE115:AE117) -> 115000 | J19: =SUM('Performances by Week'!AD115:AD117) -> 101226 | K19: =SUM('Performances by Week'!AC115:AC117) -> 1538 | L19: =SUM(E19,I19) -> 200000 | M19: =SUM(F19,J19) -> 131766 | N19: =SUM(H19,K19) -> 2056 | O19: =SUM('Performances by Week'!AG115:AG117) -> 4770 | P19: =N19/O19 -> 0.43102725 | Q19: =M19/N19 -> 64.088521
A20: CLASSICAL TRADITIONAL TOTAL | E20: =SUM(E6:E19) -> 867000 | F20: =SUM(F6:F19) -> 369419 | G20: =F20-E20 -> -497581 | H20: =SUM(H6:H19) -> 6889 | I20: =SUM(I6:I19) -> 1635000 | J20: =SUM(J6:J19) -> 1487685 | K20: =SUM(K6:K19) -> 22458 | L20: =SUM(L6:L19) -> 2502000 | M20: =SUM(F20,J20) -> 1857104 | N20: =SUM(N6:N19) -> 29347 | O20: =SUM(O6:O19) -> 65469 | P20: =N20/O20 -> 0.44825795 | Q20: =M20/N20 -> 63.28088
A22: SYMPHONIC PIAZZA
A23: Piazza CS2 | B23: =B7 -> Rachmaninoff Cele Pt 1 (SP) | D23: Oct 31 | E23: ='Performances by Week'!$Z$26 -> 22000 | F23: ='Performances by Week'!$Y$26 -> 15733 | G23: =F23-E23 -> -6267 | H23: ='Performances by Week'!$S$26 -> 330 | I23: ='Performances by Week'!$AE$26 -> 30000 | J23: ='Performances by Week'!$AD$26 -> 21329 | K23: ='Performances by Week'!$AC$26 -> 308 | L23: =SUM(E23,I23) -> 52000 | M23: =SUM(F23,J23) -> 37062 | N23: =SUM(H23,K23) -> 638 | O23: ='Performances by Week'!$AG$115 -> 1590 | P23: =N23/O23 -> 0.40125786 | Q23: =M23/N23 -> 58.090909
A24: Piazza CS3 | B24: =B8 -> Matthias and Mahler (SP) | D24: Nov 21 | E24: ='Performances by Week'!$Z$31 -> 15000 | F24: ='Performances by Week'!$Y$31 -> 9356 | G24: =F24-E24 -> -5644 | H24: ='Performances by Week'!$S$31 -> 180 | I24: ='Performances by Week'!$AE$31 -> 25000 | J24: ='Performances by Week'!$AD$31 -> 24786 | K24: ='Performances by Week'!$AC$31 -> 357 | L24: =SUM(E24,I24) -> 40000 | M24: =SUM(F24,J24) -> 34142 | N24: =SUM(H24,K24) -> 537 | O24: ='Performances by Week'!$AG$31 -> 1607 | P24: =N24/O24 -> 0.33416304 | Q24: =M24/N24 -> 63.579143
A25: Piazza CS5 | B25: =B10 -> Pines of Rome & Bruch (SP) | D25: Jan 16 | E25: ='Performances by Week'!$Z$55 -> 30000 | F25: ='Performances by Week'!$Y$55 -> 2960 | G25: =F25-E25 -> -27040 | H25: ='Performances by Week'!$S$55 -> 51 | I25: ='Performances by Week'!$AE$55 -> 30000 | J25: ='Performances by Week'!$AD$55 -> 25342 | K25: ='Performances by Week'!$AC$55 -> 368 | L25: =SUM(E25,I25) -> 60000 | M25: =SUM(F25,J25) -> 28302 | N25: =SUM(H25,K25) -> 419 | O25: ='Performances by Week'!$AG$55 -> 1590 | P25: =N25/O25 -> 0.26352201 | Q25: =M25/N25 -> 67.546539
A26: Piazza CS6 | B26: =B11 -> Beethoven+ (SP) | D26: Jan 30 | E26: ='Performances by Week'!$Z$62 -> 24000 | F26: ='Performances by Week'!$Y$62 -> 3847 | G26: =F26-E26 -> -20153 | H26: ='Performances by Week'!$S$62 -> 71 | I26: ='Performances by Week'!$AE$62 -> 30000 | J26: ='Performances by Week'!$AD$62 -> 24869 | K26: ='Performances by Week'!$AC$62 -> 364 | L26: =SUM(E26,I26) -> 54000 | M26: =SUM(F26,J26) -> 28716 | N26: =SUM(H26,K26) -> 435 | O26: ='Performances by Week'!$AG$62 -> 1590 | P26: =N26/O26 -> 0.27358491 | Q26: =M26/N26 -> 66.013793
A27: Piazza CS9 | B27: =B14 -> Midsummer Night's Dream (SP) | D27: Apr 10 | E27: ='Performances by Week'!$Z$89 -> 22000 | F27: ='Performances by Week'!$Y$89 -> 2411 | G27: =F27-E27 -> -19589 | H27: ='Performances by Week'!$S$89 -> 52 | I27: ='Performances by Week'!$AE$89 -> 30000 | J27: ='Performances by Week'!$AD$89 -> 25714 | K27: ='Performances by Week'!$AC$89 -> 368 | L27: =SUM(E27,I27) -> 52000 | M27: =SUM(F27,J27) -> 28125 | N27: =SUM(H27,K27) -> 420 | O27: ='Performances by Week'!$AG$89 -> 1433 | P27: =N27/O27 -> 0.29309142 | Q27: =M27/N27 -> 66.964286
A28: Piazza CS11 | B28: =B16 -> Grieg's Piano Concerto (SP) | D28: May 8 | E28: ='Performances by Week'!$Z$97 -> 20000 | F28: ='Performances by Week'!$Y$97 -> 2349 | G28: =F28-E28 -> -17651 | H28: ='Performances by Week'!$S$97 -> 50 | I28: ='Performances by Week'!$AE$97 -> 25000 | J28: ='Performances by Week'!$AD$97 -> 25763 | K28: ='Performances by Week'!$AC$97 -> 374 | L28: =SUM(E28,I28) -> 45000 | M28: =SUM(F28,J28) -> 28112 | N28: =SUM(H28,K28) -> 424 | O28: ='Performances by Week'!$AG$97 -> 1590 | P28: =N28/O28 -> 0.26666667 | Q28: =M28/N28 -> 66.301887
A29: Piazza CS14 | B29: =B19 -> Rhapsody in Blue (SP) | D29: Jun 19 | E29: ='Performances by Week'!$Z$115 -> 30000 | F29: ='Performances by Week'!$Y$115 -> 6390 | G29: =F29-E29 -> -23610 | H29: ='Performances by Week'!$S$115 -> 111 | I29: ='Performances by Week'!$AE$115 -> 30000 | J29: ='Performances by Week'!$AD$115 -> 26279 | K29: ='Performances by Week'!$AC$115 -> 380 | L29: =SUM(E29,I29) -> 60000 | M29: =SUM(F29,J29) -> 32669 | N29: =SUM(H29,K29) -> 491 | O29: ='Performances by Week'!$AG$115 -> 1590 | P29: =N29/O29 -> 0.30880503 | Q29: =M29/N29 -> 66.535642
A30: SYMPHONIC PIAZZA TOTAL | E30: =SUM(E23:E29) -> 163000 | F30: =SUM(F23:F29) -> 43046 | G30: =SUM(G23:G29) -> -119954 | H30: =SUM(H23:H29) -> 845 | I30: =SUM(I23:I29) -> 200000 | J30: =SUM(J23:J29) -> 174082 | K30: =SUM(K23:K29) -> 2519 | L30: =SUM(L23:L29) -> 363000 | ... O30: =SUM(O23:O29) -> 10990 | P30: =N30/O30 -> 0.30609645 | Q30: =M30/N30 -> 64.54459
A32: POPS
A33: PS1 | B33: Music of Journey | D33: Sep 19-21 | E33: =SUM('Performances by Week'!$Z$10:$Z$12) -> 178000 | F33: =SUM('Performances by Week'!$Y$10:$Y$12) -> 105385 | G33: =F33-E33 -> -72615 | H33: =SUM('Performances by Week'!$S$10:$S$12) -> 1724 | I33: =SUM('Performances by Week'!$AE$10:$AE$12) -> 124000 | J33: =SUM('Performances by Week'!$AD$10:$AD$12) -> 108064.7 | K33: =SUM('Performances by Week'!$AC$10:$AC$12) -> 1473 | L33: =SUM(E33,I33) -> 302000 | M33: =SUM(F33,J33) -> 213449.7 | N33: =SUM(H33,K33) -> 3197 | O33: =SUM('Performances by Week'!$AG$10:$AG$12) -> 4770 | P33: =N33/O33 -> 0.67023061 | Q33: =M33/N33 -> 66.765624
A34: PS2 | B34: 90s Mixtape | D34: Oct 24-26 | E34: =SUM('Performances by Week'!$Z$22:$Z$24) -> 160000 | F34: =SUM('Performances by Week'!$Y$22:$Y$24) -> 62374 | G34: =F34-E34 -> -97626 | H34: =SUM('Performances by Week'!$S$22:$S$24) -> 1287 | I34: =SUM('Performances by Week'!$AE$22:$AE$24) -> 117000 | J34: =SUM('Performances by Week'!$AD$22:$AD$24) -> 109033 | K34: =SUM('Performances by Week'!$AC$22:$AC$24) -> 1503 | L34: =SUM(E34,I34) -> 277000 | M34: =SUM(F34,J34) -> 171407 | N34: =SUM(H34,K34) -> 2790 | O34: =SUM('Performances by Week'!$AG$22:$AG$24) -> 4803 | P34: =N34/O34 -> 0.58088695 | Q34: =M34/N34 -> 61.436201
A35: PS3 | B35: She's Got Soul | D35: Feb 13-15 | E35: =SUM('Performances by Week'!$Z$70:$Z$72) -> 160000 | F35: =SUM('Performances by Week'!$Y$70:$Y$72) -> 10200 | G35: =F35-E35 -> -149800 | H35: =SUM('Performances by Week'!$S$70:$S$72) -> 175 | I35: =SUM('Performances by Week'!$AE$70:$AE$72) -> 124000 | J35: =SUM('Performances by Week'!$AD$70:$AD$72) -> 126157.2 | K35: =SUM('Performances by Week'!$AC$70:$AC$72) -> 1771 | L35: =SUM(E35,I35) -> 284000 | M35: =SUM(F35,J35) -> 136357.2 | N35: =SUM(H35,K35) -> 1946 | O35: =SUM('Performances by Week'!$AG$70:$AG$72) -> 4770 | P35: =N35/O35 -> 0.40796646 | Q35: =M35/N35 -> 70.070504
A36: PS4 | B36: Billy Joel & Elton John | D36: Mar 27-29 | E36: =SUM('Performances by Week'!$Z$85:$Z$87) -> 160000 | F36: =SUM('Performances by Week'!$Y$85:$Y$87) -> 40766 | G36: =F36-E36 -> -119234 | H36: =SUM('Performances by Week'!$S$85:$S$87) -> 579 | I36: =SUM('Performances by Week'!$AE$85:$AE$87) -> 124000 | J36: =SUM('Performances by Week'!$AD$85:$AD$87) -> 128191.5 | K36: =SUM('Performances by Week'!$AC$85:$AC$87) -> 1798 | L36: =SUM(E36,I36) -> 284000 | M36: =SUM(F36,J36) -> 168957.5 | N36: =SUM(H36,K36) -> 2377 | O36: =SUM('Performances by Week'!$AG$85:$AG$87) -> 4770 | P36: =N36/O36 -> 0.49832285 | Q36: =M36/N36 -> 71.080143
A37: PS5 | B37: Dolly Parton's Threads | D37: May 15-17 | E37: =SUM('Performances by Week'!$Z$100:$Z$102) -> 180000 | F37: =SUM('Performances by Week'!$Y$100:$Y$102) -> 19555 | G37: =F37-E37 -> -160445 | H37: =SUM('Performances by Week'!$S$100:$S$102) -> 256 | I37: =SUM('Performances by Week'!$AE$100:$AE$102) -> 130000 | J37: =SUM('Performances by Week'!$AD$100:$AD$102) -> 150672 | K37: =SUM('Performances by Week'!$AC$100:$AC$102) -> 1801 | L37: =SUM(E37,I37) -> 310000 | M37: =SUM(F37,J37) -> 170227 | N37: =SUM(H37,K37) -> 2057 | O37: =SUM('Performances by Week'!$AG$100:$AG$102) -> 3906 | P37: =N37/O37 -> 0.5266257 | Q37: =M37/N37 -> 82.754983
A38: POPS TOTAL | E38: =SUM(E33:E37) -> 838000 | F38: =SUM(F33:F37) -> 238280 | G38: =SUM(G33:G37) -> -599720 | H38: =SUM(H33:H37) -> 4021 | I38: =SUM(I33:I37) -> 619000 | J38: =SUM(J33:J37) -> 622118.4 | K38: =SUM(K33:K37) -> 8346 | L38: =SUM(L33:L37) -> 1457000 | ... O38: =SUM(O33:O37) -> 23019 | P38: =N38/O38 -> 0.53725184 | Q38: =M38/N38 -> 69.572119
A40: FAMILY
A41: FS1 | B41: The Orchestra Games | D41: Sep 28 | E41: ='Performances by Week'!$Z$13 -> 10000 | F41: ='Performances by Week'!$Y$13 -> 10721 | G41: =F41-E41 -> 721 | H41: ='Performances by Week'!$S$13 -> 503 | I41: ='Performances by Week'!$AE$13 -> 9500 | J41: ='Performances by Week'!$AD$13 -> 5975 | K41: ='Performances by Week'!$AC$13 -> 218 | L41: =SUM(E41,I41) -> 19500 | M41: =SUM(F41,J41) -> 16696 | N41: =SUM(H41,K41) -> 721 | O41: ='Performances by Week'!$AG$13 -> 1302 | P41: =N41/O41 -> 0.55376344 | Q41: =M41/N41 -> 23.156727
A42: FS2 | B42: Carnival of the Animals | D42: Nov 9 | E42: ='Performances by Week'!$Z$29 -> 10000 | F42: ='Performances by Week'!$Y$29 -> 8032 | G42: =F42-E42 -> -1968 | H42: ='Performances by Week'!$S$29 -> 256 | I42: ='Performances by Week'!$AE$29 -> 9500 | J42: ='Performances by Week'!$AD$29 -> 7594 | K42: ='Performances by Week'!$AC$29 -> 329 | L42: =SUM(E42,I42) -> 19500 | M42: =SUM(F42,J42) -> 15626 | N42: =SUM(H42,K42) -> 585 | O42: ='Performances by Week'!$AG$29 -> 1380 | P42: =N42/O42 -> 0.42391304 | Q42: =M42/N42 -> 26.711111
A43: Holiday | B43: Christmas Festival | D43: Dec 18-21 | E43: =SUM('Performances by Week'!$Z$43:$Z$48) -> 455000 | F43: =SUM('Performances by Week'!$Y$43:$Y$48) -> 138499 | G43: =F43-E43 -> -316501 | H43: =SUM('Performances by Week'!$S$43:$S$48) -> 2316 | I43: =SUM('Performances by Week'!$AE$43:$AE$48) -> 12450 | J43: =SUM('Performances by Week'!$AD$43:$AD$48) -> 7226 | K43: =SUM('Performances by Week'!$AC$43:$AC$48) -> 315 | L43: =SUM(E43,I43) -> 467450 | M43: =SUM(F43,J43) -> 145725 | N43: =SUM(H43,K43) -> 2631 | O43: =SUM('Performances by Week'!$AG$43:$AG$48) -> 8598 | P43: =N43/O43 -> 0.3060014 | Q43: =M43/N43 -> 55.387685
A44: FS3 | B44: Philharmonia Fantastique | D44: Mar 1 | E44: ='Performances by Week'!$Z$77 -> 10000 | F44: ='Performances by Week'!$Y$77 -> 1461 | G44: =F44-E44 -> -8539 | H44: ='Performances by Week'!$S$77 -> 50 | I44: ='Performances by Week'!$AE$77 -> 9500 | J44: ='Performances by Week'!$AD$77 -> 6836 | K44: ='Performances by Week'!$AC$77 -> 307 | L44: =SUM(E44,I44) -> 19500 | M44: =SUM(F44,J44) -> 8297 | N44: =SUM(H44,K44) -> 357 | O44: ='Performances by Week'!$AG$77 -> 1302 | P44: =N44/O44 -> 0.27419355 | Q44: =M44/N44 -> 23.240896
A45: FAMILY SERIES TOTAL | E45: =SUM(E41:E44) -> 485000 | F45: =SUM(F41:F44) -> 158713 | G45: =F45-E45 -> -326287 | H45: =SUM(H41:H44) -> 3125 | I45: =SUM(I41:I44) -> 40950 | J45: =SUM(J41:J44) -> 27631 | K45: =SUM(K41:K44) -> 1169 | L45: =SUM(L41:L44) -> 525950 | M45: =SUM(M41:M44) -> 186344 | N45: =SUM(N41:N44) -> 4294 | O45: =SUM(O41:O44) -> 12582 | P45: =N45/O45 -> 0.3412812 | Q45: =M45/N45 -> 43.396367
A47: FILM
A48: Top Gun: Maverick in Concert | D48: Oct 17-19 | E48: =SUM('Performances by Week'!$Z$18:$Z$20) -> 310490 | F48: =SUM('Performances by Week'!$Y$18:$Y$20) -> 263278 | G48: =F48-E48 -> -47212 | H48: =SUM('Performances by Week'!$S$18:$S$20) -> 3444 | I48: $ - | J48: $ - | K48: - | L48: =SUM(E48,I48) -> 310490 | M48: =SUM(F48,J48) -> 263278 | N48: =SUM(H48,K48) -> 3444 | O48: =SUM('Performances by Week'!$AG$18:$AG$20) -> 4026 | P48: =N48/O48 -> 0.85543964 | Q48: =M48/N48 -> 76.445412
A49: The Lodger | D49: Oct 22 | E49: ='Performances by Week'!$Z$21 -> 50000 | F49: ='Performances by Week'!$Y$21 -> 19285 | G49: =F49-E49 -> -30715 | H49: ='Performances by Week'!$S$21 -> 377 | I49: $ - | J49: $ - | K49: - | L49: =SUM(E49,I49) -> 50000 | M49: =SUM(F49,J49) -> 19285 | N49: =SUM(H49,K49) -> 377 | O49: ='Performances by Week'!$AG$21 -> 1342 | P49: =N49/O49 -> 0.28092399 | Q49: =M49/N49 -> 51.153846
A50: Elf™ in Concert | D50: Nov 28-30 | E50: =SUM('Performances by Week'!$Z$34:$Z$37) -> 430000 | F50: =SUM('Performances by Week'!$Y$34:$Y$37) -> 208664 | G50: =F50-E50 -> -221336 | H50: =SUM('Performances by Week'!$S$34:$S$37) -> 3005 | I50: $ - | J50: $ - | K50: - | L50: =SUM(E50,I50) -> 430000 | M50: =SUM(F50,J50) -> 208664 | N50: =SUM(H50,K50) -> 3005 | O50: =SUM('Performances by Week'!$AG$34:$AG$37) -> 5208 | P50: =N50/O50 -> 0.57699693 | Q50: =M50/N50 -> 69.438935
A51: It's a Wonderful Life | D51: Dec 23-24 | E51: =SUM('Performances by Week'!$Z$49:$Z$50) -> 200000 | F51: =SUM('Performances by Week'!$Y$49:$Y$50) -> 128295 | G51: =F51-E51 -> -71705 | H51: =SUM('Performances by Week'!$S$49:$S$50) -> 1582 | I51: $ - | J51: $ - | K51: - | L51: =SUM(E51,I51) -> 200000 | M51: =SUM(F51,J51) -> 128295 | N51: =SUM(H51,K51) -> 1582 | O51: =SUM('Performances by Week'!$AG$49:$AG$50) -> 2604 | P51: =N51/O51 -> 0.60752688 | Q51: =M51/N51 -> 81.096713
A52: Indiana Jones: Raiders Lost | D52: Jan 22-25 | E52: =SUM('Performances by Week'!$Z$58:$Z$61) -> 360000 | F52: =SUM('Performances by Week'!$Y$58:$Y$61) -> 93772.1 | G52: =F52-E52 -> -266227.9 | H52: =SUM('Performances by Week'!$S$58:$S$61) -> 1322 | I52: $ - | J52: $ - | K52: - | L52: =SUM(E52,I52) -> 360000 | M52: =SUM(F52,J52) -> 93772.1 | N52: =SUM(H52,K52) -> 1322 | O52: =SUM('Performances by Week'!$AG$58:$AG$61) -> 5208 | P52: =N52/O52 -> 0.25384025 | Q52: =M52/N52 -> 70.931997
A53: Harry Potter 2: Chamber | D53: Feb 19-22 | E53: =SUM('Performances by Week'!$Z$73:$Z$76) -> 445000 | F53: =SUM('Performances by Week'!$Y$73:$Y$76) -> 94720 | G53: =F53-E53 -> -350280 | H53: =SUM('Performances by Week'!$S$73:$S$76) -> 1328 | I53: $ - | J53: $ - | K53: - | L53: =SUM(E53,I53) -> 445000 | M53: =SUM(F53,J53) -> 94720 | N53: =SUM(H53,K53) -> 1328 | O53: =SUM('Performances by Week'!$AG$73:$AG$76) -> 5208 | P53: =N53/O53 -> 0.25499232 | Q53: =M53/N53 -> 71.325301
A54: FILM TOTAL | E54: =SUM(E48:E53) -> 1795490 | F54: =SUM(F48:F53) -> 808014.1 | G54: =SUM(G48:G53) -> -987475.9 | H54: =SUM(H48:H53) -> 11058 | I54: $ - | J54: $ - | K54: - | L54: =SUM(L48:L53) -> 1795490 | M54: =SUM(M48:M53) -> 808014.1 | N54: =SUM(N48:N53) -> 11058 | O54: =SUM(O48:O53) -> 23596 | P54: =N54/O54 -> 0.46863875 | Q54: =M54/N54 -> 73.070546
A56: ON STAGE
A57: George Li | D57: Oct 29 | E57: ='Performances by Week'!$Z$25 -> 11200 | F57: ='Performances by Week'!$Y$25 -> 4620 | G57: =F57-E57 -> -6580 | H57: ='Performances by Week'!$S$25 -> 38 | I57: $ - | J57: $ - | K57: - | L57: =SUM(E57,I57) -> 11200 | M57: =SUM(F57,J57) -> 4620 | N57: =SUM(H57,K57) -> 38 | O57: ='Performances by Week'!$AG$25 -> 100 | P57: =N57/O57 -> 0.38 | Q57: =M57/N57 -> 121.57895
A58: Leila Josefowicz | D58: Feb 5 | E58: ='Performances by Week'!$Z$65 -> 9000 | F58: ='Performances by Week'!$Y$65 -> 1960 | G58: =F58-E58 -> -7040 | H58: ='Performances by Week'!$S$65 -> 19 | I58: $ - | J58: $ - | K58: - | L58: =SUM(E58,I58) -> 9000 | M58: =SUM(F58,J58) -> 1960 | N58: =SUM(H58,K58) -> 19 | O58: ='Performances by Week'!$AG$65 -> 100 | P58: =N58/O58 -> 0.19 | Q58: =M58/N58 -> 103.15789
A59: Gil Shaham | D59: May 28 | E59: ='Performances by Week'!$Z$106 -> 9000 | F59: ='Performances by Week'!$Y$106 -> 1680 | G59: =F59-E59 -> -7320 | H59: ='Performances by Week'!$S$106 -> 17 | I59: $ - | J59: $ - | K59: - | L59: =SUM(E59,I59) -> 9000 | M59: =SUM(F59,J59) -> 1680 | N59: =SUM(H59,K59) -> 17 | O59: ='Performances by Week'!$AG$106 -> 100 | P59: =N59/O59 -> 0.17 | Q59: =M59/N59 -> 98.823529
A60: Yefim Bronfman | D60: Jun 4 | E60: ='Performances by Week'!$Z$110 -> 9000 | F60: ='Performances by Week'!$Y$110 -> 2100 | G60: =F60-E60 -> -6900 | H60: ='Performances by Week'!$S$110 -> 20 | I60: $ - | J60: $ - | K60: - | L60: =SUM(E60,I60) -> 9000 | M60: =SUM(F60,J60) -> 2100 | N60: =SUM(H60,K60) -> 20 | O60: ='Performances by Week'!$AG$110 -> 100 | P60: =N60/O60 -> 0.2 | Q60: =M60/N60 -> 105
A61: ON STAGE CONCERTS TOTAL | E61: =SUM(E57:E60) -> 38200 | F61: =SUM(F57:F60) -> 10360 | G61: =SUM(G57:G60) -> -27840 | H61: =SUM(H57:H60) -> 94 | I61: $ - | J61: $ - | K61: - | L61: =SUM(L57:L60) -> 38200 | M61: =SUM(M57:M60) -> 10360 | N61: =SUM(N57:N60) -> 94 | O61: =SUM(O57:O60) -> 400 | P61: =N61/O61 -> 0.235 | Q61: =M61/N61 -> 110.21277
A63: OTHER CONCERTS
A64: Morgan Freeman Symphonic Blues | D64: Sep 2-3 | E64: =SUM('Performances by Week'!$Z$6:$Z$7) -> 306947 | F64: =SUM('Performances by Week'!$Y$6:$Y$7) -> 272084 | G64: =F64-E64 -> -34863 | H64: =SUM('Performances by Week'!$S$6:$S$7) -> 2299 | I64: $ - | J64: $ - | L64: =SUM(E64,I64) -> 306947 | M64: =SUM(F64,J64) -> 272084 | N64: =SUM(H64,K64) -> 2299 | O64: =SUM('Performances by Week'!$AG$6:$AG$7) -> 2604 | P64: =N64/O64 -> 0.8828725 | Q64: =M64/N64 -> 118.34885
A65: La Nuit Sombre (Four Larks) | D65: Sep 5 | E65: ='Performances by Week'!$Z$8 -> 55000 | F65: ='Performances by Week'!$Y$8 -> 20005 | G65: =F65-E65 -> -34995 | H65: ='Performances by Week'!$S$8 -> 699 | I65: $ - | J65: $ - | L65: =SUM(E65,I65) -> 55000 | M65: =SUM(F65,J65) -> 20005 | N65: =SUM(H65,K65) -> 699 | O65: ='Performances by Week'!$AG$8 -> 600 | P65: =N65/O65 -> 1.165 | Q65: =M65/N65 -> 28.619456
A66: Handel's Messiah | D66: Dec 5-7 | E66: =SUM('Performances by Week'!$Z$38:$Z$40) -> 235000 | F66: =SUM('Performances by Week'!$Y$38:$Y$40) -> 107280 | G66: =F66-E66 -> -127720 | H66: =SUM('Performances by Week'!$S$38:$S$40) -> 2004 | I66: $ - | J66: $ - | K66: - | L66: =SUM(E66,I66) -> 235000 | M66: =SUM(F66,J66) -> 107280 | N66: =SUM(H66,K66) -> 2004 | O66: =SUM('Performances by Week'!$AG$38:$AG$40) -> 4332 | P66: =N66/O66 -> 0.46260388 | Q66: =M66/N66 -> 53.532934
A67: Leslie Odom Jr.: Christmas | D67: Dec 12-13 | E67: =SUM('Performances by Week'!$Z$41:$Z$42) -> 300000 | F67: =SUM('Performances by Week'!$Y$41:$Y$42) -> 266029 | G67: =F67-E67 -> -33971 | H67: =SUM('Performances by Week'!$S$41:$S$42) -> 2694 | I67: $ - | J67: $ - | K67: - | L67: =SUM(E67,I67) -> 300000 | M67: =SUM(F67,J67) -> 266029 | N67: =SUM(H67,K67) -> 2694 | O67: =SUM('Performances by Week'!$AG$41:$AG$42) -> 3180 | P67: =N67/O67 -> 0.84716981 | Q67: =M67/N67 -> 98.748701
A68: Chris Thile | D68: Feb 12 | E68: ='Performances by Week'!$Z$69 -> 128900 | F68: ='Performances by Week'!$Y$69 -> 30162 | G68: =F68-E68 -> -98738 | H68: ='Performances by Week'!$S$69 -> 340 | I68: $ - | J68: $ - | K68: - | L68: =SUM(E68,I68) -> 128900 | M68: =SUM(F68,J68) -> 30162 | N68: =SUM(H68,K68) -> 340 | O68: ='Performances by Week'!$AG$69 -> 1590 | P68: =N68/O68 -> 0.21383648 | Q68: =M68/N68 -> 88.711765
A69: Final Symphony | D69: Mar 25-26 | E69: =SUM('Performances by Week'!$Z$83:$Z$84) -> 168218 | F69: =SUM('Performances by Week'!$Y$83:$Y$84) -> 10464.5 | G69: =F69-E69 -> -157753.5 | H69: =SUM('Performances by Week'!$S$83:$S$84) -> 173 | I69: $ - | J69: $ - | K69: - | L69: =SUM(E69,I69) -> 168218 | M69: =SUM(F69,J69) -> 10464.5 | N69: =SUM(H69,K69) -> 173 | O69: =SUM('Performances by Week'!$AG$83:$AG$84) -> 3180 | P69: =N69/O69 -> 0.054402516 | Q69: =M69/N69 -> 60.488439
A70: Ben Rector | D70: May 21-22 | E70: =SUM('Performances by Week'!$Z$104:$Z$105) -> 224936 | F70: =SUM('Performances by Week'!$Y$104:$Y$105) -> 28268 | G70: =F70-E70 -> -196668 | H70: =SUM('Performances by Week'!$S$104:$S$105) -> 317 | L70: =SUM(E70,I70) -> 224936 | M70: =SUM(F70,J70) -> 28268 | N70: =SUM(H70,K70) -> 317 | O70: =SUM('Performances by Week'!$AG$104:$AG$105) -> 3180 | P70: =N70/O70 -> 0.099685535 | Q70: =M70/N70 -> 89.173502
A71: OTHER CONCERT TOTAL | E71: =SUM(E64:E70) -> 1419001 | F71: =SUM(F64:F70) -> 734292.5 | G71: =SUM(G64:G70) -> -684708.5 | H71: =SUM(H64:H70) -> 8526 | I71: $ - | J71: $ - | K71: - | L71: =SUM(L64:L70) -> 1419001 | M71: =SUM(M64:M70) -> 734292.5 | N71: =SUM(N64:N70) -> 8526 | O71: =SUM(O64:O70) -> 18666 | P71: =N71/O71 -> 0.45676631 | Q71: =M71/N71 -> 86.123915
A72: ALL CONCERTS | E72: =SUM(E71,E61,E54,E45,E38,E20) -> 5442691 | F72: =SUM(F71,F61,F54,F45,F38,F20) -> 2319078.6 | G72: =SUM(G71,G61,G54,G45,G38,G20) -> -3123612.4 | H72: =SUM(H71,H61,H54,H45,H38,H20) -> 33713 | I72: =SUM(I71,I61,I54,I45,I38,I20) -> 2294950 | J72: =SUM(J71,J61,J54,J45,J38,J20) -> 2137434.4 | K72: =SUM(K71,K61,K54,K45,K38,K20) -> 31973 | L72: =SUM(L71,L61,L54,L45,L38,L20) -> 7737641 | ... O72: =SUM(O71,O61,O54,O45,O38,O20) -> 143732 | P72: =N72/O72 -> 0.45700331 | Q72: =M72/N72 -> 67.845705

Sheet CS3 Mahler
D1: # weeks out
A2: Single Tickets | B2: 10 | C2: 9 | D2: 8 | E2: 7 | F2: 6 | G2: 5 | H2: 4 | I2: 3 | J2: 2 | K2: 1 | L2: 0 | Q2: Estimates Only | U2: Historical Data
A3: CS3 Mahler | B3: 45908 | C3: 45915 | D3: 45922 | E3: 45929 | F3: 45936 | G3: 45943 | H3: 45950 | I3: 45957 | J3: 45964 | K3: 45971 | L3: 45978 | M3: # Single Tickets to sell out 100% | N3: Projected OCC% | P3: # Weeks Until Performance | Q3: 10 | R3: 9 | S3: 8 | T3: 7 | U3: 6 | V3: 5 | W3: 4 | X3: 3 | Y3: 2 | Z3: 1 | AA3: 0
A4: 11/21/2025 Sales (Fri, Piazza) | B4: 55 | C4: 60 | D4: 66 | E4: 75 | M4: ='Performances by Week'!AG31-'Performances by Week'!AC31 -> 1250 | N4: ='Performances by Week'!O31 -> 0.5093581 | P4: Classical | Q4: 0.15 | R4: 0.18 | S4: 0.21 | T4: 0.24 | U4: 0.27 | V4: 0.3 | W4: 0.33 | X4: 0.39 | Y4: 0.46 | Z4: 0.59 | AA4: 1
A5: 11/22/2025 Sales (Sat) | B5: 95 | C5: 110 | D5: 114 | E5: 143 | M5: ='Performances by Week'!AG32-'Performances by Week'!AC32 -> 1033 | N5: ='Performances by Week'!O32 -> 0.73214941 | P5: Pops | Q5: 0.15 | R5: 0.18 | S5: 0.21 | T5: 0.24 | U5: 0.27 | V5: 0.3 | W5: 0.33 | X5: 0.39 | Y5: 0.46 | Z5: 0.59 | AA5: 1
A6: 11/23/2025 Sales (Sun) | B6: 75 | C6: 81 | D6: 83 | E6: 93 | M6: ='Performances by Week'!AG33-'Performances by Week'!AC33 -> 1009 | N6: ='Performances by Week'!O33 -> 0.67209165 | P6: Specials | Q6: 0.15 | R6: 0.18 | S6: 0.21 | T6: 0.24 | U6: 0.27 | V6: 0.3 | W6: 0.33 | X6: 0.39 | Y6: 0.46 | Z6: 0.59 | AA6: 1
A7: Pace for 85% OCC | B7: =$M$7*$M$12*Q4 -> 139.91 | C7: =$M$7*$M$12*R4 -> 167.892 | D7: =$M$7*$M$12*S4 -> 195.874 | E7: =$M$7*$M$12*T4 -> 223.856 | F7: =$M$7*$M$12*U4 -> 251.838 | G7: =$M$7*$M$12*V4 -> 279.82 | H7: =$M$7*$M$12*W4 -> 307.802 | I7: =$M$7*$M$12*X4 -> 363.766 | ... L7: =$M$7*$M$12*AA4 -> 932.73333 | M7: =AVERAGE(M4:M6) -> 1097.3333 | P7: Other | Q7: 0.15 | R7: 0.18 | S7: 0.21 | T7: 0.24 | U7: 0.27 | V7: 0.3 | W7: 0.33 | X7: 0.39 | Y7: 0.46 | Z7: 0.59 | AA7: 1
A8: Weekly new sales needed for Target Pace | C8: =C7-B7 -> 27.982 | D8: =D7-C7 -> 27.982 | E8: =E7-D7 -> 27.982 | F8: =F7-E7 -> 27.982 | G8: =G7-F7 -> 27.982 | H8: =H7-G7 -> 27.982 | I8: =I7-H7 -> 55.964 | J8: =J7-I7 -> 65.291333 | ... L8: =L7-K7 -> 382.42067
A9: Actual Weekly Sales | C9: =IF(C4="","Too early",AVERAGE(C4:C7)-AVERAGE(B4:B7)) -> 13.4955 | D9: =IF(D4="","Too early",AVERAGE(D4:D7)-AVERAGE(C4:C7)) -> 9.9955 | E9: =IF(E4="","Too early",AVERAGE(E4:E7)-AVERAGE(D4:D7)) -> 18.9955 | F9: =IF(F4="","Too early",AVERAGE(F4:F7)-AVERAGE(E4:E7)) -> Too early | G9: =IF(G4="","Too early",AVERAGE(G4:G7)-AVERAGE(F4:F7)) -> Too early | H9: =IF(H4="","Too early",AVERAGE(H4:H7)-AVERAGE(G4:G7)) -> Too early | I9: =IF(I4="","Too early",AVERAGE(I4:I7)-AVERAGE(H4:H7)) -> Too early | J9: =IF(J4="","Too early",AVERAGE(J4:J7)-AVERAGE(I4:I7)) -> Too early | ... L9: =IF(L4="","Too early",AVERAGE(L4:L7)-AVERAGE(K4:K7)) -> Too early
A10: Avg/Show vs Target Pace: | B10: =IF(B4>0,AVERAGE(B4:B6)-B7,"TBD") -> -64.91 | C10: =IF(C4>0,AVERAGE(C4:C6)-C7,"TBD") -> -84.225333 | D10: =IF(D4>0,AVERAGE(D4:D6)-D7,"TBD") -> -108.20733 | E10: =IF(E4>0,AVERAGE(E4:E6)-E7,"TBD") -> -120.18933 | F10: =IF(F4>0,AVERAGE(F4:F6)-F7,"TBD") -> TBD | G10: =IF(G4>0,AVERAGE(G4:G6)-G7,"TBD") -> TBD | H10: =IF(H4>0,AVERAGE(H4:H6)-H7,"TBD") -> TBD | I10: =IF(I4>0,AVERAGE(I4:I6)-I7,"TBD") -> TBD | ... L10: =IF(L4>0,AVERAGE(L4:L6)-L7,"TBD") -> TBD
M11: OCC Target
M12: 0.85
